Workbook

Sheet 목차
B2: 태양광 발전사업
B3: 재무모델 v2 (분기·5트랜치) — 재생E AI Agent 자동생성 · 2026-09-22
B6: 시트 | C6: 내용
B7: Report | C7: Executive Summary — 핵심 KPI
B8: 입력값 | C8: 화면에서 입력한 원본 값 — Funding 등이 이 시트를 참조
B9: Funding | C9: 자금조달 — 자본금 + 5트랜치 조건
B10: Debt | C10: 트랜치별 상환 스케줄 (A/B/C/D/후순위) + 합계
B11: Revenue | C11: 발전량 · 매출
B12: Opex | C12: 운영비 (선순위/후순위)
B13: IS(Q) | C13: 분기 손익계산서
B14: CF(Q) | C14: 분기 현금흐름 · DSCR · 배당
B16: ※ 입력값 시트(노란 탭) 외의 모든 값은 수식입니다. 노란 셀을 고치면 세금·DSCR·배당·IRR 까지 전부 다시 계산됩니다. 회색 셀(거치·상환·방식·투입순서, DSRA 적립기준)은 스케줄의 모양을 정하는 값이라 화면에서 다시 생성해야 합니다. 각 계산 시트 맨 아래 "가정" 블록이 입력값 시트를 참조하는 유일한 곳입니다.

Sheet Report
A1: 태양광 발전사업
A2: Executive Summary (v2 · 분기 · 5트랜치)
B4: 사업 개요
B6: 사업명 | D6: ='입력값'!C6
B7: 설비용량 [MW] | D7: ='입력값'!C7
B8: 총 기간 수(분기) | D8: 86
B9: 건설 개시 | D9: 2024-06
B11: 재원조달
B13: 총투자비(TIC) [KRWm] | D13: ='Funding'!C18
B14: 건설이자(IDC) [KRWm] | D14: ='Funding'!C17
B15: 자기자본 [KRWm] | D15: ='Funding'!C7
B16: 차입금 합계 [KRWm] | D16: ='Funding'!C13
B18: 수익성 지표
B20: Project IRR 세전 [%] | D20: ='CF(Q)'!D62
B21: Project IRR 세후 [%] | D21: ='CF(Q)'!D63
B22: Equity IRR (FCFE) [%] | D22: ='CF(Q)'!D64
B23: Equity IRR (배당) [%] | D23: ='CF(Q)'!D65
B24: Investor IRR [%] | D24: ='CF(Q)'!D66
B25: 최소 단순DSCR(연 합산) [x] | D25: ='CF(Q)'!D47
B26: 최소 누적DSCR [x] | D26: ='CF(Q)'!D48
B27: 총영업수익(전체기간) [KRWm] | D27: ='Revenue'!D17
B28: 총영업비용(전체기간) [KRWm] | D28: ='Opex'!D24
B29: 총선순위이자 [KRWm] | D29: ='Debt'!D77
B30: 총법인세 [KRWm] | D30: =-'IS(Q)'!D44
B31: 총배당(연차+청산) [KRWm] | D31: ='CF(Q)'!D16

Sheet 입력값
A1: 태양광 발전사업
A2: 입력값 — 화면에서 입력한 값 (다른 시트가 이 시트를 참조)
B4: 사업 기본 가정
B6: 사업명 | C6: 태양광 발전사업
B7: 설비용량[MW] | C7: 99.998
B8: 총사업비[억원] | C8: 1410.69
B9: 자기자본[억원] | C9: 150
B10: 판매단가[원/kWh] | C10: 154.8
B11: 판매단가 에스컬레이션[%/yr] | C11: 0
B12: 발전량 열화율[%/yr] | C12: 0.5
B13: 소내소비율[%] | C13: 0
B14: 일조시간[h/day] | C14: 3.77
B15: 상각대상 비율(TIC 대비)[%] | C15: 95
B16: 감가상각 내용연수[yr] | C16: 20
B17: 철거비(복구충당부채)[억원] | C17: 20
B18: 운영비 총액[억원/yr] | C18: 49.8
... B28: 배당 개시 운영연차 | C28: 2
B30: 법인세 가정
B32: 이월결손금 공제한도[%] | C32: 80
B33: 최저한세율[%] | C33: 0
B34: 통합투자세액공제율[%] | C34: 0
B35: 지방소득세율(법인세 대비)[%] | C35: 10
B36: 세액공제 농특세율[%] | C36: 0
B38: 판매단가 트랙 (PPA/SMP+REC 등)
B40: 트랙 | C40: 비중[%] | D40: 단가[원/kWh] | E40: 에스컬레이션[%/yr] | F40: 대금회수시차[개월]
B41: PPA | C41: 100 | D41: 154.8 | E41: 0 | F41: 1
B43: 트랜치 조건
B45: 트랜치 | C45: 금액[억원] | D45: 건설금리[%] | E45: 운영금리[%] | F45: 거치(yr) | G45: 상환(yr) | H45: 방식 | I45: 투입순서
B46: 선순위A | C46: 500 | D46: 0.056 | E46: 0.056 | F46: 2 | G46: 16 | H46: 1 | I46: 2
B47: 선순위B | C47: 500 | D47: 0.055 | E47: 0.055 | F47: 2 | G47: 16 | H47: 1 | I47: 2
B48: 선순위C | C48: 350 | D48: 0.055 | E48: 0.055 | F48: 1.25 | G48: 16 | H48: 1 | I48: 4
B49: 선순위D | C49: 0 | D49: 0.0225 | E49: 0.0225 | F49: 5 | G49: 10 | H49: 1 | I49: 3
B50: 후순위 | C50: 0 | D50: 0.0565 | E50: 0.0565 | F50: 15 | G50: 2.75 | H50: 1 | I50: 1
B51: 자본금 | C51: =C9 | I51: 1
B53: 총사업비 지출 스케줄 (건설 분기별 비중)
B55: 구 분 | C55: unit | D55: 합 계 | E55: 2024-06-30 | F55: 2024-09-30 | G55: 2024-12-31 | H55: 2025-03-31 | I55: 2025-06-30 | J55: 2025-09-30 | K55: 2025-12-31 | L55: 2026-03-31 | M55: 2026-06-30 | N55: 2026-09-30 | O55: 2026-12-31 | P55: 2027-03-31 | Q55: 2027-06-30 | R55: 2027-09-30 | S55: 2027-12-31 | T55: 2028-03-31 | U55: 2028-06-30 | V55: 2028-09-30 | W55: 2028-12-31 | X55: 2029-03-31 | Y55: 2029-06-30 | Z55: 2029-09-30 | AA55: 2029-12-31 | AB55: 2030-03-31 | AC55: 2030-06-30 | AD55: 2030-09-30 | AE55: 2030-12-31 | AF55: 2031-03-31 | AG55: 2031-06-30 | AH55: 2031-09-30 | AI55: 2031-12-31 | AJ55: 2032-03-31 | AK55: 2032-06-30 | AL55: 2032-09-30 | AM55: 2032-12-31 | AN55: 2033-03-31 | AO55: 2033-06-30 | AP55: 2033-09-30 | AQ55: 2033-12-31 | AR55: 2034-03-31 | AS55: 2034-06-30 | AT55: 2034-09-30 | AU55: 2034-12-31 | AV55: 2035-03-31 | AW55: 2035-06-30 | AX55: 2035-09-30 | AY55: 2035-12-31 | AZ55: 2036-03-31 | BA55: 2036-06-30 | BB55: 2036-09-30 | BC55: 2036-12-31 | BD55: 2037-03-31 | BE55: 2037-06-30 | BF55: 2037-09-30 | BG55: 2037-12-31 | BH55: 2038-03-31 | BI55: 2038-06-30 | BJ55: 2038-09-30 | BK55: 2038-12-31 | BL55: 2039-03-31 | BM55: 2039-06-30 | BN55: 2039-09-30 | BO55: 2039-12-31 | BP55: 2040-03-31 | BQ55: 2040-06-30 | BR55: 2040-09-30 | BS55: 2040-12-31 | BT55: 2041-03-31 | BU55: 2041-06-30 | BV55: 2041-09-30 | BW55: 2041-12-31 | BX55: 2042-03-31 | BY55: 2042-06-30 | BZ55: 2042-09-30 | CA55: 2042-12-31 | CB55: 2043-03-31 | CC55: 2043-06-30 | CD55: 2043-09-30 | CE55: 2043-12-31 | CF55: 2044-03-31 | CG55: 2044-06-30 | CH55: 2044-09-30 | CI55: 2044-12-31 | CJ55: 2045-03-31 | CK55: 2045-06-30 | CL55: 2045-09-30
B57: 지출 비중 | C57: [비율] | D57: =SUM(E57:CL57) | E57: 0.16666667 | F57: 0.16666667 | G57: 0.16666667 | H57: 0.16666667 | I57: 0.16666667 | J57: 0.16666667
B59: 총사업비 항목
B61: 항목 | C61: 금액[억원]
B62: EPC
B63: 감리비
B64: 공사보험료
B65: 토지임대료(선납)
B66: 토지임대료(분납)
B67: 사업개발비
B68: 민원처리비
B69: 사업성자문비
B70: 법인운영비
B71: 기타예비비
B72: 신주발행비용
B73: 금융부대비용
... B77: ※ 회색 셀(거치·상환·방식·투입순서, DSRA 적립기준) = 스케줄의 "모양"을 정하는 값이라 열 구성을 다시 만들어야 합니다. 엑셀에서 고쳐도 상환 스케줄은 따라오지 않으니, 이 값들을 바꾸려면 화면(HTML)에서 고친 뒤 다시 생성하세요.

Sheet Funding
A1: 태양광 발전사업
A2: 자금조달 — 자본금 + 5개 트랜치
B4: 트랜치 조건
B6: 트랜치 | C6: 금액[KRWm] | D6: 투입순서 | E6: 건설금리 | F6: 운영금리 | G6: 거치(yr) | H6: 상환(yr) | I6: 방식 | J6: 상환개시
B7: 자본금 | C7: ='입력값'!C9*100
B8: 선순위A | C8: ='입력값'!C46*100 | E8: ='입력값'!D46 | F8: ='입력값'!E46 | G8: ='입력값'!F46 | H8: ='입력값'!G46 | I8: ='입력값'!H46 | J8: 2026-09-30
B9: 선순위B | C9: ='입력값'!C47*100 | E9: ='입력값'!D47 | F9: ='입력값'!E47 | G9: ='입력값'!F47 | H9: ='입력값'!G47 | I9: ='입력값'!H47 | J9: 2026-09-30
B10: 선순위C | C10: ='입력값'!C48*100 | E10: ='입력값'!D48 | F10: ='입력값'!E48 | G10: ='입력값'!F48 | H10: ='입력값'!G48 | I10: ='입력값'!H48 | J10: 2026-09-30
B11: 선순위D | C11: ='입력값'!C49*100 | E11: ='입력값'!D49 | F11: ='입력값'!E49 | G11: ='입력값'!F49 | H11: ='입력값'!G49 | I11: ='입력값'!H49 | J11: -
B12: 후순위 | C12: ='입력값'!C50*100 | E12: ='입력값'!D50 | F12: ='입력값'!E50 | G12: ='입력값'!F50 | H12: ='입력값'!G50 | I12: ='입력값'!H50 | J12: -
B13: 차입금 합계 | C13: =C8+C9+C10+C11+C12
B15: 건설이자(IDC)
B17: IDC 합계[KRWm] | C17: ='Debt'!D15
B18: 총투자비(TIC)[KRWm] | C18: =$D$41*100+'Debt'!D15
B19: 총사업비(건설이자 제외)[KRWm] | C19: ='입력값'!C8*100
B21: 총사업비 세부내역
B23: 항목 | C23: 금액[KRWm]
B24: ='입력값'!B62
B25: ='입력값'!B63
B26: ='입력값'!B64
B27: ='입력값'!B65
B28: ='입력값'!B66
B29: ='입력값'!B67
B30: ='입력값'!B68
B31: ='입력값'!B69
B32: ='입력값'!B70
B33: ='입력값'!B71
B34: ='입력값'!B72
B35: ='입력값'!B73
B36: 총사업비 (항목별 금액 미입력) | C36: ='입력값'!C8*100
B39: 가정 (입력값 연결) — 이 시트의 계산이 쓰는 원천값 | D39: 값
B40: ※ 입력값 시트는 여기서만 참조합니다(초록 글자 = 입력값 연결). 위의 분기 계산은 이 셀들만 참조하므로, 값을 바꾸려면 입력값 시트를 고치세요.
B41: 총사업비[억원] | C41: C8 | D41: ='입력값'!C8

Sheet Debt
A1: 태양광 발전사업
A2: 차입금 상환 스케줄 — 건설기간 인출 + 트랜치별 상환
B4: 건설기간 자금조달 (인출·건설이자)
B6: 구 분 | C6: unit | D6: 합 계 | E6: 2024-06-30 | F6: 2024-09-30 | G6: 2024-12-31 | H6: 2025-03-31 | I6: 2025-06-30 | J6: 2025-09-30 | K6: 2025-12-31 | L6: 2026-03-31 | M6: 2026-06-30 | N6: 2026-09-30 | O6: 2026-12-31 | P6: 2027-03-31 | Q6: 2027-06-30 | R6: 2027-09-30 | S6: 2027-12-31 | T6: 2028-03-31 | U6: 2028-06-30 | V6: 2028-09-30 | W6: 2028-12-31 | X6: 2029-03-31 | Y6: 2029-06-30 | Z6: 2029-09-30 | AA6: 2029-12-31 | AB6: 2030-03-31 | AC6: 2030-06-30 | AD6: 2030-09-30 | AE6: 2030-12-31 | AF6: 2031-03-31 | AG6: 2031-06-30 | AH6: 2031-09-30 | AI6: 2031-12-31 | AJ6: 2032-03-31 | AK6: 2032-06-30 | AL6: 2032-09-30 | AM6: 2032-12-31 | AN6: 2033-03-31 | AO6: 2033-06-30 | AP6: 2033-09-30 | AQ6: 2033-12-31 | AR6: 2034-03-31 | AS6: 2034-06-30 | AT6: 2034-09-30 | AU6: 2034-12-31 | AV6: 2035-03-31 | AW6: 2035-06-30 | AX6: 2035-09-30 | AY6: 2035-12-31 | AZ6: 2036-03-31 | BA6: 2036-06-30 | BB6: 2036-09-30 | BC6: 2036-12-31 | BD6: 2037-03-31 | BE6: 2037-06-30 | BF6: 2037-09-30 | BG6: 2037-12-31 | BH6: 2038-03-31 | BI6: 2038-06-30 | BJ6: 2038-09-30 | BK6: 2038-12-31 | BL6: 2039-03-31 | BM6: 2039-06-30 | BN6: 2039-09-30 | BO6: 2039-12-31 | BP6: 2040-03-31 | BQ6: 2040-06-30 | BR6: 2040-09-30 | BS6: 2040-12-31 | BT6: 2041-03-31 | BU6: 2041-06-30 | BV6: 2041-09-30 | BW6: 2041-12-31 | BX6: 2042-03-31 | BY6: 2042-06-30 | BZ6: 2042-09-30 | CA6: 2042-12-31 | CB6: 2043-03-31 | CC6: 2043-06-30 | CD6: 2043-09-30 | CE6: 2043-12-31 | CF6: 2044-03-31 | CG6: 2044-06-30 | CH6: 2044-09-30 | CI6: 2044-12-31 | CJ6: 2045-03-31 | CK6: 2045-06-30 | CL6: 2045-09-30
B8: 공사비 지출 | C8: [KRWm] | D8: =SUM(E8:CL8) | E8: =E105*$D$88*100 | F8: =F105*$D$88*100 | G8: =G105*$D$88*100 | H8: =H105*$D$88*100 | I8: =I105*$D$88*100 | J8: =J105*$D$88*100 | K8: 0 | L8: 0 | M8: 0 | N8: 0 | O8: 0 | P8: 0 | Q8: 0 | R8: 0 | S8: 0 | T8: 0 | U8: 0 | V8: 0 | W8: 0 | X8: 0 | Y8: 0 | Z8: 0 | AA8: 0 | AB8: 0 | AC8: 0 | AD8: 0 | AE8: 0 | AF8: 0 | AG8: 0 | AH8: 0 | AI8: 0 | AJ8: 0 | AK8: 0 | AL8: 0 | AM8: 0 | AN8: 0 | AO8: 0 | AP8: 0 | AQ8: 0 | AR8: 0 | AS8: 0 | AT8: 0 | AU8: 0 | AV8: 0 | AW8: 0 | AX8: 0 | AY8: 0 | AZ8: 0 | BA8: 0 | BB8: 0 | BC8: 0 | BD8: 0 | BE8: 0 | BF8: 0 | BG8: 0 | BH8: 0 | BI8: 0 | BJ8: 0 | BK8: 0 | BL8: 0 | BM8: 0 | BN8: 0 | BO8: 0 | BP8: 0 | BQ8: 0 | BR8: 0 | BS8: 0 | BT8: 0 | BU8: 0 | BV8: 0 | BW8: 0 | BX8: 0 | BY8: 0 | BZ8: 0 | CA8: 0 | CB8: 0 | CC8: 0 | CD8: 0 | CE8: 0 | CF8: 0 | CG8: 0 | CH8: 0 | CI8: 0 | CJ8: 0 | CK8: 0 | CL8: 0
B9: DSRA 적립 | C9: [KRWm] | D9: =SUM(E9:CL9) | E9: 0 | F9: 0 | G9: 0 | H9: 0 | I9: 0 | J9: ='입력값'!C23*100 | K9: 0 | L9: 0 | M9: 0 | N9: 0 | O9: 0 | P9: 0 | Q9: 0 | R9: 0 | S9: 0 | T9: 0 | U9: 0 | V9: 0 | W9: 0 | X9: 0 | Y9: 0 | Z9: 0 | AA9: 0 | AB9: 0 | AC9: 0 | AD9: 0 | AE9: 0 | AF9: 0 | AG9: 0 | AH9: 0 | AI9: 0 | AJ9: 0 | AK9: 0 | AL9: 0 | AM9: 0 | AN9: 0 | AO9: 0 | AP9: 0 | AQ9: 0 | AR9: 0 | AS9: 0 | AT9: 0 | AU9: 0 | AV9: 0 | AW9: 0 | AX9: 0 | AY9: 0 | AZ9: 0 | BA9: 0 | BB9: 0 | BC9: 0 | BD9: 0 | BE9: 0 | BF9: 0 | BG9: 0 | BH9: 0 | BI9: 0 | BJ9: 0 | BK9: 0 | BL9: 0 | BM9: 0 | BN9: 0 | BO9: 0 | BP9: 0 | BQ9: 0 | BR9: 0 | BS9: 0 | BT9: 0 | BU9: 0 | BV9: 0 | BW9: 0 | BX9: 0 | BY9: 0 | BZ9: 0 | CA9: 0 | CB9: 0 | CC9: 0 | CD9: 0 | CE9: 0 | CF9: 0 | CG9: 0 | CH9: 0 | CI9: 0 | CJ9: 0 | CK9: 0 | CL9: 0
B10: 선순위A 건설이자 | C10: [KRWm] | D10: =SUM(E10:CL10) | E10: 0 | F10: =E18*$D$91/4 | G10: =F18*$D$91/4 | H10: =G18*$D$91/4 | I10: =H18*$D$91/4 | J10: =I18*$D$91/4 | K10: 0 | L10: 0 | M10: 0 | N10: 0 | O10: 0 | P10: 0 | Q10: 0 | R10: 0 | S10: 0 | T10: 0 | U10: 0 | V10: 0 | W10: 0 | X10: 0 | Y10: 0 | Z10: 0 | AA10: 0 | AB10: 0 | AC10: 0 | AD10: 0 | AE10: 0 | AF10: 0 | AG10: 0 | AH10: 0 | AI10: 0 | AJ10: 0 | AK10: 0 | AL10: 0 | AM10: 0 | AN10: 0 | AO10: 0 | AP10: 0 | AQ10: 0 | AR10: 0 | AS10: 0 | AT10: 0 | AU10: 0 | AV10: 0 | AW10: 0 | AX10: 0 | AY10: 0 | AZ10: 0 | BA10: 0 | BB10: 0 | BC10: 0 | BD10: 0 | BE10: 0 | BF10: 0 | BG10: 0 | BH10: 0 | BI10: 0 | BJ10: 0 | BK10: 0 | BL10: 0 | BM10: 0 | BN10: 0 | BO10: 0 | BP10: 0 | BQ10: 0 | BR10: 0 | BS10: 0 | BT10: 0 | BU10: 0 | BV10: 0 | BW10: 0 | BX10: 0 | BY10: 0 | BZ10: 0 | CA10: 0 | CB10: 0 | CC10: 0 | CD10: 0 | CE10: 0 | CF10: 0 | CG10: 0 | CH10: 0 | CI10: 0 | CJ10: 0 | CK10: 0 | CL10: 0
B11: 선순위B 건설이자 | C11: [KRWm] | D11: =SUM(E11:CL11) | E11: 0 | F11: =E19*$D$94/4 | G11: =F19*$D$94/4 | H11: =G19*$D$94/4 | I11: =H19*$D$94/4 | J11: =I19*$D$94/4 | K11: 0 | L11: 0 | M11: 0 | N11: 0 | O11: 0 | P11: 0 | Q11: 0 | R11: 0 | S11: 0 | T11: 0 | U11: 0 | V11: 0 | W11: 0 | X11: 0 | Y11: 0 | Z11: 0 | AA11: 0 | AB11: 0 | AC11: 0 | AD11: 0 | AE11: 0 | AF11: 0 | AG11: 0 | AH11: 0 | AI11: 0 | AJ11: 0 | AK11: 0 | AL11: 0 | AM11: 0 | AN11: 0 | AO11: 0 | AP11: 0 | AQ11: 0 | AR11: 0 | AS11: 0 | AT11: 0 | AU11: 0 | AV11: 0 | AW11: 0 | AX11: 0 | AY11: 0 | AZ11: 0 | BA11: 0 | BB11: 0 | BC11: 0 | BD11: 0 | BE11: 0 | BF11: 0 | BG11: 0 | BH11: 0 | BI11: 0 | BJ11: 0 | BK11: 0 | BL11: 0 | BM11: 0 | BN11: 0 | BO11: 0 | BP11: 0 | BQ11: 0 | BR11: 0 | BS11: 0 | BT11: 0 | BU11: 0 | BV11: 0 | BW11: 0 | BX11: 0 | BY11: 0 | BZ11: 0 | CA11: 0 | CB11: 0 | CC11: 0 | CD11: 0 | CE11: 0 | CF11: 0 | CG11: 0 | CH11: 0 | CI11: 0 | CJ11: 0 | CK11: 0 | CL11: 0
B12: 선순위C 건설이자 | C12: [KRWm] | D12: =SUM(E12:CL12) | E12: 0 | F12: =E20*$D$97/4 | G12: =F20*$D$97/4 | H12: =G20*$D$97/4 | I12: =H20*$D$97/4 | J12: =I20*$D$97/4 | K12: 0 | L12: 0 | M12: 0 | N12: 0 | O12: 0 | P12: 0 | Q12: 0 | R12: 0 | S12: 0 | T12: 0 | U12: 0 | V12: 0 | W12: 0 | X12: 0 | Y12: 0 | Z12: 0 | AA12: 0 | AB12: 0 | AC12: 0 | AD12: 0 | AE12: 0 | AF12: 0 | AG12: 0 | AH12: 0 | AI12: 0 | AJ12: 0 | AK12: 0 | AL12: 0 | AM12: 0 | AN12: 0 | AO12: 0 | AP12: 0 | AQ12: 0 | AR12: 0 | AS12: 0 | AT12: 0 | AU12: 0 | AV12: 0 | AW12: 0 | AX12: 0 | AY12: 0 | AZ12: 0 | BA12: 0 | BB12: 0 | BC12: 0 | BD12: 0 | BE12: 0 | BF12: 0 | BG12: 0 | BH12: 0 | BI12: 0 | BJ12: 0 | BK12: 0 | BL12: 0 | BM12: 0 | BN12: 0 | BO12: 0 | BP12: 0 | BQ12: 0 | BR12: 0 | BS12: 0 | BT12: 0 | BU12: 0 | BV12: 0 | BW12: 0 | BX12: 0 | BY12: 0 | BZ12: 0 | CA12: 0 | CB12: 0 | CC12: 0 | CD12: 0 | CE12: 0 | CF12: 0 | CG12: 0 | CH12: 0 | CI12: 0 | CJ12: 0 | CK12: 0 | CL12: 0
B13: 선순위D 건설이자 | C13: [KRWm] | D13: =SUM(E13:CL13) | E13: 0 | F13: =E21*$D$100/4 | G13: =F21*$D$100/4 | H13: =G21*$D$100/4 | I13: =H21*$D$100/4 | J13: =I21*$D$100/4 | K13: 0 | L13: 0 | M13: 0 | N13: 0 | O13: 0 | P13: 0 | Q13: 0 | R13: 0 | S13: 0 | T13: 0 | U13: 0 | V13: 0 | W13: 0 | X13: 0 | Y13: 0 | Z13: 0 | AA13: 0 | AB13: 0 | AC13: 0 | AD13: 0 | AE13: 0 | AF13: 0 | AG13: 0 | AH13: 0 | AI13: 0 | AJ13: 0 | AK13: 0 | AL13: 0 | AM13: 0 | AN13: 0 | AO13: 0 | AP13: 0 | AQ13: 0 | AR13: 0 | AS13: 0 | AT13: 0 | AU13: 0 | AV13: 0 | AW13: 0 | AX13: 0 | AY13: 0 | AZ13: 0 | BA13: 0 | BB13: 0 | BC13: 0 | BD13: 0 | BE13: 0 | BF13: 0 | BG13: 0 | BH13: 0 | BI13: 0 | BJ13: 0 | BK13: 0 | BL13: 0 | BM13: 0 | BN13: 0 | BO13: 0 | BP13: 0 | BQ13: 0 | BR13: 0 | BS13: 0 | BT13: 0 | BU13: 0 | BV13: 0 | BW13: 0 | BX13: 0 | BY13: 0 | BZ13: 0 | CA13: 0 | CB13: 0 | CC13: 0 | CD13: 0 | CE13: 0 | CF13: 0 | CG13: 0 | CH13: 0 | CI13: 0 | CJ13: 0 | CK13: 0 | CL13: 0
B14: 후순위 건설이자 | C14: [KRWm] | D14: =SUM(E14:CL14) | E14: 0 | F14: =E22*$D$103/4 | G14: =F22*$D$103/4 | H14: =G22*$D$103/4 | I14: =H22*$D$103/4 | J14: =I22*$D$103/4 | K14: 0 | L14: 0 | M14: 0 | N14: 0 | O14: 0 | P14: 0 | Q14: 0 | R14: 0 | S14: 0 | T14: 0 | U14: 0 | V14: 0 | W14: 0 | X14: 0 | Y14: 0 | Z14: 0 | AA14: 0 | AB14: 0 | AC14: 0 | AD14: 0 | AE14: 0 | AF14: 0 | AG14: 0 | AH14: 0 | AI14: 0 | AJ14: 0 | AK14: 0 | AL14: 0 | AM14: 0 | AN14: 0 | AO14: 0 | AP14: 0 | AQ14: 0 | AR14: 0 | AS14: 0 | AT14: 0 | AU14: 0 | AV14: 0 | AW14: 0 | AX14: 0 | AY14: 0 | AZ14: 0 | BA14: 0 | BB14: 0 | BC14: 0 | BD14: 0 | BE14: 0 | BF14: 0 | BG14: 0 | BH14: 0 | BI14: 0 | BJ14: 0 | BK14: 0 | BL14: 0 | BM14: 0 | BN14: 0 | BO14: 0 | BP14: 0 | BQ14: 0 | BR14: 0 | BS14: 0 | BT14: 0 | BU14: 0 | BV14: 0 | BW14: 0 | BX14: 0 | BY14: 0 | BZ14: 0 | CA14: 0 | CB14: 0 | CC14: 0 | CD14: 0 | CE14: 0 | CF14: 0 | CG14: 0 | CH14: 0 | CI14: 0 | CJ14: 0 | CK14: 0 | CL14: 0
B15: 건설이자 합계(당기) | C15: [KRWm] | D15: =SUM(E15:CL15) | E15: =E10+E11+E12+E13+E14 | F15: =F10+F11+F12+F13+F14 | G15: =G10+G11+G12+G13+G14 | H15: =H10+H11+H12+H13+H14 | I15: =I10+I11+I12+I13+I14 | J15: =J10+J11+J12+J13+J14 | K15: =K10+K11+K12+K13+K14 | L15: =L10+L11+L12+L13+L14 | ... CL15: =CL10+CL11+CL12+CL13+CL14
B16: 누적 소요액 | C16: [KRWm] | E16: =E8+E9+E15 | F16: =E16+F8+F9+F15 | G16: =F16+G8+G9+G15 | H16: =G16+H8+H9+H15 | I16: =H16+I8+I9+I15 | J16: =I16+J8+J9+J15 | K16: =J16+K8+K9+K15 | L16: =K16+L8+L9+L15 | M16: =L16+M8+M9+M15 | ... CL16: =CK16+CL8+CL9+CL15
B17: 자본금 누적인출 | C17: [KRWm] | E17: =MIN(MAX(E16-(0),0),$D$89*100+$D$102*100)*($D$89*100)/IF(($D$89*100+$D$102*100)=0,1,$D$89*100+$D$102*100) | F17: =MIN(MAX(F16-(0),0),$D$89*100+$D$102*100)*($D$89*100)/IF(($D$89*100+$D$102*100)=0,1,$D$89*100+$D$102*100) | G17: =MIN(MAX(G16-(0),0),$D$89*100+$D$102*100)*($D$89*100)/IF(($D$89*100+$D$102*100)=0,1,$D$89*100+$D$102*100) | H17: =MIN(MAX(H16-(0),0),$D$89*100+$D$102*100)*($D$89*100)/IF(($D$89*100+$D$102*100)=0,1,$D$89*100+$D$102*100) | I17: =MIN(MAX(I16-(0),0),$D$89*100+$D$102*100)*($D$89*100)/IF(($D$89*100+$D$102*100)=0,1,$D$89*100+$D$102*100) | J17: =MIN(MAX(J16-(0),0),$D$89*100+$D$102*100)*($D$89*100)/IF(($D$89*100+$D$102*100)=0,1,$D$89*100+$D$102*100) | K17: =MIN(MAX(K16-(0),0),$D$89*100+$D$102*100)*($D$89*100)/IF(($D$89*100+$D$102*100)=0,1,$D$89*100+$D$102*100) | L17: =MIN(MAX(L16-(0),0),$D$89*100+$D$102*100)*($D$89*100)/IF(($D$89*100+$D$102*100)=0,1,$D$89*100+$D$102*100) | ... CL17: =MIN(MAX(CL16-(0),0),$D$89*100+$D$102*100)*($D$89*100)/IF(($D$89*100+$D$102*100)=0,1,$D$89*100+$D$102*100)
B18: 선순위A 누적인출 | C18: [KRWm] | E18: =MIN(MAX(E16-($D$89*100+$D$102*100),0),$D$90*100+$D$93*100)*($D$90*100)/IF(($D$90*100+$D$93*100)=0,1,$D$90*100+$D$93*100) | F18: =MIN(MAX(F16-($D$89*100+$D$102*100),0),$D$90*100+$D$93*100)*($D$90*100)/IF(($D$90*100+$D$93*100)=0,1,$D$90*100+$D$93*100) | G18: =MIN(MAX(G16-($D$89*100+$D$102*100),0),$D$90*100+$D$93*100)*($D$90*100)/IF(($D$90*100+$D$93*100)=0,1,$D$90*100+$D$93*100) | H18: =MIN(MAX(H16-($D$89*100+$D$102*100),0),$D$90*100+$D$93*100)*($D$90*100)/IF(($D$90*100+$D$93*100)=0,1,$D$90*100+$D$93*100) | I18: =MIN(MAX(I16-($D$89*100+$D$102*100),0),$D$90*100+$D$93*100)*($D$90*100)/IF(($D$90*100+$D$93*100)=0,1,$D$90*100+$D$93*100) | J18: =MIN(MAX(J16-($D$89*100+$D$102*100),0),$D$90*100+$D$93*100)*($D$90*100)/IF(($D$90*100+$D$93*100)=0,1,$D$90*100+$D$93*100) | K18: =MIN(MAX(K16-($D$89*100+$D$102*100),0),$D$90*100+$D$93*100)*($D$90*100)/IF(($D$90*100+$D$93*100)=0,1,$D$90*100+$D$93*100) | L18: =MIN(MAX(L16-($D$89*100+$D$102*100),0),$D$90*100+$D$93*100)*($D$90*100)/IF(($D$90*100+$D$93*100)=0,1,$D$90*100+$D$93*100) | ... CL18: =MIN(MAX(CL16-($D$89*100+$D$102*100),0),$D$90*100+$D$93*100)*($D$90*100)/IF(($D$90*100+$D$93*100)=0,1,$D$90*100+$D$93*100)
B19: 선순위B 누적인출 | C19: [KRWm] | E19: =MIN(MAX(E16-($D$89*100+$D$102*100),0),$D$90*100+$D$93*100)*($D$93*100)/IF(($D$90*100+$D$93*100)=0,1,$D$90*100+$D$93*100) | F19: =MIN(MAX(F16-($D$89*100+$D$102*100),0),$D$90*100+$D$93*100)*($D$93*100)/IF(($D$90*100+$D$93*100)=0,1,$D$90*100+$D$93*100) | G19: =MIN(MAX(G16-($D$89*100+$D$102*100),0),$D$90*100+$D$93*100)*($D$93*100)/IF(($D$90*100+$D$93*100)=0,1,$D$90*100+$D$93*100) | H19: =MIN(MAX(H16-($D$89*100+$D$102*100),0),$D$90*100+$D$93*100)*($D$93*100)/IF(($D$90*100+$D$93*100)=0,1,$D$90*100+$D$93*100) | I19: =MIN(MAX(I16-($D$89*100+$D$102*100),0),$D$90*100+$D$93*100)*($D$93*100)/IF(($D$90*100+$D$93*100)=0,1,$D$90*100+$D$93*100) | J19: =MIN(MAX(J16-($D$89*100+$D$102*100),0),$D$90*100+$D$93*100)*($D$93*100)/IF(($D$90*100+$D$93*100)=0,1,$D$90*100+$D$93*100) | K19: =MIN(MAX(K16-($D$89*100+$D$102*100),0),$D$90*100+$D$93*100)*($D$93*100)/IF(($D$90*100+$D$93*100)=0,1,$D$90*100+$D$93*100) | L19: =MIN(MAX(L16-($D$89*100+$D$102*100),0),$D$90*100+$D$93*100)*($D$93*100)/IF(($D$90*100+$D$93*100)=0,1,$D$90*100+$D$93*100) | ... CL19: =MIN(MAX(CL16-($D$89*100+$D$102*100),0),$D$90*100+$D$93*100)*($D$93*100)/IF(($D$90*100+$D$93*100)=0,1,$D$90*100+$D$93*100)
B20: 선순위C 누적인출 | C20: [KRWm] | E20: =MIN(MAX(E16-($D$89*100+$D$90*100+$D$93*100+$D$99*100+$D$102*100),0),$D$96*100)*($D$96*100)/IF(($D$96*100)=0,1,$D$96*100) | F20: =MIN(MAX(F16-($D$89*100+$D$90*100+$D$93*100+$D$99*100+$D$102*100),0),$D$96*100)*($D$96*100)/IF(($D$96*100)=0,1,$D$96*100) | G20: =MIN(MAX(G16-($D$89*100+$D$90*100+$D$93*100+$D$99*100+$D$102*100),0),$D$96*100)*($D$96*100)/IF(($D$96*100)=0,1,$D$96*100) | H20: =MIN(MAX(H16-($D$89*100+$D$90*100+$D$93*100+$D$99*100+$D$102*100),0),$D$96*100)*($D$96*100)/IF(($D$96*100)=0,1,$D$96*100) | I20: =MIN(MAX(I16-($D$89*100+$D$90*100+$D$93*100+$D$99*100+$D$102*100),0),$D$96*100)*($D$96*100)/IF(($D$96*100)=0,1,$D$96*100) | J20: =MIN(MAX(J16-($D$89*100+$D$90*100+$D$93*100+$D$99*100+$D$102*100),0),$D$96*100)*($D$96*100)/IF(($D$96*100)=0,1,$D$96*100) | K20: =MIN(MAX(K16-($D$89*100+$D$90*100+$D$93*100+$D$99*100+$D$102*100),0),$D$96*100)*($D$96*100)/IF(($D$96*100)=0,1,$D$96*100) | L20: =MIN(MAX(L16-($D$89*100+$D$90*100+$D$93*100+$D$99*100+$D$102*100),0),$D$96*100)*($D$96*100)/IF(($D$96*100)=0,1,$D$96*100) | ... CL20: =MIN(MAX(CL16-($D$89*100+$D$90*100+$D$93*100+$D$99*100+$D$102*100),0),$D$96*100)*($D$96*100)/IF(($D$96*100)=0,1,$D$96*100)
B21: 선순위D 누적인출 | C21: [KRWm] | E21: =MIN(MAX(E16-($D$89*100+$D$90*100+$D$93*100+$D$102*100),0),$D$99*100)*($D$99*100)/IF(($D$99*100)=0,1,$D$99*100) | F21: =MIN(MAX(F16-($D$89*100+$D$90*100+$D$93*100+$D$102*100),0),$D$99*100)*($D$99*100)/IF(($D$99*100)=0,1,$D$99*100) | G21: =MIN(MAX(G16-($D$89*100+$D$90*100+$D$93*100+$D$102*100),0),$D$99*100)*($D$99*100)/IF(($D$99*100)=0,1,$D$99*100) | H21: =MIN(MAX(H16-($D$89*100+$D$90*100+$D$93*100+$D$102*100),0),$D$99*100)*($D$99*100)/IF(($D$99*100)=0,1,$D$99*100) | I21: =MIN(MAX(I16-($D$89*100+$D$90*100+$D$93*100+$D$102*100),0),$D$99*100)*($D$99*100)/IF(($D$99*100)=0,1,$D$99*100) | J21: =MIN(MAX(J16-($D$89*100+$D$90*100+$D$93*100+$D$102*100),0),$D$99*100)*($D$99*100)/IF(($D$99*100)=0,1,$D$99*100) | K21: =MIN(MAX(K16-($D$89*100+$D$90*100+$D$93*100+$D$102*100),0),$D$99*100)*($D$99*100)/IF(($D$99*100)=0,1,$D$99*100) | L21: =MIN(MAX(L16-($D$89*100+$D$90*100+$D$93*100+$D$102*100),0),$D$99*100)*($D$99*100)/IF(($D$99*100)=0,1,$D$99*100) | ... CL21: =MIN(MAX(CL16-($D$89*100+$D$90*100+$D$93*100+$D$102*100),0),$D$99*100)*($D$99*100)/IF(($D$99*100)=0,1,$D$99*100)
B22: 후순위 누적인출 | C22: [KRWm] | E22: =MIN(MAX(E16-(0),0),$D$89*100+$D$102*100)*($D$102*100)/IF(($D$89*100+$D$102*100)=0,1,$D$89*100+$D$102*100) | F22: =MIN(MAX(F16-(0),0),$D$89*100+$D$102*100)*($D$102*100)/IF(($D$89*100+$D$102*100)=0,1,$D$89*100+$D$102*100) | G22: =MIN(MAX(G16-(0),0),$D$89*100+$D$102*100)*($D$102*100)/IF(($D$89*100+$D$102*100)=0,1,$D$89*100+$D$102*100) | H22: =MIN(MAX(H16-(0),0),$D$89*100+$D$102*100)*($D$102*100)/IF(($D$89*100+$D$102*100)=0,1,$D$89*100+$D$102*100) | I22: =MIN(MAX(I16-(0),0),$D$89*100+$D$102*100)*($D$102*100)/IF(($D$89*100+$D$102*100)=0,1,$D$89*100+$D$102*100) | J22: =MIN(MAX(J16-(0),0),$D$89*100+$D$102*100)*($D$102*100)/IF(($D$89*100+$D$102*100)=0,1,$D$89*100+$D$102*100) | K22: =MIN(MAX(K16-(0),0),$D$89*100+$D$102*100)*($D$102*100)/IF(($D$89*100+$D$102*100)=0,1,$D$89*100+$D$102*100) | L22: =MIN(MAX(L16-(0),0),$D$89*100+$D$102*100)*($D$102*100)/IF(($D$89*100+$D$102*100)=0,1,$D$89*100+$D$102*100) | ... CL22: =MIN(MAX(CL16-(0),0),$D$89*100+$D$102*100)*($D$102*100)/IF(($D$89*100+$D$102*100)=0,1,$D$89*100+$D$102*100)
B25: 트랜치별 인출/상환 + 전체 합계
B27: 구 분 | C27: unit | D27: 합 계 | E27: 2024-06-30 | F27: 2024-09-30 | G27: 2024-12-31 | H27: 2025-03-31 | I27: 2025-06-30 | J27: 2025-09-30 | K27: 2025-12-31 | L27: 2026-03-31 | M27: 2026-06-30 | N27: 2026-09-30 | O27: 2026-12-31 | P27: 2027-03-31 | Q27: 2027-06-30 | R27: 2027-09-30 | S27: 2027-12-31 | T27: 2028-03-31 | U27: 2028-06-30 | V27: 2028-09-30 | W27: 2028-12-31 | X27: 2029-03-31 | Y27: 2029-06-30 | Z27: 2029-09-30 | AA27: 2029-12-31 | AB27: 2030-03-31 | AC27: 2030-06-30 | AD27: 2030-09-30 | AE27: 2030-12-31 | AF27: 2031-03-31 | AG27: 2031-06-30 | AH27: 2031-09-30 | AI27: 2031-12-31 | AJ27: 2032-03-31 | AK27: 2032-06-30 | AL27: 2032-09-30 | AM27: 2032-12-31 | AN27: 2033-03-31 | AO27: 2033-06-30 | AP27: 2033-09-30 | AQ27: 2033-12-31 | AR27: 2034-03-31 | AS27: 2034-06-30 | AT27: 2034-09-30 | AU27: 2034-12-31 | AV27: 2035-03-31 | AW27: 2035-06-30 | AX27: 2035-09-30 | AY27: 2035-12-31 | AZ27: 2036-03-31 | BA27: 2036-06-30 | BB27: 2036-09-30 | BC27: 2036-12-31 | BD27: 2037-03-31 | BE27: 2037-06-30 | BF27: 2037-09-30 | BG27: 2037-12-31 | BH27: 2038-03-31 | BI27: 2038-06-30 | BJ27: 2038-09-30 | BK27: 2038-12-31 | BL27: 2039-03-31 | BM27: 2039-06-30 | BN27: 2039-09-30 | BO27: 2039-12-31 | BP27: 2040-03-31 | BQ27: 2040-06-30 | BR27: 2040-09-30 | BS27: 2040-12-31 | BT27: 2041-03-31 | BU27: 2041-06-30 | BV27: 2041-09-30 | BW27: 2041-12-31 | BX27: 2042-03-31 | BY27: 2042-06-30 | BZ27: 2042-09-30 | CA27: 2042-12-31 | CB27: 2043-03-31 | CC27: 2043-06-30 | CD27: 2043-09-30 | CE27: 2043-12-31 | CF27: 2044-03-31 | CG27: 2044-06-30 | CH27: 2044-09-30 | CI27: 2044-12-31 | CJ27: 2045-03-31 | CK27: 2045-06-30 | CL27: 2045-09-30
B29: 선순위A
B30: 기초잔액 | C30: [KRWm] | E30: 0 | F30: =E35 | G30: =F35 | H30: =G35 | I30: =H35 | J30: =I35 | K30: =J35 | L30: =K35 | M30: =L35 | ... CL30: =CK35
B31: 인출 | C31: [KRWm] | D31: =SUM(E31:CL31) | E31: =E18 | F31: =F18-E18 | G31: =G18-F18 | H31: =H18-G18 | I31: =I18-H18 | J31: =J18-I18 | K31: =K18-J18 | L31: =L18-K18 | M31: =M18-L18 | ... CL31: =CL18-CK18
B32: 건설이자(IDC) | C32: [KRWm] | D32: =SUM(E32:CL32) | E32: =E10 | F32: =F10 | G32: =G10 | H32: =H10 | I32: =I10 | J32: =J10 | K32: =K10 | L32: =L10 | ... CL32: =CL10
B33: 이자(운영) | C33: [KRWm] | D33: =SUM(E33:CL33) | E33: 0 | F33: 0 | G33: 0 | H33: 0 | I33: 0 | J33: 0 | K33: =K30*$D$92/4 | L33: =L30*$D$92/4 | M33: =M30*$D$92/4 | N33: =N30*$D$92/4 | O33: =O30*$D$92/4 | P33: =P30*$D$92/4 | Q33: =Q30*$D$92/4 | R33: =R30*$D$92/4 | ... CL33: =CL30*$D$92/4
B34: 원금상환 | C34: [KRWm] | D34: =SUM(E34:CL34) | E34: 0 | F34: 0 | G34: 0 | H34: 0 | I34: 0 | J34: 0 | K34: 0 | L34: 0 | M34: 0 | N34: =N30/64 | O34: =N30/64 | P34: =N30/64 | Q34: =N30/64 | R34: =N30/64 | S34: =N30/64 | T34: =N30/64 | U34: =N30/64 | V34: =N30/64 | W34: =N30/64 | X34: =N30/64 | Y34: =N30/64 | Z34: =N30/64 | AA34: =N30/64 | AB34: =N30/64 | AC34: =N30/64 | AD34: =N30/64 | AE34: =N30/64 | AF34: =N30/64 | AG34: =N30/64 | AH34: =N30/64 | AI34: =N30/64 | AJ34: =N30/64 | AK34: =N30/64 | AL34: =N30/64 | AM34: =N30/64 | AN34: =N30/64 | AO34: =N30/64 | AP34: =N30/64 | AQ34: =N30/64 | AR34: =N30/64 | AS34: =N30/64 | AT34: =N30/64 | AU34: =N30/64 | AV34: =N30/64 | AW34: =N30/64 | AX34: =N30/64 | AY34: =N30/64 | AZ34: =N30/64 | BA34: =N30/64 | BB34: =N30/64 | BC34: =N30/64 | BD34: =N30/64 | BE34: =N30/64 | BF34: =N30/64 | BG34: =N30/64 | BH34: =N30/64 | BI34: =N30/64 | BJ34: =N30/64 | BK34: =N30/64 | BL34: =N30/64 | BM34: =N30/64 | BN34: =N30/64 | BO34: =N30/64 | BP34: =N30/64 | BQ34: =N30/64 | BR34: =N30/64 | BS34: =N30/64 | BT34: =N30/64 | BU34: =N30/64 | BV34: =N30/64 | BW34: =N30/64 | BX34: =N30/64 | BY34: =N30/64 | BZ34: 0 | CA34: 0 | CB34: 0 | CC34: 0 | CD34: 0 | CE34: 0 | CF34: 0 | CG34: 0 | CH34: 0 | CI34: 0 | CJ34: 0 | CK34: 0 | CL34: 0
B35: 기말잔액 | C35: [KRWm] | E35: =E30+E31-E34 | F35: =F30+F31-F34 | G35: =G30+G31-G34 | H35: =H30+H31-H34 | I35: =I30+I31-I34 | J35: =J30+J31-J34 | K35: =K30+K31-K34 | L35: =L30+L31-L34 | ... CL35: =CL30+CL31-CL34
B36: 미상환 잔액(검증용) | C36: [KRWm] | D36: =CL35 | F36: =IF(ABS(D36)<1,"완전상환 확인 (OK)","경고: 미상환 잔액")
B38: 선순위B
B39: 기초잔액 | C39: [KRWm] | E39: 0 | F39: =E44 | G39: =F44 | H39: =G44 | I39: =H44 | J39: =I44 | K39: =J44 | L39: =K44 | M39: =L44 | ... CL39: =CK44
B40: 인출 | C40: [KRWm] | D40: =SUM(E40:CL40) | E40: =E19 | F40: =F19-E19 | G40: =G19-F19 | H40: =H19-G19 | I40: =I19-H19 | J40: =J19-I19 | K40: =K19-J19 | L40: =L19-K19 | M40: =M19-L19 | ... CL40: =CL19-CK19
B41: 건설이자(IDC) | C41: [KRWm] | D41: =SUM(E41:CL41) | E41: =E11 | F41: =F11 | G41: =G11 | H41: =H11 | I41: =I11 | J41: =J11 | K41: =K11 | L41: =L11 | ... CL41: =CL11
B42: 이자(운영) | C42: [KRWm] | D42: =SUM(E42:CL42) | E42: 0 | F42: 0 | G42: 0 | H42: 0 | I42: 0 | J42: 0 | K42: =K39*$D$95/4 | L42: =L39*$D$95/4 | M42: =M39*$D$95/4 | N42: =N39*$D$95/4 | O42: =O39*$D$95/4 | P42: =P39*$D$95/4 | Q42: =Q39*$D$95/4 | R42: =R39*$D$95/4 | ... CL42: =CL39*$D$95/4
B43: 원금상환 | C43: [KRWm] | D43: =SUM(E43:CL43) | E43: 0 | F43: 0 | G43: 0 | H43: 0 | I43: 0 | J43: 0 | K43: 0 | L43: 0 | M43: 0 | N43: =N39/64 | O43: =N39/64 | P43: =N39/64 | Q43: =N39/64 | R43: =N39/64 | S43: =N39/64 | T43: =N39/64 | U43: =N39/64 | V43: =N39/64 | W43: =N39/64 | X43: =N39/64 | Y43: =N39/64 | Z43: =N39/64 | AA43: =N39/64 | AB43: =N39/64 | AC43: =N39/64 | AD43: =N39/64 | AE43: =N39/64 | AF43: =N39/64 | AG43: =N39/64 | AH43: =N39/64 | AI43: =N39/64 | AJ43: =N39/64 | AK43: =N39/64 | AL43: =N39/64 | AM43: =N39/64 | AN43: =N39/64 | AO43: =N39/64 | AP43: =N39/64 | AQ43: =N39/64 | AR43: =N39/64 | AS43: =N39/64 | AT43: =N39/64 | AU43: =N39/64 | AV43: =N39/64 | AW43: =N39/64 | AX43: =N39/64 | AY43: =N39/64 | AZ43: =N39/64 | BA43: =N39/64 | BB43: =N39/64 | BC43: =N39/64 | BD43: =N39/64 | BE43: =N39/64 | BF43: =N39/64 | BG43: =N39/64 | BH43: =N39/64 | BI43: =N39/64 | BJ43: =N39/64 | BK43: =N39/64 | BL43: =N39/64 | BM43: =N39/64 | BN43: =N39/64 | BO43: =N39/64 | BP43: =N39/64 | BQ43: =N39/64 | BR43: =N39/64 | BS43: =N39/64 | BT43: =N39/64 | BU43: =N39/64 | BV43: =N39/64 | BW43: =N39/64 | BX43: =N39/64 | BY43: =N39/64 | BZ43: 0 | CA43: 0 | CB43: 0 | CC43: 0 | CD43: 0 | CE43: 0 | CF43: 0 | CG43: 0 | CH43: 0 | CI43: 0 | CJ43: 0 | CK43: 0 | CL43: 0
B44: 기말잔액 | C44: [KRWm] | E44: =E39+E40-E43 | F44: =F39+F40-F43 | G44: =G39+G40-G43 | H44: =H39+H40-H43 | I44: =I39+I40-I43 | J44: =J39+J40-J43 | K44: =K39+K40-K43 | L44: =L39+L40-L43 | ... CL44: =CL39+CL40-CL43
B45: 미상환 잔액(검증용) | C45: [KRWm] | D45: =CL44 | F45: =IF(ABS(D45)<1,"완전상환 확인 (OK)","경고: 미상환 잔액")
B47: 선순위C
B48: 기초잔액 | C48: [KRWm] | E48: 0 | F48: =E53 | G48: =F53 | H48: =G53 | I48: =H53 | J48: =I53 | K48: =J53 | L48: =K53 | M48: =L53 | ... CL48: =CK53
B49: 인출 | C49: [KRWm] | D49: =SUM(E49:CL49) | E49: =E20 | F49: =F20-E20 | G49: =G20-F20 | H49: =H20-G20 | I49: =I20-H20 | J49: =J20-I20 | K49: =K20-J20 | L49: =L20-K20 | M49: =M20-L20 | ... CL49: =CL20-CK20
B50: 건설이자(IDC) | C50: [KRWm] | D50: =SUM(E50:CL50) | E50: =E12 | F50: =F12 | G50: =G12 | H50: =H12 | I50: =I12 | J50: =J12 | K50: =K12 | L50: =L12 | ... CL50: =CL12
B51: 이자(운영) | C51: [KRWm] | D51: =SUM(E51:CL51) | E51: 0 | F51: 0 | G51: 0 | H51: 0 | I51: 0 | J51: 0 | K51: =K48*$D$98/4 | L51: =L48*$D$98/4 | M51: =M48*$D$98/4 | N51: =N48*$D$98/4 | O51: =O48*$D$98/4 | P51: =P48*$D$98/4 | Q51: =Q48*$D$98/4 | R51: =R48*$D$98/4 | ... CL51: =CL48*$D$98/4
B52: 원금상환 | C52: [KRWm] | D52: =SUM(E52:CL52) | E52: 0 | F52: 0 | G52: 0 | H52: 0 | I52: 0 | J52: 0 | K52: 0 | L52: 0 | M52: 0 | N52: =N48/64 | O52: =N48/64 | P52: =N48/64 | Q52: =N48/64 | R52: =N48/64 | S52: =N48/64 | T52: =N48/64 | U52: =N48/64 | V52: =N48/64 | W52: =N48/64 | X52: =N48/64 | Y52: =N48/64 | Z52: =N48/64 | AA52: =N48/64 | AB52: =N48/64 | AC52: =N48/64 | AD52: =N48/64 | AE52: =N48/64 | AF52: =N48/64 | AG52: =N48/64 | AH52: =N48/64 | AI52: =N48/64 | AJ52: =N48/64 | AK52: =N48/64 | AL52: =N48/64 | AM52: =N48/64 | AN52: =N48/64 | AO52: =N48/64 | AP52: =N48/64 | AQ52: =N48/64 | AR52: =N48/64 | AS52: =N48/64 | AT52: =N48/64 | AU52: =N48/64 | AV52: =N48/64 | AW52: =N48/64 | AX52: =N48/64 | AY52: =N48/64 | AZ52: =N48/64 | BA52: =N48/64 | BB52: =N48/64 | BC52: =N48/64 | BD52: =N48/64 | BE52: =N48/64 | BF52: =N48/64 | BG52: =N48/64 | BH52: =N48/64 | BI52: =N48/64 | BJ52: =N48/64 | BK52: =N48/64 | BL52: =N48/64 | BM52: =N48/64 | BN52: =N48/64 | BO52: =N48/64 | BP52: =N48/64 | BQ52: =N48/64 | BR52: =N48/64 | BS52: =N48/64 | BT52: =N48/64 | BU52: =N48/64 | BV52: =N48/64 | BW52: =N48/64 | BX52: =N48/64 | BY52: =N48/64 | BZ52: 0 | CA52: 0 | CB52: 0 | CC52: 0 | CD52: 0 | CE52: 0 | CF52: 0 | CG52: 0 | CH52: 0 | CI52: 0 | CJ52: 0 | CK52: 0 | CL52: 0
B53: 기말잔액 | C53: [KRWm] | E53: =E48+E49-E52 | F53: =F48+F49-F52 | G53: =G48+G49-G52 | H53: =H48+H49-H52 | I53: =I48+I49-I52 | J53: =J48+J49-J52 | K53: =K48+K49-K52 | L53: =L48+L49-L52 | ... CL53: =CL48+CL49-CL52
B54: 미상환 잔액(검증용) | C54: [KRWm] | D54: =CL53 | F54: =IF(ABS(D54)<1,"완전상환 확인 (OK)","경고: 미상환 잔액")
B55: 인출 시작 가정 검증 | F55: =IF(AND(H20<1,I20>1),"인출 시작 분기 일치 (OK)","경고: 첫 인출 분기가 생성 당시(2025-06-30)와 달라졌습니다. 상환 스케줄이 들어간 열은 고정이라 실제와 어긋납니다 — 화면(HTML)에서 다시 생성하세요.")
B57: 선순위D
B58: 기초잔액 | C58: [KRWm] | E58: 0 | F58: =E63 | G58: =F63 | H58: =G63 | I58: =H63 | J58: =I63 | K58: =J63 | L58: =K63 | M58: =L63 | ... CL58: =CK63
B59: 인출 | C59: [KRWm] | D59: =SUM(E59:CL59) | E59: =E21 | F59: =F21-E21 | G59: =G21-F21 | H59: =H21-G21 | I59: =I21-H21 | J59: =J21-I21 | K59: =K21-J21 | L59: =L21-K21 | M59: =M21-L21 | ... CL59: =CL21-CK21
B60: 건설이자(IDC) | C60: [KRWm] | D60: =SUM(E60:CL60) | E60: =E13 | F60: =F13 | G60: =G13 | H60: =H13 | I60: =I13 | J60: =J13 | K60: =K13 | L60: =L13 | ... CL60: =CL13
B61: 이자(운영) | C61: [KRWm] | D61: =SUM(E61:CL61) | E61: 0 | F61: 0 | G61: 0 | H61: 0 | I61: 0 | J61: 0 | K61: =K58*$D$101/4 | L61: =L58*$D$101/4 | M61: =M58*$D$101/4 | N61: =N58*$D$101/4 | O61: =O58*$D$101/4 | P61: =P58*$D$101/4 | Q61: =Q58*$D$101/4 | R61: =R58*$D$101/4 | ... CL61: =CL58*$D$101/4
B62: 원금상환 | C62: [KRWm] | D62: =SUM(E62:CL62) | E62: 0 | F62: 0 | G62: 0 | H62: 0 | I62: 0 | J62: 0 | K62: 0 | L62: 0 | M62: 0 | N62: 0 | O62: 0 | P62: 0 | Q62: 0 | R62: 0 | S62: 0 | T62: 0 | U62: 0 | V62: 0 | W62: 0 | X62: 0 | Y62: 0 | Z62: 0 | AA62: 0 | AB62: 0 | AC62: 0 | AD62: 0 | AE62: 0 | AF62: 0 | AG62: 0 | AH62: 0 | AI62: 0 | AJ62: 0 | AK62: 0 | AL62: 0 | AM62: 0 | AN62: 0 | AO62: 0 | AP62: 0 | AQ62: 0 | AR62: 0 | AS62: 0 | AT62: 0 | AU62: 0 | AV62: 0 | AW62: 0 | AX62: 0 | AY62: 0 | AZ62: 0 | BA62: 0 | BB62: 0 | BC62: 0 | BD62: 0 | BE62: 0 | BF62: 0 | BG62: 0 | BH62: 0 | BI62: 0 | BJ62: 0 | BK62: 0 | BL62: 0 | BM62: 0 | BN62: 0 | BO62: 0 | BP62: 0 | BQ62: 0 | BR62: 0 | BS62: 0 | BT62: 0 | BU62: 0 | BV62: 0 | BW62: 0 | BX62: 0 | BY62: 0 | BZ62: 0 | CA62: 0 | CB62: 0 | CC62: 0 | CD62: 0 | CE62: 0 | CF62: 0 | CG62: 0 | CH62: 0 | CI62: 0 | CJ62: 0 | CK62: 0 | CL62: 0
B63: 기말잔액 | C63: [KRWm] | E63: =E58+E59-E62 | F63: =F58+F59-F62 | G63: =G58+G59-G62 | H63: =H58+H59-H62 | I63: =I58+I59-I62 | J63: =J58+J59-J62 | K63: =K58+K59-K62 | L63: =L58+L59-L62 | ... CL63: =CL58+CL59-CL62
B64: 미상환 잔액(검증용) | C64: [KRWm] | D64: =CL63 | F64: =IF(ABS(D64)<1,"완전상환 확인 (OK)","경고: 미상환 잔액") | H64: ※ 미사용 트랜치(금액 0) — 인출·상환 없음
B66: 후순위
B67: 기초잔액 | C67: [KRWm] | E67: 0 | F67: =E72 | G67: =F72 | H67: =G72 | I67: =H72 | J67: =I72 | K67: =J72 | L67: =K72 | M67: =L72 | ... CL67: =CK72
B68: 인출 | C68: [KRWm] | D68: =SUM(E68:CL68) | E68: =E22 | F68: =F22-E22 | G68: =G22-F22 | H68: =H22-G22 | I68: =I22-H22 | J68: =J22-I22 | K68: =K22-J22 | L68: =L22-K22 | M68: =M22-L22 | ... CL68: =CL22-CK22
B69: 건설이자(IDC) | C69: [KRWm] | D69: =SUM(E69:CL69) | E69: =E14 | F69: =F14 | G69: =G14 | H69: =H14 | I69: =I14 | J69: =J14 | K69: =K14 | L69: =L14 | ... CL69: =CL14
B70: 이자(운영) | C70: [KRWm] | D70: =SUM(E70:CL70) | E70: 0 | F70: 0 | G70: 0 | H70: 0 | I70: 0 | J70: 0 | K70: =K67*$D$104/4 | L70: =L67*$D$104/4 | M70: =M67*$D$104/4 | N70: =N67*$D$104/4 | O70: =O67*$D$104/4 | P70: =P67*$D$104/4 | Q70: =Q67*$D$104/4 | R70: =R67*$D$104/4 | ... CL70: =CL67*$D$104/4
B71: 원금상환 | C71: [KRWm] | D71: =SUM(E71:CL71) | E71: 0 | F71: 0 | G71: 0 | H71: 0 | I71: 0 | J71: 0 | K71: 0 | L71: 0 | M71: 0 | N71: 0 | O71: 0 | P71: 0 | Q71: 0 | R71: 0 | S71: 0 | T71: 0 | U71: 0 | V71: 0 | W71: 0 | X71: 0 | Y71: 0 | Z71: 0 | AA71: 0 | AB71: 0 | AC71: 0 | AD71: 0 | AE71: 0 | AF71: 0 | AG71: 0 | AH71: 0 | AI71: 0 | AJ71: 0 | AK71: 0 | AL71: 0 | AM71: 0 | AN71: 0 | AO71: 0 | AP71: 0 | AQ71: 0 | AR71: 0 | AS71: 0 | AT71: 0 | AU71: 0 | AV71: 0 | AW71: 0 | AX71: 0 | AY71: 0 | AZ71: 0 | BA71: 0 | BB71: 0 | BC71: 0 | BD71: 0 | BE71: 0 | BF71: 0 | BG71: 0 | BH71: 0 | BI71: 0 | BJ71: 0 | BK71: 0 | BL71: 0 | BM71: 0 | BN71: 0 | BO71: 0 | BP71: 0 | BQ71: 0 | BR71: 0 | BS71: 0 | BT71: 0 | BU71: 0 | BV71: 0 | BW71: 0 | BX71: 0 | BY71: 0 | BZ71: 0 | CA71: 0 | CB71: 0 | CC71: 0 | CD71: 0 | CE71: 0 | CF71: 0 | CG71: 0 | CH71: 0 | CI71: 0 | CJ71: 0 | CK71: 0 | CL71: 0
B72: 기말잔액 | C72: [KRWm] | E72: =E67+E68-E71 | F72: =F67+F68-F71 | G72: =G67+G68-G71 | H72: =H67+H68-H71 | I72: =I67+I68-I71 | J72: =J67+J68-J71 | K72: =K67+K68-K71 | L72: =L67+L68-L71 | ... CL72: =CL67+CL68-CL71
B73: 미상환 잔액(검증용) | C73: [KRWm] | D73: =CL72 | F73: =IF(ABS(D73)<1,"완전상환 확인 (OK)","경고: 미상환 잔액") | H73: ※ 미사용 트랜치(금액 0) — 인출·상환 없음
B75: 전체 합계
B76: 기초잔액 | C76: [KRWm] | E76: =E30+E39+E48+E58+E67 | F76: =F30+F39+F48+F58+F67 | G76: =G30+G39+G48+G58+G67 | H76: =H30+H39+H48+H58+H67 | I76: =I30+I39+I48+I58+I67 | J76: =J30+J39+J48+J58+J67 | K76: =K30+K39+K48+K58+K67 | L76: =L30+L39+L48+L58+L67 | ... CL76: =CL30+CL39+CL48+CL58+CL67
B77: 이자 | C77: [KRWm] | D77: =SUM(E77:CL77) | E77: =E33+E42+E51+E61+E70 | F77: =F33+F42+F51+F61+F70 | G77: =G33+G42+G51+G61+G70 | H77: =H33+H42+H51+H61+H70 | I77: =I33+I42+I51+I61+I70 | J77: =J33+J42+J51+J61+J70 | K77: =K33+K42+K51+K61+K70 | L77: =L33+L42+L51+L61+L70 | ... CL77: =CL33+CL42+CL51+CL61+CL70
B78: 원금상환 | C78: [KRWm] | D78: =SUM(E78:CL78) | E78: =E34+E43+E52+E62+E71 | F78: =F34+F43+F52+F62+F71 | G78: =G34+G43+G52+G62+G71 | H78: =H34+H43+H52+H62+H71 | I78: =I34+I43+I52+I62+I71 | J78: =J34+J43+J52+J62+J71 | K78: =K34+K43+K52+K62+K71 | L78: =L34+L43+L52+L62+L71 | ... CL78: =CL34+CL43+CL52+CL62+CL71
B79: 원리금(DS) | C79: [KRWm] | D79: =SUM(E79:CL79) | E79: =E77+E78 | F79: =F77+F78 | G79: =G77+G78 | H79: =H77+H78 | I79: =I77+I78 | J79: =J77+J78 | K79: =K77+K78 | L79: =L77+L78 | ... CL79: =CL77+CL78
B80: 기말잔액 | C80: [KRWm] | E80: =E35+E44+E53+E63+E72 | F80: =F35+F44+F53+F63+F72 | G80: =G35+G44+G53+G63+G72 | H80: =H35+H44+H53+H63+H72 | I80: =I35+I44+I53+I63+I72 | J80: =J35+J44+J53+J63+J72 | K80: =K35+K44+K53+K63+K72 | L80: =L35+L44+L53+L63+L72 | ... CL80: =CL35+CL44+CL53+CL63+CL72
B82: DSRA 기초잔액 | C82: [KRWm] | E82: =0 | F82: =E83 | G82: =F83 | H82: =G83 | I82: =H83 | J82: ='입력값'!C23*100 | K82: =J83 | L82: =K83 | M82: =L83 | N82: =M83 | O82: =N83 | P82: =O83 | Q82: =P83 | R82: =Q83 | ... CL82: =CK83
B83: DSRA 기말잔액 | C83: [KRWm] | E83: =E82 | F83: =F82 | G83: =G82 | H83: =H82 | I83: =I82 | J83: =J82 | K83: =L79+M79 | L83: =M79+N79 | M83: =N79+O79 | N83: =O79+P79 | O83: =P79+Q79 | P83: =Q79+R79 | Q83: =R79+S79 | R83: =S79+T79 | ... CJ83: =CK79+CL79 | CK83: =CL79 | CL83: =0
B86: 가정 (입력값 연결) — 이 시트의 계산이 쓰는 원천값 | D86: 값
B87: ※ 입력값 시트는 여기서만 참조합니다(초록 글자 = 입력값 연결). 위의 분기 계산은 이 셀들만 참조하므로, 값을 바꾸려면 입력값 시트를 고치세요.
B88: 총사업비[억원] | C88: C8 | D88: ='입력값'!C8
B89: 자기자본[억원] | C89: C9 | D89: ='입력값'!C9
B90: 선순위A · 금액[억원] | C90: C46 | D90: ='입력값'!C46
B91: 선순위A · 건설금리[%] | C91: D46 | D91: ='입력값'!D46
B92: 선순위A · 운영금리[%] | C92: E46 | D92: ='입력값'!E46
B93: 선순위B · 금액[억원] | C93: C47 | D93: ='입력값'!C47
B94: 선순위B · 건설금리[%] | C94: D47 | D94: ='입력값'!D47
B95: 선순위B · 운영금리[%] | C95: E47 | D95: ='입력값'!E47
B96: 선순위C · 금액[억원] | C96: C48 | D96: ='입력값'!C48
B97: 선순위C · 건설금리[%] | C97: D48 | D97: ='입력값'!D48
B98: 선순위C · 운영금리[%] | C98: E48 | D98: ='입력값'!E48
B99: 선순위D · 금액[억원] | C99: C49 | D99: ='입력값'!C49
B100: 선순위D · 건설금리[%] | C100: D49 | D100: ='입력값'!D49
B101: 선순위D · 운영금리[%] | C101: E49 | D101: ='입력값'!E49
B102: 후순위 · 금액[억원] | C102: C50 | D102: ='입력값'!C50
B103: 후순위 · 건설금리[%] | C103: D50 | D103: ='입력값'!D50
B104: 후순위 · 운영금리[%] | C104: E50 | D104: ='입력값'!E50
B105: 지출 비중 | C105: 입력값 57행 | E105: ='입력값'!E57 | F105: ='입력값'!F57 | G105: ='입력값'!G57 | H105: ='입력값'!H57 | I105: ='입력값'!I57 | J105: ='입력값'!J57

Sheet Revenue
A1: 태양광 발전사업
A2: 영업수익 추정
B4: 발전량 및 매출
B6: 구 분 | C6: unit | D6: 합 계 | E6: 2024-06-30 | F6: 2024-09-30 | G6: 2024-12-31 | H6: 2025-03-31 | I6: 2025-06-30 | J6: 2025-09-30 | K6: 2025-12-31 | L6: 2026-03-31 | M6: 2026-06-30 | N6: 2026-09-30 | O6: 2026-12-31 | P6: 2027-03-31 | Q6: 2027-06-30 | R6: 2027-09-30 | S6: 2027-12-31 | T6: 2028-03-31 | U6: 2028-06-30 | V6: 2028-09-30 | W6: 2028-12-31 | X6: 2029-03-31 | Y6: 2029-06-30 | Z6: 2029-09-30 | AA6: 2029-12-31 | AB6: 2030-03-31 | AC6: 2030-06-30 | AD6: 2030-09-30 | AE6: 2030-12-31 | AF6: 2031-03-31 | AG6: 2031-06-30 | AH6: 2031-09-30 | AI6: 2031-12-31 | AJ6: 2032-03-31 | AK6: 2032-06-30 | AL6: 2032-09-30 | AM6: 2032-12-31 | AN6: 2033-03-31 | AO6: 2033-06-30 | AP6: 2033-09-30 | AQ6: 2033-12-31 | AR6: 2034-03-31 | AS6: 2034-06-30 | AT6: 2034-09-30 | AU6: 2034-12-31 | AV6: 2035-03-31 | AW6: 2035-06-30 | AX6: 2035-09-30 | AY6: 2035-12-31 | AZ6: 2036-03-31 | BA6: 2036-06-30 | BB6: 2036-09-30 | BC6: 2036-12-31 | BD6: 2037-03-31 | BE6: 2037-06-30 | BF6: 2037-09-30 | BG6: 2037-12-31 | BH6: 2038-03-31 | BI6: 2038-06-30 | BJ6: 2038-09-30 | BK6: 2038-12-31 | BL6: 2039-03-31 | BM6: 2039-06-30 | BN6: 2039-09-30 | BO6: 2039-12-31 | BP6: 2040-03-31 | BQ6: 2040-06-30 | BR6: 2040-09-30 | BS6: 2040-12-31 | BT6: 2041-03-31 | BU6: 2041-06-30 | BV6: 2041-09-30 | BW6: 2041-12-31 | BX6: 2042-03-31 | BY6: 2042-06-30 | BZ6: 2042-09-30 | CA6: 2042-12-31 | CB6: 2043-03-31 | CC6: 2043-06-30 | CD6: 2043-09-30 | CE6: 2043-12-31 | CF6: 2044-03-31 | CG6: 2044-06-30 | CH6: 2044-09-30 | CI6: 2044-12-31 | CJ6: 2045-03-31 | CK6: 2045-06-30 | CL6: 2045-09-30
B8: 운영연차 (첫 해 = 0) | C8: [yr] | E8: 0 | F8: 0 | G8: 0 | H8: 0 | I8: 0 | J8: 0 | K8: 0 | L8: 0 | M8: 0 | N8: 0 | O8: 1 | P8: 1 | Q8: 1 | R8: 1 | S8: 2 | T8: 2 | U8: 2 | V8: 2 | W8: 3 | X8: 3 | Y8: 3 | Z8: 3 | AA8: 4 | AB8: 4 | AC8: 4 | AD8: 4 | AE8: 5 | AF8: 5 | AG8: 5 | AH8: 5 | AI8: 6 | AJ8: 6 | AK8: 6 | AL8: 6 | AM8: 7 | AN8: 7 | AO8: 7 | AP8: 7 | AQ8: 8 | AR8: 8 | AS8: 8 | AT8: 8 | AU8: 9 | AV8: 9 | AW8: 9 | AX8: 9 | AY8: 10 | AZ8: 10 | BA8: 10 | BB8: 10 | BC8: 11 | BD8: 11 | BE8: 11 | BF8: 11 | BG8: 12 | BH8: 12 | BI8: 12 | BJ8: 12 | BK8: 13 | BL8: 13 | BM8: 13 | BN8: 13 | BO8: 14 | BP8: 14 | BQ8: 14 | BR8: 14 | BS8: 15 | BT8: 15 | BU8: 15 | BV8: 15 | BW8: 16 | BX8: 16 | BY8: 16 | BZ8: 16 | CA8: 17 | CB8: 17 | CC8: 17 | CD8: 17 | CE8: 18 | CF8: 18 | CG8: 18 | CH8: 18 | CI8: 19 | CJ8: 19 | CK8: 19 | CL8: 19
B9: 발전 기간비중 (연간 = 1) | C9: [배] | E9: 0 | F9: 0 | G9: 0 | H9: 0 | I9: 0 | J9: 0 | K9: 0.25 | L9: 0.25 | M9: 0.25 | N9: 0.25 | O9: 0.25 | P9: 0.25 | Q9: 0.25 | R9: 0.25 | S9: 0.25 | T9: 0.25 | U9: 0.25 | V9: 0.25 | W9: 0.25 | X9: 0.25 | Y9: 0.25 | Z9: 0.25 | AA9: 0.25 | AB9: 0.25 | AC9: 0.25 | AD9: 0.25 | AE9: 0.25 | AF9: 0.25 | AG9: 0.25 | AH9: 0.25 | AI9: 0.25 | AJ9: 0.25 | AK9: 0.25 | AL9: 0.25 | AM9: 0.25 | AN9: 0.25 | AO9: 0.25 | AP9: 0.25 | AQ9: 0.25 | AR9: 0.25 | AS9: 0.25 | AT9: 0.25 | AU9: 0.25 | AV9: 0.25 | AW9: 0.25 | AX9: 0.25 | AY9: 0.25 | AZ9: 0.25 | BA9: 0.25 | BB9: 0.25 | BC9: 0.25 | BD9: 0.25 | BE9: 0.25 | BF9: 0.25 | BG9: 0.25 | BH9: 0.25 | BI9: 0.25 | BJ9: 0.25 | BK9: 0.25 | BL9: 0.25 | BM9: 0.25 | BN9: 0.25 | BO9: 0.25 | BP9: 0.25 | BQ9: 0.25 | BR9: 0.25 | BS9: 0.25 | BT9: 0.25 | BU9: 0.25 | BV9: 0.25 | BW9: 0.25 | BX9: 0.25 | BY9: 0.25 | BZ9: 0.25 | CA9: 0.25 | CB9: 0.25 | CC9: 0.25 | CD9: 0.25 | CE9: 0.25 | CF9: 0.25 | CG9: 0.25 | CH9: 0.25 | CI9: 0.25 | CJ9: 0.25 | CK9: 0.25 | CL9: 0.25
B11: 발전량 | C11: [MWh] | D11: =SUM(E11:CL11) | E11: =($D$28*$D$31*365)*MAX(0,1-$D$29/100*E8)*(1-$D$30/100)*E9 | F11: =($D$28*$D$31*365)*MAX(0,1-$D$29/100*F8)*(1-$D$30/100)*F9 | G11: =($D$28*$D$31*365)*MAX(0,1-$D$29/100*G8)*(1-$D$30/100)*G9 | H11: =($D$28*$D$31*365)*MAX(0,1-$D$29/100*H8)*(1-$D$30/100)*H9 | I11: =($D$28*$D$31*365)*MAX(0,1-$D$29/100*I8)*(1-$D$30/100)*I9 | J11: =($D$28*$D$31*365)*MAX(0,1-$D$29/100*J8)*(1-$D$30/100)*J9 | K11: =($D$28*$D$31*365)*MAX(0,1-$D$29/100*K8)*(1-$D$30/100)*K9 | L11: =($D$28*$D$31*365)*MAX(0,1-$D$29/100*L8)*(1-$D$30/100)*L9 | ... CL11: =($D$28*$D$31*365)*MAX(0,1-$D$29/100*CL8)*(1-$D$30/100)*CL9
B13: PPA 판매단가 | C13: [원/kWh] | K13: =$D$33*(1+$D$34/100)^K8 | L13: =$D$33*(1+$D$34/100)^L8 | M13: =$D$33*(1+$D$34/100)^M8 | N13: =$D$33*(1+$D$34/100)^N8 | O13: =$D$33*(1+$D$34/100)^O8 | P13: =$D$33*(1+$D$34/100)^P8 | Q13: =$D$33*(1+$D$34/100)^Q8 | R13: =$D$33*(1+$D$34/100)^R8 | ... CL13: =$D$33*(1+$D$34/100)^CL8
B14: PPA 매출 | C14: [KRWm] | D14: =SUM(E14:CL14) | E14: 0 | F14: 0 | G14: 0 | H14: 0 | I14: 0 | J14: 0 | K14: =K11*$D$32/100*K13/1000 | L14: =L11*$D$32/100*L13/1000 | M14: =M11*$D$32/100*M13/1000 | N14: =N11*$D$32/100*N13/1000 | O14: =O11*$D$32/100*O13/1000 | P14: =P11*$D$32/100*P13/1000 | Q14: =Q11*$D$32/100*Q13/1000 | R14: =R11*$D$32/100*R13/1000 | ... CL14: =CL11*$D$32/100*CL13/1000
B16: 판매단가 (가중평균) | C16: [원/kWh] | K16: =IF(K11=0,0,K17*1000/K11) | L16: =IF(L11=0,0,L17*1000/L11) | M16: =IF(M11=0,0,M17*1000/M11) | N16: =IF(N11=0,0,N17*1000/N11) | O16: =IF(O11=0,0,O17*1000/O11) | P16: =IF(P11=0,0,P17*1000/P11) | Q16: =IF(Q11=0,0,Q17*1000/Q11) | R16: =IF(R11=0,0,R17*1000/R11) | ... CL16: =IF(CL11=0,0,CL17*1000/CL11)
B17: 영업수익 | C17: [KRWm] | D17: =SUM(E17:CL17) | E17: 0 | F17: 0 | G17: 0 | H17: 0 | I17: 0 | J17: 0 | K17: =SUM(K14:K14) | L17: =SUM(L14:L14) | M17: =SUM(M14:M14) | N17: =SUM(N14:N14) | O17: =SUM(O14:O14) | P17: =SUM(P14:P14) | Q17: =SUM(Q14:Q14) | R17: =SUM(R14:R14) | ... CL17: =SUM(CL14:CL14)
B19: 매출채권(A/R) 회수 시차
B21: PPA 기말 미수금 | C21: [KRWm] | E21: =MIN($D$35,3)/3*E14+MAX($D$35-3,0)/3*0 | F21: =MIN($D$35,3)/3*F14+MAX($D$35-3,0)/3*E14 | G21: =MIN($D$35,3)/3*G14+MAX($D$35-3,0)/3*F14 | H21: =MIN($D$35,3)/3*H14+MAX($D$35-3,0)/3*G14 | I21: =MIN($D$35,3)/3*I14+MAX($D$35-3,0)/3*H14 | J21: =MIN($D$35,3)/3*J14+MAX($D$35-3,0)/3*I14 | K21: =MIN($D$35,3)/3*K14+MAX($D$35-3,0)/3*J14 | L21: =MIN($D$35,3)/3*L14+MAX($D$35-3,0)/3*K14 | M21: =MIN($D$35,3)/3*M14+MAX($D$35-3,0)/3*L14 | ... CK21: =MIN($D$35,3)/3*CK14+MAX($D$35-3,0)/3*CJ14 | CL21: 0
B22: 운전자본 증감(A/R) | C22: [KRWm] | D22: =SUM(E22:CL22) | E22: =0-E21 | F22: =E21-F21 | G22: =F21-G21 | H22: =G21-H21 | I22: =H21-I21 | J22: =I21-J21 | K22: =J21-K21 | L22: =K21-L21 | M22: =L21-M21 | ... CL22: =CK21-CL21
B23: ※ 20년 전체 합계는 0입니다(초기에 묶인 미수금을 마지막에 전액 회수). 다만 분기별로는 크게 움직여서 준공 직후 DSCR과 Equity IRR에 영향을 줍니다.
B26: 가정 (입력값 연결) — 이 시트의 계산이 쓰는 원천값 | D26: 값
B27: ※ 입력값 시트는 여기서만 참조합니다(초록 글자 = 입력값 연결). 위의 분기 계산은 이 셀들만 참조하므로, 값을 바꾸려면 입력값 시트를 고치세요.
B28: 설비용량[MW] | C28: C7 | D28: ='입력값'!C7
B29: 발전량 열화율[%/yr] | C29: C12 | D29: ='입력값'!C12
B30: 소내소비율[%] | C30: C13 | D30: ='입력값'!C13
B31: 일조시간[h/day] | C31: C14 | D31: ='입력값'!C14
B32: PPA · 비중[%] | C32: C41 | D32: ='입력값'!C41
B33: PPA · 단가[원/kWh] | C33: D41 | D33: ='입력값'!D41
B34: PPA · 에스컬레이션[%/yr] | C34: E41 | D34: ='입력값'!E41
B35: PPA · 대금회수시차[개월] | C35: F41 | D35: ='입력값'!F41

Sheet Opex
A1: 태양광 발전사업
A2: 영업비용 추정
B4: 운영비용 (선순위/후순위 지급순위 반영)
B6: 구 분 | C6: unit | D6: 합 계 | E6: 2024-06-30 | F6: 2024-09-30 | G6: 2024-12-31 | H6: 2025-03-31 | I6: 2025-06-30 | J6: 2025-09-30 | K6: 2025-12-31 | L6: 2026-03-31 | M6: 2026-06-30 | N6: 2026-09-30 | O6: 2026-12-31 | P6: 2027-03-31 | Q6: 2027-06-30 | R6: 2027-09-30 | S6: 2027-12-31 | T6: 2028-03-31 | U6: 2028-06-30 | V6: 2028-09-30 | W6: 2028-12-31 | X6: 2029-03-31 | Y6: 2029-06-30 | Z6: 2029-09-30 | AA6: 2029-12-31 | AB6: 2030-03-31 | AC6: 2030-06-30 | AD6: 2030-09-30 | AE6: 2030-12-31 | AF6: 2031-03-31 | AG6: 2031-06-30 | AH6: 2031-09-30 | AI6: 2031-12-31 | AJ6: 2032-03-31 | AK6: 2032-06-30 | AL6: 2032-09-30 | AM6: 2032-12-31 | AN6: 2033-03-31 | AO6: 2033-06-30 | AP6: 2033-09-30 | AQ6: 2033-12-31 | AR6: 2034-03-31 | AS6: 2034-06-30 | AT6: 2034-09-30 | AU6: 2034-12-31 | AV6: 2035-03-31 | AW6: 2035-06-30 | AX6: 2035-09-30 | AY6: 2035-12-31 | AZ6: 2036-03-31 | BA6: 2036-06-30 | BB6: 2036-09-30 | BC6: 2036-12-31 | BD6: 2037-03-31 | BE6: 2037-06-30 | BF6: 2037-09-30 | BG6: 2037-12-31 | BH6: 2038-03-31 | BI6: 2038-06-30 | BJ6: 2038-09-30 | BK6: 2038-12-31 | BL6: 2039-03-31 | BM6: 2039-06-30 | BN6: 2039-09-30 | BO6: 2039-12-31 | BP6: 2040-03-31 | BQ6: 2040-06-30 | BR6: 2040-09-30 | BS6: 2040-12-31 | BT6: 2041-03-31 | BU6: 2041-06-30 | BV6: 2041-09-30 | BW6: 2041-12-31 | BX6: 2042-03-31 | BY6: 2042-06-30 | BZ6: 2042-09-30 | CA6: 2042-12-31 | CB6: 2043-03-31 | CC6: 2043-06-30 | CD6: 2043-09-30 | CE6: 2043-12-31 | CF6: 2044-03-31 | CG6: 2044-06-30 | CH6: 2044-09-30 | CI6: 2044-12-31 | CJ6: 2045-03-31 | CK6: 2045-06-30 | CL6: 2045-09-30
B8: 항목별 세부내역
B9: 부지임대료 | C9: [KRWm]
B10: O&M | C10: [KRWm]
B11: 보험료 | C11: [KRWm]
B12: 환경모니터링비용 | C12: [KRWm]
B13: 소내전력비 | C13: [KRWm]
B14: 인건비 | C14: [KRWm]
B15: 법인운영비 | C15: [KRWm]
B16: 주민보상비 | C16: [KRWm]
B17: 도로점용료 | C17: [KRWm]
B18: 예비비 | C18: [KRWm]
B19: 전력거래수수료 | C19: [KRWm]
B20: 관리운영비 성과보수 | C20: [KRWm]
B22: 선순위운영비 | C22: [KRWm] | D22: =SUM(E22:CL22) | E22: 0 | F22: 0 | G22: 0 | H22: 0 | I22: 0 | J22: 0 | K22: =K24-K23 | L22: =L24-L23 | M22: =M24-M23 | N22: =N24-N23 | O22: =O24-O23 | P22: =P24-P23 | Q22: =Q24-Q23 | R22: =R24-R23 | ... CL22: =CL24-CL23
B23: 후순위운영비 | C23: [KRWm] | D23: =SUM(E23:CL23) | E23: 0 | F23: 0 | G23: 0 | H23: 0 | I23: 0 | J23: 0 | K23: =K24*$D$33/100 | L23: =L24*$D$33/100 | M23: =M24*$D$33/100 | N23: =N24*$D$33/100 | O23: =O24*$D$33/100 | P23: =P24*$D$33/100 | Q23: =Q24*$D$33/100 | R23: =R24*$D$33/100 | ... CL23: =CL24*$D$33/100
B24: 영업비용 합계 | C24: [KRWm] | D24: =SUM(E24:CL24) | E24: =E22+E23 | F24: =F22+F23 | G24: =G22+G23 | H24: =H22+H23 | I24: =I22+I23 | J24: =J22+J23 | K24: =$D$31*100*(1+$D$32/100)^0*(3/12) | L24: =$D$31*100*(1+$D$32/100)^0*(3/12) | M24: =$D$31*100*(1+$D$32/100)^0*(3/12) | N24: =$D$31*100*(1+$D$32/100)^0*(3/12) | O24: =$D$31*100*(1+$D$32/100)^1*(3/12) | P24: =$D$31*100*(1+$D$32/100)^1*(3/12) | Q24: =$D$31*100*(1+$D$32/100)^1*(3/12) | R24: =$D$31*100*(1+$D$32/100)^1*(3/12) | S24: =$D$31*100*(1+$D$32/100)^2*(3/12) | T24: =$D$31*100*(1+$D$32/100)^2*(3/12) | U24: =$D$31*100*(1+$D$32/100)^2*(3/12) | V24: =$D$31*100*(1+$D$32/100)^2*(3/12) | W24: =$D$31*100*(1+$D$32/100)^3*(3/12) | X24: =$D$31*100*(1+$D$32/100)^3*(3/12) | Y24: =$D$31*100*(1+$D$32/100)^3*(3/12) | Z24: =$D$31*100*(1+$D$32/100)^3*(3/12) | AA24: =$D$31*100*(1+$D$32/100)^4*(3/12) | AB24: =$D$31*100*(1+$D$32/100)^4*(3/12) | AC24: =$D$31*100*(1+$D$32/100)^4*(3/12) | AD24: =$D$31*100*(1+$D$32/100)^4*(3/12) | AE24: =$D$31*100*(1+$D$32/100)^5*(3/12) | AF24: =$D$31*100*(1+$D$32/100)^5*(3/12) | AG24: =$D$31*100*(1+$D$32/100)^5*(3/12) | AH24: =$D$31*100*(1+$D$32/100)^5*(3/12) | AI24: =$D$31*100*(1+$D$32/100)^6*(3/12) | AJ24: =$D$31*100*(1+$D$32/100)^6*(3/12) | AK24: =$D$31*100*(1+$D$32/100)^6*(3/12) | AL24: =$D$31*100*(1+$D$32/100)^6*(3/12) | AM24: =$D$31*100*(1+$D$32/100)^7*(3/12) | AN24: =$D$31*100*(1+$D$32/100)^7*(3/12) | AO24: =$D$31*100*(1+$D$32/100)^7*(3/12) | AP24: =$D$31*100*(1+$D$32/100)^7*(3/12) | AQ24: =$D$31*100*(1+$D$32/100)^8*(3/12) | AR24: =$D$31*100*(1+$D$32/100)^8*(3/12) | AS24: =$D$31*100*(1+$D$32/100)^8*(3/12) | AT24: =$D$31*100*(1+$D$32/100)^8*(3/12) | AU24: =$D$31*100*(1+$D$32/100)^9*(3/12) | AV24: =$D$31*100*(1+$D$32/100)^9*(3/12) | AW24: =$D$31*100*(1+$D$32/100)^9*(3/12) | AX24: =$D$31*100*(1+$D$32/100)^9*(3/12) | AY24: =$D$31*100*(1+$D$32/100)^10*(3/12) | AZ24: =$D$31*100*(1+$D$32/100)^10*(3/12) | BA24: =$D$31*100*(1+$D$32/100)^10*(3/12) | BB24: =$D$31*100*(1+$D$32/100)^10*(3/12) | BC24: =$D$31*100*(1+$D$32/100)^11*(3/12) | BD24: =$D$31*100*(1+$D$32/100)^11*(3/12) | BE24: =$D$31*100*(1+$D$32/100)^11*(3/12) | BF24: =$D$31*100*(1+$D$32/100)^11*(3/12) | BG24: =$D$31*100*(1+$D$32/100)^12*(3/12) | BH24: =$D$31*100*(1+$D$32/100)^12*(3/12) | BI24: =$D$31*100*(1+$D$32/100)^12*(3/12) | BJ24: =$D$31*100*(1+$D$32/100)^12*(3/12) | BK24: =$D$31*100*(1+$D$32/100)^13*(3/12) | BL24: =$D$31*100*(1+$D$32/100)^13*(3/12) | BM24: =$D$31*100*(1+$D$32/100)^13*(3/12) | BN24: =$D$31*100*(1+$D$32/100)^13*(3/12) | BO24: =$D$31*100*(1+$D$32/100)^14*(3/12) | BP24: =$D$31*100*(1+$D$32/100)^14*(3/12) | BQ24: =$D$31*100*(1+$D$32/100)^14*(3/12) | BR24: =$D$31*100*(1+$D$32/100)^14*(3/12) | BS24: =$D$31*100*(1+$D$32/100)^15*(3/12) | BT24: =$D$31*100*(1+$D$32/100)^15*(3/12) | BU24: =$D$31*100*(1+$D$32/100)^15*(3/12) | BV24: =$D$31*100*(1+$D$32/100)^15*(3/12) | BW24: =$D$31*100*(1+$D$32/100)^16*(3/12) | BX24: =$D$31*100*(1+$D$32/100)^16*(3/12) | BY24: =$D$31*100*(1+$D$32/100)^16*(3/12) | BZ24: =$D$31*100*(1+$D$32/100)^16*(3/12) | CA24: =$D$31*100*(1+$D$32/100)^17*(3/12) | CB24: =$D$31*100*(1+$D$32/100)^17*(3/12) | CC24: =$D$31*100*(1+$D$32/100)^17*(3/12) | CD24: =$D$31*100*(1+$D$32/100)^17*(3/12) | CE24: =$D$31*100*(1+$D$32/100)^18*(3/12) | CF24: =$D$31*100*(1+$D$32/100)^18*(3/12) | CG24: =$D$31*100*(1+$D$32/100)^18*(3/12) | CH24: =$D$31*100*(1+$D$32/100)^18*(3/12) | CI24: =$D$31*100*(1+$D$32/100)^19*(3/12) | CJ24: =$D$31*100*(1+$D$32/100)^19*(3/12) | CK24: =$D$31*100*(1+$D$32/100)^19*(3/12) | CL24: =$D$31*100*(1+$D$32/100)^19*(3/12)
B26: ※ 화면에서 운영비를 합계로만 입력해서 항목별 금액은 비어 있습니다 — 항목별로 입력하면 이 표에 실제 금액이 채워집니다.
B29: 가정 (입력값 연결) — 이 시트의 계산이 쓰는 원천값 | D29: 값
B30: ※ 입력값 시트는 여기서만 참조합니다(초록 글자 = 입력값 연결). 위의 분기 계산은 이 셀들만 참조하므로, 값을 바꾸려면 입력값 시트를 고치세요.
B31: 운영비 총액[억원/yr] | C31: C18 | D31: ='입력값'!C18
B32: 운영비 에스컬레이션[%/yr] | C32: C19 | D32: ='입력값'!C19
B33: 운영비 중 후순위 비중[%] | C33: C20 | D33: ='입력값'!C20

Sheet IS(Q)
A1: 태양광 발전사업
A2: 추정 손익계산서 (분기)
B4: 손익계산서
B6: 구 분 | C6: unit | D6: 합 계 | E6: 2024-06-30 | F6: 2024-09-30 | G6: 2024-12-31 | H6: 2025-03-31 | I6: 2025-06-30 | J6: 2025-09-30 | K6: 2025-12-31 | L6: 2026-03-31 | M6: 2026-06-30 | N6: 2026-09-30 | O6: 2026-12-31 | P6: 2027-03-31 | Q6: 2027-06-30 | R6: 2027-09-30 | S6: 2027-12-31 | T6: 2028-03-31 | U6: 2028-06-30 | V6: 2028-09-30 | W6: 2028-12-31 | X6: 2029-03-31 | Y6: 2029-06-30 | Z6: 2029-09-30 | AA6: 2029-12-31 | AB6: 2030-03-31 | AC6: 2030-06-30 | AD6: 2030-09-30 | AE6: 2030-12-31 | AF6: 2031-03-31 | AG6: 2031-06-30 | AH6: 2031-09-30 | AI6: 2031-12-31 | AJ6: 2032-03-31 | AK6: 2032-06-30 | AL6: 2032-09-30 | AM6: 2032-12-31 | AN6: 2033-03-31 | AO6: 2033-06-30 | AP6: 2033-09-30 | AQ6: 2033-12-31 | AR6: 2034-03-31 | AS6: 2034-06-30 | AT6: 2034-09-30 | AU6: 2034-12-31 | AV6: 2035-03-31 | AW6: 2035-06-30 | AX6: 2035-09-30 | AY6: 2035-12-31 | AZ6: 2036-03-31 | BA6: 2036-06-30 | BB6: 2036-09-30 | BC6: 2036-12-31 | BD6: 2037-03-31 | BE6: 2037-06-30 | BF6: 2037-09-30 | BG6: 2037-12-31 | BH6: 2038-03-31 | BI6: 2038-06-30 | BJ6: 2038-09-30 | BK6: 2038-12-31 | BL6: 2039-03-31 | BM6: 2039-06-30 | BN6: 2039-09-30 | BO6: 2039-12-31 | BP6: 2040-03-31 | BQ6: 2040-06-30 | BR6: 2040-09-30 | BS6: 2040-12-31 | BT6: 2041-03-31 | BU6: 2041-06-30 | BV6: 2041-09-30 | BW6: 2041-12-31 | BX6: 2042-03-31 | BY6: 2042-06-30 | BZ6: 2042-09-30 | CA6: 2042-12-31 | CB6: 2043-03-31 | CC6: 2043-06-30 | CD6: 2043-09-30 | CE6: 2043-12-31 | CF6: 2044-03-31 | CG6: 2044-06-30 | CH6: 2044-09-30 | CI6: 2044-12-31 | CJ6: 2045-03-31 | CK6: 2045-06-30 | CL6: 2045-09-30
B8: 영업수익 | C8: [KRWm] | D8: =SUM(E8:CL8) | E8: ='Revenue'!E17 | F8: ='Revenue'!F17 | G8: ='Revenue'!G17 | H8: ='Revenue'!H17 | I8: ='Revenue'!I17 | J8: ='Revenue'!J17 | K8: ='Revenue'!K17 | L8: ='Revenue'!L17 | ... CL8: ='Revenue'!CL17
B10: 영업비용 세부내역
B11: 부지임대료 | C11: [KRWm]
B12: O&M | C12: [KRWm]
B13: 보험료 | C13: [KRWm]
B14: 환경모니터링비용 | C14: [KRWm]
B15: 소내전력비 | C15: [KRWm]
B16: 인건비 | C16: [KRWm]
B17: 법인운영비 | C17: [KRWm]
B18: 주민보상비 | C18: [KRWm]
B19: 도로점용료 | C19: [KRWm]
B20: 예비비 | C20: [KRWm]
B21: 전력거래수수료 | C21: [KRWm]
B22: 관리운영비 성과보수 | C22: [KRWm]
B23: 영업비용 합계 | C23: [KRWm] | D23: =SUM(E23:CL23) | E23: =-'Opex'!E24 | F23: =-'Opex'!F24 | G23: =-'Opex'!G24 | H23: =-'Opex'!H24 | I23: =-'Opex'!I24 | J23: =-'Opex'!J24 | K23: =-'Opex'!K24 | L23: =-'Opex'!L24 | ... CL23: =-'Opex'!CL24
B25: EBITDA | C25: [KRWm] | D25: =SUM(E25:CL25) | E25: =E8+E23 | F25: =F8+F23 | G25: =G8+G23 | H25: =H8+H23 | I25: =I8+I23 | J25: =J8+J23 | K25: =K8+K23 | L25: =L8+L23 | ... CL25: =CL8+CL23
B26: EBITDA 마진 | C26: [%] | E26: =IF(E8<=0,"",E25/E8) | F26: =IF(F8<=0,"",F25/F8) | G26: =IF(G8<=0,"",G25/G8) | H26: =IF(H8<=0,"",H25/H8) | I26: =IF(I8<=0,"",I25/I8) | J26: =IF(J8<=0,"",J25/J8) | K26: =IF(K8<=0,"",K25/K8) | L26: =IF(L8<=0,"",L25/L8) | ... CL26: =IF(CL8<=0,"",CL25/CL8)
B28: 감가상각비 | C28: [KRWm] | D28: =SUM(E28:CL28) | E28: 0 | F28: 0 | G28: 0 | H28: 0 | I28: 0 | J28: 0 | K28: =-(('Funding'!C18*$D$75/100)/$D$76*(3/12)) | L28: =-(('Funding'!C18*$D$75/100)/$D$76*(3/12)) | M28: =-(('Funding'!C18*$D$75/100)/$D$76*(3/12)) | N28: =-(('Funding'!C18*$D$75/100)/$D$76*(3/12)) | O28: =-(('Funding'!C18*$D$75/100)/$D$76*(3/12)) | P28: =-(('Funding'!C18*$D$75/100)/$D$76*(3/12)) | Q28: =-(('Funding'!C18*$D$75/100)/$D$76*(3/12)) | R28: =-(('Funding'!C18*$D$75/100)/$D$76*(3/12)) | S28: =-(('Funding'!C18*$D$75/100)/$D$76*(3/12)) | T28: =-(('Funding'!C18*$D$75/100)/$D$76*(3/12)) | U28: =-(('Funding'!C18*$D$75/100)/$D$76*(3/12)) | V28: =-(('Funding'!C18*$D$75/100)/$D$76*(3/12)) | W28: =-(('Funding'!C18*$D$75/100)/$D$76*(3/12)) | X28: =-(('Funding'!C18*$D$75/100)/$D$76*(3/12)) | Y28: =-(('Funding'!C18*$D$75/100)/$D$76*(3/12)) | Z28: =-(('Funding'!C18*$D$75/100)/$D$76*(3/12)) | AA28: =-(('Funding'!C18*$D$75/100)/$D$76*(3/12)) | AB28: =-(('Funding'!C18*$D$75/100)/$D$76*(3/12)) | AC28: =-(('Funding'!C18*$D$75/100)/$D$76*(3/12)) | AD28: =-(('Funding'!C18*$D$75/100)/$D$76*(3/12)) | AE28: =-(('Funding'!C18*$D$75/100)/$D$76*(3/12)) | AF28: =-(('Funding'!C18*$D$75/100)/$D$76*(3/12)) | AG28: =-(('Funding'!C18*$D$75/100)/$D$76*(3/12)) | AH28: =-(('Funding'!C18*$D$75/100)/$D$76*(3/12)) | AI28: =-(('Funding'!C18*$D$75/100)/$D$76*(3/12)) | AJ28: =-(('Funding'!C18*$D$75/100)/$D$76*(3/12)) | AK28: =-(('Funding'!C18*$D$75/100)/$D$76*(3/12)) | AL28: =-(('Funding'!C18*$D$75/100)/$D$76*(3/12)) | AM28: =-(('Funding'!C18*$D$75/100)/$D$76*(3/12)) | AN28: =-(('Funding'!C18*$D$75/100)/$D$76*(3/12)) | AO28: =-(('Funding'!C18*$D$75/100)/$D$76*(3/12)) | AP28: =-(('Funding'!C18*$D$75/100)/$D$76*(3/12)) | AQ28: =-(('Funding'!C18*$D$75/100)/$D$76*(3/12)) | AR28: =-(('Funding'!C18*$D$75/100)/$D$76*(3/12)) | AS28: =-(('Funding'!C18*$D$75/100)/$D$76*(3/12)) | AT28: =-(('Funding'!C18*$D$75/100)/$D$76*(3/12)) | AU28: =-(('Funding'!C18*$D$75/100)/$D$76*(3/12)) | AV28: =-(('Funding'!C18*$D$75/100)/$D$76*(3/12)) | AW28: =-(('Funding'!C18*$D$75/100)/$D$76*(3/12)) | AX28: =-(('Funding'!C18*$D$75/100)/$D$76*(3/12)) | AY28: =-(('Funding'!C18*$D$75/100)/$D$76*(3/12)) | AZ28: =-(('Funding'!C18*$D$75/100)/$D$76*(3/12)) | BA28: =-(('Funding'!C18*$D$75/100)/$D$76*(3/12)) | BB28: =-(('Funding'!C18*$D$75/100)/$D$76*(3/12)) | BC28: =-(('Funding'!C18*$D$75/100)/$D$76*(3/12)) | BD28: =-(('Funding'!C18*$D$75/100)/$D$76*(3/12)) | BE28: =-(('Funding'!C18*$D$75/100)/$D$76*(3/12)) | BF28: =-(('Funding'!C18*$D$75/100)/$D$76*(3/12)) | BG28: =-(('Funding'!C18*$D$75/100)/$D$76*(3/12)) | BH28: =-(('Funding'!C18*$D$75/100)/$D$76*(3/12)) | BI28: =-(('Funding'!C18*$D$75/100)/$D$76*(3/12)) | BJ28: =-(('Funding'!C18*$D$75/100)/$D$76*(3/12)) | BK28: =-(('Funding'!C18*$D$75/100)/$D$76*(3/12)) | BL28: =-(('Funding'!C18*$D$75/100)/$D$76*(3/12)) | BM28: =-(('Funding'!C18*$D$75/100)/$D$76*(3/12)) | BN28: =-(('Funding'!C18*$D$75/100)/$D$76*(3/12)) | BO28: =-(('Funding'!C18*$D$75/100)/$D$76*(3/12)) | BP28: =-(('Funding'!C18*$D$75/100)/$D$76*(3/12)) | BQ28: =-(('Funding'!C18*$D$75/100)/$D$76*(3/12)) | BR28: =-(('Funding'!C18*$D$75/100)/$D$76*(3/12)) | BS28: =-(('Funding'!C18*$D$75/100)/$D$76*(3/12)) | BT28: =-(('Funding'!C18*$D$75/100)/$D$76*(3/12)) | BU28: =-(('Funding'!C18*$D$75/100)/$D$76*(3/12)) | BV28: =-(('Funding'!C18*$D$75/100)/$D$76*(3/12)) | BW28: =-(('Funding'!C18*$D$75/100)/$D$76*(3/12)) | BX28: =-(('Funding'!C18*$D$75/100)/$D$76*(3/12)) | BY28: =-(('Funding'!C18*$D$75/100)/$D$76*(3/12)) | BZ28: =-(('Funding'!C18*$D$75/100)/$D$76*(3/12)) | CA28: =-(('Funding'!C18*$D$75/100)/$D$76*(3/12)) | CB28: =-(('Funding'!C18*$D$75/100)/$D$76*(3/12)) | CC28: =-(('Funding'!C18*$D$75/100)/$D$76*(3/12)) | CD28: =-(('Funding'!C18*$D$75/100)/$D$76*(3/12)) | CE28: =-(('Funding'!C18*$D$75/100)/$D$76*(3/12)) | CF28: =-(('Funding'!C18*$D$75/100)/$D$76*(3/12)) | CG28: =-(('Funding'!C18*$D$75/100)/$D$76*(3/12)) | CH28: =-(('Funding'!C18*$D$75/100)/$D$76*(3/12)) | CI28: =-(('Funding'!C18*$D$75/100)/$D$76*(3/12)) | CJ28: =-(('Funding'!C18*$D$75/100)/$D$76*(3/12)) | CK28: =-(('Funding'!C18*$D$75/100)/$D$76*(3/12)) | CL28: =-(('Funding'!C18*$D$75/100)/$D$76*(3/12))
B29: 복구충당부채 전입액 | C29: [KRWm] | D29: =SUM(E29:CL29) | E29: 0 | F29: 0 | G29: 0 | H29: 0 | I29: 0 | J29: 0 | K29: =-($D$77*100/80) | L29: =-($D$77*100/80) | M29: =-($D$77*100/80) | N29: =-($D$77*100/80) | O29: =-($D$77*100/80) | P29: =-($D$77*100/80) | Q29: =-($D$77*100/80) | R29: =-($D$77*100/80) | ... CL29: =-($D$77*100/80)
B30: 기타 비현금 세무손금 | C30: [KRWm] | D30: =SUM(E30:CL30) | E30: 0 | F30: 0 | G30: 0 | H30: 0 | I30: 0 | J30: 0 | K30: =-($D$79/80) | L30: =-($D$79/80) | M30: =-($D$79/80) | N30: =-($D$79/80) | O30: =-($D$79/80) | P30: =-($D$79/80) | Q30: =-($D$79/80) | R30: =-($D$79/80) | ... CL30: =-($D$79/80)
B31: 대리은행수수료 | C31: [KRWm] | D31: =SUM(E31:CL31) | E31: 0 | F31: 0 | G31: 0 | H31: 0 | I31: 0 | J31: 0 | K31: =-($D$78/80) | L31: =-($D$78/80) | M31: =-($D$78/80) | N31: =-($D$78/80) | O31: =-($D$78/80) | P31: =-($D$78/80) | Q31: =-($D$78/80) | R31: =-($D$78/80) | ... CL31: =-($D$78/80)
B32: 영업이익(EBIT) | C32: [KRWm] | D32: =SUM(E32:CL32) | E32: =E25+E28+E29+E30+E31 | F32: =F25+F28+F29+F30+F31 | G32: =G25+G28+G29+G30+G31 | H32: =H25+H28+H29+H30+H31 | I32: =I25+I28+I29+I30+I31 | J32: =J25+J28+J29+J30+J31 | K32: =K25+K28+K29+K30+K31 | L32: =L25+L28+L29+L30+L31 | ... CL32: =CL25+CL28+CL29+CL30+CL31
B33: 영업이익률 | C33: [%] | E33: =IF(E8<=0,"",E32/E8) | F33: =IF(F8<=0,"",F32/F8) | G33: =IF(G8<=0,"",G32/G8) | H33: =IF(H8<=0,"",H32/H8) | I33: =IF(I8<=0,"",I32/I8) | J33: =IF(J8<=0,"",J32/J8) | K33: =IF(K8<=0,"",K32/K8) | L33: =IF(L8<=0,"",L32/L8) | ... CL33: =IF(CL8<=0,"",CL32/CL8)
B35: 이자비용 세부내역
B36: 선순위A 이자 | C36: [KRWm] | D36: =SUM(E36:CL36) | E36: =-'Debt'!E33 | F36: =-'Debt'!F33 | G36: =-'Debt'!G33 | H36: =-'Debt'!H33 | I36: =-'Debt'!I33 | J36: =-'Debt'!J33 | K36: =-'Debt'!K33 | L36: =-'Debt'!L33 | ... CL36: =-'Debt'!CL33
B37: 선순위B 이자 | C37: [KRWm] | D37: =SUM(E37:CL37) | E37: =-'Debt'!E42 | F37: =-'Debt'!F42 | G37: =-'Debt'!G42 | H37: =-'Debt'!H42 | I37: =-'Debt'!I42 | J37: =-'Debt'!J42 | K37: =-'Debt'!K42 | L37: =-'Debt'!L42 | ... CL37: =-'Debt'!CL42
B38: 선순위C 이자 | C38: [KRWm] | D38: =SUM(E38:CL38) | E38: =-'Debt'!E51 | F38: =-'Debt'!F51 | G38: =-'Debt'!G51 | H38: =-'Debt'!H51 | I38: =-'Debt'!I51 | J38: =-'Debt'!J51 | K38: =-'Debt'!K51 | L38: =-'Debt'!L51 | ... CL38: =-'Debt'!CL51
B39: 선순위D 이자 | C39: [KRWm] | D39: =SUM(E39:CL39) | E39: =-'Debt'!E61 | F39: =-'Debt'!F61 | G39: =-'Debt'!G61 | H39: =-'Debt'!H61 | I39: =-'Debt'!I61 | J39: =-'Debt'!J61 | K39: =-'Debt'!K61 | L39: =-'Debt'!L61 | ... CL39: =-'Debt'!CL61
B40: 후순위 이자 | C40: [KRWm] | D40: =SUM(E40:CL40) | E40: =-'Debt'!E70 | F40: =-'Debt'!F70 | G40: =-'Debt'!G70 | H40: =-'Debt'!H70 | I40: =-'Debt'!I70 | J40: =-'Debt'!J70 | K40: =-'Debt'!K70 | L40: =-'Debt'!L70 | ... CL40: =-'Debt'!CL70
B41: 이자비용 합계 | C41: [KRWm] | D41: =SUM(E41:CL41) | E41: =E36+E37+E38+E39+E40 | F41: =F36+F37+F38+F39+F40 | G41: =G36+G37+G38+G39+G40 | H41: =H36+H37+H38+H39+H40 | I41: =I36+I37+I38+I39+I40 | J41: =J36+J37+J38+J39+J40 | K41: =K36+K37+K38+K39+K40 | L41: =L36+L37+L38+L39+L40 | ... CL41: =CL36+CL37+CL38+CL39+CL40
B43: 법인세차감전순이익 | C43: [KRWm] | D43: =SUM(E43:CL43) | E43: =E32+E41 | F43: =F32+F41 | G43: =G32+G41 | H43: =H32+H41 | I43: =I32+I41 | J43: =J32+J41 | K43: =K32+K41 | L43: =L32+L41 | ... CL43: =CL32+CL41
B44: 법인세비용 | C44: [KRWm] | D44: =SUM(E44:CL44) | E44: =IF(AND(E43>0,E67>0),-E66*E43/E67,0) | F44: =IF(AND(F43>0,E67>0),-E66*F43/E67,0) | G44: =IF(AND(G43>0,E67>0),-E66*G43/E67,0) | H44: =IF(AND(H43>0,F67>0),-F66*H43/F67,0) | I44: =IF(AND(I43>0,F67>0),-F66*I43/F67,0) | J44: =IF(AND(J43>0,F67>0),-F66*J43/F67,0) | K44: =IF(AND(K43>0,F67>0),-F66*K43/F67,0) | L44: =IF(AND(L43>0,G67>0),-G66*L43/G67,0) | M44: =IF(AND(M43>0,G67>0),-G66*M43/G67,0) | N44: =IF(AND(N43>0,G67>0),-G66*N43/G67,0) | O44: =IF(AND(O43>0,G67>0),-G66*O43/G67,0) | P44: =IF(AND(P43>0,H67>0),-H66*P43/H67,0) | Q44: =IF(AND(Q43>0,H67>0),-H66*Q43/H67,0) | R44: =IF(AND(R43>0,H67>0),-H66*R43/H67,0) | S44: =IF(AND(S43>0,H67>0),-H66*S43/H67,0) | T44: =IF(AND(T43>0,I67>0),-I66*T43/I67,0) | U44: =IF(AND(U43>0,I67>0),-I66*U43/I67,0) | V44: =IF(AND(V43>0,I67>0),-I66*V43/I67,0) | W44: =IF(AND(W43>0,I67>0),-I66*W43/I67,0) | X44: =IF(AND(X43>0,J67>0),-J66*X43/J67,0) | Y44: =IF(AND(Y43>0,J67>0),-J66*Y43/J67,0) | Z44: =IF(AND(Z43>0,J67>0),-J66*Z43/J67,0) | AA44: =IF(AND(AA43>0,J67>0),-J66*AA43/J67,0) | AB44: =IF(AND(AB43>0,K67>0),-K66*AB43/K67,0) | AC44: =IF(AND(AC43>0,K67>0),-K66*AC43/K67,0) | AD44: =IF(AND(AD43>0,K67>0),-K66*AD43/K67,0) | AE44: =IF(AND(AE43>0,K67>0),-K66*AE43/K67,0) | AF44: =IF(AND(AF43>0,L67>0),-L66*AF43/L67,0) | AG44: =IF(AND(AG43>0,L67>0),-L66*AG43/L67,0) | AH44: =IF(AND(AH43>0,L67>0),-L66*AH43/L67,0) | AI44: =IF(AND(AI43>0,L67>0),-L66*AI43/L67,0) | AJ44: =IF(AND(AJ43>0,M67>0),-M66*AJ43/M67,0) | AK44: =IF(AND(AK43>0,M67>0),-M66*AK43/M67,0) | AL44: =IF(AND(AL43>0,M67>0),-M66*AL43/M67,0) | AM44: =IF(AND(AM43>0,M67>0),-M66*AM43/M67,0) | AN44: =IF(AND(AN43>0,N67>0),-N66*AN43/N67,0) | AO44: =IF(AND(AO43>0,N67>0),-N66*AO43/N67,0) | AP44: =IF(AND(AP43>0,N67>0),-N66*AP43/N67,0) | AQ44: =IF(AND(AQ43>0,N67>0),-N66*AQ43/N67,0) | AR44: =IF(AND(AR43>0,O67>0),-O66*AR43/O67,0) | AS44: =IF(AND(AS43>0,O67>0),-O66*AS43/O67,0) | AT44: =IF(AND(AT43>0,O67>0),-O66*AT43/O67,0) | AU44: =IF(AND(AU43>0,O67>0),-O66*AU43/O67,0) | AV44: =IF(AND(AV43>0,P67>0),-P66*AV43/P67,0) | AW44: =IF(AND(AW43>0,P67>0),-P66*AW43/P67,0) | AX44: =IF(AND(AX43>0,P67>0),-P66*AX43/P67,0) | AY44: =IF(AND(AY43>0,P67>0),-P66*AY43/P67,0) | AZ44: =IF(AND(AZ43>0,Q67>0),-Q66*AZ43/Q67,0) | BA44: =IF(AND(BA43>0,Q67>0),-Q66*BA43/Q67,0) | BB44: =IF(AND(BB43>0,Q67>0),-Q66*BB43/Q67,0) | BC44: =IF(AND(BC43>0,Q67>0),-Q66*BC43/Q67,0) | BD44: =IF(AND(BD43>0,R67>0),-R66*BD43/R67,0) | BE44: =IF(AND(BE43>0,R67>0),-R66*BE43/R67,0) | BF44: =IF(AND(BF43>0,R67>0),-R66*BF43/R67,0) | BG44: =IF(AND(BG43>0,R67>0),-R66*BG43/R67,0) | BH44: =IF(AND(BH43>0,S67>0),-S66*BH43/S67,0) | BI44: =IF(AND(BI43>0,S67>0),-S66*BI43/S67,0) | BJ44: =IF(AND(BJ43>0,S67>0),-S66*BJ43/S67,0) | BK44: =IF(AND(BK43>0,S67>0),-S66*BK43/S67,0) | BL44: =IF(AND(BL43>0,T67>0),-T66*BL43/T67,0) | BM44: =IF(AND(BM43>0,T67>0),-T66*BM43/T67,0) | BN44: =IF(AND(BN43>0,T67>0),-T66*BN43/T67,0) | BO44: =IF(AND(BO43>0,T67>0),-T66*BO43/T67,0) | BP44: =IF(AND(BP43>0,U67>0),-U66*BP43/U67,0) | BQ44: =IF(AND(BQ43>0,U67>0),-U66*BQ43/U67,0) | BR44: =IF(AND(BR43>0,U67>0),-U66*BR43/U67,0) | BS44: =IF(AND(BS43>0,U67>0),-U66*BS43/U67,0) | BT44: =IF(AND(BT43>0,V67>0),-V66*BT43/V67,0) | BU44: =IF(AND(BU43>0,V67>0),-V66*BU43/V67,0) | BV44: =IF(AND(BV43>0,V67>0),-V66*BV43/V67,0) | BW44: =IF(AND(BW43>0,V67>0),-V66*BW43/V67,0) | BX44: =IF(AND(BX43>0,W67>0),-W66*BX43/W67,0) | BY44: =IF(AND(BY43>0,W67>0),-W66*BY43/W67,0) | BZ44: =IF(AND(BZ43>0,W67>0),-W66*BZ43/W67,0) | CA44: =IF(AND(CA43>0,W67>0),-W66*CA43/W67,0) | CB44: =IF(AND(CB43>0,X67>0),-X66*CB43/X67,0) | CC44: =IF(AND(CC43>0,X67>0),-X66*CC43/X67,0) | CD44: =IF(AND(CD43>0,X67>0),-X66*CD43/X67,0) | CE44: =IF(AND(CE43>0,X67>0),-X66*CE43/X67,0) | CF44: =IF(AND(CF43>0,Y67>0),-Y66*CF43/Y67,0) | CG44: =IF(AND(CG43>0,Y67>0),-Y66*CG43/Y67,0) | CH44: =IF(AND(CH43>0,Y67>0),-Y66*CH43/Y67,0) | CI44: =IF(AND(CI43>0,Y67>0),-Y66*CI43/Y67,0) | CJ44: =IF(AND(CJ43>0,Z67>0),-Z66*CJ43/Z67,0) | CK44: =IF(AND(CK43>0,Z67>0),-Z66*CK43/Z67,0) | CL44: =IF(AND(CL43>0,Z67>0),-Z66*CL43/Z67,0)
B45: 당기순이익 | C45: [KRWm] | D45: =SUM(E45:CL45) | E45: =E43+E44 | F45: =F43+F44 | G45: =G43+G44 | H45: =H43+H44 | I45: =I43+I44 | J45: =J43+J44 | K45: =K43+K44 | L45: =L43+L44 | ... CL45: =CL43+CL44
B48: 연도별 법인세 산출
B50: 세무상 과세표준(분기, 연간집계용) | C50: [KRWm] | D50: =SUM(E50:CL50) | E50: =E43-E29-(0) | F50: =F43-F29-(0) | G50: =G43-G29-(0) | H50: =H43-H29-(0) | I50: =I43-I29-(0) | J50: =J43-J29-(0) | K50: =K43-K29-(0) | L50: =L43-L29-(0) | ... CK50: =CK43-CK29-(0) | CL50: =CL43-CL29-($D$77*100)
B52: 연도 | E52: 2024 | F52: 2025 | G52: 2026 | H52: 2027 | I52: 2028 | J52: 2029 | K52: 2030 | L52: 2031 | M52: 2032 | N52: 2033 | O52: 2034 | P52: 2035 | Q52: 2036 | R52: 2037 | S52: 2038 | T52: 2039 | U52: 2040 | V52: 2041 | W52: 2042 | X52: 2043 | Y52: 2044 | Z52: 2045
B53: 과세표준(연간, 손실이월 전) | C53: [KRWm] | E53: =E50+F50+G50 | F53: =H50+I50+J50+K50 | G53: =L50+M50+N50+O50 | H53: =P50+Q50+R50+S50 | I53: =T50+U50+V50+W50 | J53: =X50+Y50+Z50+AA50 | K53: =AB50+AC50+AD50+AE50 | L53: =AF50+AG50+AH50+AI50 | M53: =AJ50+AK50+AL50+AM50 | N53: =AN50+AO50+AP50+AQ50 | O53: =AR50+AS50+AT50+AU50 | P53: =AV50+AW50+AX50+AY50 | Q53: =AZ50+BA50+BB50+BC50 | R53: =BD50+BE50+BF50+BG50 | S53: =BH50+BI50+BJ50+BK50 | T53: =BL50+BM50+BN50+BO50 | U53: =BP50+BQ50+BR50+BS50 | V53: =BT50+BU50+BV50+BW50 | W53: =BX50+BY50+BZ50+CA50 | X53: =CB50+CC50+CD50+CE50 | Y53: =CF50+CG50+CH50+CI50 | Z53: =CJ50+CK50+CL50
B54: 직전 이월결손금(기초) | C54: [KRWm] | E54: =0 | F54: =E56 | G54: =F56 | H54: =G56 | I54: =H56 | J54: =I56 | K54: =J56 | L54: =K56 | M54: =L56 | ... Z54: =Y56
B55: 당해 결손금 공제액 | C55: [KRWm] | E55: =IF(E53<=0,0,MIN(E54,E53*$D$80/100)) | F55: =IF(F53<=0,0,MIN(F54,F53*$D$80/100)) | G55: =IF(G53<=0,0,MIN(G54,G53*$D$80/100)) | H55: =IF(H53<=0,0,MIN(H54,H53*$D$80/100)) | I55: =IF(I53<=0,0,MIN(I54,I53*$D$80/100)) | J55: =IF(J53<=0,0,MIN(J54,J53*$D$80/100)) | K55: =IF(K53<=0,0,MIN(K54,K53*$D$80/100)) | L55: =IF(L53<=0,0,MIN(L54,L53*$D$80/100)) | ... Z55: =IF(Z53<=0,0,MIN(Z54,Z53*$D$80/100))
B56: 이월결손금(기말) | C56: [KRWm] | E56: =IF(E53<=0,E54-E53,E54-E55) | F56: =IF(F53<=0,F54-F53,F54-F55) | G56: =IF(G53<=0,G54-G53,G54-G55) | H56: =IF(H53<=0,H54-H53,H54-H55) | I56: =IF(I53<=0,I54-I53,I54-I55) | J56: =IF(J53<=0,J54-J53,J54-J55) | K56: =IF(K53<=0,K54-K53,K54-K55) | L56: =IF(L53<=0,L54-L53,L54-L55) | ... Z56: =IF(Z53<=0,Z54-Z53,Z54-Z55)
B57: 과세표준(공제후) | C57: [KRWm] | E57: =MAX(0,E53-E55) | F57: =MAX(0,F53-F55) | G57: =MAX(0,G53-G55) | H57: =MAX(0,H53-H55) | I57: =MAX(0,I53-I55) | J57: =MAX(0,J53-J55) | K57: =MAX(0,K53-K55) | L57: =MAX(0,L53-L55) | ... Z57: =MAX(0,Z53-Z55)
B58: 산출세액 | C58: [KRWm] | E58: =IF(E53<=0,0,MIN(MAX(E57,0),200)*0.09+MIN(MAX(E57-200,0),19800)*0.19+MIN(MAX(E57-20000,0),280000)*0.21+MAX(E57-300000,0)*0.24) | F58: =IF(F53<=0,0,MIN(MAX(F57,0),200)*0.09+MIN(MAX(F57-200,0),19800)*0.19+MIN(MAX(F57-20000,0),280000)*0.21+MAX(F57-300000,0)*0.24) | G58: =IF(G53<=0,0,MIN(MAX(G57,0),200)*0.09+MIN(MAX(G57-200,0),19800)*0.19+MIN(MAX(G57-20000,0),280000)*0.21+MAX(G57-300000,0)*0.24) | H58: =IF(H53<=0,0,MIN(MAX(H57,0),200)*0.09+MIN(MAX(H57-200,0),19800)*0.19+MIN(MAX(H57-20000,0),280000)*0.21+MAX(H57-300000,0)*0.24) | I58: =IF(I53<=0,0,MIN(MAX(I57,0),200)*0.09+MIN(MAX(I57-200,0),19800)*0.19+MIN(MAX(I57-20000,0),280000)*0.21+MAX(I57-300000,0)*0.24) | J58: =IF(J53<=0,0,MIN(MAX(J57,0),200)*0.09+MIN(MAX(J57-200,0),19800)*0.19+MIN(MAX(J57-20000,0),280000)*0.21+MAX(J57-300000,0)*0.24) | K58: =IF(K53<=0,0,MIN(MAX(K57,0),200)*0.09+MIN(MAX(K57-200,0),19800)*0.19+MIN(MAX(K57-20000,0),280000)*0.21+MAX(K57-300000,0)*0.24) | L58: =IF(L53<=0,0,MIN(MAX(L57,0),200)*0.09+MIN(MAX(L57-200,0),19800)*0.19+MIN(MAX(L57-20000,0),280000)*0.21+MAX(L57-300000,0)*0.24) | ... Z58: =IF(Z53<=0,0,MIN(MAX(Z57,0),200)*0.09+MIN(MAX(Z57-200,0),19800)*0.19+MIN(MAX(Z57-20000,0),280000)*0.21+MAX(Z57-300000,0)*0.24)
B59: 최저한세 | C59: [KRWm] | E59: =E57*$D$81/100 | F59: =F57*$D$81/100 | G59: =G57*$D$81/100 | H59: =H57*$D$81/100 | I59: =I57*$D$81/100 | J59: =J57*$D$81/100 | K59: =K57*$D$81/100 | L59: =L57*$D$81/100 | ... Z59: =Z57*$D$81/100
B60: 직전 세액공제 잔액(기초) | C60: [KRWm] | E60: =0 | F60: =E65 | G60: =F65 | H60: =G65 | I60: =H65 | J60: =I65 | K60: =J65 | L60: =K65 | M60: =L65 | ... Z60: =Y65
B61: 당해 신규 세액공제 | C61: [KRWm] | E61: =(0)*$D$82/100 | F61: =(0)*$D$82/100 | G61: =(0)*$D$82/100 | H61: =(0)*$D$82/100 | I61: =(0)*$D$82/100 | J61: =(0)*$D$82/100 | K61: =(0)*$D$82/100 | L61: =(0)*$D$82/100 | ... Z61: =(0)*$D$82/100
B62: 공제후 세액 | C62: [KRWm] | E62: =MAX(0,E58-(E60+E61)) | F62: =MAX(0,F58-(F60+F61)) | G62: =MAX(0,G58-(G60+G61)) | H62: =MAX(0,H58-(H60+H61)) | I62: =MAX(0,I58-(I60+I61)) | J62: =MAX(0,J58-(J60+J61)) | K62: =MAX(0,K58-(K60+K61)) | L62: =MAX(0,L58-(L60+L61)) | ... Z62: =MAX(0,Z58-(Z60+Z61))
B63: 최종 산출세액(MAX) | C63: [KRWm] | E63: =IF(E53<=0,0,MAX(E59,E62)) | F63: =IF(F53<=0,0,MAX(F59,F62)) | G63: =IF(G53<=0,0,MAX(G59,G62)) | H63: =IF(H53<=0,0,MAX(H59,H62)) | I63: =IF(I53<=0,0,MAX(I59,I62)) | J63: =IF(J53<=0,0,MAX(J59,J62)) | K63: =IF(K53<=0,0,MAX(K59,K62)) | L63: =IF(L53<=0,0,MAX(L59,L62)) | ... Z63: =IF(Z53<=0,0,MAX(Z59,Z62))
B64: 세액공제 사용액 | C64: [KRWm] | E64: =E58-E63 | F64: =F58-F63 | G64: =G58-G63 | H64: =H58-H63 | I64: =I58-I63 | J64: =J58-J63 | K64: =K58-K63 | L64: =L58-L63 | ... Z64: =Z58-Z63
B65: 세액공제 잔액(기말) | C65: [KRWm] | E65: =E60+E61-E64 | F65: =F60+F61-F64 | G65: =G60+G61-G64 | H65: =H60+H61-H64 | I65: =I60+I61-I64 | J65: =J60+J61-J64 | K65: =K60+K61-K64 | L65: =L60+L61-L64 | ... Z65: =Z60+Z61-Z64
B66: 법인세비용(연간) | C66: [KRWm] | E66: =E63*(1+$D$83/100)+E64*$D$84/100 | F66: =F63*(1+$D$83/100)+F64*$D$84/100 | G66: =G63*(1+$D$83/100)+G64*$D$84/100 | H66: =H63*(1+$D$83/100)+H64*$D$84/100 | I66: =I63*(1+$D$83/100)+I64*$D$84/100 | J66: =J63*(1+$D$83/100)+J64*$D$84/100 | K66: =K63*(1+$D$83/100)+K64*$D$84/100 | L66: =L63*(1+$D$83/100)+L64*$D$84/100 | ... Z66: =Z63*(1+$D$83/100)+Z64*$D$84/100
B67: 양수 EBT 합(연간, 분기배분용) | C67: [KRWm] | E67: =MAX(0,E43)+MAX(0,F43)+MAX(0,G43) | F67: =MAX(0,H43)+MAX(0,I43)+MAX(0,J43)+MAX(0,K43) | G67: =MAX(0,L43)+MAX(0,M43)+MAX(0,N43)+MAX(0,O43) | H67: =MAX(0,P43)+MAX(0,Q43)+MAX(0,R43)+MAX(0,S43) | I67: =MAX(0,T43)+MAX(0,U43)+MAX(0,V43)+MAX(0,W43) | J67: =MAX(0,X43)+MAX(0,Y43)+MAX(0,Z43)+MAX(0,AA43) | K67: =MAX(0,AB43)+MAX(0,AC43)+MAX(0,AD43)+MAX(0,AE43) | L67: =MAX(0,AF43)+MAX(0,AG43)+MAX(0,AH43)+MAX(0,AI43) | M67: =MAX(0,AJ43)+MAX(0,AK43)+MAX(0,AL43)+MAX(0,AM43) | N67: =MAX(0,AN43)+MAX(0,AO43)+MAX(0,AP43)+MAX(0,AQ43) | O67: =MAX(0,AR43)+MAX(0,AS43)+MAX(0,AT43)+MAX(0,AU43) | P67: =MAX(0,AV43)+MAX(0,AW43)+MAX(0,AX43)+MAX(0,AY43) | Q67: =MAX(0,AZ43)+MAX(0,BA43)+MAX(0,BB43)+MAX(0,BC43) | R67: =MAX(0,BD43)+MAX(0,BE43)+MAX(0,BF43)+MAX(0,BG43) | S67: =MAX(0,BH43)+MAX(0,BI43)+MAX(0,BJ43)+MAX(0,BK43) | T67: =MAX(0,BL43)+MAX(0,BM43)+MAX(0,BN43)+MAX(0,BO43) | U67: =MAX(0,BP43)+MAX(0,BQ43)+MAX(0,BR43)+MAX(0,BS43) | V67: =MAX(0,BT43)+MAX(0,BU43)+MAX(0,BV43)+MAX(0,BW43) | W67: =MAX(0,BX43)+MAX(0,BY43)+MAX(0,BZ43)+MAX(0,CA43) | X67: =MAX(0,CB43)+MAX(0,CC43)+MAX(0,CD43)+MAX(0,CE43) | Y67: =MAX(0,CF43)+MAX(0,CG43)+MAX(0,CH43)+MAX(0,CI43) | Z67: =MAX(0,CJ43)+MAX(0,CK43)+MAX(0,CL43)
B69: ※ 이월결손금(공제한도 이내)·세액공제(10년 이월, 통합투자세액공제)·최저한세(MAX)를 원본과 같은 순서로 연도 단위 수식 체인으로 계산합니다(반복계산 아님 — Debt 시트의 "기초잔액=직전 기말잔액"과 같은 방식). 분기별 법인세비용은 이 표의 연간 법인세를 그 분기 양수EBT 비중으로 비례배분합니다.
B70: ※ 화면에서 운영비를 합계로만 입력해서 항목별 금액은 비어 있습니다 — 항목별로 입력하면 이 표에 실제 금액이 채워집니다.
B73: 가정 (입력값 연결) — 이 시트의 계산이 쓰는 원천값 | D73: 값
B74: ※ 입력값 시트는 여기서만 참조합니다(초록 글자 = 입력값 연결). 위의 분기 계산은 이 셀들만 참조하므로, 값을 바꾸려면 입력값 시트를 고치세요.
B75: 상각대상 비율(TIC 대비)[%] | C75: C15 | D75: ='입력값'!C15
B76: 감가상각 내용연수[yr] | C76: C16 | D76: ='입력값'!C16
B77: 철거비(복구충당부채)[억원] | C77: C17 | D77: ='입력값'!C17
B78: 대리은행수수료(총액)[KRWm] | C78: C21 | D78: ='입력값'!C21
B79: 기타 비현금 세무손금(총액)[KRWm] | C79: C22 | D79: ='입력값'!C22
B80: 이월결손금 공제한도[%] | C80: C32 | D80: ='입력값'!C32
B81: 최저한세율[%] | C81: C33 | D81: ='입력값'!C33
B82: 통합투자세액공제율[%] | C82: C34 | D82: ='입력값'!C34
B83: 지방소득세율(법인세 대비)[%] | C83: C35 | D83: ='입력값'!C35
B84: 세액공제 농특세율[%] | C84: C36 | D84: ='입력값'!C36

Sheet CF(Q)
A1: 태양광 발전사업
A2: 추정 현금흐름표 (분기) · DSCR · 배당
B4: 영업/재무 현금흐름
B6: 구 분 | C6: unit | D6: 합 계 | E6: 2024-06-30 | F6: 2024-09-30 | G6: 2024-12-31 | H6: 2025-03-31 | I6: 2025-06-30 | J6: 2025-09-30 | K6: 2025-12-31 | L6: 2026-03-31 | M6: 2026-06-30 | N6: 2026-09-30 | O6: 2026-12-31 | P6: 2027-03-31 | Q6: 2027-06-30 | R6: 2027-09-30 | S6: 2027-12-31 | T6: 2028-03-31 | U6: 2028-06-30 | V6: 2028-09-30 | W6: 2028-12-31 | X6: 2029-03-31 | Y6: 2029-06-30 | Z6: 2029-09-30 | AA6: 2029-12-31 | AB6: 2030-03-31 | AC6: 2030-06-30 | AD6: 2030-09-30 | AE6: 2030-12-31 | AF6: 2031-03-31 | AG6: 2031-06-30 | AH6: 2031-09-30 | AI6: 2031-12-31 | AJ6: 2032-03-31 | AK6: 2032-06-30 | AL6: 2032-09-30 | AM6: 2032-12-31 | AN6: 2033-03-31 | AO6: 2033-06-30 | AP6: 2033-09-30 | AQ6: 2033-12-31 | AR6: 2034-03-31 | AS6: 2034-06-30 | AT6: 2034-09-30 | AU6: 2034-12-31 | AV6: 2035-03-31 | AW6: 2035-06-30 | AX6: 2035-09-30 | AY6: 2035-12-31 | AZ6: 2036-03-31 | BA6: 2036-06-30 | BB6: 2036-09-30 | BC6: 2036-12-31 | BD6: 2037-03-31 | BE6: 2037-06-30 | BF6: 2037-09-30 | BG6: 2037-12-31 | BH6: 2038-03-31 | BI6: 2038-06-30 | BJ6: 2038-09-30 | BK6: 2038-12-31 | BL6: 2039-03-31 | BM6: 2039-06-30 | BN6: 2039-09-30 | BO6: 2039-12-31 | BP6: 2040-03-31 | BQ6: 2040-06-30 | BR6: 2040-09-30 | BS6: 2040-12-31 | BT6: 2041-03-31 | BU6: 2041-06-30 | BV6: 2041-09-30 | BW6: 2041-12-31 | BX6: 2042-03-31 | BY6: 2042-06-30 | BZ6: 2042-09-30 | CA6: 2042-12-31 | CB6: 2043-03-31 | CC6: 2043-06-30 | CD6: 2043-09-30 | CE6: 2043-12-31 | CF6: 2044-03-31 | CG6: 2044-06-30 | CH6: 2044-09-30 | CI6: 2044-12-31 | CJ6: 2045-03-31 | CK6: 2045-06-30 | CL6: 2045-09-30
B9: CFADS (원리금상환재원) | C9: [KRWm] | D9: =SUM(E9:CL9) | E9: ='Revenue'!E17-'Opex'!E22+'IS(Q)'!E44+'IS(Q)'!E31+'Revenue'!E22 | F9: ='Revenue'!F17-'Opex'!F22+'IS(Q)'!F44+'IS(Q)'!F31+'Revenue'!F22 | G9: ='Revenue'!G17-'Opex'!G22+'IS(Q)'!G44+'IS(Q)'!G31+'Revenue'!G22 | H9: ='Revenue'!H17-'Opex'!H22+'IS(Q)'!H44+'IS(Q)'!H31+'Revenue'!H22 | I9: ='Revenue'!I17-'Opex'!I22+'IS(Q)'!I44+'IS(Q)'!I31+'Revenue'!I22 | J9: ='Revenue'!J17-'Opex'!J22+'IS(Q)'!J44+'IS(Q)'!J31+'Revenue'!J22 | K9: ='Revenue'!K17-'Opex'!K22+'IS(Q)'!K44+'IS(Q)'!K31+'Revenue'!K22 | L9: ='Revenue'!L17-'Opex'!L22+'IS(Q)'!L44+'IS(Q)'!L31+'Revenue'!L22 | ... CL9: ='Revenue'!CL17-'Opex'!CL22+'IS(Q)'!CL44+'IS(Q)'!CL31+'Revenue'!CL22
B10: 원리금(DS) | C10: [KRWm] | D10: =SUM(E10:CL10) | E10: ='Debt'!E79 | F10: ='Debt'!F79 | G10: ='Debt'!G79 | H10: ='Debt'!H79 | I10: ='Debt'!I79 | J10: ='Debt'!J79 | K10: ='Debt'!K79 | L10: ='Debt'!L79 | ... CL10: ='Debt'!CL79
B11: 단순 DSCR | C11: [x] | K11: =K9/K10 | L11: =L9/L10 | M11: =M9/M10 | N11: =N9/N10 | O11: =O9/O10 | P11: =P9/P10 | Q11: =Q9/Q10 | R11: =R9/R10 | ... BY11: =BY9/BY10
B13: FCFE | C13: [KRWm] | D13: =SUM(E13:CL13) | E13: =E9-E10-E14-'Opex'!E23+E19 | F13: =F9-F10-F14-'Opex'!F23+F19 | G13: =G9-G10-G14-'Opex'!G23+G19 | H13: =H9-H10-H14-'Opex'!H23+H19 | I13: =I9-I10-I14-'Opex'!I23+I19 | J13: =J9-J10-J14-'Opex'!J23+J19 | K13: =K9-K10-K14-'Opex'!K23+K19 | L13: =L9-L10-L14-'Opex'!L23+L19 | ... CK13: =CK9-CK10-CK14-'Opex'!CK23+CK19 | CL13: =CL9-CL10-CL14-'Opex'!CL23-$D$73*100+CL19
B14: DSRA 증감 | C14: [KRWm] | D14: =SUM(E14:CL14) | E14: =E21-E20 | F14: =F21-F20 | G14: =G21-G20 | H14: =H21-H20 | I14: =I21-I20 | J14: =J21-J20 | K14: =K21-K20 | L14: =L21-L20 | ... CL14: =CL21-CL20
B15: 기초현금 | C15: [KRWm] | E15: =0 | F15: =E17 | G15: =F17 | H15: =G17 | I15: =H17 | J15: =I17 | K15: =J17 | L15: =K17 | M15: =L17 | ... CL15: =CK17
B16: 배당(연차+청산) | C16: [KRWm] | D16: =SUM(E16:CL16) | E16: =0 | F16: =0 | G16: =0 | H16: =0 | I16: =0 | J16: =0 | K16: =IF(AND(0>=($D$77-1),OR(ISBLANK(K11),K11>=$D$75),OR(ISBLANK(K48),K48>=$D$76)),MAX(0,K18-$D$74*100),0) | L16: =IF(AND(0>=($D$77-1),OR(ISBLANK(L11),L11>=$D$75),OR(ISBLANK(L48),L48>=$D$76)),MAX(0,L18-$D$74*100),0) | M16: =IF(AND(0>=($D$77-1),OR(ISBLANK(M11),M11>=$D$75),OR(ISBLANK(M48),M48>=$D$76)),MAX(0,M18-$D$74*100),0) | N16: =IF(AND(0>=($D$77-1),OR(ISBLANK(N11),N11>=$D$75),OR(ISBLANK(N48),N48>=$D$76)),MAX(0,N18-$D$74*100),0) | O16: =IF(AND(1>=($D$77-1),OR(ISBLANK(O11),O11>=$D$75),OR(ISBLANK(O48),O48>=$D$76)),MAX(0,O18-$D$74*100),0) | P16: =IF(AND(1>=($D$77-1),OR(ISBLANK(P11),P11>=$D$75),OR(ISBLANK(P48),P48>=$D$76)),MAX(0,P18-$D$74*100),0) | Q16: =IF(AND(1>=($D$77-1),OR(ISBLANK(Q11),Q11>=$D$75),OR(ISBLANK(Q48),Q48>=$D$76)),MAX(0,Q18-$D$74*100),0) | R16: =IF(AND(1>=($D$77-1),OR(ISBLANK(R11),R11>=$D$75),OR(ISBLANK(R48),R48>=$D$76)),MAX(0,R18-$D$74*100),0) | S16: =IF(AND(2>=($D$77-1),OR(ISBLANK(S11),S11>=$D$75),OR(ISBLANK(S48),S48>=$D$76)),MAX(0,S18-$D$74*100),0) | T16: =IF(AND(2>=($D$77-1),OR(ISBLANK(T11),T11>=$D$75),OR(ISBLANK(T48),T48>=$D$76)),MAX(0,T18-$D$74*100),0) | U16: =IF(AND(2>=($D$77-1),OR(ISBLANK(U11),U11>=$D$75),OR(ISBLANK(U48),U48>=$D$76)),MAX(0,U18-$D$74*100),0) | V16: =IF(AND(2>=($D$77-1),OR(ISBLANK(V11),V11>=$D$75),OR(ISBLANK(V48),V48>=$D$76)),MAX(0,V18-$D$74*100),0) | W16: =IF(AND(3>=($D$77-1),OR(ISBLANK(W11),W11>=$D$75),OR(ISBLANK(W48),W48>=$D$76)),MAX(0,W18-$D$74*100),0) | X16: =IF(AND(3>=($D$77-1),OR(ISBLANK(X11),X11>=$D$75),OR(ISBLANK(X48),X48>=$D$76)),MAX(0,X18-$D$74*100),0) | Y16: =IF(AND(3>=($D$77-1),OR(ISBLANK(Y11),Y11>=$D$75),OR(ISBLANK(Y48),Y48>=$D$76)),MAX(0,Y18-$D$74*100),0) | Z16: =IF(AND(3>=($D$77-1),OR(ISBLANK(Z11),Z11>=$D$75),OR(ISBLANK(Z48),Z48>=$D$76)),MAX(0,Z18-$D$74*100),0) | AA16: =IF(AND(4>=($D$77-1),OR(ISBLANK(AA11),AA11>=$D$75),OR(ISBLANK(AA48),AA48>=$D$76)),MAX(0,AA18-$D$74*100),0) | AB16: =IF(AND(4>=($D$77-1),OR(ISBLANK(AB11),AB11>=$D$75),OR(ISBLANK(AB48),AB48>=$D$76)),MAX(0,AB18-$D$74*100),0) | AC16: =IF(AND(4>=($D$77-1),OR(ISBLANK(AC11),AC11>=$D$75),OR(ISBLANK(AC48),AC48>=$D$76)),MAX(0,AC18-$D$74*100),0) | AD16: =IF(AND(4>=($D$77-1),OR(ISBLANK(AD11),AD11>=$D$75),OR(ISBLANK(AD48),AD48>=$D$76)),MAX(0,AD18-$D$74*100),0) | AE16: =IF(AND(5>=($D$77-1),OR(ISBLANK(AE11),AE11>=$D$75),OR(ISBLANK(AE48),AE48>=$D$76)),MAX(0,AE18-$D$74*100),0) | AF16: =IF(AND(5>=($D$77-1),OR(ISBLANK(AF11),AF11>=$D$75),OR(ISBLANK(AF48),AF48>=$D$76)),MAX(0,AF18-$D$74*100),0) | AG16: =IF(AND(5>=($D$77-1),OR(ISBLANK(AG11),AG11>=$D$75),OR(ISBLANK(AG48),AG48>=$D$76)),MAX(0,AG18-$D$74*100),0) | AH16: =IF(AND(5>=($D$77-1),OR(ISBLANK(AH11),AH11>=$D$75),OR(ISBLANK(AH48),AH48>=$D$76)),MAX(0,AH18-$D$74*100),0) | AI16: =IF(AND(6>=($D$77-1),OR(ISBLANK(AI11),AI11>=$D$75),OR(ISBLANK(AI48),AI48>=$D$76)),MAX(0,AI18-$D$74*100),0) | AJ16: =IF(AND(6>=($D$77-1),OR(ISBLANK(AJ11),AJ11>=$D$75),OR(ISBLANK(AJ48),AJ48>=$D$76)),MAX(0,AJ18-$D$74*100),0) | AK16: =IF(AND(6>=($D$77-1),OR(ISBLANK(AK11),AK11>=$D$75),OR(ISBLANK(AK48),AK48>=$D$76)),MAX(0,AK18-$D$74*100),0) | AL16: =IF(AND(6>=($D$77-1),OR(ISBLANK(AL11),AL11>=$D$75),OR(ISBLANK(AL48),AL48>=$D$76)),MAX(0,AL18-$D$74*100),0) | AM16: =IF(AND(7>=($D$77-1),OR(ISBLANK(AM11),AM11>=$D$75),OR(ISBLANK(AM48),AM48>=$D$76)),MAX(0,AM18-$D$74*100),0) | AN16: =IF(AND(7>=($D$77-1),OR(ISBLANK(AN11),AN11>=$D$75),OR(ISBLANK(AN48),AN48>=$D$76)),MAX(0,AN18-$D$74*100),0) | AO16: =IF(AND(7>=($D$77-1),OR(ISBLANK(AO11),AO11>=$D$75),OR(ISBLANK(AO48),AO48>=$D$76)),MAX(0,AO18-$D$74*100),0) | AP16: =IF(AND(7>=($D$77-1),OR(ISBLANK(AP11),AP11>=$D$75),OR(ISBLANK(AP48),AP48>=$D$76)),MAX(0,AP18-$D$74*100),0) | AQ16: =IF(AND(8>=($D$77-1),OR(ISBLANK(AQ11),AQ11>=$D$75),OR(ISBLANK(AQ48),AQ48>=$D$76)),MAX(0,AQ18-$D$74*100),0) | AR16: =IF(AND(8>=($D$77-1),OR(ISBLANK(AR11),AR11>=$D$75),OR(ISBLANK(AR48),AR48>=$D$76)),MAX(0,AR18-$D$74*100),0) | AS16: =IF(AND(8>=($D$77-1),OR(ISBLANK(AS11),AS11>=$D$75),OR(ISBLANK(AS48),AS48>=$D$76)),MAX(0,AS18-$D$74*100),0) | AT16: =IF(AND(8>=($D$77-1),OR(ISBLANK(AT11),AT11>=$D$75),OR(ISBLANK(AT48),AT48>=$D$76)),MAX(0,AT18-$D$74*100),0) | AU16: =IF(AND(9>=($D$77-1),OR(ISBLANK(AU11),AU11>=$D$75),OR(ISBLANK(AU48),AU48>=$D$76)),MAX(0,AU18-$D$74*100),0) | AV16: =IF(AND(9>=($D$77-1),OR(ISBLANK(AV11),AV11>=$D$75),OR(ISBLANK(AV48),AV48>=$D$76)),MAX(0,AV18-$D$74*100),0) | AW16: =IF(AND(9>=($D$77-1),OR(ISBLANK(AW11),AW11>=$D$75),OR(ISBLANK(AW48),AW48>=$D$76)),MAX(0,AW18-$D$74*100),0) | AX16: =IF(AND(9>=($D$77-1),OR(ISBLANK(AX11),AX11>=$D$75),OR(ISBLANK(AX48),AX48>=$D$76)),MAX(0,AX18-$D$74*100),0) | AY16: =IF(AND(10>=($D$77-1),OR(ISBLANK(AY11),AY11>=$D$75),OR(ISBLANK(AY48),AY48>=$D$76)),MAX(0,AY18-$D$74*100),0) | AZ16: =IF(AND(10>=($D$77-1),OR(ISBLANK(AZ11),AZ11>=$D$75),OR(ISBLANK(AZ48),AZ48>=$D$76)),MAX(0,AZ18-$D$74*100),0) | BA16: =IF(AND(10>=($D$77-1),OR(ISBLANK(BA11),BA11>=$D$75),OR(ISBLANK(BA48),BA48>=$D$76)),MAX(0,BA18-$D$74*100),0) | BB16: =IF(AND(10>=($D$77-1),OR(ISBLANK(BB11),BB11>=$D$75),OR(ISBLANK(BB48),BB48>=$D$76)),MAX(0,BB18-$D$74*100),0) | BC16: =IF(AND(11>=($D$77-1),OR(ISBLANK(BC11),BC11>=$D$75),OR(ISBLANK(BC48),BC48>=$D$76)),MAX(0,BC18-$D$74*100),0) | BD16: =IF(AND(11>=($D$77-1),OR(ISBLANK(BD11),BD11>=$D$75),OR(ISBLANK(BD48),BD48>=$D$76)),MAX(0,BD18-$D$74*100),0) | BE16: =IF(AND(11>=($D$77-1),OR(ISBLANK(BE11),BE11>=$D$75),OR(ISBLANK(BE48),BE48>=$D$76)),MAX(0,BE18-$D$74*100),0) | BF16: =IF(AND(11>=($D$77-1),OR(ISBLANK(BF11),BF11>=$D$75),OR(ISBLANK(BF48),BF48>=$D$76)),MAX(0,BF18-$D$74*100),0) | BG16: =IF(AND(12>=($D$77-1),OR(ISBLANK(BG11),BG11>=$D$75),OR(ISBLANK(BG48),BG48>=$D$76)),MAX(0,BG18-$D$74*100),0) | BH16: =IF(AND(12>=($D$77-1),OR(ISBLANK(BH11),BH11>=$D$75),OR(ISBLANK(BH48),BH48>=$D$76)),MAX(0,BH18-$D$74*100),0) | BI16: =IF(AND(12>=($D$77-1),OR(ISBLANK(BI11),BI11>=$D$75),OR(ISBLANK(BI48),BI48>=$D$76)),MAX(0,BI18-$D$74*100),0) | BJ16: =IF(AND(12>=($D$77-1),OR(ISBLANK(BJ11),BJ11>=$D$75),OR(ISBLANK(BJ48),BJ48>=$D$76)),MAX(0,BJ18-$D$74*100),0) | BK16: =IF(AND(13>=($D$77-1),OR(ISBLANK(BK11),BK11>=$D$75),OR(ISBLANK(BK48),BK48>=$D$76)),MAX(0,BK18-$D$74*100),0) | BL16: =IF(AND(13>=($D$77-1),OR(ISBLANK(BL11),BL11>=$D$75),OR(ISBLANK(BL48),BL48>=$D$76)),MAX(0,BL18-$D$74*100),0) | BM16: =IF(AND(13>=($D$77-1),OR(ISBLANK(BM11),BM11>=$D$75),OR(ISBLANK(BM48),BM48>=$D$76)),MAX(0,BM18-$D$74*100),0) | BN16: =IF(AND(13>=($D$77-1),OR(ISBLANK(BN11),BN11>=$D$75),OR(ISBLANK(BN48),BN48>=$D$76)),MAX(0,BN18-$D$74*100),0) | BO16: =IF(AND(14>=($D$77-1),OR(ISBLANK(BO11),BO11>=$D$75),OR(ISBLANK(BO48),BO48>=$D$76)),MAX(0,BO18-$D$74*100),0) | BP16: =IF(AND(14>=($D$77-1),OR(ISBLANK(BP11),BP11>=$D$75),OR(ISBLANK(BP48),BP48>=$D$76)),MAX(0,BP18-$D$74*100),0) | BQ16: =IF(AND(14>=($D$77-1),OR(ISBLANK(BQ11),BQ11>=$D$75),OR(ISBLANK(BQ48),BQ48>=$D$76)),MAX(0,BQ18-$D$74*100),0) | BR16: =IF(AND(14>=($D$77-1),OR(ISBLANK(BR11),BR11>=$D$75),OR(ISBLANK(BR48),BR48>=$D$76)),MAX(0,BR18-$D$74*100),0) | BS16: =IF(AND(15>=($D$77-1),OR(ISBLANK(BS11),BS11>=$D$75),OR(ISBLANK(BS48),BS48>=$D$76)),MAX(0,BS18-$D$74*100),0) | BT16: =IF(AND(15>=($D$77-1),OR(ISBLANK(BT11),BT11>=$D$75),OR(ISBLANK(BT48),BT48>=$D$76)),MAX(0,BT18-$D$74*100),0) | BU16: =IF(AND(15>=($D$77-1),OR(ISBLANK(BU11),BU11>=$D$75),OR(ISBLANK(BU48),BU48>=$D$76)),MAX(0,BU18-$D$74*100),0) | BV16: =IF(AND(15>=($D$77-1),OR(ISBLANK(BV11),BV11>=$D$75),OR(ISBLANK(BV48),BV48>=$D$76)),MAX(0,BV18-$D$74*100),0) | BW16: =IF(AND(16>=($D$77-1),OR(ISBLANK(BW11),BW11>=$D$75),OR(ISBLANK(BW48),BW48>=$D$76)),MAX(0,BW18-$D$74*100),0) | BX16: =IF(AND(16>=($D$77-1),OR(ISBLANK(BX11),BX11>=$D$75),OR(ISBLANK(BX48),BX48>=$D$76)),MAX(0,BX18-$D$74*100),0) | BY16: =IF(AND(16>=($D$77-1),OR(ISBLANK(BY11),BY11>=$D$75),OR(ISBLANK(BY48),BY48>=$D$76)),MAX(0,BY18-$D$74*100),0) | BZ16: =IF(AND(16>=($D$77-1),OR(ISBLANK(BZ11),BZ11>=$D$75),OR(ISBLANK(BZ48),BZ48>=$D$76)),MAX(0,BZ18-$D$74*100),0) | CA16: =IF(AND(17>=($D$77-1),OR(ISBLANK(CA11),CA11>=$D$75),OR(ISBLANK(CA48),CA48>=$D$76)),MAX(0,CA18-$D$74*100),0) | CB16: =IF(AND(17>=($D$77-1),OR(ISBLANK(CB11),CB11>=$D$75),OR(ISBLANK(CB48),CB48>=$D$76)),MAX(0,CB18-$D$74*100),0) | CC16: =IF(AND(17>=($D$77-1),OR(ISBLANK(CC11),CC11>=$D$75),OR(ISBLANK(CC48),CC48>=$D$76)),MAX(0,CC18-$D$74*100),0) | CD16: =IF(AND(17>=($D$77-1),OR(ISBLANK(CD11),CD11>=$D$75),OR(ISBLANK(CD48),CD48>=$D$76)),MAX(0,CD18-$D$74*100),0) | CE16: =IF(AND(18>=($D$77-1),OR(ISBLANK(CE11),CE11>=$D$75),OR(ISBLANK(CE48),CE48>=$D$76)),MAX(0,CE18-$D$74*100),0) | CF16: =IF(AND(18>=($D$77-1),OR(ISBLANK(CF11),CF11>=$D$75),OR(ISBLANK(CF48),CF48>=$D$76)),MAX(0,CF18-$D$74*100),0) | CG16: =IF(AND(18>=($D$77-1),OR(ISBLANK(CG11),CG11>=$D$75),OR(ISBLANK(CG48),CG48>=$D$76)),MAX(0,CG18-$D$74*100),0) | CH16: =IF(AND(18>=($D$77-1),OR(ISBLANK(CH11),CH11>=$D$75),OR(ISBLANK(CH48),CH48>=$D$76)),MAX(0,CH18-$D$74*100),0) | CI16: =IF(AND(19>=($D$77-1),OR(ISBLANK(CI11),CI11>=$D$75),OR(ISBLANK(CI48),CI48>=$D$76)),MAX(0,CI18-$D$74*100),0) | CJ16: =IF(AND(19>=($D$77-1),OR(ISBLANK(CJ11),CJ11>=$D$75),OR(ISBLANK(CJ48),CJ48>=$D$76)),MAX(0,CJ18-$D$74*100),0) | CK16: =IF(AND(19>=($D$77-1),OR(ISBLANK(CK11),CK11>=$D$75),OR(ISBLANK(CK48),CK48>=$D$76)),MAX(0,CK18-$D$74*100),0) | CL16: =MAX(0,CL18)
B17: 기말현금 | C17: [KRWm] | E17: =E18-E16 | F17: =F18-F16 | G17: =G18-G16 | H17: =H18-H16 | I17: =I18-I16 | J17: =J18-J16 | K17: =K18-K16 | L17: =L18-L16 | ... CL17: =CL18-CL16
B18: (가용현금=기초현금+FCFE, 내부용) | C18: [KRWm] | E18: =E15+E13 | F18: =F15+F13 | G18: =G15+G13 | H18: =H15+H13 | I18: =I15+I13 | J18: =J15+J13 | K18: =K15+K13 | L18: =L15+L13 | ... CL18: =CL15+CL13
B19: (세금 현금조정, 내부용) | C19: [KRWm] | E19: 0 | F19: 0 | G19: 0 | H19: 0 | I19: 0 | J19: 0 | K19: 0 | L19: 0 | M19: 0 | N19: 0 | O19: 0 | P19: 0 | Q19: 0 | R19: 0 | S19: 0 | T19: 0 | U19: 0 | V19: 0 | W19: 0 | X19: 0 | Y19: 0 | Z19: 0 | AA19: 0 | AB19: 0 | AC19: 0 | AD19: 0 | AE19: 0 | AF19: 0 | AG19: 0 | AH19: 0 | AI19: 0 | AJ19: 0 | AK19: 0 | AL19: 0 | AM19: 0 | AN19: 0 | AO19: 0 | AP19: 0 | AQ19: 0 | AR19: 0 | AS19: 0 | AT19: 0 | AU19: 0 | AV19: 0 | AW19: 0 | AX19: 0 | AY19: 0 | AZ19: 0 | BA19: 0 | BB19: 0 | BC19: 0 | BD19: 0 | BE19: 0 | BF19: 0 | BG19: 0 | BH19: 0 | BI19: 0 | BJ19: 0 | BK19: 0 | BL19: 0 | BM19: 0 | BN19: 0 | BO19: 0 | BP19: 0 | BQ19: 0 | BR19: 0 | BS19: 0 | BT19: 0 | BU19: 0 | BV19: 0 | BW19: 0 | BX19: 0 | BY19: 0 | BZ19: 0 | CA19: 0 | CB19: 0 | CC19: 0 | CD19: 0 | CE19: 0 | CF19: 0 | CG19: 0 | CH19: 0 | CI19: 0 | CJ19: 0 | CK19: 0 | CL19: 0
B20: (DSRA 기초잔액, 내부용) | C20: [KRWm] | E20: =0 | F20: =E21 | G20: =F21 | H20: =G21 | I20: =H21 | J20: ='입력값'!C23*100 | K20: =J21 | L20: =K21 | M20: =L21 | N20: =M21 | O20: =N21 | P20: =O21 | Q20: =P21 | R20: =Q21 | ... CL20: =CK21
B21: (DSRA 기말잔액, 내부용) | C21: [KRWm] | E21: =E20 | F21: =F20 | G21: =G20 | H21: =H20 | I21: =I20 | J21: =J20 | K21: =L10+M10 | L21: =M10+N10 | M21: =N10+O10 | N21: =O10+P10 | O21: =P10+Q10 | P21: =Q10+R10 | Q21: =R10+S10 | R21: =S10+T10 | ... CJ21: =CK10+CL10 | CK21: =CL10 | CL21: =0
B22: (배당가능이익 누적, 내부용) | C22: [KRWm] | E22: =0 | F22: =E22 | G22: =F22 | H22: =G22 | I22: =H22 | J22: =I22 | K22: =J22+'IS(Q)'!K45 | L22: =K22+'IS(Q)'!L45 | M22: =L22+'IS(Q)'!M45 | N22: =M22+'IS(Q)'!N45 | O22: =N22+'IS(Q)'!O45 | P22: =O22+'IS(Q)'!P45 | Q22: =P22+'IS(Q)'!Q45 | R22: =Q22+'IS(Q)'!R45 | ... CL22: =CK22+'IS(Q)'!CL45
B23: (이익준비금 누적, 내부용) | C23: [KRWm] | E23: =0 | F23: =E23 | G23: =F23 | H23: =G23 | I23: =H23 | J23: =I23 | K23: =J23 | L23: =K23 | M23: =L23 | ... CL23: =CK23
B24: 연도별 DSCR · 배당 게이트 | C24: [KRWm] | E24: =0 | F24: =E24 | G24: =F24 | H24: =G24 | I24: =H24 | J24: =I24 | K24: =J24 | L24: =K24 | M24: =L24 | ... CL24: =CK24
B26: 연도 | E26: 2025 | F26: 2026 | G26: 2027 | H26: 2028 | I26: 2029 | J26: 2030 | K26: 2031 | L26: 2032 | M26: 2033 | N26: 2034 | O26: 2035 | P26: 2036 | Q26: 2037 | R26: 2038 | S26: 2039 | T26: 2040 | U26: 2041 | V26: 2042
B27: 원리금 합(연간) | C27: [KRWm] | E27: =K10 | F27: =L10+M10+N10+O10 | G27: =P10+Q10+R10+S10 | H27: =T10+U10+V10+W10 | I27: =X10+Y10+Z10+AA10 | J27: =AB10+AC10+AD10+AE10 | K27: =AF10+AG10+AH10+AI10 | L27: =AJ10+AK10+AL10+AM10 | M27: =AN10+AO10+AP10+AQ10 | N27: =AR10+AS10+AT10+AU10 | O27: =AV10+AW10+AX10+AY10 | P27: =AZ10+BA10+BB10+BC10 | Q27: =BD10+BE10+BF10+BG10 | R27: =BH10+BI10+BJ10+BK10 | S27: =BL10+BM10+BN10+BO10 | T27: =BP10+BQ10+BR10+BS10 | U27: =BT10+BU10+BV10+BW10 | V27: =BX10+BY10
B28: CFADS 합(연간) | C28: [KRWm] | E28: =K9 | F28: =L9+M9+N9+O9 | G28: =P9+Q9+R9+S9 | H28: =T9+U9+V9+W9 | I28: =X9+Y9+Z9+AA9 | J28: =AB9+AC9+AD9+AE9 | K28: =AF9+AG9+AH9+AI9 | L28: =AJ9+AK9+AL9+AM9 | M28: =AN9+AO9+AP9+AQ9 | N28: =AR9+AS9+AT9+AU9 | O28: =AV9+AW9+AX9+AY9 | P28: =AZ9+BA9+BB9+BC9 | Q28: =BD9+BE9+BF9+BG9 | R28: =BH9+BI9+BJ9+BK9 | S28: =BL9+BM9+BN9+BO9 | T28: =BP9+BQ9+BR9+BS9 | U28: =BT9+BU9+BV9+BW9 | V28: =BX9+BY9
B29: 단순 DSCR(연 합산) | C29: [x] | E29: =IF(E27=0,"",E28/E27) | F29: =IF(F27=0,"",F28/F27) | G29: =IF(G27=0,"",G28/G27) | H29: =IF(H27=0,"",H28/H27) | I29: =IF(I27=0,"",I28/I27) | J29: =IF(J27=0,"",J28/J27) | K29: =IF(K27=0,"",K28/K27) | L29: =IF(L27=0,"",L28/L27) | ... V29: =IF(V27=0,"",V28/V27)
B30: 누적 DSCR(연간) | C30: [x] | E30: =IF(E27=0,"",(H15+H20+E28)/E27) | F30: =IF(F27=0,"",(L15+L20+F28)/F27) | G30: =IF(G27=0,"",(P15+P20+G28)/G27) | H30: =IF(H27=0,"",(T15+T20+H28)/H27) | I30: =IF(I27=0,"",(X15+X20+I28)/I27) | J30: =IF(J27=0,"",(AB15+AB20+J28)/J27) | K30: =IF(K27=0,"",(AF15+AF20+K28)/K27) | L30: =IF(L27=0,"",(AJ15+AJ20+L28)/L27) | M30: =IF(M27=0,"",(AN15+AN20+M28)/M27) | N30: =IF(N27=0,"",(AR15+AR20+N28)/N27) | O30: =IF(O27=0,"",(AV15+AV20+O28)/O27) | P30: =IF(P27=0,"",(AZ15+AZ20+P28)/P27) | Q30: =IF(Q27=0,"",(BD15+BD20+Q28)/Q27) | R30: =IF(R27=0,"",(BH15+BH20+R28)/R27) | S30: =IF(S27=0,"",(BL15+BL20+S28)/S27) | T30: =IF(T27=0,"",(BP15+BP20+T28)/T27) | U30: =IF(U27=0,"",(BT15+BT20+U28)/U27) | V30: =IF(V27=0,"",(BX15+BX20+V28)/V27)
B31: CFADS 합(현금기준, 연간) | C31: [KRWm]
B32: 그 해 첫 운영분기 기초현금+DSRA | C32: [KRWm]
B33: 그 해 첫 운영분기 기초현금 | C33: [KRWm]
B34: 그 해 지급월 기초현금-배당 | C34: [KRWm]
B35: 단순DSCR 게이트 통과 | C35: [bool]
B36: 누적DSCR 게이트 통과 | C36: [bool]
B37: 배당 결의 가능 | C37: [bool]
B38: 배당가능이익 한도 | C38: [KRWm]
B39: 현금 한도 | C39: [KRWm]
B40: 원리금상환재원 기준선 | C40: [KRWm]
B41: 원리금상환재원 한도 | C41: [KRWm]
B42: 결정 배당액 | C42: [KRWm]
B43: 이익준비금 적립액 | C43: [KRWm]
B45: 검증
B46: (누적 CFADS, 내부용) | C46: [KRWm] | E46: =0 | F46: =E46 | G46: =F46 | H46: =G46 | I46: =H46 | J46: =I46 | K46: =J46+K9 | L46: =K46+L9 | M46: =L46+M9 | N46: =M46+N9 | O46: =N46+O9 | P46: =O46+P9 | Q46: =P46+Q9 | R46: =Q46+R9 | ... CL46: =CK46+CL9
B47: 최소 단순DSCR(연 합산) | C47: [x] | D47: =MIN(E29:V29) | E47: =0 | F47: =E47 | G47: =F47 | H47: =G47 | I47: =H47 | J47: =I47 | K47: =J47+K10 | L47: =K47+L10 | M47: =L47+M10 | N47: =M47+N10 | O47: =N47+O10 | P47: =O47+P10 | Q47: =P47+Q10 | R47: =Q47+R10 | ... CL47: =CK47+CL10
B48: 최소 누적DSCR | C48: [x] | D48: =MIN(E30:V30) | K48: =IF(K47>0,K46/K47,"") | L48: =IF(L47>0,L46/L47,"") | M48: =IF(M47>0,M46/M47,"") | N48: =IF(N47>0,N46/N47,"") | O48: =IF(O47>0,O46/O47,"") | P48: =IF(P47>0,P46/P47,"") | Q48: =IF(Q47>0,Q46/Q47,"") | R48: =IF(R47>0,R46/R47,"") | ... CL48: =IF(CL47>0,CL46/CL47,"")
B49: 최종 기말현금(음수면 오류) | C49: [KRWm] | D49: =CL17
B51: IRR용 현금흐름 (참고)
B53: 구 분 | C53: unit | D53: 합 계 | E53: 2024-06-30 | F53: 2024-09-30 | G53: 2024-12-31 | H53: 2025-03-31 | I53: 2025-06-30 | J53: 2025-09-30 | K53: 2025-12-31 | L53: 2026-03-31 | M53: 2026-06-30 | N53: 2026-09-30 | O53: 2026-12-31 | P53: 2027-03-31 | Q53: 2027-06-30 | R53: 2027-09-30 | S53: 2027-12-31 | T53: 2028-03-31 | U53: 2028-06-30 | V53: 2028-09-30 | W53: 2028-12-31 | X53: 2029-03-31 | Y53: 2029-06-30 | Z53: 2029-09-30 | AA53: 2029-12-31 | AB53: 2030-03-31 | AC53: 2030-06-30 | AD53: 2030-09-30 | AE53: 2030-12-31 | AF53: 2031-03-31 | AG53: 2031-06-30 | AH53: 2031-09-30 | AI53: 2031-12-31 | AJ53: 2032-03-31 | AK53: 2032-06-30 | AL53: 2032-09-30 | AM53: 2032-12-31 | AN53: 2033-03-31 | AO53: 2033-06-30 | AP53: 2033-09-30 | AQ53: 2033-12-31 | AR53: 2034-03-31 | AS53: 2034-06-30 | AT53: 2034-09-30 | AU53: 2034-12-31 | AV53: 2035-03-31 | AW53: 2035-06-30 | AX53: 2035-09-30 | AY53: 2035-12-31 | AZ53: 2036-03-31 | BA53: 2036-06-30 | BB53: 2036-09-30 | BC53: 2036-12-31 | BD53: 2037-03-31 | BE53: 2037-06-30 | BF53: 2037-09-30 | BG53: 2037-12-31 | BH53: 2038-03-31 | BI53: 2038-06-30 | BJ53: 2038-09-30 | BK53: 2038-12-31 | BL53: 2039-03-31 | BM53: 2039-06-30 | BN53: 2039-09-30 | BO53: 2039-12-31 | BP53: 2040-03-31 | BQ53: 2040-06-30 | BR53: 2040-09-30 | BS53: 2040-12-31 | BT53: 2041-03-31 | BU53: 2041-06-30 | BV53: 2041-09-30 | BW53: 2041-12-31 | BX53: 2042-03-31 | BY53: 2042-06-30 | BZ53: 2042-09-30 | CA53: 2042-12-31 | CB53: 2043-03-31 | CC53: 2043-06-30 | CD53: 2043-09-30 | CE53: 2043-12-31 | CF53: 2044-03-31 | CG53: 2044-06-30 | CH53: 2044-09-30 | CI53: 2044-12-31 | CJ53: 2045-03-31 | CK53: 2045-06-30 | CL53: 2045-09-30
B55: 자본금 인출 | C55: [KRWm] | D55: =SUM(E55:CL55) | E55: ='Debt'!E17 | F55: ='Debt'!F17-'Debt'!E17 | G55: ='Debt'!G17-'Debt'!F17 | H55: ='Debt'!H17-'Debt'!G17 | I55: ='Debt'!I17-'Debt'!H17 | J55: ='Debt'!J17-'Debt'!I17 | K55: ='Debt'!K17-'Debt'!J17 | L55: ='Debt'!L17-'Debt'!K17 | M55: ='Debt'!M17-'Debt'!L17 | ... CL55: ='Debt'!CL17-'Debt'!CK17
B56: Project 현금흐름 | C56: [KRWm] | E56: ='Revenue'!E17-'Opex'!E24+'IS(Q)'!E44+'IS(Q)'!E31+'Revenue'!E22-('Debt'!E8) | F56: ='Revenue'!F17-'Opex'!F24+'IS(Q)'!F44+'IS(Q)'!F31+'Revenue'!F22-('Debt'!F8) | G56: ='Revenue'!G17-'Opex'!G24+'IS(Q)'!G44+'IS(Q)'!G31+'Revenue'!G22-('Debt'!G8) | H56: ='Revenue'!H17-'Opex'!H24+'IS(Q)'!H44+'IS(Q)'!H31+'Revenue'!H22-('Debt'!H8) | I56: ='Revenue'!I17-'Opex'!I24+'IS(Q)'!I44+'IS(Q)'!I31+'Revenue'!I22-('Debt'!I8) | J56: ='Revenue'!J17-'Opex'!J24+'IS(Q)'!J44+'IS(Q)'!J31+'Revenue'!J22-('Debt'!J8) | K56: ='Revenue'!K17-'Opex'!K24+'IS(Q)'!K44+'IS(Q)'!K31+'Revenue'!K22-('Debt'!K8) | L56: ='Revenue'!L17-'Opex'!L24+'IS(Q)'!L44+'IS(Q)'!L31+'Revenue'!L22-('Debt'!L8) | ... CK56: ='Revenue'!CK17-'Opex'!CK24+'IS(Q)'!CK44+'IS(Q)'!CK31+'Revenue'!CK22-('Debt'!CK8) | CL56: ='Revenue'!CL17-'Opex'!CL24+'IS(Q)'!CL44-$D$73*100+'IS(Q)'!CL31+'Revenue'!CL22-('Debt'!CL8)
B57: Project 현금흐름(세전) | C57: [KRWm] | E57: ='Revenue'!E17-'Opex'!E24+'IS(Q)'!E31+'Revenue'!E22-('Debt'!E8) | F57: ='Revenue'!F17-'Opex'!F24+'IS(Q)'!F31+'Revenue'!F22-('Debt'!F8) | G57: ='Revenue'!G17-'Opex'!G24+'IS(Q)'!G31+'Revenue'!G22-('Debt'!G8) | H57: ='Revenue'!H17-'Opex'!H24+'IS(Q)'!H31+'Revenue'!H22-('Debt'!H8) | I57: ='Revenue'!I17-'Opex'!I24+'IS(Q)'!I31+'Revenue'!I22-('Debt'!I8) | J57: ='Revenue'!J17-'Opex'!J24+'IS(Q)'!J31+'Revenue'!J22-('Debt'!J8) | K57: ='Revenue'!K17-'Opex'!K24+'IS(Q)'!K31+'Revenue'!K22-('Debt'!K8) | L57: ='Revenue'!L17-'Opex'!L24+'IS(Q)'!L31+'Revenue'!L22-('Debt'!L8) | ... CK57: ='Revenue'!CK17-'Opex'!CK24+'IS(Q)'!CK31+'Revenue'!CK22-('Debt'!CK8) | CL57: ='Revenue'!CL17-'Opex'!CL24-$D$73*100+'IS(Q)'!CL31+'Revenue'!CL22-('Debt'!CL8)
B58: Equity 현금흐름(FCFE 기준) | C58: [KRWm] | E58: =E13-E55 | F58: =F13-F55 | G58: =G13-G55 | H58: =H13-H55 | I58: =I13-I55 | J58: =J13-J55 | K58: =K13-K55 | L58: =L13-L55 | ... CL58: =CL13-CL55
B59: Equity 현금흐름(배당 기준) | C59: [KRWm] | E59: =E16-E55 | F59: =F16-F55 | G59: =G16-G55 | H59: =H16-H55 | I59: =I16-I55 | J59: =J16-J55 | K59: =K16-K55 | L59: =L16-L55 | ... CL59: =CL16-CL55
B60: Investor 현금흐름 | C60: [KRWm] | E60: =-E55-('Debt'!E18+'Debt'!E19+'Debt'!E20+'Debt'!E21+'Debt'!E22)+'Debt'!E77+'Debt'!E78+E16 | F60: =-F55-('Debt'!F18-'Debt'!E18+'Debt'!F19-'Debt'!E19+'Debt'!F20-'Debt'!E20+'Debt'!F21-'Debt'!E21+'Debt'!F22-'Debt'!E22)+'Debt'!F77+'Debt'!F78+F16 | G60: =-G55-('Debt'!G18-'Debt'!F18+'Debt'!G19-'Debt'!F19+'Debt'!G20-'Debt'!F20+'Debt'!G21-'Debt'!F21+'Debt'!G22-'Debt'!F22)+'Debt'!G77+'Debt'!G78+G16 | H60: =-H55-('Debt'!H18-'Debt'!G18+'Debt'!H19-'Debt'!G19+'Debt'!H20-'Debt'!G20+'Debt'!H21-'Debt'!G21+'Debt'!H22-'Debt'!G22)+'Debt'!H77+'Debt'!H78+H16 | I60: =-I55-('Debt'!I18-'Debt'!H18+'Debt'!I19-'Debt'!H19+'Debt'!I20-'Debt'!H20+'Debt'!I21-'Debt'!H21+'Debt'!I22-'Debt'!H22)+'Debt'!I77+'Debt'!I78+I16 | J60: =-J55-('Debt'!J18-'Debt'!I18+'Debt'!J19-'Debt'!I19+'Debt'!J20-'Debt'!I20+'Debt'!J21-'Debt'!I21+'Debt'!J22-'Debt'!I22)+'Debt'!J77+'Debt'!J78+J16+'Debt'!D15 | K60: =-K55-('Debt'!K18-'Debt'!J18+'Debt'!K19-'Debt'!J19+'Debt'!K20-'Debt'!J20+'Debt'!K21-'Debt'!J21+'Debt'!K22-'Debt'!J22)+'Debt'!K77+'Debt'!K78+K16 | L60: =-L55-('Debt'!L18-'Debt'!K18+'Debt'!L19-'Debt'!K19+'Debt'!L20-'Debt'!K20+'Debt'!L21-'Debt'!K21+'Debt'!L22-'Debt'!K22)+'Debt'!L77+'Debt'!L78+L16 | M60: =-M55-('Debt'!M18-'Debt'!L18+'Debt'!M19-'Debt'!L19+'Debt'!M20-'Debt'!L20+'Debt'!M21-'Debt'!L21+'Debt'!M22-'Debt'!L22)+'Debt'!M77+'Debt'!M78+M16 | N60: =-N55-('Debt'!N18-'Debt'!M18+'Debt'!N19-'Debt'!M19+'Debt'!N20-'Debt'!M20+'Debt'!N21-'Debt'!M21+'Debt'!N22-'Debt'!M22)+'Debt'!N77+'Debt'!N78+N16 | O60: =-O55-('Debt'!O18-'Debt'!N18+'Debt'!O19-'Debt'!N19+'Debt'!O20-'Debt'!N20+'Debt'!O21-'Debt'!N21+'Debt'!O22-'Debt'!N22)+'Debt'!O77+'Debt'!O78+O16 | P60: =-P55-('Debt'!P18-'Debt'!O18+'Debt'!P19-'Debt'!O19+'Debt'!P20-'Debt'!O20+'Debt'!P21-'Debt'!O21+'Debt'!P22-'Debt'!O22)+'Debt'!P77+'Debt'!P78+P16 | Q60: =-Q55-('Debt'!Q18-'Debt'!P18+'Debt'!Q19-'Debt'!P19+'Debt'!Q20-'Debt'!P20+'Debt'!Q21-'Debt'!P21+'Debt'!Q22-'Debt'!P22)+'Debt'!Q77+'Debt'!Q78+Q16 | R60: =-R55-('Debt'!R18-'Debt'!Q18+'Debt'!R19-'Debt'!Q19+'Debt'!R20-'Debt'!Q20+'Debt'!R21-'Debt'!Q21+'Debt'!R22-'Debt'!Q22)+'Debt'!R77+'Debt'!R78+R16 | ... CL60: =-CL55-('Debt'!CL18-'Debt'!CK18+'Debt'!CL19-'Debt'!CK19+'Debt'!CL20-'Debt'!CK20+'Debt'!CL21-'Debt'!CK21+'Debt'!CL22-'Debt'!CK22)+'Debt'!CL77+'Debt'!CL78+CL16
B62: Project IRR(세전) | C62: [%] | D62: =(1+IRR(E57:CL57,0.020476572460195186))^4-1
B63: Project IRR(세후) | C63: [%] | D63: =(1+IRR(E56:CL56,0.01873021186520507))^4-1
B64: Equity IRR(FCFE) | C64: [%] | D64: =(1+IRR(E58:CL58,0.029916661783614185))^4-1
B65: Equity IRR(배당) | C65: [%] | D65: =(1+IRR(E59:CL59,0.024356261515786404))^4-1
B66: Investor IRR | C66: [%] | D66: =(1+IRR(E60:CL60,0.01683102724296992))^4-1
B68: ※ IRR()의 두 번째 인자(초기 추정치)에 현재 계산된 값을 넣어 엉뚱한 근으로 수렴하는 걸 방지했습니다. 입력값을 크게 바꿔서 결과가 비정상적으로 크게(수백% 이상) 나오면, 그 근처의 추정치로 다시 만들어야 정확합니다 — 화면(HTML) 값과 대조해서 확인하세요.
B71: 가정 (입력값 연결) — 이 시트의 계산이 쓰는 원천값 | D71: 값
B72: ※ 입력값 시트는 여기서만 참조합니다(초록 글자 = 입력값 연결). 위의 분기 계산은 이 셀들만 참조하므로, 값을 바꾸려면 입력값 시트를 고치세요.
B73: 철거비(복구충당부채)[억원] | C73: C17 | D73: ='입력값'!C17
B74: 최소 보유현금[억원] | C74: C25 | D74: ='입력값'!C25
B75: 배당 게이트 — 단순DSCR 최소치[x] | C75: C26 | D75: ='입력값'!C26
B76: 배당 게이트 — 누적DSCR 최소치[x] | C76: C27 | D76: ='입력값'!C27
B77: 배당 개시 운영연차 | C77: C28 | D77: ='입력값'!C28
