Workbook

Sheet 목차
B2: 당진 태양광발전
B3: 재무모델 v2 (분기·5트랜치) — 재생E AI Agent 자동생성 · 2026-08-26
B6: 시트 | C6: 내용
B7: Report | C7: Executive Summary — 핵심 KPI
B8: 입력값 | C8: 화면에서 입력한 원본 값 — Funding 등이 이 시트를 참조
B9: Funding | C9: 자금조달 — 자본금 + 5트랜치 조건
B10: Debt | C10: 트랜치별 상환 스케줄 (A/B/C/D/후순위) + 합계
B11: Revenue | C11: 발전량 · 매출
B12: Opex | C12: 운영비 (선순위/후순위)
B13: IS(Q) | C13: 분기 손익계산서
B14: CF(Q) | C14: 분기 현금흐름 · DSCR · 배당
B16: ※ Funding 시트의 트랜치 조건·총사업비 항목·사업자 지분은 "입력값" 시트를 참조하는 수식입니다(입력값 시트를 고치면 같이 바뀝니다). 그 외 계산 결과(세금·DSCR·배당 등)는 값(baked) 기준이라 가정을 바꾸려면 생성기에서 다시 뽑아야 합니다.

Sheet Report
A1: 당진 태양광발전
A2: Executive Summary (v2 · 분기 · 5트랜치)
B4: 사업 개요
B6: 사업명 | D6: ='입력값'!C6
B7: 설비용량 [MW] | D7: ='입력값'!C7
B8: 총 기간 수(분기) | D8: 86
B9: 건설 개시 | D9: 2024-06
B11: 재원조달
B13: 총투자비(TIC) [KRWm] | D13: ='Funding'!C18
B14: 건설이자(IDC) [KRWm] | D14: ='Funding'!C17
B15: 자기자본 [KRWm] | D15: ='Funding'!C7
B16: 차입금 합계 [KRWm] | D16: ='Funding'!C13
B18: 수익성 지표
B20: Project IRR 세전 [%] | D20: 0.084668087
B21: Project IRR 세후 [%] | D21: 0.078606546
B22: Equity IRR (FCFE) [%] | D22: 0.13333655
B23: Equity IRR (배당) [%] | D23: 0.12119452
B24: Investor IRR [%] | D24: 0.072853729
B25: 최소 단순DSCR(연 합산) [x] | D25: 1.217936
B26: 최소 누적DSCR [x] | D26: 1.4488807
B27: 총영업수익(전체기간) [KRWm] | D27: 405781.18
B28: 총영업비용(전체기간) [KRWm] | D28: 105377.38
B29: 총선순위이자 [KRWm] | D29: 66082.737
B30: 총법인세 [KRWm] | D30: 16762.222
B31: 총배당(연차+청산) [KRWm] | D31: 85238.842

Sheet 입력값
A1: 당진 태양광발전
A2: 입력값 — 화면에서 입력한 값 (다른 시트가 이 시트를 참조)
B4: 사업 기본 가정
B6: 사업명 | C6: 당진 태양광발전
B7: 설비용량[MW] | C7: 99.998
B8: 총사업비[억원] | C8: 1410.6882
B9: 자기자본[억원] | C9: 150
B10: 판매단가[원/kWh]
B11: 판매단가 에스컬레이션[%/yr]
B12: 발전량 열화율[%/yr] | C12: 0.5
B13: 소내소비율[%] | C13: 0
B14: 일조시간[h/day] | C14: 3.77
B15: 상각대상액(직접입력)[KRWm] | C15: 137976.35
B16: 감가상각 내용연수[yr] | C16: 20
B17: 철거비(복구충당부채)[억원] | C17: 20
B19: 판매단가 트랙 (PPA/SMP+REC 등)
B21: 트랙 | C21: 비중[%] | D21: 단가[원/kWh] | E21: 에스컬레이션[%/yr]
B22: 트랙1 | C22: 0 | D22: 0 | E22: 0
B23: 트랙2 | C23: 60.0012 | D23: 160 | E23: 0
B24: 트랙3 | C24: 39.9988 | D24: 147 | E24: 0
B26: 트랜치 조건
B28: 트랜치 | C28: 금액[억원] | D28: 건설금리[%] | E28: 운영금리[%] | F28: 거치(yr) | G28: 상환(yr) | H28: 방식
B29: 선순위A | C29: 500 | D29: 0.056 | E29: 0.056 | F29: 2 | G29: 16 | H29: 3
B30: 선순위B | C30: 500 | D30: 0.055 | E30: 0.055 | F30: 2 | G30: 16 | H30: 3
B31: 선순위C | C31: 350 | D31: 0.055 | E31: 0.055 | F31: 1.25 | G31: 16 | H31: 3
B32: 선순위D | C32: 0 | D32: 0.0225 | E32: 0.0225 | F32: 5 | G32: 10 | H32: 3
B33: 후순위 | C33: 0 | D33: 0.0565 | E33: 0.0565 | F33: 15 | G33: 2.75 | H33: 3
B35: 방식3 상환비율 ("예시 불러오기" 전용 — 원본 상환 스케줄)
B37: 구 분 | C37: unit | D37: 합 계 | E37: 2024-06-30 | F37: 2024-09-30 | G37: 2024-12-31 | H37: 2025-03-31 | I37: 2025-06-30 | J37: 2025-09-30 | K37: 2025-12-31 | L37: 2026-03-31 | M37: 2026-06-30 | N37: 2026-09-30 | O37: 2026-12-31 | P37: 2027-03-31 | Q37: 2027-06-30 | R37: 2027-09-30 | S37: 2027-12-31 | T37: 2028-03-31 | U37: 2028-06-30 | V37: 2028-09-30 | W37: 2028-12-31 | X37: 2029-03-31 | Y37: 2029-06-30 | Z37: 2029-09-30 | AA37: 2029-12-31 | AB37: 2030-03-31 | AC37: 2030-06-30 | AD37: 2030-09-30 | AE37: 2030-12-31 | AF37: 2031-03-31 | AG37: 2031-06-30 | AH37: 2031-09-30 | AI37: 2031-12-31 | AJ37: 2032-03-31 | AK37: 2032-06-30 | AL37: 2032-09-30 | AM37: 2032-12-31 | AN37: 2033-03-31 | AO37: 2033-06-30 | AP37: 2033-09-30 | AQ37: 2033-12-31 | AR37: 2034-03-31 | AS37: 2034-06-30 | AT37: 2034-09-30 | AU37: 2034-12-31 | AV37: 2035-03-31 | AW37: 2035-06-30 | AX37: 2035-09-30 | AY37: 2035-12-31 | AZ37: 2036-03-31 | BA37: 2036-06-30 | BB37: 2036-09-30 | BC37: 2036-12-31 | BD37: 2037-03-31 | BE37: 2037-06-30 | BF37: 2037-09-30 | BG37: 2037-12-31 | BH37: 2038-03-31 | BI37: 2038-06-30 | BJ37: 2038-09-30 | BK37: 2038-12-31 | BL37: 2039-03-31 | BM37: 2039-06-30 | BN37: 2039-09-30 | BO37: 2039-12-31 | BP37: 2040-03-31 | BQ37: 2040-06-30 | BR37: 2040-09-30 | BS37: 2040-12-31 | BT37: 2041-03-31 | BU37: 2041-06-30 | BV37: 2041-09-30 | BW37: 2041-12-31 | BX37: 2042-03-31 | BY37: 2042-06-30 | BZ37: 2042-09-30 | CA37: 2042-12-31 | CB37: 2043-03-31 | CC37: 2043-06-30 | CD37: 2043-09-30 | CE37: 2043-12-31 | CF37: 2044-03-31 | CG37: 2044-06-30 | CH37: 2044-09-30 | CI37: 2044-12-31 | CJ37: 2045-03-31 | CK37: 2045-06-30 | CL37: 2045-09-30
B39: 선순위A 상환비율 | C39: [비율] | N39: 0.030625 | O39: 0.021 | P39: 0.013 | Q39: 0.013 | R39: 0.014 | S39: 0.014 | T39: 0.014 | U39: 0.014 | V39: 0.014 | W39: 0.014 | X39: 0.014 | Y39: 0.015 | Z39: 0.015 | AA39: 0.015 | AB39: 0.015 | AC39: 0.015 | AD39: 0.015 | AE39: 0.015625 | AF39: 0.015625 | AG39: 0.015625 | AH39: 0.015625 | AI39: 0.015625 | AJ39: 0.015625 | AK39: 0.015625 | AL39: 0.015625 | AM39: 0.015625 | AN39: 0.015625 | AO39: 0.015625 | AP39: 0.015625 | AQ39: 0.015625 | AR39: 0.015625 | AS39: 0.015625 | AT39: 0.015625 | AU39: 0.015625 | AV39: 0.015625 | AW39: 0.015625 | AX39: 0.015625 | AY39: 0.015625 | AZ39: 0.015625 | BA39: 0.015625 | BB39: 0.015625 | BC39: 0.015625 | BD39: 0.015625 | BE39: 0.015625 | BF39: 0.015625 | BG39: 0.015625 | BH39: 0.015625 | BI39: 0.015625 | BJ39: 0.015625 | BK39: 0.015625 | BL39: 0.015625 | BM39: 0.015625 | BN39: 0.015625 | BO39: 0.015625 | BP39: 0.015625 | BQ39: 0.015625 | BR39: 0.015625 | BS39: 0.015625 | BT39: 0.015625 | BU39: 0.015625 | BV39: 0.015625 | BW39: 0.015625 | BX39: 0.015625 | BY39: 0.015625
B40: 선순위B 상환비율 | C40: [비율] | N40: 0.030625 | O40: 0.021 | P40: 0.013 | Q40: 0.013 | R40: 0.014 | S40: 0.014 | T40: 0.014 | U40: 0.014 | V40: 0.014 | W40: 0.014 | X40: 0.014 | Y40: 0.015 | Z40: 0.015 | AA40: 0.015 | AB40: 0.015 | AC40: 0.015 | AD40: 0.015 | AE40: 0.015625 | AF40: 0.015625 | AG40: 0.015625 | AH40: 0.015625 | AI40: 0.015625 | AJ40: 0.015625 | AK40: 0.015625 | AL40: 0.015625 | AM40: 0.015625 | AN40: 0.015625 | AO40: 0.015625 | AP40: 0.015625 | AQ40: 0.015625 | AR40: 0.015625 | AS40: 0.015625 | AT40: 0.015625 | AU40: 0.015625 | AV40: 0.015625 | AW40: 0.015625 | AX40: 0.015625 | AY40: 0.015625 | AZ40: 0.015625 | BA40: 0.015625 | BB40: 0.015625 | BC40: 0.015625 | BD40: 0.015625 | BE40: 0.015625 | BF40: 0.015625 | BG40: 0.015625 | BH40: 0.015625 | BI40: 0.015625 | BJ40: 0.015625 | BK40: 0.015625 | BL40: 0.015625 | BM40: 0.015625 | BN40: 0.015625 | BO40: 0.015625 | BP40: 0.015625 | BQ40: 0.015625 | BR40: 0.015625 | BS40: 0.015625 | BT40: 0.015625 | BU40: 0.015625 | BV40: 0.015625 | BW40: 0.015625 | BX40: 0.015625 | BY40: 0.015625
B41: 선순위C 상환비율 | C41: [비율] | N41: 0.030625 | O41: 0.021 | P41: 0.013 | Q41: 0.013 | R41: 0.014 | S41: 0.014 | T41: 0.014 | U41: 0.014 | V41: 0.014 | W41: 0.014 | X41: 0.014 | Y41: 0.015 | Z41: 0.015 | AA41: 0.015 | AB41: 0.015 | AC41: 0.015 | AD41: 0.015 | AE41: 0.015625 | AF41: 0.015625 | AG41: 0.015625 | AH41: 0.015625 | AI41: 0.015625 | AJ41: 0.015625 | AK41: 0.015625 | AL41: 0.015625 | AM41: 0.015625 | AN41: 0.015625 | AO41: 0.015625 | AP41: 0.015625 | AQ41: 0.015625 | AR41: 0.015625 | AS41: 0.015625 | AT41: 0.015625 | AU41: 0.015625 | AV41: 0.015625 | AW41: 0.015625 | AX41: 0.015625 | AY41: 0.015625 | AZ41: 0.015625 | BA41: 0.015625 | BB41: 0.015625 | BC41: 0.015625 | BD41: 0.015625 | BE41: 0.015625 | BF41: 0.015625 | BG41: 0.015625 | BH41: 0.015625 | BI41: 0.015625 | BJ41: 0.015625 | BK41: 0.015625 | BL41: 0.015625 | BM41: 0.015625 | BN41: 0.015625 | BO41: 0.015625 | BP41: 0.015625 | BQ41: 0.015625 | BR41: 0.015625 | BS41: 0.015625 | BT41: 0.015625 | BU41: 0.015625 | BV41: 0.015625 | BW41: 0.015625 | BX41: 0.015625 | BY41: 0.015625
B43: 총사업비 항목
B45: 항목 | C45: 금액[억원]
B46: EPC
B47: 감리비
B48: 공사보험료
B49: 토지임대료(선납)
B50: 토지임대료(분납)
B51: 사업개발비
B52: 민원처리비
B53: 사업성자문비
B54: 법인운영비
B55: 기타예비비
B56: 신주발행비용
B57: 금융부대비용
B59: 운영비 항목
B61: 항목 | C61: 연간금액[억원/yr] | D61: 에스컬레이션[%/yr]
B62: 부지임대료 | C62: 9.555 | D62: 0
B63: O&M | C63: 15 | D63: 1.5
B64: 보험료 | C64: 6.5 | D64: 0
B65: 환경모니터링비용 | C65: 1.095 | D65: 0
B66: 소내전력비 | C66: 2 | D66: 2
B67: 인건비 | C67: 2 | D67: 2
B68: 법인운영비 | C68: 1.5 | D68: 2
B69: 주민보상비 | C69: 8 | D69: 0
B70: 도로점용료 | C70: 0.3 | D70: 0
B71: 예비비 | C71: 3 | D71: 0
B72: 전력거래수수료 | C72: 0.21416 | D72: 0
B73: 관리운영비 성과보수 | C73: 0 | D73: 0
B76: 실측 오버라이드 ("예시 불러오기" 전용 — 공식이 아니라 원본 FS의 분기별 실제값)
B78: 구 분 | C78: unit | D78: 합 계 | E78: 2024-06-30 | F78: 2024-09-30 | G78: 2024-12-31 | H78: 2025-03-31 | I78: 2025-06-30 | J78: 2025-09-30 | K78: 2025-12-31 | L78: 2026-03-31 | M78: 2026-06-30 | N78: 2026-09-30 | O78: 2026-12-31 | P78: 2027-03-31 | Q78: 2027-06-30 | R78: 2027-09-30 | S78: 2027-12-31 | T78: 2028-03-31 | U78: 2028-06-30 | V78: 2028-09-30 | W78: 2028-12-31 | X78: 2029-03-31 | Y78: 2029-06-30 | Z78: 2029-09-30 | AA78: 2029-12-31 | AB78: 2030-03-31 | AC78: 2030-06-30 | AD78: 2030-09-30 | AE78: 2030-12-31 | AF78: 2031-03-31 | AG78: 2031-06-30 | AH78: 2031-09-30 | AI78: 2031-12-31 | AJ78: 2032-03-31 | AK78: 2032-06-30 | AL78: 2032-09-30 | AM78: 2032-12-31 | AN78: 2033-03-31 | AO78: 2033-06-30 | AP78: 2033-09-30 | AQ78: 2033-12-31 | AR78: 2034-03-31 | AS78: 2034-06-30 | AT78: 2034-09-30 | AU78: 2034-12-31 | AV78: 2035-03-31 | AW78: 2035-06-30 | AX78: 2035-09-30 | AY78: 2035-12-31 | AZ78: 2036-03-31 | BA78: 2036-06-30 | BB78: 2036-09-30 | BC78: 2036-12-31 | BD78: 2037-03-31 | BE78: 2037-06-30 | BF78: 2037-09-30 | BG78: 2037-12-31 | BH78: 2038-03-31 | BI78: 2038-06-30 | BJ78: 2038-09-30 | BK78: 2038-12-31 | BL78: 2039-03-31 | BM78: 2039-06-30 | BN78: 2039-09-30 | BO78: 2039-12-31 | BP78: 2040-03-31 | BQ78: 2040-06-30 | BR78: 2040-09-30 | BS78: 2040-12-31 | BT78: 2041-03-31 | BU78: 2041-06-30 | BV78: 2041-09-30 | BW78: 2041-12-31 | BX78: 2042-03-31 | BY78: 2042-06-30 | BZ78: 2042-09-30 | CA78: 2042-12-31 | CB78: 2043-03-31 | CC78: 2043-06-30 | CD78: 2043-09-30 | CE78: 2043-12-31 | CF78: 2044-03-31 | CG78: 2044-06-30 | CH78: 2044-09-30 | CI78: 2044-12-31 | CJ78: 2045-03-31 | CK78: 2045-06-30 | CL78: 2045-09-30
B80: 판매단가(실측) | C80: [원/kWh] | K80: 154.80016 | L80: 154.80016 | M80: 154.80016 | N80: 154.80016 | O80: 154.80016 | P80: 154.80016 | Q80: 154.80016 | R80: 154.80016 | S80: 154.80016 | T80: 154.80016 | U80: 154.80016 | V80: 154.80016 | W80: 154.80016 | X80: 154.80016 | Y80: 154.80016 | Z80: 154.80016 | AA80: 154.80016 | AB80: 154.80016 | AC80: 154.80016 | AD80: 154.80016 | AE80: 154.80016 | AF80: 154.80016 | AG80: 154.80016 | AH80: 154.80016 | AI80: 154.80016 | AJ80: 154.80016 | AK80: 154.80016 | AL80: 154.80016 | AM80: 154.80016 | AN80: 154.80016 | AO80: 154.80016 | AP80: 154.80016 | AQ80: 154.80016 | AR80: 154.80016 | AS80: 154.80016 | AT80: 154.80016 | AU80: 154.80016 | AV80: 154.80016 | AW80: 154.80016 | AX80: 154.80016 | AY80: 154.80016 | AZ80: 154.80016 | BA80: 154.80016 | BB80: 154.80016 | BC80: 154.80016 | BD80: 154.80016 | BE80: 154.80016 | BF80: 154.80016 | BG80: 154.80016 | BH80: 154.80016 | BI80: 154.80016 | BJ80: 154.80016 | BK80: 154.80016 | BL80: 154.80016 | BM80: 154.80016 | BN80: 154.80016 | BO80: 154.80016 | BP80: 154.80016 | BQ80: 154.80016 | BR80: 154.80016 | BS80: 154.80016 | BT80: 154.80016 | BU80: 154.80016 | BV80: 154.80016 | BW80: 154.80016 | BX80: 154.80016 | BY80: 154.80016 | BZ80: 154.80016 | CA80: 154.80016 | CB80: 154.80016 | CC80: 154.80016 | CD80: 154.80016 | CE80: 154.80016 | CF80: 154.80016 | CG80: 154.80016 | CH80: 154.80016 | CI80: 154.80016 | CJ80: 154.80016 | CK80: 154.80016 | CL80: 154.80016
B81: 선순위운영비(실측) | C81: [KRWm] | K81: 625.27708 | L81: 625.3895 | M81: 1606.8735 | N81: 624.94431 | O81: 628.0007 | P81: 628.11256 | Q81: 1609.5891 | R81: 627.66959 | S81: 630.77931 | T81: 630.89061 | U81: 1612.3597 | V81: 630.44987 | W81: 626.11403 | X81: 626.22476 | Y81: 1607.6865 | Z81: 625.78625 | AA81: 629.00596 | AB81: 629.11614 | AC81: 1610.5704 | AD81: 628.67985 | AE81: 626.95627 | AF81: 627.06588 | AG81: 1608.5127 | AH81: 626.63182 | AI81: 629.9661 | AJ81: 630.07515 | AK81: 1611.5146 | AL81: 629.64332 | AM81: 633.03666 | AN81: 633.14515 | AO81: 1614.5772 | AP81: 632.71554 | AQ81: 636.16916 | AR81: 636.27709 | AS81: 1617.7017 | AT81: 635.84971 | AU81: 639.36484 | AV81: 639.4722 | AW81: 1620.8894 | AX81: 639.04705 | AY81: 642.62496 | AZ81: 642.73176 | BA81: 1624.1415 | BB81: 642.30883 | BC81: 645.95081 | BD81: 646.05705 | BE81: 1627.4594 | BF81: 645.63634 | BG81: 649.3437 | BH81: 649.44938 | BI81: 1630.8443 | BJ81: 649.0309 | BK81: 652.80498 | BL81: 652.9101 | BM81: 1634.2976 | BN81: 652.49384 | BO81: 656.33602 | BP81: 656.44057 | BQ81: 1637.8207 | BR81: 656.02654 | BS81: 659.9382 | BT81: 660.04219 | BU81: 1641.4149 | BV81: 659.63039 | BW81: 663.61295 | BX81: 663.71638 | BY81: 1645.0816 | BZ81: 663.3068 | CA81: 667.36173 | CB81: 667.46459 | CC81: 1648.8224 | CD81: 667.05724 | CE81: 671.186 | CF81: 671.28831 | CG81: 1652.6387 | CH81: 670.88318 | CI81: 675.0873 | CJ81: 675.18904 | CK81: 1166.532 | CL81: 674.78614
B82: 후순위운영비(실측) | C82: [KRWm] | K82: 375 | L82: 375 | M82: 375 | N82: 375 | O82: 380.625 | P82: 380.625 | Q82: 380.625 | R82: 380.625 | S82: 386.33437 | T82: 386.33437 | U82: 386.33437 | V82: 386.33437 | W82: 392.12939 | X82: 392.12939 | Y82: 392.12939 | Z82: 392.12939 | AA82: 398.01133 | AB82: 398.01133 | AC82: 398.01133 | AD82: 398.01133 | AE82: 403.9815 | AF82: 403.9815 | AG82: 403.9815 | AH82: 403.9815 | AI82: 410.04122 | AJ82: 410.04122 | AK82: 410.04122 | AL82: 410.04122 | AM82: 416.19184 | AN82: 416.19184 | AO82: 416.19184 | AP82: 416.19184 | AQ82: 422.43472 | AR82: 422.43472 | AS82: 422.43472 | AT82: 422.43472 | AU82: 428.77124 | AV82: 428.77124 | AW82: 428.77124 | AX82: 428.77124 | AY82: 435.20281 | AZ82: 435.20281 | BA82: 435.20281 | BB82: 435.20281 | BC82: 441.73085 | BD82: 441.73085 | BE82: 441.73085 | BF82: 441.73085 | BG82: 448.35681 | BH82: 448.35681 | BI82: 448.35681 | BJ82: 448.35681 | BK82: 455.08217 | BL82: 455.08217 | BM82: 455.08217 | BN82: 455.08217 | BO82: 461.9084 | BP82: 461.9084 | BQ82: 461.9084 | BR82: 461.9084 | BS82: 468.83702 | BT82: 468.83702 | BU82: 468.83702 | BV82: 468.83702 | BW82: 475.86958 | BX82: 475.86958 | BY82: 475.86958 | BZ82: 475.86958 | CA82: 483.00762 | CB82: 483.00762 | CC82: 483.00762 | CD82: 483.00762 | CE82: 490.25274 | CF82: 490.25274 | CG82: 490.25274 | CH82: 490.25274 | CI82: 497.60653 | CJ82: 497.60653 | CK82: 497.60653 | CL82: 497.60653
B83: 복구충당부채 전입액(실측) | C83: [KRWm] | K83: 25 | L83: 25 | M83: 25 | N83: 25 | O83: 25 | P83: 25 | Q83: 25 | R83: 25 | S83: 25 | T83: 25 | U83: 25 | V83: 25 | W83: 25 | X83: 25 | Y83: 25 | Z83: 25 | AA83: 25 | AB83: 25 | AC83: 25 | AD83: 25 | AE83: 25 | AF83: 25 | AG83: 25 | AH83: 25 | AI83: 25 | AJ83: 25 | AK83: 25 | AL83: 25 | AM83: 25 | AN83: 25 | AO83: 25 | AP83: 25 | AQ83: 25 | AR83: 25 | AS83: 25 | AT83: 25 | AU83: 25 | AV83: 25 | AW83: 25 | AX83: 25 | AY83: 25 | AZ83: 25 | BA83: 25 | BB83: 25 | BC83: 25 | BD83: 25 | BE83: 25 | BF83: 25 | BG83: 25 | BH83: 25 | BI83: 25 | BJ83: 25 | BK83: 25 | BL83: 25 | BM83: 25 | BN83: 25 | BO83: 25 | BP83: 25 | BQ83: 25 | BR83: 25 | BS83: 25 | BT83: 25 | BU83: 25 | BV83: 25 | BW83: 25 | BX83: 25 | BY83: 25 | BZ83: 25 | CA83: 25 | CB83: 25 | CC83: 25 | CD83: 25 | CE83: 25 | CF83: 25 | CG83: 25 | CH83: 25 | CI83: 25 | CJ83: 25 | CK83: 25 | CL83: 25
B85: ※ 노란색 셀 = 화면에서 직접 key-in했거나("예시 불러오기"의 실측치 포함) 그에 준하는 입력값(재무모델링 관례). 세금·최저한세·배당가능이익 캡 등 IS(Q)/CF(Q)의 계산 결과는 반복계산·조건부 누적 로직이 얽혀 있어 여기 대상이 아니며 값(baked) 기준입니다.

Sheet Funding
A1: 당진 태양광발전
A2: 자금조달 — 자본금 + 5개 트랜치
B4: 트랜치 조건
B6: 트랜치 | C6: 금액[KRWm] | D6: 투입순서 | E6: 건설금리 | F6: 운영금리 | G6: 거치(yr) | H6: 상환(yr) | I6: 방식 | J6: 상환개시
B7: 자본금 | C7: ='입력값'!C9*100
B8: 선순위A | C8: ='입력값'!C29*100 | E8: ='입력값'!D29 | F8: ='입력값'!E29 | G8: ='입력값'!F29 | H8: ='입력값'!G29 | I8: ='입력값'!H29 | J8: 2026-09-30
B9: 선순위B | C9: ='입력값'!C30*100 | E9: ='입력값'!D30 | F9: ='입력값'!E30 | G9: ='입력값'!F30 | H9: ='입력값'!G30 | I9: ='입력값'!H30 | J9: 2026-09-30
B10: 선순위C | C10: ='입력값'!C31*100 | E10: ='입력값'!D31 | F10: ='입력값'!E31 | G10: ='입력값'!F31 | H10: ='입력값'!G31 | I10: ='입력값'!H31 | J10: 2026-09-30
B11: 선순위D | C11: ='입력값'!C32*100 | E11: ='입력값'!D32 | F11: ='입력값'!E32 | G11: ='입력값'!F32 | H11: ='입력값'!G32 | I11: ='입력값'!H32 | J11: -
B12: 후순위 | C12: ='입력값'!C33*100 | E12: ='입력값'!D33 | F12: ='입력값'!E33 | G12: ='입력값'!F33 | H12: ='입력값'!G33 | I12: ='입력값'!H33 | J12: -
B13: 차입금 합계 | C13: =C8+C9+C10+C11+C12
B15: 건설이자(IDC)
B17: IDC 합계[KRWm] | C17: 3931.1785
B18: 총투자비(TIC)[KRWm] | C18: 145000
B19: 총사업비(건설이자 제외)[KRWm] | C19: ='입력값'!C8*100
B21: 총사업비 세부내역
B23: 항목 | C23: 금액[KRWm]
B24: ='입력값'!B46
B25: ='입력값'!B47
B26: ='입력값'!B48
B27: ='입력값'!B49
B28: ='입력값'!B50
B29: ='입력값'!B51
B30: ='입력값'!B52
B31: ='입력값'!B53
B32: ='입력값'!B54
B33: ='입력값'!B55
B34: ='입력값'!B56
B35: ='입력값'!B57
B36: 합계 | C36: ='입력값'!C8*100

Sheet Debt
A1: 당진 태양광발전
A2: 차입금 상환 스케줄 — 트랜치별 + 합계
B4: 트랜치별 인출/상환 + 전체 합계
B6: 구 분 | C6: unit | D6: 합 계 | E6: 2024-06-30 | F6: 2024-09-30 | G6: 2024-12-31 | H6: 2025-03-31 | I6: 2025-06-30 | J6: 2025-09-30 | K6: 2025-12-31 | L6: 2026-03-31 | M6: 2026-06-30 | N6: 2026-09-30 | O6: 2026-12-31 | P6: 2027-03-31 | Q6: 2027-06-30 | R6: 2027-09-30 | S6: 2027-12-31 | T6: 2028-03-31 | U6: 2028-06-30 | V6: 2028-09-30 | W6: 2028-12-31 | X6: 2029-03-31 | Y6: 2029-06-30 | Z6: 2029-09-30 | AA6: 2029-12-31 | AB6: 2030-03-31 | AC6: 2030-06-30 | AD6: 2030-09-30 | AE6: 2030-12-31 | AF6: 2031-03-31 | AG6: 2031-06-30 | AH6: 2031-09-30 | AI6: 2031-12-31 | AJ6: 2032-03-31 | AK6: 2032-06-30 | AL6: 2032-09-30 | AM6: 2032-12-31 | AN6: 2033-03-31 | AO6: 2033-06-30 | AP6: 2033-09-30 | AQ6: 2033-12-31 | AR6: 2034-03-31 | AS6: 2034-06-30 | AT6: 2034-09-30 | AU6: 2034-12-31 | AV6: 2035-03-31 | AW6: 2035-06-30 | AX6: 2035-09-30 | AY6: 2035-12-31 | AZ6: 2036-03-31 | BA6: 2036-06-30 | BB6: 2036-09-30 | BC6: 2036-12-31 | BD6: 2037-03-31 | BE6: 2037-06-30 | BF6: 2037-09-30 | BG6: 2037-12-31 | BH6: 2038-03-31 | BI6: 2038-06-30 | BJ6: 2038-09-30 | BK6: 2038-12-31 | BL6: 2039-03-31 | BM6: 2039-06-30 | BN6: 2039-09-30 | BO6: 2039-12-31 | BP6: 2040-03-31 | BQ6: 2040-06-30 | BR6: 2040-09-30 | BS6: 2040-12-31 | BT6: 2041-03-31 | BU6: 2041-06-30 | BV6: 2041-09-30 | BW6: 2041-12-31 | BX6: 2042-03-31 | BY6: 2042-06-30 | BZ6: 2042-09-30 | CA6: 2042-12-31 | CB6: 2043-03-31 | CC6: 2043-06-30 | CD6: 2043-09-30 | CE6: 2043-12-31 | CF6: 2044-03-31 | CG6: 2044-06-30 | CH6: 2044-09-30 | CI6: 2044-12-31 | CJ6: 2045-03-31 | CK6: 2045-06-30 | CL6: 2045-09-30
B8: 선순위A
B9: 기초잔액 | C9: [KRWm] | E9: 0 | F9: =E14 | G9: =F14 | H9: =G14 | I9: =H14 | J9: =I14 | K9: =J14 | L9: =K14 | M9: =L14 | ... CL9: =CK14
B10: 인출 | C10: [KRWm] | D10: =SUM(E10:CL10) | E10: 9935.1614 | F10: 5714.3708 | G10: 11330.803 | H10: 11493.863 | I10: 11525.802 | J10: 0 | K10: 0 | L10: 0 | M10: 0 | N10: 0 | O10: 0 | P10: 0 | Q10: 0 | R10: 0 | S10: 0 | T10: 0 | U10: 0 | V10: 0 | W10: 0 | X10: 0 | Y10: 0 | Z10: 0 | AA10: 0 | AB10: 0 | AC10: 0 | AD10: 0 | AE10: 0 | AF10: 0 | AG10: 0 | AH10: 0 | AI10: 0 | AJ10: 0 | AK10: 0 | AL10: 0 | AM10: 0 | AN10: 0 | AO10: 0 | AP10: 0 | AQ10: 0 | AR10: 0 | AS10: 0 | AT10: 0 | AU10: 0 | AV10: 0 | AW10: 0 | AX10: 0 | AY10: 0 | AZ10: 0 | BA10: 0 | BB10: 0 | BC10: 0 | BD10: 0 | BE10: 0 | BF10: 0 | BG10: 0 | BH10: 0 | BI10: 0 | BJ10: 0 | BK10: 0 | BL10: 0 | BM10: 0 | BN10: 0 | BO10: 0 | BP10: 0 | BQ10: 0 | BR10: 0 | BS10: 0 | BT10: 0 | BU10: 0 | BV10: 0 | BW10: 0 | BX10: 0 | BY10: 0 | BZ10: 0 | CA10: 0 | CB10: 0 | CC10: 0 | CD10: 0 | CE10: 0 | CF10: 0 | CG10: 0 | CH10: 0 | CI10: 0 | CJ10: 0 | CK10: 0 | CL10: 0
B11: 건설이자(IDC) | C11: [KRWm] | D11: =SUM(E11:CL11) | E11: 0 | F11: 139.09226 | G11: 219.09345 | H11: 377.72469 | I11: 538.63878 | J11: 700 | K11: 0 | L11: 0 | M11: 0 | N11: 0 | O11: 0 | P11: 0 | Q11: 0 | R11: 0 | S11: 0 | T11: 0 | U11: 0 | V11: 0 | W11: 0 | X11: 0 | Y11: 0 | Z11: 0 | AA11: 0 | AB11: 0 | AC11: 0 | AD11: 0 | AE11: 0 | AF11: 0 | AG11: 0 | AH11: 0 | AI11: 0 | AJ11: 0 | AK11: 0 | AL11: 0 | AM11: 0 | AN11: 0 | AO11: 0 | AP11: 0 | AQ11: 0 | AR11: 0 | AS11: 0 | AT11: 0 | AU11: 0 | AV11: 0 | AW11: 0 | AX11: 0 | AY11: 0 | AZ11: 0 | BA11: 0 | BB11: 0 | BC11: 0 | BD11: 0 | BE11: 0 | BF11: 0 | BG11: 0 | BH11: 0 | BI11: 0 | BJ11: 0 | BK11: 0 | BL11: 0 | BM11: 0 | BN11: 0 | BO11: 0 | BP11: 0 | BQ11: 0 | BR11: 0 | BS11: 0 | BT11: 0 | BU11: 0 | BV11: 0 | BW11: 0 | BX11: 0 | BY11: 0 | BZ11: 0 | CA11: 0 | CB11: 0 | CC11: 0 | CD11: 0 | CE11: 0 | CF11: 0 | CG11: 0 | CH11: 0 | CI11: 0 | CJ11: 0 | CK11: 0 | CL11: 0
B12: 이자(운영) | C12: [KRWm] | D12: =SUM(E12:CL12) | E12: 0 | F12: 0 | G12: 0 | H12: 0 | I12: 0 | J12: 0 | K12: =K9*'입력값'!E29/4 | L12: =L9*'입력값'!E29/4 | M12: =M9*'입력값'!E29/4 | N12: =N9*'입력값'!E29/4 | O12: =O9*'입력값'!E29/4 | P12: =P9*'입력값'!E29/4 | Q12: =Q9*'입력값'!E29/4 | R12: =R9*'입력값'!E29/4 | S12: =S9*'입력값'!E29/4 | T12: =T9*'입력값'!E29/4 | U12: =U9*'입력값'!E29/4 | V12: =V9*'입력값'!E29/4 | W12: =W9*'입력값'!E29/4 | X12: =X9*'입력값'!E29/4 | Y12: =Y9*'입력값'!E29/4 | Z12: =Z9*'입력값'!E29/4 | AA12: =AA9*'입력값'!E29/4 | AB12: =AB9*'입력값'!E29/4 | AC12: =AC9*'입력값'!E29/4 | AD12: =AD9*'입력값'!E29/4 | AE12: =AE9*'입력값'!E29/4 | AF12: =AF9*'입력값'!E29/4 | AG12: =AG9*'입력값'!E29/4 | AH12: =AH9*'입력값'!E29/4 | AI12: =AI9*'입력값'!E29/4 | AJ12: =AJ9*'입력값'!E29/4 | AK12: =AK9*'입력값'!E29/4 | AL12: =AL9*'입력값'!E29/4 | AM12: =AM9*'입력값'!E29/4 | AN12: =AN9*'입력값'!E29/4 | AO12: =AO9*'입력값'!E29/4 | AP12: =AP9*'입력값'!E29/4 | AQ12: =AQ9*'입력값'!E29/4 | AR12: =AR9*'입력값'!E29/4 | AS12: =AS9*'입력값'!E29/4 | AT12: =AT9*'입력값'!E29/4 | AU12: =AU9*'입력값'!E29/4 | AV12: =AV9*'입력값'!E29/4 | AW12: =AW9*'입력값'!E29/4 | AX12: =AX9*'입력값'!E29/4 | AY12: =AY9*'입력값'!E29/4 | AZ12: =AZ9*'입력값'!E29/4 | BA12: =BA9*'입력값'!E29/4 | BB12: =BB9*'입력값'!E29/4 | BC12: =BC9*'입력값'!E29/4 | BD12: =BD9*'입력값'!E29/4 | BE12: =BE9*'입력값'!E29/4 | BF12: =BF9*'입력값'!E29/4 | BG12: =BG9*'입력값'!E29/4 | BH12: =BH9*'입력값'!E29/4 | BI12: =BI9*'입력값'!E29/4 | BJ12: =BJ9*'입력값'!E29/4 | BK12: =BK9*'입력값'!E29/4 | BL12: =BL9*'입력값'!E29/4 | BM12: =BM9*'입력값'!E29/4 | BN12: =BN9*'입력값'!E29/4 | BO12: =BO9*'입력값'!E29/4 | BP12: =BP9*'입력값'!E29/4 | BQ12: =BQ9*'입력값'!E29/4 | BR12: =BR9*'입력값'!E29/4 | BS12: =BS9*'입력값'!E29/4 | BT12: =BT9*'입력값'!E29/4 | BU12: =BU9*'입력값'!E29/4 | BV12: =BV9*'입력값'!E29/4 | BW12: =BW9*'입력값'!E29/4 | BX12: =BX9*'입력값'!E29/4 | BY12: =BY9*'입력값'!E29/4 | BZ12: =BZ9*'입력값'!E29/4 | CA12: =CA9*'입력값'!E29/4 | CB12: =CB9*'입력값'!E29/4 | CC12: =CC9*'입력값'!E29/4 | CD12: =CD9*'입력값'!E29/4 | CE12: =CE9*'입력값'!E29/4 | CF12: =CF9*'입력값'!E29/4 | CG12: =CG9*'입력값'!E29/4 | CH12: =CH9*'입력값'!E29/4 | CI12: =CI9*'입력값'!E29/4 | CJ12: =CJ9*'입력값'!E29/4 | CK12: =CK9*'입력값'!E29/4 | CL12: =CL9*'입력값'!E29/4
B13: 원금상환 | C13: [KRWm] | D13: =SUM(E13:CL13) | E13: 0 | F13: 0 | G13: 0 | H13: 0 | I13: 0 | J13: 0 | K13: 0 | L13: 0 | M13: 0 | N13: ='입력값'!N39*'입력값'!C29*100 | O13: ='입력값'!O39*'입력값'!C29*100 | P13: ='입력값'!P39*'입력값'!C29*100 | Q13: ='입력값'!Q39*'입력값'!C29*100 | R13: ='입력값'!R39*'입력값'!C29*100 | S13: ='입력값'!S39*'입력값'!C29*100 | T13: ='입력값'!T39*'입력값'!C29*100 | U13: ='입력값'!U39*'입력값'!C29*100 | V13: ='입력값'!V39*'입력값'!C29*100 | W13: ='입력값'!W39*'입력값'!C29*100 | X13: ='입력값'!X39*'입력값'!C29*100 | Y13: ='입력값'!Y39*'입력값'!C29*100 | Z13: ='입력값'!Z39*'입력값'!C29*100 | AA13: ='입력값'!AA39*'입력값'!C29*100 | AB13: ='입력값'!AB39*'입력값'!C29*100 | AC13: ='입력값'!AC39*'입력값'!C29*100 | AD13: ='입력값'!AD39*'입력값'!C29*100 | AE13: ='입력값'!AE39*'입력값'!C29*100 | AF13: ='입력값'!AF39*'입력값'!C29*100 | AG13: ='입력값'!AG39*'입력값'!C29*100 | AH13: ='입력값'!AH39*'입력값'!C29*100 | AI13: ='입력값'!AI39*'입력값'!C29*100 | AJ13: ='입력값'!AJ39*'입력값'!C29*100 | AK13: ='입력값'!AK39*'입력값'!C29*100 | AL13: ='입력값'!AL39*'입력값'!C29*100 | AM13: ='입력값'!AM39*'입력값'!C29*100 | AN13: ='입력값'!AN39*'입력값'!C29*100 | AO13: ='입력값'!AO39*'입력값'!C29*100 | AP13: ='입력값'!AP39*'입력값'!C29*100 | AQ13: ='입력값'!AQ39*'입력값'!C29*100 | AR13: ='입력값'!AR39*'입력값'!C29*100 | AS13: ='입력값'!AS39*'입력값'!C29*100 | AT13: ='입력값'!AT39*'입력값'!C29*100 | AU13: ='입력값'!AU39*'입력값'!C29*100 | AV13: ='입력값'!AV39*'입력값'!C29*100 | AW13: ='입력값'!AW39*'입력값'!C29*100 | AX13: ='입력값'!AX39*'입력값'!C29*100 | AY13: ='입력값'!AY39*'입력값'!C29*100 | AZ13: ='입력값'!AZ39*'입력값'!C29*100 | BA13: ='입력값'!BA39*'입력값'!C29*100 | BB13: ='입력값'!BB39*'입력값'!C29*100 | BC13: ='입력값'!BC39*'입력값'!C29*100 | BD13: ='입력값'!BD39*'입력값'!C29*100 | BE13: ='입력값'!BE39*'입력값'!C29*100 | BF13: ='입력값'!BF39*'입력값'!C29*100 | BG13: ='입력값'!BG39*'입력값'!C29*100 | BH13: ='입력값'!BH39*'입력값'!C29*100 | BI13: ='입력값'!BI39*'입력값'!C29*100 | BJ13: ='입력값'!BJ39*'입력값'!C29*100 | BK13: ='입력값'!BK39*'입력값'!C29*100 | BL13: ='입력값'!BL39*'입력값'!C29*100 | BM13: ='입력값'!BM39*'입력값'!C29*100 | BN13: ='입력값'!BN39*'입력값'!C29*100 | BO13: ='입력값'!BO39*'입력값'!C29*100 | BP13: ='입력값'!BP39*'입력값'!C29*100 | BQ13: ='입력값'!BQ39*'입력값'!C29*100 | BR13: ='입력값'!BR39*'입력값'!C29*100 | BS13: ='입력값'!BS39*'입력값'!C29*100 | BT13: ='입력값'!BT39*'입력값'!C29*100 | BU13: ='입력값'!BU39*'입력값'!C29*100 | BV13: ='입력값'!BV39*'입력값'!C29*100 | BW13: ='입력값'!BW39*'입력값'!C29*100 | BX13: ='입력값'!BX39*'입력값'!C29*100 | BY13: ='입력값'!BY39*'입력값'!C29*100 | BZ13: 0 | CA13: 0 | CB13: 0 | CC13: 0 | CD13: 0 | CE13: 0 | CF13: 0 | CG13: 0 | CH13: 0 | CI13: 0 | CJ13: 0 | CK13: 0 | CL13: 0
B14: 기말잔액 | C14: [KRWm] | E14: =E9+E10-E13 | F14: =F9+F10-F13 | G14: =G9+G10-G13 | H14: =H9+H10-H13 | I14: =I9+I10-I13 | J14: =J9+J10-J13 | K14: =K9+K10-K13 | L14: =L9+L10-L13 | ... CL14: =CL9+CL10-CL13
B15: 미상환 잔액(검증용) | C15: [KRWm] | D15: =CL14 | F15: 완전상환 확인 (OK) | H15: ※ 방식 3(직접 키인) — 원금상환은 "입력값" 시트의 상환비율 표를 참조하는 수식
B17: 선순위B
B18: 기초잔액 | C18: [KRWm] | E18: 0 | F18: =E23 | G18: =F23 | H18: =G23 | I18: =H23 | J18: =I23 | K18: =J23 | L18: =K23 | M18: =L23 | ... CL18: =CK23
B19: 인출 | C19: [KRWm] | D19: =SUM(E19:CL19) | E19: 9935.1614 | F19: 5714.3708 | G19: 11330.803 | H19: 11493.863 | I19: 11525.802 | J19: 0 | K19: 0 | L19: 0 | M19: 0 | N19: 0 | O19: 0 | P19: 0 | Q19: 0 | R19: 0 | S19: 0 | T19: 0 | U19: 0 | V19: 0 | W19: 0 | X19: 0 | Y19: 0 | Z19: 0 | AA19: 0 | AB19: 0 | AC19: 0 | AD19: 0 | AE19: 0 | AF19: 0 | AG19: 0 | AH19: 0 | AI19: 0 | AJ19: 0 | AK19: 0 | AL19: 0 | AM19: 0 | AN19: 0 | AO19: 0 | AP19: 0 | AQ19: 0 | AR19: 0 | AS19: 0 | AT19: 0 | AU19: 0 | AV19: 0 | AW19: 0 | AX19: 0 | AY19: 0 | AZ19: 0 | BA19: 0 | BB19: 0 | BC19: 0 | BD19: 0 | BE19: 0 | BF19: 0 | BG19: 0 | BH19: 0 | BI19: 0 | BJ19: 0 | BK19: 0 | BL19: 0 | BM19: 0 | BN19: 0 | BO19: 0 | BP19: 0 | BQ19: 0 | BR19: 0 | BS19: 0 | BT19: 0 | BU19: 0 | BV19: 0 | BW19: 0 | BX19: 0 | BY19: 0 | BZ19: 0 | CA19: 0 | CB19: 0 | CC19: 0 | CD19: 0 | CE19: 0 | CF19: 0 | CG19: 0 | CH19: 0 | CI19: 0 | CJ19: 0 | CK19: 0 | CL19: 0
B20: 건설이자(IDC) | C20: [KRWm] | D20: =SUM(E20:CL20) | E20: 0 | F20: 136.60847 | G20: 215.18107 | H20: 370.97961 | I20: 529.02023 | J20: 687.5 | K20: 0 | L20: 0 | M20: 0 | N20: 0 | O20: 0 | P20: 0 | Q20: 0 | R20: 0 | S20: 0 | T20: 0 | U20: 0 | V20: 0 | W20: 0 | X20: 0 | Y20: 0 | Z20: 0 | AA20: 0 | AB20: 0 | AC20: 0 | AD20: 0 | AE20: 0 | AF20: 0 | AG20: 0 | AH20: 0 | AI20: 0 | AJ20: 0 | AK20: 0 | AL20: 0 | AM20: 0 | AN20: 0 | AO20: 0 | AP20: 0 | AQ20: 0 | AR20: 0 | AS20: 0 | AT20: 0 | AU20: 0 | AV20: 0 | AW20: 0 | AX20: 0 | AY20: 0 | AZ20: 0 | BA20: 0 | BB20: 0 | BC20: 0 | BD20: 0 | BE20: 0 | BF20: 0 | BG20: 0 | BH20: 0 | BI20: 0 | BJ20: 0 | BK20: 0 | BL20: 0 | BM20: 0 | BN20: 0 | BO20: 0 | BP20: 0 | BQ20: 0 | BR20: 0 | BS20: 0 | BT20: 0 | BU20: 0 | BV20: 0 | BW20: 0 | BX20: 0 | BY20: 0 | BZ20: 0 | CA20: 0 | CB20: 0 | CC20: 0 | CD20: 0 | CE20: 0 | CF20: 0 | CG20: 0 | CH20: 0 | CI20: 0 | CJ20: 0 | CK20: 0 | CL20: 0
B21: 이자(운영) | C21: [KRWm] | D21: =SUM(E21:CL21) | E21: 0 | F21: 0 | G21: 0 | H21: 0 | I21: 0 | J21: 0 | K21: =K18*'입력값'!E30/4 | L21: =L18*'입력값'!E30/4 | M21: =M18*'입력값'!E30/4 | N21: =N18*'입력값'!E30/4 | O21: =O18*'입력값'!E30/4 | P21: =P18*'입력값'!E30/4 | Q21: =Q18*'입력값'!E30/4 | R21: =R18*'입력값'!E30/4 | S21: =S18*'입력값'!E30/4 | T21: =T18*'입력값'!E30/4 | U21: =U18*'입력값'!E30/4 | V21: =V18*'입력값'!E30/4 | W21: =W18*'입력값'!E30/4 | X21: =X18*'입력값'!E30/4 | Y21: =Y18*'입력값'!E30/4 | Z21: =Z18*'입력값'!E30/4 | AA21: =AA18*'입력값'!E30/4 | AB21: =AB18*'입력값'!E30/4 | AC21: =AC18*'입력값'!E30/4 | AD21: =AD18*'입력값'!E30/4 | AE21: =AE18*'입력값'!E30/4 | AF21: =AF18*'입력값'!E30/4 | AG21: =AG18*'입력값'!E30/4 | AH21: =AH18*'입력값'!E30/4 | AI21: =AI18*'입력값'!E30/4 | AJ21: =AJ18*'입력값'!E30/4 | AK21: =AK18*'입력값'!E30/4 | AL21: =AL18*'입력값'!E30/4 | AM21: =AM18*'입력값'!E30/4 | AN21: =AN18*'입력값'!E30/4 | AO21: =AO18*'입력값'!E30/4 | AP21: =AP18*'입력값'!E30/4 | AQ21: =AQ18*'입력값'!E30/4 | AR21: =AR18*'입력값'!E30/4 | AS21: =AS18*'입력값'!E30/4 | AT21: =AT18*'입력값'!E30/4 | AU21: =AU18*'입력값'!E30/4 | AV21: =AV18*'입력값'!E30/4 | AW21: =AW18*'입력값'!E30/4 | AX21: =AX18*'입력값'!E30/4 | AY21: =AY18*'입력값'!E30/4 | AZ21: =AZ18*'입력값'!E30/4 | BA21: =BA18*'입력값'!E30/4 | BB21: =BB18*'입력값'!E30/4 | BC21: =BC18*'입력값'!E30/4 | BD21: =BD18*'입력값'!E30/4 | BE21: =BE18*'입력값'!E30/4 | BF21: =BF18*'입력값'!E30/4 | BG21: =BG18*'입력값'!E30/4 | BH21: =BH18*'입력값'!E30/4 | BI21: =BI18*'입력값'!E30/4 | BJ21: =BJ18*'입력값'!E30/4 | BK21: =BK18*'입력값'!E30/4 | BL21: =BL18*'입력값'!E30/4 | BM21: =BM18*'입력값'!E30/4 | BN21: =BN18*'입력값'!E30/4 | BO21: =BO18*'입력값'!E30/4 | BP21: =BP18*'입력값'!E30/4 | BQ21: =BQ18*'입력값'!E30/4 | BR21: =BR18*'입력값'!E30/4 | BS21: =BS18*'입력값'!E30/4 | BT21: =BT18*'입력값'!E30/4 | BU21: =BU18*'입력값'!E30/4 | BV21: =BV18*'입력값'!E30/4 | BW21: =BW18*'입력값'!E30/4 | BX21: =BX18*'입력값'!E30/4 | BY21: =BY18*'입력값'!E30/4 | BZ21: =BZ18*'입력값'!E30/4 | CA21: =CA18*'입력값'!E30/4 | CB21: =CB18*'입력값'!E30/4 | CC21: =CC18*'입력값'!E30/4 | CD21: =CD18*'입력값'!E30/4 | CE21: =CE18*'입력값'!E30/4 | CF21: =CF18*'입력값'!E30/4 | CG21: =CG18*'입력값'!E30/4 | CH21: =CH18*'입력값'!E30/4 | CI21: =CI18*'입력값'!E30/4 | CJ21: =CJ18*'입력값'!E30/4 | CK21: =CK18*'입력값'!E30/4 | CL21: =CL18*'입력값'!E30/4
B22: 원금상환 | C22: [KRWm] | D22: =SUM(E22:CL22) | E22: 0 | F22: 0 | G22: 0 | H22: 0 | I22: 0 | J22: 0 | K22: 0 | L22: 0 | M22: 0 | N22: ='입력값'!N40*'입력값'!C30*100 | O22: ='입력값'!O40*'입력값'!C30*100 | P22: ='입력값'!P40*'입력값'!C30*100 | Q22: ='입력값'!Q40*'입력값'!C30*100 | R22: ='입력값'!R40*'입력값'!C30*100 | S22: ='입력값'!S40*'입력값'!C30*100 | T22: ='입력값'!T40*'입력값'!C30*100 | U22: ='입력값'!U40*'입력값'!C30*100 | V22: ='입력값'!V40*'입력값'!C30*100 | W22: ='입력값'!W40*'입력값'!C30*100 | X22: ='입력값'!X40*'입력값'!C30*100 | Y22: ='입력값'!Y40*'입력값'!C30*100 | Z22: ='입력값'!Z40*'입력값'!C30*100 | AA22: ='입력값'!AA40*'입력값'!C30*100 | AB22: ='입력값'!AB40*'입력값'!C30*100 | AC22: ='입력값'!AC40*'입력값'!C30*100 | AD22: ='입력값'!AD40*'입력값'!C30*100 | AE22: ='입력값'!AE40*'입력값'!C30*100 | AF22: ='입력값'!AF40*'입력값'!C30*100 | AG22: ='입력값'!AG40*'입력값'!C30*100 | AH22: ='입력값'!AH40*'입력값'!C30*100 | AI22: ='입력값'!AI40*'입력값'!C30*100 | AJ22: ='입력값'!AJ40*'입력값'!C30*100 | AK22: ='입력값'!AK40*'입력값'!C30*100 | AL22: ='입력값'!AL40*'입력값'!C30*100 | AM22: ='입력값'!AM40*'입력값'!C30*100 | AN22: ='입력값'!AN40*'입력값'!C30*100 | AO22: ='입력값'!AO40*'입력값'!C30*100 | AP22: ='입력값'!AP40*'입력값'!C30*100 | AQ22: ='입력값'!AQ40*'입력값'!C30*100 | AR22: ='입력값'!AR40*'입력값'!C30*100 | AS22: ='입력값'!AS40*'입력값'!C30*100 | AT22: ='입력값'!AT40*'입력값'!C30*100 | AU22: ='입력값'!AU40*'입력값'!C30*100 | AV22: ='입력값'!AV40*'입력값'!C30*100 | AW22: ='입력값'!AW40*'입력값'!C30*100 | AX22: ='입력값'!AX40*'입력값'!C30*100 | AY22: ='입력값'!AY40*'입력값'!C30*100 | AZ22: ='입력값'!AZ40*'입력값'!C30*100 | BA22: ='입력값'!BA40*'입력값'!C30*100 | BB22: ='입력값'!BB40*'입력값'!C30*100 | BC22: ='입력값'!BC40*'입력값'!C30*100 | BD22: ='입력값'!BD40*'입력값'!C30*100 | BE22: ='입력값'!BE40*'입력값'!C30*100 | BF22: ='입력값'!BF40*'입력값'!C30*100 | BG22: ='입력값'!BG40*'입력값'!C30*100 | BH22: ='입력값'!BH40*'입력값'!C30*100 | BI22: ='입력값'!BI40*'입력값'!C30*100 | BJ22: ='입력값'!BJ40*'입력값'!C30*100 | BK22: ='입력값'!BK40*'입력값'!C30*100 | BL22: ='입력값'!BL40*'입력값'!C30*100 | BM22: ='입력값'!BM40*'입력값'!C30*100 | BN22: ='입력값'!BN40*'입력값'!C30*100 | BO22: ='입력값'!BO40*'입력값'!C30*100 | BP22: ='입력값'!BP40*'입력값'!C30*100 | BQ22: ='입력값'!BQ40*'입력값'!C30*100 | BR22: ='입력값'!BR40*'입력값'!C30*100 | BS22: ='입력값'!BS40*'입력값'!C30*100 | BT22: ='입력값'!BT40*'입력값'!C30*100 | BU22: ='입력값'!BU40*'입력값'!C30*100 | BV22: ='입력값'!BV40*'입력값'!C30*100 | BW22: ='입력값'!BW40*'입력값'!C30*100 | BX22: ='입력값'!BX40*'입력값'!C30*100 | BY22: ='입력값'!BY40*'입력값'!C30*100 | BZ22: 0 | CA22: 0 | CB22: 0 | CC22: 0 | CD22: 0 | CE22: 0 | CF22: 0 | CG22: 0 | CH22: 0 | CI22: 0 | CJ22: 0 | CK22: 0 | CL22: 0
B23: 기말잔액 | C23: [KRWm] | E23: =E18+E19-E22 | F23: =F18+F19-F22 | G23: =G18+G19-G22 | H23: =H18+H19-H22 | I23: =I18+I19-I22 | J23: =J18+J19-J22 | K23: =K18+K19-K22 | L23: =L18+L19-L22 | ... CL23: =CL18+CL19-CL22
B24: 미상환 잔액(검증용) | C24: [KRWm] | D24: =CL23 | F24: 완전상환 확인 (OK) | H24: ※ 방식 3(직접 키인) — 원금상환은 "입력값" 시트의 상환비율 표를 참조하는 수식
B26: 선순위C
B27: 기초잔액 | C27: [KRWm] | E27: 0 | F27: =E32 | G27: =F32 | H27: =G32 | I27: =H32 | J27: =I32 | K27: =J32 | L27: =K32 | M27: =L32 | ... CL27: =CK32
B28: 인출 | C28: [KRWm] | D28: =SUM(E28:CL28) | E28: 0 | F28: 0 | G28: 0 | H28: 0 | I28: 1261.0874 | J28: 33738.912 | K28: 0 | L28: 0 | M28: 0 | N28: 0 | O28: 0 | P28: 0 | Q28: 0 | R28: 0 | S28: 0 | T28: 0 | U28: 0 | V28: 0 | W28: 0 | X28: 0 | Y28: 0 | Z28: 0 | AA28: 0 | AB28: 0 | AC28: 0 | AD28: 0 | AE28: 0 | AF28: 0 | AG28: 0 | AH28: 0 | AI28: 0 | AJ28: 0 | AK28: 0 | AL28: 0 | AM28: 0 | AN28: 0 | AO28: 0 | AP28: 0 | AQ28: 0 | AR28: 0 | AS28: 0 | AT28: 0 | AU28: 0 | AV28: 0 | AW28: 0 | AX28: 0 | AY28: 0 | AZ28: 0 | BA28: 0 | BB28: 0 | BC28: 0 | BD28: 0 | BE28: 0 | BF28: 0 | BG28: 0 | BH28: 0 | BI28: 0 | BJ28: 0 | BK28: 0 | BL28: 0 | BM28: 0 | BN28: 0 | BO28: 0 | BP28: 0 | BQ28: 0 | BR28: 0 | BS28: 0 | BT28: 0 | BU28: 0 | BV28: 0 | BW28: 0 | BX28: 0 | BY28: 0 | BZ28: 0 | CA28: 0 | CB28: 0 | CC28: 0 | CD28: 0 | CE28: 0 | CF28: 0 | CG28: 0 | CH28: 0 | CI28: 0 | CJ28: 0 | CK28: 0 | CL28: 0
B29: 건설이자(IDC) | C29: [KRWm] | D29: =SUM(E29:CL29) | E29: 0 | F29: 0 | G29: 0 | H29: 0 | I29: 0 | J29: 17.339952 | K29: 0 | L29: 0 | M29: 0 | N29: 0 | O29: 0 | P29: 0 | Q29: 0 | R29: 0 | S29: 0 | T29: 0 | U29: 0 | V29: 0 | W29: 0 | X29: 0 | Y29: 0 | Z29: 0 | AA29: 0 | AB29: 0 | AC29: 0 | AD29: 0 | AE29: 0 | AF29: 0 | AG29: 0 | AH29: 0 | AI29: 0 | AJ29: 0 | AK29: 0 | AL29: 0 | AM29: 0 | AN29: 0 | AO29: 0 | AP29: 0 | AQ29: 0 | AR29: 0 | AS29: 0 | AT29: 0 | AU29: 0 | AV29: 0 | AW29: 0 | AX29: 0 | AY29: 0 | AZ29: 0 | BA29: 0 | BB29: 0 | BC29: 0 | BD29: 0 | BE29: 0 | BF29: 0 | BG29: 0 | BH29: 0 | BI29: 0 | BJ29: 0 | BK29: 0 | BL29: 0 | BM29: 0 | BN29: 0 | BO29: 0 | BP29: 0 | BQ29: 0 | BR29: 0 | BS29: 0 | BT29: 0 | BU29: 0 | BV29: 0 | BW29: 0 | BX29: 0 | BY29: 0 | BZ29: 0 | CA29: 0 | CB29: 0 | CC29: 0 | CD29: 0 | CE29: 0 | CF29: 0 | CG29: 0 | CH29: 0 | CI29: 0 | CJ29: 0 | CK29: 0 | CL29: 0
B30: 이자(운영) | C30: [KRWm] | D30: =SUM(E30:CL30) | E30: 0 | F30: 0 | G30: 0 | H30: 0 | I30: 0 | J30: 0 | K30: =K27*'입력값'!E31/4 | L30: =L27*'입력값'!E31/4 | M30: =M27*'입력값'!E31/4 | N30: =N27*'입력값'!E31/4 | O30: =O27*'입력값'!E31/4 | P30: =P27*'입력값'!E31/4 | Q30: =Q27*'입력값'!E31/4 | R30: =R27*'입력값'!E31/4 | S30: =S27*'입력값'!E31/4 | T30: =T27*'입력값'!E31/4 | U30: =U27*'입력값'!E31/4 | V30: =V27*'입력값'!E31/4 | W30: =W27*'입력값'!E31/4 | X30: =X27*'입력값'!E31/4 | Y30: =Y27*'입력값'!E31/4 | Z30: =Z27*'입력값'!E31/4 | AA30: =AA27*'입력값'!E31/4 | AB30: =AB27*'입력값'!E31/4 | AC30: =AC27*'입력값'!E31/4 | AD30: =AD27*'입력값'!E31/4 | AE30: =AE27*'입력값'!E31/4 | AF30: =AF27*'입력값'!E31/4 | AG30: =AG27*'입력값'!E31/4 | AH30: =AH27*'입력값'!E31/4 | AI30: =AI27*'입력값'!E31/4 | AJ30: =AJ27*'입력값'!E31/4 | AK30: =AK27*'입력값'!E31/4 | AL30: =AL27*'입력값'!E31/4 | AM30: =AM27*'입력값'!E31/4 | AN30: =AN27*'입력값'!E31/4 | AO30: =AO27*'입력값'!E31/4 | AP30: =AP27*'입력값'!E31/4 | AQ30: =AQ27*'입력값'!E31/4 | AR30: =AR27*'입력값'!E31/4 | AS30: =AS27*'입력값'!E31/4 | AT30: =AT27*'입력값'!E31/4 | AU30: =AU27*'입력값'!E31/4 | AV30: =AV27*'입력값'!E31/4 | AW30: =AW27*'입력값'!E31/4 | AX30: =AX27*'입력값'!E31/4 | AY30: =AY27*'입력값'!E31/4 | AZ30: =AZ27*'입력값'!E31/4 | BA30: =BA27*'입력값'!E31/4 | BB30: =BB27*'입력값'!E31/4 | BC30: =BC27*'입력값'!E31/4 | BD30: =BD27*'입력값'!E31/4 | BE30: =BE27*'입력값'!E31/4 | BF30: =BF27*'입력값'!E31/4 | BG30: =BG27*'입력값'!E31/4 | BH30: =BH27*'입력값'!E31/4 | BI30: =BI27*'입력값'!E31/4 | BJ30: =BJ27*'입력값'!E31/4 | BK30: =BK27*'입력값'!E31/4 | BL30: =BL27*'입력값'!E31/4 | BM30: =BM27*'입력값'!E31/4 | BN30: =BN27*'입력값'!E31/4 | BO30: =BO27*'입력값'!E31/4 | BP30: =BP27*'입력값'!E31/4 | BQ30: =BQ27*'입력값'!E31/4 | BR30: =BR27*'입력값'!E31/4 | BS30: =BS27*'입력값'!E31/4 | BT30: =BT27*'입력값'!E31/4 | BU30: =BU27*'입력값'!E31/4 | BV30: =BV27*'입력값'!E31/4 | BW30: =BW27*'입력값'!E31/4 | BX30: =BX27*'입력값'!E31/4 | BY30: =BY27*'입력값'!E31/4 | BZ30: =BZ27*'입력값'!E31/4 | CA30: =CA27*'입력값'!E31/4 | CB30: =CB27*'입력값'!E31/4 | CC30: =CC27*'입력값'!E31/4 | CD30: =CD27*'입력값'!E31/4 | CE30: =CE27*'입력값'!E31/4 | CF30: =CF27*'입력값'!E31/4 | CG30: =CG27*'입력값'!E31/4 | CH30: =CH27*'입력값'!E31/4 | CI30: =CI27*'입력값'!E31/4 | CJ30: =CJ27*'입력값'!E31/4 | CK30: =CK27*'입력값'!E31/4 | CL30: =CL27*'입력값'!E31/4
B31: 원금상환 | C31: [KRWm] | D31: =SUM(E31:CL31) | E31: 0 | F31: 0 | G31: 0 | H31: 0 | I31: 0 | J31: 0 | K31: 0 | L31: 0 | M31: 0 | N31: ='입력값'!N41*'입력값'!C31*100 | O31: ='입력값'!O41*'입력값'!C31*100 | P31: ='입력값'!P41*'입력값'!C31*100 | Q31: ='입력값'!Q41*'입력값'!C31*100 | R31: ='입력값'!R41*'입력값'!C31*100 | S31: ='입력값'!S41*'입력값'!C31*100 | T31: ='입력값'!T41*'입력값'!C31*100 | U31: ='입력값'!U41*'입력값'!C31*100 | V31: ='입력값'!V41*'입력값'!C31*100 | W31: ='입력값'!W41*'입력값'!C31*100 | X31: ='입력값'!X41*'입력값'!C31*100 | Y31: ='입력값'!Y41*'입력값'!C31*100 | Z31: ='입력값'!Z41*'입력값'!C31*100 | AA31: ='입력값'!AA41*'입력값'!C31*100 | AB31: ='입력값'!AB41*'입력값'!C31*100 | AC31: ='입력값'!AC41*'입력값'!C31*100 | AD31: ='입력값'!AD41*'입력값'!C31*100 | AE31: ='입력값'!AE41*'입력값'!C31*100 | AF31: ='입력값'!AF41*'입력값'!C31*100 | AG31: ='입력값'!AG41*'입력값'!C31*100 | AH31: ='입력값'!AH41*'입력값'!C31*100 | AI31: ='입력값'!AI41*'입력값'!C31*100 | AJ31: ='입력값'!AJ41*'입력값'!C31*100 | AK31: ='입력값'!AK41*'입력값'!C31*100 | AL31: ='입력값'!AL41*'입력값'!C31*100 | AM31: ='입력값'!AM41*'입력값'!C31*100 | AN31: ='입력값'!AN41*'입력값'!C31*100 | AO31: ='입력값'!AO41*'입력값'!C31*100 | AP31: ='입력값'!AP41*'입력값'!C31*100 | AQ31: ='입력값'!AQ41*'입력값'!C31*100 | AR31: ='입력값'!AR41*'입력값'!C31*100 | AS31: ='입력값'!AS41*'입력값'!C31*100 | AT31: ='입력값'!AT41*'입력값'!C31*100 | AU31: ='입력값'!AU41*'입력값'!C31*100 | AV31: ='입력값'!AV41*'입력값'!C31*100 | AW31: ='입력값'!AW41*'입력값'!C31*100 | AX31: ='입력값'!AX41*'입력값'!C31*100 | AY31: ='입력값'!AY41*'입력값'!C31*100 | AZ31: ='입력값'!AZ41*'입력값'!C31*100 | BA31: ='입력값'!BA41*'입력값'!C31*100 | BB31: ='입력값'!BB41*'입력값'!C31*100 | BC31: ='입력값'!BC41*'입력값'!C31*100 | BD31: ='입력값'!BD41*'입력값'!C31*100 | BE31: ='입력값'!BE41*'입력값'!C31*100 | BF31: ='입력값'!BF41*'입력값'!C31*100 | BG31: ='입력값'!BG41*'입력값'!C31*100 | BH31: ='입력값'!BH41*'입력값'!C31*100 | BI31: ='입력값'!BI41*'입력값'!C31*100 | BJ31: ='입력값'!BJ41*'입력값'!C31*100 | BK31: ='입력값'!BK41*'입력값'!C31*100 | BL31: ='입력값'!BL41*'입력값'!C31*100 | BM31: ='입력값'!BM41*'입력값'!C31*100 | BN31: ='입력값'!BN41*'입력값'!C31*100 | BO31: ='입력값'!BO41*'입력값'!C31*100 | BP31: ='입력값'!BP41*'입력값'!C31*100 | BQ31: ='입력값'!BQ41*'입력값'!C31*100 | BR31: ='입력값'!BR41*'입력값'!C31*100 | BS31: ='입력값'!BS41*'입력값'!C31*100 | BT31: ='입력값'!BT41*'입력값'!C31*100 | BU31: ='입력값'!BU41*'입력값'!C31*100 | BV31: ='입력값'!BV41*'입력값'!C31*100 | BW31: ='입력값'!BW41*'입력값'!C31*100 | BX31: ='입력값'!BX41*'입력값'!C31*100 | BY31: ='입력값'!BY41*'입력값'!C31*100 | BZ31: 0 | CA31: 0 | CB31: 0 | CC31: 0 | CD31: 0 | CE31: 0 | CF31: 0 | CG31: 0 | CH31: 0 | CI31: 0 | CJ31: 0 | CK31: 0 | CL31: 0
B32: 기말잔액 | C32: [KRWm] | E32: =E27+E28-E31 | F32: =F27+F28-F31 | G32: =G27+G28-G31 | H32: =H27+H28-H31 | I32: =I27+I28-I31 | J32: =J27+J28-J31 | K32: =K27+K28-K31 | L32: =L27+L28-L31 | ... CL32: =CL27+CL28-CL31
B33: 미상환 잔액(검증용) | C33: [KRWm] | D33: =CL32 | F33: 완전상환 확인 (OK) | H33: ※ 방식 3(직접 키인) — 원금상환은 "입력값" 시트의 상환비율 표를 참조하는 수식
B35: 선순위D
B36: 기초잔액 | C36: [KRWm] | E36: 0 | F36: =E41 | G36: =F41 | H36: =G41 | I36: =H41 | J36: =I41 | K36: =J41 | L36: =K41 | M36: =L41 | ... CL36: =CK41
B37: 인출 | C37: [KRWm] | D37: =SUM(E37:CL37) | E37: 0 | F37: 0 | G37: 0 | H37: 0 | I37: 0 | J37: 0 | K37: 0 | L37: 0 | M37: 0 | N37: 0 | O37: 0 | P37: 0 | Q37: 0 | R37: 0 | S37: 0 | T37: 0 | U37: 0 | V37: 0 | W37: 0 | X37: 0 | Y37: 0 | Z37: 0 | AA37: 0 | AB37: 0 | AC37: 0 | AD37: 0 | AE37: 0 | AF37: 0 | AG37: 0 | AH37: 0 | AI37: 0 | AJ37: 0 | AK37: 0 | AL37: 0 | AM37: 0 | AN37: 0 | AO37: 0 | AP37: 0 | AQ37: 0 | AR37: 0 | AS37: 0 | AT37: 0 | AU37: 0 | AV37: 0 | AW37: 0 | AX37: 0 | AY37: 0 | AZ37: 0 | BA37: 0 | BB37: 0 | BC37: 0 | BD37: 0 | BE37: 0 | BF37: 0 | BG37: 0 | BH37: 0 | BI37: 0 | BJ37: 0 | BK37: 0 | BL37: 0 | BM37: 0 | BN37: 0 | BO37: 0 | BP37: 0 | BQ37: 0 | BR37: 0 | BS37: 0 | BT37: 0 | BU37: 0 | BV37: 0 | BW37: 0 | BX37: 0 | BY37: 0 | BZ37: 0 | CA37: 0 | CB37: 0 | CC37: 0 | CD37: 0 | CE37: 0 | CF37: 0 | CG37: 0 | CH37: 0 | CI37: 0 | CJ37: 0 | CK37: 0 | CL37: 0
B38: 건설이자(IDC) | C38: [KRWm] | D38: =SUM(E38:CL38) | E38: 0 | F38: 0 | G38: 0 | H38: 0 | I38: 0 | J38: 0 | K38: 0 | L38: 0 | M38: 0 | N38: 0 | O38: 0 | P38: 0 | Q38: 0 | R38: 0 | S38: 0 | T38: 0 | U38: 0 | V38: 0 | W38: 0 | X38: 0 | Y38: 0 | Z38: 0 | AA38: 0 | AB38: 0 | AC38: 0 | AD38: 0 | AE38: 0 | AF38: 0 | AG38: 0 | AH38: 0 | AI38: 0 | AJ38: 0 | AK38: 0 | AL38: 0 | AM38: 0 | AN38: 0 | AO38: 0 | AP38: 0 | AQ38: 0 | AR38: 0 | AS38: 0 | AT38: 0 | AU38: 0 | AV38: 0 | AW38: 0 | AX38: 0 | AY38: 0 | AZ38: 0 | BA38: 0 | BB38: 0 | BC38: 0 | BD38: 0 | BE38: 0 | BF38: 0 | BG38: 0 | BH38: 0 | BI38: 0 | BJ38: 0 | BK38: 0 | BL38: 0 | BM38: 0 | BN38: 0 | BO38: 0 | BP38: 0 | BQ38: 0 | BR38: 0 | BS38: 0 | BT38: 0 | BU38: 0 | BV38: 0 | BW38: 0 | BX38: 0 | BY38: 0 | BZ38: 0 | CA38: 0 | CB38: 0 | CC38: 0 | CD38: 0 | CE38: 0 | CF38: 0 | CG38: 0 | CH38: 0 | CI38: 0 | CJ38: 0 | CK38: 0 | CL38: 0
B39: 이자(운영) | C39: [KRWm] | D39: =SUM(E39:CL39) | E39: 0 | F39: 0 | G39: 0 | H39: 0 | I39: 0 | J39: 0 | K39: =K36*'입력값'!E32/4 | L39: =L36*'입력값'!E32/4 | M39: =M36*'입력값'!E32/4 | N39: =N36*'입력값'!E32/4 | O39: =O36*'입력값'!E32/4 | P39: =P36*'입력값'!E32/4 | Q39: =Q36*'입력값'!E32/4 | R39: =R36*'입력값'!E32/4 | S39: =S36*'입력값'!E32/4 | T39: =T36*'입력값'!E32/4 | U39: =U36*'입력값'!E32/4 | V39: =V36*'입력값'!E32/4 | W39: =W36*'입력값'!E32/4 | X39: =X36*'입력값'!E32/4 | Y39: =Y36*'입력값'!E32/4 | Z39: =Z36*'입력값'!E32/4 | AA39: =AA36*'입력값'!E32/4 | AB39: =AB36*'입력값'!E32/4 | AC39: =AC36*'입력값'!E32/4 | AD39: =AD36*'입력값'!E32/4 | AE39: =AE36*'입력값'!E32/4 | AF39: =AF36*'입력값'!E32/4 | AG39: =AG36*'입력값'!E32/4 | AH39: =AH36*'입력값'!E32/4 | AI39: =AI36*'입력값'!E32/4 | AJ39: =AJ36*'입력값'!E32/4 | AK39: =AK36*'입력값'!E32/4 | AL39: =AL36*'입력값'!E32/4 | AM39: =AM36*'입력값'!E32/4 | AN39: =AN36*'입력값'!E32/4 | AO39: =AO36*'입력값'!E32/4 | AP39: =AP36*'입력값'!E32/4 | AQ39: =AQ36*'입력값'!E32/4 | AR39: =AR36*'입력값'!E32/4 | AS39: =AS36*'입력값'!E32/4 | AT39: =AT36*'입력값'!E32/4 | AU39: =AU36*'입력값'!E32/4 | AV39: =AV36*'입력값'!E32/4 | AW39: =AW36*'입력값'!E32/4 | AX39: =AX36*'입력값'!E32/4 | AY39: =AY36*'입력값'!E32/4 | AZ39: =AZ36*'입력값'!E32/4 | BA39: =BA36*'입력값'!E32/4 | BB39: =BB36*'입력값'!E32/4 | BC39: =BC36*'입력값'!E32/4 | BD39: =BD36*'입력값'!E32/4 | BE39: =BE36*'입력값'!E32/4 | BF39: =BF36*'입력값'!E32/4 | BG39: =BG36*'입력값'!E32/4 | BH39: =BH36*'입력값'!E32/4 | BI39: =BI36*'입력값'!E32/4 | BJ39: =BJ36*'입력값'!E32/4 | BK39: =BK36*'입력값'!E32/4 | BL39: =BL36*'입력값'!E32/4 | BM39: =BM36*'입력값'!E32/4 | BN39: =BN36*'입력값'!E32/4 | BO39: =BO36*'입력값'!E32/4 | BP39: =BP36*'입력값'!E32/4 | BQ39: =BQ36*'입력값'!E32/4 | BR39: =BR36*'입력값'!E32/4 | BS39: =BS36*'입력값'!E32/4 | BT39: =BT36*'입력값'!E32/4 | BU39: =BU36*'입력값'!E32/4 | BV39: =BV36*'입력값'!E32/4 | BW39: =BW36*'입력값'!E32/4 | BX39: =BX36*'입력값'!E32/4 | BY39: =BY36*'입력값'!E32/4 | BZ39: =BZ36*'입력값'!E32/4 | CA39: =CA36*'입력값'!E32/4 | CB39: =CB36*'입력값'!E32/4 | CC39: =CC36*'입력값'!E32/4 | CD39: =CD36*'입력값'!E32/4 | CE39: =CE36*'입력값'!E32/4 | CF39: =CF36*'입력값'!E32/4 | CG39: =CG36*'입력값'!E32/4 | CH39: =CH36*'입력값'!E32/4 | CI39: =CI36*'입력값'!E32/4 | CJ39: =CJ36*'입력값'!E32/4 | CK39: =CK36*'입력값'!E32/4 | CL39: =CL36*'입력값'!E32/4
B40: 원금상환 | C40: [KRWm] | D40: =SUM(E40:CL40) | E40: 0 | F40: 0 | G40: 0 | H40: 0 | I40: 0 | J40: 0 | K40: 0 | L40: 0 | M40: 0 | N40: 0 | O40: 0 | P40: 0 | Q40: 0 | R40: 0 | S40: 0 | T40: 0 | U40: 0 | V40: 0 | W40: 0 | X40: 0 | Y40: 0 | Z40: 0 | AA40: 0 | AB40: 0 | AC40: 0 | AD40: 0 | AE40: 0 | AF40: 0 | AG40: 0 | AH40: 0 | AI40: 0 | AJ40: 0 | AK40: 0 | AL40: 0 | AM40: 0 | AN40: 0 | AO40: 0 | AP40: 0 | AQ40: 0 | AR40: 0 | AS40: 0 | AT40: 0 | AU40: 0 | AV40: 0 | AW40: 0 | AX40: 0 | AY40: 0 | AZ40: 0 | BA40: 0 | BB40: 0 | BC40: 0 | BD40: 0 | BE40: 0 | BF40: 0 | BG40: 0 | BH40: 0 | BI40: 0 | BJ40: 0 | BK40: 0 | BL40: 0 | BM40: 0 | BN40: 0 | BO40: 0 | BP40: 0 | BQ40: 0 | BR40: 0 | BS40: 0 | BT40: 0 | BU40: 0 | BV40: 0 | BW40: 0 | BX40: 0 | BY40: 0 | BZ40: 0 | CA40: 0 | CB40: 0 | CC40: 0 | CD40: 0 | CE40: 0 | CF40: 0 | CG40: 0 | CH40: 0 | CI40: 0 | CJ40: 0 | CK40: 0 | CL40: 0
B41: 기말잔액 | C41: [KRWm] | E41: =E36+E37-E40 | F41: =F36+F37-F40 | G41: =G36+G37-G40 | H41: =H36+H37-H40 | I41: =I36+I37-I40 | J41: =J36+J37-J40 | K41: =K36+K37-K40 | L41: =L36+L37-L40 | ... CL41: =CL36+CL37-CL40
B42: 미상환 잔액(검증용) | C42: [KRWm] | D42: =CL41 | F42: 완전상환 확인 (OK) | H42: ※ 미사용 트랜치 — 값(baked) 기준
B44: 후순위
B45: 기초잔액 | C45: [KRWm] | E45: 0 | F45: =E50 | G45: =F50 | H45: =G50 | I45: =H50 | J45: =I50 | K45: =J50 | L45: =K50 | M45: =L50 | ... CL45: =CK50
B46: 인출 | C46: [KRWm] | D46: =SUM(E46:CL46) | E46: 0 | F46: 0 | G46: 0 | H46: 0 | I46: 0 | J46: 0 | K46: 0 | L46: 0 | M46: 0 | N46: 0 | O46: 0 | P46: 0 | Q46: 0 | R46: 0 | S46: 0 | T46: 0 | U46: 0 | V46: 0 | W46: 0 | X46: 0 | Y46: 0 | Z46: 0 | AA46: 0 | AB46: 0 | AC46: 0 | AD46: 0 | AE46: 0 | AF46: 0 | AG46: 0 | AH46: 0 | AI46: 0 | AJ46: 0 | AK46: 0 | AL46: 0 | AM46: 0 | AN46: 0 | AO46: 0 | AP46: 0 | AQ46: 0 | AR46: 0 | AS46: 0 | AT46: 0 | AU46: 0 | AV46: 0 | AW46: 0 | AX46: 0 | AY46: 0 | AZ46: 0 | BA46: 0 | BB46: 0 | BC46: 0 | BD46: 0 | BE46: 0 | BF46: 0 | BG46: 0 | BH46: 0 | BI46: 0 | BJ46: 0 | BK46: 0 | BL46: 0 | BM46: 0 | BN46: 0 | BO46: 0 | BP46: 0 | BQ46: 0 | BR46: 0 | BS46: 0 | BT46: 0 | BU46: 0 | BV46: 0 | BW46: 0 | BX46: 0 | BY46: 0 | BZ46: 0 | CA46: 0 | CB46: 0 | CC46: 0 | CD46: 0 | CE46: 0 | CF46: 0 | CG46: 0 | CH46: 0 | CI46: 0 | CJ46: 0 | CK46: 0 | CL46: 0
B47: 건설이자(IDC) | C47: [KRWm] | D47: =SUM(E47:CL47) | E47: 0 | F47: 0 | G47: 0 | H47: 0 | I47: 0 | J47: 0 | K47: 0 | L47: 0 | M47: 0 | N47: 0 | O47: 0 | P47: 0 | Q47: 0 | R47: 0 | S47: 0 | T47: 0 | U47: 0 | V47: 0 | W47: 0 | X47: 0 | Y47: 0 | Z47: 0 | AA47: 0 | AB47: 0 | AC47: 0 | AD47: 0 | AE47: 0 | AF47: 0 | AG47: 0 | AH47: 0 | AI47: 0 | AJ47: 0 | AK47: 0 | AL47: 0 | AM47: 0 | AN47: 0 | AO47: 0 | AP47: 0 | AQ47: 0 | AR47: 0 | AS47: 0 | AT47: 0 | AU47: 0 | AV47: 0 | AW47: 0 | AX47: 0 | AY47: 0 | AZ47: 0 | BA47: 0 | BB47: 0 | BC47: 0 | BD47: 0 | BE47: 0 | BF47: 0 | BG47: 0 | BH47: 0 | BI47: 0 | BJ47: 0 | BK47: 0 | BL47: 0 | BM47: 0 | BN47: 0 | BO47: 0 | BP47: 0 | BQ47: 0 | BR47: 0 | BS47: 0 | BT47: 0 | BU47: 0 | BV47: 0 | BW47: 0 | BX47: 0 | BY47: 0 | BZ47: 0 | CA47: 0 | CB47: 0 | CC47: 0 | CD47: 0 | CE47: 0 | CF47: 0 | CG47: 0 | CH47: 0 | CI47: 0 | CJ47: 0 | CK47: 0 | CL47: 0
B48: 이자(운영) | C48: [KRWm] | D48: =SUM(E48:CL48) | E48: 0 | F48: 0 | G48: 0 | H48: 0 | I48: 0 | J48: 0 | K48: =K45*'입력값'!E33/4 | L48: =L45*'입력값'!E33/4 | M48: =M45*'입력값'!E33/4 | N48: =N45*'입력값'!E33/4 | O48: =O45*'입력값'!E33/4 | P48: =P45*'입력값'!E33/4 | Q48: =Q45*'입력값'!E33/4 | R48: =R45*'입력값'!E33/4 | S48: =S45*'입력값'!E33/4 | T48: =T45*'입력값'!E33/4 | U48: =U45*'입력값'!E33/4 | V48: =V45*'입력값'!E33/4 | W48: =W45*'입력값'!E33/4 | X48: =X45*'입력값'!E33/4 | Y48: =Y45*'입력값'!E33/4 | Z48: =Z45*'입력값'!E33/4 | AA48: =AA45*'입력값'!E33/4 | AB48: =AB45*'입력값'!E33/4 | AC48: =AC45*'입력값'!E33/4 | AD48: =AD45*'입력값'!E33/4 | AE48: =AE45*'입력값'!E33/4 | AF48: =AF45*'입력값'!E33/4 | AG48: =AG45*'입력값'!E33/4 | AH48: =AH45*'입력값'!E33/4 | AI48: =AI45*'입력값'!E33/4 | AJ48: =AJ45*'입력값'!E33/4 | AK48: =AK45*'입력값'!E33/4 | AL48: =AL45*'입력값'!E33/4 | AM48: =AM45*'입력값'!E33/4 | AN48: =AN45*'입력값'!E33/4 | AO48: =AO45*'입력값'!E33/4 | AP48: =AP45*'입력값'!E33/4 | AQ48: =AQ45*'입력값'!E33/4 | AR48: =AR45*'입력값'!E33/4 | AS48: =AS45*'입력값'!E33/4 | AT48: =AT45*'입력값'!E33/4 | AU48: =AU45*'입력값'!E33/4 | AV48: =AV45*'입력값'!E33/4 | AW48: =AW45*'입력값'!E33/4 | AX48: =AX45*'입력값'!E33/4 | AY48: =AY45*'입력값'!E33/4 | AZ48: =AZ45*'입력값'!E33/4 | BA48: =BA45*'입력값'!E33/4 | BB48: =BB45*'입력값'!E33/4 | BC48: =BC45*'입력값'!E33/4 | BD48: =BD45*'입력값'!E33/4 | BE48: =BE45*'입력값'!E33/4 | BF48: =BF45*'입력값'!E33/4 | BG48: =BG45*'입력값'!E33/4 | BH48: =BH45*'입력값'!E33/4 | BI48: =BI45*'입력값'!E33/4 | BJ48: =BJ45*'입력값'!E33/4 | BK48: =BK45*'입력값'!E33/4 | BL48: =BL45*'입력값'!E33/4 | BM48: =BM45*'입력값'!E33/4 | BN48: =BN45*'입력값'!E33/4 | BO48: =BO45*'입력값'!E33/4 | BP48: =BP45*'입력값'!E33/4 | BQ48: =BQ45*'입력값'!E33/4 | BR48: =BR45*'입력값'!E33/4 | BS48: =BS45*'입력값'!E33/4 | BT48: =BT45*'입력값'!E33/4 | BU48: =BU45*'입력값'!E33/4 | BV48: =BV45*'입력값'!E33/4 | BW48: =BW45*'입력값'!E33/4 | BX48: =BX45*'입력값'!E33/4 | BY48: =BY45*'입력값'!E33/4 | BZ48: =BZ45*'입력값'!E33/4 | CA48: =CA45*'입력값'!E33/4 | CB48: =CB45*'입력값'!E33/4 | CC48: =CC45*'입력값'!E33/4 | CD48: =CD45*'입력값'!E33/4 | CE48: =CE45*'입력값'!E33/4 | CF48: =CF45*'입력값'!E33/4 | CG48: =CG45*'입력값'!E33/4 | CH48: =CH45*'입력값'!E33/4 | CI48: =CI45*'입력값'!E33/4 | CJ48: =CJ45*'입력값'!E33/4 | CK48: =CK45*'입력값'!E33/4 | CL48: =CL45*'입력값'!E33/4
B49: 원금상환 | C49: [KRWm] | D49: =SUM(E49:CL49) | E49: 0 | F49: 0 | G49: 0 | H49: 0 | I49: 0 | J49: 0 | K49: 0 | L49: 0 | M49: 0 | N49: 0 | O49: 0 | P49: 0 | Q49: 0 | R49: 0 | S49: 0 | T49: 0 | U49: 0 | V49: 0 | W49: 0 | X49: 0 | Y49: 0 | Z49: 0 | AA49: 0 | AB49: 0 | AC49: 0 | AD49: 0 | AE49: 0 | AF49: 0 | AG49: 0 | AH49: 0 | AI49: 0 | AJ49: 0 | AK49: 0 | AL49: 0 | AM49: 0 | AN49: 0 | AO49: 0 | AP49: 0 | AQ49: 0 | AR49: 0 | AS49: 0 | AT49: 0 | AU49: 0 | AV49: 0 | AW49: 0 | AX49: 0 | AY49: 0 | AZ49: 0 | BA49: 0 | BB49: 0 | BC49: 0 | BD49: 0 | BE49: 0 | BF49: 0 | BG49: 0 | BH49: 0 | BI49: 0 | BJ49: 0 | BK49: 0 | BL49: 0 | BM49: 0 | BN49: 0 | BO49: 0 | BP49: 0 | BQ49: 0 | BR49: 0 | BS49: 0 | BT49: 0 | BU49: 0 | BV49: 0 | BW49: 0 | BX49: 0 | BY49: 0 | BZ49: 0 | CA49: 0 | CB49: 0 | CC49: 0 | CD49: 0 | CE49: 0 | CF49: 0 | CG49: 0 | CH49: 0 | CI49: 0 | CJ49: 0 | CK49: 0 | CL49: 0
B50: 기말잔액 | C50: [KRWm] | E50: =E45+E46-E49 | F50: =F45+F46-F49 | G50: =G45+G46-G49 | H50: =H45+H46-H49 | I50: =I45+I46-I49 | J50: =J45+J46-J49 | K50: =K45+K46-K49 | L50: =L45+L46-L49 | ... CL50: =CL45+CL46-CL49
B51: 미상환 잔액(검증용) | C51: [KRWm] | D51: =CL50 | F51: 완전상환 확인 (OK) | H51: ※ 미사용 트랜치 — 값(baked) 기준
B53: 전체 합계
B54: 기초잔액 | C54: [KRWm] | E54: 0 | F54: 19870.323 | G54: 31299.064 | H54: 53960.671 | I54: 76948.397 | J54: 101261.09 | K54: 135000 | L54: 135000 | M54: 135000 | N54: 135000 | O54: 130865.62 | P54: 128030.62 | Q54: 126275.62 | R54: 124520.62 | S54: 122630.62 | T54: 120740.62 | U54: 118850.62 | V54: 116960.62 | W54: 115070.62 | X54: 113180.62 | Y54: 111290.62 | Z54: 109265.62 | AA54: 107240.62 | AB54: 105215.62 | AC54: 103190.62 | AD54: 101165.62 | AE54: 99140.625 | AF54: 97031.25 | AG54: 94921.875 | AH54: 92812.5 | AI54: 90703.125 | AJ54: 88593.75 | AK54: 86484.375 | AL54: 84375 | AM54: 82265.625 | AN54: 80156.25 | AO54: 78046.875 | AP54: 75937.5 | AQ54: 73828.125 | AR54: 71718.75 | AS54: 69609.375 | AT54: 67500 | AU54: 65390.625 | AV54: 63281.25 | AW54: 61171.875 | AX54: 59062.5 | AY54: 56953.125 | AZ54: 54843.75 | BA54: 52734.375 | BB54: 50625 | BC54: 48515.625 | BD54: 46406.25 | BE54: 44296.875 | BF54: 42187.5 | BG54: 40078.125 | BH54: 37968.75 | BI54: 35859.375 | BJ54: 33750 | BK54: 31640.625 | BL54: 29531.25 | BM54: 27421.875 | BN54: 25312.5 | BO54: 23203.125 | BP54: 21093.75 | BQ54: 18984.375 | BR54: 16875 | BS54: 14765.625 | BT54: 12656.25 | BU54: 10546.875 | BV54: 8437.5 | BW54: 6328.125 | BX54: 4218.75 | BY54: 2109.375 | BZ54: 0 | CA54: 0 | CB54: 0 | CC54: 0 | CD54: 0 | CE54: 0 | CF54: 0 | CG54: 0 | CH54: 0 | CI54: 0 | CJ54: 0 | CK54: 0 | CL54: 0
B55: 이자 | C55: [KRWm] | D55: =SUM(E55:CL55) | E55: =E12+E21+E30+E39+E48 | F55: =F12+F21+F30+F39+F48 | G55: =G12+G21+G30+G39+G48 | H55: =H12+H21+H30+H39+H48 | I55: =I12+I21+I30+I39+I48 | J55: =J12+J21+J30+J39+J48 | K55: =K12+K21+K30+K39+K48 | L55: =L12+L21+L30+L39+L48 | ... CL55: =CL12+CL21+CL30+CL39+CL48
B56: 원금상환 | C56: [KRWm] | D56: =SUM(E56:CL56) | E56: =E13+E22+E31+E40+E49 | F56: =F13+F22+F31+F40+F49 | G56: =G13+G22+G31+G40+G49 | H56: =H13+H22+H31+H40+H49 | I56: =I13+I22+I31+I40+I49 | J56: =J13+J22+J31+J40+J49 | K56: =K13+K22+K31+K40+K49 | L56: =L13+L22+L31+L40+L49 | ... CL56: =CL13+CL22+CL31+CL40+CL49
B57: 원리금(DS) | C57: [KRWm] | D57: =SUM(E57:CL57) | E57: =E55+E56 | F57: =F55+F56 | G57: =G55+G56 | H57: =H55+H56 | I57: =I55+I56 | J57: =J55+J56 | K57: =K55+K56 | L57: =L55+L56 | ... CL57: =CL55+CL56
B58: 기말잔액 | C58: [KRWm] | E58: =E14+E23+E32+E41+E50 | F58: =F14+F23+F32+F41+F50 | G58: =G14+G23+G32+G41+G50 | H58: =H14+H23+H32+H41+H50 | I58: =I14+I23+I32+I41+I50 | J58: =J14+J23+J32+J41+J50 | K58: =K14+K23+K32+K41+K50 | L58: =L14+L23+L32+L41+L50 | ... CL58: =CL14+CL23+CL32+CL41+CL50
B60: DSRA 기말잔액 | C60: [KRWm] | E60: 0 | F60: 0 | G60: 0 | H60: 0 | I60: 0 | J60: 5000 | K60: 3737.5 | L60: 7871.875 | M60: 10649.644 | N60: 8173.7953 | O60: 7030.2578 | P60: 7116.6703 | Q60: 7201.214 | R60: 7148.889 | S60: 7096.564 | T60: 7044.239 | U60: 6991.914 | V60: 6939.589 | W60: 7022.264 | X60: 7103.0703 | Y60: 7047.0078 | Z60: 6990.9453 | AA60: 6934.8828 | AB60: 6878.8203 | AC60: 6907.1328 | AD60: 6934.2773 | AE60: 6875.8789 | AF60: 6817.4804 | AG60: 6759.082 | AH60: 6700.6836 | AI60: 6642.2851 | AJ60: 6583.8867 | AK60: 6525.4883 | AL60: 6467.0898 | AM60: 6408.6914 | AN60: 6350.2929 | AO60: 6291.8945 | AP60: 6233.4961 | AQ60: 6175.0976 | AR60: 6116.6992 | AS60: 6058.3008 | AT60: 5999.9023 | AU60: 5941.5039 | AV60: 5883.1054 | AW60: 5824.707 | AX60: 5766.3086 | AY60: 5707.9101 | AZ60: 5649.5117 | BA60: 5591.1133 | BB60: 5532.7148 | BC60: 5474.3164 | BD60: 5415.9179 | BE60: 5357.5195 | BF60: 5299.1211 | BG60: 5240.7226 | BH60: 5182.3242 | BI60: 5123.9258 | BJ60: 5065.5273 | BK60: 5007.1289 | BL60: 4948.7305 | BM60: 4890.332 | BN60: 4831.9336 | BO60: 4773.5351 | BP60: 4715.1367 | BQ60: 4656.7383 | BR60: 4598.3398 | BS60: 4539.9414 | BT60: 4481.543 | BU60: 4423.1445 | BV60: 4364.7461 | BW60: 4306.3476 | BX60: 2138.5742 | BY60: 0 | BZ60: 0 | CA60: 0 | CB60: 0 | CC60: 0 | CD60: 0 | CE60: 0 | CF60: 0 | CG60: 0 | CH60: 0 | CI60: 0 | CJ60: 0 | CK60: 0 | CL60: 0

Sheet Revenue
A1: 당진 태양광발전
A2: 영업수익 추정
B4: 발전량 및 매출
B6: 구 분 | C6: unit | D6: 합 계 | E6: 2024-06-30 | F6: 2024-09-30 | G6: 2024-12-31 | H6: 2025-03-31 | I6: 2025-06-30 | J6: 2025-09-30 | K6: 2025-12-31 | L6: 2026-03-31 | M6: 2026-06-30 | N6: 2026-09-30 | O6: 2026-12-31 | P6: 2027-03-31 | Q6: 2027-06-30 | R6: 2027-09-30 | S6: 2027-12-31 | T6: 2028-03-31 | U6: 2028-06-30 | V6: 2028-09-30 | W6: 2028-12-31 | X6: 2029-03-31 | Y6: 2029-06-30 | Z6: 2029-09-30 | AA6: 2029-12-31 | AB6: 2030-03-31 | AC6: 2030-06-30 | AD6: 2030-09-30 | AE6: 2030-12-31 | AF6: 2031-03-31 | AG6: 2031-06-30 | AH6: 2031-09-30 | AI6: 2031-12-31 | AJ6: 2032-03-31 | AK6: 2032-06-30 | AL6: 2032-09-30 | AM6: 2032-12-31 | AN6: 2033-03-31 | AO6: 2033-06-30 | AP6: 2033-09-30 | AQ6: 2033-12-31 | AR6: 2034-03-31 | AS6: 2034-06-30 | AT6: 2034-09-30 | AU6: 2034-12-31 | AV6: 2035-03-31 | AW6: 2035-06-30 | AX6: 2035-09-30 | AY6: 2035-12-31 | AZ6: 2036-03-31 | BA6: 2036-06-30 | BB6: 2036-09-30 | BC6: 2036-12-31 | BD6: 2037-03-31 | BE6: 2037-06-30 | BF6: 2037-09-30 | BG6: 2037-12-31 | BH6: 2038-03-31 | BI6: 2038-06-30 | BJ6: 2038-09-30 | BK6: 2038-12-31 | BL6: 2039-03-31 | BM6: 2039-06-30 | BN6: 2039-09-30 | BO6: 2039-12-31 | BP6: 2040-03-31 | BQ6: 2040-06-30 | BR6: 2040-09-30 | BS6: 2040-12-31 | BT6: 2041-03-31 | BU6: 2041-06-30 | BV6: 2041-09-30 | BW6: 2041-12-31 | BX6: 2042-03-31 | BY6: 2042-06-30 | BZ6: 2042-09-30 | CA6: 2042-12-31 | CB6: 2043-03-31 | CC6: 2043-06-30 | CD6: 2043-09-30 | CE6: 2043-12-31 | CF6: 2044-03-31 | CG6: 2044-06-30 | CH6: 2044-09-30 | CI6: 2044-12-31 | CJ6: 2045-03-31 | CK6: 2045-06-30 | CL6: 2045-09-30
B9: 발전량 | C9: [MWh] | D9: =SUM(E9:CL9) | E9: =('입력값'!C7*'입력값'!C14*365)*MAX(0,1-'입력값'!C12/100*0)*(1-'입력값'!C13/100)*0 | F9: =('입력값'!C7*'입력값'!C14*365)*MAX(0,1-'입력값'!C12/100*0)*(1-'입력값'!C13/100)*0 | G9: =('입력값'!C7*'입력값'!C14*365)*MAX(0,1-'입력값'!C12/100*0)*(1-'입력값'!C13/100)*0 | H9: =('입력값'!C7*'입력값'!C14*365)*MAX(0,1-'입력값'!C12/100*0)*(1-'입력값'!C13/100)*0 | I9: =('입력값'!C7*'입력값'!C14*365)*MAX(0,1-'입력값'!C12/100*0)*(1-'입력값'!C13/100)*0 | J9: =('입력값'!C7*'입력값'!C14*365)*MAX(0,1-'입력값'!C12/100*0)*(1-'입력값'!C13/100)*0 | K9: =('입력값'!C7*'입력값'!C14*365)*MAX(0,1-'입력값'!C12/100*0)*(1-'입력값'!C13/100)*0.2347 | L9: =('입력값'!C7*'입력값'!C14*365)*MAX(0,1-'입력값'!C12/100*0)*(1-'입력값'!C13/100)*0.2397 | M9: =('입력값'!C7*'입력값'!C14*365)*MAX(0,1-'입력값'!C12/100*0)*(1-'입력값'!C13/100)*0.3057 | N9: =('입력값'!C7*'입력값'!C14*365)*MAX(0,1-'입력값'!C12/100*0)*(1-'입력값'!C13/100)*0.2199 | O9: =('입력값'!C7*'입력값'!C14*365)*MAX(0,1-'입력값'!C12/100*1)*(1-'입력값'!C13/100)*0.2347 | P9: =('입력값'!C7*'입력값'!C14*365)*MAX(0,1-'입력값'!C12/100*1)*(1-'입력값'!C13/100)*0.2397 | Q9: =('입력값'!C7*'입력값'!C14*365)*MAX(0,1-'입력값'!C12/100*1)*(1-'입력값'!C13/100)*0.3057 | R9: =('입력값'!C7*'입력값'!C14*365)*MAX(0,1-'입력값'!C12/100*1)*(1-'입력값'!C13/100)*0.2199 | S9: =('입력값'!C7*'입력값'!C14*365)*MAX(0,1-'입력값'!C12/100*2)*(1-'입력값'!C13/100)*0.2347 | T9: =('입력값'!C7*'입력값'!C14*365)*MAX(0,1-'입력값'!C12/100*2)*(1-'입력값'!C13/100)*0.2397 | U9: =('입력값'!C7*'입력값'!C14*365)*MAX(0,1-'입력값'!C12/100*2)*(1-'입력값'!C13/100)*0.3057 | V9: =('입력값'!C7*'입력값'!C14*365)*MAX(0,1-'입력값'!C12/100*2)*(1-'입력값'!C13/100)*0.2199 | W9: =('입력값'!C7*'입력값'!C14*365)*MAX(0,1-'입력값'!C12/100*3)*(1-'입력값'!C13/100)*0.2347 | X9: =('입력값'!C7*'입력값'!C14*365)*MAX(0,1-'입력값'!C12/100*3)*(1-'입력값'!C13/100)*0.2397 | Y9: =('입력값'!C7*'입력값'!C14*365)*MAX(0,1-'입력값'!C12/100*3)*(1-'입력값'!C13/100)*0.3057 | Z9: =('입력값'!C7*'입력값'!C14*365)*MAX(0,1-'입력값'!C12/100*3)*(1-'입력값'!C13/100)*0.2199 | AA9: =('입력값'!C7*'입력값'!C14*365)*MAX(0,1-'입력값'!C12/100*4)*(1-'입력값'!C13/100)*0.2347 | AB9: =('입력값'!C7*'입력값'!C14*365)*MAX(0,1-'입력값'!C12/100*4)*(1-'입력값'!C13/100)*0.2397 | AC9: =('입력값'!C7*'입력값'!C14*365)*MAX(0,1-'입력값'!C12/100*4)*(1-'입력값'!C13/100)*0.3057 | AD9: =('입력값'!C7*'입력값'!C14*365)*MAX(0,1-'입력값'!C12/100*4)*(1-'입력값'!C13/100)*0.2199 | AE9: =('입력값'!C7*'입력값'!C14*365)*MAX(0,1-'입력값'!C12/100*5)*(1-'입력값'!C13/100)*0.2347 | AF9: =('입력값'!C7*'입력값'!C14*365)*MAX(0,1-'입력값'!C12/100*5)*(1-'입력값'!C13/100)*0.2397 | AG9: =('입력값'!C7*'입력값'!C14*365)*MAX(0,1-'입력값'!C12/100*5)*(1-'입력값'!C13/100)*0.3057 | AH9: =('입력값'!C7*'입력값'!C14*365)*MAX(0,1-'입력값'!C12/100*5)*(1-'입력값'!C13/100)*0.2199 | AI9: =('입력값'!C7*'입력값'!C14*365)*MAX(0,1-'입력값'!C12/100*6)*(1-'입력값'!C13/100)*0.2347 | AJ9: =('입력값'!C7*'입력값'!C14*365)*MAX(0,1-'입력값'!C12/100*6)*(1-'입력값'!C13/100)*0.2397 | AK9: =('입력값'!C7*'입력값'!C14*365)*MAX(0,1-'입력값'!C12/100*6)*(1-'입력값'!C13/100)*0.3057 | AL9: =('입력값'!C7*'입력값'!C14*365)*MAX(0,1-'입력값'!C12/100*6)*(1-'입력값'!C13/100)*0.2199 | AM9: =('입력값'!C7*'입력값'!C14*365)*MAX(0,1-'입력값'!C12/100*7)*(1-'입력값'!C13/100)*0.2347 | AN9: =('입력값'!C7*'입력값'!C14*365)*MAX(0,1-'입력값'!C12/100*7)*(1-'입력값'!C13/100)*0.2397 | AO9: =('입력값'!C7*'입력값'!C14*365)*MAX(0,1-'입력값'!C12/100*7)*(1-'입력값'!C13/100)*0.3057 | AP9: =('입력값'!C7*'입력값'!C14*365)*MAX(0,1-'입력값'!C12/100*7)*(1-'입력값'!C13/100)*0.2199 | AQ9: =('입력값'!C7*'입력값'!C14*365)*MAX(0,1-'입력값'!C12/100*8)*(1-'입력값'!C13/100)*0.2347 | AR9: =('입력값'!C7*'입력값'!C14*365)*MAX(0,1-'입력값'!C12/100*8)*(1-'입력값'!C13/100)*0.2397 | AS9: =('입력값'!C7*'입력값'!C14*365)*MAX(0,1-'입력값'!C12/100*8)*(1-'입력값'!C13/100)*0.3057 | AT9: =('입력값'!C7*'입력값'!C14*365)*MAX(0,1-'입력값'!C12/100*8)*(1-'입력값'!C13/100)*0.2199 | AU9: =('입력값'!C7*'입력값'!C14*365)*MAX(0,1-'입력값'!C12/100*9)*(1-'입력값'!C13/100)*0.2347 | AV9: =('입력값'!C7*'입력값'!C14*365)*MAX(0,1-'입력값'!C12/100*9)*(1-'입력값'!C13/100)*0.2397 | AW9: =('입력값'!C7*'입력값'!C14*365)*MAX(0,1-'입력값'!C12/100*9)*(1-'입력값'!C13/100)*0.3057 | AX9: =('입력값'!C7*'입력값'!C14*365)*MAX(0,1-'입력값'!C12/100*9)*(1-'입력값'!C13/100)*0.2199 | AY9: =('입력값'!C7*'입력값'!C14*365)*MAX(0,1-'입력값'!C12/100*10)*(1-'입력값'!C13/100)*0.2347 | AZ9: =('입력값'!C7*'입력값'!C14*365)*MAX(0,1-'입력값'!C12/100*10)*(1-'입력값'!C13/100)*0.2397 | BA9: =('입력값'!C7*'입력값'!C14*365)*MAX(0,1-'입력값'!C12/100*10)*(1-'입력값'!C13/100)*0.3057 | BB9: =('입력값'!C7*'입력값'!C14*365)*MAX(0,1-'입력값'!C12/100*10)*(1-'입력값'!C13/100)*0.2199 | BC9: =('입력값'!C7*'입력값'!C14*365)*MAX(0,1-'입력값'!C12/100*11)*(1-'입력값'!C13/100)*0.2347 | BD9: =('입력값'!C7*'입력값'!C14*365)*MAX(0,1-'입력값'!C12/100*11)*(1-'입력값'!C13/100)*0.2397 | BE9: =('입력값'!C7*'입력값'!C14*365)*MAX(0,1-'입력값'!C12/100*11)*(1-'입력값'!C13/100)*0.3057 | BF9: =('입력값'!C7*'입력값'!C14*365)*MAX(0,1-'입력값'!C12/100*11)*(1-'입력값'!C13/100)*0.2199 | BG9: =('입력값'!C7*'입력값'!C14*365)*MAX(0,1-'입력값'!C12/100*12)*(1-'입력값'!C13/100)*0.2347 | BH9: =('입력값'!C7*'입력값'!C14*365)*MAX(0,1-'입력값'!C12/100*12)*(1-'입력값'!C13/100)*0.2397 | BI9: =('입력값'!C7*'입력값'!C14*365)*MAX(0,1-'입력값'!C12/100*12)*(1-'입력값'!C13/100)*0.3057 | BJ9: =('입력값'!C7*'입력값'!C14*365)*MAX(0,1-'입력값'!C12/100*12)*(1-'입력값'!C13/100)*0.2199 | BK9: =('입력값'!C7*'입력값'!C14*365)*MAX(0,1-'입력값'!C12/100*13)*(1-'입력값'!C13/100)*0.2347 | BL9: =('입력값'!C7*'입력값'!C14*365)*MAX(0,1-'입력값'!C12/100*13)*(1-'입력값'!C13/100)*0.2397 | BM9: =('입력값'!C7*'입력값'!C14*365)*MAX(0,1-'입력값'!C12/100*13)*(1-'입력값'!C13/100)*0.3057 | BN9: =('입력값'!C7*'입력값'!C14*365)*MAX(0,1-'입력값'!C12/100*13)*(1-'입력값'!C13/100)*0.2199 | BO9: =('입력값'!C7*'입력값'!C14*365)*MAX(0,1-'입력값'!C12/100*14)*(1-'입력값'!C13/100)*0.2347 | BP9: =('입력값'!C7*'입력값'!C14*365)*MAX(0,1-'입력값'!C12/100*14)*(1-'입력값'!C13/100)*0.2397 | BQ9: =('입력값'!C7*'입력값'!C14*365)*MAX(0,1-'입력값'!C12/100*14)*(1-'입력값'!C13/100)*0.3057 | BR9: =('입력값'!C7*'입력값'!C14*365)*MAX(0,1-'입력값'!C12/100*14)*(1-'입력값'!C13/100)*0.2199 | BS9: =('입력값'!C7*'입력값'!C14*365)*MAX(0,1-'입력값'!C12/100*15)*(1-'입력값'!C13/100)*0.2347 | BT9: =('입력값'!C7*'입력값'!C14*365)*MAX(0,1-'입력값'!C12/100*15)*(1-'입력값'!C13/100)*0.2397 | BU9: =('입력값'!C7*'입력값'!C14*365)*MAX(0,1-'입력값'!C12/100*15)*(1-'입력값'!C13/100)*0.3057 | BV9: =('입력값'!C7*'입력값'!C14*365)*MAX(0,1-'입력값'!C12/100*15)*(1-'입력값'!C13/100)*0.2199 | BW9: =('입력값'!C7*'입력값'!C14*365)*MAX(0,1-'입력값'!C12/100*16)*(1-'입력값'!C13/100)*0.2347 | BX9: =('입력값'!C7*'입력값'!C14*365)*MAX(0,1-'입력값'!C12/100*16)*(1-'입력값'!C13/100)*0.2397 | BY9: =('입력값'!C7*'입력값'!C14*365)*MAX(0,1-'입력값'!C12/100*16)*(1-'입력값'!C13/100)*0.3057 | BZ9: =('입력값'!C7*'입력값'!C14*365)*MAX(0,1-'입력값'!C12/100*16)*(1-'입력값'!C13/100)*0.2199 | CA9: =('입력값'!C7*'입력값'!C14*365)*MAX(0,1-'입력값'!C12/100*17)*(1-'입력값'!C13/100)*0.2347 | CB9: =('입력값'!C7*'입력값'!C14*365)*MAX(0,1-'입력값'!C12/100*17)*(1-'입력값'!C13/100)*0.2397 | CC9: =('입력값'!C7*'입력값'!C14*365)*MAX(0,1-'입력값'!C12/100*17)*(1-'입력값'!C13/100)*0.3057 | CD9: =('입력값'!C7*'입력값'!C14*365)*MAX(0,1-'입력값'!C12/100*17)*(1-'입력값'!C13/100)*0.2199 | CE9: =('입력값'!C7*'입력값'!C14*365)*MAX(0,1-'입력값'!C12/100*18)*(1-'입력값'!C13/100)*0.2347 | CF9: =('입력값'!C7*'입력값'!C14*365)*MAX(0,1-'입력값'!C12/100*18)*(1-'입력값'!C13/100)*0.2397 | CG9: =('입력값'!C7*'입력값'!C14*365)*MAX(0,1-'입력값'!C12/100*18)*(1-'입력값'!C13/100)*0.3057 | CH9: =('입력값'!C7*'입력값'!C14*365)*MAX(0,1-'입력값'!C12/100*18)*(1-'입력값'!C13/100)*0.2199 | CI9: =('입력값'!C7*'입력값'!C14*365)*MAX(0,1-'입력값'!C12/100*19)*(1-'입력값'!C13/100)*0.2347 | CJ9: =('입력값'!C7*'입력값'!C14*365)*MAX(0,1-'입력값'!C12/100*19)*(1-'입력값'!C13/100)*0.2397 | CK9: =('입력값'!C7*'입력값'!C14*365)*MAX(0,1-'입력값'!C12/100*19)*(1-'입력값'!C13/100)*0.3057 | CL9: =('입력값'!C7*'입력값'!C14*365)*MAX(0,1-'입력값'!C12/100*19)*(1-'입력값'!C13/100)*0.2199
B10: 판매단가 | C10: [원/kWh] | K10: ='입력값'!K80 | L10: ='입력값'!L80 | M10: ='입력값'!M80 | N10: ='입력값'!N80 | O10: ='입력값'!O80 | P10: ='입력값'!P80 | Q10: ='입력값'!Q80 | R10: ='입력값'!R80 | ... CL10: ='입력값'!CL80
B12: 영업수익 | C12: [KRWm] | D12: =SUM(E12:CL12) | E12: 0 | F12: 0 | G12: 0 | H12: 0 | I12: 0 | J12: 0 | K12: =K9*K10/1000 | L12: =L9*L10/1000 | M12: =M9*M10/1000 | N12: =N9*N10/1000 | O12: =O9*O10/1000 | P12: =P9*P10/1000 | Q12: =Q9*Q10/1000 | R12: =R9*R10/1000 | ... CL12: =CL9*CL10/1000
B14: ※ 실측 오버라이드가 적용된 분기는 "판매단가"가 그 분기의 실제 정산단가(실측 사실, baked)이고, "영업수익"은 다른 분기와 동일하게 발전량×판매단가/1000 수식으로 계산됩니다(값은 원본과 그대로 일치).

Sheet Opex
A1: 당진 태양광발전
A2: 영업비용 추정
B4: 운영비용 (선순위/후순위 지급순위 반영)
B6: 구 분 | C6: unit | D6: 합 계 | E6: 2024-06-30 | F6: 2024-09-30 | G6: 2024-12-31 | H6: 2025-03-31 | I6: 2025-06-30 | J6: 2025-09-30 | K6: 2025-12-31 | L6: 2026-03-31 | M6: 2026-06-30 | N6: 2026-09-30 | O6: 2026-12-31 | P6: 2027-03-31 | Q6: 2027-06-30 | R6: 2027-09-30 | S6: 2027-12-31 | T6: 2028-03-31 | U6: 2028-06-30 | V6: 2028-09-30 | W6: 2028-12-31 | X6: 2029-03-31 | Y6: 2029-06-30 | Z6: 2029-09-30 | AA6: 2029-12-31 | AB6: 2030-03-31 | AC6: 2030-06-30 | AD6: 2030-09-30 | AE6: 2030-12-31 | AF6: 2031-03-31 | AG6: 2031-06-30 | AH6: 2031-09-30 | AI6: 2031-12-31 | AJ6: 2032-03-31 | AK6: 2032-06-30 | AL6: 2032-09-30 | AM6: 2032-12-31 | AN6: 2033-03-31 | AO6: 2033-06-30 | AP6: 2033-09-30 | AQ6: 2033-12-31 | AR6: 2034-03-31 | AS6: 2034-06-30 | AT6: 2034-09-30 | AU6: 2034-12-31 | AV6: 2035-03-31 | AW6: 2035-06-30 | AX6: 2035-09-30 | AY6: 2035-12-31 | AZ6: 2036-03-31 | BA6: 2036-06-30 | BB6: 2036-09-30 | BC6: 2036-12-31 | BD6: 2037-03-31 | BE6: 2037-06-30 | BF6: 2037-09-30 | BG6: 2037-12-31 | BH6: 2038-03-31 | BI6: 2038-06-30 | BJ6: 2038-09-30 | BK6: 2038-12-31 | BL6: 2039-03-31 | BM6: 2039-06-30 | BN6: 2039-09-30 | BO6: 2039-12-31 | BP6: 2040-03-31 | BQ6: 2040-06-30 | BR6: 2040-09-30 | BS6: 2040-12-31 | BT6: 2041-03-31 | BU6: 2041-06-30 | BV6: 2041-09-30 | BW6: 2041-12-31 | BX6: 2042-03-31 | BY6: 2042-06-30 | BZ6: 2042-09-30 | CA6: 2042-12-31 | CB6: 2043-03-31 | CC6: 2043-06-30 | CD6: 2043-09-30 | CE6: 2043-12-31 | CF6: 2044-03-31 | CG6: 2044-06-30 | CH6: 2044-09-30 | CI6: 2044-12-31 | CJ6: 2045-03-31 | CK6: 2045-06-30 | CL6: 2045-09-30
B8: 항목별 세부내역
B9: 부지임대료 | C9: [KRWm] | D9: =SUM(E9:CL9) | E9: 0 | F9: 0 | G9: 0 | H9: 0 | I9: 0 | J9: 0 | K9: =-(IF(('입력값'!C62*100*(3/12))+('입력값'!C63*100*(3/12)*(1+'입력값'!D63/100)^0)+('입력값'!C64*100*(3/12))+('입력값'!C65*100*(3/12))+('입력값'!C66*100*(3/12)*(1+'입력값'!D66/100)^0)+('입력값'!C67*100*(3/12)*(1+'입력값'!D67/100)^0)+('입력값'!C68*100*(3/12)*(1+'입력값'!D68/100)^0)+('입력값'!C69*100*(3/12))+('입력값'!C70*100*(3/12))+('입력값'!C71*100*(3/12))+('입력값'!C72*100*(3/12))+('입력값'!C73*100*(3/12))=0,0,('입력값'!K81+'입력값'!K82)*('입력값'!C62*100*(3/12))/(('입력값'!C62*100*(3/12))+('입력값'!C63*100*(3/12)*(1+'입력값'!D63/100)^0)+('입력값'!C64*100*(3/12))+('입력값'!C65*100*(3/12))+('입력값'!C66*100*(3/12)*(1+'입력값'!D66/100)^0)+('입력값'!C67*100*(3/12)*(1+'입력값'!D67/100)^0)+('입력값'!C68*100*(3/12)*(1+'입력값'!D68/100)^0)+('입력값'!C69*100*(3/12))+('입력값'!C70*100*(3/12))+('입력값'!C71*100*(3/12))+('입력값'!C72*100*(3/12))+('입력값'!C73*100*(3/12))))) | L9: =-(IF(('입력값'!C62*100*(3/12))+('입력값'!C63*100*(3/12)*(1+'입력값'!D63/100)^0)+('입력값'!C64*100*(3/12))+('입력값'!C65*100*(3/12))+('입력값'!C66*100*(3/12)*(1+'입력값'!D66/100)^0)+('입력값'!C67*100*(3/12)*(1+'입력값'!D67/100)^0)+('입력값'!C68*100*(3/12)*(1+'입력값'!D68/100)^0)+('입력값'!C69*100*(3/12))+('입력값'!C70*100*(3/12))+('입력값'!C71*100*(3/12))+('입력값'!C72*100*(3/12))+('입력값'!C73*100*(3/12))=0,0,('입력값'!L81+'입력값'!L82)*('입력값'!C62*100*(3/12))/(('입력값'!C62*100*(3/12))+('입력값'!C63*100*(3/12)*(1+'입력값'!D63/100)^0)+('입력값'!C64*100*(3/12))+('입력값'!C65*100*(3/12))+('입력값'!C66*100*(3/12)*(1+'입력값'!D66/100)^0)+('입력값'!C67*100*(3/12)*(1+'입력값'!D67/100)^0)+('입력값'!C68*100*(3/12)*(1+'입력값'!D68/100)^0)+('입력값'!C69*100*(3/12))+('입력값'!C70*100*(3/12))+('입력값'!C71*100*(3/12))+('입력값'!C72*100*(3/12))+('입력값'!C73*100*(3/12))))) | M9: =-(IF(('입력값'!C62*100*(3/12))+('입력값'!C63*100*(3/12)*(1+'입력값'!D63/100)^0)+('입력값'!C64*100*(3/12))+('입력값'!C65*100*(3/12))+('입력값'!C66*100*(3/12)*(1+'입력값'!D66/100)^0)+('입력값'!C67*100*(3/12)*(1+'입력값'!D67/100)^0)+('입력값'!C68*100*(3/12)*(1+'입력값'!D68/100)^0)+('입력값'!C69*100*(3/12))+('입력값'!C70*100*(3/12))+('입력값'!C71*100*(3/12))+('입력값'!C72*100*(3/12))+('입력값'!C73*100*(3/12))=0,0,('입력값'!M81+'입력값'!M82)*('입력값'!C62*100*(3/12))/(('입력값'!C62*100*(3/12))+('입력값'!C63*100*(3/12)*(1+'입력값'!D63/100)^0)+('입력값'!C64*100*(3/12))+('입력값'!C65*100*(3/12))+('입력값'!C66*100*(3/12)*(1+'입력값'!D66/100)^0)+('입력값'!C67*100*(3/12)*(1+'입력값'!D67/100)^0)+('입력값'!C68*100*(3/12)*(1+'입력값'!D68/100)^0)+('입력값'!C69*100*(3/12))+('입력값'!C70*100*(3/12))+('입력값'!C71*100*(3/12))+('입력값'!C72*100*(3/12))+('입력값'!C73*100*(3/12))))) | N9: =-(IF(('입력값'!C62*100*(3/12))+('입력값'!C63*100*(3/12)*(1+'입력값'!D63/100)^0)+('입력값'!C64*100*(3/12))+('입력값'!C65*100*(3/12))+('입력값'!C66*100*(3/12)*(1+'입력값'!D66/100)^0)+('입력값'!C67*100*(3/12)*(1+'입력값'!D67/100)^0)+('입력값'!C68*100*(3/12)*(1+'입력값'!D68/100)^0)+('입력값'!C69*100*(3/12))+('입력값'!C70*100*(3/12))+('입력값'!C71*100*(3/12))+('입력값'!C72*100*(3/12))+('입력값'!C73*100*(3/12))=0,0,('입력값'!N81+'입력값'!N82)*('입력값'!C62*100*(3/12))/(('입력값'!C62*100*(3/12))+('입력값'!C63*100*(3/12)*(1+'입력값'!D63/100)^0)+('입력값'!C64*100*(3/12))+('입력값'!C65*100*(3/12))+('입력값'!C66*100*(3/12)*(1+'입력값'!D66/100)^0)+('입력값'!C67*100*(3/12)*(1+'입력값'!D67/100)^0)+('입력값'!C68*100*(3/12)*(1+'입력값'!D68/100)^0)+('입력값'!C69*100*(3/12))+('입력값'!C70*100*(3/12))+('입력값'!C71*100*(3/12))+('입력값'!C72*100*(3/12))+('입력값'!C73*100*(3/12))))) | O9: =-(IF(('입력값'!C62*100*(3/12))+('입력값'!C63*100*(3/12)*(1+'입력값'!D63/100)^1)+('입력값'!C64*100*(3/12))+('입력값'!C65*100*(3/12))+('입력값'!C66*100*(3/12)*(1+'입력값'!D66/100)^1)+('입력값'!C67*100*(3/12)*(1+'입력값'!D67/100)^1)+('입력값'!C68*100*(3/12)*(1+'입력값'!D68/100)^1)+('입력값'!C69*100*(3/12))+('입력값'!C70*100*(3/12))+('입력값'!C71*100*(3/12))+('입력값'!C72*100*(3/12))+('입력값'!C73*100*(3/12))=0,0,('입력값'!O81+'입력값'!O82)*('입력값'!C62*100*(3/12))/(('입력값'!C62*100*(3/12))+('입력값'!C63*100*(3/12)*(1+'입력값'!D63/100)^1)+('입력값'!C64*100*(3/12))+('입력값'!C65*100*(3/12))+('입력값'!C66*100*(3/12)*(1+'입력값'!D66/100)^1)+('입력값'!C67*100*(3/12)*(1+'입력값'!D67/100)^1)+('입력값'!C68*100*(3/12)*(1+'입력값'!D68/100)^1)+('입력값'!C69*100*(3/12))+('입력값'!C70*100*(3/12))+('입력값'!C71*100*(3/12))+('입력값'!C72*100*(3/12))+('입력값'!C73*100*(3/12))))) | P9: =-(IF(('입력값'!C62*100*(3/12))+('입력값'!C63*100*(3/12)*(1+'입력값'!D63/100)^1)+('입력값'!C64*100*(3/12))+('입력값'!C65*100*(3/12))+('입력값'!C66*100*(3/12)*(1+'입력값'!D66/100)^1)+('입력값'!C67*100*(3/12)*(1+'입력값'!D67/100)^1)+('입력값'!C68*100*(3/12)*(1+'입력값'!D68/100)^1)+('입력값'!C69*100*(3/12))+('입력값'!C70*100*(3/12))+('입력값'!C71*100*(3/12))+('입력값'!C72*100*(3/12))+('입력값'!C73*100*(3/12))=0,0,('입력값'!P81+'입력값'!P82)*('입력값'!C62*100*(3/12))/(('입력값'!C62*100*(3/12))+('입력값'!C63*100*(3/12)*(1+'입력값'!D63/100)^1)+('입력값'!C64*100*(3/12))+('입력값'!C65*100*(3/12))+('입력값'!C66*100*(3/12)*(1+'입력값'!D66/100)^1)+('입력값'!C67*100*(3/12)*(1+'입력값'!D67/100)^1)+('입력값'!C68*100*(3/12)*(1+'입력값'!D68/100)^1)+('입력값'!C69*100*(3/12))+('입력값'!C70*100*(3/12))+('입력값'!C71*100*(3/12))+('입력값'!C72*100*(3/12))+('입력값'!C73*100*(3/12))))) | Q9: =-(IF(('입력값'!C62*100*(3/12))+('입력값'!C63*100*(3/12)*(1+'입력값'!D63/100)^1)+('입력값'!C64*100*(3/12))+('입력값'!C65*100*(3/12))+('입력값'!C66*100*(3/12)*(1+'입력값'!D66/100)^1)+('입력값'!C67*100*(3/12)*(1+'입력값'!D67/100)^1)+('입력값'!C68*100*(3/12)*(1+'입력값'!D68/100)^1)+('입력값'!C69*100*(3/12))+('입력값'!C70*100*(3/12))+('입력값'!C71*100*(3/12))+('입력값'!C72*100*(3/12))+('입력값'!C73*100*(3/12))=0,0,('입력값'!Q81+'입력값'!Q82)*('입력값'!C62*100*(3/12))/(('입력값'!C62*100*(3/12))+('입력값'!C63*100*(3/12)*(1+'입력값'!D63/100)^1)+('입력값'!C64*100*(3/12))+('입력값'!C65*100*(3/12))+('입력값'!C66*100*(3/12)*(1+'입력값'!D66/100)^1)+('입력값'!C67*100*(3/12)*(1+'입력값'!D67/100)^1)+('입력값'!C68*100*(3/12)*(1+'입력값'!D68/100)^1)+('입력값'!C69*100*(3/12))+('입력값'!C70*100*(3/12))+('입력값'!C71*100*(3/12))+('입력값'!C72*100*(3/12))+('입력값'!C73*100*(3/12))))) | R9: =-(IF(('입력값'!C62*100*(3/12))+('입력값'!C63*100*(3/12)*(1+'입력값'!D63/100)^1)+('입력값'!C64*100*(3/12))+('입력값'!C65*100*(3/12))+('입력값'!C66*100*(3/12)*(1+'입력값'!D66/100)^1)+('입력값'!C67*100*(3/12)*(1+'입력값'!D67/100)^1)+('입력값'!C68*100*(3/12)*(1+'입력값'!D68/100)^1)+('입력값'!C69*100*(3/12))+('입력값'!C70*100*(3/12))+('입력값'!C71*100*(3/12))+('입력값'!C72*100*(3/12))+('입력값'!C73*100*(3/12))=0,0,('입력값'!R81+'입력값'!R82)*('입력값'!C62*100*(3/12))/(('입력값'!C62*100*(3/12))+('입력값'!C63*100*(3/12)*(1+'입력값'!D63/100)^1)+('입력값'!C64*100*(3/12))+('입력값'!C65*100*(3/12))+('입력값'!C66*100*(3/12)*(1+'입력값'!D66/100)^1)+('입력값'!C67*100*(3/12)*(1+'입력값'!D67/100)^1)+('입력값'!C68*100*(3/12)*(1+'입력값'!D68/100)^1)+('입력값'!C69*100*(3/12))+('입력값'!C70*100*(3/12))+('입력값'!C71*100*(3/12))+('입력값'!C72*100*(3/12))+('입력값'!C73*100*(3/12))))) | S9: =-(IF(('입력값'!C62*100*(3/12))+('입력값'!C63*100*(3/12)*(1+'입력값'!D63/100)^2)+('입력값'!C64*100*(3/12))+('입력값'!C65*100*(3/12))+('입력값'!C66*100*(3/12)*(1+'입력값'!D66/100)^2)+('입력값'!C67*100*(3/12)*(1+'입력값'!D67/100)^2)+('입력값'!C68*100*(3/12)*(1+'입력값'!D68/100)^2)+('입력값'!C69*100*(3/12))+('입력값'!C70*100*(3/12))+('입력값'!C71*100*(3/12))+('입력값'!C72*100*(3/12))+('입력값'!C73*100*(3/12))=0,0,('입력값'!S81+'입력값'!S82)*('입력값'!C62*100*(3/12))/(('입력값'!C62*100*(3/12))+('입력값'!C63*100*(3/12)*(1+'입력값'!D63/100)^2)+('입력값'!C64*100*(3/12))+('입력값'!C65*100*(3/12))+('입력값'!C66*100*(3/12)*(1+'입력값'!D66/100)^2)+('입력값'!C67*100*(3/12)*(1+'입력값'!D67/100)^2)+('입력값'!C68*100*(3/12)*(1+'입력값'!D68/100)^2)+('입력값'!C69*100*(3/12))+('입력값'!C70*100*(3/12))+('입력값'!C71*100*(3/12))+('입력값'!C72*100*(3/12))+('입력값'!C73*100*(3/12))))) | T9: =-(IF(('입력값'!C62*100*(3/12))+('입력값'!C63*100*(3/12)*(1+'입력값'!D63/100)^2)+('입력값'!C64*100*(3/12))+('입력값'!C65*100*(3/12))+('입력값'!C66*100*(3/12)*(1+'입력값'!D66/100)^2)+('입력값'!C67*100*(3/12)*(1+'입력값'!D67/100)^2)+('입력값'!C68*100*(3/12)*(1+'입력값'!D68/100)^2)+('입력값'!C69*100*(3/12))+('입력값'!C70*100*(3/12))+('입력값'!C71*100*(3/12))+('입력값'!C72*100*(3/12))+('입력값'!C73*100*(3/12))=0,0,('입력값'!T81+'입력값'!T82)*('입력값'!C62*100*(3/12))/(('입력값'!C62*100*(3/12))+('입력값'!C63*100*(3/12)*(1+'입력값'!D63/100)^2)+('입력값'!C64*100*(3/12))+('입력값'!C65*100*(3/12))+('입력값'!C66*100*(3/12)*(1+'입력값'!D66/100)^2)+('입력값'!C67*100*(3/12)*(1+'입력값'!D67/100)^2)+('입력값'!C68*100*(3/12)*(1+'입력값'!D68/100)^2)+('입력값'!C69*100*(3/12))+('입력값'!C70*100*(3/12))+('입력값'!C71*100*(3/12))+('입력값'!C72*100*(3/12))+('입력값'!C73*100*(3/12))))) | U9: =-(IF(('입력값'!C62*100*(3/12))+('입력값'!C63*100*(3/12)*(1+'입력값'!D63/100)^2)+('입력값'!C64*100*(3/12))+('입력값'!C65*100*(3/12))+('입력값'!C66*100*(3/12)*(1+'입력값'!D66/100)^2)+('입력값'!C67*100*(3/12)*(1+'입력값'!D67/100)^2)+('입력값'!C68*100*(3/12)*(1+'입력값'!D68/100)^2)+('입력값'!C69*100*(3/12))+('입력값'!C70*100*(3/12))+('입력값'!C71*100*(3/12))+('입력값'!C72*100*(3/12))+('입력값'!C73*100*(3/12))=0,0,('입력값'!U81+'입력값'!U82)*('입력값'!C62*100*(3/12))/(('입력값'!C62*100*(3/12))+('입력값'!C63*100*(3/12)*(1+'입력값'!D63/100)^2)+('입력값'!C64*100*(3/12))+('입력값'!C65*100*(3/12))+('입력값'!C66*100*(3/12)*(1+'입력값'!D66/100)^2)+('입력값'!C67*100*(3/12)*(1+'입력값'!D67/100)^2)+('입력값'!C68*100*(3/12)*(1+'입력값'!D68/100)^2)+('입력값'!C69*100*(3/12))+('입력값'!C70*100*(3/12))+('입력값'!C71*100*(3/12))+('입력값'!C72*100*(3/12))+('입력값'!C73*100*(3/12))))) | V9: =-(IF(('입력값'!C62*100*(3/12))+('입력값'!C63*100*(3/12)*(1+'입력값'!D63/100)^2)+('입력값'!C64*100*(3/12))+('입력값'!C65*100*(3/12))+('입력값'!C66*100*(3/12)*(1+'입력값'!D66/100)^2)+('입력값'!C67*100*(3/12)*(1+'입력값'!D67/100)^2)+('입력값'!C68*100*(3/12)*(1+'입력값'!D68/100)^2)+('입력값'!C69*100*(3/12))+('입력값'!C70*100*(3/12))+('입력값'!C71*100*(3/12))+('입력값'!C72*100*(3/12))+('입력값'!C73*100*(3/12))=0,0,('입력값'!V81+'입력값'!V82)*('입력값'!C62*100*(3/12))/(('입력값'!C62*100*(3/12))+('입력값'!C63*100*(3/12)*(1+'입력값'!D63/100)^2)+('입력값'!C64*100*(3/12))+('입력값'!C65*100*(3/12))+('입력값'!C66*100*(3/12)*(1+'입력값'!D66/100)^2)+('입력값'!C67*100*(3/12)*(1+'입력값'!D67/100)^2)+('입력값'!C68*100*(3/12)*(1+'입력값'!D68/100)^2)+('입력값'!C69*100*(3/12))+('입력값'!C70*100*(3/12))+('입력값'!C71*100*(3/12))+('입력값'!C72*100*(3/12))+('입력값'!C73*100*(3/12))))) | W9: =-(IF(('입력값'!C62*100*(3/12))+('입력값'!C63*100*(3/12)*(1+'입력값'!D63/100)^3)+('입력값'!C64*100*(3/12))+('입력값'!C65*100*(3/12))+('입력값'!C66*100*(3/12)*(1+'입력값'!D66/100)^3)+('입력값'!C67*100*(3/12)*(1+'입력값'!D67/100)^3)+('입력값'!C68*100*(3/12)*(1+'입력값'!D68/100)^3)+('입력값'!C69*100*(3/12))+('입력값'!C70*100*(3/12))+('입력값'!C71*100*(3/12))+('입력값'!C72*100*(3/12))+('입력값'!C73*100*(3/12))=0,0,('입력값'!W81+'입력값'!W82)*('입력값'!C62*100*(3/12))/(('입력값'!C62*100*(3/12))+('입력값'!C63*100*(3/12)*(1+'입력값'!D63/100)^3)+('입력값'!C64*100*(3/12))+('입력값'!C65*100*(3/12))+('입력값'!C66*100*(3/12)*(1+'입력값'!D66/100)^3)+('입력값'!C67*100*(3/12)*(1+'입력값'!D67/100)^3)+('입력값'!C68*100*(3/12)*(1+'입력값'!D68/100)^3)+('입력값'!C69*100*(3/12))+('입력값'!C70*100*(3/12))+('입력값'!C71*100*(3/12))+('입력값'!C72*100*(3/12))+('입력값'!C73*100*(3/12))))) | X9: =-(IF(('입력값'!C62*100*(3/12))+('입력값'!C63*100*(3/12)*(1+'입력값'!D63/100)^3)+('입력값'!C64*100*(3/12))+('입력값'!C65*100*(3/12))+('입력값'!C66*100*(3/12)*(1+'입력값'!D66/100)^3)+('입력값'!C67*100*(3/12)*(1+'입력값'!D67/100)^3)+('입력값'!C68*100*(3/12)*(1+'입력값'!D68/100)^3)+('입력값'!C69*100*(3/12))+('입력값'!C70*100*(3/12))+('입력값'!C71*100*(3/12))+('입력값'!C72*100*(3/12))+('입력값'!C73*100*(3/12))=0,0,('입력값'!X81+'입력값'!X82)*('입력값'!C62*100*(3/12))/(('입력값'!C62*100*(3/12))+('입력값'!C63*100*(3/12)*(1+'입력값'!D63/100)^3)+('입력값'!C64*100*(3/12))+('입력값'!C65*100*(3/12))+('입력값'!C66*100*(3/12)*(1+'입력값'!D66/100)^3)+('입력값'!C67*100*(3/12)*(1+'입력값'!D67/100)^3)+('입력값'!C68*100*(3/12)*(1+'입력값'!D68/100)^3)+('입력값'!C69*100*(3/12))+('입력값'!C70*100*(3/12))+('입력값'!C71*100*(3/12))+('입력값'!C72*100*(3/12))+('입력값'!C73*100*(3/12))))) | Y9: =-(IF(('입력값'!C62*100*(3/12))+('입력값'!C63*100*(3/12)*(1+'입력값'!D63/100)^3)+('입력값'!C64*100*(3/12))+('입력값'!C65*100*(3/12))+('입력값'!C66*100*(3/12)*(1+'입력값'!D66/100)^3)+('입력값'!C67*100*(3/12)*(1+'입력값'!D67/100)^3)+('입력값'!C68*100*(3/12)*(1+'입력값'!D68/100)^3)+('입력값'!C69*100*(3/12))+('입력값'!C70*100*(3/12))+('입력값'!C71*100*(3/12))+('입력값'!C72*100*(3/12))+('입력값'!C73*100*(3/12))=0,0,('입력값'!Y81+'입력값'!Y82)*('입력값'!C62*100*(3/12))/(('입력값'!C62*100*(3/12))+('입력값'!C63*100*(3/12)*(1+'입력값'!D63/100)^3)+('입력값'!C64*100*(3/12))+('입력값'!C65*100*(3/12))+('입력값'!C66*100*(3/12)*(1+'입력값'!D66/100)^3)+('입력값'!C67*100*(3/12)*(1+'입력값'!D67/100)^3)+('입력값'!C68*100*(3/12)*(1+'입력값'!D68/100)^3)+('입력값'!C69*100*(3/12))+('입력값'!C70*100*(3/12))+('입력값'!C71*100*(3/12))+('입력값'!C72*100*(3/12))+('입력값'!C73*100*(3/12))))) | Z9: =-(IF(('입력값'!C62*100*(3/12))+('입력값'!C63*100*(3/12)*(1+'입력값'!D63/100)^3)+('입력값'!C64*100*(3/12))+('입력값'!C65*100*(3/12))+('입력값'!C66*100*(3/12)*(1+'입력값'!D66/100)^3)+('입력값'!C67*100*(3/12)*(1+'입력값'!D67/100)^3)+('입력값'!C68*100*(3/12)*(1+'입력값'!D68/100)^3)+('입력값'!C69*100*(3/12))+('입력값'!C70*100*(3/12))+('입력값'!C71*100*(3/12))+('입력값'!C72*100*(3/12))+('입력값'!C73*100*(3/12))=0,0,('입력값'!Z81+'입력값'!Z82)*('입력값'!C62*100*(3/12))/(('입력값'!C62*100*(3/12))+('입력값'!C63*100*(3/12)*(1+'입력값'!D63/100)^3)+('입력값'!C64*100*(3/12))+('입력값'!C65*100*(3/12))+('입력값'!C66*100*(3/12)*(1+'입력값'!D66/100)^3)+('입력값'!C67*100*(3/12)*(1+'입력값'!D67/100)^3)+('입력값'!C68*100*(3/12)*(1+'입력값'!D68/100)^3)+('입력값'!C69*100*(3/12))+('입력값'!C70*100*(3/12))+('입력값'!C71*100*(3/12))+('입력값'!C72*100*(3/12))+('입력값'!C73*100*(3/12))))) | AA9: =-(IF(('입력값'!C62*100*(3/12))+('입력값'!C63*100*(3/12)*(1+'입력값'!D63/100)^4)+('입력값'!C64*100*(3/12))+('입력값'!C65*100*(3/12))+('입력값'!C66*100*(3/12)*(1+'입력값'!D66/100)^4)+('입력값'!C67*100*(3/12)*(1+'입력값'!D67/100)^4)+('입력값'!C68*100*(3/12)*(1+'입력값'!D68/100)^4)+('입력값'!C69*100*(3/12))+('입력값'!C70*100*(3/12))+('입력값'!C71*100*(3/12))+('입력값'!C72*100*(3/12))+('입력값'!C73*100*(3/12))=0,0,('입력값'!AA81+'입력값'!AA82)*('입력값'!C62*100*(3/12))/(('입력값'!C62*100*(3/12))+('입력값'!C63*100*(3/12)*(1+'입력값'!D63/100)^4)+('입력값'!C64*100*(3/12))+('입력값'!C65*100*(3/12))+('입력값'!C66*100*(3/12)*(1+'입력값'!D66/100)^4)+('입력값'!C67*100*(3/12)*(1+'입력값'!D67/100)^4)+('입력값'!C68*100*(3/12)*(1+'입력값'!D68/100)^4)+('입력값'!C69*100*(3/12))+('입력값'!C70*100*(3/12))+('입력값'!C71*100*(3/12))+('입력값'!C72*100*(3/12))+('입력값'!C73*100*(3/12))))) | AB9: =-(IF(('입력값'!C62*100*(3/12))+('입력값'!C63*100*(3/12)*(1+'입력값'!D63/100)^4)+('입력값'!C64*100*(3/12))+('입력값'!C65*100*(3/12))+('입력값'!C66*100*(3/12)*(1+'입력값'!D66/100)^4)+('입력값'!C67*100*(3/12)*(1+'입력값'!D67/100)^4)+('입력값'!C68*100*(3/12)*(1+'입력값'!D68/100)^4)+('입력값'!C69*100*(3/12))+('입력값'!C70*100*(3/12))+('입력값'!C71*100*(3/12))+('입력값'!C72*100*(3/12))+('입력값'!C73*100*(3/12))=0,0,('입력값'!AB81+'입력값'!AB82)*('입력값'!C62*100*(3/12))/(('입력값'!C62*100*(3/12))+('입력값'!C63*100*(3/12)*(1+'입력값'!D63/100)^4)+('입력값'!C64*100*(3/12))+('입력값'!C65*100*(3/12))+('입력값'!C66*100*(3/12)*(1+'입력값'!D66/100)^4)+('입력값'!C67*100*(3/12)*(1+'입력값'!D67/100)^4)+('입력값'!C68*100*(3/12)*(1+'입력값'!D68/100)^4)+('입력값'!C69*100*(3/12))+('입력값'!C70*100*(3/12))+('입력값'!C71*100*(3/12))+('입력값'!C72*100*(3/12))+('입력값'!C73*100*(3/12))))) | AC9: =-(IF(('입력값'!C62*100*(3/12))+('입력값'!C63*100*(3/12)*(1+'입력값'!D63/100)^4)+('입력값'!C64*100*(3/12))+('입력값'!C65*100*(3/12))+('입력값'!C66*100*(3/12)*(1+'입력값'!D66/100)^4)+('입력값'!C67*100*(3/12)*(1+'입력값'!D67/100)^4)+('입력값'!C68*100*(3/12)*(1+'입력값'!D68/100)^4)+('입력값'!C69*100*(3/12))+('입력값'!C70*100*(3/12))+('입력값'!C71*100*(3/12))+('입력값'!C72*100*(3/12))+('입력값'!C73*100*(3/12))=0,0,('입력값'!AC81+'입력값'!AC82)*('입력값'!C62*100*(3/12))/(('입력값'!C62*100*(3/12))+('입력값'!C63*100*(3/12)*(1+'입력값'!D63/100)^4)+('입력값'!C64*100*(3/12))+('입력값'!C65*100*(3/12))+('입력값'!C66*100*(3/12)*(1+'입력값'!D66/100)^4)+('입력값'!C67*100*(3/12)*(1+'입력값'!D67/100)^4)+('입력값'!C68*100*(3/12)*(1+'입력값'!D68/100)^4)+('입력값'!C69*100*(3/12))+('입력값'!C70*100*(3/12))+('입력값'!C71*100*(3/12))+('입력값'!C72*100*(3/12))+('입력값'!C73*100*(3/12))))) | AD9: =-(IF(('입력값'!C62*100*(3/12))+('입력값'!C63*100*(3/12)*(1+'입력값'!D63/100)^4)+('입력값'!C64*100*(3/12))+('입력값'!C65*100*(3/12))+('입력값'!C66*100*(3/12)*(1+'입력값'!D66/100)^4)+('입력값'!C67*100*(3/12)*(1+'입력값'!D67/100)^4)+('입력값'!C68*100*(3/12)*(1+'입력값'!D68/100)^4)+('입력값'!C69*100*(3/12))+('입력값'!C70*100*(3/12))+('입력값'!C71*100*(3/12))+('입력값'!C72*100*(3/12))+('입력값'!C73*100*(3/12))=0,0,('입력값'!AD81+'입력값'!AD82)*('입력값'!C62*100*(3/12))/(('입력값'!C62*100*(3/12))+('입력값'!C63*100*(3/12)*(1+'입력값'!D63/100)^4)+('입력값'!C64*100*(3/12))+('입력값'!C65*100*(3/12))+('입력값'!C66*100*(3/12)*(1+'입력값'!D66/100)^4)+('입력값'!C67*100*(3/12)*(1+'입력값'!D67/100)^4)+('입력값'!C68*100*(3/12)*(1+'입력값'!D68/100)^4)+('입력값'!C69*100*(3/12))+('입력값'!C70*100*(3/12))+('입력값'!C71*100*(3/12))+('입력값'!C72*100*(3/12))+('입력값'!C73*100*(3/12))))) | AE9: =-(IF(('입력값'!C62*100*(3/12))+('입력값'!C63*100*(3/12)*(1+'입력값'!D63/100)^5)+('입력값'!C64*100*(3/12))+('입력값'!C65*100*(3/12))+('입력값'!C66*100*(3/12)*(1+'입력값'!D66/100)^5)+('입력값'!C67*100*(3/12)*(1+'입력값'!D67/100)^5)+('입력값'!C68*100*(3/12)*(1+'입력값'!D68/100)^5)+('입력값'!C69*100*(3/12))+('입력값'!C70*100*(3/12))+('입력값'!C71*100*(3/12))+('입력값'!C72*100*(3/12))+('입력값'!C73*100*(3/12))=0,0,('입력값'!AE81+'입력값'!AE82)*('입력값'!C62*100*(3/12))/(('입력값'!C62*100*(3/12))+('입력값'!C63*100*(3/12)*(1+'입력값'!D63/100)^5)+('입력값'!C64*100*(3/12))+('입력값'!C65*100*(3/12))+('입력값'!C66*100*(3/12)*(1+'입력값'!D66/100)^5)+('입력값'!C67*100*(3/12)*(1+'입력값'!D67/100)^5)+('입력값'!C68*100*(3/12)*(1+'입력값'!D68/100)^5)+('입력값'!C69*100*(3/12))+('입력값'!C70*100*(3/12))+('입력값'!C71*100*(3/12))+('입력값'!C72*100*(3/12))+('입력값'!C73*100*(3/12))))) | AF9: =-(IF(('입력값'!C62*100*(3/12))+('입력값'!C63*100*(3/12)*(1+'입력값'!D63/100)^5)+('입력값'!C64*100*(3/12))+('입력값'!C65*100*(3/12))+('입력값'!C66*100*(3/12)*(1+'입력값'!D66/100)^5)+('입력값'!C67*100*(3/12)*(1+'입력값'!D67/100)^5)+('입력값'!C68*100*(3/12)*(1+'입력값'!D68/100)^5)+('입력값'!C69*100*(3/12))+('입력값'!C70*100*(3/12))+('입력값'!C71*100*(3/12))+('입력값'!C72*100*(3/12))+('입력값'!C73*100*(3/12))=0,0,('입력값'!AF81+'입력값'!AF82)*('입력값'!C62*100*(3/12))/(('입력값'!C62*100*(3/12))+('입력값'!C63*100*(3/12)*(1+'입력값'!D63/100)^5)+('입력값'!C64*100*(3/12))+('입력값'!C65*100*(3/12))+('입력값'!C66*100*(3/12)*(1+'입력값'!D66/100)^5)+('입력값'!C67*100*(3/12)*(1+'입력값'!D67/100)^5)+('입력값'!C68*100*(3/12)*(1+'입력값'!D68/100)^5)+('입력값'!C69*100*(3/12))+('입력값'!C70*100*(3/12))+('입력값'!C71*100*(3/12))+('입력값'!C72*100*(3/12))+('입력값'!C73*100*(3/12))))) | AG9: =-(IF(('입력값'!C62*100*(3/12))+('입력값'!C63*100*(3/12)*(1+'입력값'!D63/100)^5)+('입력값'!C64*100*(3/12))+('입력값'!C65*100*(3/12))+('입력값'!C66*100*(3/12)*(1+'입력값'!D66/100)^5)+('입력값'!C67*100*(3/12)*(1+'입력값'!D67/100)^5)+('입력값'!C68*100*(3/12)*(1+'입력값'!D68/100)^5)+('입력값'!C69*100*(3/12))+('입력값'!C70*100*(3/12))+('입력값'!C71*100*(3/12))+('입력값'!C72*100*(3/12))+('입력값'!C73*100*(3/12))=0,0,('입력값'!AG81+'입력값'!AG82)*('입력값'!C62*100*(3/12))/(('입력값'!C62*100*(3/12))+('입력값'!C63*100*(3/12)*(1+'입력값'!D63/100)^5)+('입력값'!C64*100*(3/12))+('입력값'!C65*100*(3/12))+('입력값'!C66*100*(3/12)*(1+'입력값'!D66/100)^5)+('입력값'!C67*100*(3/12)*(1+'입력값'!D67/100)^5)+('입력값'!C68*100*(3/12)*(1+'입력값'!D68/100)^5)+('입력값'!C69*100*(3/12))+('입력값'!C70*100*(3/12))+('입력값'!C71*100*(3/12))+('입력값'!C72*100*(3/12))+('입력값'!C73*100*(3/12))))) | AH9: =-(IF(('입력값'!C62*100*(3/12))+('입력값'!C63*100*(3/12)*(1+'입력값'!D63/100)^5)+('입력값'!C64*100*(3/12))+('입력값'!C65*100*(3/12))+('입력값'!C66*100*(3/12)*(1+'입력값'!D66/100)^5)+('입력값'!C67*100*(3/12)*(1+'입력값'!D67/100)^5)+('입력값'!C68*100*(3/12)*(1+'입력값'!D68/100)^5)+('입력값'!C69*100*(3/12))+('입력값'!C70*100*(3/12))+('입력값'!C71*100*(3/12))+('입력값'!C72*100*(3/12))+('입력값'!C73*100*(3/12))=0,0,('입력값'!AH81+'입력값'!AH82)*('입력값'!C62*100*(3/12))/(('입력값'!C62*100*(3/12))+('입력값'!C63*100*(3/12)*(1+'입력값'!D63/100)^5)+('입력값'!C64*100*(3/12))+('입력값'!C65*100*(3/12))+('입력값'!C66*100*(3/12)*(1+'입력값'!D66/100)^5)+('입력값'!C67*100*(3/12)*(1+'입력값'!D67/100)^5)+('입력값'!C68*100*(3/12)*(1+'입력값'!D68/100)^5)+('입력값'!C69*100*(3/12))+('입력값'!C70*100*(3/12))+('입력값'!C71*100*(3/12))+('입력값'!C72*100*(3/12))+('입력값'!C73*100*(3/12))))) | AI9: =-(IF(('입력값'!C62*100*(3/12))+('입력값'!C63*100*(3/12)*(1+'입력값'!D63/100)^6)+('입력값'!C64*100*(3/12))+('입력값'!C65*100*(3/12))+('입력값'!C66*100*(3/12)*(1+'입력값'!D66/100)^6)+('입력값'!C67*100*(3/12)*(1+'입력값'!D67/100)^6)+('입력값'!C68*100*(3/12)*(1+'입력값'!D68/100)^6)+('입력값'!C69*100*(3/12))+('입력값'!C70*100*(3/12))+('입력값'!C71*100*(3/12))+('입력값'!C72*100*(3/12))+('입력값'!C73*100*(3/12))=0,0,('입력값'!AI81+'입력값'!AI82)*('입력값'!C62*100*(3/12))/(('입력값'!C62*100*(3/12))+('입력값'!C63*100*(3/12)*(1+'입력값'!D63/100)^6)+('입력값'!C64*100*(3/12))+('입력값'!C65*100*(3/12))+('입력값'!C66*100*(3/12)*(1+'입력값'!D66/100)^6)+('입력값'!C67*100*(3/12)*(1+'입력값'!D67/100)^6)+('입력값'!C68*100*(3/12)*(1+'입력값'!D68/100)^6)+('입력값'!C69*100*(3/12))+('입력값'!C70*100*(3/12))+('입력값'!C71*100*(3/12))+('입력값'!C72*100*(3/12))+('입력값'!C73*100*(3/12))))) | AJ9: =-(IF(('입력값'!C62*100*(3/12))+('입력값'!C63*100*(3/12)*(1+'입력값'!D63/100)^6)+('입력값'!C64*100*(3/12))+('입력값'!C65*100*(3/12))+('입력값'!C66*100*(3/12)*(1+'입력값'!D66/100)^6)+('입력값'!C67*100*(3/12)*(1+'입력값'!D67/100)^6)+('입력값'!C68*100*(3/12)*(1+'입력값'!D68/100)^6)+('입력값'!C69*100*(3/12))+('입력값'!C70*100*(3/12))+('입력값'!C71*100*(3/12))+('입력값'!C72*100*(3/12))+('입력값'!C73*100*(3/12))=0,0,('입력값'!AJ81+'입력값'!AJ82)*('입력값'!C62*100*(3/12))/(('입력값'!C62*100*(3/12))+('입력값'!C63*100*(3/12)*(1+'입력값'!D63/100)^6)+('입력값'!C64*100*(3/12))+('입력값'!C65*100*(3/12))+('입력값'!C66*100*(3/12)*(1+'입력값'!D66/100)^6)+('입력값'!C67*100*(3/12)*(1+'입력값'!D67/100)^6)+('입력값'!C68*100*(3/12)*(1+'입력값'!D68/100)^6)+('입력값'!C69*100*(3/12))+('입력값'!C70*100*(3/12))+('입력값'!C71*100*(3/12))+('입력값'!C72*100*(3/12))+('입력값'!C73*100*(3/12))))) | AK9: =-(IF(('입력값'!C62*100*(3/12))+('입력값'!C63*100*(3/12)*(1+'입력값'!D63/100)^6)+('입력값'!C64*100*(3/12))+('입력값'!C65*100*(3/12))+('입력값'!C66*100*(3/12)*(1+'입력값'!D66/100)^6)+('입력값'!C67*100*(3/12)*(1+'입력값'!D67/100)^6)+('입력값'!C68*100*(3/12)*(1+'입력값'!D68/100)^6)+('입력값'!C69*100*(3/12))+('입력값'!C70*100*(3/12))+('입력값'!C71*100*(3/12))+('입력값'!C72*100*(3/12))+('입력값'!C73*100*(3/12))=0,0,('입력값'!AK81+'입력값'!AK82)*('입력값'!C62*100*(3/12))/(('입력값'!C62*100*(3/12))+('입력값'!C63*100*(3/12)*(1+'입력값'!D63/100)^6)+('입력값'!C64*100*(3/12))+('입력값'!C65*100*(3/12))+('입력값'!C66*100*(3/12)*(1+'입력값'!D66/100)^6)+('입력값'!C67*100*(3/12)*(1+'입력값'!D67/100)^6)+('입력값'!C68*100*(3/12)*(1+'입력값'!D68/100)^6)+('입력값'!C69*100*(3/12))+('입력값'!C70*100*(3/12))+('입력값'!C71*100*(3/12))+('입력값'!C72*100*(3/12))+('입력값'!C73*100*(3/12))))) | AL9: =-(IF(('입력값'!C62*100*(3/12))+('입력값'!C63*100*(3/12)*(1+'입력값'!D63/100)^6)+('입력값'!C64*100*(3/12))+('입력값'!C65*100*(3/12))+('입력값'!C66*100*(3/12)*(1+'입력값'!D66/100)^6)+('입력값'!C67*100*(3/12)*(1+'입력값'!D67/100)^6)+('입력값'!C68*100*(3/12)*(1+'입력값'!D68/100)^6)+('입력값'!C69*100*(3/12))+('입력값'!C70*100*(3/12))+('입력값'!C71*100*(3/12))+('입력값'!C72*100*(3/12))+('입력값'!C73*100*(3/12))=0,0,('입력값'!AL81+'입력값'!AL82)*('입력값'!C62*100*(3/12))/(('입력값'!C62*100*(3/12))+('입력값'!C63*100*(3/12)*(1+'입력값'!D63/100)^6)+('입력값'!C64*100*(3/12))+('입력값'!C65*100*(3/12))+('입력값'!C66*100*(3/12)*(1+'입력값'!D66/100)^6)+('입력값'!C67*100*(3/12)*(1+'입력값'!D67/100)^6)+('입력값'!C68*100*(3/12)*(1+'입력값'!D68/100)^6)+('입력값'!C69*100*(3/12))+('입력값'!C70*100*(3/12))+('입력값'!C71*100*(3/12))+('입력값'!C72*100*(3/12))+('입력값'!C73*100*(3/12))))) | AM9: =-(IF(('입력값'!C62*100*(3/12))+('입력값'!C63*100*(3/12)*(1+'입력값'!D63/100)^7)+('입력값'!C64*100*(3/12))+('입력값'!C65*100*(3/12))+('입력값'!C66*100*(3/12)*(1+'입력값'!D66/100)^7)+('입력값'!C67*100*(3/12)*(1+'입력값'!D67/100)^7)+('입력값'!C68*100*(3/12)*(1+'입력값'!D68/100)^7)+('입력값'!C69*100*(3/12))+('입력값'!C70*100*(3/12))+('입력값'!C71*100*(3/12))+('입력값'!C72*100*(3/12))+('입력값'!C73*100*(3/12))=0,0,('입력값'!AM81+'입력값'!AM82)*('입력값'!C62*100*(3/12))/(('입력값'!C62*100*(3/12))+('입력값'!C63*100*(3/12)*(1+'입력값'!D63/100)^7)+('입력값'!C64*100*(3/12))+('입력값'!C65*100*(3/12))+('입력값'!C66*100*(3/12)*(1+'입력값'!D66/100)^7)+('입력값'!C67*100*(3/12)*(1+'입력값'!D67/100)^7)+('입력값'!C68*100*(3/12)*(1+'입력값'!D68/100)^7)+('입력값'!C69*100*(3/12))+('입력값'!C70*100*(3/12))+('입력값'!C71*100*(3/12))+('입력값'!C72*100*(3/12))+('입력값'!C73*100*(3/12))))) | AN9: =-(IF(('입력값'!C62*100*(3/12))+('입력값'!C63*100*(3/12)*(1+'입력값'!D63/100)^7)+('입력값'!C64*100*(3/12))+('입력값'!C65*100*(3/12))+('입력값'!C66*100*(3/12)*(1+'입력값'!D66/100)^7)+('입력값'!C67*100*(3/12)*(1+'입력값'!D67/100)^7)+('입력값'!C68*100*(3/12)*(1+'입력값'!D68/100)^7)+('입력값'!C69*100*(3/12))+('입력값'!C70*100*(3/12))+('입력값'!C71*100*(3/12))+('입력값'!C72*100*(3/12))+('입력값'!C73*100*(3/12))=0,0,('입력값'!AN81+'입력값'!AN82)*('입력값'!C62*100*(3/12))/(('입력값'!C62*100*(3/12))+('입력값'!C63*100*(3/12)*(1+'입력값'!D63/100)^7)+('입력값'!C64*100*(3/12))+('입력값'!C65*100*(3/12))+('입력값'!C66*100*(3/12)*(1+'입력값'!D66/100)^7)+('입력값'!C67*100*(3/12)*(1+'입력값'!D67/100)^7)+('입력값'!C68*100*(3/12)*(1+'입력값'!D68/100)^7)+('입력값'!C69*100*(3/12))+('입력값'!C70*100*(3/12))+('입력값'!C71*100*(3/12))+('입력값'!C72*100*(3/12))+('입력값'!C73*100*(3/12))))) | AO9: =-(IF(('입력값'!C62*100*(3/12))+('입력값'!C63*100*(3/12)*(1+'입력값'!D63/100)^7)+('입력값'!C64*100*(3/12))+('입력값'!C65*100*(3/12))+('입력값'!C66*100*(3/12)*(1+'입력값'!D66/100)^7)+('입력값'!C67*100*(3/12)*(1+'입력값'!D67/100)^7)+('입력값'!C68*100*(3/12)*(1+'입력값'!D68/100)^7)+('입력값'!C69*100*(3/12))+('입력값'!C70*100*(3/12))+('입력값'!C71*100*(3/12))+('입력값'!C72*100*(3/12))+('입력값'!C73*100*(3/12))=0,0,('입력값'!AO81+'입력값'!AO82)*('입력값'!C62*100*(3/12))/(('입력값'!C62*100*(3/12))+('입력값'!C63*100*(3/12)*(1+'입력값'!D63/100)^7)+('입력값'!C64*100*(3/12))+('입력값'!C65*100*(3/12))+('입력값'!C66*100*(3/12)*(1+'입력값'!D66/100)^7)+('입력값'!C67*100*(3/12)*(1+'입력값'!D67/100)^7)+('입력값'!C68*100*(3/12)*(1+'입력값'!D68/100)^7)+('입력값'!C69*100*(3/12))+('입력값'!C70*100*(3/12))+('입력값'!C71*100*(3/12))+('입력값'!C72*100*(3/12))+('입력값'!C73*100*(3/12))))) | AP9: =-(IF(('입력값'!C62*100*(3/12))+('입력값'!C63*100*(3/12)*(1+'입력값'!D63/100)^7)+('입력값'!C64*100*(3/12))+('입력값'!C65*100*(3/12))+('입력값'!C66*100*(3/12)*(1+'입력값'!D66/100)^7)+('입력값'!C67*100*(3/12)*(1+'입력값'!D67/100)^7)+('입력값'!C68*100*(3/12)*(1+'입력값'!D68/100)^7)+('입력값'!C69*100*(3/12))+('입력값'!C70*100*(3/12))+('입력값'!C71*100*(3/12))+('입력값'!C72*100*(3/12))+('입력값'!C73*100*(3/12))=0,0,('입력값'!AP81+'입력값'!AP82)*('입력값'!C62*100*(3/12))/(('입력값'!C62*100*(3/12))+('입력값'!C63*100*(3/12)*(1+'입력값'!D63/100)^7)+('입력값'!C64*100*(3/12))+('입력값'!C65*100*(3/12))+('입력값'!C66*100*(3/12)*(1+'입력값'!D66/100)^7)+('입력값'!C67*100*(3/12)*(1+'입력값'!D67/100)^7)+('입력값'!C68*100*(3/12)*(1+'입력값'!D68/100)^7)+('입력값'!C69*100*(3/12))+('입력값'!C70*100*(3/12))+('입력값'!C71*100*(3/12))+('입력값'!C72*100*(3/12))+('입력값'!C73*100*(3/12))))) | AQ9: =-(IF(('입력값'!C62*100*(3/12))+('입력값'!C63*100*(3/12)*(1+'입력값'!D63/100)^8)+('입력값'!C64*100*(3/12))+('입력값'!C65*100*(3/12))+('입력값'!C66*100*(3/12)*(1+'입력값'!D66/100)^8)+('입력값'!C67*100*(3/12)*(1+'입력값'!D67/100)^8)+('입력값'!C68*100*(3/12)*(1+'입력값'!D68/100)^8)+('입력값'!C69*100*(3/12))+('입력값'!C70*100*(3/12))+('입력값'!C71*100*(3/12))+('입력값'!C72*100*(3/12))+('입력값'!C73*100*(3/12))=0,0,('입력값'!AQ81+'입력값'!AQ82)*('입력값'!C62*100*(3/12))/(('입력값'!C62*100*(3/12))+('입력값'!C63*100*(3/12)*(1+'입력값'!D63/100)^8)+('입력값'!C64*100*(3/12))+('입력값'!C65*100*(3/12))+('입력값'!C66*100*(3/12)*(1+'입력값'!D66/100)^8)+('입력값'!C67*100*(3/12)*(1+'입력값'!D67/100)^8)+('입력값'!C68*100*(3/12)*(1+'입력값'!D68/100)^8)+('입력값'!C69*100*(3/12))+('입력값'!C70*100*(3/12))+('입력값'!C71*100*(3/12))+('입력값'!C72*100*(3/12))+('입력값'!C73*100*(3/12))))) | AR9: =-(IF(('입력값'!C62*100*(3/12))+('입력값'!C63*100*(3/12)*(1+'입력값'!D63/100)^8)+('입력값'!C64*100*(3/12))+('입력값'!C65*100*(3/12))+('입력값'!C66*100*(3/12)*(1+'입력값'!D66/100)^8)+('입력값'!C67*100*(3/12)*(1+'입력값'!D67/100)^8)+('입력값'!C68*100*(3/12)*(1+'입력값'!D68/100)^8)+('입력값'!C69*100*(3/12))+('입력값'!C70*100*(3/12))+('입력값'!C71*100*(3/12))+('입력값'!C72*100*(3/12))+('입력값'!C73*100*(3/12))=0,0,('입력값'!AR81+'입력값'!AR82)*('입력값'!C62*100*(3/12))/(('입력값'!C62*100*(3/12))+('입력값'!C63*100*(3/12)*(1+'입력값'!D63/100)^8)+('입력값'!C64*100*(3/12))+('입력값'!C65*100*(3/12))+('입력값'!C66*100*(3/12)*(1+'입력값'!D66/100)^8)+('입력값'!C67*100*(3/12)*(1+'입력값'!D67/100)^8)+('입력값'!C68*100*(3/12)*(1+'입력값'!D68/100)^8)+('입력값'!C69*100*(3/12))+('입력값'!C70*100*(3/12))+('입력값'!C71*100*(3/12))+('입력값'!C72*100*(3/12))+('입력값'!C73*100*(3/12))))) | AS9: =-(IF(('입력값'!C62*100*(3/12))+('입력값'!C63*100*(3/12)*(1+'입력값'!D63/100)^8)+('입력값'!C64*100*(3/12))+('입력값'!C65*100*(3/12))+('입력값'!C66*100*(3/12)*(1+'입력값'!D66/100)^8)+('입력값'!C67*100*(3/12)*(1+'입력값'!D67/100)^8)+('입력값'!C68*100*(3/12)*(1+'입력값'!D68/100)^8)+('입력값'!C69*100*(3/12))+('입력값'!C70*100*(3/12))+('입력값'!C71*100*(3/12))+('입력값'!C72*100*(3/12))+('입력값'!C73*100*(3/12))=0,0,('입력값'!AS81+'입력값'!AS82)*('입력값'!C62*100*(3/12))/(('입력값'!C62*100*(3/12))+('입력값'!C63*100*(3/12)*(1+'입력값'!D63/100)^8)+('입력값'!C64*100*(3/12))+('입력값'!C65*100*(3/12))+('입력값'!C66*100*(3/12)*(1+'입력값'!D66/100)^8)+('입력값'!C67*100*(3/12)*(1+'입력값'!D67/100)^8)+('입력값'!C68*100*(3/12)*(1+'입력값'!D68/100)^8)+('입력값'!C69*100*(3/12))+('입력값'!C70*100*(3/12))+('입력값'!C71*100*(3/12))+('입력값'!C72*100*(3/12))+('입력값'!C73*100*(3/12))))) | AT9: =-(IF(('입력값'!C62*100*(3/12))+('입력값'!C63*100*(3/12)*(1+'입력값'!D63/100)^8)+('입력값'!C64*100*(3/12))+('입력값'!C65*100*(3/12))+('입력값'!C66*100*(3/12)*(1+'입력값'!D66/100)^8)+('입력값'!C67*100*(3/12)*(1+'입력값'!D67/100)^8)+('입력값'!C68*100*(3/12)*(1+'입력값'!D68/100)^8)+('입력값'!C69*100*(3/12))+('입력값'!C70*100*(3/12))+('입력값'!C71*100*(3/12))+('입력값'!C72*100*(3/12))+('입력값'!C73*100*(3/12))=0,0,('입력값'!AT81+'입력값'!AT82)*('입력값'!C62*100*(3/12))/(('입력값'!C62*100*(3/12))+('입력값'!C63*100*(3/12)*(1+'입력값'!D63/100)^8)+('입력값'!C64*100*(3/12))+('입력값'!C65*100*(3/12))+('입력값'!C66*100*(3/12)*(1+'입력값'!D66/100)^8)+('입력값'!C67*100*(3/12)*(1+'입력값'!D67/100)^8)+('입력값'!C68*100*(3/12)*(1+'입력값'!D68/100)^8)+('입력값'!C69*100*(3/12))+('입력값'!C70*100*(3/12))+('입력값'!C71*100*(3/12))+('입력값'!C72*100*(3/12))+('입력값'!C73*100*(3/12))))) | AU9: =-(IF(('입력값'!C62*100*(3/12))+('입력값'!C63*100*(3/12)*(1+'입력값'!D63/100)^9)+('입력값'!C64*100*(3/12))+('입력값'!C65*100*(3/12))+('입력값'!C66*100*(3/12)*(1+'입력값'!D66/100)^9)+('입력값'!C67*100*(3/12)*(1+'입력값'!D67/100)^9)+('입력값'!C68*100*(3/12)*(1+'입력값'!D68/100)^9)+('입력값'!C69*100*(3/12))+('입력값'!C70*100*(3/12))+('입력값'!C71*100*(3/12))+('입력값'!C72*100*(3/12))+('입력값'!C73*100*(3/12))=0,0,('입력값'!AU81+'입력값'!AU82)*('입력값'!C62*100*(3/12))/(('입력값'!C62*100*(3/12))+('입력값'!C63*100*(3/12)*(1+'입력값'!D63/100)^9)+('입력값'!C64*100*(3/12))+('입력값'!C65*100*(3/12))+('입력값'!C66*100*(3/12)*(1+'입력값'!D66/100)^9)+('입력값'!C67*100*(3/12)*(1+'입력값'!D67/100)^9)+('입력값'!C68*100*(3/12)*(1+'입력값'!D68/100)^9)+('입력값'!C69*100*(3/12))+('입력값'!C70*100*(3/12))+('입력값'!C71*100*(3/12))+('입력값'!C72*100*(3/12))+('입력값'!C73*100*(3/12))))) | AV9: =-(IF(('입력값'!C62*100*(3/12))+('입력값'!C63*100*(3/12)*(1+'입력값'!D63/100)^9)+('입력값'!C64*100*(3/12))+('입력값'!C65*100*(3/12))+('입력값'!C66*100*(3/12)*(1+'입력값'!D66/100)^9)+('입력값'!C67*100*(3/12)*(1+'입력값'!D67/100)^9)+('입력값'!C68*100*(3/12)*(1+'입력값'!D68/100)^9)+('입력값'!C69*100*(3/12))+('입력값'!C70*100*(3/12))+('입력값'!C71*100*(3/12))+('입력값'!C72*100*(3/12))+('입력값'!C73*100*(3/12))=0,0,('입력값'!AV81+'입력값'!AV82)*('입력값'!C62*100*(3/12))/(('입력값'!C62*100*(3/12))+('입력값'!C63*100*(3/12)*(1+'입력값'!D63/100)^9)+('입력값'!C64*100*(3/12))+('입력값'!C65*100*(3/12))+('입력값'!C66*100*(3/12)*(1+'입력값'!D66/100)^9)+('입력값'!C67*100*(3/12)*(1+'입력값'!D67/100)^9)+('입력값'!C68*100*(3/12)*(1+'입력값'!D68/100)^9)+('입력값'!C69*100*(3/12))+('입력값'!C70*100*(3/12))+('입력값'!C71*100*(3/12))+('입력값'!C72*100*(3/12))+('입력값'!C73*100*(3/12))))) | AW9: =-(IF(('입력값'!C62*100*(3/12))+('입력값'!C63*100*(3/12)*(1+'입력값'!D63/100)^9)+('입력값'!C64*100*(3/12))+('입력값'!C65*100*(3/12))+('입력값'!C66*100*(3/12)*(1+'입력값'!D66/100)^9)+('입력값'!C67*100*(3/12)*(1+'입력값'!D67/100)^9)+('입력값'!C68*100*(3/12)*(1+'입력값'!D68/100)^9)+('입력값'!C69*100*(3/12))+('입력값'!C70*100*(3/12))+('입력값'!C71*100*(3/12))+('입력값'!C72*100*(3/12))+('입력값'!C73*100*(3/12))=0,0,('입력값'!AW81+'입력값'!AW82)*('입력값'!C62*100*(3/12))/(('입력값'!C62*100*(3/12))+('입력값'!C63*100*(3/12)*(1+'입력값'!D63/100)^9)+('입력값'!C64*100*(3/12))+('입력값'!C65*100*(3/12))+('입력값'!C66*100*(3/12)*(1+'입력값'!D66/100)^9)+('입력값'!C67*100*(3/12)*(1+'입력값'!D67/100)^9)+('입력값'!C68*100*(3/12)*(1+'입력값'!D68/100)^9)+('입력값'!C69*100*(3/12))+('입력값'!C70*100*(3/12))+('입력값'!C71*100*(3/12))+('입력값'!C72*100*(3/12))+('입력값'!C73*100*(3/12))))) | AX9: =-(IF(('입력값'!C62*100*(3/12))+('입력값'!C63*100*(3/12)*(1+'입력값'!D63/100)^9)+('입력값'!C64*100*(3/12))+('입력값'!C65*100*(3/12))+('입력값'!C66*100*(3/12)*(1+'입력값'!D66/100)^9)+('입력값'!C67*100*(3/12)*(1+'입력값'!D67/100)^9)+('입력값'!C68*100*(3/12)*(1+'입력값'!D68/100)^9)+('입력값'!C69*100*(3/12))+('입력값'!C70*100*(3/12))+('입력값'!C71*100*(3/12))+('입력값'!C72*100*(3/12))+('입력값'!C73*100*(3/12))=0,0,('입력값'!AX81+'입력값'!AX82)*('입력값'!C62*100*(3/12))/(('입력값'!C62*100*(3/12))+('입력값'!C63*100*(3/12)*(1+'입력값'!D63/100)^9)+('입력값'!C64*100*(3/12))+('입력값'!C65*100*(3/12))+('입력값'!C66*100*(3/12)*(1+'입력값'!D66/100)^9)+('입력값'!C67*100*(3/12)*(1+'입력값'!D67/100)^9)+('입력값'!C68*100*(3/12)*(1+'입력값'!D68/100)^9)+('입력값'!C69*100*(3/12))+('입력값'!C70*100*(3/12))+('입력값'!C71*100*(3/12))+('입력값'!C72*100*(3/12))+('입력값'!C73*100*(3/12))))) | AY9: =-(IF(('입력값'!C62*100*(3/12))+('입력값'!C63*100*(3/12)*(1+'입력값'!D63/100)^10)+('입력값'!C64*100*(3/12))+('입력값'!C65*100*(3/12))+('입력값'!C66*100*(3/12)*(1+'입력값'!D66/100)^10)+('입력값'!C67*100*(3/12)*(1+'입력값'!D67/100)^10)+('입력값'!C68*100*(3/12)*(1+'입력값'!D68/100)^10)+('입력값'!C69*100*(3/12))+('입력값'!C70*100*(3/12))+('입력값'!C71*100*(3/12))+('입력값'!C72*100*(3/12))+('입력값'!C73*100*(3/12))=0,0,('입력값'!AY81+'입력값'!AY82)*('입력값'!C62*100*(3/12))/(('입력값'!C62*100*(3/12))+('입력값'!C63*100*(3/12)*(1+'입력값'!D63/100)^10)+('입력값'!C64*100*(3/12))+('입력값'!C65*100*(3/12))+('입력값'!C66*100*(3/12)*(1+'입력값'!D66/100)^10)+('입력값'!C67*100*(3/12)*(1+'입력값'!D67/100)^10)+('입력값'!C68*100*(3/12)*(1+'입력값'!D68/100)^10)+('입력값'!C69*100*(3/12))+('입력값'!C70*100*(3/12))+('입력값'!C71*100*(3/12))+('입력값'!C72*100*(3/12))+('입력값'!C73*100*(3/12))))) | AZ9: =-(IF(('입력값'!C62*100*(3/12))+('입력값'!C63*100*(3/12)*(1+'입력값'!D63/100)^10)+('입력값'!C64*100*(3/12))+('입력값'!C65*100*(3/12))+('입력값'!C66*100*(3/12)*(1+'입력값'!D66/100)^10)+('입력값'!C67*100*(3/12)*(1+'입력값'!D67/100)^10)+('입력값'!C68*100*(3/12)*(1+'입력값'!D68/100)^10)+('입력값'!C69*100*(3/12))+('입력값'!C70*100*(3/12))+('입력값'!C71*100*(3/12))+('입력값'!C72*100*(3/12))+('입력값'!C73*100*(3/12))=0,0,('입력값'!AZ81+'입력값'!AZ82)*('입력값'!C62*100*(3/12))/(('입력값'!C62*100*(3/12))+('입력값'!C63*100*(3/12)*(1+'입력값'!D63/100)^10)+('입력값'!C64*100*(3/12))+('입력값'!C65*100*(3/12))+('입력값'!C66*100*(3/12)*(1+'입력값'!D66/100)^10)+('입력값'!C67*100*(3/12)*(1+'입력값'!D67/100)^10)+('입력값'!C68*100*(3/12)*(1+'입력값'!D68/100)^10)+('입력값'!C69*100*(3/12))+('입력값'!C70*100*(3/12))+('입력값'!C71*100*(3/12))+('입력값'!C72*100*(3/12))+('입력값'!C73*100*(3/12))))) | BA9: =-(IF(('입력값'!C62*100*(3/12))+('입력값'!C63*100*(3/12)*(1+'입력값'!D63/100)^10)+('입력값'!C64*100*(3/12))+('입력값'!C65*100*(3/12))+('입력값'!C66*100*(3/12)*(1+'입력값'!D66/100)^10)+('입력값'!C67*100*(3/12)*(1+'입력값'!D67/100)^10)+('입력값'!C68*100*(3/12)*(1+'입력값'!D68/100)^10)+('입력값'!C69*100*(3/12))+('입력값'!C70*100*(3/12))+('입력값'!C71*100*(3/12))+('입력값'!C72*100*(3/12))+('입력값'!C73*100*(3/12))=0,0,('입력값'!BA81+'입력값'!BA82)*('입력값'!C62*100*(3/12))/(('입력값'!C62*100*(3/12))+('입력값'!C63*100*(3/12)*(1+'입력값'!D63/100)^10)+('입력값'!C64*100*(3/12))+('입력값'!C65*100*(3/12))+('입력값'!C66*100*(3/12)*(1+'입력값'!D66/100)^10)+('입력값'!C67*100*(3/12)*(1+'입력값'!D67/100)^10)+('입력값'!C68*100*(3/12)*(1+'입력값'!D68/100)^10)+('입력값'!C69*100*(3/12))+('입력값'!C70*100*(3/12))+('입력값'!C71*100*(3/12))+('입력값'!C72*100*(3/12))+('입력값'!C73*100*(3/12))))) | BB9: =-(IF(('입력값'!C62*100*(3/12))+('입력값'!C63*100*(3/12)*(1+'입력값'!D63/100)^10)+('입력값'!C64*100*(3/12))+('입력값'!C65*100*(3/12))+('입력값'!C66*100*(3/12)*(1+'입력값'!D66/100)^10)+('입력값'!C67*100*(3/12)*(1+'입력값'!D67/100)^10)+('입력값'!C68*100*(3/12)*(1+'입력값'!D68/100)^10)+('입력값'!C69*100*(3/12))+('입력값'!C70*100*(3/12))+('입력값'!C71*100*(3/12))+('입력값'!C72*100*(3/12))+('입력값'!C73*100*(3/12))=0,0,('입력값'!BB81+'입력값'!BB82)*('입력값'!C62*100*(3/12))/(('입력값'!C62*100*(3/12))+('입력값'!C63*100*(3/12)*(1+'입력값'!D63/100)^10)+('입력값'!C64*100*(3/12))+('입력값'!C65*100*(3/12))+('입력값'!C66*100*(3/12)*(1+'입력값'!D66/100)^10)+('입력값'!C67*100*(3/12)*(1+'입력값'!D67/100)^10)+('입력값'!C68*100*(3/12)*(1+'입력값'!D68/100)^10)+('입력값'!C69*100*(3/12))+('입력값'!C70*100*(3/12))+('입력값'!C71*100*(3/12))+('입력값'!C72*100*(3/12))+('입력값'!C73*100*(3/12))))) | BC9: =-(IF(('입력값'!C62*100*(3/12))+('입력값'!C63*100*(3/12)*(1+'입력값'!D63/100)^11)+('입력값'!C64*100*(3/12))+('입력값'!C65*100*(3/12))+('입력값'!C66*100*(3/12)*(1+'입력값'!D66/100)^11)+('입력값'!C67*100*(3/12)*(1+'입력값'!D67/100)^11)+('입력값'!C68*100*(3/12)*(1+'입력값'!D68/100)^11)+('입력값'!C69*100*(3/12))+('입력값'!C70*100*(3/12))+('입력값'!C71*100*(3/12))+('입력값'!C72*100*(3/12))+('입력값'!C73*100*(3/12))=0,0,('입력값'!BC81+'입력값'!BC82)*('입력값'!C62*100*(3/12))/(('입력값'!C62*100*(3/12))+('입력값'!C63*100*(3/12)*(1+'입력값'!D63/100)^11)+('입력값'!C64*100*(3/12))+('입력값'!C65*100*(3/12))+('입력값'!C66*100*(3/12)*(1+'입력값'!D66/100)^11)+('입력값'!C67*100*(3/12)*(1+'입력값'!D67/100)^11)+('입력값'!C68*100*(3/12)*(1+'입력값'!D68/100)^11)+('입력값'!C69*100*(3/12))+('입력값'!C70*100*(3/12))+('입력값'!C71*100*(3/12))+('입력값'!C72*100*(3/12))+('입력값'!C73*100*(3/12))))) | BD9: =-(IF(('입력값'!C62*100*(3/12))+('입력값'!C63*100*(3/12)*(1+'입력값'!D63/100)^11)+('입력값'!C64*100*(3/12))+('입력값'!C65*100*(3/12))+('입력값'!C66*100*(3/12)*(1+'입력값'!D66/100)^11)+('입력값'!C67*100*(3/12)*(1+'입력값'!D67/100)^11)+('입력값'!C68*100*(3/12)*(1+'입력값'!D68/100)^11)+('입력값'!C69*100*(3/12))+('입력값'!C70*100*(3/12))+('입력값'!C71*100*(3/12))+('입력값'!C72*100*(3/12))+('입력값'!C73*100*(3/12))=0,0,('입력값'!BD81+'입력값'!BD82)*('입력값'!C62*100*(3/12))/(('입력값'!C62*100*(3/12))+('입력값'!C63*100*(3/12)*(1+'입력값'!D63/100)^11)+('입력값'!C64*100*(3/12))+('입력값'!C65*100*(3/12))+('입력값'!C66*100*(3/12)*(1+'입력값'!D66/100)^11)+('입력값'!C67*100*(3/12)*(1+'입력값'!D67/100)^11)+('입력값'!C68*100*(3/12)*(1+'입력값'!D68/100)^11)+('입력값'!C69*100*(3/12))+('입력값'!C70*100*(3/12))+('입력값'!C71*100*(3/12))+('입력값'!C72*100*(3/12))+('입력값'!C73*100*(3/12))))) | BE9: =-(IF(('입력값'!C62*100*(3/12))+('입력값'!C63*100*(3/12)*(1+'입력값'!D63/100)^11)+('입력값'!C64*100*(3/12))+('입력값'!C65*100*(3/12))+('입력값'!C66*100*(3/12)*(1+'입력값'!D66/100)^11)+('입력값'!C67*100*(3/12)*(1+'입력값'!D67/100)^11)+('입력값'!C68*100*(3/12)*(1+'입력값'!D68/100)^11)+('입력값'!C69*100*(3/12))+('입력값'!C70*100*(3/12))+('입력값'!C71*100*(3/12))+('입력값'!C72*100*(3/12))+('입력값'!C73*100*(3/12))=0,0,('입력값'!BE81+'입력값'!BE82)*('입력값'!C62*100*(3/12))/(('입력값'!C62*100*(3/12))+('입력값'!C63*100*(3/12)*(1+'입력값'!D63/100)^11)+('입력값'!C64*100*(3/12))+('입력값'!C65*100*(3/12))+('입력값'!C66*100*(3/12)*(1+'입력값'!D66/100)^11)+('입력값'!C67*100*(3/12)*(1+'입력값'!D67/100)^11)+('입력값'!C68*100*(3/12)*(1+'입력값'!D68/100)^11)+('입력값'!C69*100*(3/12))+('입력값'!C70*100*(3/12))+('입력값'!C71*100*(3/12))+('입력값'!C72*100*(3/12))+('입력값'!C73*100*(3/12))))) | BF9: =-(IF(('입력값'!C62*100*(3/12))+('입력값'!C63*100*(3/12)*(1+'입력값'!D63/100)^11)+('입력값'!C64*100*(3/12))+('입력값'!C65*100*(3/12))+('입력값'!C66*100*(3/12)*(1+'입력값'!D66/100)^11)+('입력값'!C67*100*(3/12)*(1+'입력값'!D67/100)^11)+('입력값'!C68*100*(3/12)*(1+'입력값'!D68/100)^11)+('입력값'!C69*100*(3/12))+('입력값'!C70*100*(3/12))+('입력값'!C71*100*(3/12))+('입력값'!C72*100*(3/12))+('입력값'!C73*100*(3/12))=0,0,('입력값'!BF81+'입력값'!BF82)*('입력값'!C62*100*(3/12))/(('입력값'!C62*100*(3/12))+('입력값'!C63*100*(3/12)*(1+'입력값'!D63/100)^11)+('입력값'!C64*100*(3/12))+('입력값'!C65*100*(3/12))+('입력값'!C66*100*(3/12)*(1+'입력값'!D66/100)^11)+('입력값'!C67*100*(3/12)*(1+'입력값'!D67/100)^11)+('입력값'!C68*100*(3/12)*(1+'입력값'!D68/100)^11)+('입력값'!C69*100*(3/12))+('입력값'!C70*100*(3/12))+('입력값'!C71*100*(3/12))+('입력값'!C72*100*(3/12))+('입력값'!C73*100*(3/12))))) | BG9: =-(IF(('입력값'!C62*100*(3/12))+('입력값'!C63*100*(3/12)*(1+'입력값'!D63/100)^12)+('입력값'!C64*100*(3/12))+('입력값'!C65*100*(3/12))+('입력값'!C66*100*(3/12)*(1+'입력값'!D66/100)^12)+('입력값'!C67*100*(3/12)*(1+'입력값'!D67/100)^12)+('입력값'!C68*100*(3/12)*(1+'입력값'!D68/100)^12)+('입력값'!C69*100*(3/12))+('입력값'!C70*100*(3/12))+('입력값'!C71*100*(3/12))+('입력값'!C72*100*(3/12))+('입력값'!C73*100*(3/12))=0,0,('입력값'!BG81+'입력값'!BG82)*('입력값'!C62*100*(3/12))/(('입력값'!C62*100*(3/12))+('입력값'!C63*100*(3/12)*(1+'입력값'!D63/100)^12)+('입력값'!C64*100*(3/12))+('입력값'!C65*100*(3/12))+('입력값'!C66*100*(3/12)*(1+'입력값'!D66/100)^12)+('입력값'!C67*100*(3/12)*(1+'입력값'!D67/100)^12)+('입력값'!C68*100*(3/12)*(1+'입력값'!D68/100)^12)+('입력값'!C69*100*(3/12))+('입력값'!C70*100*(3/12))+('입력값'!C71*100*(3/12))+('입력값'!C72*100*(3/12))+('입력값'!C73*100*(3/12))))) | BH9: =-(IF(('입력값'!C62*100*(3/12))+('입력값'!C63*100*(3/12)*(1+'입력값'!D63/100)^12)+('입력값'!C64*100*(3/12))+('입력값'!C65*100*(3/12))+('입력값'!C66*100*(3/12)*(1+'입력값'!D66/100)^12)+('입력값'!C67*100*(3/12)*(1+'입력값'!D67/100)^12)+('입력값'!C68*100*(3/12)*(1+'입력값'!D68/100)^12)+('입력값'!C69*100*(3/12))+('입력값'!C70*100*(3/12))+('입력값'!C71*100*(3/12))+('입력값'!C72*100*(3/12))+('입력값'!C73*100*(3/12))=0,0,('입력값'!BH81+'입력값'!BH82)*('입력값'!C62*100*(3/12))/(('입력값'!C62*100*(3/12))+('입력값'!C63*100*(3/12)*(1+'입력값'!D63/100)^12)+('입력값'!C64*100*(3/12))+('입력값'!C65*100*(3/12))+('입력값'!C66*100*(3/12)*(1+'입력값'!D66/100)^12)+('입력값'!C67*100*(3/12)*(1+'입력값'!D67/100)^12)+('입력값'!C68*100*(3/12)*(1+'입력값'!D68/100)^12)+('입력값'!C69*100*(3/12))+('입력값'!C70*100*(3/12))+('입력값'!C71*100*(3/12))+('입력값'!C72*100*(3/12))+('입력값'!C73*100*(3/12))))) | BI9: =-(IF(('입력값'!C62*100*(3/12))+('입력값'!C63*100*(3/12)*(1+'입력값'!D63/100)^12)+('입력값'!C64*100*(3/12))+('입력값'!C65*100*(3/12))+('입력값'!C66*100*(3/12)*(1+'입력값'!D66/100)^12)+('입력값'!C67*100*(3/12)*(1+'입력값'!D67/100)^12)+('입력값'!C68*100*(3/12)*(1+'입력값'!D68/100)^12)+('입력값'!C69*100*(3/12))+('입력값'!C70*100*(3/12))+('입력값'!C71*100*(3/12))+('입력값'!C72*100*(3/12))+('입력값'!C73*100*(3/12))=0,0,('입력값'!BI81+'입력값'!BI82)*('입력값'!C62*100*(3/12))/(('입력값'!C62*100*(3/12))+('입력값'!C63*100*(3/12)*(1+'입력값'!D63/100)^12)+('입력값'!C64*100*(3/12))+('입력값'!C65*100*(3/12))+('입력값'!C66*100*(3/12)*(1+'입력값'!D66/100)^12)+('입력값'!C67*100*(3/12)*(1+'입력값'!D67/100)^12)+('입력값'!C68*100*(3/12)*(1+'입력값'!D68/100)^12)+('입력값'!C69*100*(3/12))+('입력값'!C70*100*(3/12))+('입력값'!C71*100*(3/12))+('입력값'!C72*100*(3/12))+('입력값'!C73*100*(3/12))))) | BJ9: =-(IF(('입력값'!C62*100*(3/12))+('입력값'!C63*100*(3/12)*(1+'입력값'!D63/100)^12)+('입력값'!C64*100*(3/12))+('입력값'!C65*100*(3/12))+('입력값'!C66*100*(3/12)*(1+'입력값'!D66/100)^12)+('입력값'!C67*100*(3/12)*(1+'입력값'!D67/100)^12)+('입력값'!C68*100*(3/12)*(1+'입력값'!D68/100)^12)+('입력값'!C69*100*(3/12))+('입력값'!C70*100*(3/12))+('입력값'!C71*100*(3/12))+('입력값'!C72*100*(3/12))+('입력값'!C73*100*(3/12))=0,0,('입력값'!BJ81+'입력값'!BJ82)*('입력값'!C62*100*(3/12))/(('입력값'!C62*100*(3/12))+('입력값'!C63*100*(3/12)*(1+'입력값'!D63/100)^12)+('입력값'!C64*100*(3/12))+('입력값'!C65*100*(3/12))+('입력값'!C66*100*(3/12)*(1+'입력값'!D66/100)^12)+('입력값'!C67*100*(3/12)*(1+'입력값'!D67/100)^12)+('입력값'!C68*100*(3/12)*(1+'입력값'!D68/100)^12)+('입력값'!C69*100*(3/12))+('입력값'!C70*100*(3/12))+('입력값'!C71*100*(3/12))+('입력값'!C72*100*(3/12))+('입력값'!C73*100*(3/12))))) | BK9: =-(IF(('입력값'!C62*100*(3/12))+('입력값'!C63*100*(3/12)*(1+'입력값'!D63/100)^13)+('입력값'!C64*100*(3/12))+('입력값'!C65*100*(3/12))+('입력값'!C66*100*(3/12)*(1+'입력값'!D66/100)^13)+('입력값'!C67*100*(3/12)*(1+'입력값'!D67/100)^13)+('입력값'!C68*100*(3/12)*(1+'입력값'!D68/100)^13)+('입력값'!C69*100*(3/12))+('입력값'!C70*100*(3/12))+('입력값'!C71*100*(3/12))+('입력값'!C72*100*(3/12))+('입력값'!C73*100*(3/12))=0,0,('입력값'!BK81+'입력값'!BK82)*('입력값'!C62*100*(3/12))/(('입력값'!C62*100*(3/12))+('입력값'!C63*100*(3/12)*(1+'입력값'!D63/100)^13)+('입력값'!C64*100*(3/12))+('입력값'!C65*100*(3/12))+('입력값'!C66*100*(3/12)*(1+'입력값'!D66/100)^13)+('입력값'!C67*100*(3/12)*(1+'입력값'!D67/100)^13)+('입력값'!C68*100*(3/12)*(1+'입력값'!D68/100)^13)+('입력값'!C69*100*(3/12))+('입력값'!C70*100*(3/12))+('입력값'!C71*100*(3/12))+('입력값'!C72*100*(3/12))+('입력값'!C73*100*(3/12))))) | BL9: =-(IF(('입력값'!C62*100*(3/12))+('입력값'!C63*100*(3/12)*(1+'입력값'!D63/100)^13)+('입력값'!C64*100*(3/12))+('입력값'!C65*100*(3/12))+('입력값'!C66*100*(3/12)*(1+'입력값'!D66/100)^13)+('입력값'!C67*100*(3/12)*(1+'입력값'!D67/100)^13)+('입력값'!C68*100*(3/12)*(1+'입력값'!D68/100)^13)+('입력값'!C69*100*(3/12))+('입력값'!C70*100*(3/12))+('입력값'!C71*100*(3/12))+('입력값'!C72*100*(3/12))+('입력값'!C73*100*(3/12))=0,0,('입력값'!BL81+'입력값'!BL82)*('입력값'!C62*100*(3/12))/(('입력값'!C62*100*(3/12))+('입력값'!C63*100*(3/12)*(1+'입력값'!D63/100)^13)+('입력값'!C64*100*(3/12))+('입력값'!C65*100*(3/12))+('입력값'!C66*100*(3/12)*(1+'입력값'!D66/100)^13)+('입력값'!C67*100*(3/12)*(1+'입력값'!D67/100)^13)+('입력값'!C68*100*(3/12)*(1+'입력값'!D68/100)^13)+('입력값'!C69*100*(3/12))+('입력값'!C70*100*(3/12))+('입력값'!C71*100*(3/12))+('입력값'!C72*100*(3/12))+('입력값'!C73*100*(3/12))))) | BM9: =-(IF(('입력값'!C62*100*(3/12))+('입력값'!C63*100*(3/12)*(1+'입력값'!D63/100)^13)+('입력값'!C64*100*(3/12))+('입력값'!C65*100*(3/12))+('입력값'!C66*100*(3/12)*(1+'입력값'!D66/100)^13)+('입력값'!C67*100*(3/12)*(1+'입력값'!D67/100)^13)+('입력값'!C68*100*(3/12)*(1+'입력값'!D68/100)^13)+('입력값'!C69*100*(3/12))+('입력값'!C70*100*(3/12))+('입력값'!C71*100*(3/12))+('입력값'!C72*100*(3/12))+('입력값'!C73*100*(3/12))=0,0,('입력값'!BM81+'입력값'!BM82)*('입력값'!C62*100*(3/12))/(('입력값'!C62*100*(3/12))+('입력값'!C63*100*(3/12)*(1+'입력값'!D63/100)^13)+('입력값'!C64*100*(3/12))+('입력값'!C65*100*(3/12))+('입력값'!C66*100*(3/12)*(1+'입력값'!D66/100)^13)+('입력값'!C67*100*(3/12)*(1+'입력값'!D67/100)^13)+('입력값'!C68*100*(3/12)*(1+'입력값'!D68/100)^13)+('입력값'!C69*100*(3/12))+('입력값'!C70*100*(3/12))+('입력값'!C71*100*(3/12))+('입력값'!C72*100*(3/12))+('입력값'!C73*100*(3/12))))) | BN9: =-(IF(('입력값'!C62*100*(3/12))+('입력값'!C63*100*(3/12)*(1+'입력값'!D63/100)^13)+('입력값'!C64*100*(3/12))+('입력값'!C65*100*(3/12))+('입력값'!C66*100*(3/12)*(1+'입력값'!D66/100)^13)+('입력값'!C67*100*(3/12)*(1+'입력값'!D67/100)^13)+('입력값'!C68*100*(3/12)*(1+'입력값'!D68/100)^13)+('입력값'!C69*100*(3/12))+('입력값'!C70*100*(3/12))+('입력값'!C71*100*(3/12))+('입력값'!C72*100*(3/12))+('입력값'!C73*100*(3/12))=0,0,('입력값'!BN81+'입력값'!BN82)*('입력값'!C62*100*(3/12))/(('입력값'!C62*100*(3/12))+('입력값'!C63*100*(3/12)*(1+'입력값'!D63/100)^13)+('입력값'!C64*100*(3/12))+('입력값'!C65*100*(3/12))+('입력값'!C66*100*(3/12)*(1+'입력값'!D66/100)^13)+('입력값'!C67*100*(3/12)*(1+'입력값'!D67/100)^13)+('입력값'!C68*100*(3/12)*(1+'입력값'!D68/100)^13)+('입력값'!C69*100*(3/12))+('입력값'!C70*100*(3/12))+('입력값'!C71*100*(3/12))+('입력값'!C72*100*(3/12))+('입력값'!C73*100*(3/12))))) | BO9: =-(IF(('입력값'!C62*100*(3/12))+('입력값'!C63*100*(3/12)*(1+'입력값'!D63/100)^14)+('입력값'!C64*100*(3/12))+('입력값'!C65*100*(3/12))+('입력값'!C66*100*(3/12)*(1+'입력값'!D66/100)^14)+('입력값'!C67*100*(3/12)*(1+'입력값'!D67/100)^14)+('입력값'!C68*100*(3/12)*(1+'입력값'!D68/100)^14)+('입력값'!C69*100*(3/12))+('입력값'!C70*100*(3/12))+('입력값'!C71*100*(3/12))+('입력값'!C72*100*(3/12))+('입력값'!C73*100*(3/12))=0,0,('입력값'!BO81+'입력값'!BO82)*('입력값'!C62*100*(3/12))/(('입력값'!C62*100*(3/12))+('입력값'!C63*100*(3/12)*(1+'입력값'!D63/100)^14)+('입력값'!C64*100*(3/12))+('입력값'!C65*100*(3/12))+('입력값'!C66*100*(3/12)*(1+'입력값'!D66/100)^14)+('입력값'!C67*100*(3/12)*(1+'입력값'!D67/100)^14)+('입력값'!C68*100*(3/12)*(1+'입력값'!D68/100)^14)+('입력값'!C69*100*(3/12))+('입력값'!C70*100*(3/12))+('입력값'!C71*100*(3/12))+('입력값'!C72*100*(3/12))+('입력값'!C73*100*(3/12))))) | BP9: =-(IF(('입력값'!C62*100*(3/12))+('입력값'!C63*100*(3/12)*(1+'입력값'!D63/100)^14)+('입력값'!C64*100*(3/12))+('입력값'!C65*100*(3/12))+('입력값'!C66*100*(3/12)*(1+'입력값'!D66/100)^14)+('입력값'!C67*100*(3/12)*(1+'입력값'!D67/100)^14)+('입력값'!C68*100*(3/12)*(1+'입력값'!D68/100)^14)+('입력값'!C69*100*(3/12))+('입력값'!C70*100*(3/12))+('입력값'!C71*100*(3/12))+('입력값'!C72*100*(3/12))+('입력값'!C73*100*(3/12))=0,0,('입력값'!BP81+'입력값'!BP82)*('입력값'!C62*100*(3/12))/(('입력값'!C62*100*(3/12))+('입력값'!C63*100*(3/12)*(1+'입력값'!D63/100)^14)+('입력값'!C64*100*(3/12))+('입력값'!C65*100*(3/12))+('입력값'!C66*100*(3/12)*(1+'입력값'!D66/100)^14)+('입력값'!C67*100*(3/12)*(1+'입력값'!D67/100)^14)+('입력값'!C68*100*(3/12)*(1+'입력값'!D68/100)^14)+('입력값'!C69*100*(3/12))+('입력값'!C70*100*(3/12))+('입력값'!C71*100*(3/12))+('입력값'!C72*100*(3/12))+('입력값'!C73*100*(3/12))))) | BQ9: =-(IF(('입력값'!C62*100*(3/12))+('입력값'!C63*100*(3/12)*(1+'입력값'!D63/100)^14)+('입력값'!C64*100*(3/12))+('입력값'!C65*100*(3/12))+('입력값'!C66*100*(3/12)*(1+'입력값'!D66/100)^14)+('입력값'!C67*100*(3/12)*(1+'입력값'!D67/100)^14)+('입력값'!C68*100*(3/12)*(1+'입력값'!D68/100)^14)+('입력값'!C69*100*(3/12))+('입력값'!C70*100*(3/12))+('입력값'!C71*100*(3/12))+('입력값'!C72*100*(3/12))+('입력값'!C73*100*(3/12))=0,0,('입력값'!BQ81+'입력값'!BQ82)*('입력값'!C62*100*(3/12))/(('입력값'!C62*100*(3/12))+('입력값'!C63*100*(3/12)*(1+'입력값'!D63/100)^14)+('입력값'!C64*100*(3/12))+('입력값'!C65*100*(3/12))+('입력값'!C66*100*(3/12)*(1+'입력값'!D66/100)^14)+('입력값'!C67*100*(3/12)*(1+'입력값'!D67/100)^14)+('입력값'!C68*100*(3/12)*(1+'입력값'!D68/100)^14)+('입력값'!C69*100*(3/12))+('입력값'!C70*100*(3/12))+('입력값'!C71*100*(3/12))+('입력값'!C72*100*(3/12))+('입력값'!C73*100*(3/12))))) | BR9: =-(IF(('입력값'!C62*100*(3/12))+('입력값'!C63*100*(3/12)*(1+'입력값'!D63/100)^14)+('입력값'!C64*100*(3/12))+('입력값'!C65*100*(3/12))+('입력값'!C66*100*(3/12)*(1+'입력값'!D66/100)^14)+('입력값'!C67*100*(3/12)*(1+'입력값'!D67/100)^14)+('입력값'!C68*100*(3/12)*(1+'입력값'!D68/100)^14)+('입력값'!C69*100*(3/12))+('입력값'!C70*100*(3/12))+('입력값'!C71*100*(3/12))+('입력값'!C72*100*(3/12))+('입력값'!C73*100*(3/12))=0,0,('입력값'!BR81+'입력값'!BR82)*('입력값'!C62*100*(3/12))/(('입력값'!C62*100*(3/12))+('입력값'!C63*100*(3/12)*(1+'입력값'!D63/100)^14)+('입력값'!C64*100*(3/12))+('입력값'!C65*100*(3/12))+('입력값'!C66*100*(3/12)*(1+'입력값'!D66/100)^14)+('입력값'!C67*100*(3/12)*(1+'입력값'!D67/100)^14)+('입력값'!C68*100*(3/12)*(1+'입력값'!D68/100)^14)+('입력값'!C69*100*(3/12))+('입력값'!C70*100*(3/12))+('입력값'!C71*100*(3/12))+('입력값'!C72*100*(3/12))+('입력값'!C73*100*(3/12))))) | BS9: =-(IF(('입력값'!C62*100*(3/12))+('입력값'!C63*100*(3/12)*(1+'입력값'!D63/100)^15)+('입력값'!C64*100*(3/12))+('입력값'!C65*100*(3/12))+('입력값'!C66*100*(3/12)*(1+'입력값'!D66/100)^15)+('입력값'!C67*100*(3/12)*(1+'입력값'!D67/100)^15)+('입력값'!C68*100*(3/12)*(1+'입력값'!D68/100)^15)+('입력값'!C69*100*(3/12))+('입력값'!C70*100*(3/12))+('입력값'!C71*100*(3/12))+('입력값'!C72*100*(3/12))+('입력값'!C73*100*(3/12))=0,0,('입력값'!BS81+'입력값'!BS82)*('입력값'!C62*100*(3/12))/(('입력값'!C62*100*(3/12))+('입력값'!C63*100*(3/12)*(1+'입력값'!D63/100)^15)+('입력값'!C64*100*(3/12))+('입력값'!C65*100*(3/12))+('입력값'!C66*100*(3/12)*(1+'입력값'!D66/100)^15)+('입력값'!C67*100*(3/12)*(1+'입력값'!D67/100)^15)+('입력값'!C68*100*(3/12)*(1+'입력값'!D68/100)^15)+('입력값'!C69*100*(3/12))+('입력값'!C70*100*(3/12))+('입력값'!C71*100*(3/12))+('입력값'!C72*100*(3/12))+('입력값'!C73*100*(3/12))))) | BT9: =-(IF(('입력값'!C62*100*(3/12))+('입력값'!C63*100*(3/12)*(1+'입력값'!D63/100)^15)+('입력값'!C64*100*(3/12))+('입력값'!C65*100*(3/12))+('입력값'!C66*100*(3/12)*(1+'입력값'!D66/100)^15)+('입력값'!C67*100*(3/12)*(1+'입력값'!D67/100)^15)+('입력값'!C68*100*(3/12)*(1+'입력값'!D68/100)^15)+('입력값'!C69*100*(3/12))+('입력값'!C70*100*(3/12))+('입력값'!C71*100*(3/12))+('입력값'!C72*100*(3/12))+('입력값'!C73*100*(3/12))=0,0,('입력값'!BT81+'입력값'!BT82)*('입력값'!C62*100*(3/12))/(('입력값'!C62*100*(3/12))+('입력값'!C63*100*(3/12)*(1+'입력값'!D63/100)^15)+('입력값'!C64*100*(3/12))+('입력값'!C65*100*(3/12))+('입력값'!C66*100*(3/12)*(1+'입력값'!D66/100)^15)+('입력값'!C67*100*(3/12)*(1+'입력값'!D67/100)^15)+('입력값'!C68*100*(3/12)*(1+'입력값'!D68/100)^15)+('입력값'!C69*100*(3/12))+('입력값'!C70*100*(3/12))+('입력값'!C71*100*(3/12))+('입력값'!C72*100*(3/12))+('입력값'!C73*100*(3/12))))) | BU9: =-(IF(('입력값'!C62*100*(3/12))+('입력값'!C63*100*(3/12)*(1+'입력값'!D63/100)^15)+('입력값'!C64*100*(3/12))+('입력값'!C65*100*(3/12))+('입력값'!C66*100*(3/12)*(1+'입력값'!D66/100)^15)+('입력값'!C67*100*(3/12)*(1+'입력값'!D67/100)^15)+('입력값'!C68*100*(3/12)*(1+'입력값'!D68/100)^15)+('입력값'!C69*100*(3/12))+('입력값'!C70*100*(3/12))+('입력값'!C71*100*(3/12))+('입력값'!C72*100*(3/12))+('입력값'!C73*100*(3/12))=0,0,('입력값'!BU81+'입력값'!BU82)*('입력값'!C62*100*(3/12))/(('입력값'!C62*100*(3/12))+('입력값'!C63*100*(3/12)*(1+'입력값'!D63/100)^15)+('입력값'!C64*100*(3/12))+('입력값'!C65*100*(3/12))+('입력값'!C66*100*(3/12)*(1+'입력값'!D66/100)^15)+('입력값'!C67*100*(3/12)*(1+'입력값'!D67/100)^15)+('입력값'!C68*100*(3/12)*(1+'입력값'!D68/100)^15)+('입력값'!C69*100*(3/12))+('입력값'!C70*100*(3/12))+('입력값'!C71*100*(3/12))+('입력값'!C72*100*(3/12))+('입력값'!C73*100*(3/12))))) | BV9: =-(IF(('입력값'!C62*100*(3/12))+('입력값'!C63*100*(3/12)*(1+'입력값'!D63/100)^15)+('입력값'!C64*100*(3/12))+('입력값'!C65*100*(3/12))+('입력값'!C66*100*(3/12)*(1+'입력값'!D66/100)^15)+('입력값'!C67*100*(3/12)*(1+'입력값'!D67/100)^15)+('입력값'!C68*100*(3/12)*(1+'입력값'!D68/100)^15)+('입력값'!C69*100*(3/12))+('입력값'!C70*100*(3/12))+('입력값'!C71*100*(3/12))+('입력값'!C72*100*(3/12))+('입력값'!C73*100*(3/12))=0,0,('입력값'!BV81+'입력값'!BV82)*('입력값'!C62*100*(3/12))/(('입력값'!C62*100*(3/12))+('입력값'!C63*100*(3/12)*(1+'입력값'!D63/100)^15)+('입력값'!C64*100*(3/12))+('입력값'!C65*100*(3/12))+('입력값'!C66*100*(3/12)*(1+'입력값'!D66/100)^15)+('입력값'!C67*100*(3/12)*(1+'입력값'!D67/100)^15)+('입력값'!C68*100*(3/12)*(1+'입력값'!D68/100)^15)+('입력값'!C69*100*(3/12))+('입력값'!C70*100*(3/12))+('입력값'!C71*100*(3/12))+('입력값'!C72*100*(3/12))+('입력값'!C73*100*(3/12))))) | BW9: =-(IF(('입력값'!C62*100*(3/12))+('입력값'!C63*100*(3/12)*(1+'입력값'!D63/100)^16)+('입력값'!C64*100*(3/12))+('입력값'!C65*100*(3/12))+('입력값'!C66*100*(3/12)*(1+'입력값'!D66/100)^16)+('입력값'!C67*100*(3/12)*(1+'입력값'!D67/100)^16)+('입력값'!C68*100*(3/12)*(1+'입력값'!D68/100)^16)+('입력값'!C69*100*(3/12))+('입력값'!C70*100*(3/12))+('입력값'!C71*100*(3/12))+('입력값'!C72*100*(3/12))+('입력값'!C73*100*(3/12))=0,0,('입력값'!BW81+'입력값'!BW82)*('입력값'!C62*100*(3/12))/(('입력값'!C62*100*(3/12))+('입력값'!C63*100*(3/12)*(1+'입력값'!D63/100)^16)+('입력값'!C64*100*(3/12))+('입력값'!C65*100*(3/12))+('입력값'!C66*100*(3/12)*(1+'입력값'!D66/100)^16)+('입력값'!C67*100*(3/12)*(1+'입력값'!D67/100)^16)+('입력값'!C68*100*(3/12)*(1+'입력값'!D68/100)^16)+('입력값'!C69*100*(3/12))+('입력값'!C70*100*(3/12))+('입력값'!C71*100*(3/12))+('입력값'!C72*100*(3/12))+('입력값'!C73*100*(3/12))))) | BX9: =-(IF(('입력값'!C62*100*(3/12))+('입력값'!C63*100*(3/12)*(1+'입력값'!D63/100)^16)+('입력값'!C64*100*(3/12))+('입력값'!C65*100*(3/12))+('입력값'!C66*100*(3/12)*(1+'입력값'!D66/100)^16)+('입력값'!C67*100*(3/12)*(1+'입력값'!D67/100)^16)+('입력값'!C68*100*(3/12)*(1+'입력값'!D68/100)^16)+('입력값'!C69*100*(3/12))+('입력값'!C70*100*(3/12))+('입력값'!C71*100*(3/12))+('입력값'!C72*100*(3/12))+('입력값'!C73*100*(3/12))=0,0,('입력값'!BX81+'입력값'!BX82)*('입력값'!C62*100*(3/12))/(('입력값'!C62*100*(3/12))+('입력값'!C63*100*(3/12)*(1+'입력값'!D63/100)^16)+('입력값'!C64*100*(3/12))+('입력값'!C65*100*(3/12))+('입력값'!C66*100*(3/12)*(1+'입력값'!D66/100)^16)+('입력값'!C67*100*(3/12)*(1+'입력값'!D67/100)^16)+('입력값'!C68*100*(3/12)*(1+'입력값'!D68/100)^16)+('입력값'!C69*100*(3/12))+('입력값'!C70*100*(3/12))+('입력값'!C71*100*(3/12))+('입력값'!C72*100*(3/12))+('입력값'!C73*100*(3/12))))) | BY9: =-(IF(('입력값'!C62*100*(3/12))+('입력값'!C63*100*(3/12)*(1+'입력값'!D63/100)^16)+('입력값'!C64*100*(3/12))+('입력값'!C65*100*(3/12))+('입력값'!C66*100*(3/12)*(1+'입력값'!D66/100)^16)+('입력값'!C67*100*(3/12)*(1+'입력값'!D67/100)^16)+('입력값'!C68*100*(3/12)*(1+'입력값'!D68/100)^16)+('입력값'!C69*100*(3/12))+('입력값'!C70*100*(3/12))+('입력값'!C71*100*(3/12))+('입력값'!C72*100*(3/12))+('입력값'!C73*100*(3/12))=0,0,('입력값'!BY81+'입력값'!BY82)*('입력값'!C62*100*(3/12))/(('입력값'!C62*100*(3/12))+('입력값'!C63*100*(3/12)*(1+'입력값'!D63/100)^16)+('입력값'!C64*100*(3/12))+('입력값'!C65*100*(3/12))+('입력값'!C66*100*(3/12)*(1+'입력값'!D66/100)^16)+('입력값'!C67*100*(3/12)*(1+'입력값'!D67/100)^16)+('입력값'!C68*100*(3/12)*(1+'입력값'!D68/100)^16)+('입력값'!C69*100*(3/12))+('입력값'!C70*100*(3/12))+('입력값'!C71*100*(3/12))+('입력값'!C72*100*(3/12))+('입력값'!C73*100*(3/12))))) | BZ9: =-(IF(('입력값'!C62*100*(3/12))+('입력값'!C63*100*(3/12)*(1+'입력값'!D63/100)^16)+('입력값'!C64*100*(3/12))+('입력값'!C65*100*(3/12))+('입력값'!C66*100*(3/12)*(1+'입력값'!D66/100)^16)+('입력값'!C67*100*(3/12)*(1+'입력값'!D67/100)^16)+('입력값'!C68*100*(3/12)*(1+'입력값'!D68/100)^16)+('입력값'!C69*100*(3/12))+('입력값'!C70*100*(3/12))+('입력값'!C71*100*(3/12))+('입력값'!C72*100*(3/12))+('입력값'!C73*100*(3/12))=0,0,('입력값'!BZ81+'입력값'!BZ82)*('입력값'!C62*100*(3/12))/(('입력값'!C62*100*(3/12))+('입력값'!C63*100*(3/12)*(1+'입력값'!D63/100)^16)+('입력값'!C64*100*(3/12))+('입력값'!C65*100*(3/12))+('입력값'!C66*100*(3/12)*(1+'입력값'!D66/100)^16)+('입력값'!C67*100*(3/12)*(1+'입력값'!D67/100)^16)+('입력값'!C68*100*(3/12)*(1+'입력값'!D68/100)^16)+('입력값'!C69*100*(3/12))+('입력값'!C70*100*(3/12))+('입력값'!C71*100*(3/12))+('입력값'!C72*100*(3/12))+('입력값'!C73*100*(3/12))))) | CA9: =-(IF(('입력값'!C62*100*(3/12))+('입력값'!C63*100*(3/12)*(1+'입력값'!D63/100)^17)+('입력값'!C64*100*(3/12))+('입력값'!C65*100*(3/12))+('입력값'!C66*100*(3/12)*(1+'입력값'!D66/100)^17)+('입력값'!C67*100*(3/12)*(1+'입력값'!D67/100)^17)+('입력값'!C68*100*(3/12)*(1+'입력값'!D68/100)^17)+('입력값'!C69*100*(3/12))+('입력값'!C70*100*(3/12))+('입력값'!C71*100*(3/12))+('입력값'!C72*100*(3/12))+('입력값'!C73*100*(3/12))=0,0,('입력값'!CA81+'입력값'!CA82)*('입력값'!C62*100*(3/12))/(('입력값'!C62*100*(3/12))+('입력값'!C63*100*(3/12)*(1+'입력값'!D63/100)^17)+('입력값'!C64*100*(3/12))+('입력값'!C65*100*(3/12))+('입력값'!C66*100*(3/12)*(1+'입력값'!D66/100)^17)+('입력값'!C67*100*(3/12)*(1+'입력값'!D67/100)^17)+('입력값'!C68*100*(3/12)*(1+'입력값'!D68/100)^17)+('입력값'!C69*100*(3/12))+('입력값'!C70*100*(3/12))+('입력값'!C71*100*(3/12))+('입력값'!C72*100*(3/12))+('입력값'!C73*100*(3/12))))) | CB9: =-(IF(('입력값'!C62*100*(3/12))+('입력값'!C63*100*(3/12)*(1+'입력값'!D63/100)^17)+('입력값'!C64*100*(3/12))+('입력값'!C65*100*(3/12))+('입력값'!C66*100*(3/12)*(1+'입력값'!D66/100)^17)+('입력값'!C67*100*(3/12)*(1+'입력값'!D67/100)^17)+('입력값'!C68*100*(3/12)*(1+'입력값'!D68/100)^17)+('입력값'!C69*100*(3/12))+('입력값'!C70*100*(3/12))+('입력값'!C71*100*(3/12))+('입력값'!C72*100*(3/12))+('입력값'!C73*100*(3/12))=0,0,('입력값'!CB81+'입력값'!CB82)*('입력값'!C62*100*(3/12))/(('입력값'!C62*100*(3/12))+('입력값'!C63*100*(3/12)*(1+'입력값'!D63/100)^17)+('입력값'!C64*100*(3/12))+('입력값'!C65*100*(3/12))+('입력값'!C66*100*(3/12)*(1+'입력값'!D66/100)^17)+('입력값'!C67*100*(3/12)*(1+'입력값'!D67/100)^17)+('입력값'!C68*100*(3/12)*(1+'입력값'!D68/100)^17)+('입력값'!C69*100*(3/12))+('입력값'!C70*100*(3/12))+('입력값'!C71*100*(3/12))+('입력값'!C72*100*(3/12))+('입력값'!C73*100*(3/12))))) | CC9: =-(IF(('입력값'!C62*100*(3/12))+('입력값'!C63*100*(3/12)*(1+'입력값'!D63/100)^17)+('입력값'!C64*100*(3/12))+('입력값'!C65*100*(3/12))+('입력값'!C66*100*(3/12)*(1+'입력값'!D66/100)^17)+('입력값'!C67*100*(3/12)*(1+'입력값'!D67/100)^17)+('입력값'!C68*100*(3/12)*(1+'입력값'!D68/100)^17)+('입력값'!C69*100*(3/12))+('입력값'!C70*100*(3/12))+('입력값'!C71*100*(3/12))+('입력값'!C72*100*(3/12))+('입력값'!C73*100*(3/12))=0,0,('입력값'!CC81+'입력값'!CC82)*('입력값'!C62*100*(3/12))/(('입력값'!C62*100*(3/12))+('입력값'!C63*100*(3/12)*(1+'입력값'!D63/100)^17)+('입력값'!C64*100*(3/12))+('입력값'!C65*100*(3/12))+('입력값'!C66*100*(3/12)*(1+'입력값'!D66/100)^17)+('입력값'!C67*100*(3/12)*(1+'입력값'!D67/100)^17)+('입력값'!C68*100*(3/12)*(1+'입력값'!D68/100)^17)+('입력값'!C69*100*(3/12))+('입력값'!C70*100*(3/12))+('입력값'!C71*100*(3/12))+('입력값'!C72*100*(3/12))+('입력값'!C73*100*(3/12))))) | CD9: =-(IF(('입력값'!C62*100*(3/12))+('입력값'!C63*100*(3/12)*(1+'입력값'!D63/100)^17)+('입력값'!C64*100*(3/12))+('입력값'!C65*100*(3/12))+('입력값'!C66*100*(3/12)*(1+'입력값'!D66/100)^17)+('입력값'!C67*100*(3/12)*(1+'입력값'!D67/100)^17)+('입력값'!C68*100*(3/12)*(1+'입력값'!D68/100)^17)+('입력값'!C69*100*(3/12))+('입력값'!C70*100*(3/12))+('입력값'!C71*100*(3/12))+('입력값'!C72*100*(3/12))+('입력값'!C73*100*(3/12))=0,0,('입력값'!CD81+'입력값'!CD82)*('입력값'!C62*100*(3/12))/(('입력값'!C62*100*(3/12))+('입력값'!C63*100*(3/12)*(1+'입력값'!D63/100)^17)+('입력값'!C64*100*(3/12))+('입력값'!C65*100*(3/12))+('입력값'!C66*100*(3/12)*(1+'입력값'!D66/100)^17)+('입력값'!C67*100*(3/12)*(1+'입력값'!D67/100)^17)+('입력값'!C68*100*(3/12)*(1+'입력값'!D68/100)^17)+('입력값'!C69*100*(3/12))+('입력값'!C70*100*(3/12))+('입력값'!C71*100*(3/12))+('입력값'!C72*100*(3/12))+('입력값'!C73*100*(3/12))))) | CE9: =-(IF(('입력값'!C62*100*(3/12))+('입력값'!C63*100*(3/12)*(1+'입력값'!D63/100)^18)+('입력값'!C64*100*(3/12))+('입력값'!C65*100*(3/12))+('입력값'!C66*100*(3/12)*(1+'입력값'!D66/100)^18)+('입력값'!C67*100*(3/12)*(1+'입력값'!D67/100)^18)+('입력값'!C68*100*(3/12)*(1+'입력값'!D68/100)^18)+('입력값'!C69*100*(3/12))+('입력값'!C70*100*(3/12))+('입력값'!C71*100*(3/12))+('입력값'!C72*100*(3/12))+('입력값'!C73*100*(3/12))=0,0,('입력값'!CE81+'입력값'!CE82)*('입력값'!C62*100*(3/12))/(('입력값'!C62*100*(3/12))+('입력값'!C63*100*(3/12)*(1+'입력값'!D63/100)^18)+('입력값'!C64*100*(3/12))+('입력값'!C65*100*(3/12))+('입력값'!C66*100*(3/12)*(1+'입력값'!D66/100)^18)+('입력값'!C67*100*(3/12)*(1+'입력값'!D67/100)^18)+('입력값'!C68*100*(3/12)*(1+'입력값'!D68/100)^18)+('입력값'!C69*100*(3/12))+('입력값'!C70*100*(3/12))+('입력값'!C71*100*(3/12))+('입력값'!C72*100*(3/12))+('입력값'!C73*100*(3/12))))) | CF9: =-(IF(('입력값'!C62*100*(3/12))+('입력값'!C63*100*(3/12)*(1+'입력값'!D63/100)^18)+('입력값'!C64*100*(3/12))+('입력값'!C65*100*(3/12))+('입력값'!C66*100*(3/12)*(1+'입력값'!D66/100)^18)+('입력값'!C67*100*(3/12)*(1+'입력값'!D67/100)^18)+('입력값'!C68*100*(3/12)*(1+'입력값'!D68/100)^18)+('입력값'!C69*100*(3/12))+('입력값'!C70*100*(3/12))+('입력값'!C71*100*(3/12))+('입력값'!C72*100*(3/12))+('입력값'!C73*100*(3/12))=0,0,('입력값'!CF81+'입력값'!CF82)*('입력값'!C62*100*(3/12))/(('입력값'!C62*100*(3/12))+('입력값'!C63*100*(3/12)*(1+'입력값'!D63/100)^18)+('입력값'!C64*100*(3/12))+('입력값'!C65*100*(3/12))+('입력값'!C66*100*(3/12)*(1+'입력값'!D66/100)^18)+('입력값'!C67*100*(3/12)*(1+'입력값'!D67/100)^18)+('입력값'!C68*100*(3/12)*(1+'입력값'!D68/100)^18)+('입력값'!C69*100*(3/12))+('입력값'!C70*100*(3/12))+('입력값'!C71*100*(3/12))+('입력값'!C72*100*(3/12))+('입력값'!C73*100*(3/12))))) | CG9: =-(IF(('입력값'!C62*100*(3/12))+('입력값'!C63*100*(3/12)*(1+'입력값'!D63/100)^18)+('입력값'!C64*100*(3/12))+('입력값'!C65*100*(3/12))+('입력값'!C66*100*(3/12)*(1+'입력값'!D66/100)^18)+('입력값'!C67*100*(3/12)*(1+'입력값'!D67/100)^18)+('입력값'!C68*100*(3/12)*(1+'입력값'!D68/100)^18)+('입력값'!C69*100*(3/12))+('입력값'!C70*100*(3/12))+('입력값'!C71*100*(3/12))+('입력값'!C72*100*(3/12))+('입력값'!C73*100*(3/12))=0,0,('입력값'!CG81+'입력값'!CG82)*('입력값'!C62*100*(3/12))/(('입력값'!C62*100*(3/12))+('입력값'!C63*100*(3/12)*(1+'입력값'!D63/100)^18)+('입력값'!C64*100*(3/12))+('입력값'!C65*100*(3/12))+('입력값'!C66*100*(3/12)*(1+'입력값'!D66/100)^18)+('입력값'!C67*100*(3/12)*(1+'입력값'!D67/100)^18)+('입력값'!C68*100*(3/12)*(1+'입력값'!D68/100)^18)+('입력값'!C69*100*(3/12))+('입력값'!C70*100*(3/12))+('입력값'!C71*100*(3/12))+('입력값'!C72*100*(3/12))+('입력값'!C73*100*(3/12))))) | CH9: =-(IF(('입력값'!C62*100*(3/12))+('입력값'!C63*100*(3/12)*(1+'입력값'!D63/100)^18)+('입력값'!C64*100*(3/12))+('입력값'!C65*100*(3/12))+('입력값'!C66*100*(3/12)*(1+'입력값'!D66/100)^18)+('입력값'!C67*100*(3/12)*(1+'입력값'!D67/100)^18)+('입력값'!C68*100*(3/12)*(1+'입력값'!D68/100)^18)+('입력값'!C69*100*(3/12))+('입력값'!C70*100*(3/12))+('입력값'!C71*100*(3/12))+('입력값'!C72*100*(3/12))+('입력값'!C73*100*(3/12))=0,0,('입력값'!CH81+'입력값'!CH82)*('입력값'!C62*100*(3/12))/(('입력값'!C62*100*(3/12))+('입력값'!C63*100*(3/12)*(1+'입력값'!D63/100)^18)+('입력값'!C64*100*(3/12))+('입력값'!C65*100*(3/12))+('입력값'!C66*100*(3/12)*(1+'입력값'!D66/100)^18)+('입력값'!C67*100*(3/12)*(1+'입력값'!D67/100)^18)+('입력값'!C68*100*(3/12)*(1+'입력값'!D68/100)^18)+('입력값'!C69*100*(3/12))+('입력값'!C70*100*(3/12))+('입력값'!C71*100*(3/12))+('입력값'!C72*100*(3/12))+('입력값'!C73*100*(3/12))))) | CI9: =-(IF(('입력값'!C62*100*(3/12))+('입력값'!C63*100*(3/12)*(1+'입력값'!D63/100)^19)+('입력값'!C64*100*(3/12))+('입력값'!C65*100*(3/12))+('입력값'!C66*100*(3/12)*(1+'입력값'!D66/100)^19)+('입력값'!C67*100*(3/12)*(1+'입력값'!D67/100)^19)+('입력값'!C68*100*(3/12)*(1+'입력값'!D68/100)^19)+('입력값'!C69*100*(3/12))+('입력값'!C70*100*(3/12))+('입력값'!C71*100*(3/12))+('입력값'!C72*100*(3/12))+('입력값'!C73*100*(3/12))=0,0,('입력값'!CI81+'입력값'!CI82)*('입력값'!C62*100*(3/12))/(('입력값'!C62*100*(3/12))+('입력값'!C63*100*(3/12)*(1+'입력값'!D63/100)^19)+('입력값'!C64*100*(3/12))+('입력값'!C65*100*(3/12))+('입력값'!C66*100*(3/12)*(1+'입력값'!D66/100)^19)+('입력값'!C67*100*(3/12)*(1+'입력값'!D67/100)^19)+('입력값'!C68*100*(3/12)*(1+'입력값'!D68/100)^19)+('입력값'!C69*100*(3/12))+('입력값'!C70*100*(3/12))+('입력값'!C71*100*(3/12))+('입력값'!C72*100*(3/12))+('입력값'!C73*100*(3/12))))) | CJ9: =-(IF(('입력값'!C62*100*(3/12))+('입력값'!C63*100*(3/12)*(1+'입력값'!D63/100)^19)+('입력값'!C64*100*(3/12))+('입력값'!C65*100*(3/12))+('입력값'!C66*100*(3/12)*(1+'입력값'!D66/100)^19)+('입력값'!C67*100*(3/12)*(1+'입력값'!D67/100)^19)+('입력값'!C68*100*(3/12)*(1+'입력값'!D68/100)^19)+('입력값'!C69*100*(3/12))+('입력값'!C70*100*(3/12))+('입력값'!C71*100*(3/12))+('입력값'!C72*100*(3/12))+('입력값'!C73*100*(3/12))=0,0,('입력값'!CJ81+'입력값'!CJ82)*('입력값'!C62*100*(3/12))/(('입력값'!C62*100*(3/12))+('입력값'!C63*100*(3/12)*(1+'입력값'!D63/100)^19)+('입력값'!C64*100*(3/12))+('입력값'!C65*100*(3/12))+('입력값'!C66*100*(3/12)*(1+'입력값'!D66/100)^19)+('입력값'!C67*100*(3/12)*(1+'입력값'!D67/100)^19)+('입력값'!C68*100*(3/12)*(1+'입력값'!D68/100)^19)+('입력값'!C69*100*(3/12))+('입력값'!C70*100*(3/12))+('입력값'!C71*100*(3/12))+('입력값'!C72*100*(3/12))+('입력값'!C73*100*(3/12))))) | CK9: =-(IF(('입력값'!C62*100*(3/12))+('입력값'!C63*100*(3/12)*(1+'입력값'!D63/100)^19)+('입력값'!C64*100*(3/12))+('입력값'!C65*100*(3/12))+('입력값'!C66*100*(3/12)*(1+'입력값'!D66/100)^19)+('입력값'!C67*100*(3/12)*(1+'입력값'!D67/100)^19)+('입력값'!C68*100*(3/12)*(1+'입력값'!D68/100)^19)+('입력값'!C69*100*(3/12))+('입력값'!C70*100*(3/12))+('입력값'!C71*100*(3/12))+('입력값'!C72*100*(3/12))+('입력값'!C73*100*(3/12))=0,0,('입력값'!CK81+'입력값'!CK82)*('입력값'!C62*100*(3/12))/(('입력값'!C62*100*(3/12))+('입력값'!C63*100*(3/12)*(1+'입력값'!D63/100)^19)+('입력값'!C64*100*(3/12))+('입력값'!C65*100*(3/12))+('입력값'!C66*100*(3/12)*(1+'입력값'!D66/100)^19)+('입력값'!C67*100*(3/12)*(1+'입력값'!D67/100)^19)+('입력값'!C68*100*(3/12)*(1+'입력값'!D68/100)^19)+('입력값'!C69*100*(3/12))+('입력값'!C70*100*(3/12))+('입력값'!C71*100*(3/12))+('입력값'!C72*100*(3/12))+('입력값'!C73*100*(3/12))))) | CL9: =-(IF(('입력값'!C62*100*(3/12))+('입력값'!C63*100*(3/12)*(1+'입력값'!D63/100)^19)+('입력값'!C64*100*(3/12))+('입력값'!C65*100*(3/12))+('입력값'!C66*100*(3/12)*(1+'입력값'!D66/100)^19)+('입력값'!C67*100*(3/12)*(1+'입력값'!D67/100)^19)+('입력값'!C68*100*(3/12)*(1+'입력값'!D68/100)^19)+('입력값'!C69*100*(3/12))+('입력값'!C70*100*(3/12))+('입력값'!C71*100*(3/12))+('입력값'!C72*100*(3/12))+('입력값'!C73*100*(3/12))=0,0,('입력값'!CL81+'입력값'!CL82)*('입력값'!C62*100*(3/12))/(('입력값'!C62*100*(3/12))+('입력값'!C63*100*(3/12)*(1+'입력값'!D63/100)^19)+('입력값'!C64*100*(3/12))+('입력값'!C65*100*(3/12))+('입력값'!C66*100*(3/12)*(1+'입력값'!D66/100)^19)+('입력값'!C67*100*(3/12)*(1+'입력값'!D67/100)^19)+('입력값'!C68*100*(3/12)*(1+'입력값'!D68/100)^19)+('입력값'!C69*100*(3/12))+('입력값'!C70*100*(3/12))+('입력값'!C71*100*(3/12))+('입력값'!C72*100*(3/12))+('입력값'!C73*100*(3/12)))))
B10: O&M | C10: [KRWm] | D10: =SUM(E10:CL10) | E10: 0 | F10: 0 | G10: 0 | H10: 0 | I10: 0 | J10: 0 | K10: =-(IF(('입력값'!C62*100*(3/12))+('입력값'!C63*100*(3/12)*(1+'입력값'!D63/100)^0)+('입력값'!C64*100*(3/12))+('입력값'!C65*100*(3/12))+('입력값'!C66*100*(3/12)*(1+'입력값'!D66/100)^0)+('입력값'!C67*100*(3/12)*(1+'입력값'!D67/100)^0)+('입력값'!C68*100*(3/12)*(1+'입력값'!D68/100)^0)+('입력값'!C69*100*(3/12))+('입력값'!C70*100*(3/12))+('입력값'!C71*100*(3/12))+('입력값'!C72*100*(3/12))+('입력값'!C73*100*(3/12))=0,0,('입력값'!K81+'입력값'!K82)*('입력값'!C63*100*(3/12)*(1+'입력값'!D63/100)^0)/(('입력값'!C62*100*(3/12))+('입력값'!C63*100*(3/12)*(1+'입력값'!D63/100)^0)+('입력값'!C64*100*(3/12))+('입력값'!C65*100*(3/12))+('입력값'!C66*100*(3/12)*(1+'입력값'!D66/100)^0)+('입력값'!C67*100*(3/12)*(1+'입력값'!D67/100)^0)+('입력값'!C68*100*(3/12)*(1+'입력값'!D68/100)^0)+('입력값'!C69*100*(3/12))+('입력값'!C70*100*(3/12))+('입력값'!C71*100*(3/12))+('입력값'!C72*100*(3/12))+('입력값'!C73*100*(3/12))))) | L10: =-(IF(('입력값'!C62*100*(3/12))+('입력값'!C63*100*(3/12)*(1+'입력값'!D63/100)^0)+('입력값'!C64*100*(3/12))+('입력값'!C65*100*(3/12))+('입력값'!C66*100*(3/12)*(1+'입력값'!D66/100)^0)+('입력값'!C67*100*(3/12)*(1+'입력값'!D67/100)^0)+('입력값'!C68*100*(3/12)*(1+'입력값'!D68/100)^0)+('입력값'!C69*100*(3/12))+('입력값'!C70*100*(3/12))+('입력값'!C71*100*(3/12))+('입력값'!C72*100*(3/12))+('입력값'!C73*100*(3/12))=0,0,('입력값'!L81+'입력값'!L82)*('입력값'!C63*100*(3/12)*(1+'입력값'!D63/100)^0)/(('입력값'!C62*100*(3/12))+('입력값'!C63*100*(3/12)*(1+'입력값'!D63/100)^0)+('입력값'!C64*100*(3/12))+('입력값'!C65*100*(3/12))+('입력값'!C66*100*(3/12)*(1+'입력값'!D66/100)^0)+('입력값'!C67*100*(3/12)*(1+'입력값'!D67/100)^0)+('입력값'!C68*100*(3/12)*(1+'입력값'!D68/100)^0)+('입력값'!C69*100*(3/12))+('입력값'!C70*100*(3/12))+('입력값'!C71*100*(3/12))+('입력값'!C72*100*(3/12))+('입력값'!C73*100*(3/12))))) | M10: =-(IF(('입력값'!C62*100*(3/12))+('입력값'!C63*100*(3/12)*(1+'입력값'!D63/100)^0)+('입력값'!C64*100*(3/12))+('입력값'!C65*100*(3/12))+('입력값'!C66*100*(3/12)*(1+'입력값'!D66/100)^0)+('입력값'!C67*100*(3/12)*(1+'입력값'!D67/100)^0)+('입력값'!C68*100*(3/12)*(1+'입력값'!D68/100)^0)+('입력값'!C69*100*(3/12))+('입력값'!C70*100*(3/12))+('입력값'!C71*100*(3/12))+('입력값'!C72*100*(3/12))+('입력값'!C73*100*(3/12))=0,0,('입력값'!M81+'입력값'!M82)*('입력값'!C63*100*(3/12)*(1+'입력값'!D63/100)^0)/(('입력값'!C62*100*(3/12))+('입력값'!C63*100*(3/12)*(1+'입력값'!D63/100)^0)+('입력값'!C64*100*(3/12))+('입력값'!C65*100*(3/12))+('입력값'!C66*100*(3/12)*(1+'입력값'!D66/100)^0)+('입력값'!C67*100*(3/12)*(1+'입력값'!D67/100)^0)+('입력값'!C68*100*(3/12)*(1+'입력값'!D68/100)^0)+('입력값'!C69*100*(3/12))+('입력값'!C70*100*(3/12))+('입력값'!C71*100*(3/12))+('입력값'!C72*100*(3/12))+('입력값'!C73*100*(3/12))))) | N10: =-(IF(('입력값'!C62*100*(3/12))+('입력값'!C63*100*(3/12)*(1+'입력값'!D63/100)^0)+('입력값'!C64*100*(3/12))+('입력값'!C65*100*(3/12))+('입력값'!C66*100*(3/12)*(1+'입력값'!D66/100)^0)+('입력값'!C67*100*(3/12)*(1+'입력값'!D67/100)^0)+('입력값'!C68*100*(3/12)*(1+'입력값'!D68/100)^0)+('입력값'!C69*100*(3/12))+('입력값'!C70*100*(3/12))+('입력값'!C71*100*(3/12))+('입력값'!C72*100*(3/12))+('입력값'!C73*100*(3/12))=0,0,('입력값'!N81+'입력값'!N82)*('입력값'!C63*100*(3/12)*(1+'입력값'!D63/100)^0)/(('입력값'!C62*100*(3/12))+('입력값'!C63*100*(3/12)*(1+'입력값'!D63/100)^0)+('입력값'!C64*100*(3/12))+('입력값'!C65*100*(3/12))+('입력값'!C66*100*(3/12)*(1+'입력값'!D66/100)^0)+('입력값'!C67*100*(3/12)*(1+'입력값'!D67/100)^0)+('입력값'!C68*100*(3/12)*(1+'입력값'!D68/100)^0)+('입력값'!C69*100*(3/12))+('입력값'!C70*100*(3/12))+('입력값'!C71*100*(3/12))+('입력값'!C72*100*(3/12))+('입력값'!C73*100*(3/12))))) | O10: =-(IF(('입력값'!C62*100*(3/12))+('입력값'!C63*100*(3/12)*(1+'입력값'!D63/100)^1)+('입력값'!C64*100*(3/12))+('입력값'!C65*100*(3/12))+('입력값'!C66*100*(3/12)*(1+'입력값'!D66/100)^1)+('입력값'!C67*100*(3/12)*(1+'입력값'!D67/100)^1)+('입력값'!C68*100*(3/12)*(1+'입력값'!D68/100)^1)+('입력값'!C69*100*(3/12))+('입력값'!C70*100*(3/12))+('입력값'!C71*100*(3/12))+('입력값'!C72*100*(3/12))+('입력값'!C73*100*(3/12))=0,0,('입력값'!O81+'입력값'!O82)*('입력값'!C63*100*(3/12)*(1+'입력값'!D63/100)^1)/(('입력값'!C62*100*(3/12))+('입력값'!C63*100*(3/12)*(1+'입력값'!D63/100)^1)+('입력값'!C64*100*(3/12))+('입력값'!C65*100*(3/12))+('입력값'!C66*100*(3/12)*(1+'입력값'!D66/100)^1)+('입력값'!C67*100*(3/12)*(1+'입력값'!D67/100)^1)+('입력값'!C68*100*(3/12)*(1+'입력값'!D68/100)^1)+('입력값'!C69*100*(3/12))+('입력값'!C70*100*(3/12))+('입력값'!C71*100*(3/12))+('입력값'!C72*100*(3/12))+('입력값'!C73*100*(3/12))))) | P10: =-(IF(('입력값'!C62*100*(3/12))+('입력값'!C63*100*(3/12)*(1+'입력값'!D63/100)^1)+('입력값'!C64*100*(3/12))+('입력값'!C65*100*(3/12))+('입력값'!C66*100*(3/12)*(1+'입력값'!D66/100)^1)+('입력값'!C67*100*(3/12)*(1+'입력값'!D67/100)^1)+('입력값'!C68*100*(3/12)*(1+'입력값'!D68/100)^1)+('입력값'!C69*100*(3/12))+('입력값'!C70*100*(3/12))+('입력값'!C71*100*(3/12))+('입력값'!C72*100*(3/12))+('입력값'!C73*100*(3/12))=0,0,('입력값'!P81+'입력값'!P82)*('입력값'!C63*100*(3/12)*(1+'입력값'!D63/100)^1)/(('입력값'!C62*100*(3/12))+('입력값'!C63*100*(3/12)*(1+'입력값'!D63/100)^1)+('입력값'!C64*100*(3/12))+('입력값'!C65*100*(3/12))+('입력값'!C66*100*(3/12)*(1+'입력값'!D66/100)^1)+('입력값'!C67*100*(3/12)*(1+'입력값'!D67/100)^1)+('입력값'!C68*100*(3/12)*(1+'입력값'!D68/100)^1)+('입력값'!C69*100*(3/12))+('입력값'!C70*100*(3/12))+('입력값'!C71*100*(3/12))+('입력값'!C72*100*(3/12))+('입력값'!C73*100*(3/12))))) | Q10: =-(IF(('입력값'!C62*100*(3/12))+('입력값'!C63*100*(3/12)*(1+'입력값'!D63/100)^1)+('입력값'!C64*100*(3/12))+('입력값'!C65*100*(3/12))+('입력값'!C66*100*(3/12)*(1+'입력값'!D66/100)^1)+('입력값'!C67*100*(3/12)*(1+'입력값'!D67/100)^1)+('입력값'!C68*100*(3/12)*(1+'입력값'!D68/100)^1)+('입력값'!C69*100*(3/12))+('입력값'!C70*100*(3/12))+('입력값'!C71*100*(3/12))+('입력값'!C72*100*(3/12))+('입력값'!C73*100*(3/12))=0,0,('입력값'!Q81+'입력값'!Q82)*('입력값'!C63*100*(3/12)*(1+'입력값'!D63/100)^1)/(('입력값'!C62*100*(3/12))+('입력값'!C63*100*(3/12)*(1+'입력값'!D63/100)^1)+('입력값'!C64*100*(3/12))+('입력값'!C65*100*(3/12))+('입력값'!C66*100*(3/12)*(1+'입력값'!D66/100)^1)+('입력값'!C67*100*(3/12)*(1+'입력값'!D67/100)^1)+('입력값'!C68*100*(3/12)*(1+'입력값'!D68/100)^1)+('입력값'!C69*100*(3/12))+('입력값'!C70*100*(3/12))+('입력값'!C71*100*(3/12))+('입력값'!C72*100*(3/12))+('입력값'!C73*100*(3/12))))) | R10: =-(IF(('입력값'!C62*100*(3/12))+('입력값'!C63*100*(3/12)*(1+'입력값'!D63/100)^1)+('입력값'!C64*100*(3/12))+('입력값'!C65*100*(3/12))+('입력값'!C66*100*(3/12)*(1+'입력값'!D66/100)^1)+('입력값'!C67*100*(3/12)*(1+'입력값'!D67/100)^1)+('입력값'!C68*100*(3/12)*(1+'입력값'!D68/100)^1)+('입력값'!C69*100*(3/12))+('입력값'!C70*100*(3/12))+('입력값'!C71*100*(3/12))+('입력값'!C72*100*(3/12))+('입력값'!C73*100*(3/12))=0,0,('입력값'!R81+'입력값'!R82)*('입력값'!C63*100*(3/12)*(1+'입력값'!D63/100)^1)/(('입력값'!C62*100*(3/12))+('입력값'!C63*100*(3/12)*(1+'입력값'!D63/100)^1)+('입력값'!C64*100*(3/12))+('입력값'!C65*100*(3/12))+('입력값'!C66*100*(3/12)*(1+'입력값'!D66/100)^1)+('입력값'!C67*100*(3/12)*(1+'입력값'!D67/100)^1)+('입력값'!C68*100*(3/12)*(1+'입력값'!D68/100)^1)+('입력값'!C69*100*(3/12))+('입력값'!C70*100*(3/12))+('입력값'!C71*100*(3/12))+('입력값'!C72*100*(3/12))+('입력값'!C73*100*(3/12))))) | S10: =-(IF(('입력값'!C62*100*(3/12))+('입력값'!C63*100*(3/12)*(1+'입력값'!D63/100)^2)+('입력값'!C64*100*(3/12))+('입력값'!C65*100*(3/12))+('입력값'!C66*100*(3/12)*(1+'입력값'!D66/100)^2)+('입력값'!C67*100*(3/12)*(1+'입력값'!D67/100)^2)+('입력값'!C68*100*(3/12)*(1+'입력값'!D68/100)^2)+('입력값'!C69*100*(3/12))+('입력값'!C70*100*(3/12))+('입력값'!C71*100*(3/12))+('입력값'!C72*100*(3/12))+('입력값'!C73*100*(3/12))=0,0,('입력값'!S81+'입력값'!S82)*('입력값'!C63*100*(3/12)*(1+'입력값'!D63/100)^2)/(('입력값'!C62*100*(3/12))+('입력값'!C63*100*(3/12)*(1+'입력값'!D63/100)^2)+('입력값'!C64*100*(3/12))+('입력값'!C65*100*(3/12))+('입력값'!C66*100*(3/12)*(1+'입력값'!D66/100)^2)+('입력값'!C67*100*(3/12)*(1+'입력값'!D67/100)^2)+('입력값'!C68*100*(3/12)*(1+'입력값'!D68/100)^2)+('입력값'!C69*100*(3/12))+('입력값'!C70*100*(3/12))+('입력값'!C71*100*(3/12))+('입력값'!C72*100*(3/12))+('입력값'!C73*100*(3/12))))) | T10: =-(IF(('입력값'!C62*100*(3/12))+('입력값'!C63*100*(3/12)*(1+'입력값'!D63/100)^2)+('입력값'!C64*100*(3/12))+('입력값'!C65*100*(3/12))+('입력값'!C66*100*(3/12)*(1+'입력값'!D66/100)^2)+('입력값'!C67*100*(3/12)*(1+'입력값'!D67/100)^2)+('입력값'!C68*100*(3/12)*(1+'입력값'!D68/100)^2)+('입력값'!C69*100*(3/12))+('입력값'!C70*100*(3/12))+('입력값'!C71*100*(3/12))+('입력값'!C72*100*(3/12))+('입력값'!C73*100*(3/12))=0,0,('입력값'!T81+'입력값'!T82)*('입력값'!C63*100*(3/12)*(1+'입력값'!D63/100)^2)/(('입력값'!C62*100*(3/12))+('입력값'!C63*100*(3/12)*(1+'입력값'!D63/100)^2)+('입력값'!C64*100*(3/12))+('입력값'!C65*100*(3/12))+('입력값'!C66*100*(3/12)*(1+'입력값'!D66/100)^2)+('입력값'!C67*100*(3/12)*(1+'입력값'!D67/100)^2)+('입력값'!C68*100*(3/12)*(1+'입력값'!D68/100)^2)+('입력값'!C69*100*(3/12))+('입력값'!C70*100*(3/12))+('입력값'!C71*100*(3/12))+('입력값'!C72*100*(3/12))+('입력값'!C73*100*(3/12))))) | U10: =-(IF(('입력값'!C62*100*(3/12))+('입력값'!C63*100*(3/12)*(1+'입력값'!D63/100)^2)+('입력값'!C64*100*(3/12))+('입력값'!C65*100*(3/12))+('입력값'!C66*100*(3/12)*(1+'입력값'!D66/100)^2)+('입력값'!C67*100*(3/12)*(1+'입력값'!D67/100)^2)+('입력값'!C68*100*(3/12)*(1+'입력값'!D68/100)^2)+('입력값'!C69*100*(3/12))+('입력값'!C70*100*(3/12))+('입력값'!C71*100*(3/12))+('입력값'!C72*100*(3/12))+('입력값'!C73*100*(3/12))=0,0,('입력값'!U81+'입력값'!U82)*('입력값'!C63*100*(3/12)*(1+'입력값'!D63/100)^2)/(('입력값'!C62*100*(3/12))+('입력값'!C63*100*(3/12)*(1+'입력값'!D63/100)^2)+('입력값'!C64*100*(3/12))+('입력값'!C65*100*(3/12))+('입력값'!C66*100*(3/12)*(1+'입력값'!D66/100)^2)+('입력값'!C67*100*(3/12)*(1+'입력값'!D67/100)^2)+('입력값'!C68*100*(3/12)*(1+'입력값'!D68/100)^2)+('입력값'!C69*100*(3/12))+('입력값'!C70*100*(3/12))+('입력값'!C71*100*(3/12))+('입력값'!C72*100*(3/12))+('입력값'!C73*100*(3/12))))) | V10: =-(IF(('입력값'!C62*100*(3/12))+('입력값'!C63*100*(3/12)*(1+'입력값'!D63/100)^2)+('입력값'!C64*100*(3/12))+('입력값'!C65*100*(3/12))+('입력값'!C66*100*(3/12)*(1+'입력값'!D66/100)^2)+('입력값'!C67*100*(3/12)*(1+'입력값'!D67/100)^2)+('입력값'!C68*100*(3/12)*(1+'입력값'!D68/100)^2)+('입력값'!C69*100*(3/12))+('입력값'!C70*100*(3/12))+('입력값'!C71*100*(3/12))+('입력값'!C72*100*(3/12))+('입력값'!C73*100*(3/12))=0,0,('입력값'!V81+'입력값'!V82)*('입력값'!C63*100*(3/12)*(1+'입력값'!D63/100)^2)/(('입력값'!C62*100*(3/12))+('입력값'!C63*100*(3/12)*(1+'입력값'!D63/100)^2)+('입력값'!C64*100*(3/12))+('입력값'!C65*100*(3/12))+('입력값'!C66*100*(3/12)*(1+'입력값'!D66/100)^2)+('입력값'!C67*100*(3/12)*(1+'입력값'!D67/100)^2)+('입력값'!C68*100*(3/12)*(1+'입력값'!D68/100)^2)+('입력값'!C69*100*(3/12))+('입력값'!C70*100*(3/12))+('입력값'!C71*100*(3/12))+('입력값'!C72*100*(3/12))+('입력값'!C73*100*(3/12))))) | W10: =-(IF(('입력값'!C62*100*(3/12))+('입력값'!C63*100*(3/12)*(1+'입력값'!D63/100)^3)+('입력값'!C64*100*(3/12))+('입력값'!C65*100*(3/12))+('입력값'!C66*100*(3/12)*(1+'입력값'!D66/100)^3)+('입력값'!C67*100*(3/12)*(1+'입력값'!D67/100)^3)+('입력값'!C68*100*(3/12)*(1+'입력값'!D68/100)^3)+('입력값'!C69*100*(3/12))+('입력값'!C70*100*(3/12))+('입력값'!C71*100*(3/12))+('입력값'!C72*100*(3/12))+('입력값'!C73*100*(3/12))=0,0,('입력값'!W81+'입력값'!W82)*('입력값'!C63*100*(3/12)*(1+'입력값'!D63/100)^3)/(('입력값'!C62*100*(3/12))+('입력값'!C63*100*(3/12)*(1+'입력값'!D63/100)^3)+('입력값'!C64*100*(3/12))+('입력값'!C65*100*(3/12))+('입력값'!C66*100*(3/12)*(1+'입력값'!D66/100)^3)+('입력값'!C67*100*(3/12)*(1+'입력값'!D67/100)^3)+('입력값'!C68*100*(3/12)*(1+'입력값'!D68/100)^3)+('입력값'!C69*100*(3/12))+('입력값'!C70*100*(3/12))+('입력값'!C71*100*(3/12))+('입력값'!C72*100*(3/12))+('입력값'!C73*100*(3/12))))) | X10: =-(IF(('입력값'!C62*100*(3/12))+('입력값'!C63*100*(3/12)*(1+'입력값'!D63/100)^3)+('입력값'!C64*100*(3/12))+('입력값'!C65*100*(3/12))+('입력값'!C66*100*(3/12)*(1+'입력값'!D66/100)^3)+('입력값'!C67*100*(3/12)*(1+'입력값'!D67/100)^3)+('입력값'!C68*100*(3/12)*(1+'입력값'!D68/100)^3)+('입력값'!C69*100*(3/12))+('입력값'!C70*100*(3/12))+('입력값'!C71*100*(3/12))+('입력값'!C72*100*(3/12))+('입력값'!C73*100*(3/12))=0,0,('입력값'!X81+'입력값'!X82)*('입력값'!C63*100*(3/12)*(1+'입력값'!D63/100)^3)/(('입력값'!C62*100*(3/12))+('입력값'!C63*100*(3/12)*(1+'입력값'!D63/100)^3)+('입력값'!C64*100*(3/12))+('입력값'!C65*100*(3/12))+('입력값'!C66*100*(3/12)*(1+'입력값'!D66/100)^3)+('입력값'!C67*100*(3/12)*(1+'입력값'!D67/100)^3)+('입력값'!C68*100*(3/12)*(1+'입력값'!D68/100)^3)+('입력값'!C69*100*(3/12))+('입력값'!C70*100*(3/12))+('입력값'!C71*100*(3/12))+('입력값'!C72*100*(3/12))+('입력값'!C73*100*(3/12))))) | Y10: =-(IF(('입력값'!C62*100*(3/12))+('입력값'!C63*100*(3/12)*(1+'입력값'!D63/100)^3)+('입력값'!C64*100*(3/12))+('입력값'!C65*100*(3/12))+('입력값'!C66*100*(3/12)*(1+'입력값'!D66/100)^3)+('입력값'!C67*100*(3/12)*(1+'입력값'!D67/100)^3)+('입력값'!C68*100*(3/12)*(1+'입력값'!D68/100)^3)+('입력값'!C69*100*(3/12))+('입력값'!C70*100*(3/12))+('입력값'!C71*100*(3/12))+('입력값'!C72*100*(3/12))+('입력값'!C73*100*(3/12))=0,0,('입력값'!Y81+'입력값'!Y82)*('입력값'!C63*100*(3/12)*(1+'입력값'!D63/100)^3)/(('입력값'!C62*100*(3/12))+('입력값'!C63*100*(3/12)*(1+'입력값'!D63/100)^3)+('입력값'!C64*100*(3/12))+('입력값'!C65*100*(3/12))+('입력값'!C66*100*(3/12)*(1+'입력값'!D66/100)^3)+('입력값'!C67*100*(3/12)*(1+'입력값'!D67/100)^3)+('입력값'!C68*100*(3/12)*(1+'입력값'!D68/100)^3)+('입력값'!C69*100*(3/12))+('입력값'!C70*100*(3/12))+('입력값'!C71*100*(3/12))+('입력값'!C72*100*(3/12))+('입력값'!C73*100*(3/12))))) | Z10: =-(IF(('입력값'!C62*100*(3/12))+('입력값'!C63*100*(3/12)*(1+'입력값'!D63/100)^3)+('입력값'!C64*100*(3/12))+('입력값'!C65*100*(3/12))+('입력값'!C66*100*(3/12)*(1+'입력값'!D66/100)^3)+('입력값'!C67*100*(3/12)*(1+'입력값'!D67/100)^3)+('입력값'!C68*100*(3/12)*(1+'입력값'!D68/100)^3)+('입력값'!C69*100*(3/12))+('입력값'!C70*100*(3/12))+('입력값'!C71*100*(3/12))+('입력값'!C72*100*(3/12))+('입력값'!C73*100*(3/12))=0,0,('입력값'!Z81+'입력값'!Z82)*('입력값'!C63*100*(3/12)*(1+'입력값'!D63/100)^3)/(('입력값'!C62*100*(3/12))+('입력값'!C63*100*(3/12)*(1+'입력값'!D63/100)^3)+('입력값'!C64*100*(3/12))+('입력값'!C65*100*(3/12))+('입력값'!C66*100*(3/12)*(1+'입력값'!D66/100)^3)+('입력값'!C67*100*(3/12)*(1+'입력값'!D67/100)^3)+('입력값'!C68*100*(3/12)*(1+'입력값'!D68/100)^3)+('입력값'!C69*100*(3/12))+('입력값'!C70*100*(3/12))+('입력값'!C71*100*(3/12))+('입력값'!C72*100*(3/12))+('입력값'!C73*100*(3/12))))) | AA10: =-(IF(('입력값'!C62*100*(3/12))+('입력값'!C63*100*(3/12)*(1+'입력값'!D63/100)^4)+('입력값'!C64*100*(3/12))+('입력값'!C65*100*(3/12))+('입력값'!C66*100*(3/12)*(1+'입력값'!D66/100)^4)+('입력값'!C67*100*(3/12)*(1+'입력값'!D67/100)^4)+('입력값'!C68*100*(3/12)*(1+'입력값'!D68/100)^4)+('입력값'!C69*100*(3/12))+('입력값'!C70*100*(3/12))+('입력값'!C71*100*(3/12))+('입력값'!C72*100*(3/12))+('입력값'!C73*100*(3/12))=0,0,('입력값'!AA81+'입력값'!AA82)*('입력값'!C63*100*(3/12)*(1+'입력값'!D63/100)^4)/(('입력값'!C62*100*(3/12))+('입력값'!C63*100*(3/12)*(1+'입력값'!D63/100)^4)+('입력값'!C64*100*(3/12))+('입력값'!C65*100*(3/12))+('입력값'!C66*100*(3/12)*(1+'입력값'!D66/100)^4)+('입력값'!C67*100*(3/12)*(1+'입력값'!D67/100)^4)+('입력값'!C68*100*(3/12)*(1+'입력값'!D68/100)^4)+('입력값'!C69*100*(3/12))+('입력값'!C70*100*(3/12))+('입력값'!C71*100*(3/12))+('입력값'!C72*100*(3/12))+('입력값'!C73*100*(3/12))))) | AB10: =-(IF(('입력값'!C62*100*(3/12))+('입력값'!C63*100*(3/12)*(1+'입력값'!D63/100)^4)+('입력값'!C64*100*(3/12))+('입력값'!C65*100*(3/12))+('입력값'!C66*100*(3/12)*(1+'입력값'!D66/100)^4)+('입력값'!C67*100*(3/12)*(1+'입력값'!D67/100)^4)+('입력값'!C68*100*(3/12)*(1+'입력값'!D68/100)^4)+('입력값'!C69*100*(3/12))+('입력값'!C70*100*(3/12))+('입력값'!C71*100*(3/12))+('입력값'!C72*100*(3/12))+('입력값'!C73*100*(3/12))=0,0,('입력값'!AB81+'입력값'!AB82)*('입력값'!C63*100*(3/12)*(1+'입력값'!D63/100)^4)/(('입력값'!C62*100*(3/12))+('입력값'!C63*100*(3/12)*(1+'입력값'!D63/100)^4)+('입력값'!C64*100*(3/12))+('입력값'!C65*100*(3/12))+('입력값'!C66*100*(3/12)*(1+'입력값'!D66/100)^4)+('입력값'!C67*100*(3/12)*(1+'입력값'!D67/100)^4)+('입력값'!C68*100*(3/12)*(1+'입력값'!D68/100)^4)+('입력값'!C69*100*(3/12))+('입력값'!C70*100*(3/12))+('입력값'!C71*100*(3/12))+('입력값'!C72*100*(3/12))+('입력값'!C73*100*(3/12))))) | AC10: =-(IF(('입력값'!C62*100*(3/12))+('입력값'!C63*100*(3/12)*(1+'입력값'!D63/100)^4)+('입력값'!C64*100*(3/12))+('입력값'!C65*100*(3/12))+('입력값'!C66*100*(3/12)*(1+'입력값'!D66/100)^4)+('입력값'!C67*100*(3/12)*(1+'입력값'!D67/100)^4)+('입력값'!C68*100*(3/12)*(1+'입력값'!D68/100)^4)+('입력값'!C69*100*(3/12))+('입력값'!C70*100*(3/12))+('입력값'!C71*100*(3/12))+('입력값'!C72*100*(3/12))+('입력값'!C73*100*(3/12))=0,0,('입력값'!AC81+'입력값'!AC82)*('입력값'!C63*100*(3/12)*(1+'입력값'!D63/100)^4)/(('입력값'!C62*100*(3/12))+('입력값'!C63*100*(3/12)*(1+'입력값'!D63/100)^4)+('입력값'!C64*100*(3/12))+('입력값'!C65*100*(3/12))+('입력값'!C66*100*(3/12)*(1+'입력값'!D66/100)^4)+('입력값'!C67*100*(3/12)*(1+'입력값'!D67/100)^4)+('입력값'!C68*100*(3/12)*(1+'입력값'!D68/100)^4)+('입력값'!C69*100*(3/12))+('입력값'!C70*100*(3/12))+('입력값'!C71*100*(3/12))+('입력값'!C72*100*(3/12))+('입력값'!C73*100*(3/12))))) | AD10: =-(IF(('입력값'!C62*100*(3/12))+('입력값'!C63*100*(3/12)*(1+'입력값'!D63/100)^4)+('입력값'!C64*100*(3/12))+('입력값'!C65*100*(3/12))+('입력값'!C66*100*(3/12)*(1+'입력값'!D66/100)^4)+('입력값'!C67*100*(3/12)*(1+'입력값'!D67/100)^4)+('입력값'!C68*100*(3/12)*(1+'입력값'!D68/100)^4)+('입력값'!C69*100*(3/12))+('입력값'!C70*100*(3/12))+('입력값'!C71*100*(3/12))+('입력값'!C72*100*(3/12))+('입력값'!C73*100*(3/12))=0,0,('입력값'!AD81+'입력값'!AD82)*('입력값'!C63*100*(3/12)*(1+'입력값'!D63/100)^4)/(('입력값'!C62*100*(3/12))+('입력값'!C63*100*(3/12)*(1+'입력값'!D63/100)^4)+('입력값'!C64*100*(3/12))+('입력값'!C65*100*(3/12))+('입력값'!C66*100*(3/12)*(1+'입력값'!D66/100)^4)+('입력값'!C67*100*(3/12)*(1+'입력값'!D67/100)^4)+('입력값'!C68*100*(3/12)*(1+'입력값'!D68/100)^4)+('입력값'!C69*100*(3/12))+('입력값'!C70*100*(3/12))+('입력값'!C71*100*(3/12))+('입력값'!C72*100*(3/12))+('입력값'!C73*100*(3/12))))) | AE10: =-(IF(('입력값'!C62*100*(3/12))+('입력값'!C63*100*(3/12)*(1+'입력값'!D63/100)^5)+('입력값'!C64*100*(3/12))+('입력값'!C65*100*(3/12))+('입력값'!C66*100*(3/12)*(1+'입력값'!D66/100)^5)+('입력값'!C67*100*(3/12)*(1+'입력값'!D67/100)^5)+('입력값'!C68*100*(3/12)*(1+'입력값'!D68/100)^5)+('입력값'!C69*100*(3/12))+('입력값'!C70*100*(3/12))+('입력값'!C71*100*(3/12))+('입력값'!C72*100*(3/12))+('입력값'!C73*100*(3/12))=0,0,('입력값'!AE81+'입력값'!AE82)*('입력값'!C63*100*(3/12)*(1+'입력값'!D63/100)^5)/(('입력값'!C62*100*(3/12))+('입력값'!C63*100*(3/12)*(1+'입력값'!D63/100)^5)+('입력값'!C64*100*(3/12))+('입력값'!C65*100*(3/12))+('입력값'!C66*100*(3/12)*(1+'입력값'!D66/100)^5)+('입력값'!C67*100*(3/12)*(1+'입력값'!D67/100)^5)+('입력값'!C68*100*(3/12)*(1+'입력값'!D68/100)^5)+('입력값'!C69*100*(3/12))+('입력값'!C70*100*(3/12))+('입력값'!C71*100*(3/12))+('입력값'!C72*100*(3/12))+('입력값'!C73*100*(3/12))))) | AF10: =-(IF(('입력값'!C62*100*(3/12))+('입력값'!C63*100*(3/12)*(1+'입력값'!D63/100)^5)+('입력값'!C64*100*(3/12))+('입력값'!C65*100*(3/12))+('입력값'!C66*100*(3/12)*(1+'입력값'!D66/100)^5)+('입력값'!C67*100*(3/12)*(1+'입력값'!D67/100)^5)+('입력값'!C68*100*(3/12)*(1+'입력값'!D68/100)^5)+('입력값'!C69*100*(3/12))+('입력값'!C70*100*(3/12))+('입력값'!C71*100*(3/12))+('입력값'!C72*100*(3/12))+('입력값'!C73*100*(3/12))=0,0,('입력값'!AF81+'입력값'!AF82)*('입력값'!C63*100*(3/12)*(1+'입력값'!D63/100)^5)/(('입력값'!C62*100*(3/12))+('입력값'!C63*100*(3/12)*(1+'입력값'!D63/100)^5)+('입력값'!C64*100*(3/12))+('입력값'!C65*100*(3/12))+('입력값'!C66*100*(3/12)*(1+'입력값'!D66/100)^5)+('입력값'!C67*100*(3/12)*(1+'입력값'!D67/100)^5)+('입력값'!C68*100*(3/12)*(1+'입력값'!D68/100)^5)+('입력값'!C69*100*(3/12))+('입력값'!C70*100*(3/12))+('입력값'!C71*100*(3/12))+('입력값'!C72*100*(3/12))+('입력값'!C73*100*(3/12))))) | AG10: =-(IF(('입력값'!C62*100*(3/12))+('입력값'!C63*100*(3/12)*(1+'입력값'!D63/100)^5)+('입력값'!C64*100*(3/12))+('입력값'!C65*100*(3/12))+('입력값'!C66*100*(3/12)*(1+'입력값'!D66/100)^5)+('입력값'!C67*100*(3/12)*(1+'입력값'!D67/100)^5)+('입력값'!C68*100*(3/12)*(1+'입력값'!D68/100)^5)+('입력값'!C69*100*(3/12))+('입력값'!C70*100*(3/12))+('입력값'!C71*100*(3/12))+('입력값'!C72*100*(3/12))+('입력값'!C73*100*(3/12))=0,0,('입력값'!AG81+'입력값'!AG82)*('입력값'!C63*100*(3/12)*(1+'입력값'!D63/100)^5)/(('입력값'!C62*100*(3/12))+('입력값'!C63*100*(3/12)*(1+'입력값'!D63/100)^5)+('입력값'!C64*100*(3/12))+('입력값'!C65*100*(3/12))+('입력값'!C66*100*(3/12)*(1+'입력값'!D66/100)^5)+('입력값'!C67*100*(3/12)*(1+'입력값'!D67/100)^5)+('입력값'!C68*100*(3/12)*(1+'입력값'!D68/100)^5)+('입력값'!C69*100*(3/12))+('입력값'!C70*100*(3/12))+('입력값'!C71*100*(3/12))+('입력값'!C72*100*(3/12))+('입력값'!C73*100*(3/12))))) | AH10: =-(IF(('입력값'!C62*100*(3/12))+('입력값'!C63*100*(3/12)*(1+'입력값'!D63/100)^5)+('입력값'!C64*100*(3/12))+('입력값'!C65*100*(3/12))+('입력값'!C66*100*(3/12)*(1+'입력값'!D66/100)^5)+('입력값'!C67*100*(3/12)*(1+'입력값'!D67/100)^5)+('입력값'!C68*100*(3/12)*(1+'입력값'!D68/100)^5)+('입력값'!C69*100*(3/12))+('입력값'!C70*100*(3/12))+('입력값'!C71*100*(3/12))+('입력값'!C72*100*(3/12))+('입력값'!C73*100*(3/12))=0,0,('입력값'!AH81+'입력값'!AH82)*('입력값'!C63*100*(3/12)*(1+'입력값'!D63/100)^5)/(('입력값'!C62*100*(3/12))+('입력값'!C63*100*(3/12)*(1+'입력값'!D63/100)^5)+('입력값'!C64*100*(3/12))+('입력값'!C65*100*(3/12))+('입력값'!C66*100*(3/12)*(1+'입력값'!D66/100)^5)+('입력값'!C67*100*(3/12)*(1+'입력값'!D67/100)^5)+('입력값'!C68*100*(3/12)*(1+'입력값'!D68/100)^5)+('입력값'!C69*100*(3/12))+('입력값'!C70*100*(3/12))+('입력값'!C71*100*(3/12))+('입력값'!C72*100*(3/12))+('입력값'!C73*100*(3/12))))) | AI10: =-(IF(('입력값'!C62*100*(3/12))+('입력값'!C63*100*(3/12)*(1+'입력값'!D63/100)^6)+('입력값'!C64*100*(3/12))+('입력값'!C65*100*(3/12))+('입력값'!C66*100*(3/12)*(1+'입력값'!D66/100)^6)+('입력값'!C67*100*(3/12)*(1+'입력값'!D67/100)^6)+('입력값'!C68*100*(3/12)*(1+'입력값'!D68/100)^6)+('입력값'!C69*100*(3/12))+('입력값'!C70*100*(3/12))+('입력값'!C71*100*(3/12))+('입력값'!C72*100*(3/12))+('입력값'!C73*100*(3/12))=0,0,('입력값'!AI81+'입력값'!AI82)*('입력값'!C63*100*(3/12)*(1+'입력값'!D63/100)^6)/(('입력값'!C62*100*(3/12))+('입력값'!C63*100*(3/12)*(1+'입력값'!D63/100)^6)+('입력값'!C64*100*(3/12))+('입력값'!C65*100*(3/12))+('입력값'!C66*100*(3/12)*(1+'입력값'!D66/100)^6)+('입력값'!C67*100*(3/12)*(1+'입력값'!D67/100)^6)+('입력값'!C68*100*(3/12)*(1+'입력값'!D68/100)^6)+('입력값'!C69*100*(3/12))+('입력값'!C70*100*(3/12))+('입력값'!C71*100*(3/12))+('입력값'!C72*100*(3/12))+('입력값'!C73*100*(3/12))))) | AJ10: =-(IF(('입력값'!C62*100*(3/12))+('입력값'!C63*100*(3/12)*(1+'입력값'!D63/100)^6)+('입력값'!C64*100*(3/12))+('입력값'!C65*100*(3/12))+('입력값'!C66*100*(3/12)*(1+'입력값'!D66/100)^6)+('입력값'!C67*100*(3/12)*(1+'입력값'!D67/100)^6)+('입력값'!C68*100*(3/12)*(1+'입력값'!D68/100)^6)+('입력값'!C69*100*(3/12))+('입력값'!C70*100*(3/12))+('입력값'!C71*100*(3/12))+('입력값'!C72*100*(3/12))+('입력값'!C73*100*(3/12))=0,0,('입력값'!AJ81+'입력값'!AJ82)*('입력값'!C63*100*(3/12)*(1+'입력값'!D63/100)^6)/(('입력값'!C62*100*(3/12))+('입력값'!C63*100*(3/12)*(1+'입력값'!D63/100)^6)+('입력값'!C64*100*(3/12))+('입력값'!C65*100*(3/12))+('입력값'!C66*100*(3/12)*(1+'입력값'!D66/100)^6)+('입력값'!C67*100*(3/12)*(1+'입력값'!D67/100)^6)+('입력값'!C68*100*(3/12)*(1+'입력값'!D68/100)^6)+('입력값'!C69*100*(3/12))+('입력값'!C70*100*(3/12))+('입력값'!C71*100*(3/12))+('입력값'!C72*100*(3/12))+('입력값'!C73*100*(3/12))))) | AK10: =-(IF(('입력값'!C62*100*(3/12))+('입력값'!C63*100*(3/12)*(1+'입력값'!D63/100)^6)+('입력값'!C64*100*(3/12))+('입력값'!C65*100*(3/12))+('입력값'!C66*100*(3/12)*(1+'입력값'!D66/100)^6)+('입력값'!C67*100*(3/12)*(1+'입력값'!D67/100)^6)+('입력값'!C68*100*(3/12)*(1+'입력값'!D68/100)^6)+('입력값'!C69*100*(3/12))+('입력값'!C70*100*(3/12))+('입력값'!C71*100*(3/12))+('입력값'!C72*100*(3/12))+('입력값'!C73*100*(3/12))=0,0,('입력값'!AK81+'입력값'!AK82)*('입력값'!C63*100*(3/12)*(1+'입력값'!D63/100)^6)/(('입력값'!C62*100*(3/12))+('입력값'!C63*100*(3/12)*(1+'입력값'!D63/100)^6)+('입력값'!C64*100*(3/12))+('입력값'!C65*100*(3/12))+('입력값'!C66*100*(3/12)*(1+'입력값'!D66/100)^6)+('입력값'!C67*100*(3/12)*(1+'입력값'!D67/100)^6)+('입력값'!C68*100*(3/12)*(1+'입력값'!D68/100)^6)+('입력값'!C69*100*(3/12))+('입력값'!C70*100*(3/12))+('입력값'!C71*100*(3/12))+('입력값'!C72*100*(3/12))+('입력값'!C73*100*(3/12))))) | AL10: =-(IF(('입력값'!C62*100*(3/12))+('입력값'!C63*100*(3/12)*(1+'입력값'!D63/100)^6)+('입력값'!C64*100*(3/12))+('입력값'!C65*100*(3/12))+('입력값'!C66*100*(3/12)*(1+'입력값'!D66/100)^6)+('입력값'!C67*100*(3/12)*(1+'입력값'!D67/100)^6)+('입력값'!C68*100*(3/12)*(1+'입력값'!D68/100)^6)+('입력값'!C69*100*(3/12))+('입력값'!C70*100*(3/12))+('입력값'!C71*100*(3/12))+('입력값'!C72*100*(3/12))+('입력값'!C73*100*(3/12))=0,0,('입력값'!AL81+'입력값'!AL82)*('입력값'!C63*100*(3/12)*(1+'입력값'!D63/100)^6)/(('입력값'!C62*100*(3/12))+('입력값'!C63*100*(3/12)*(1+'입력값'!D63/100)^6)+('입력값'!C64*100*(3/12))+('입력값'!C65*100*(3/12))+('입력값'!C66*100*(3/12)*(1+'입력값'!D66/100)^6)+('입력값'!C67*100*(3/12)*(1+'입력값'!D67/100)^6)+('입력값'!C68*100*(3/12)*(1+'입력값'!D68/100)^6)+('입력값'!C69*100*(3/12))+('입력값'!C70*100*(3/12))+('입력값'!C71*100*(3/12))+('입력값'!C72*100*(3/12))+('입력값'!C73*100*(3/12))))) | AM10: =-(IF(('입력값'!C62*100*(3/12))+('입력값'!C63*100*(3/12)*(1+'입력값'!D63/100)^7)+('입력값'!C64*100*(3/12))+('입력값'!C65*100*(3/12))+('입력값'!C66*100*(3/12)*(1+'입력값'!D66/100)^7)+('입력값'!C67*100*(3/12)*(1+'입력값'!D67/100)^7)+('입력값'!C68*100*(3/12)*(1+'입력값'!D68/100)^7)+('입력값'!C69*100*(3/12))+('입력값'!C70*100*(3/12))+('입력값'!C71*100*(3/12))+('입력값'!C72*100*(3/12))+('입력값'!C73*100*(3/12))=0,0,('입력값'!AM81+'입력값'!AM82)*('입력값'!C63*100*(3/12)*(1+'입력값'!D63/100)^7)/(('입력값'!C62*100*(3/12))+('입력값'!C63*100*(3/12)*(1+'입력값'!D63/100)^7)+('입력값'!C64*100*(3/12))+('입력값'!C65*100*(3/12))+('입력값'!C66*100*(3/12)*(1+'입력값'!D66/100)^7)+('입력값'!C67*100*(3/12)*(1+'입력값'!D67/100)^7)+('입력값'!C68*100*(3/12)*(1+'입력값'!D68/100)^7)+('입력값'!C69*100*(3/12))+('입력값'!C70*100*(3/12))+('입력값'!C71*100*(3/12))+('입력값'!C72*100*(3/12))+('입력값'!C73*100*(3/12))))) | AN10: =-(IF(('입력값'!C62*100*(3/12))+('입력값'!C63*100*(3/12)*(1+'입력값'!D63/100)^7)+('입력값'!C64*100*(3/12))+('입력값'!C65*100*(3/12))+('입력값'!C66*100*(3/12)*(1+'입력값'!D66/100)^7)+('입력값'!C67*100*(3/12)*(1+'입력값'!D67/100)^7)+('입력값'!C68*100*(3/12)*(1+'입력값'!D68/100)^7)+('입력값'!C69*100*(3/12))+('입력값'!C70*100*(3/12))+('입력값'!C71*100*(3/12))+('입력값'!C72*100*(3/12))+('입력값'!C73*100*(3/12))=0,0,('입력값'!AN81+'입력값'!AN82)*('입력값'!C63*100*(3/12)*(1+'입력값'!D63/100)^7)/(('입력값'!C62*100*(3/12))+('입력값'!C63*100*(3/12)*(1+'입력값'!D63/100)^7)+('입력값'!C64*100*(3/12))+('입력값'!C65*100*(3/12))+('입력값'!C66*100*(3/12)*(1+'입력값'!D66/100)^7)+('입력값'!C67*100*(3/12)*(1+'입력값'!D67/100)^7)+('입력값'!C68*100*(3/12)*(1+'입력값'!D68/100)^7)+('입력값'!C69*100*(3/12))+('입력값'!C70*100*(3/12))+('입력값'!C71*100*(3/12))+('입력값'!C72*100*(3/12))+('입력값'!C73*100*(3/12))))) | AO10: =-(IF(('입력값'!C62*100*(3/12))+('입력값'!C63*100*(3/12)*(1+'입력값'!D63/100)^7)+('입력값'!C64*100*(3/12))+('입력값'!C65*100*(3/12))+('입력값'!C66*100*(3/12)*(1+'입력값'!D66/100)^7)+('입력값'!C67*100*(3/12)*(1+'입력값'!D67/100)^7)+('입력값'!C68*100*(3/12)*(1+'입력값'!D68/100)^7)+('입력값'!C69*100*(3/12))+('입력값'!C70*100*(3/12))+('입력값'!C71*100*(3/12))+('입력값'!C72*100*(3/12))+('입력값'!C73*100*(3/12))=0,0,('입력값'!AO81+'입력값'!AO82)*('입력값'!C63*100*(3/12)*(1+'입력값'!D63/100)^7)/(('입력값'!C62*100*(3/12))+('입력값'!C63*100*(3/12)*(1+'입력값'!D63/100)^7)+('입력값'!C64*100*(3/12))+('입력값'!C65*100*(3/12))+('입력값'!C66*100*(3/12)*(1+'입력값'!D66/100)^7)+('입력값'!C67*100*(3/12)*(1+'입력값'!D67/100)^7)+('입력값'!C68*100*(3/12)*(1+'입력값'!D68/100)^7)+('입력값'!C69*100*(3/12))+('입력값'!C70*100*(3/12))+('입력값'!C71*100*(3/12))+('입력값'!C72*100*(3/12))+('입력값'!C73*100*(3/12))))) | AP10: =-(IF(('입력값'!C62*100*(3/12))+('입력값'!C63*100*(3/12)*(1+'입력값'!D63/100)^7)+('입력값'!C64*100*(3/12))+('입력값'!C65*100*(3/12))+('입력값'!C66*100*(3/12)*(1+'입력값'!D66/100)^7)+('입력값'!C67*100*(3/12)*(1+'입력값'!D67/100)^7)+('입력값'!C68*100*(3/12)*(1+'입력값'!D68/100)^7)+('입력값'!C69*100*(3/12))+('입력값'!C70*100*(3/12))+('입력값'!C71*100*(3/12))+('입력값'!C72*100*(3/12))+('입력값'!C73*100*(3/12))=0,0,('입력값'!AP81+'입력값'!AP82)*('입력값'!C63*100*(3/12)*(1+'입력값'!D63/100)^7)/(('입력값'!C62*100*(3/12))+('입력값'!C63*100*(3/12)*(1+'입력값'!D63/100)^7)+('입력값'!C64*100*(3/12))+('입력값'!C65*100*(3/12))+('입력값'!C66*100*(3/12)*(1+'입력값'!D66/100)^7)+('입력값'!C67*100*(3/12)*(1+'입력값'!D67/100)^7)+('입력값'!C68*100*(3/12)*(1+'입력값'!D68/100)^7)+('입력값'!C69*100*(3/12))+('입력값'!C70*100*(3/12))+('입력값'!C71*100*(3/12))+('입력값'!C72*100*(3/12))+('입력값'!C73*100*(3/12))))) | AQ10: =-(IF(('입력값'!C62*100*(3/12))+('입력값'!C63*100*(3/12)*(1+'입력값'!D63/100)^8)+('입력값'!C64*100*(3/12))+('입력값'!C65*100*(3/12))+('입력값'!C66*100*(3/12)*(1+'입력값'!D66/100)^8)+('입력값'!C67*100*(3/12)*(1+'입력값'!D67/100)^8)+('입력값'!C68*100*(3/12)*(1+'입력값'!D68/100)^8)+('입력값'!C69*100*(3/12))+('입력값'!C70*100*(3/12))+('입력값'!C71*100*(3/12))+('입력값'!C72*100*(3/12))+('입력값'!C73*100*(3/12))=0,0,('입력값'!AQ81+'입력값'!AQ82)*('입력값'!C63*100*(3/12)*(1+'입력값'!D63/100)^8)/(('입력값'!C62*100*(3/12))+('입력값'!C63*100*(3/12)*(1+'입력값'!D63/100)^8)+('입력값'!C64*100*(3/12))+('입력값'!C65*100*(3/12))+('입력값'!C66*100*(3/12)*(1+'입력값'!D66/100)^8)+('입력값'!C67*100*(3/12)*(1+'입력값'!D67/100)^8)+('입력값'!C68*100*(3/12)*(1+'입력값'!D68/100)^8)+('입력값'!C69*100*(3/12))+('입력값'!C70*100*(3/12))+('입력값'!C71*100*(3/12))+('입력값'!C72*100*(3/12))+('입력값'!C73*100*(3/12))))) | AR10: =-(IF(('입력값'!C62*100*(3/12))+('입력값'!C63*100*(3/12)*(1+'입력값'!D63/100)^8)+('입력값'!C64*100*(3/12))+('입력값'!C65*100*(3/12))+('입력값'!C66*100*(3/12)*(1+'입력값'!D66/100)^8)+('입력값'!C67*100*(3/12)*(1+'입력값'!D67/100)^8)+('입력값'!C68*100*(3/12)*(1+'입력값'!D68/100)^8)+('입력값'!C69*100*(3/12))+('입력값'!C70*100*(3/12))+('입력값'!C71*100*(3/12))+('입력값'!C72*100*(3/12))+('입력값'!C73*100*(3/12))=0,0,('입력값'!AR81+'입력값'!AR82)*('입력값'!C63*100*(3/12)*(1+'입력값'!D63/100)^8)/(('입력값'!C62*100*(3/12))+('입력값'!C63*100*(3/12)*(1+'입력값'!D63/100)^8)+('입력값'!C64*100*(3/12))+('입력값'!C65*100*(3/12))+('입력값'!C66*100*(3/12)*(1+'입력값'!D66/100)^8)+('입력값'!C67*100*(3/12)*(1+'입력값'!D67/100)^8)+('입력값'!C68*100*(3/12)*(1+'입력값'!D68/100)^8)+('입력값'!C69*100*(3/12))+('입력값'!C70*100*(3/12))+('입력값'!C71*100*(3/12))+('입력값'!C72*100*(3/12))+('입력값'!C73*100*(3/12))))) | AS10: =-(IF(('입력값'!C62*100*(3/12))+('입력값'!C63*100*(3/12)*(1+'입력값'!D63/100)^8)+('입력값'!C64*100*(3/12))+('입력값'!C65*100*(3/12))+('입력값'!C66*100*(3/12)*(1+'입력값'!D66/100)^8)+('입력값'!C67*100*(3/12)*(1+'입력값'!D67/100)^8)+('입력값'!C68*100*(3/12)*(1+'입력값'!D68/100)^8)+('입력값'!C69*100*(3/12))+('입력값'!C70*100*(3/12))+('입력값'!C71*100*(3/12))+('입력값'!C72*100*(3/12))+('입력값'!C73*100*(3/12))=0,0,('입력값'!AS81+'입력값'!AS82)*('입력값'!C63*100*(3/12)*(1+'입력값'!D63/100)^8)/(('입력값'!C62*100*(3/12))+('입력값'!C63*100*(3/12)*(1+'입력값'!D63/100)^8)+('입력값'!C64*100*(3/12))+('입력값'!C65*100*(3/12))+('입력값'!C66*100*(3/12)*(1+'입력값'!D66/100)^8)+('입력값'!C67*100*(3/12)*(1+'입력값'!D67/100)^8)+('입력값'!C68*100*(3/12)*(1+'입력값'!D68/100)^8)+('입력값'!C69*100*(3/12))+('입력값'!C70*100*(3/12))+('입력값'!C71*100*(3/12))+('입력값'!C72*100*(3/12))+('입력값'!C73*100*(3/12))))) | AT10: =-(IF(('입력값'!C62*100*(3/12))+('입력값'!C63*100*(3/12)*(1+'입력값'!D63/100)^8)+('입력값'!C64*100*(3/12))+('입력값'!C65*100*(3/12))+('입력값'!C66*100*(3/12)*(1+'입력값'!D66/100)^8)+('입력값'!C67*100*(3/12)*(1+'입력값'!D67/100)^8)+('입력값'!C68*100*(3/12)*(1+'입력값'!D68/100)^8)+('입력값'!C69*100*(3/12))+('입력값'!C70*100*(3/12))+('입력값'!C71*100*(3/12))+('입력값'!C72*100*(3/12))+('입력값'!C73*100*(3/12))=0,0,('입력값'!AT81+'입력값'!AT82)*('입력값'!C63*100*(3/12)*(1+'입력값'!D63/100)^8)/(('입력값'!C62*100*(3/12))+('입력값'!C63*100*(3/12)*(1+'입력값'!D63/100)^8)+('입력값'!C64*100*(3/12))+('입력값'!C65*100*(3/12))+('입력값'!C66*100*(3/12)*(1+'입력값'!D66/100)^8)+('입력값'!C67*100*(3/12)*(1+'입력값'!D67/100)^8)+('입력값'!C68*100*(3/12)*(1+'입력값'!D68/100)^8)+('입력값'!C69*100*(3/12))+('입력값'!C70*100*(3/12))+('입력값'!C71*100*(3/12))+('입력값'!C72*100*(3/12))+('입력값'!C73*100*(3/12))))) | AU10: =-(IF(('입력값'!C62*100*(3/12))+('입력값'!C63*100*(3/12)*(1+'입력값'!D63/100)^9)+('입력값'!C64*100*(3/12))+('입력값'!C65*100*(3/12))+('입력값'!C66*100*(3/12)*(1+'입력값'!D66/100)^9)+('입력값'!C67*100*(3/12)*(1+'입력값'!D67/100)^9)+('입력값'!C68*100*(3/12)*(1+'입력값'!D68/100)^9)+('입력값'!C69*100*(3/12))+('입력값'!C70*100*(3/12))+('입력값'!C71*100*(3/12))+('입력값'!C72*100*(3/12))+('입력값'!C73*100*(3/12))=0,0,('입력값'!AU81+'입력값'!AU82)*('입력값'!C63*100*(3/12)*(1+'입력값'!D63/100)^9)/(('입력값'!C62*100*(3/12))+('입력값'!C63*100*(3/12)*(1+'입력값'!D63/100)^9)+('입력값'!C64*100*(3/12))+('입력값'!C65*100*(3/12))+('입력값'!C66*100*(3/12)*(1+'입력값'!D66/100)^9)+('입력값'!C67*100*(3/12)*(1+'입력값'!D67/100)^9)+('입력값'!C68*100*(3/12)*(1+'입력값'!D68/100)^9)+('입력값'!C69*100*(3/12))+('입력값'!C70*100*(3/12))+('입력값'!C71*100*(3/12))+('입력값'!C72*100*(3/12))+('입력값'!C73*100*(3/12))))) | AV10: =-(IF(('입력값'!C62*100*(3/12))+('입력값'!C63*100*(3/12)*(1+'입력값'!D63/100)^9)+('입력값'!C64*100*(3/12))+('입력값'!C65*100*(3/12))+('입력값'!C66*100*(3/12)*(1+'입력값'!D66/100)^9)+('입력값'!C67*100*(3/12)*(1+'입력값'!D67/100)^9)+('입력값'!C68*100*(3/12)*(1+'입력값'!D68/100)^9)+('입력값'!C69*100*(3/12))+('입력값'!C70*100*(3/12))+('입력값'!C71*100*(3/12))+('입력값'!C72*100*(3/12))+('입력값'!C73*100*(3/12))=0,0,('입력값'!AV81+'입력값'!AV82)*('입력값'!C63*100*(3/12)*(1+'입력값'!D63/100)^9)/(('입력값'!C62*100*(3/12))+('입력값'!C63*100*(3/12)*(1+'입력값'!D63/100)^9)+('입력값'!C64*100*(3/12))+('입력값'!C65*100*(3/12))+('입력값'!C66*100*(3/12)*(1+'입력값'!D66/100)^9)+('입력값'!C67*100*(3/12)*(1+'입력값'!D67/100)^9)+('입력값'!C68*100*(3/12)*(1+'입력값'!D68/100)^9)+('입력값'!C69*100*(3/12))+('입력값'!C70*100*(3/12))+('입력값'!C71*100*(3/12))+('입력값'!C72*100*(3/12))+('입력값'!C73*100*(3/12))))) | AW10: =-(IF(('입력값'!C62*100*(3/12))+('입력값'!C63*100*(3/12)*(1+'입력값'!D63/100)^9)+('입력값'!C64*100*(3/12))+('입력값'!C65*100*(3/12))+('입력값'!C66*100*(3/12)*(1+'입력값'!D66/100)^9)+('입력값'!C67*100*(3/12)*(1+'입력값'!D67/100)^9)+('입력값'!C68*100*(3/12)*(1+'입력값'!D68/100)^9)+('입력값'!C69*100*(3/12))+('입력값'!C70*100*(3/12))+('입력값'!C71*100*(3/12))+('입력값'!C72*100*(3/12))+('입력값'!C73*100*(3/12))=0,0,('입력값'!AW81+'입력값'!AW82)*('입력값'!C63*100*(3/12)*(1+'입력값'!D63/100)^9)/(('입력값'!C62*100*(3/12))+('입력값'!C63*100*(3/12)*(1+'입력값'!D63/100)^9)+('입력값'!C64*100*(3/12))+('입력값'!C65*100*(3/12))+('입력값'!C66*100*(3/12)*(1+'입력값'!D66/100)^9)+('입력값'!C67*100*(3/12)*(1+'입력값'!D67/100)^9)+('입력값'!C68*100*(3/12)*(1+'입력값'!D68/100)^9)+('입력값'!C69*100*(3/12))+('입력값'!C70*100*(3/12))+('입력값'!C71*100*(3/12))+('입력값'!C72*100*(3/12))+('입력값'!C73*100*(3/12))))) | AX10: =-(IF(('입력값'!C62*100*(3/12))+('입력값'!C63*100*(3/12)*(1+'입력값'!D63/100)^9)+('입력값'!C64*100*(3/12))+('입력값'!C65*100*(3/12))+('입력값'!C66*100*(3/12)*(1+'입력값'!D66/100)^9)+('입력값'!C67*100*(3/12)*(1+'입력값'!D67/100)^9)+('입력값'!C68*100*(3/12)*(1+'입력값'!D68/100)^9)+('입력값'!C69*100*(3/12))+('입력값'!C70*100*(3/12))+('입력값'!C71*100*(3/12))+('입력값'!C72*100*(3/12))+('입력값'!C73*100*(3/12))=0,0,('입력값'!AX81+'입력값'!AX82)*('입력값'!C63*100*(3/12)*(1+'입력값'!D63/100)^9)/(('입력값'!C62*100*(3/12))+('입력값'!C63*100*(3/12)*(1+'입력값'!D63/100)^9)+('입력값'!C64*100*(3/12))+('입력값'!C65*100*(3/12))+('입력값'!C66*100*(3/12)*(1+'입력값'!D66/100)^9)+('입력값'!C67*100*(3/12)*(1+'입력값'!D67/100)^9)+('입력값'!C68*100*(3/12)*(1+'입력값'!D68/100)^9)+('입력값'!C69*100*(3/12))+('입력값'!C70*100*(3/12))+('입력값'!C71*100*(3/12))+('입력값'!C72*100*(3/12))+('입력값'!C73*100*(3/12))))) | AY10: =-(IF(('입력값'!C62*100*(3/12))+('입력값'!C63*100*(3/12)*(1+'입력값'!D63/100)^10)+('입력값'!C64*100*(3/12))+('입력값'!C65*100*(3/12))+('입력값'!C66*100*(3/12)*(1+'입력값'!D66/100)^10)+('입력값'!C67*100*(3/12)*(1+'입력값'!D67/100)^10)+('입력값'!C68*100*(3/12)*(1+'입력값'!D68/100)^10)+('입력값'!C69*100*(3/12))+('입력값'!C70*100*(3/12))+('입력값'!C71*100*(3/12))+('입력값'!C72*100*(3/12))+('입력값'!C73*100*(3/12))=0,0,('입력값'!AY81+'입력값'!AY82)*('입력값'!C63*100*(3/12)*(1+'입력값'!D63/100)^10)/(('입력값'!C62*100*(3/12))+('입력값'!C63*100*(3/12)*(1+'입력값'!D63/100)^10)+('입력값'!C64*100*(3/12))+('입력값'!C65*100*(3/12))+('입력값'!C66*100*(3/12)*(1+'입력값'!D66/100)^10)+('입력값'!C67*100*(3/12)*(1+'입력값'!D67/100)^10)+('입력값'!C68*100*(3/12)*(1+'입력값'!D68/100)^10)+('입력값'!C69*100*(3/12))+('입력값'!C70*100*(3/12))+('입력값'!C71*100*(3/12))+('입력값'!C72*100*(3/12))+('입력값'!C73*100*(3/12))))) | AZ10: =-(IF(('입력값'!C62*100*(3/12))+('입력값'!C63*100*(3/12)*(1+'입력값'!D63/100)^10)+('입력값'!C64*100*(3/12))+('입력값'!C65*100*(3/12))+('입력값'!C66*100*(3/12)*(1+'입력값'!D66/100)^10)+('입력값'!C67*100*(3/12)*(1+'입력값'!D67/100)^10)+('입력값'!C68*100*(3/12)*(1+'입력값'!D68/100)^10)+('입력값'!C69*100*(3/12))+('입력값'!C70*100*(3/12))+('입력값'!C71*100*(3/12))+('입력값'!C72*100*(3/12))+('입력값'!C73*100*(3/12))=0,0,('입력값'!AZ81+'입력값'!AZ82)*('입력값'!C63*100*(3/12)*(1+'입력값'!D63/100)^10)/(('입력값'!C62*100*(3/12))+('입력값'!C63*100*(3/12)*(1+'입력값'!D63/100)^10)+('입력값'!C64*100*(3/12))+('입력값'!C65*100*(3/12))+('입력값'!C66*100*(3/12)*(1+'입력값'!D66/100)^10)+('입력값'!C67*100*(3/12)*(1+'입력값'!D67/100)^10)+('입력값'!C68*100*(3/12)*(1+'입력값'!D68/100)^10)+('입력값'!C69*100*(3/12))+('입력값'!C70*100*(3/12))+('입력값'!C71*100*(3/12))+('입력값'!C72*100*(3/12))+('입력값'!C73*100*(3/12))))) | BA10: =-(IF(('입력값'!C62*100*(3/12))+('입력값'!C63*100*(3/12)*(1+'입력값'!D63/100)^10)+('입력값'!C64*100*(3/12))+('입력값'!C65*100*(3/12))+('입력값'!C66*100*(3/12)*(1+'입력값'!D66/100)^10)+('입력값'!C67*100*(3/12)*(1+'입력값'!D67/100)^10)+('입력값'!C68*100*(3/12)*(1+'입력값'!D68/100)^10)+('입력값'!C69*100*(3/12))+('입력값'!C70*100*(3/12))+('입력값'!C71*100*(3/12))+('입력값'!C72*100*(3/12))+('입력값'!C73*100*(3/12))=0,0,('입력값'!BA81+'입력값'!BA82)*('입력값'!C63*100*(3/12)*(1+'입력값'!D63/100)^10)/(('입력값'!C62*100*(3/12))+('입력값'!C63*100*(3/12)*(1+'입력값'!D63/100)^10)+('입력값'!C64*100*(3/12))+('입력값'!C65*100*(3/12))+('입력값'!C66*100*(3/12)*(1+'입력값'!D66/100)^10)+('입력값'!C67*100*(3/12)*(1+'입력값'!D67/100)^10)+('입력값'!C68*100*(3/12)*(1+'입력값'!D68/100)^10)+('입력값'!C69*100*(3/12))+('입력값'!C70*100*(3/12))+('입력값'!C71*100*(3/12))+('입력값'!C72*100*(3/12))+('입력값'!C73*100*(3/12))))) | BB10: =-(IF(('입력값'!C62*100*(3/12))+('입력값'!C63*100*(3/12)*(1+'입력값'!D63/100)^10)+('입력값'!C64*100*(3/12))+('입력값'!C65*100*(3/12))+('입력값'!C66*100*(3/12)*(1+'입력값'!D66/100)^10)+('입력값'!C67*100*(3/12)*(1+'입력값'!D67/100)^10)+('입력값'!C68*100*(3/12)*(1+'입력값'!D68/100)^10)+('입력값'!C69*100*(3/12))+('입력값'!C70*100*(3/12))+('입력값'!C71*100*(3/12))+('입력값'!C72*100*(3/12))+('입력값'!C73*100*(3/12))=0,0,('입력값'!BB81+'입력값'!BB82)*('입력값'!C63*100*(3/12)*(1+'입력값'!D63/100)^10)/(('입력값'!C62*100*(3/12))+('입력값'!C63*100*(3/12)*(1+'입력값'!D63/100)^10)+('입력값'!C64*100*(3/12))+('입력값'!C65*100*(3/12))+('입력값'!C66*100*(3/12)*(1+'입력값'!D66/100)^10)+('입력값'!C67*100*(3/12)*(1+'입력값'!D67/100)^10)+('입력값'!C68*100*(3/12)*(1+'입력값'!D68/100)^10)+('입력값'!C69*100*(3/12))+('입력값'!C70*100*(3/12))+('입력값'!C71*100*(3/12))+('입력값'!C72*100*(3/12))+('입력값'!C73*100*(3/12))))) | BC10: =-(IF(('입력값'!C62*100*(3/12))+('입력값'!C63*100*(3/12)*(1+'입력값'!D63/100)^11)+('입력값'!C64*100*(3/12))+('입력값'!C65*100*(3/12))+('입력값'!C66*100*(3/12)*(1+'입력값'!D66/100)^11)+('입력값'!C67*100*(3/12)*(1+'입력값'!D67/100)^11)+('입력값'!C68*100*(3/12)*(1+'입력값'!D68/100)^11)+('입력값'!C69*100*(3/12))+('입력값'!C70*100*(3/12))+('입력값'!C71*100*(3/12))+('입력값'!C72*100*(3/12))+('입력값'!C73*100*(3/12))=0,0,('입력값'!BC81+'입력값'!BC82)*('입력값'!C63*100*(3/12)*(1+'입력값'!D63/100)^11)/(('입력값'!C62*100*(3/12))+('입력값'!C63*100*(3/12)*(1+'입력값'!D63/100)^11)+('입력값'!C64*100*(3/12))+('입력값'!C65*100*(3/12))+('입력값'!C66*100*(3/12)*(1+'입력값'!D66/100)^11)+('입력값'!C67*100*(3/12)*(1+'입력값'!D67/100)^11)+('입력값'!C68*100*(3/12)*(1+'입력값'!D68/100)^11)+('입력값'!C69*100*(3/12))+('입력값'!C70*100*(3/12))+('입력값'!C71*100*(3/12))+('입력값'!C72*100*(3/12))+('입력값'!C73*100*(3/12))))) | BD10: =-(IF(('입력값'!C62*100*(3/12))+('입력값'!C63*100*(3/12)*(1+'입력값'!D63/100)^11)+('입력값'!C64*100*(3/12))+('입력값'!C65*100*(3/12))+('입력값'!C66*100*(3/12)*(1+'입력값'!D66/100)^11)+('입력값'!C67*100*(3/12)*(1+'입력값'!D67/100)^11)+('입력값'!C68*100*(3/12)*(1+'입력값'!D68/100)^11)+('입력값'!C69*100*(3/12))+('입력값'!C70*100*(3/12))+('입력값'!C71*100*(3/12))+('입력값'!C72*100*(3/12))+('입력값'!C73*100*(3/12))=0,0,('입력값'!BD81+'입력값'!BD82)*('입력값'!C63*100*(3/12)*(1+'입력값'!D63/100)^11)/(('입력값'!C62*100*(3/12))+('입력값'!C63*100*(3/12)*(1+'입력값'!D63/100)^11)+('입력값'!C64*100*(3/12))+('입력값'!C65*100*(3/12))+('입력값'!C66*100*(3/12)*(1+'입력값'!D66/100)^11)+('입력값'!C67*100*(3/12)*(1+'입력값'!D67/100)^11)+('입력값'!C68*100*(3/12)*(1+'입력값'!D68/100)^11)+('입력값'!C69*100*(3/12))+('입력값'!C70*100*(3/12))+('입력값'!C71*100*(3/12))+('입력값'!C72*100*(3/12))+('입력값'!C73*100*(3/12))))) | BE10: =-(IF(('입력값'!C62*100*(3/12))+('입력값'!C63*100*(3/12)*(1+'입력값'!D63/100)^11)+('입력값'!C64*100*(3/12))+('입력값'!C65*100*(3/12))+('입력값'!C66*100*(3/12)*(1+'입력값'!D66/100)^11)+('입력값'!C67*100*(3/12)*(1+'입력값'!D67/100)^11)+('입력값'!C68*100*(3/12)*(1+'입력값'!D68/100)^11)+('입력값'!C69*100*(3/12))+('입력값'!C70*100*(3/12))+('입력값'!C71*100*(3/12))+('입력값'!C72*100*(3/12))+('입력값'!C73*100*(3/12))=0,0,('입력값'!BE81+'입력값'!BE82)*('입력값'!C63*100*(3/12)*(1+'입력값'!D63/100)^11)/(('입력값'!C62*100*(3/12))+('입력값'!C63*100*(3/12)*(1+'입력값'!D63/100)^11)+('입력값'!C64*100*(3/12))+('입력값'!C65*100*(3/12))+('입력값'!C66*100*(3/12)*(1+'입력값'!D66/100)^11)+('입력값'!C67*100*(3/12)*(1+'입력값'!D67/100)^11)+('입력값'!C68*100*(3/12)*(1+'입력값'!D68/100)^11)+('입력값'!C69*100*(3/12))+('입력값'!C70*100*(3/12))+('입력값'!C71*100*(3/12))+('입력값'!C72*100*(3/12))+('입력값'!C73*100*(3/12))))) | BF10: =-(IF(('입력값'!C62*100*(3/12))+('입력값'!C63*100*(3/12)*(1+'입력값'!D63/100)^11)+('입력값'!C64*100*(3/12))+('입력값'!C65*100*(3/12))+('입력값'!C66*100*(3/12)*(1+'입력값'!D66/100)^11)+('입력값'!C67*100*(3/12)*(1+'입력값'!D67/100)^11)+('입력값'!C68*100*(3/12)*(1+'입력값'!D68/100)^11)+('입력값'!C69*100*(3/12))+('입력값'!C70*100*(3/12))+('입력값'!C71*100*(3/12))+('입력값'!C72*100*(3/12))+('입력값'!C73*100*(3/12))=0,0,('입력값'!BF81+'입력값'!BF82)*('입력값'!C63*100*(3/12)*(1+'입력값'!D63/100)^11)/(('입력값'!C62*100*(3/12))+('입력값'!C63*100*(3/12)*(1+'입력값'!D63/100)^11)+('입력값'!C64*100*(3/12))+('입력값'!C65*100*(3/12))+('입력값'!C66*100*(3/12)*(1+'입력값'!D66/100)^11)+('입력값'!C67*100*(3/12)*(1+'입력값'!D67/100)^11)+('입력값'!C68*100*(3/12)*(1+'입력값'!D68/100)^11)+('입력값'!C69*100*(3/12))+('입력값'!C70*100*(3/12))+('입력값'!C71*100*(3/12))+('입력값'!C72*100*(3/12))+('입력값'!C73*100*(3/12))))) | BG10: =-(IF(('입력값'!C62*100*(3/12))+('입력값'!C63*100*(3/12)*(1+'입력값'!D63/100)^12)+('입력값'!C64*100*(3/12))+('입력값'!C65*100*(3/12))+('입력값'!C66*100*(3/12)*(1+'입력값'!D66/100)^12)+('입력값'!C67*100*(3/12)*(1+'입력값'!D67/100)^12)+('입력값'!C68*100*(3/12)*(1+'입력값'!D68/100)^12)+('입력값'!C69*100*(3/12))+('입력값'!C70*100*(3/12))+('입력값'!C71*100*(3/12))+('입력값'!C72*100*(3/12))+('입력값'!C73*100*(3/12))=0,0,('입력값'!BG81+'입력값'!BG82)*('입력값'!C63*100*(3/12)*(1+'입력값'!D63/100)^12)/(('입력값'!C62*100*(3/12))+('입력값'!C63*100*(3/12)*(1+'입력값'!D63/100)^12)+('입력값'!C64*100*(3/12))+('입력값'!C65*100*(3/12))+('입력값'!C66*100*(3/12)*(1+'입력값'!D66/100)^12)+('입력값'!C67*100*(3/12)*(1+'입력값'!D67/100)^12)+('입력값'!C68*100*(3/12)*(1+'입력값'!D68/100)^12)+('입력값'!C69*100*(3/12))+('입력값'!C70*100*(3/12))+('입력값'!C71*100*(3/12))+('입력값'!C72*100*(3/12))+('입력값'!C73*100*(3/12))))) | BH10: =-(IF(('입력값'!C62*100*(3/12))+('입력값'!C63*100*(3/12)*(1+'입력값'!D63/100)^12)+('입력값'!C64*100*(3/12))+('입력값'!C65*100*(3/12))+('입력값'!C66*100*(3/12)*(1+'입력값'!D66/100)^12)+('입력값'!C67*100*(3/12)*(1+'입력값'!D67/100)^12)+('입력값'!C68*100*(3/12)*(1+'입력값'!D68/100)^12)+('입력값'!C69*100*(3/12))+('입력값'!C70*100*(3/12))+('입력값'!C71*100*(3/12))+('입력값'!C72*100*(3/12))+('입력값'!C73*100*(3/12))=0,0,('입력값'!BH81+'입력값'!BH82)*('입력값'!C63*100*(3/12)*(1+'입력값'!D63/100)^12)/(('입력값'!C62*100*(3/12))+('입력값'!C63*100*(3/12)*(1+'입력값'!D63/100)^12)+('입력값'!C64*100*(3/12))+('입력값'!C65*100*(3/12))+('입력값'!C66*100*(3/12)*(1+'입력값'!D66/100)^12)+('입력값'!C67*100*(3/12)*(1+'입력값'!D67/100)^12)+('입력값'!C68*100*(3/12)*(1+'입력값'!D68/100)^12)+('입력값'!C69*100*(3/12))+('입력값'!C70*100*(3/12))+('입력값'!C71*100*(3/12))+('입력값'!C72*100*(3/12))+('입력값'!C73*100*(3/12))))) | BI10: =-(IF(('입력값'!C62*100*(3/12))+('입력값'!C63*100*(3/12)*(1+'입력값'!D63/100)^12)+('입력값'!C64*100*(3/12))+('입력값'!C65*100*(3/12))+('입력값'!C66*100*(3/12)*(1+'입력값'!D66/100)^12)+('입력값'!C67*100*(3/12)*(1+'입력값'!D67/100)^12)+('입력값'!C68*100*(3/12)*(1+'입력값'!D68/100)^12)+('입력값'!C69*100*(3/12))+('입력값'!C70*100*(3/12))+('입력값'!C71*100*(3/12))+('입력값'!C72*100*(3/12))+('입력값'!C73*100*(3/12))=0,0,('입력값'!BI81+'입력값'!BI82)*('입력값'!C63*100*(3/12)*(1+'입력값'!D63/100)^12)/(('입력값'!C62*100*(3/12))+('입력값'!C63*100*(3/12)*(1+'입력값'!D63/100)^12)+('입력값'!C64*100*(3/12))+('입력값'!C65*100*(3/12))+('입력값'!C66*100*(3/12)*(1+'입력값'!D66/100)^12)+('입력값'!C67*100*(3/12)*(1+'입력값'!D67/100)^12)+('입력값'!C68*100*(3/12)*(1+'입력값'!D68/100)^12)+('입력값'!C69*100*(3/12))+('입력값'!C70*100*(3/12))+('입력값'!C71*100*(3/12))+('입력값'!C72*100*(3/12))+('입력값'!C73*100*(3/12))))) | BJ10: =-(IF(('입력값'!C62*100*(3/12))+('입력값'!C63*100*(3/12)*(1+'입력값'!D63/100)^12)+('입력값'!C64*100*(3/12))+('입력값'!C65*100*(3/12))+('입력값'!C66*100*(3/12)*(1+'입력값'!D66/100)^12)+('입력값'!C67*100*(3/12)*(1+'입력값'!D67/100)^12)+('입력값'!C68*100*(3/12)*(1+'입력값'!D68/100)^12)+('입력값'!C69*100*(3/12))+('입력값'!C70*100*(3/12))+('입력값'!C71*100*(3/12))+('입력값'!C72*100*(3/12))+('입력값'!C73*100*(3/12))=0,0,('입력값'!BJ81+'입력값'!BJ82)*('입력값'!C63*100*(3/12)*(1+'입력값'!D63/100)^12)/(('입력값'!C62*100*(3/12))+('입력값'!C63*100*(3/12)*(1+'입력값'!D63/100)^12)+('입력값'!C64*100*(3/12))+('입력값'!C65*100*(3/12))+('입력값'!C66*100*(3/12)*(1+'입력값'!D66/100)^12)+('입력값'!C67*100*(3/12)*(1+'입력값'!D67/100)^12)+('입력값'!C68*100*(3/12)*(1+'입력값'!D68/100)^12)+('입력값'!C69*100*(3/12))+('입력값'!C70*100*(3/12))+('입력값'!C71*100*(3/12))+('입력값'!C72*100*(3/12))+('입력값'!C73*100*(3/12))))) | BK10: =-(IF(('입력값'!C62*100*(3/12))+('입력값'!C63*100*(3/12)*(1+'입력값'!D63/100)^13)+('입력값'!C64*100*(3/12))+('입력값'!C65*100*(3/12))+('입력값'!C66*100*(3/12)*(1+'입력값'!D66/100)^13)+('입력값'!C67*100*(3/12)*(1+'입력값'!D67/100)^13)+('입력값'!C68*100*(3/12)*(1+'입력값'!D68/100)^13)+('입력값'!C69*100*(3/12))+('입력값'!C70*100*(3/12))+('입력값'!C71*100*(3/12))+('입력값'!C72*100*(3/12))+('입력값'!C73*100*(3/12))=0,0,('입력값'!BK81+'입력값'!BK82)*('입력값'!C63*100*(3/12)*(1+'입력값'!D63/100)^13)/(('입력값'!C62*100*(3/12))+('입력값'!C63*100*(3/12)*(1+'입력값'!D63/100)^13)+('입력값'!C64*100*(3/12))+('입력값'!C65*100*(3/12))+('입력값'!C66*100*(3/12)*(1+'입력값'!D66/100)^13)+('입력값'!C67*100*(3/12)*(1+'입력값'!D67/100)^13)+('입력값'!C68*100*(3/12)*(1+'입력값'!D68/100)^13)+('입력값'!C69*100*(3/12))+('입력값'!C70*100*(3/12))+('입력값'!C71*100*(3/12))+('입력값'!C72*100*(3/12))+('입력값'!C73*100*(3/12))))) | BL10: =-(IF(('입력값'!C62*100*(3/12))+('입력값'!C63*100*(3/12)*(1+'입력값'!D63/100)^13)+('입력값'!C64*100*(3/12))+('입력값'!C65*100*(3/12))+('입력값'!C66*100*(3/12)*(1+'입력값'!D66/100)^13)+('입력값'!C67*100*(3/12)*(1+'입력값'!D67/100)^13)+('입력값'!C68*100*(3/12)*(1+'입력값'!D68/100)^13)+('입력값'!C69*100*(3/12))+('입력값'!C70*100*(3/12))+('입력값'!C71*100*(3/12))+('입력값'!C72*100*(3/12))+('입력값'!C73*100*(3/12))=0,0,('입력값'!BL81+'입력값'!BL82)*('입력값'!C63*100*(3/12)*(1+'입력값'!D63/100)^13)/(('입력값'!C62*100*(3/12))+('입력값'!C63*100*(3/12)*(1+'입력값'!D63/100)^13)+('입력값'!C64*100*(3/12))+('입력값'!C65*100*(3/12))+('입력값'!C66*100*(3/12)*(1+'입력값'!D66/100)^13)+('입력값'!C67*100*(3/12)*(1+'입력값'!D67/100)^13)+('입력값'!C68*100*(3/12)*(1+'입력값'!D68/100)^13)+('입력값'!C69*100*(3/12))+('입력값'!C70*100*(3/12))+('입력값'!C71*100*(3/12))+('입력값'!C72*100*(3/12))+('입력값'!C73*100*(3/12))))) | BM10: =-(IF(('입력값'!C62*100*(3/12))+('입력값'!C63*100*(3/12)*(1+'입력값'!D63/100)^13)+('입력값'!C64*100*(3/12))+('입력값'!C65*100*(3/12))+('입력값'!C66*100*(3/12)*(1+'입력값'!D66/100)^13)+('입력값'!C67*100*(3/12)*(1+'입력값'!D67/100)^13)+('입력값'!C68*100*(3/12)*(1+'입력값'!D68/100)^13)+('입력값'!C69*100*(3/12))+('입력값'!C70*100*(3/12))+('입력값'!C71*100*(3/12))+('입력값'!C72*100*(3/12))+('입력값'!C73*100*(3/12))=0,0,('입력값'!BM81+'입력값'!BM82)*('입력값'!C63*100*(3/12)*(1+'입력값'!D63/100)^13)/(('입력값'!C62*100*(3/12))+('입력값'!C63*100*(3/12)*(1+'입력값'!D63/100)^13)+('입력값'!C64*100*(3/12))+('입력값'!C65*100*(3/12))+('입력값'!C66*100*(3/12)*(1+'입력값'!D66/100)^13)+('입력값'!C67*100*(3/12)*(1+'입력값'!D67/100)^13)+('입력값'!C68*100*(3/12)*(1+'입력값'!D68/100)^13)+('입력값'!C69*100*(3/12))+('입력값'!C70*100*(3/12))+('입력값'!C71*100*(3/12))+('입력값'!C72*100*(3/12))+('입력값'!C73*100*(3/12))))) | BN10: =-(IF(('입력값'!C62*100*(3/12))+('입력값'!C63*100*(3/12)*(1+'입력값'!D63/100)^13)+('입력값'!C64*100*(3/12))+('입력값'!C65*100*(3/12))+('입력값'!C66*100*(3/12)*(1+'입력값'!D66/100)^13)+('입력값'!C67*100*(3/12)*(1+'입력값'!D67/100)^13)+('입력값'!C68*100*(3/12)*(1+'입력값'!D68/100)^13)+('입력값'!C69*100*(3/12))+('입력값'!C70*100*(3/12))+('입력값'!C71*100*(3/12))+('입력값'!C72*100*(3/12))+('입력값'!C73*100*(3/12))=0,0,('입력값'!BN81+'입력값'!BN82)*('입력값'!C63*100*(3/12)*(1+'입력값'!D63/100)^13)/(('입력값'!C62*100*(3/12))+('입력값'!C63*100*(3/12)*(1+'입력값'!D63/100)^13)+('입력값'!C64*100*(3/12))+('입력값'!C65*100*(3/12))+('입력값'!C66*100*(3/12)*(1+'입력값'!D66/100)^13)+('입력값'!C67*100*(3/12)*(1+'입력값'!D67/100)^13)+('입력값'!C68*100*(3/12)*(1+'입력값'!D68/100)^13)+('입력값'!C69*100*(3/12))+('입력값'!C70*100*(3/12))+('입력값'!C71*100*(3/12))+('입력값'!C72*100*(3/12))+('입력값'!C73*100*(3/12))))) | BO10: =-(IF(('입력값'!C62*100*(3/12))+('입력값'!C63*100*(3/12)*(1+'입력값'!D63/100)^14)+('입력값'!C64*100*(3/12))+('입력값'!C65*100*(3/12))+('입력값'!C66*100*(3/12)*(1+'입력값'!D66/100)^14)+('입력값'!C67*100*(3/12)*(1+'입력값'!D67/100)^14)+('입력값'!C68*100*(3/12)*(1+'입력값'!D68/100)^14)+('입력값'!C69*100*(3/12))+('입력값'!C70*100*(3/12))+('입력값'!C71*100*(3/12))+('입력값'!C72*100*(3/12))+('입력값'!C73*100*(3/12))=0,0,('입력값'!BO81+'입력값'!BO82)*('입력값'!C63*100*(3/12)*(1+'입력값'!D63/100)^14)/(('입력값'!C62*100*(3/12))+('입력값'!C63*100*(3/12)*(1+'입력값'!D63/100)^14)+('입력값'!C64*100*(3/12))+('입력값'!C65*100*(3/12))+('입력값'!C66*100*(3/12)*(1+'입력값'!D66/100)^14)+('입력값'!C67*100*(3/12)*(1+'입력값'!D67/100)^14)+('입력값'!C68*100*(3/12)*(1+'입력값'!D68/100)^14)+('입력값'!C69*100*(3/12))+('입력값'!C70*100*(3/12))+('입력값'!C71*100*(3/12))+('입력값'!C72*100*(3/12))+('입력값'!C73*100*(3/12))))) | BP10: =-(IF(('입력값'!C62*100*(3/12))+('입력값'!C63*100*(3/12)*(1+'입력값'!D63/100)^14)+('입력값'!C64*100*(3/12))+('입력값'!C65*100*(3/12))+('입력값'!C66*100*(3/12)*(1+'입력값'!D66/100)^14)+('입력값'!C67*100*(3/12)*(1+'입력값'!D67/100)^14)+('입력값'!C68*100*(3/12)*(1+'입력값'!D68/100)^14)+('입력값'!C69*100*(3/12))+('입력값'!C70*100*(3/12))+('입력값'!C71*100*(3/12))+('입력값'!C72*100*(3/12))+('입력값'!C73*100*(3/12))=0,0,('입력값'!BP81+'입력값'!BP82)*('입력값'!C63*100*(3/12)*(1+'입력값'!D63/100)^14)/(('입력값'!C62*100*(3/12))+('입력값'!C63*100*(3/12)*(1+'입력값'!D63/100)^14)+('입력값'!C64*100*(3/12))+('입력값'!C65*100*(3/12))+('입력값'!C66*100*(3/12)*(1+'입력값'!D66/100)^14)+('입력값'!C67*100*(3/12)*(1+'입력값'!D67/100)^14)+('입력값'!C68*100*(3/12)*(1+'입력값'!D68/100)^14)+('입력값'!C69*100*(3/12))+('입력값'!C70*100*(3/12))+('입력값'!C71*100*(3/12))+('입력값'!C72*100*(3/12))+('입력값'!C73*100*(3/12))))) | BQ10: =-(IF(('입력값'!C62*100*(3/12))+('입력값'!C63*100*(3/12)*(1+'입력값'!D63/100)^14)+('입력값'!C64*100*(3/12))+('입력값'!C65*100*(3/12))+('입력값'!C66*100*(3/12)*(1+'입력값'!D66/100)^14)+('입력값'!C67*100*(3/12)*(1+'입력값'!D67/100)^14)+('입력값'!C68*100*(3/12)*(1+'입력값'!D68/100)^14)+('입력값'!C69*100*(3/12))+('입력값'!C70*100*(3/12))+('입력값'!C71*100*(3/12))+('입력값'!C72*100*(3/12))+('입력값'!C73*100*(3/12))=0,0,('입력값'!BQ81+'입력값'!BQ82)*('입력값'!C63*100*(3/12)*(1+'입력값'!D63/100)^14)/(('입력값'!C62*100*(3/12))+('입력값'!C63*100*(3/12)*(1+'입력값'!D63/100)^14)+('입력값'!C64*100*(3/12))+('입력값'!C65*100*(3/12))+('입력값'!C66*100*(3/12)*(1+'입력값'!D66/100)^14)+('입력값'!C67*100*(3/12)*(1+'입력값'!D67/100)^14)+('입력값'!C68*100*(3/12)*(1+'입력값'!D68/100)^14)+('입력값'!C69*100*(3/12))+('입력값'!C70*100*(3/12))+('입력값'!C71*100*(3/12))+('입력값'!C72*100*(3/12))+('입력값'!C73*100*(3/12))))) | BR10: =-(IF(('입력값'!C62*100*(3/12))+('입력값'!C63*100*(3/12)*(1+'입력값'!D63/100)^14)+('입력값'!C64*100*(3/12))+('입력값'!C65*100*(3/12))+('입력값'!C66*100*(3/12)*(1+'입력값'!D66/100)^14)+('입력값'!C67*100*(3/12)*(1+'입력값'!D67/100)^14)+('입력값'!C68*100*(3/12)*(1+'입력값'!D68/100)^14)+('입력값'!C69*100*(3/12))+('입력값'!C70*100*(3/12))+('입력값'!C71*100*(3/12))+('입력값'!C72*100*(3/12))+('입력값'!C73*100*(3/12))=0,0,('입력값'!BR81+'입력값'!BR82)*('입력값'!C63*100*(3/12)*(1+'입력값'!D63/100)^14)/(('입력값'!C62*100*(3/12))+('입력값'!C63*100*(3/12)*(1+'입력값'!D63/100)^14)+('입력값'!C64*100*(3/12))+('입력값'!C65*100*(3/12))+('입력값'!C66*100*(3/12)*(1+'입력값'!D66/100)^14)+('입력값'!C67*100*(3/12)*(1+'입력값'!D67/100)^14)+('입력값'!C68*100*(3/12)*(1+'입력값'!D68/100)^14)+('입력값'!C69*100*(3/12))+('입력값'!C70*100*(3/12))+('입력값'!C71*100*(3/12))+('입력값'!C72*100*(3/12))+('입력값'!C73*100*(3/12))))) | BS10: =-(IF(('입력값'!C62*100*(3/12))+('입력값'!C63*100*(3/12)*(1+'입력값'!D63/100)^15)+('입력값'!C64*100*(3/12))+('입력값'!C65*100*(3/12))+('입력값'!C66*100*(3/12)*(1+'입력값'!D66/100)^15)+('입력값'!C67*100*(3/12)*(1+'입력값'!D67/100)^15)+('입력값'!C68*100*(3/12)*(1+'입력값'!D68/100)^15)+('입력값'!C69*100*(3/12))+('입력값'!C70*100*(3/12))+('입력값'!C71*100*(3/12))+('입력값'!C72*100*(3/12))+('입력값'!C73*100*(3/12))=0,0,('입력값'!BS81+'입력값'!BS82)*('입력값'!C63*100*(3/12)*(1+'입력값'!D63/100)^15)/(('입력값'!C62*100*(3/12))+('입력값'!C63*100*(3/12)*(1+'입력값'!D63/100)^15)+('입력값'!C64*100*(3/12))+('입력값'!C65*100*(3/12))+('입력값'!C66*100*(3/12)*(1+'입력값'!D66/100)^15)+('입력값'!C67*100*(3/12)*(1+'입력값'!D67/100)^15)+('입력값'!C68*100*(3/12)*(1+'입력값'!D68/100)^15)+('입력값'!C69*100*(3/12))+('입력값'!C70*100*(3/12))+('입력값'!C71*100*(3/12))+('입력값'!C72*100*(3/12))+('입력값'!C73*100*(3/12))))) | BT10: =-(IF(('입력값'!C62*100*(3/12))+('입력값'!C63*100*(3/12)*(1+'입력값'!D63/100)^15)+('입력값'!C64*100*(3/12))+('입력값'!C65*100*(3/12))+('입력값'!C66*100*(3/12)*(1+'입력값'!D66/100)^15)+('입력값'!C67*100*(3/12)*(1+'입력값'!D67/100)^15)+('입력값'!C68*100*(3/12)*(1+'입력값'!D68/100)^15)+('입력값'!C69*100*(3/12))+('입력값'!C70*100*(3/12))+('입력값'!C71*100*(3/12))+('입력값'!C72*100*(3/12))+('입력값'!C73*100*(3/12))=0,0,('입력값'!BT81+'입력값'!BT82)*('입력값'!C63*100*(3/12)*(1+'입력값'!D63/100)^15)/(('입력값'!C62*100*(3/12))+('입력값'!C63*100*(3/12)*(1+'입력값'!D63/100)^15)+('입력값'!C64*100*(3/12))+('입력값'!C65*100*(3/12))+('입력값'!C66*100*(3/12)*(1+'입력값'!D66/100)^15)+('입력값'!C67*100*(3/12)*(1+'입력값'!D67/100)^15)+('입력값'!C68*100*(3/12)*(1+'입력값'!D68/100)^15)+('입력값'!C69*100*(3/12))+('입력값'!C70*100*(3/12))+('입력값'!C71*100*(3/12))+('입력값'!C72*100*(3/12))+('입력값'!C73*100*(3/12))))) | BU10: =-(IF(('입력값'!C62*100*(3/12))+('입력값'!C63*100*(3/12)*(1+'입력값'!D63/100)^15)+('입력값'!C64*100*(3/12))+('입력값'!C65*100*(3/12))+('입력값'!C66*100*(3/12)*(1+'입력값'!D66/100)^15)+('입력값'!C67*100*(3/12)*(1+'입력값'!D67/100)^15)+('입력값'!C68*100*(3/12)*(1+'입력값'!D68/100)^15)+('입력값'!C69*100*(3/12))+('입력값'!C70*100*(3/12))+('입력값'!C71*100*(3/12))+('입력값'!C72*100*(3/12))+('입력값'!C73*100*(3/12))=0,0,('입력값'!BU81+'입력값'!BU82)*('입력값'!C63*100*(3/12)*(1+'입력값'!D63/100)^15)/(('입력값'!C62*100*(3/12))+('입력값'!C63*100*(3/12)*(1+'입력값'!D63/100)^15)+('입력값'!C64*100*(3/12))+('입력값'!C65*100*(3/12))+('입력값'!C66*100*(3/12)*(1+'입력값'!D66/100)^15)+('입력값'!C67*100*(3/12)*(1+'입력값'!D67/100)^15)+('입력값'!C68*100*(3/12)*(1+'입력값'!D68/100)^15)+('입력값'!C69*100*(3/12))+('입력값'!C70*100*(3/12))+('입력값'!C71*100*(3/12))+('입력값'!C72*100*(3/12))+('입력값'!C73*100*(3/12))))) | BV10: =-(IF(('입력값'!C62*100*(3/12))+('입력값'!C63*100*(3/12)*(1+'입력값'!D63/100)^15)+('입력값'!C64*100*(3/12))+('입력값'!C65*100*(3/12))+('입력값'!C66*100*(3/12)*(1+'입력값'!D66/100)^15)+('입력값'!C67*100*(3/12)*(1+'입력값'!D67/100)^15)+('입력값'!C68*100*(3/12)*(1+'입력값'!D68/100)^15)+('입력값'!C69*100*(3/12))+('입력값'!C70*100*(3/12))+('입력값'!C71*100*(3/12))+('입력값'!C72*100*(3/12))+('입력값'!C73*100*(3/12))=0,0,('입력값'!BV81+'입력값'!BV82)*('입력값'!C63*100*(3/12)*(1+'입력값'!D63/100)^15)/(('입력값'!C62*100*(3/12))+('입력값'!C63*100*(3/12)*(1+'입력값'!D63/100)^15)+('입력값'!C64*100*(3/12))+('입력값'!C65*100*(3/12))+('입력값'!C66*100*(3/12)*(1+'입력값'!D66/100)^15)+('입력값'!C67*100*(3/12)*(1+'입력값'!D67/100)^15)+('입력값'!C68*100*(3/12)*(1+'입력값'!D68/100)^15)+('입력값'!C69*100*(3/12))+('입력값'!C70*100*(3/12))+('입력값'!C71*100*(3/12))+('입력값'!C72*100*(3/12))+('입력값'!C73*100*(3/12))))) | BW10: =-(IF(('입력값'!C62*100*(3/12))+('입력값'!C63*100*(3/12)*(1+'입력값'!D63/100)^16)+('입력값'!C64*100*(3/12))+('입력값'!C65*100*(3/12))+('입력값'!C66*100*(3/12)*(1+'입력값'!D66/100)^16)+('입력값'!C67*100*(3/12)*(1+'입력값'!D67/100)^16)+('입력값'!C68*100*(3/12)*(1+'입력값'!D68/100)^16)+('입력값'!C69*100*(3/12))+('입력값'!C70*100*(3/12))+('입력값'!C71*100*(3/12))+('입력값'!C72*100*(3/12))+('입력값'!C73*100*(3/12))=0,0,('입력값'!BW81+'입력값'!BW82)*('입력값'!C63*100*(3/12)*(1+'입력값'!D63/100)^16)/(('입력값'!C62*100*(3/12))+('입력값'!C63*100*(3/12)*(1+'입력값'!D63/100)^16)+('입력값'!C64*100*(3/12))+('입력값'!C65*100*(3/12))+('입력값'!C66*100*(3/12)*(1+'입력값'!D66/100)^16)+('입력값'!C67*100*(3/12)*(1+'입력값'!D67/100)^16)+('입력값'!C68*100*(3/12)*(1+'입력값'!D68/100)^16)+('입력값'!C69*100*(3/12))+('입력값'!C70*100*(3/12))+('입력값'!C71*100*(3/12))+('입력값'!C72*100*(3/12))+('입력값'!C73*100*(3/12))))) | BX10: =-(IF(('입력값'!C62*100*(3/12))+('입력값'!C63*100*(3/12)*(1+'입력값'!D63/100)^16)+('입력값'!C64*100*(3/12))+('입력값'!C65*100*(3/12))+('입력값'!C66*100*(3/12)*(1+'입력값'!D66/100)^16)+('입력값'!C67*100*(3/12)*(1+'입력값'!D67/100)^16)+('입력값'!C68*100*(3/12)*(1+'입력값'!D68/100)^16)+('입력값'!C69*100*(3/12))+('입력값'!C70*100*(3/12))+('입력값'!C71*100*(3/12))+('입력값'!C72*100*(3/12))+('입력값'!C73*100*(3/12))=0,0,('입력값'!BX81+'입력값'!BX82)*('입력값'!C63*100*(3/12)*(1+'입력값'!D63/100)^16)/(('입력값'!C62*100*(3/12))+('입력값'!C63*100*(3/12)*(1+'입력값'!D63/100)^16)+('입력값'!C64*100*(3/12))+('입력값'!C65*100*(3/12))+('입력값'!C66*100*(3/12)*(1+'입력값'!D66/100)^16)+('입력값'!C67*100*(3/12)*(1+'입력값'!D67/100)^16)+('입력값'!C68*100*(3/12)*(1+'입력값'!D68/100)^16)+('입력값'!C69*100*(3/12))+('입력값'!C70*100*(3/12))+('입력값'!C71*100*(3/12))+('입력값'!C72*100*(3/12))+('입력값'!C73*100*(3/12))))) | BY10: =-(IF(('입력값'!C62*100*(3/12))+('입력값'!C63*100*(3/12)*(1+'입력값'!D63/100)^16)+('입력값'!C64*100*(3/12))+('입력값'!C65*100*(3/12))+('입력값'!C66*100*(3/12)*(1+'입력값'!D66/100)^16)+('입력값'!C67*100*(3/12)*(1+'입력값'!D67/100)^16)+('입력값'!C68*100*(3/12)*(1+'입력값'!D68/100)^16)+('입력값'!C69*100*(3/12))+('입력값'!C70*100*(3/12))+('입력값'!C71*100*(3/12))+('입력값'!C72*100*(3/12))+('입력값'!C73*100*(3/12))=0,0,('입력값'!BY81+'입력값'!BY82)*('입력값'!C63*100*(3/12)*(1+'입력값'!D63/100)^16)/(('입력값'!C62*100*(3/12))+('입력값'!C63*100*(3/12)*(1+'입력값'!D63/100)^16)+('입력값'!C64*100*(3/12))+('입력값'!C65*100*(3/12))+('입력값'!C66*100*(3/12)*(1+'입력값'!D66/100)^16)+('입력값'!C67*100*(3/12)*(1+'입력값'!D67/100)^16)+('입력값'!C68*100*(3/12)*(1+'입력값'!D68/100)^16)+('입력값'!C69*100*(3/12))+('입력값'!C70*100*(3/12))+('입력값'!C71*100*(3/12))+('입력값'!C72*100*(3/12))+('입력값'!C73*100*(3/12))))) | BZ10: =-(IF(('입력값'!C62*100*(3/12))+('입력값'!C63*100*(3/12)*(1+'입력값'!D63/100)^16)+('입력값'!C64*100*(3/12))+('입력값'!C65*100*(3/12))+('입력값'!C66*100*(3/12)*(1+'입력값'!D66/100)^16)+('입력값'!C67*100*(3/12)*(1+'입력값'!D67/100)^16)+('입력값'!C68*100*(3/12)*(1+'입력값'!D68/100)^16)+('입력값'!C69*100*(3/12))+('입력값'!C70*100*(3/12))+('입력값'!C71*100*(3/12))+('입력값'!C72*100*(3/12))+('입력값'!C73*100*(3/12))=0,0,('입력값'!BZ81+'입력값'!BZ82)*('입력값'!C63*100*(3/12)*(1+'입력값'!D63/100)^16)/(('입력값'!C62*100*(3/12))+('입력값'!C63*100*(3/12)*(1+'입력값'!D63/100)^16)+('입력값'!C64*100*(3/12))+('입력값'!C65*100*(3/12))+('입력값'!C66*100*(3/12)*(1+'입력값'!D66/100)^16)+('입력값'!C67*100*(3/12)*(1+'입력값'!D67/100)^16)+('입력값'!C68*100*(3/12)*(1+'입력값'!D68/100)^16)+('입력값'!C69*100*(3/12))+('입력값'!C70*100*(3/12))+('입력값'!C71*100*(3/12))+('입력값'!C72*100*(3/12))+('입력값'!C73*100*(3/12))))) | CA10: =-(IF(('입력값'!C62*100*(3/12))+('입력값'!C63*100*(3/12)*(1+'입력값'!D63/100)^17)+('입력값'!C64*100*(3/12))+('입력값'!C65*100*(3/12))+('입력값'!C66*100*(3/12)*(1+'입력값'!D66/100)^17)+('입력값'!C67*100*(3/12)*(1+'입력값'!D67/100)^17)+('입력값'!C68*100*(3/12)*(1+'입력값'!D68/100)^17)+('입력값'!C69*100*(3/12))+('입력값'!C70*100*(3/12))+('입력값'!C71*100*(3/12))+('입력값'!C72*100*(3/12))+('입력값'!C73*100*(3/12))=0,0,('입력값'!CA81+'입력값'!CA82)*('입력값'!C63*100*(3/12)*(1+'입력값'!D63/100)^17)/(('입력값'!C62*100*(3/12))+('입력값'!C63*100*(3/12)*(1+'입력값'!D63/100)^17)+('입력값'!C64*100*(3/12))+('입력값'!C65*100*(3/12))+('입력값'!C66*100*(3/12)*(1+'입력값'!D66/100)^17)+('입력값'!C67*100*(3/12)*(1+'입력값'!D67/100)^17)+('입력값'!C68*100*(3/12)*(1+'입력값'!D68/100)^17)+('입력값'!C69*100*(3/12))+('입력값'!C70*100*(3/12))+('입력값'!C71*100*(3/12))+('입력값'!C72*100*(3/12))+('입력값'!C73*100*(3/12))))) | CB10: =-(IF(('입력값'!C62*100*(3/12))+('입력값'!C63*100*(3/12)*(1+'입력값'!D63/100)^17)+('입력값'!C64*100*(3/12))+('입력값'!C65*100*(3/12))+('입력값'!C66*100*(3/12)*(1+'입력값'!D66/100)^17)+('입력값'!C67*100*(3/12)*(1+'입력값'!D67/100)^17)+('입력값'!C68*100*(3/12)*(1+'입력값'!D68/100)^17)+('입력값'!C69*100*(3/12))+('입력값'!C70*100*(3/12))+('입력값'!C71*100*(3/12))+('입력값'!C72*100*(3/12))+('입력값'!C73*100*(3/12))=0,0,('입력값'!CB81+'입력값'!CB82)*('입력값'!C63*100*(3/12)*(1+'입력값'!D63/100)^17)/(('입력값'!C62*100*(3/12))+('입력값'!C63*100*(3/12)*(1+'입력값'!D63/100)^17)+('입력값'!C64*100*(3/12))+('입력값'!C65*100*(3/12))+('입력값'!C66*100*(3/12)*(1+'입력값'!D66/100)^17)+('입력값'!C67*100*(3/12)*(1+'입력값'!D67/100)^17)+('입력값'!C68*100*(3/12)*(1+'입력값'!D68/100)^17)+('입력값'!C69*100*(3/12))+('입력값'!C70*100*(3/12))+('입력값'!C71*100*(3/12))+('입력값'!C72*100*(3/12))+('입력값'!C73*100*(3/12))))) | CC10: =-(IF(('입력값'!C62*100*(3/12))+('입력값'!C63*100*(3/12)*(1+'입력값'!D63/100)^17)+('입력값'!C64*100*(3/12))+('입력값'!C65*100*(3/12))+('입력값'!C66*100*(3/12)*(1+'입력값'!D66/100)^17)+('입력값'!C67*100*(3/12)*(1+'입력값'!D67/100)^17)+('입력값'!C68*100*(3/12)*(1+'입력값'!D68/100)^17)+('입력값'!C69*100*(3/12))+('입력값'!C70*100*(3/12))+('입력값'!C71*100*(3/12))+('입력값'!C72*100*(3/12))+('입력값'!C73*100*(3/12))=0,0,('입력값'!CC81+'입력값'!CC82)*('입력값'!C63*100*(3/12)*(1+'입력값'!D63/100)^17)/(('입력값'!C62*100*(3/12))+('입력값'!C63*100*(3/12)*(1+'입력값'!D63/100)^17)+('입력값'!C64*100*(3/12))+('입력값'!C65*100*(3/12))+('입력값'!C66*100*(3/12)*(1+'입력값'!D66/100)^17)+('입력값'!C67*100*(3/12)*(1+'입력값'!D67/100)^17)+('입력값'!C68*100*(3/12)*(1+'입력값'!D68/100)^17)+('입력값'!C69*100*(3/12))+('입력값'!C70*100*(3/12))+('입력값'!C71*100*(3/12))+('입력값'!C72*100*(3/12))+('입력값'!C73*100*(3/12))))) | CD10: =-(IF(('입력값'!C62*100*(3/12))+('입력값'!C63*100*(3/12)*(1+'입력값'!D63/100)^17)+('입력값'!C64*100*(3/12))+('입력값'!C65*100*(3/12))+('입력값'!C66*100*(3/12)*(1+'입력값'!D66/100)^17)+('입력값'!C67*100*(3/12)*(1+'입력값'!D67/100)^17)+('입력값'!C68*100*(3/12)*(1+'입력값'!D68/100)^17)+('입력값'!C69*100*(3/12))+('입력값'!C70*100*(3/12))+('입력값'!C71*100*(3/12))+('입력값'!C72*100*(3/12))+('입력값'!C73*100*(3/12))=0,0,('입력값'!CD81+'입력값'!CD82)*('입력값'!C63*100*(3/12)*(1+'입력값'!D63/100)^17)/(('입력값'!C62*100*(3/12))+('입력값'!C63*100*(3/12)*(1+'입력값'!D63/100)^17)+('입력값'!C64*100*(3/12))+('입력값'!C65*100*(3/12))+('입력값'!C66*100*(3/12)*(1+'입력값'!D66/100)^17)+('입력값'!C67*100*(3/12)*(1+'입력값'!D67/100)^17)+('입력값'!C68*100*(3/12)*(1+'입력값'!D68/100)^17)+('입력값'!C69*100*(3/12))+('입력값'!C70*100*(3/12))+('입력값'!C71*100*(3/12))+('입력값'!C72*100*(3/12))+('입력값'!C73*100*(3/12))))) | CE10: =-(IF(('입력값'!C62*100*(3/12))+('입력값'!C63*100*(3/12)*(1+'입력값'!D63/100)^18)+('입력값'!C64*100*(3/12))+('입력값'!C65*100*(3/12))+('입력값'!C66*100*(3/12)*(1+'입력값'!D66/100)^18)+('입력값'!C67*100*(3/12)*(1+'입력값'!D67/100)^18)+('입력값'!C68*100*(3/12)*(1+'입력값'!D68/100)^18)+('입력값'!C69*100*(3/12))+('입력값'!C70*100*(3/12))+('입력값'!C71*100*(3/12))+('입력값'!C72*100*(3/12))+('입력값'!C73*100*(3/12))=0,0,('입력값'!CE81+'입력값'!CE82)*('입력값'!C63*100*(3/12)*(1+'입력값'!D63/100)^18)/(('입력값'!C62*100*(3/12))+('입력값'!C63*100*(3/12)*(1+'입력값'!D63/100)^18)+('입력값'!C64*100*(3/12))+('입력값'!C65*100*(3/12))+('입력값'!C66*100*(3/12)*(1+'입력값'!D66/100)^18)+('입력값'!C67*100*(3/12)*(1+'입력값'!D67/100)^18)+('입력값'!C68*100*(3/12)*(1+'입력값'!D68/100)^18)+('입력값'!C69*100*(3/12))+('입력값'!C70*100*(3/12))+('입력값'!C71*100*(3/12))+('입력값'!C72*100*(3/12))+('입력값'!C73*100*(3/12))))) | CF10: =-(IF(('입력값'!C62*100*(3/12))+('입력값'!C63*100*(3/12)*(1+'입력값'!D63/100)^18)+('입력값'!C64*100*(3/12))+('입력값'!C65*100*(3/12))+('입력값'!C66*100*(3/12)*(1+'입력값'!D66/100)^18)+('입력값'!C67*100*(3/12)*(1+'입력값'!D67/100)^18)+('입력값'!C68*100*(3/12)*(1+'입력값'!D68/100)^18)+('입력값'!C69*100*(3/12))+('입력값'!C70*100*(3/12))+('입력값'!C71*100*(3/12))+('입력값'!C72*100*(3/12))+('입력값'!C73*100*(3/12))=0,0,('입력값'!CF81+'입력값'!CF82)*('입력값'!C63*100*(3/12)*(1+'입력값'!D63/100)^18)/(('입력값'!C62*100*(3/12))+('입력값'!C63*100*(3/12)*(1+'입력값'!D63/100)^18)+('입력값'!C64*100*(3/12))+('입력값'!C65*100*(3/12))+('입력값'!C66*100*(3/12)*(1+'입력값'!D66/100)^18)+('입력값'!C67*100*(3/12)*(1+'입력값'!D67/100)^18)+('입력값'!C68*100*(3/12)*(1+'입력값'!D68/100)^18)+('입력값'!C69*100*(3/12))+('입력값'!C70*100*(3/12))+('입력값'!C71*100*(3/12))+('입력값'!C72*100*(3/12))+('입력값'!C73*100*(3/12))))) | CG10: =-(IF(('입력값'!C62*100*(3/12))+('입력값'!C63*100*(3/12)*(1+'입력값'!D63/100)^18)+('입력값'!C64*100*(3/12))+('입력값'!C65*100*(3/12))+('입력값'!C66*100*(3/12)*(1+'입력값'!D66/100)^18)+('입력값'!C67*100*(3/12)*(1+'입력값'!D67/100)^18)+('입력값'!C68*100*(3/12)*(1+'입력값'!D68/100)^18)+('입력값'!C69*100*(3/12))+('입력값'!C70*100*(3/12))+('입력값'!C71*100*(3/12))+('입력값'!C72*100*(3/12))+('입력값'!C73*100*(3/12))=0,0,('입력값'!CG81+'입력값'!CG82)*('입력값'!C63*100*(3/12)*(1+'입력값'!D63/100)^18)/(('입력값'!C62*100*(3/12))+('입력값'!C63*100*(3/12)*(1+'입력값'!D63/100)^18)+('입력값'!C64*100*(3/12))+('입력값'!C65*100*(3/12))+('입력값'!C66*100*(3/12)*(1+'입력값'!D66/100)^18)+('입력값'!C67*100*(3/12)*(1+'입력값'!D67/100)^18)+('입력값'!C68*100*(3/12)*(1+'입력값'!D68/100)^18)+('입력값'!C69*100*(3/12))+('입력값'!C70*100*(3/12))+('입력값'!C71*100*(3/12))+('입력값'!C72*100*(3/12))+('입력값'!C73*100*(3/12))))) | CH10: =-(IF(('입력값'!C62*100*(3/12))+('입력값'!C63*100*(3/12)*(1+'입력값'!D63/100)^18)+('입력값'!C64*100*(3/12))+('입력값'!C65*100*(3/12))+('입력값'!C66*100*(3/12)*(1+'입력값'!D66/100)^18)+('입력값'!C67*100*(3/12)*(1+'입력값'!D67/100)^18)+('입력값'!C68*100*(3/12)*(1+'입력값'!D68/100)^18)+('입력값'!C69*100*(3/12))+('입력값'!C70*100*(3/12))+('입력값'!C71*100*(3/12))+('입력값'!C72*100*(3/12))+('입력값'!C73*100*(3/12))=0,0,('입력값'!CH81+'입력값'!CH82)*('입력값'!C63*100*(3/12)*(1+'입력값'!D63/100)^18)/(('입력값'!C62*100*(3/12))+('입력값'!C63*100*(3/12)*(1+'입력값'!D63/100)^18)+('입력값'!C64*100*(3/12))+('입력값'!C65*100*(3/12))+('입력값'!C66*100*(3/12)*(1+'입력값'!D66/100)^18)+('입력값'!C67*100*(3/12)*(1+'입력값'!D67/100)^18)+('입력값'!C68*100*(3/12)*(1+'입력값'!D68/100)^18)+('입력값'!C69*100*(3/12))+('입력값'!C70*100*(3/12))+('입력값'!C71*100*(3/12))+('입력값'!C72*100*(3/12))+('입력값'!C73*100*(3/12))))) | CI10: =-(IF(('입력값'!C62*100*(3/12))+('입력값'!C63*100*(3/12)*(1+'입력값'!D63/100)^19)+('입력값'!C64*100*(3/12))+('입력값'!C65*100*(3/12))+('입력값'!C66*100*(3/12)*(1+'입력값'!D66/100)^19)+('입력값'!C67*100*(3/12)*(1+'입력값'!D67/100)^19)+('입력값'!C68*100*(3/12)*(1+'입력값'!D68/100)^19)+('입력값'!C69*100*(3/12))+('입력값'!C70*100*(3/12))+('입력값'!C71*100*(3/12))+('입력값'!C72*100*(3/12))+('입력값'!C73*100*(3/12))=0,0,('입력값'!CI81+'입력값'!CI82)*('입력값'!C63*100*(3/12)*(1+'입력값'!D63/100)^19)/(('입력값'!C62*100*(3/12))+('입력값'!C63*100*(3/12)*(1+'입력값'!D63/100)^19)+('입력값'!C64*100*(3/12))+('입력값'!C65*100*(3/12))+('입력값'!C66*100*(3/12)*(1+'입력값'!D66/100)^19)+('입력값'!C67*100*(3/12)*(1+'입력값'!D67/100)^19)+('입력값'!C68*100*(3/12)*(1+'입력값'!D68/100)^19)+('입력값'!C69*100*(3/12))+('입력값'!C70*100*(3/12))+('입력값'!C71*100*(3/12))+('입력값'!C72*100*(3/12))+('입력값'!C73*100*(3/12))))) | CJ10: =-(IF(('입력값'!C62*100*(3/12))+('입력값'!C63*100*(3/12)*(1+'입력값'!D63/100)^19)+('입력값'!C64*100*(3/12))+('입력값'!C65*100*(3/12))+('입력값'!C66*100*(3/12)*(1+'입력값'!D66/100)^19)+('입력값'!C67*100*(3/12)*(1+'입력값'!D67/100)^19)+('입력값'!C68*100*(3/12)*(1+'입력값'!D68/100)^19)+('입력값'!C69*100*(3/12))+('입력값'!C70*100*(3/12))+('입력값'!C71*100*(3/12))+('입력값'!C72*100*(3/12))+('입력값'!C73*100*(3/12))=0,0,('입력값'!CJ81+'입력값'!CJ82)*('입력값'!C63*100*(3/12)*(1+'입력값'!D63/100)^19)/(('입력값'!C62*100*(3/12))+('입력값'!C63*100*(3/12)*(1+'입력값'!D63/100)^19)+('입력값'!C64*100*(3/12))+('입력값'!C65*100*(3/12))+('입력값'!C66*100*(3/12)*(1+'입력값'!D66/100)^19)+('입력값'!C67*100*(3/12)*(1+'입력값'!D67/100)^19)+('입력값'!C68*100*(3/12)*(1+'입력값'!D68/100)^19)+('입력값'!C69*100*(3/12))+('입력값'!C70*100*(3/12))+('입력값'!C71*100*(3/12))+('입력값'!C72*100*(3/12))+('입력값'!C73*100*(3/12))))) | CK10: =-(IF(('입력값'!C62*100*(3/12))+('입력값'!C63*100*(3/12)*(1+'입력값'!D63/100)^19)+('입력값'!C64*100*(3/12))+('입력값'!C65*100*(3/12))+('입력값'!C66*100*(3/12)*(1+'입력값'!D66/100)^19)+('입력값'!C67*100*(3/12)*(1+'입력값'!D67/100)^19)+('입력값'!C68*100*(3/12)*(1+'입력값'!D68/100)^19)+('입력값'!C69*100*(3/12))+('입력값'!C70*100*(3/12))+('입력값'!C71*100*(3/12))+('입력값'!C72*100*(3/12))+('입력값'!C73*100*(3/12))=0,0,('입력값'!CK81+'입력값'!CK82)*('입력값'!C63*100*(3/12)*(1+'입력값'!D63/100)^19)/(('입력값'!C62*100*(3/12))+('입력값'!C63*100*(3/12)*(1+'입력값'!D63/100)^19)+('입력값'!C64*100*(3/12))+('입력값'!C65*100*(3/12))+('입력값'!C66*100*(3/12)*(1+'입력값'!D66/100)^19)+('입력값'!C67*100*(3/12)*(1+'입력값'!D67/100)^19)+('입력값'!C68*100*(3/12)*(1+'입력값'!D68/100)^19)+('입력값'!C69*100*(3/12))+('입력값'!C70*100*(3/12))+('입력값'!C71*100*(3/12))+('입력값'!C72*100*(3/12))+('입력값'!C73*100*(3/12))))) | CL10: =-(IF(('입력값'!C62*100*(3/12))+('입력값'!C63*100*(3/12)*(1+'입력값'!D63/100)^19)+('입력값'!C64*100*(3/12))+('입력값'!C65*100*(3/12))+('입력값'!C66*100*(3/12)*(1+'입력값'!D66/100)^19)+('입력값'!C67*100*(3/12)*(1+'입력값'!D67/100)^19)+('입력값'!C68*100*(3/12)*(1+'입력값'!D68/100)^19)+('입력값'!C69*100*(3/12))+('입력값'!C70*100*(3/12))+('입력값'!C71*100*(3/12))+('입력값'!C72*100*(3/12))+('입력값'!C73*100*(3/12))=0,0,('입력값'!CL81+'입력값'!CL82)*('입력값'!C63*100*(3/12)*(1+'입력값'!D63/100)^19)/(('입력값'!C62*100*(3/12))+('입력값'!C63*100*(3/12)*(1+'입력값'!D63/100)^19)+('입력값'!C64*100*(3/12))+('입력값'!C65*100*(3/12))+('입력값'!C66*100*(3/12)*(1+'입력값'!D66/100)^19)+('입력값'!C67*100*(3/12)*(1+'입력값'!D67/100)^19)+('입력값'!C68*100*(3/12)*(1+'입력값'!D68/100)^19)+('입력값'!C69*100*(3/12))+('입력값'!C70*100*(3/12))+('입력값'!C71*100*(3/12))+('입력값'!C72*100*(3/12))+('입력값'!C73*100*(3/12)))))
