Workbook

Sheet 목차
B2: 당진 태양광발전
B3: 재무모델 v2 (분기·5트랜치) — 재생E AI Agent 자동생성 · 2026-08-27
B6: 시트 | C6: 내용
B7: Report | C7: Executive Summary — 핵심 KPI
B8: 입력값 | C8: 화면에서 입력한 원본 값 — Funding 등이 이 시트를 참조
B9: Funding | C9: 자금조달 — 자본금 + 5트랜치 조건
B10: Debt | C10: 트랜치별 상환 스케줄 (A/B/C/D/후순위) + 합계
B11: Revenue | C11: 발전량 · 매출
B12: Opex | C12: 운영비 (선순위/후순위)
B13: IS(Q) | C13: 분기 손익계산서
B14: CF(Q) | C14: 분기 현금흐름 · DSCR · 배당
B16: ※ Funding 시트의 트랜치 조건·총사업비 항목·사업자 지분은 "입력값" 시트를 참조하는 수식입니다(입력값 시트를 고치면 같이 바뀝니다). 그 외 계산 결과(세금·DSCR·배당 등)는 값(baked) 기준이라 가정을 바꾸려면 생성기에서 다시 뽑아야 합니다.

Sheet Report
A1: 당진 태양광발전
A2: Executive Summary (v2 · 분기 · 5트랜치)
B4: 사업 개요
B6: 사업명 | D6: ='입력값'!C6
B7: 설비용량 [MW] | D7: ='입력값'!C7
B8: 총 기간 수(분기) | D8: 86
B9: 건설 개시 | D9: 2024-06
B11: 재원조달
B13: 총투자비(TIC) [KRWm] | D13: ='Funding'!C18
B14: 건설이자(IDC) [KRWm] | D14: ='Funding'!C17
B15: 자기자본 [KRWm] | D15: ='Funding'!C7
B16: 차입금 합계 [KRWm] | D16: ='Funding'!C13
B18: 수익성 지표
B20: Project IRR 세전 [%] | D20: ='CF(Q)'!D62
B21: Project IRR 세후 [%] | D21: ='CF(Q)'!D63
B22: Equity IRR (FCFE) [%] | D22: ='CF(Q)'!D64
B23: Equity IRR (배당) [%] | D23: ='CF(Q)'!D65
B24: Investor IRR [%] | D24: ='CF(Q)'!D66
B25: 최소 단순DSCR(연 합산) [x] | D25: ='CF(Q)'!D47
B26: 최소 누적DSCR [x] | D26: ='CF(Q)'!D48
B27: 총영업수익(전체기간) [KRWm] | D27: ='Revenue'!D12
B28: 총영업비용(전체기간) [KRWm] | D28: ='Opex'!D24
B29: 총선순위이자 [KRWm] | D29: ='Debt'!D76
B30: 총법인세 [KRWm] | D30: =-'IS(Q)'!D44
B31: 총배당(연차+청산) [KRWm] | D31: ='CF(Q)'!D16

Sheet 입력값
A1: 당진 태양광발전
A2: 입력값 — 화면에서 입력한 값 (다른 시트가 이 시트를 참조)
B4: 사업 기본 가정
B6: 사업명 | C6: 당진 태양광발전
B7: 설비용량[MW] | C7: 99.998
B8: 총사업비[억원] | C8: 1410.6882
B9: 자기자본[억원] | C9: 150
B10: 판매단가[원/kWh]
B11: 판매단가 에스컬레이션[%/yr]
B12: 발전량 열화율[%/yr] | C12: 0.5
B13: 소내소비율[%] | C13: 0
B14: 일조시간[h/day] | C14: 3.77
B15: 상각대상액(직접입력)[KRWm] | C15: 137976.35
B16: 감가상각 내용연수[yr] | C16: 20
B17: 철거비(복구충당부채)[억원] | C17: 20
B18: 대리은행수수료(총액)[KRWm] | C18: 320
B19: 기타 비현금 세무손금(총액)[KRWm] | C19: 6743.65
B20: DSRA 최초 적립액[억원] | C20: 50
B21: DSRA 적립기준(차기 X개월분) | C21: 6
B22: 최소 보유현금[억원] | C22: 10
B23: 배당 게이트 — 단순DSCR 최소치[x] | C23: 1.1
... B26: 최초 배당 가능 연도 | C26: 2028
B28: 법인세 가정
B30: 이월결손금 공제한도[%] | C30: 80
B31: 최저한세율[%] | C31: 10
B32: 통합투자세액공제율[%] | C32: 1
B33: 지방소득세율(법인세 대비)[%] | C33: 10
B34: 세액공제 농특세율[%] | C34: 20
B36: 건설기간 손실(연도별)
B38: 연도 | C38: 금액[KRWm]
B39: 2024 | C39: 140
B40: 2025 | C40: 140
B42: 통합투자세액공제 기준액(연도별)
B44: 연도 | C44: 금액[KRWm]
B45: 2024 | C45: 43600
B46: 2025 | C46: 65400
B48: 판매단가 트랙 (PPA/SMP+REC 등)
B50: 트랙 | C50: 비중[%] | D50: 단가[원/kWh] | E50: 에스컬레이션[%/yr]
B51: 트랙1 | C51: 0 | D51: 0 | E51: 0
B52: 트랙2 | C52: 60.0012 | D52: 160 | E52: 0
B53: 트랙3 | C53: 39.9988 | D53: 147 | E53: 0
B55: 트랜치 조건
B57: 트랜치 | C57: 금액[억원] | D57: 건설금리[%] | E57: 운영금리[%] | F57: 거치(yr) | G57: 상환(yr) | H57: 방식 | I57: 투입순서
B58: 선순위A | C58: 500 | D58: 0.056 | E58: 0.056 | F58: 2 | G58: 16 | H58: 3 | I58: 2
B59: 선순위B | C59: 500 | D59: 0.055 | E59: 0.055 | F59: 2 | G59: 16 | H59: 3 | I59: 2
B60: 선순위C | C60: 350 | D60: 0.055 | E60: 0.055 | F60: 1.25 | G60: 16 | H60: 3 | I60: 4
B61: 선순위D | C61: 0 | D61: 0.0225 | E61: 0.0225 | F61: 5 | G61: 10 | H61: 3 | I61: 3
B62: 후순위 | C62: 0 | D62: 0.0565 | E62: 0.0565 | F62: 15 | G62: 2.75 | H62: 3 | I62: 1
B63: 자본금 | C63: =C9 | I63: 1
B65: 총사업비 지출 스케줄 (건설 분기별 비중)
B67: 구 분 | C67: unit | D67: 합 계 | E67: 2024-06-30 | F67: 2024-09-30 | G67: 2024-12-31 | H67: 2025-03-31 | I67: 2025-06-30 | J67: 2025-09-30 | K67: 2025-12-31 | L67: 2026-03-31 | M67: 2026-06-30 | N67: 2026-09-30 | O67: 2026-12-31 | P67: 2027-03-31 | Q67: 2027-06-30 | R67: 2027-09-30 | S67: 2027-12-31 | T67: 2028-03-31 | U67: 2028-06-30 | V67: 2028-09-30 | W67: 2028-12-31 | X67: 2029-03-31 | Y67: 2029-06-30 | Z67: 2029-09-30 | AA67: 2029-12-31 | AB67: 2030-03-31 | AC67: 2030-06-30 | AD67: 2030-09-30 | AE67: 2030-12-31 | AF67: 2031-03-31 | AG67: 2031-06-30 | AH67: 2031-09-30 | AI67: 2031-12-31 | AJ67: 2032-03-31 | AK67: 2032-06-30 | AL67: 2032-09-30 | AM67: 2032-12-31 | AN67: 2033-03-31 | AO67: 2033-06-30 | AP67: 2033-09-30 | AQ67: 2033-12-31 | AR67: 2034-03-31 | AS67: 2034-06-30 | AT67: 2034-09-30 | AU67: 2034-12-31 | AV67: 2035-03-31 | AW67: 2035-06-30 | AX67: 2035-09-30 | AY67: 2035-12-31 | AZ67: 2036-03-31 | BA67: 2036-06-30 | BB67: 2036-09-30 | BC67: 2036-12-31 | BD67: 2037-03-31 | BE67: 2037-06-30 | BF67: 2037-09-30 | BG67: 2037-12-31 | BH67: 2038-03-31 | BI67: 2038-06-30 | BJ67: 2038-09-30 | BK67: 2038-12-31 | BL67: 2039-03-31 | BM67: 2039-06-30 | BN67: 2039-09-30 | BO67: 2039-12-31 | BP67: 2040-03-31 | BQ67: 2040-06-30 | BR67: 2040-09-30 | BS67: 2040-12-31 | BT67: 2041-03-31 | BU67: 2041-06-30 | BV67: 2041-09-30 | BW67: 2041-12-31 | BX67: 2042-03-31 | BY67: 2042-06-30 | BZ67: 2042-09-30 | CA67: 2042-12-31 | CB67: 2043-03-31 | CC67: 2043-06-30 | CD67: 2043-09-30 | CE67: 2043-12-31 | CF67: 2044-03-31 | CG67: 2044-06-30 | CH67: 2044-09-30 | CI67: 2044-12-31 | CJ67: 2045-03-31 | CK67: 2045-06-30 | CL67: 2045-09-30
B69: 지출 비중 | C69: [비율] | D69: =SUM(E69:CL69) | E69: 0.2471866 | F69: 0.079060992 | G69: 0.15756374 | H69: 0.15764661 | I69: 0.16477795 | J69: 0.19376409
B71: 방식3 상환비율 ("예시 불러오기" 전용 — 원본 상환 스케줄)
B73: 구 분 | C73: unit | D73: 합 계 | E73: 2024-06-30 | F73: 2024-09-30 | G73: 2024-12-31 | H73: 2025-03-31 | I73: 2025-06-30 | J73: 2025-09-30 | K73: 2025-12-31 | L73: 2026-03-31 | M73: 2026-06-30 | N73: 2026-09-30 | O73: 2026-12-31 | P73: 2027-03-31 | Q73: 2027-06-30 | R73: 2027-09-30 | S73: 2027-12-31 | T73: 2028-03-31 | U73: 2028-06-30 | V73: 2028-09-30 | W73: 2028-12-31 | X73: 2029-03-31 | Y73: 2029-06-30 | Z73: 2029-09-30 | AA73: 2029-12-31 | AB73: 2030-03-31 | AC73: 2030-06-30 | AD73: 2030-09-30 | AE73: 2030-12-31 | AF73: 2031-03-31 | AG73: 2031-06-30 | AH73: 2031-09-30 | AI73: 2031-12-31 | AJ73: 2032-03-31 | AK73: 2032-06-30 | AL73: 2032-09-30 | AM73: 2032-12-31 | AN73: 2033-03-31 | AO73: 2033-06-30 | AP73: 2033-09-30 | AQ73: 2033-12-31 | AR73: 2034-03-31 | AS73: 2034-06-30 | AT73: 2034-09-30 | AU73: 2034-12-31 | AV73: 2035-03-31 | AW73: 2035-06-30 | AX73: 2035-09-30 | AY73: 2035-12-31 | AZ73: 2036-03-31 | BA73: 2036-06-30 | BB73: 2036-09-30 | BC73: 2036-12-31 | BD73: 2037-03-31 | BE73: 2037-06-30 | BF73: 2037-09-30 | BG73: 2037-12-31 | BH73: 2038-03-31 | BI73: 2038-06-30 | BJ73: 2038-09-30 | BK73: 2038-12-31 | BL73: 2039-03-31 | BM73: 2039-06-30 | BN73: 2039-09-30 | BO73: 2039-12-31 | BP73: 2040-03-31 | BQ73: 2040-06-30 | BR73: 2040-09-30 | BS73: 2040-12-31 | BT73: 2041-03-31 | BU73: 2041-06-30 | BV73: 2041-09-30 | BW73: 2041-12-31 | BX73: 2042-03-31 | BY73: 2042-06-30 | BZ73: 2042-09-30 | CA73: 2042-12-31 | CB73: 2043-03-31 | CC73: 2043-06-30 | CD73: 2043-09-30 | CE73: 2043-12-31 | CF73: 2044-03-31 | CG73: 2044-06-30 | CH73: 2044-09-30 | CI73: 2044-12-31 | CJ73: 2045-03-31 | CK73: 2045-06-30 | CL73: 2045-09-30
B75: 선순위A 상환비율 | C75: [비율] | N75: 0.030625 | O75: 0.021 | P75: 0.013 | Q75: 0.013 | R75: 0.014 | S75: 0.014 | T75: 0.014 | U75: 0.014 | V75: 0.014 | W75: 0.014 | X75: 0.014 | Y75: 0.015 | Z75: 0.015 | AA75: 0.015 | AB75: 0.015 | AC75: 0.015 | AD75: 0.015 | AE75: 0.015625 | AF75: 0.015625 | AG75: 0.015625 | AH75: 0.015625 | AI75: 0.015625 | AJ75: 0.015625 | AK75: 0.015625 | AL75: 0.015625 | AM75: 0.015625 | AN75: 0.015625 | AO75: 0.015625 | AP75: 0.015625 | AQ75: 0.015625 | AR75: 0.015625 | AS75: 0.015625 | AT75: 0.015625 | AU75: 0.015625 | AV75: 0.015625 | AW75: 0.015625 | AX75: 0.015625 | AY75: 0.015625 | AZ75: 0.015625 | BA75: 0.015625 | BB75: 0.015625 | BC75: 0.015625 | BD75: 0.015625 | BE75: 0.015625 | BF75: 0.015625 | BG75: 0.015625 | BH75: 0.015625 | BI75: 0.015625 | BJ75: 0.015625 | BK75: 0.015625 | BL75: 0.015625 | BM75: 0.015625 | BN75: 0.015625 | BO75: 0.015625 | BP75: 0.015625 | BQ75: 0.015625 | BR75: 0.015625 | BS75: 0.015625 | BT75: 0.015625 | BU75: 0.015625 | BV75: 0.015625 | BW75: 0.015625 | BX75: 0.015625 | BY75: 0.015625
B76: 선순위B 상환비율 | C76: [비율] | N76: 0.030625 | O76: 0.021 | P76: 0.013 | Q76: 0.013 | R76: 0.014 | S76: 0.014 | T76: 0.014 | U76: 0.014 | V76: 0.014 | W76: 0.014 | X76: 0.014 | Y76: 0.015 | Z76: 0.015 | AA76: 0.015 | AB76: 0.015 | AC76: 0.015 | AD76: 0.015 | AE76: 0.015625 | AF76: 0.015625 | AG76: 0.015625 | AH76: 0.015625 | AI76: 0.015625 | AJ76: 0.015625 | AK76: 0.015625 | AL76: 0.015625 | AM76: 0.015625 | AN76: 0.015625 | AO76: 0.015625 | AP76: 0.015625 | AQ76: 0.015625 | AR76: 0.015625 | AS76: 0.015625 | AT76: 0.015625 | AU76: 0.015625 | AV76: 0.015625 | AW76: 0.015625 | AX76: 0.015625 | AY76: 0.015625 | AZ76: 0.015625 | BA76: 0.015625 | BB76: 0.015625 | BC76: 0.015625 | BD76: 0.015625 | BE76: 0.015625 | BF76: 0.015625 | BG76: 0.015625 | BH76: 0.015625 | BI76: 0.015625 | BJ76: 0.015625 | BK76: 0.015625 | BL76: 0.015625 | BM76: 0.015625 | BN76: 0.015625 | BO76: 0.015625 | BP76: 0.015625 | BQ76: 0.015625 | BR76: 0.015625 | BS76: 0.015625 | BT76: 0.015625 | BU76: 0.015625 | BV76: 0.015625 | BW76: 0.015625 | BX76: 0.015625 | BY76: 0.015625
B77: 선순위C 상환비율 | C77: [비율] | N77: 0.030625 | O77: 0.021 | P77: 0.013 | Q77: 0.013 | R77: 0.014 | S77: 0.014 | T77: 0.014 | U77: 0.014 | V77: 0.014 | W77: 0.014 | X77: 0.014 | Y77: 0.015 | Z77: 0.015 | AA77: 0.015 | AB77: 0.015 | AC77: 0.015 | AD77: 0.015 | AE77: 0.015625 | AF77: 0.015625 | AG77: 0.015625 | AH77: 0.015625 | AI77: 0.015625 | AJ77: 0.015625 | AK77: 0.015625 | AL77: 0.015625 | AM77: 0.015625 | AN77: 0.015625 | AO77: 0.015625 | AP77: 0.015625 | AQ77: 0.015625 | AR77: 0.015625 | AS77: 0.015625 | AT77: 0.015625 | AU77: 0.015625 | AV77: 0.015625 | AW77: 0.015625 | AX77: 0.015625 | AY77: 0.015625 | AZ77: 0.015625 | BA77: 0.015625 | BB77: 0.015625 | BC77: 0.015625 | BD77: 0.015625 | BE77: 0.015625 | BF77: 0.015625 | BG77: 0.015625 | BH77: 0.015625 | BI77: 0.015625 | BJ77: 0.015625 | BK77: 0.015625 | BL77: 0.015625 | BM77: 0.015625 | BN77: 0.015625 | BO77: 0.015625 | BP77: 0.015625 | BQ77: 0.015625 | BR77: 0.015625 | BS77: 0.015625 | BT77: 0.015625 | BU77: 0.015625 | BV77: 0.015625 | BW77: 0.015625 | BX77: 0.015625 | BY77: 0.015625
B79: 총사업비 항목
B81: 항목 | C81: 금액[억원]
B82: EPC
B83: 감리비
B84: 공사보험료
B85: 토지임대료(선납)
B86: 토지임대료(분납)
B87: 사업개발비
B88: 민원처리비
B89: 사업성자문비
B90: 법인운영비
B91: 기타예비비
B92: 신주발행비용
B93: 금융부대비용
B95: 운영비 항목
B97: 항목 | C97: 연간금액[억원/yr] | D97: 에스컬레이션[%/yr]
B98: 부지임대료 | C98: 9.555 | D98: 0
B99: O&M | C99: 15 | D99: 1.5
B100: 보험료 | C100: 6.5 | D100: 0
B101: 환경모니터링비용 | C101: 1.095 | D101: 0
B102: 소내전력비 | C102: 2 | D102: 2
B103: 인건비 | C103: 2 | D103: 2
B104: 법인운영비 | C104: 1.5 | D104: 2
B105: 주민보상비 | C105: 8 | D105: 0
B106: 도로점용료 | C106: 0.3 | D106: 0
B107: 예비비 | C107: 3 | D107: 0
B108: 전력거래수수료 | C108: 0.21416 | D108: 0
B109: 관리운영비 성과보수 | C109: 0 | D109: 0
B112: 실측 오버라이드 ("예시 불러오기" 전용 — 공식이 아니라 원본 FS의 분기별 실제값)
B114: 구 분 | C114: unit | D114: 합 계 | E114: 2024-06-30 | F114: 2024-09-30 | G114: 2024-12-31 | H114: 2025-03-31 | I114: 2025-06-30 | J114: 2025-09-30 | K114: 2025-12-31 | L114: 2026-03-31 | M114: 2026-06-30 | N114: 2026-09-30 | O114: 2026-12-31 | P114: 2027-03-31 | Q114: 2027-06-30 | R114: 2027-09-30 | S114: 2027-12-31 | T114: 2028-03-31 | U114: 2028-06-30 | V114: 2028-09-30 | W114: 2028-12-31 | X114: 2029-03-31 | Y114: 2029-06-30 | Z114: 2029-09-30 | AA114: 2029-12-31 | AB114: 2030-03-31 | AC114: 2030-06-30 | AD114: 2030-09-30 | AE114: 2030-12-31 | AF114: 2031-03-31 | AG114: 2031-06-30 | AH114: 2031-09-30 | AI114: 2031-12-31 | AJ114: 2032-03-31 | AK114: 2032-06-30 | AL114: 2032-09-30 | AM114: 2032-12-31 | AN114: 2033-03-31 | AO114: 2033-06-30 | AP114: 2033-09-30 | AQ114: 2033-12-31 | AR114: 2034-03-31 | AS114: 2034-06-30 | AT114: 2034-09-30 | AU114: 2034-12-31 | AV114: 2035-03-31 | AW114: 2035-06-30 | AX114: 2035-09-30 | AY114: 2035-12-31 | AZ114: 2036-03-31 | BA114: 2036-06-30 | BB114: 2036-09-30 | BC114: 2036-12-31 | BD114: 2037-03-31 | BE114: 2037-06-30 | BF114: 2037-09-30 | BG114: 2037-12-31 | BH114: 2038-03-31 | BI114: 2038-06-30 | BJ114: 2038-09-30 | BK114: 2038-12-31 | BL114: 2039-03-31 | BM114: 2039-06-30 | BN114: 2039-09-30 | BO114: 2039-12-31 | BP114: 2040-03-31 | BQ114: 2040-06-30 | BR114: 2040-09-30 | BS114: 2040-12-31 | BT114: 2041-03-31 | BU114: 2041-06-30 | BV114: 2041-09-30 | BW114: 2041-12-31 | BX114: 2042-03-31 | BY114: 2042-06-30 | BZ114: 2042-09-30 | CA114: 2042-12-31 | CB114: 2043-03-31 | CC114: 2043-06-30 | CD114: 2043-09-30 | CE114: 2043-12-31 | CF114: 2044-03-31 | CG114: 2044-06-30 | CH114: 2044-09-30 | CI114: 2044-12-31 | CJ114: 2045-03-31 | CK114: 2045-06-30 | CL114: 2045-09-30
B116: 판매단가(실측) | C116: [원/kWh] | K116: 154.80016 | L116: 154.80016 | M116: 154.80016 | N116: 154.80016 | O116: 154.80016 | P116: 154.80016 | Q116: 154.80016 | R116: 154.80016 | S116: 154.80016 | T116: 154.80016 | U116: 154.80016 | V116: 154.80016 | W116: 154.80016 | X116: 154.80016 | Y116: 154.80016 | Z116: 154.80016 | AA116: 154.80016 | AB116: 154.80016 | AC116: 154.80016 | AD116: 154.80016 | AE116: 154.80016 | AF116: 154.80016 | AG116: 154.80016 | AH116: 154.80016 | AI116: 154.80016 | AJ116: 154.80016 | AK116: 154.80016 | AL116: 154.80016 | AM116: 154.80016 | AN116: 154.80016 | AO116: 154.80016 | AP116: 154.80016 | AQ116: 154.80016 | AR116: 154.80016 | AS116: 154.80016 | AT116: 154.80016 | AU116: 154.80016 | AV116: 154.80016 | AW116: 154.80016 | AX116: 154.80016 | AY116: 154.80016 | AZ116: 154.80016 | BA116: 154.80016 | BB116: 154.80016 | BC116: 154.80016 | BD116: 154.80016 | BE116: 154.80016 | BF116: 154.80016 | BG116: 154.80016 | BH116: 154.80016 | BI116: 154.80016 | BJ116: 154.80016 | BK116: 154.80016 | BL116: 154.80016 | BM116: 154.80016 | BN116: 154.80016 | BO116: 154.80016 | BP116: 154.80016 | BQ116: 154.80016 | BR116: 154.80016 | BS116: 154.80016 | BT116: 154.80016 | BU116: 154.80016 | BV116: 154.80016 | BW116: 154.80016 | BX116: 154.80016 | BY116: 154.80016 | BZ116: 154.80016 | CA116: 154.80016 | CB116: 154.80016 | CC116: 154.80016 | CD116: 154.80016 | CE116: 154.80016 | CF116: 154.80016 | CG116: 154.80016 | CH116: 154.80016 | CI116: 154.80016 | CJ116: 154.80016 | CK116: 154.80016 | CL116: 154.80016
B117: 선순위운영비(실측) | C117: [KRWm] | K117: 625.27708 | L117: 625.3895 | M117: 1606.8735 | N117: 624.94431 | O117: 628.0007 | P117: 628.11256 | Q117: 1609.5891 | R117: 627.66959 | S117: 630.77931 | T117: 630.89061 | U117: 1612.3597 | V117: 630.44987 | W117: 626.11403 | X117: 626.22476 | Y117: 1607.6865 | Z117: 625.78625 | AA117: 629.00596 | AB117: 629.11614 | AC117: 1610.5704 | AD117: 628.67985 | AE117: 626.95627 | AF117: 627.06588 | AG117: 1608.5127 | AH117: 626.63182 | AI117: 629.9661 | AJ117: 630.07515 | AK117: 1611.5146 | AL117: 629.64332 | AM117: 633.03666 | AN117: 633.14515 | AO117: 1614.5772 | AP117: 632.71554 | AQ117: 636.16916 | AR117: 636.27709 | AS117: 1617.7017 | AT117: 635.84971 | AU117: 639.36484 | AV117: 639.4722 | AW117: 1620.8894 | AX117: 639.04705 | AY117: 642.62496 | AZ117: 642.73176 | BA117: 1624.1415 | BB117: 642.30883 | BC117: 645.95081 | BD117: 646.05705 | BE117: 1627.4594 | BF117: 645.63634 | BG117: 649.3437 | BH117: 649.44938 | BI117: 1630.8443 | BJ117: 649.0309 | BK117: 652.80498 | BL117: 652.9101 | BM117: 1634.2976 | BN117: 652.49384 | BO117: 656.33602 | BP117: 656.44057 | BQ117: 1637.8207 | BR117: 656.02654 | BS117: 659.9382 | BT117: 660.04219 | BU117: 1641.4149 | BV117: 659.63039 | BW117: 663.61295 | BX117: 663.71638 | BY117: 1645.0816 | BZ117: 663.3068 | CA117: 667.36173 | CB117: 667.46459 | CC117: 1648.8224 | CD117: 667.05724 | CE117: 671.186 | CF117: 671.28831 | CG117: 1652.6387 | CH117: 670.88318 | CI117: 675.0873 | CJ117: 675.18904 | CK117: 1166.532 | CL117: 674.78614
B118: 후순위운영비(실측) | C118: [KRWm] | K118: 375 | L118: 375 | M118: 375 | N118: 375 | O118: 380.625 | P118: 380.625 | Q118: 380.625 | R118: 380.625 | S118: 386.33437 | T118: 386.33437 | U118: 386.33437 | V118: 386.33437 | W118: 392.12939 | X118: 392.12939 | Y118: 392.12939 | Z118: 392.12939 | AA118: 398.01133 | AB118: 398.01133 | AC118: 398.01133 | AD118: 398.01133 | AE118: 403.9815 | AF118: 403.9815 | AG118: 403.9815 | AH118: 403.9815 | AI118: 410.04122 | AJ118: 410.04122 | AK118: 410.04122 | AL118: 410.04122 | AM118: 416.19184 | AN118: 416.19184 | AO118: 416.19184 | AP118: 416.19184 | AQ118: 422.43472 | AR118: 422.43472 | AS118: 422.43472 | AT118: 422.43472 | AU118: 428.77124 | AV118: 428.77124 | AW118: 428.77124 | AX118: 428.77124 | AY118: 435.20281 | AZ118: 435.20281 | BA118: 435.20281 | BB118: 435.20281 | BC118: 441.73085 | BD118: 441.73085 | BE118: 441.73085 | BF118: 441.73085 | BG118: 448.35681 | BH118: 448.35681 | BI118: 448.35681 | BJ118: 448.35681 | BK118: 455.08217 | BL118: 455.08217 | BM118: 455.08217 | BN118: 455.08217 | BO118: 461.9084 | BP118: 461.9084 | BQ118: 461.9084 | BR118: 461.9084 | BS118: 468.83702 | BT118: 468.83702 | BU118: 468.83702 | BV118: 468.83702 | BW118: 475.86958 | BX118: 475.86958 | BY118: 475.86958 | BZ118: 475.86958 | CA118: 483.00762 | CB118: 483.00762 | CC118: 483.00762 | CD118: 483.00762 | CE118: 490.25274 | CF118: 490.25274 | CG118: 490.25274 | CH118: 490.25274 | CI118: 497.60653 | CJ118: 497.60653 | CK118: 497.60653 | CL118: 497.60653
B119: 복구충당부채 전입액(실측) | C119: [KRWm] | K119: 25 | L119: 25 | M119: 25 | N119: 25 | O119: 25 | P119: 25 | Q119: 25 | R119: 25 | S119: 25 | T119: 25 | U119: 25 | V119: 25 | W119: 25 | X119: 25 | Y119: 25 | Z119: 25 | AA119: 25 | AB119: 25 | AC119: 25 | AD119: 25 | AE119: 25 | AF119: 25 | AG119: 25 | AH119: 25 | AI119: 25 | AJ119: 25 | AK119: 25 | AL119: 25 | AM119: 25 | AN119: 25 | AO119: 25 | AP119: 25 | AQ119: 25 | AR119: 25 | AS119: 25 | AT119: 25 | AU119: 25 | AV119: 25 | AW119: 25 | AX119: 25 | AY119: 25 | AZ119: 25 | BA119: 25 | BB119: 25 | BC119: 25 | BD119: 25 | BE119: 25 | BF119: 25 | BG119: 25 | BH119: 25 | BI119: 25 | BJ119: 25 | BK119: 25 | BL119: 25 | BM119: 25 | BN119: 25 | BO119: 25 | BP119: 25 | BQ119: 25 | BR119: 25 | BS119: 25 | BT119: 25 | BU119: 25 | BV119: 25 | BW119: 25 | BX119: 25 | BY119: 25 | BZ119: 25 | CA119: 25 | CB119: 25 | CC119: 25 | CD119: 25 | CE119: 25 | CF119: 25 | CG119: 25 | CH119: 25 | CI119: 25 | CJ119: 25 | CK119: 25 | CL119: 25
B120: 대리은행수수료(실측) | C120: [KRWm] | K120: 0 | L120: 0 | M120: 20 | N120: 0 | O120: 0 | P120: 0 | Q120: 20 | R120: 0 | S120: 0 | T120: 0 | U120: 20 | V120: 0 | W120: 0 | X120: 0 | Y120: 20 | Z120: 0 | AA120: 0 | AB120: 0 | AC120: 20 | AD120: 0 | AE120: 0 | AF120: 0 | AG120: 20 | AH120: 0 | AI120: 0 | AJ120: 0 | AK120: 20 | AL120: 0 | AM120: 0 | AN120: 0 | AO120: 20 | AP120: 0 | AQ120: 0 | AR120: 0 | AS120: 20 | AT120: 0 | AU120: 0 | AV120: 0 | AW120: 20 | AX120: 0 | AY120: 0 | AZ120: 0 | BA120: 20 | BB120: 0 | BC120: 0 | BD120: 0 | BE120: 20 | BF120: 0 | BG120: 0 | BH120: 0 | BI120: 20 | BJ120: 0 | BK120: 0 | BL120: 0 | BM120: 20 | BN120: 0 | BO120: 0 | BP120: 0 | BQ120: 20 | BR120: 0 | BS120: 0 | BT120: 0 | BU120: 20 | BV120: 0 | BW120: 0 | BX120: 0 | BY120: 0 | BZ120: 0 | CA120: 0 | CB120: 0 | CC120: 0 | CD120: 0 | CE120: 0 | CF120: 0 | CG120: 0 | CH120: 0 | CI120: 0 | CJ120: 0 | CK120: 0 | CL120: 0
B121: 기타 비현금 세무손금(실측) | C121: [KRWm] | K121: 328.7542 | L121: 328.7542 | M121: -651.2458 | N121: 328.7542 | O121: 328.7542 | P121: 328.7542 | Q121: -651.2458 | R121: 328.7542 | S121: 328.7542 | T121: 328.7542 | U121: -651.2458 | V121: 328.7542 | W121: 328.7542 | X121: 328.7542 | Y121: -651.2458 | Z121: 328.7542 | AA121: 328.7542 | AB121: 328.7542 | AC121: -651.2458 | AD121: 328.7542 | AE121: 328.7542 | AF121: 328.7542 | AG121: -651.2458 | AH121: 328.7542 | AI121: 328.7542 | AJ121: 328.7542 | AK121: -651.2458 | AL121: 328.7542 | AM121: 328.7542 | AN121: 328.7542 | AO121: -651.2458 | AP121: 328.7542 | AQ121: 328.7542 | AR121: 328.7542 | AS121: -651.2458 | AT121: 328.7542 | AU121: 328.7542 | AV121: 328.7542 | AW121: -651.2458 | AX121: 328.7542 | AY121: 328.7542 | AZ121: 328.7542 | BA121: -651.2458 | BB121: 328.7542 | BC121: 328.7542 | BD121: 328.7542 | BE121: -651.2458 | BF121: 328.7542 | BG121: 328.7542 | BH121: 328.7542 | BI121: -651.2458 | BJ121: 328.7542 | BK121: 328.7542 | BL121: 328.7542 | BM121: -651.2458 | BN121: 328.7542 | BO121: 328.7542 | BP121: 328.7542 | BQ121: -651.2458 | BR121: 328.7542 | BS121: 328.7542 | BT121: 328.7542 | BU121: -651.2458 | BV121: 328.7542 | BW121: 328.7542 | BX121: 328.7542 | BY121: -651.2458 | BZ121: 328.7542 | CA121: 328.7542 | CB121: 328.7542 | CC121: -651.2458 | CD121: 328.7542 | CE121: 328.7542 | CF121: 328.7542 | CG121: -679.16387 | CH121: 245 | CI121: 245 | CJ121: 245 | CK121: -245 | CL121: 245
B122: 현금기준 법인세(실측) | C122: [KRWm] | K122: 0 | L122: 0 | M122: 0 | N122: 0 | O122: 0 | P122: 176.51067 | Q122: 0 | R122: 0 | S122: 0 | T122: 245.55934 | U122: 0 | V122: 0 | W122: 0 | X122: 281.38689 | Y122: 0 | Z122: 0 | AA122: 0 | AB122: 320.49675 | AC122: 0 | AD122: 0 | AE122: 0 | AF122: 360.1629 | AG122: 0 | AH122: 0 | AI122: 0 | AJ122: 459.71817 | AK122: 0 | AL122: 0 | AM122: 0 | AN122: 709.94606 | AO122: 0 | AP122: 0 | AQ122: 0 | AR122: 777.58917 | AS122: 0 | AT122: 0 | AU122: 0 | AV122: 845.10281 | AW122: 0 | AX122: 0 | AY122: 0 | AZ122: 912.4848 | BA122: 0 | BB122: 0 | BC122: 0 | BD122: 979.73289 | BE122: 0 | BF122: 0 | BG122: 0 | BH122: 1046.8448 | BI122: 0 | BJ122: 0 | BK122: 0 | BL122: 1113.8182 | BM122: 0 | BN122: 0 | BO122: 0 | BP122: 1180.6508 | BQ122: 0 | BR122: 0 | BS122: 0 | BT122: 1247.34 | BU122: 0 | BV122: 0 | BW122: 0 | BX122: 1313.8836 | BY122: 0 | BZ122: 0 | CA122: 0 | CB122: 1378.3564 | CC122: 0 | CD122: 0 | CE122: 0 | CF122: 1365.2668 | CG122: 0 | CH122: 0 | CI122: 0 | CJ122: 1374.5602 | CK122: 0 | CL122: 672.81083
B123: DSRA FCFE 조정(실측) | C123: [KRWm] | K123: -2.5465852e-11 | L123: -2000 | M123: 0 | N123: 0 | O123: 0 | P123: -116.67031 | Q123: -84.54375 | R123: 52.325 | S123: 52.325 | T123: 52.325 | U123: 52.325 | V123: 52.325 | W123: -82.675 | X123: -80.80625 | Y123: 56.0625 | Z123: 56.0625 | AA123: 56.0625 | AB123: 56.0625 | AC123: -28.3125 | AD123: -27.144531 | AE123: 58.398437 | AF123: 58.398437 | AG123: 58.398437 | AH123: 58.398437 | AI123: 58.398437 | AJ123: 58.398437 | AK123: 58.398437 | AL123: 58.398437 | AM123: 58.398437 | AN123: 58.398437 | AO123: 58.398437 | AP123: 58.398437 | AQ123: 58.398437 | AR123: 58.398437 | AS123: 58.398438 | AT123: 58.398438 | AU123: 58.398438 | AV123: 58.398438 | AW123: 58.398438 | AX123: 58.398438 | AY123: 58.398438 | AZ123: 58.398438 | BA123: 58.398438 | BB123: 58.398438 | BC123: 58.398438 | BD123: 58.398438 | BE123: 58.398438 | BF123: 58.398438 | BG123: 58.398438 | BH123: 58.398438 | BI123: 58.398438 | BJ123: 58.398438 | BK123: 58.398438 | BL123: 58.398438 | BM123: 58.398438 | BN123: 58.398438 | BO123: 58.398438 | BP123: 58.398438 | BQ123: 58.398438 | BR123: 58.398438 | BS123: 58.398438 | BT123: 58.398438 | BU123: 58.398438 | BV123: 58.398438 | BW123: 58.398438 | BX123: 2167.7734 | BY123: 2138.5742 | BZ123: 0 | CA123: 0 | CB123: 0 | CC123: 0 | CD123: 0 | CE123: 0 | CF123: 0 | CG123: 0 | CH123: 0 | CI123: 0 | CJ123: 0 | CK123: 0 | CL123: 0
B124: 운전자본 증감(실측) | C124: [KRWm] | K124: -1666.4365 | L124: -35.501416 | M124: -468.61869 | N124: 609.20429 | O124: -96.752008 | P124: -35.323909 | Q124: -466.27559 | R124: 606.15827 | S124: -96.226587 | T124: -35.146402 | U124: -463.9325 | V124: 603.11225 | W124: -95.701166 | X124: -34.968894 | Y124: -461.58941 | Z124: 600.06623 | AA124: -95.175745 | AB124: -34.791387 | AC124: -459.24631 | AD124: 597.02021 | AE124: -94.650324 | AF124: -34.61388 | AG124: -456.90322 | AH124: 593.97419 | AI124: -94.124904 | AJ124: -34.436373 | AK124: -454.56013 | AL124: 590.92817 | AM124: -93.599483 | AN124: -34.258866 | AO124: -452.21703 | AP124: 587.88214 | AQ124: -93.074062 | AR124: -34.081359 | AS124: -449.87394 | AT124: 584.83612 | AU124: -92.548641 | AV124: -33.903852 | AW124: -447.53085 | AX124: 581.7901 | AY124: -92.02322 | AZ124: -33.726345 | BA124: -445.18775 | BB124: 578.74408 | BC124: -91.497799 | BD124: -33.548838 | BE124: -442.84466 | BF124: 575.69806 | BG124: -90.972378 | BH124: -33.371331 | BI124: -440.50157 | BJ124: 572.65204 | BK124: -90.446957 | BL124: -33.193824 | BM124: -438.15847 | BN124: 569.60601 | BO124: -89.921536 | BP124: -33.016317 | BQ124: -435.81538 | BR124: 566.55999 | BS124: -89.396115 | BT124: -32.83881 | BU124: -433.47229 | BV124: 563.51397 | BW124: -88.870694 | BX124: -32.661302 | BY124: -431.12919 | BZ124: 560.46795 | CA124: -88.345273 | CB124: -32.483795 | CC124: -428.7861 | CD124: 557.42193 | CE124: -87.819852 | CF124: -32.306288 | CG124: -426.44301 | CH124: 554.37591 | CI124: -87.294431 | CJ124: -32.128781 | CK124: -424.09991 | CL124: 1964.3537
B126: ※ 노란색 셀 = 화면에서 직접 key-in했거나("예시 불러오기"의 실측치 포함) 그에 준하는 입력값(재무모델링 관례). 세금·최저한세·배당가능이익 캡 등 IS(Q)/CF(Q)의 계산 결과는 반복계산·조건부 누적 로직이 얽혀 있어 여기 대상이 아니며 값(baked) 기준입니다.

Sheet Funding
A1: 당진 태양광발전
A2: 자금조달 — 자본금 + 5개 트랜치
B4: 트랜치 조건
B6: 트랜치 | C6: 금액[KRWm] | D6: 투입순서 | E6: 건설금리 | F6: 운영금리 | G6: 거치(yr) | H6: 상환(yr) | I6: 방식 | J6: 상환개시
B7: 자본금 | C7: ='입력값'!C9*100
B8: 선순위A | C8: ='입력값'!C58*100 | E8: ='입력값'!D58 | F8: ='입력값'!E58 | G8: ='입력값'!F58 | H8: ='입력값'!G58 | I8: ='입력값'!H58 | J8: 2026-09-30
B9: 선순위B | C9: ='입력값'!C59*100 | E9: ='입력값'!D59 | F9: ='입력값'!E59 | G9: ='입력값'!F59 | H9: ='입력값'!G59 | I9: ='입력값'!H59 | J9: 2026-09-30
B10: 선순위C | C10: ='입력값'!C60*100 | E10: ='입력값'!D60 | F10: ='입력값'!E60 | G10: ='입력값'!F60 | H10: ='입력값'!G60 | I10: ='입력값'!H60 | J10: 2026-09-30
B11: 선순위D | C11: ='입력값'!C61*100 | E11: ='입력값'!D61 | F11: ='입력값'!E61 | G11: ='입력값'!F61 | H11: ='입력값'!G61 | I11: ='입력값'!H61 | J11: -
B12: 후순위 | C12: ='입력값'!C62*100 | E12: ='입력값'!D62 | F12: ='입력값'!E62 | G12: ='입력값'!F62 | H12: ='입력값'!G62 | I12: ='입력값'!H62 | J12: -
B13: 차입금 합계 | C13: =C8+C9+C10+C11+C12
B15: 건설이자(IDC)
B17: IDC 합계[KRWm] | C17: ='Debt'!D15
B18: 총투자비(TIC)[KRWm] | C18: ='입력값'!C8*100+'Debt'!D15
B19: 총사업비(건설이자 제외)[KRWm] | C19: ='입력값'!C8*100
B21: 총사업비 세부내역
B23: 항목 | C23: 금액[KRWm]
B24: ='입력값'!B82
B25: ='입력값'!B83
B26: ='입력값'!B84
B27: ='입력값'!B85
B28: ='입력값'!B86
B29: ='입력값'!B87
B30: ='입력값'!B88
B31: ='입력값'!B89
B32: ='입력값'!B90
B33: ='입력값'!B91
B34: ='입력값'!B92
B35: ='입력값'!B93
B36: 합계 | C36: ='입력값'!C8*100

Sheet Debt
A1: 당진 태양광발전
A2: 차입금 상환 스케줄 — 건설기간 인출 + 트랜치별 상환
B4: 건설기간 자금조달 (인출·건설이자)
B6: 구 분 | C6: unit | D6: 합 계 | E6: 2024-06-30 | F6: 2024-09-30 | G6: 2024-12-31 | H6: 2025-03-31 | I6: 2025-06-30 | J6: 2025-09-30 | K6: 2025-12-31 | L6: 2026-03-31 | M6: 2026-06-30 | N6: 2026-09-30 | O6: 2026-12-31 | P6: 2027-03-31 | Q6: 2027-06-30 | R6: 2027-09-30 | S6: 2027-12-31 | T6: 2028-03-31 | U6: 2028-06-30 | V6: 2028-09-30 | W6: 2028-12-31 | X6: 2029-03-31 | Y6: 2029-06-30 | Z6: 2029-09-30 | AA6: 2029-12-31 | AB6: 2030-03-31 | AC6: 2030-06-30 | AD6: 2030-09-30 | AE6: 2030-12-31 | AF6: 2031-03-31 | AG6: 2031-06-30 | AH6: 2031-09-30 | AI6: 2031-12-31 | AJ6: 2032-03-31 | AK6: 2032-06-30 | AL6: 2032-09-30 | AM6: 2032-12-31 | AN6: 2033-03-31 | AO6: 2033-06-30 | AP6: 2033-09-30 | AQ6: 2033-12-31 | AR6: 2034-03-31 | AS6: 2034-06-30 | AT6: 2034-09-30 | AU6: 2034-12-31 | AV6: 2035-03-31 | AW6: 2035-06-30 | AX6: 2035-09-30 | AY6: 2035-12-31 | AZ6: 2036-03-31 | BA6: 2036-06-30 | BB6: 2036-09-30 | BC6: 2036-12-31 | BD6: 2037-03-31 | BE6: 2037-06-30 | BF6: 2037-09-30 | BG6: 2037-12-31 | BH6: 2038-03-31 | BI6: 2038-06-30 | BJ6: 2038-09-30 | BK6: 2038-12-31 | BL6: 2039-03-31 | BM6: 2039-06-30 | BN6: 2039-09-30 | BO6: 2039-12-31 | BP6: 2040-03-31 | BQ6: 2040-06-30 | BR6: 2040-09-30 | BS6: 2040-12-31 | BT6: 2041-03-31 | BU6: 2041-06-30 | BV6: 2041-09-30 | BW6: 2041-12-31 | BX6: 2042-03-31 | BY6: 2042-06-30 | BZ6: 2042-09-30 | CA6: 2042-12-31 | CB6: 2043-03-31 | CC6: 2043-06-30 | CD6: 2043-09-30 | CE6: 2043-12-31 | CF6: 2044-03-31 | CG6: 2044-06-30 | CH6: 2044-09-30 | CI6: 2044-12-31 | CJ6: 2045-03-31 | CK6: 2045-06-30 | CL6: 2045-09-30
B8: 공사비 지출 | C8: [KRWm] | D8: =SUM(E8:CL8) | E8: ='입력값'!E69*'입력값'!C8*100 | F8: ='입력값'!F69*'입력값'!C8*100 | G8: ='입력값'!G69*'입력값'!C8*100 | H8: ='입력값'!H69*'입력값'!C8*100 | I8: ='입력값'!I69*'입력값'!C8*100 | J8: ='입력값'!J69*'입력값'!C8*100 | K8: ='입력값'!K69*'입력값'!C8*100 | L8: ='입력값'!L69*'입력값'!C8*100 | M8: ='입력값'!M69*'입력값'!C8*100 | N8: ='입력값'!N69*'입력값'!C8*100 | O8: ='입력값'!O69*'입력값'!C8*100 | P8: ='입력값'!P69*'입력값'!C8*100 | Q8: ='입력값'!Q69*'입력값'!C8*100 | R8: ='입력값'!R69*'입력값'!C8*100 | S8: ='입력값'!S69*'입력값'!C8*100 | T8: ='입력값'!T69*'입력값'!C8*100 | U8: ='입력값'!U69*'입력값'!C8*100 | V8: ='입력값'!V69*'입력값'!C8*100 | W8: ='입력값'!W69*'입력값'!C8*100 | X8: ='입력값'!X69*'입력값'!C8*100 | Y8: ='입력값'!Y69*'입력값'!C8*100 | Z8: ='입력값'!Z69*'입력값'!C8*100 | AA8: ='입력값'!AA69*'입력값'!C8*100 | AB8: ='입력값'!AB69*'입력값'!C8*100 | AC8: ='입력값'!AC69*'입력값'!C8*100 | AD8: ='입력값'!AD69*'입력값'!C8*100 | AE8: ='입력값'!AE69*'입력값'!C8*100 | AF8: ='입력값'!AF69*'입력값'!C8*100 | AG8: ='입력값'!AG69*'입력값'!C8*100 | AH8: ='입력값'!AH69*'입력값'!C8*100 | AI8: ='입력값'!AI69*'입력값'!C8*100 | AJ8: ='입력값'!AJ69*'입력값'!C8*100 | AK8: ='입력값'!AK69*'입력값'!C8*100 | AL8: ='입력값'!AL69*'입력값'!C8*100 | AM8: ='입력값'!AM69*'입력값'!C8*100 | AN8: ='입력값'!AN69*'입력값'!C8*100 | AO8: ='입력값'!AO69*'입력값'!C8*100 | AP8: ='입력값'!AP69*'입력값'!C8*100 | AQ8: ='입력값'!AQ69*'입력값'!C8*100 | AR8: ='입력값'!AR69*'입력값'!C8*100 | AS8: ='입력값'!AS69*'입력값'!C8*100 | AT8: ='입력값'!AT69*'입력값'!C8*100 | AU8: ='입력값'!AU69*'입력값'!C8*100 | AV8: ='입력값'!AV69*'입력값'!C8*100 | AW8: ='입력값'!AW69*'입력값'!C8*100 | AX8: ='입력값'!AX69*'입력값'!C8*100 | AY8: ='입력값'!AY69*'입력값'!C8*100 | AZ8: ='입력값'!AZ69*'입력값'!C8*100 | BA8: ='입력값'!BA69*'입력값'!C8*100 | BB8: ='입력값'!BB69*'입력값'!C8*100 | BC8: ='입력값'!BC69*'입력값'!C8*100 | BD8: ='입력값'!BD69*'입력값'!C8*100 | BE8: ='입력값'!BE69*'입력값'!C8*100 | BF8: ='입력값'!BF69*'입력값'!C8*100 | BG8: ='입력값'!BG69*'입력값'!C8*100 | BH8: ='입력값'!BH69*'입력값'!C8*100 | BI8: ='입력값'!BI69*'입력값'!C8*100 | BJ8: ='입력값'!BJ69*'입력값'!C8*100 | BK8: ='입력값'!BK69*'입력값'!C8*100 | BL8: ='입력값'!BL69*'입력값'!C8*100 | BM8: ='입력값'!BM69*'입력값'!C8*100 | BN8: ='입력값'!BN69*'입력값'!C8*100 | BO8: ='입력값'!BO69*'입력값'!C8*100 | BP8: ='입력값'!BP69*'입력값'!C8*100 | BQ8: ='입력값'!BQ69*'입력값'!C8*100 | BR8: ='입력값'!BR69*'입력값'!C8*100 | BS8: ='입력값'!BS69*'입력값'!C8*100 | BT8: ='입력값'!BT69*'입력값'!C8*100 | BU8: ='입력값'!BU69*'입력값'!C8*100 | BV8: ='입력값'!BV69*'입력값'!C8*100 | BW8: ='입력값'!BW69*'입력값'!C8*100 | BX8: ='입력값'!BX69*'입력값'!C8*100 | BY8: ='입력값'!BY69*'입력값'!C8*100 | BZ8: ='입력값'!BZ69*'입력값'!C8*100 | CA8: ='입력값'!CA69*'입력값'!C8*100 | CB8: ='입력값'!CB69*'입력값'!C8*100 | CC8: ='입력값'!CC69*'입력값'!C8*100 | CD8: ='입력값'!CD69*'입력값'!C8*100 | CE8: ='입력값'!CE69*'입력값'!C8*100 | CF8: ='입력값'!CF69*'입력값'!C8*100 | CG8: ='입력값'!CG69*'입력값'!C8*100 | CH8: ='입력값'!CH69*'입력값'!C8*100 | CI8: ='입력값'!CI69*'입력값'!C8*100 | CJ8: ='입력값'!CJ69*'입력값'!C8*100 | CK8: ='입력값'!CK69*'입력값'!C8*100 | CL8: ='입력값'!CL69*'입력값'!C8*100
B9: DSRA 적립 | C9: [KRWm] | D9: =SUM(E9:CL9) | E9: 0 | F9: 0 | G9: 0 | H9: 0 | I9: 0 | J9: ='입력값'!C20*100 | K9: 0 | L9: 0 | M9: 0 | N9: 0 | O9: 0 | P9: 0 | Q9: 0 | R9: 0 | S9: 0 | T9: 0 | U9: 0 | V9: 0 | W9: 0 | X9: 0 | Y9: 0 | Z9: 0 | AA9: 0 | AB9: 0 | AC9: 0 | AD9: 0 | AE9: 0 | AF9: 0 | AG9: 0 | AH9: 0 | AI9: 0 | AJ9: 0 | AK9: 0 | AL9: 0 | AM9: 0 | AN9: 0 | AO9: 0 | AP9: 0 | AQ9: 0 | AR9: 0 | AS9: 0 | AT9: 0 | AU9: 0 | AV9: 0 | AW9: 0 | AX9: 0 | AY9: 0 | AZ9: 0 | BA9: 0 | BB9: 0 | BC9: 0 | BD9: 0 | BE9: 0 | BF9: 0 | BG9: 0 | BH9: 0 | BI9: 0 | BJ9: 0 | BK9: 0 | BL9: 0 | BM9: 0 | BN9: 0 | BO9: 0 | BP9: 0 | BQ9: 0 | BR9: 0 | BS9: 0 | BT9: 0 | BU9: 0 | BV9: 0 | BW9: 0 | BX9: 0 | BY9: 0 | BZ9: 0 | CA9: 0 | CB9: 0 | CC9: 0 | CD9: 0 | CE9: 0 | CF9: 0 | CG9: 0 | CH9: 0 | CI9: 0 | CJ9: 0 | CK9: 0 | CL9: 0
B10: 선순위A 건설이자 | C10: [KRWm] | D10: =SUM(E10:CL10) | E10: 0 | F10: =E18*'입력값'!D58/4 | G10: =F18*'입력값'!D58/4 | H10: =G18*'입력값'!D58/4 | I10: =H18*'입력값'!D58/4 | J10: =I18*'입력값'!D58/4 | K10: 0 | L10: 0 | M10: 0 | N10: 0 | O10: 0 | P10: 0 | Q10: 0 | R10: 0 | S10: 0 | T10: 0 | U10: 0 | V10: 0 | W10: 0 | X10: 0 | Y10: 0 | Z10: 0 | AA10: 0 | AB10: 0 | AC10: 0 | AD10: 0 | AE10: 0 | AF10: 0 | AG10: 0 | AH10: 0 | AI10: 0 | AJ10: 0 | AK10: 0 | AL10: 0 | AM10: 0 | AN10: 0 | AO10: 0 | AP10: 0 | AQ10: 0 | AR10: 0 | AS10: 0 | AT10: 0 | AU10: 0 | AV10: 0 | AW10: 0 | AX10: 0 | AY10: 0 | AZ10: 0 | BA10: 0 | BB10: 0 | BC10: 0 | BD10: 0 | BE10: 0 | BF10: 0 | BG10: 0 | BH10: 0 | BI10: 0 | BJ10: 0 | BK10: 0 | BL10: 0 | BM10: 0 | BN10: 0 | BO10: 0 | BP10: 0 | BQ10: 0 | BR10: 0 | BS10: 0 | BT10: 0 | BU10: 0 | BV10: 0 | BW10: 0 | BX10: 0 | BY10: 0 | BZ10: 0 | CA10: 0 | CB10: 0 | CC10: 0 | CD10: 0 | CE10: 0 | CF10: 0 | CG10: 0 | CH10: 0 | CI10: 0 | CJ10: 0 | CK10: 0 | CL10: 0
B11: 선순위B 건설이자 | C11: [KRWm] | D11: =SUM(E11:CL11) | E11: 0 | F11: =E19*'입력값'!D59/4 | G11: =F19*'입력값'!D59/4 | H11: =G19*'입력값'!D59/4 | I11: =H19*'입력값'!D59/4 | J11: =I19*'입력값'!D59/4 | K11: 0 | L11: 0 | M11: 0 | N11: 0 | O11: 0 | P11: 0 | Q11: 0 | R11: 0 | S11: 0 | T11: 0 | U11: 0 | V11: 0 | W11: 0 | X11: 0 | Y11: 0 | Z11: 0 | AA11: 0 | AB11: 0 | AC11: 0 | AD11: 0 | AE11: 0 | AF11: 0 | AG11: 0 | AH11: 0 | AI11: 0 | AJ11: 0 | AK11: 0 | AL11: 0 | AM11: 0 | AN11: 0 | AO11: 0 | AP11: 0 | AQ11: 0 | AR11: 0 | AS11: 0 | AT11: 0 | AU11: 0 | AV11: 0 | AW11: 0 | AX11: 0 | AY11: 0 | AZ11: 0 | BA11: 0 | BB11: 0 | BC11: 0 | BD11: 0 | BE11: 0 | BF11: 0 | BG11: 0 | BH11: 0 | BI11: 0 | BJ11: 0 | BK11: 0 | BL11: 0 | BM11: 0 | BN11: 0 | BO11: 0 | BP11: 0 | BQ11: 0 | BR11: 0 | BS11: 0 | BT11: 0 | BU11: 0 | BV11: 0 | BW11: 0 | BX11: 0 | BY11: 0 | BZ11: 0 | CA11: 0 | CB11: 0 | CC11: 0 | CD11: 0 | CE11: 0 | CF11: 0 | CG11: 0 | CH11: 0 | CI11: 0 | CJ11: 0 | CK11: 0 | CL11: 0
B12: 선순위C 건설이자 | C12: [KRWm] | D12: =SUM(E12:CL12) | E12: 0 | F12: =E20*'입력값'!D60/4 | G12: =F20*'입력값'!D60/4 | H12: =G20*'입력값'!D60/4 | I12: =H20*'입력값'!D60/4 | J12: =I20*'입력값'!D60/4 | K12: 0 | L12: 0 | M12: 0 | N12: 0 | O12: 0 | P12: 0 | Q12: 0 | R12: 0 | S12: 0 | T12: 0 | U12: 0 | V12: 0 | W12: 0 | X12: 0 | Y12: 0 | Z12: 0 | AA12: 0 | AB12: 0 | AC12: 0 | AD12: 0 | AE12: 0 | AF12: 0 | AG12: 0 | AH12: 0 | AI12: 0 | AJ12: 0 | AK12: 0 | AL12: 0 | AM12: 0 | AN12: 0 | AO12: 0 | AP12: 0 | AQ12: 0 | AR12: 0 | AS12: 0 | AT12: 0 | AU12: 0 | AV12: 0 | AW12: 0 | AX12: 0 | AY12: 0 | AZ12: 0 | BA12: 0 | BB12: 0 | BC12: 0 | BD12: 0 | BE12: 0 | BF12: 0 | BG12: 0 | BH12: 0 | BI12: 0 | BJ12: 0 | BK12: 0 | BL12: 0 | BM12: 0 | BN12: 0 | BO12: 0 | BP12: 0 | BQ12: 0 | BR12: 0 | BS12: 0 | BT12: 0 | BU12: 0 | BV12: 0 | BW12: 0 | BX12: 0 | BY12: 0 | BZ12: 0 | CA12: 0 | CB12: 0 | CC12: 0 | CD12: 0 | CE12: 0 | CF12: 0 | CG12: 0 | CH12: 0 | CI12: 0 | CJ12: 0 | CK12: 0 | CL12: 0
B13: 선순위D 건설이자 | C13: [KRWm] | D13: =SUM(E13:CL13) | E13: 0 | F13: =E21*'입력값'!D61/4 | G13: =F21*'입력값'!D61/4 | H13: =G21*'입력값'!D61/4 | I13: =H21*'입력값'!D61/4 | J13: =I21*'입력값'!D61/4 | K13: 0 | L13: 0 | M13: 0 | N13: 0 | O13: 0 | P13: 0 | Q13: 0 | R13: 0 | S13: 0 | T13: 0 | U13: 0 | V13: 0 | W13: 0 | X13: 0 | Y13: 0 | Z13: 0 | AA13: 0 | AB13: 0 | AC13: 0 | AD13: 0 | AE13: 0 | AF13: 0 | AG13: 0 | AH13: 0 | AI13: 0 | AJ13: 0 | AK13: 0 | AL13: 0 | AM13: 0 | AN13: 0 | AO13: 0 | AP13: 0 | AQ13: 0 | AR13: 0 | AS13: 0 | AT13: 0 | AU13: 0 | AV13: 0 | AW13: 0 | AX13: 0 | AY13: 0 | AZ13: 0 | BA13: 0 | BB13: 0 | BC13: 0 | BD13: 0 | BE13: 0 | BF13: 0 | BG13: 0 | BH13: 0 | BI13: 0 | BJ13: 0 | BK13: 0 | BL13: 0 | BM13: 0 | BN13: 0 | BO13: 0 | BP13: 0 | BQ13: 0 | BR13: 0 | BS13: 0 | BT13: 0 | BU13: 0 | BV13: 0 | BW13: 0 | BX13: 0 | BY13: 0 | BZ13: 0 | CA13: 0 | CB13: 0 | CC13: 0 | CD13: 0 | CE13: 0 | CF13: 0 | CG13: 0 | CH13: 0 | CI13: 0 | CJ13: 0 | CK13: 0 | CL13: 0
B14: 후순위 건설이자 | C14: [KRWm] | D14: =SUM(E14:CL14) | E14: 0 | F14: =E22*'입력값'!D62/4 | G14: =F22*'입력값'!D62/4 | H14: =G22*'입력값'!D62/4 | I14: =H22*'입력값'!D62/4 | J14: =I22*'입력값'!D62/4 | K14: 0 | L14: 0 | M14: 0 | N14: 0 | O14: 0 | P14: 0 | Q14: 0 | R14: 0 | S14: 0 | T14: 0 | U14: 0 | V14: 0 | W14: 0 | X14: 0 | Y14: 0 | Z14: 0 | AA14: 0 | AB14: 0 | AC14: 0 | AD14: 0 | AE14: 0 | AF14: 0 | AG14: 0 | AH14: 0 | AI14: 0 | AJ14: 0 | AK14: 0 | AL14: 0 | AM14: 0 | AN14: 0 | AO14: 0 | AP14: 0 | AQ14: 0 | AR14: 0 | AS14: 0 | AT14: 0 | AU14: 0 | AV14: 0 | AW14: 0 | AX14: 0 | AY14: 0 | AZ14: 0 | BA14: 0 | BB14: 0 | BC14: 0 | BD14: 0 | BE14: 0 | BF14: 0 | BG14: 0 | BH14: 0 | BI14: 0 | BJ14: 0 | BK14: 0 | BL14: 0 | BM14: 0 | BN14: 0 | BO14: 0 | BP14: 0 | BQ14: 0 | BR14: 0 | BS14: 0 | BT14: 0 | BU14: 0 | BV14: 0 | BW14: 0 | BX14: 0 | BY14: 0 | BZ14: 0 | CA14: 0 | CB14: 0 | CC14: 0 | CD14: 0 | CE14: 0 | CF14: 0 | CG14: 0 | CH14: 0 | CI14: 0 | CJ14: 0 | CK14: 0 | CL14: 0
B15: 건설이자 합계(당기) | C15: [KRWm] | D15: =SUM(E15:CL15) | E15: =E10+E11+E12+E13+E14 | F15: =F10+F11+F12+F13+F14 | G15: =G10+G11+G12+G13+G14 | H15: =H10+H11+H12+H13+H14 | I15: =I10+I11+I12+I13+I14 | J15: =J10+J11+J12+J13+J14 | K15: =K10+K11+K12+K13+K14 | L15: =L10+L11+L12+L13+L14 | ... CL15: =CL10+CL11+CL12+CL13+CL14
B16: 누적 소요액 | C16: [KRWm] | E16: =E8+E9+E15 | F16: =E16+F8+F9+F15 | G16: =F16+G8+G9+G15 | H16: =G16+H8+H9+H15 | I16: =H16+I8+I9+I15 | J16: =I16+J8+J9+J15 | K16: =J16+K8+K9+K15 | L16: =K16+L8+L9+L15 | M16: =L16+M8+M9+M15 | ... CL16: =CK16+CL8+CL9+CL15
B17: 자본금 누적인출 | C17: [KRWm] | E17: =MIN(MAX(E16-(0),0),'입력값'!C9*100+'입력값'!C62*100)*('입력값'!C9*100)/IF(('입력값'!C9*100+'입력값'!C62*100)=0,1,'입력값'!C9*100+'입력값'!C62*100) | F17: =MIN(MAX(F16-(0),0),'입력값'!C9*100+'입력값'!C62*100)*('입력값'!C9*100)/IF(('입력값'!C9*100+'입력값'!C62*100)=0,1,'입력값'!C9*100+'입력값'!C62*100) | G17: =MIN(MAX(G16-(0),0),'입력값'!C9*100+'입력값'!C62*100)*('입력값'!C9*100)/IF(('입력값'!C9*100+'입력값'!C62*100)=0,1,'입력값'!C9*100+'입력값'!C62*100) | H17: =MIN(MAX(H16-(0),0),'입력값'!C9*100+'입력값'!C62*100)*('입력값'!C9*100)/IF(('입력값'!C9*100+'입력값'!C62*100)=0,1,'입력값'!C9*100+'입력값'!C62*100) | I17: =MIN(MAX(I16-(0),0),'입력값'!C9*100+'입력값'!C62*100)*('입력값'!C9*100)/IF(('입력값'!C9*100+'입력값'!C62*100)=0,1,'입력값'!C9*100+'입력값'!C62*100) | J17: =MIN(MAX(J16-(0),0),'입력값'!C9*100+'입력값'!C62*100)*('입력값'!C9*100)/IF(('입력값'!C9*100+'입력값'!C62*100)=0,1,'입력값'!C9*100+'입력값'!C62*100) | K17: =MIN(MAX(K16-(0),0),'입력값'!C9*100+'입력값'!C62*100)*('입력값'!C9*100)/IF(('입력값'!C9*100+'입력값'!C62*100)=0,1,'입력값'!C9*100+'입력값'!C62*100) | L17: =MIN(MAX(L16-(0),0),'입력값'!C9*100+'입력값'!C62*100)*('입력값'!C9*100)/IF(('입력값'!C9*100+'입력값'!C62*100)=0,1,'입력값'!C9*100+'입력값'!C62*100) | M17: =MIN(MAX(M16-(0),0),'입력값'!C9*100+'입력값'!C62*100)*('입력값'!C9*100)/IF(('입력값'!C9*100+'입력값'!C62*100)=0,1,'입력값'!C9*100+'입력값'!C62*100) | N17: =MIN(MAX(N16-(0),0),'입력값'!C9*100+'입력값'!C62*100)*('입력값'!C9*100)/IF(('입력값'!C9*100+'입력값'!C62*100)=0,1,'입력값'!C9*100+'입력값'!C62*100) | O17: =MIN(MAX(O16-(0),0),'입력값'!C9*100+'입력값'!C62*100)*('입력값'!C9*100)/IF(('입력값'!C9*100+'입력값'!C62*100)=0,1,'입력값'!C9*100+'입력값'!C62*100) | P17: =MIN(MAX(P16-(0),0),'입력값'!C9*100+'입력값'!C62*100)*('입력값'!C9*100)/IF(('입력값'!C9*100+'입력값'!C62*100)=0,1,'입력값'!C9*100+'입력값'!C62*100) | Q17: =MIN(MAX(Q16-(0),0),'입력값'!C9*100+'입력값'!C62*100)*('입력값'!C9*100)/IF(('입력값'!C9*100+'입력값'!C62*100)=0,1,'입력값'!C9*100+'입력값'!C62*100) | R17: =MIN(MAX(R16-(0),0),'입력값'!C9*100+'입력값'!C62*100)*('입력값'!C9*100)/IF(('입력값'!C9*100+'입력값'!C62*100)=0,1,'입력값'!C9*100+'입력값'!C62*100) | S17: =MIN(MAX(S16-(0),0),'입력값'!C9*100+'입력값'!C62*100)*('입력값'!C9*100)/IF(('입력값'!C9*100+'입력값'!C62*100)=0,1,'입력값'!C9*100+'입력값'!C62*100) | T17: =MIN(MAX(T16-(0),0),'입력값'!C9*100+'입력값'!C62*100)*('입력값'!C9*100)/IF(('입력값'!C9*100+'입력값'!C62*100)=0,1,'입력값'!C9*100+'입력값'!C62*100) | U17: =MIN(MAX(U16-(0),0),'입력값'!C9*100+'입력값'!C62*100)*('입력값'!C9*100)/IF(('입력값'!C9*100+'입력값'!C62*100)=0,1,'입력값'!C9*100+'입력값'!C62*100) | V17: =MIN(MAX(V16-(0),0),'입력값'!C9*100+'입력값'!C62*100)*('입력값'!C9*100)/IF(('입력값'!C9*100+'입력값'!C62*100)=0,1,'입력값'!C9*100+'입력값'!C62*100) | W17: =MIN(MAX(W16-(0),0),'입력값'!C9*100+'입력값'!C62*100)*('입력값'!C9*100)/IF(('입력값'!C9*100+'입력값'!C62*100)=0,1,'입력값'!C9*100+'입력값'!C62*100) | X17: =MIN(MAX(X16-(0),0),'입력값'!C9*100+'입력값'!C62*100)*('입력값'!C9*100)/IF(('입력값'!C9*100+'입력값'!C62*100)=0,1,'입력값'!C9*100+'입력값'!C62*100) | Y17: =MIN(MAX(Y16-(0),0),'입력값'!C9*100+'입력값'!C62*100)*('입력값'!C9*100)/IF(('입력값'!C9*100+'입력값'!C62*100)=0,1,'입력값'!C9*100+'입력값'!C62*100) | Z17: =MIN(MAX(Z16-(0),0),'입력값'!C9*100+'입력값'!C62*100)*('입력값'!C9*100)/IF(('입력값'!C9*100+'입력값'!C62*100)=0,1,'입력값'!C9*100+'입력값'!C62*100) | AA17: =MIN(MAX(AA16-(0),0),'입력값'!C9*100+'입력값'!C62*100)*('입력값'!C9*100)/IF(('입력값'!C9*100+'입력값'!C62*100)=0,1,'입력값'!C9*100+'입력값'!C62*100) | AB17: =MIN(MAX(AB16-(0),0),'입력값'!C9*100+'입력값'!C62*100)*('입력값'!C9*100)/IF(('입력값'!C9*100+'입력값'!C62*100)=0,1,'입력값'!C9*100+'입력값'!C62*100) | AC17: =MIN(MAX(AC16-(0),0),'입력값'!C9*100+'입력값'!C62*100)*('입력값'!C9*100)/IF(('입력값'!C9*100+'입력값'!C62*100)=0,1,'입력값'!C9*100+'입력값'!C62*100) | AD17: =MIN(MAX(AD16-(0),0),'입력값'!C9*100+'입력값'!C62*100)*('입력값'!C9*100)/IF(('입력값'!C9*100+'입력값'!C62*100)=0,1,'입력값'!C9*100+'입력값'!C62*100) | AE17: =MIN(MAX(AE16-(0),0),'입력값'!C9*100+'입력값'!C62*100)*('입력값'!C9*100)/IF(('입력값'!C9*100+'입력값'!C62*100)=0,1,'입력값'!C9*100+'입력값'!C62*100) | AF17: =MIN(MAX(AF16-(0),0),'입력값'!C9*100+'입력값'!C62*100)*('입력값'!C9*100)/IF(('입력값'!C9*100+'입력값'!C62*100)=0,1,'입력값'!C9*100+'입력값'!C62*100) | AG17: =MIN(MAX(AG16-(0),0),'입력값'!C9*100+'입력값'!C62*100)*('입력값'!C9*100)/IF(('입력값'!C9*100+'입력값'!C62*100)=0,1,'입력값'!C9*100+'입력값'!C62*100) | AH17: =MIN(MAX(AH16-(0),0),'입력값'!C9*100+'입력값'!C62*100)*('입력값'!C9*100)/IF(('입력값'!C9*100+'입력값'!C62*100)=0,1,'입력값'!C9*100+'입력값'!C62*100) | AI17: =MIN(MAX(AI16-(0),0),'입력값'!C9*100+'입력값'!C62*100)*('입력값'!C9*100)/IF(('입력값'!C9*100+'입력값'!C62*100)=0,1,'입력값'!C9*100+'입력값'!C62*100) | AJ17: =MIN(MAX(AJ16-(0),0),'입력값'!C9*100+'입력값'!C62*100)*('입력값'!C9*100)/IF(('입력값'!C9*100+'입력값'!C62*100)=0,1,'입력값'!C9*100+'입력값'!C62*100) | AK17: =MIN(MAX(AK16-(0),0),'입력값'!C9*100+'입력값'!C62*100)*('입력값'!C9*100)/IF(('입력값'!C9*100+'입력값'!C62*100)=0,1,'입력값'!C9*100+'입력값'!C62*100) | AL17: =MIN(MAX(AL16-(0),0),'입력값'!C9*100+'입력값'!C62*100)*('입력값'!C9*100)/IF(('입력값'!C9*100+'입력값'!C62*100)=0,1,'입력값'!C9*100+'입력값'!C62*100) | AM17: =MIN(MAX(AM16-(0),0),'입력값'!C9*100+'입력값'!C62*100)*('입력값'!C9*100)/IF(('입력값'!C9*100+'입력값'!C62*100)=0,1,'입력값'!C9*100+'입력값'!C62*100) | AN17: =MIN(MAX(AN16-(0),0),'입력값'!C9*100+'입력값'!C62*100)*('입력값'!C9*100)/IF(('입력값'!C9*100+'입력값'!C62*100)=0,1,'입력값'!C9*100+'입력값'!C62*100) | AO17: =MIN(MAX(AO16-(0),0),'입력값'!C9*100+'입력값'!C62*100)*('입력값'!C9*100)/IF(('입력값'!C9*100+'입력값'!C62*100)=0,1,'입력값'!C9*100+'입력값'!C62*100) | AP17: =MIN(MAX(AP16-(0),0),'입력값'!C9*100+'입력값'!C62*100)*('입력값'!C9*100)/IF(('입력값'!C9*100+'입력값'!C62*100)=0,1,'입력값'!C9*100+'입력값'!C62*100) | AQ17: =MIN(MAX(AQ16-(0),0),'입력값'!C9*100+'입력값'!C62*100)*('입력값'!C9*100)/IF(('입력값'!C9*100+'입력값'!C62*100)=0,1,'입력값'!C9*100+'입력값'!C62*100) | AR17: =MIN(MAX(AR16-(0),0),'입력값'!C9*100+'입력값'!C62*100)*('입력값'!C9*100)/IF(('입력값'!C9*100+'입력값'!C62*100)=0,1,'입력값'!C9*100+'입력값'!C62*100) | AS17: =MIN(MAX(AS16-(0),0),'입력값'!C9*100+'입력값'!C62*100)*('입력값'!C9*100)/IF(('입력값'!C9*100+'입력값'!C62*100)=0,1,'입력값'!C9*100+'입력값'!C62*100) | AT17: =MIN(MAX(AT16-(0),0),'입력값'!C9*100+'입력값'!C62*100)*('입력값'!C9*100)/IF(('입력값'!C9*100+'입력값'!C62*100)=0,1,'입력값'!C9*100+'입력값'!C62*100) | AU17: =MIN(MAX(AU16-(0),0),'입력값'!C9*100+'입력값'!C62*100)*('입력값'!C9*100)/IF(('입력값'!C9*100+'입력값'!C62*100)=0,1,'입력값'!C9*100+'입력값'!C62*100) | AV17: =MIN(MAX(AV16-(0),0),'입력값'!C9*100+'입력값'!C62*100)*('입력값'!C9*100)/IF(('입력값'!C9*100+'입력값'!C62*100)=0,1,'입력값'!C9*100+'입력값'!C62*100) | AW17: =MIN(MAX(AW16-(0),0),'입력값'!C9*100+'입력값'!C62*100)*('입력값'!C9*100)/IF(('입력값'!C9*100+'입력값'!C62*100)=0,1,'입력값'!C9*100+'입력값'!C62*100) | AX17: =MIN(MAX(AX16-(0),0),'입력값'!C9*100+'입력값'!C62*100)*('입력값'!C9*100)/IF(('입력값'!C9*100+'입력값'!C62*100)=0,1,'입력값'!C9*100+'입력값'!C62*100) | AY17: =MIN(MAX(AY16-(0),0),'입력값'!C9*100+'입력값'!C62*100)*('입력값'!C9*100)/IF(('입력값'!C9*100+'입력값'!C62*100)=0,1,'입력값'!C9*100+'입력값'!C62*100) | AZ17: =MIN(MAX(AZ16-(0),0),'입력값'!C9*100+'입력값'!C62*100)*('입력값'!C9*100)/IF(('입력값'!C9*100+'입력값'!C62*100)=0,1,'입력값'!C9*100+'입력값'!C62*100) | BA17: =MIN(MAX(BA16-(0),0),'입력값'!C9*100+'입력값'!C62*100)*('입력값'!C9*100)/IF(('입력값'!C9*100+'입력값'!C62*100)=0,1,'입력값'!C9*100+'입력값'!C62*100) | BB17: =MIN(MAX(BB16-(0),0),'입력값'!C9*100+'입력값'!C62*100)*('입력값'!C9*100)/IF(('입력값'!C9*100+'입력값'!C62*100)=0,1,'입력값'!C9*100+'입력값'!C62*100) | BC17: =MIN(MAX(BC16-(0),0),'입력값'!C9*100+'입력값'!C62*100)*('입력값'!C9*100)/IF(('입력값'!C9*100+'입력값'!C62*100)=0,1,'입력값'!C9*100+'입력값'!C62*100) | BD17: =MIN(MAX(BD16-(0),0),'입력값'!C9*100+'입력값'!C62*100)*('입력값'!C9*100)/IF(('입력값'!C9*100+'입력값'!C62*100)=0,1,'입력값'!C9*100+'입력값'!C62*100) | BE17: =MIN(MAX(BE16-(0),0),'입력값'!C9*100+'입력값'!C62*100)*('입력값'!C9*100)/IF(('입력값'!C9*100+'입력값'!C62*100)=0,1,'입력값'!C9*100+'입력값'!C62*100) | BF17: =MIN(MAX(BF16-(0),0),'입력값'!C9*100+'입력값'!C62*100)*('입력값'!C9*100)/IF(('입력값'!C9*100+'입력값'!C62*100)=0,1,'입력값'!C9*100+'입력값'!C62*100) | BG17: =MIN(MAX(BG16-(0),0),'입력값'!C9*100+'입력값'!C62*100)*('입력값'!C9*100)/IF(('입력값'!C9*100+'입력값'!C62*100)=0,1,'입력값'!C9*100+'입력값'!C62*100) | BH17: =MIN(MAX(BH16-(0),0),'입력값'!C9*100+'입력값'!C62*100)*('입력값'!C9*100)/IF(('입력값'!C9*100+'입력값'!C62*100)=0,1,'입력값'!C9*100+'입력값'!C62*100) | BI17: =MIN(MAX(BI16-(0),0),'입력값'!C9*100+'입력값'!C62*100)*('입력값'!C9*100)/IF(('입력값'!C9*100+'입력값'!C62*100)=0,1,'입력값'!C9*100+'입력값'!C62*100) | BJ17: =MIN(MAX(BJ16-(0),0),'입력값'!C9*100+'입력값'!C62*100)*('입력값'!C9*100)/IF(('입력값'!C9*100+'입력값'!C62*100)=0,1,'입력값'!C9*100+'입력값'!C62*100) | BK17: =MIN(MAX(BK16-(0),0),'입력값'!C9*100+'입력값'!C62*100)*('입력값'!C9*100)/IF(('입력값'!C9*100+'입력값'!C62*100)=0,1,'입력값'!C9*100+'입력값'!C62*100) | BL17: =MIN(MAX(BL16-(0),0),'입력값'!C9*100+'입력값'!C62*100)*('입력값'!C9*100)/IF(('입력값'!C9*100+'입력값'!C62*100)=0,1,'입력값'!C9*100+'입력값'!C62*100) | BM17: =MIN(MAX(BM16-(0),0),'입력값'!C9*100+'입력값'!C62*100)*('입력값'!C9*100)/IF(('입력값'!C9*100+'입력값'!C62*100)=0,1,'입력값'!C9*100+'입력값'!C62*100) | BN17: =MIN(MAX(BN16-(0),0),'입력값'!C9*100+'입력값'!C62*100)*('입력값'!C9*100)/IF(('입력값'!C9*100+'입력값'!C62*100)=0,1,'입력값'!C9*100+'입력값'!C62*100) | BO17: =MIN(MAX(BO16-(0),0),'입력값'!C9*100+'입력값'!C62*100)*('입력값'!C9*100)/IF(('입력값'!C9*100+'입력값'!C62*100)=0,1,'입력값'!C9*100+'입력값'!C62*100) | BP17: =MIN(MAX(BP16-(0),0),'입력값'!C9*100+'입력값'!C62*100)*('입력값'!C9*100)/IF(('입력값'!C9*100+'입력값'!C62*100)=0,1,'입력값'!C9*100+'입력값'!C62*100) | BQ17: =MIN(MAX(BQ16-(0),0),'입력값'!C9*100+'입력값'!C62*100)*('입력값'!C9*100)/IF(('입력값'!C9*100+'입력값'!C62*100)=0,1,'입력값'!C9*100+'입력값'!C62*100) | BR17: =MIN(MAX(BR16-(0),0),'입력값'!C9*100+'입력값'!C62*100)*('입력값'!C9*100)/IF(('입력값'!C9*100+'입력값'!C62*100)=0,1,'입력값'!C9*100+'입력값'!C62*100) | BS17: =MIN(MAX(BS16-(0),0),'입력값'!C9*100+'입력값'!C62*100)*('입력값'!C9*100)/IF(('입력값'!C9*100+'입력값'!C62*100)=0,1,'입력값'!C9*100+'입력값'!C62*100) | BT17: =MIN(MAX(BT16-(0),0),'입력값'!C9*100+'입력값'!C62*100)*('입력값'!C9*100)/IF(('입력값'!C9*100+'입력값'!C62*100)=0,1,'입력값'!C9*100+'입력값'!C62*100) | BU17: =MIN(MAX(BU16-(0),0),'입력값'!C9*100+'입력값'!C62*100)*('입력값'!C9*100)/IF(('입력값'!C9*100+'입력값'!C62*100)=0,1,'입력값'!C9*100+'입력값'!C62*100) | BV17: =MIN(MAX(BV16-(0),0),'입력값'!C9*100+'입력값'!C62*100)*('입력값'!C9*100)/IF(('입력값'!C9*100+'입력값'!C62*100)=0,1,'입력값'!C9*100+'입력값'!C62*100) | BW17: =MIN(MAX(BW16-(0),0),'입력값'!C9*100+'입력값'!C62*100)*('입력값'!C9*100)/IF(('입력값'!C9*100+'입력값'!C62*100)=0,1,'입력값'!C9*100+'입력값'!C62*100) | BX17: =MIN(MAX(BX16-(0),0),'입력값'!C9*100+'입력값'!C62*100)*('입력값'!C9*100)/IF(('입력값'!C9*100+'입력값'!C62*100)=0,1,'입력값'!C9*100+'입력값'!C62*100) | BY17: =MIN(MAX(BY16-(0),0),'입력값'!C9*100+'입력값'!C62*100)*('입력값'!C9*100)/IF(('입력값'!C9*100+'입력값'!C62*100)=0,1,'입력값'!C9*100+'입력값'!C62*100) | BZ17: =MIN(MAX(BZ16-(0),0),'입력값'!C9*100+'입력값'!C62*100)*('입력값'!C9*100)/IF(('입력값'!C9*100+'입력값'!C62*100)=0,1,'입력값'!C9*100+'입력값'!C62*100) | CA17: =MIN(MAX(CA16-(0),0),'입력값'!C9*100+'입력값'!C62*100)*('입력값'!C9*100)/IF(('입력값'!C9*100+'입력값'!C62*100)=0,1,'입력값'!C9*100+'입력값'!C62*100) | CB17: =MIN(MAX(CB16-(0),0),'입력값'!C9*100+'입력값'!C62*100)*('입력값'!C9*100)/IF(('입력값'!C9*100+'입력값'!C62*100)=0,1,'입력값'!C9*100+'입력값'!C62*100) | CC17: =MIN(MAX(CC16-(0),0),'입력값'!C9*100+'입력값'!C62*100)*('입력값'!C9*100)/IF(('입력값'!C9*100+'입력값'!C62*100)=0,1,'입력값'!C9*100+'입력값'!C62*100) | CD17: =MIN(MAX(CD16-(0),0),'입력값'!C9*100+'입력값'!C62*100)*('입력값'!C9*100)/IF(('입력값'!C9*100+'입력값'!C62*100)=0,1,'입력값'!C9*100+'입력값'!C62*100) | CE17: =MIN(MAX(CE16-(0),0),'입력값'!C9*100+'입력값'!C62*100)*('입력값'!C9*100)/IF(('입력값'!C9*100+'입력값'!C62*100)=0,1,'입력값'!C9*100+'입력값'!C62*100) | CF17: =MIN(MAX(CF16-(0),0),'입력값'!C9*100+'입력값'!C62*100)*('입력값'!C9*100)/IF(('입력값'!C9*100+'입력값'!C62*100)=0,1,'입력값'!C9*100+'입력값'!C62*100) | CG17: =MIN(MAX(CG16-(0),0),'입력값'!C9*100+'입력값'!C62*100)*('입력값'!C9*100)/IF(('입력값'!C9*100+'입력값'!C62*100)=0,1,'입력값'!C9*100+'입력값'!C62*100) | CH17: =MIN(MAX(CH16-(0),0),'입력값'!C9*100+'입력값'!C62*100)*('입력값'!C9*100)/IF(('입력값'!C9*100+'입력값'!C62*100)=0,1,'입력값'!C9*100+'입력값'!C62*100) | CI17: =MIN(MAX(CI16-(0),0),'입력값'!C9*100+'입력값'!C62*100)*('입력값'!C9*100)/IF(('입력값'!C9*100+'입력값'!C62*100)=0,1,'입력값'!C9*100+'입력값'!C62*100) | CJ17: =MIN(MAX(CJ16-(0),0),'입력값'!C9*100+'입력값'!C62*100)*('입력값'!C9*100)/IF(('입력값'!C9*100+'입력값'!C62*100)=0,1,'입력값'!C9*100+'입력값'!C62*100) | CK17: =MIN(MAX(CK16-(0),0),'입력값'!C9*100+'입력값'!C62*100)*('입력값'!C9*100)/IF(('입력값'!C9*100+'입력값'!C62*100)=0,1,'입력값'!C9*100+'입력값'!C62*100) | CL17: =MIN(MAX(CL16-(0),0),'입력값'!C9*100+'입력값'!C62*100)*('입력값'!C9*100)/IF(('입력값'!C9*100+'입력값'!C62*100)=0,1,'입력값'!C9*100+'입력값'!C62*100)
B18: 선순위A 누적인출 | C18: [KRWm] | E18: =MIN(MAX(E16-('입력값'!C9*100+'입력값'!C62*100),0),'입력값'!C58*100+'입력값'!C59*100)*('입력값'!C58*100)/IF(('입력값'!C58*100+'입력값'!C59*100)=0,1,'입력값'!C58*100+'입력값'!C59*100) | F18: =MIN(MAX(F16-('입력값'!C9*100+'입력값'!C62*100),0),'입력값'!C58*100+'입력값'!C59*100)*('입력값'!C58*100)/IF(('입력값'!C58*100+'입력값'!C59*100)=0,1,'입력값'!C58*100+'입력값'!C59*100) | G18: =MIN(MAX(G16-('입력값'!C9*100+'입력값'!C62*100),0),'입력값'!C58*100+'입력값'!C59*100)*('입력값'!C58*100)/IF(('입력값'!C58*100+'입력값'!C59*100)=0,1,'입력값'!C58*100+'입력값'!C59*100) | H18: =MIN(MAX(H16-('입력값'!C9*100+'입력값'!C62*100),0),'입력값'!C58*100+'입력값'!C59*100)*('입력값'!C58*100)/IF(('입력값'!C58*100+'입력값'!C59*100)=0,1,'입력값'!C58*100+'입력값'!C59*100) | I18: =MIN(MAX(I16-('입력값'!C9*100+'입력값'!C62*100),0),'입력값'!C58*100+'입력값'!C59*100)*('입력값'!C58*100)/IF(('입력값'!C58*100+'입력값'!C59*100)=0,1,'입력값'!C58*100+'입력값'!C59*100) | J18: =MIN(MAX(J16-('입력값'!C9*100+'입력값'!C62*100),0),'입력값'!C58*100+'입력값'!C59*100)*('입력값'!C58*100)/IF(('입력값'!C58*100+'입력값'!C59*100)=0,1,'입력값'!C58*100+'입력값'!C59*100) | K18: =MIN(MAX(K16-('입력값'!C9*100+'입력값'!C62*100),0),'입력값'!C58*100+'입력값'!C59*100)*('입력값'!C58*100)/IF(('입력값'!C58*100+'입력값'!C59*100)=0,1,'입력값'!C58*100+'입력값'!C59*100) | L18: =MIN(MAX(L16-('입력값'!C9*100+'입력값'!C62*100),0),'입력값'!C58*100+'입력값'!C59*100)*('입력값'!C58*100)/IF(('입력값'!C58*100+'입력값'!C59*100)=0,1,'입력값'!C58*100+'입력값'!C59*100) | M18: =MIN(MAX(M16-('입력값'!C9*100+'입력값'!C62*100),0),'입력값'!C58*100+'입력값'!C59*100)*('입력값'!C58*100)/IF(('입력값'!C58*100+'입력값'!C59*100)=0,1,'입력값'!C58*100+'입력값'!C59*100) | N18: =MIN(MAX(N16-('입력값'!C9*100+'입력값'!C62*100),0),'입력값'!C58*100+'입력값'!C59*100)*('입력값'!C58*100)/IF(('입력값'!C58*100+'입력값'!C59*100)=0,1,'입력값'!C58*100+'입력값'!C59*100) | O18: =MIN(MAX(O16-('입력값'!C9*100+'입력값'!C62*100),0),'입력값'!C58*100+'입력값'!C59*100)*('입력값'!C58*100)/IF(('입력값'!C58*100+'입력값'!C59*100)=0,1,'입력값'!C58*100+'입력값'!C59*100) | P18: =MIN(MAX(P16-('입력값'!C9*100+'입력값'!C62*100),0),'입력값'!C58*100+'입력값'!C59*100)*('입력값'!C58*100)/IF(('입력값'!C58*100+'입력값'!C59*100)=0,1,'입력값'!C58*100+'입력값'!C59*100) | Q18: =MIN(MAX(Q16-('입력값'!C9*100+'입력값'!C62*100),0),'입력값'!C58*100+'입력값'!C59*100)*('입력값'!C58*100)/IF(('입력값'!C58*100+'입력값'!C59*100)=0,1,'입력값'!C58*100+'입력값'!C59*100) | R18: =MIN(MAX(R16-('입력값'!C9*100+'입력값'!C62*100),0),'입력값'!C58*100+'입력값'!C59*100)*('입력값'!C58*100)/IF(('입력값'!C58*100+'입력값'!C59*100)=0,1,'입력값'!C58*100+'입력값'!C59*100) | S18: =MIN(MAX(S16-('입력값'!C9*100+'입력값'!C62*100),0),'입력값'!C58*100+'입력값'!C59*100)*('입력값'!C58*100)/IF(('입력값'!C58*100+'입력값'!C59*100)=0,1,'입력값'!C58*100+'입력값'!C59*100) | T18: =MIN(MAX(T16-('입력값'!C9*100+'입력값'!C62*100),0),'입력값'!C58*100+'입력값'!C59*100)*('입력값'!C58*100)/IF(('입력값'!C58*100+'입력값'!C59*100)=0,1,'입력값'!C58*100+'입력값'!C59*100) | U18: =MIN(MAX(U16-('입력값'!C9*100+'입력값'!C62*100),0),'입력값'!C58*100+'입력값'!C59*100)*('입력값'!C58*100)/IF(('입력값'!C58*100+'입력값'!C59*100)=0,1,'입력값'!C58*100+'입력값'!C59*100) | V18: =MIN(MAX(V16-('입력값'!C9*100+'입력값'!C62*100),0),'입력값'!C58*100+'입력값'!C59*100)*('입력값'!C58*100)/IF(('입력값'!C58*100+'입력값'!C59*100)=0,1,'입력값'!C58*100+'입력값'!C59*100) | W18: =MIN(MAX(W16-('입력값'!C9*100+'입력값'!C62*100),0),'입력값'!C58*100+'입력값'!C59*100)*('입력값'!C58*100)/IF(('입력값'!C58*100+'입력값'!C59*100)=0,1,'입력값'!C58*100+'입력값'!C59*100) | X18: =MIN(MAX(X16-('입력값'!C9*100+'입력값'!C62*100),0),'입력값'!C58*100+'입력값'!C59*100)*('입력값'!C58*100)/IF(('입력값'!C58*100+'입력값'!C59*100)=0,1,'입력값'!C58*100+'입력값'!C59*100) | Y18: =MIN(MAX(Y16-('입력값'!C9*100+'입력값'!C62*100),0),'입력값'!C58*100+'입력값'!C59*100)*('입력값'!C58*100)/IF(('입력값'!C58*100+'입력값'!C59*100)=0,1,'입력값'!C58*100+'입력값'!C59*100) | Z18: =MIN(MAX(Z16-('입력값'!C9*100+'입력값'!C62*100),0),'입력값'!C58*100+'입력값'!C59*100)*('입력값'!C58*100)/IF(('입력값'!C58*100+'입력값'!C59*100)=0,1,'입력값'!C58*100+'입력값'!C59*100) | AA18: =MIN(MAX(AA16-('입력값'!C9*100+'입력값'!C62*100),0),'입력값'!C58*100+'입력값'!C59*100)*('입력값'!C58*100)/IF(('입력값'!C58*100+'입력값'!C59*100)=0,1,'입력값'!C58*100+'입력값'!C59*100) | AB18: =MIN(MAX(AB16-('입력값'!C9*100+'입력값'!C62*100),0),'입력값'!C58*100+'입력값'!C59*100)*('입력값'!C58*100)/IF(('입력값'!C58*100+'입력값'!C59*100)=0,1,'입력값'!C58*100+'입력값'!C59*100) | AC18: =MIN(MAX(AC16-('입력값'!C9*100+'입력값'!C62*100),0),'입력값'!C58*100+'입력값'!C59*100)*('입력값'!C58*100)/IF(('입력값'!C58*100+'입력값'!C59*100)=0,1,'입력값'!C58*100+'입력값'!C59*100) | AD18: =MIN(MAX(AD16-('입력값'!C9*100+'입력값'!C62*100),0),'입력값'!C58*100+'입력값'!C59*100)*('입력값'!C58*100)/IF(('입력값'!C58*100+'입력값'!C59*100)=0,1,'입력값'!C58*100+'입력값'!C59*100) | AE18: =MIN(MAX(AE16-('입력값'!C9*100+'입력값'!C62*100),0),'입력값'!C58*100+'입력값'!C59*100)*('입력값'!C58*100)/IF(('입력값'!C58*100+'입력값'!C59*100)=0,1,'입력값'!C58*100+'입력값'!C59*100) | AF18: =MIN(MAX(AF16-('입력값'!C9*100+'입력값'!C62*100),0),'입력값'!C58*100+'입력값'!C59*100)*('입력값'!C58*100)/IF(('입력값'!C58*100+'입력값'!C59*100)=0,1,'입력값'!C58*100+'입력값'!C59*100) | AG18: =MIN(MAX(AG16-('입력값'!C9*100+'입력값'!C62*100),0),'입력값'!C58*100+'입력값'!C59*100)*('입력값'!C58*100)/IF(('입력값'!C58*100+'입력값'!C59*100)=0,1,'입력값'!C58*100+'입력값'!C59*100) | AH18: =MIN(MAX(AH16-('입력값'!C9*100+'입력값'!C62*100),0),'입력값'!C58*100+'입력값'!C59*100)*('입력값'!C58*100)/IF(('입력값'!C58*100+'입력값'!C59*100)=0,1,'입력값'!C58*100+'입력값'!C59*100) | AI18: =MIN(MAX(AI16-('입력값'!C9*100+'입력값'!C62*100),0),'입력값'!C58*100+'입력값'!C59*100)*('입력값'!C58*100)/IF(('입력값'!C58*100+'입력값'!C59*100)=0,1,'입력값'!C58*100+'입력값'!C59*100) | AJ18: =MIN(MAX(AJ16-('입력값'!C9*100+'입력값'!C62*100),0),'입력값'!C58*100+'입력값'!C59*100)*('입력값'!C58*100)/IF(('입력값'!C58*100+'입력값'!C59*100)=0,1,'입력값'!C58*100+'입력값'!C59*100) | AK18: =MIN(MAX(AK16-('입력값'!C9*100+'입력값'!C62*100),0),'입력값'!C58*100+'입력값'!C59*100)*('입력값'!C58*100)/IF(('입력값'!C58*100+'입력값'!C59*100)=0,1,'입력값'!C58*100+'입력값'!C59*100) | AL18: =MIN(MAX(AL16-('입력값'!C9*100+'입력값'!C62*100),0),'입력값'!C58*100+'입력값'!C59*100)*('입력값'!C58*100)/IF(('입력값'!C58*100+'입력값'!C59*100)=0,1,'입력값'!C58*100+'입력값'!C59*100) | AM18: =MIN(MAX(AM16-('입력값'!C9*100+'입력값'!C62*100),0),'입력값'!C58*100+'입력값'!C59*100)*('입력값'!C58*100)/IF(('입력값'!C58*100+'입력값'!C59*100)=0,1,'입력값'!C58*100+'입력값'!C59*100) | AN18: =MIN(MAX(AN16-('입력값'!C9*100+'입력값'!C62*100),0),'입력값'!C58*100+'입력값'!C59*100)*('입력값'!C58*100)/IF(('입력값'!C58*100+'입력값'!C59*100)=0,1,'입력값'!C58*100+'입력값'!C59*100) | AO18: =MIN(MAX(AO16-('입력값'!C9*100+'입력값'!C62*100),0),'입력값'!C58*100+'입력값'!C59*100)*('입력값'!C58*100)/IF(('입력값'!C58*100+'입력값'!C59*100)=0,1,'입력값'!C58*100+'입력값'!C59*100) | AP18: =MIN(MAX(AP16-('입력값'!C9*100+'입력값'!C62*100),0),'입력값'!C58*100+'입력값'!C59*100)*('입력값'!C58*100)/IF(('입력값'!C58*100+'입력값'!C59*100)=0,1,'입력값'!C58*100+'입력값'!C59*100) | AQ18: =MIN(MAX(AQ16-('입력값'!C9*100+'입력값'!C62*100),0),'입력값'!C58*100+'입력값'!C59*100)*('입력값'!C58*100)/IF(('입력값'!C58*100+'입력값'!C59*100)=0,1,'입력값'!C58*100+'입력값'!C59*100) | AR18: =MIN(MAX(AR16-('입력값'!C9*100+'입력값'!C62*100),0),'입력값'!C58*100+'입력값'!C59*100)*('입력값'!C58*100)/IF(('입력값'!C58*100+'입력값'!C59*100)=0,1,'입력값'!C58*100+'입력값'!C59*100) | AS18: =MIN(MAX(AS16-('입력값'!C9*100+'입력값'!C62*100),0),'입력값'!C58*100+'입력값'!C59*100)*('입력값'!C58*100)/IF(('입력값'!C58*100+'입력값'!C59*100)=0,1,'입력값'!C58*100+'입력값'!C59*100) | AT18: =MIN(MAX(AT16-('입력값'!C9*100+'입력값'!C62*100),0),'입력값'!C58*100+'입력값'!C59*100)*('입력값'!C58*100)/IF(('입력값'!C58*100+'입력값'!C59*100)=0,1,'입력값'!C58*100+'입력값'!C59*100) | AU18: =MIN(MAX(AU16-('입력값'!C9*100+'입력값'!C62*100),0),'입력값'!C58*100+'입력값'!C59*100)*('입력값'!C58*100)/IF(('입력값'!C58*100+'입력값'!C59*100)=0,1,'입력값'!C58*100+'입력값'!C59*100) | AV18: =MIN(MAX(AV16-('입력값'!C9*100+'입력값'!C62*100),0),'입력값'!C58*100+'입력값'!C59*100)*('입력값'!C58*100)/IF(('입력값'!C58*100+'입력값'!C59*100)=0,1,'입력값'!C58*100+'입력값'!C59*100) | AW18: =MIN(MAX(AW16-('입력값'!C9*100+'입력값'!C62*100),0),'입력값'!C58*100+'입력값'!C59*100)*('입력값'!C58*100)/IF(('입력값'!C58*100+'입력값'!C59*100)=0,1,'입력값'!C58*100+'입력값'!C59*100) | AX18: =MIN(MAX(AX16-('입력값'!C9*100+'입력값'!C62*100),0),'입력값'!C58*100+'입력값'!C59*100)*('입력값'!C58*100)/IF(('입력값'!C58*100+'입력값'!C59*100)=0,1,'입력값'!C58*100+'입력값'!C59*100) | AY18: =MIN(MAX(AY16-('입력값'!C9*100+'입력값'!C62*100),0),'입력값'!C58*100+'입력값'!C59*100)*('입력값'!C58*100)/IF(('입력값'!C58*100+'입력값'!C59*100)=0,1,'입력값'!C58*100+'입력값'!C59*100) | AZ18: =MIN(MAX(AZ16-('입력값'!C9*100+'입력값'!C62*100),0),'입력값'!C58*100+'입력값'!C59*100)*('입력값'!C58*100)/IF(('입력값'!C58*100+'입력값'!C59*100)=0,1,'입력값'!C58*100+'입력값'!C59*100) | BA18: =MIN(MAX(BA16-('입력값'!C9*100+'입력값'!C62*100),0),'입력값'!C58*100+'입력값'!C59*100)*('입력값'!C58*100)/IF(('입력값'!C58*100+'입력값'!C59*100)=0,1,'입력값'!C58*100+'입력값'!C59*100) | BB18: =MIN(MAX(BB16-('입력값'!C9*100+'입력값'!C62*100),0),'입력값'!C58*100+'입력값'!C59*100)*('입력값'!C58*100)/IF(('입력값'!C58*100+'입력값'!C59*100)=0,1,'입력값'!C58*100+'입력값'!C59*100) | BC18: =MIN(MAX(BC16-('입력값'!C9*100+'입력값'!C62*100),0),'입력값'!C58*100+'입력값'!C59*100)*('입력값'!C58*100)/IF(('입력값'!C58*100+'입력값'!C59*100)=0,1,'입력값'!C58*100+'입력값'!C59*100) | BD18: =MIN(MAX(BD16-('입력값'!C9*100+'입력값'!C62*100),0),'입력값'!C58*100+'입력값'!C59*100)*('입력값'!C58*100)/IF(('입력값'!C58*100+'입력값'!C59*100)=0,1,'입력값'!C58*100+'입력값'!C59*100) | BE18: =MIN(MAX(BE16-('입력값'!C9*100+'입력값'!C62*100),0),'입력값'!C58*100+'입력값'!C59*100)*('입력값'!C58*100)/IF(('입력값'!C58*100+'입력값'!C59*100)=0,1,'입력값'!C58*100+'입력값'!C59*100) | BF18: =MIN(MAX(BF16-('입력값'!C9*100+'입력값'!C62*100),0),'입력값'!C58*100+'입력값'!C59*100)*('입력값'!C58*100)/IF(('입력값'!C58*100+'입력값'!C59*100)=0,1,'입력값'!C58*100+'입력값'!C59*100) | BG18: =MIN(MAX(BG16-('입력값'!C9*100+'입력값'!C62*100),0),'입력값'!C58*100+'입력값'!C59*100)*('입력값'!C58*100)/IF(('입력값'!C58*100+'입력값'!C59*100)=0,1,'입력값'!C58*100+'입력값'!C59*100) | BH18: =MIN(MAX(BH16-('입력값'!C9*100+'입력값'!C62*100),0),'입력값'!C58*100+'입력값'!C59*100)*('입력값'!C58*100)/IF(('입력값'!C58*100+'입력값'!C59*100)=0,1,'입력값'!C58*100+'입력값'!C59*100) | BI18: =MIN(MAX(BI16-('입력값'!C9*100+'입력값'!C62*100),0),'입력값'!C58*100+'입력값'!C59*100)*('입력값'!C58*100)/IF(('입력값'!C58*100+'입력값'!C59*100)=0,1,'입력값'!C58*100+'입력값'!C59*100) | BJ18: =MIN(MAX(BJ16-('입력값'!C9*100+'입력값'!C62*100),0),'입력값'!C58*100+'입력값'!C59*100)*('입력값'!C58*100)/IF(('입력값'!C58*100+'입력값'!C59*100)=0,1,'입력값'!C58*100+'입력값'!C59*100) | BK18: =MIN(MAX(BK16-('입력값'!C9*100+'입력값'!C62*100),0),'입력값'!C58*100+'입력값'!C59*100)*('입력값'!C58*100)/IF(('입력값'!C58*100+'입력값'!C59*100)=0,1,'입력값'!C58*100+'입력값'!C59*100) | BL18: =MIN(MAX(BL16-('입력값'!C9*100+'입력값'!C62*100),0),'입력값'!C58*100+'입력값'!C59*100)*('입력값'!C58*100)/IF(('입력값'!C58*100+'입력값'!C59*100)=0,1,'입력값'!C58*100+'입력값'!C59*100) | BM18: =MIN(MAX(BM16-('입력값'!C9*100+'입력값'!C62*100),0),'입력값'!C58*100+'입력값'!C59*100)*('입력값'!C58*100)/IF(('입력값'!C58*100+'입력값'!C59*100)=0,1,'입력값'!C58*100+'입력값'!C59*100) | BN18: =MIN(MAX(BN16-('입력값'!C9*100+'입력값'!C62*100),0),'입력값'!C58*100+'입력값'!C59*100)*('입력값'!C58*100)/IF(('입력값'!C58*100+'입력값'!C59*100)=0,1,'입력값'!C58*100+'입력값'!C59*100) | BO18: =MIN(MAX(BO16-('입력값'!C9*100+'입력값'!C62*100),0),'입력값'!C58*100+'입력값'!C59*100)*('입력값'!C58*100)/IF(('입력값'!C58*100+'입력값'!C59*100)=0,1,'입력값'!C58*100+'입력값'!C59*100) | BP18: =MIN(MAX(BP16-('입력값'!C9*100+'입력값'!C62*100),0),'입력값'!C58*100+'입력값'!C59*100)*('입력값'!C58*100)/IF(('입력값'!C58*100+'입력값'!C59*100)=0,1,'입력값'!C58*100+'입력값'!C59*100) | BQ18: =MIN(MAX(BQ16-('입력값'!C9*100+'입력값'!C62*100),0),'입력값'!C58*100+'입력값'!C59*100)*('입력값'!C58*100)/IF(('입력값'!C58*100+'입력값'!C59*100)=0,1,'입력값'!C58*100+'입력값'!C59*100) | BR18: =MIN(MAX(BR16-('입력값'!C9*100+'입력값'!C62*100),0),'입력값'!C58*100+'입력값'!C59*100)*('입력값'!C58*100)/IF(('입력값'!C58*100+'입력값'!C59*100)=0,1,'입력값'!C58*100+'입력값'!C59*100) | BS18: =MIN(MAX(BS16-('입력값'!C9*100+'입력값'!C62*100),0),'입력값'!C58*100+'입력값'!C59*100)*('입력값'!C58*100)/IF(('입력값'!C58*100+'입력값'!C59*100)=0,1,'입력값'!C58*100+'입력값'!C59*100) | BT18: =MIN(MAX(BT16-('입력값'!C9*100+'입력값'!C62*100),0),'입력값'!C58*100+'입력값'!C59*100)*('입력값'!C58*100)/IF(('입력값'!C58*100+'입력값'!C59*100)=0,1,'입력값'!C58*100+'입력값'!C59*100) | BU18: =MIN(MAX(BU16-('입력값'!C9*100+'입력값'!C62*100),0),'입력값'!C58*100+'입력값'!C59*100)*('입력값'!C58*100)/IF(('입력값'!C58*100+'입력값'!C59*100)=0,1,'입력값'!C58*100+'입력값'!C59*100) | BV18: =MIN(MAX(BV16-('입력값'!C9*100+'입력값'!C62*100),0),'입력값'!C58*100+'입력값'!C59*100)*('입력값'!C58*100)/IF(('입력값'!C58*100+'입력값'!C59*100)=0,1,'입력값'!C58*100+'입력값'!C59*100) | BW18: =MIN(MAX(BW16-('입력값'!C9*100+'입력값'!C62*100),0),'입력값'!C58*100+'입력값'!C59*100)*('입력값'!C58*100)/IF(('입력값'!C58*100+'입력값'!C59*100)=0,1,'입력값'!C58*100+'입력값'!C59*100) | BX18: =MIN(MAX(BX16-('입력값'!C9*100+'입력값'!C62*100),0),'입력값'!C58*100+'입력값'!C59*100)*('입력값'!C58*100)/IF(('입력값'!C58*100+'입력값'!C59*100)=0,1,'입력값'!C58*100+'입력값'!C59*100) | BY18: =MIN(MAX(BY16-('입력값'!C9*100+'입력값'!C62*100),0),'입력값'!C58*100+'입력값'!C59*100)*('입력값'!C58*100)/IF(('입력값'!C58*100+'입력값'!C59*100)=0,1,'입력값'!C58*100+'입력값'!C59*100) | BZ18: =MIN(MAX(BZ16-('입력값'!C9*100+'입력값'!C62*100),0),'입력값'!C58*100+'입력값'!C59*100)*('입력값'!C58*100)/IF(('입력값'!C58*100+'입력값'!C59*100)=0,1,'입력값'!C58*100+'입력값'!C59*100) | CA18: =MIN(MAX(CA16-('입력값'!C9*100+'입력값'!C62*100),0),'입력값'!C58*100+'입력값'!C59*100)*('입력값'!C58*100)/IF(('입력값'!C58*100+'입력값'!C59*100)=0,1,'입력값'!C58*100+'입력값'!C59*100) | CB18: =MIN(MAX(CB16-('입력값'!C9*100+'입력값'!C62*100),0),'입력값'!C58*100+'입력값'!C59*100)*('입력값'!C58*100)/IF(('입력값'!C58*100+'입력값'!C59*100)=0,1,'입력값'!C58*100+'입력값'!C59*100) | CC18: =MIN(MAX(CC16-('입력값'!C9*100+'입력값'!C62*100),0),'입력값'!C58*100+'입력값'!C59*100)*('입력값'!C58*100)/IF(('입력값'!C58*100+'입력값'!C59*100)=0,1,'입력값'!C58*100+'입력값'!C59*100) | CD18: =MIN(MAX(CD16-('입력값'!C9*100+'입력값'!C62*100),0),'입력값'!C58*100+'입력값'!C59*100)*('입력값'!C58*100)/IF(('입력값'!C58*100+'입력값'!C59*100)=0,1,'입력값'!C58*100+'입력값'!C59*100) | CE18: =MIN(MAX(CE16-('입력값'!C9*100+'입력값'!C62*100),0),'입력값'!C58*100+'입력값'!C59*100)*('입력값'!C58*100)/IF(('입력값'!C58*100+'입력값'!C59*100)=0,1,'입력값'!C58*100+'입력값'!C59*100) | CF18: =MIN(MAX(CF16-('입력값'!C9*100+'입력값'!C62*100),0),'입력값'!C58*100+'입력값'!C59*100)*('입력값'!C58*100)/IF(('입력값'!C58*100+'입력값'!C59*100)=0,1,'입력값'!C58*100+'입력값'!C59*100) | CG18: =MIN(MAX(CG16-('입력값'!C9*100+'입력값'!C62*100),0),'입력값'!C58*100+'입력값'!C59*100)*('입력값'!C58*100)/IF(('입력값'!C58*100+'입력값'!C59*100)=0,1,'입력값'!C58*100+'입력값'!C59*100) | CH18: =MIN(MAX(CH16-('입력값'!C9*100+'입력값'!C62*100),0),'입력값'!C58*100+'입력값'!C59*100)*('입력값'!C58*100)/IF(('입력값'!C58*100+'입력값'!C59*100)=0,1,'입력값'!C58*100+'입력값'!C59*100) | CI18: =MIN(MAX(CI16-('입력값'!C9*100+'입력값'!C62*100),0),'입력값'!C58*100+'입력값'!C59*100)*('입력값'!C58*100)/IF(('입력값'!C58*100+'입력값'!C59*100)=0,1,'입력값'!C58*100+'입력값'!C59*100) | CJ18: =MIN(MAX(CJ16-('입력값'!C9*100+'입력값'!C62*100),0),'입력값'!C58*100+'입력값'!C59*100)*('입력값'!C58*100)/IF(('입력값'!C58*100+'입력값'!C59*100)=0,1,'입력값'!C58*100+'입력값'!C59*100) | CK18: =MIN(MAX(CK16-('입력값'!C9*100+'입력값'!C62*100),0),'입력값'!C58*100+'입력값'!C59*100)*('입력값'!C58*100)/IF(('입력값'!C58*100+'입력값'!C59*100)=0,1,'입력값'!C58*100+'입력값'!C59*100) | CL18: =MIN(MAX(CL16-('입력값'!C9*100+'입력값'!C62*100),0),'입력값'!C58*100+'입력값'!C59*100)*('입력값'!C58*100)/IF(('입력값'!C58*100+'입력값'!C59*100)=0,1,'입력값'!C58*100+'입력값'!C59*100)
B19: 선순위B 누적인출 | C19: [KRWm] | E19: =MIN(MAX(E16-('입력값'!C9*100+'입력값'!C62*100),0),'입력값'!C58*100+'입력값'!C59*100)*('입력값'!C59*100)/IF(('입력값'!C58*100+'입력값'!C59*100)=0,1,'입력값'!C58*100+'입력값'!C59*100) | F19: =MIN(MAX(F16-('입력값'!C9*100+'입력값'!C62*100),0),'입력값'!C58*100+'입력값'!C59*100)*('입력값'!C59*100)/IF(('입력값'!C58*100+'입력값'!C59*100)=0,1,'입력값'!C58*100+'입력값'!C59*100) | G19: =MIN(MAX(G16-('입력값'!C9*100+'입력값'!C62*100),0),'입력값'!C58*100+'입력값'!C59*100)*('입력값'!C59*100)/IF(('입력값'!C58*100+'입력값'!C59*100)=0,1,'입력값'!C58*100+'입력값'!C59*100) | H19: =MIN(MAX(H16-('입력값'!C9*100+'입력값'!C62*100),0),'입력값'!C58*100+'입력값'!C59*100)*('입력값'!C59*100)/IF(('입력값'!C58*100+'입력값'!C59*100)=0,1,'입력값'!C58*100+'입력값'!C59*100) | I19: =MIN(MAX(I16-('입력값'!C9*100+'입력값'!C62*100),0),'입력값'!C58*100+'입력값'!C59*100)*('입력값'!C59*100)/IF(('입력값'!C58*100+'입력값'!C59*100)=0,1,'입력값'!C58*100+'입력값'!C59*100) | J19: =MIN(MAX(J16-('입력값'!C9*100+'입력값'!C62*100),0),'입력값'!C58*100+'입력값'!C59*100)*('입력값'!C59*100)/IF(('입력값'!C58*100+'입력값'!C59*100)=0,1,'입력값'!C58*100+'입력값'!C59*100) | K19: =MIN(MAX(K16-('입력값'!C9*100+'입력값'!C62*100),0),'입력값'!C58*100+'입력값'!C59*100)*('입력값'!C59*100)/IF(('입력값'!C58*100+'입력값'!C59*100)=0,1,'입력값'!C58*100+'입력값'!C59*100) | L19: =MIN(MAX(L16-('입력값'!C9*100+'입력값'!C62*100),0),'입력값'!C58*100+'입력값'!C59*100)*('입력값'!C59*100)/IF(('입력값'!C58*100+'입력값'!C59*100)=0,1,'입력값'!C58*100+'입력값'!C59*100) | M19: =MIN(MAX(M16-('입력값'!C9*100+'입력값'!C62*100),0),'입력값'!C58*100+'입력값'!C59*100)*('입력값'!C59*100)/IF(('입력값'!C58*100+'입력값'!C59*100)=0,1,'입력값'!C58*100+'입력값'!C59*100) | N19: =MIN(MAX(N16-('입력값'!C9*100+'입력값'!C62*100),0),'입력값'!C58*100+'입력값'!C59*100)*('입력값'!C59*100)/IF(('입력값'!C58*100+'입력값'!C59*100)=0,1,'입력값'!C58*100+'입력값'!C59*100) | O19: =MIN(MAX(O16-('입력값'!C9*100+'입력값'!C62*100),0),'입력값'!C58*100+'입력값'!C59*100)*('입력값'!C59*100)/IF(('입력값'!C58*100+'입력값'!C59*100)=0,1,'입력값'!C58*100+'입력값'!C59*100) | P19: =MIN(MAX(P16-('입력값'!C9*100+'입력값'!C62*100),0),'입력값'!C58*100+'입력값'!C59*100)*('입력값'!C59*100)/IF(('입력값'!C58*100+'입력값'!C59*100)=0,1,'입력값'!C58*100+'입력값'!C59*100) | Q19: =MIN(MAX(Q16-('입력값'!C9*100+'입력값'!C62*100),0),'입력값'!C58*100+'입력값'!C59*100)*('입력값'!C59*100)/IF(('입력값'!C58*100+'입력값'!C59*100)=0,1,'입력값'!C58*100+'입력값'!C59*100) | R19: =MIN(MAX(R16-('입력값'!C9*100+'입력값'!C62*100),0),'입력값'!C58*100+'입력값'!C59*100)*('입력값'!C59*100)/IF(('입력값'!C58*100+'입력값'!C59*100)=0,1,'입력값'!C58*100+'입력값'!C59*100) | S19: =MIN(MAX(S16-('입력값'!C9*100+'입력값'!C62*100),0),'입력값'!C58*100+'입력값'!C59*100)*('입력값'!C59*100)/IF(('입력값'!C58*100+'입력값'!C59*100)=0,1,'입력값'!C58*100+'입력값'!C59*100) | T19: =MIN(MAX(T16-('입력값'!C9*100+'입력값'!C62*100),0),'입력값'!C58*100+'입력값'!C59*100)*('입력값'!C59*100)/IF(('입력값'!C58*100+'입력값'!C59*100)=0,1,'입력값'!C58*100+'입력값'!C59*100) | U19: =MIN(MAX(U16-('입력값'!C9*100+'입력값'!C62*100),0),'입력값'!C58*100+'입력값'!C59*100)*('입력값'!C59*100)/IF(('입력값'!C58*100+'입력값'!C59*100)=0,1,'입력값'!C58*100+'입력값'!C59*100) | V19: =MIN(MAX(V16-('입력값'!C9*100+'입력값'!C62*100),0),'입력값'!C58*100+'입력값'!C59*100)*('입력값'!C59*100)/IF(('입력값'!C58*100+'입력값'!C59*100)=0,1,'입력값'!C58*100+'입력값'!C59*100) | W19: =MIN(MAX(W16-('입력값'!C9*100+'입력값'!C62*100),0),'입력값'!C58*100+'입력값'!C59*100)*('입력값'!C59*100)/IF(('입력값'!C58*100+'입력값'!C59*100)=0,1,'입력값'!C58*100+'입력값'!C59*100) | X19: =MIN(MAX(X16-('입력값'!C9*100+'입력값'!C62*100),0),'입력값'!C58*100+'입력값'!C59*100)*('입력값'!C59*100)/IF(('입력값'!C58*100+'입력값'!C59*100)=0,1,'입력값'!C58*100+'입력값'!C59*100) | Y19: =MIN(MAX(Y16-('입력값'!C9*100+'입력값'!C62*100),0),'입력값'!C58*100+'입력값'!C59*100)*('입력값'!C59*100)/IF(('입력값'!C58*100+'입력값'!C59*100)=0,1,'입력값'!C58*100+'입력값'!C59*100) | Z19: =MIN(MAX(Z16-('입력값'!C9*100+'입력값'!C62*100),0),'입력값'!C58*100+'입력값'!C59*100)*('입력값'!C59*100)/IF(('입력값'!C58*100+'입력값'!C59*100)=0,1,'입력값'!C58*100+'입력값'!C59*100) | AA19: =MIN(MAX(AA16-('입력값'!C9*100+'입력값'!C62*100),0),'입력값'!C58*100+'입력값'!C59*100)*('입력값'!C59*100)/IF(('입력값'!C58*100+'입력값'!C59*100)=0,1,'입력값'!C58*100+'입력값'!C59*100) | AB19: =MIN(MAX(AB16-('입력값'!C9*100+'입력값'!C62*100),0),'입력값'!C58*100+'입력값'!C59*100)*('입력값'!C59*100)/IF(('입력값'!C58*100+'입력값'!C59*100)=0,1,'입력값'!C58*100+'입력값'!C59*100) | AC19: =MIN(MAX(AC16-('입력값'!C9*100+'입력값'!C62*100),0),'입력값'!C58*100+'입력값'!C59*100)*('입력값'!C59*100)/IF(('입력값'!C58*100+'입력값'!C59*100)=0,1,'입력값'!C58*100+'입력값'!C59*100) | AD19: =MIN(MAX(AD16-('입력값'!C9*100+'입력값'!C62*100),0),'입력값'!C58*100+'입력값'!C59*100)*('입력값'!C59*100)/IF(('입력값'!C58*100+'입력값'!C59*100)=0,1,'입력값'!C58*100+'입력값'!C59*100) | AE19: =MIN(MAX(AE16-('입력값'!C9*100+'입력값'!C62*100),0),'입력값'!C58*100+'입력값'!C59*100)*('입력값'!C59*100)/IF(('입력값'!C58*100+'입력값'!C59*100)=0,1,'입력값'!C58*100+'입력값'!C59*100) | AF19: =MIN(MAX(AF16-('입력값'!C9*100+'입력값'!C62*100),0),'입력값'!C58*100+'입력값'!C59*100)*('입력값'!C59*100)/IF(('입력값'!C58*100+'입력값'!C59*100)=0,1,'입력값'!C58*100+'입력값'!C59*100) | AG19: =MIN(MAX(AG16-('입력값'!C9*100+'입력값'!C62*100),0),'입력값'!C58*100+'입력값'!C59*100)*('입력값'!C59*100)/IF(('입력값'!C58*100+'입력값'!C59*100)=0,1,'입력값'!C58*100+'입력값'!C59*100) | AH19: =MIN(MAX(AH16-('입력값'!C9*100+'입력값'!C62*100),0),'입력값'!C58*100+'입력값'!C59*100)*('입력값'!C59*100)/IF(('입력값'!C58*100+'입력값'!C59*100)=0,1,'입력값'!C58*100+'입력값'!C59*100) | AI19: =MIN(MAX(AI16-('입력값'!C9*100+'입력값'!C62*100),0),'입력값'!C58*100+'입력값'!C59*100)*('입력값'!C59*100)/IF(('입력값'!C58*100+'입력값'!C59*100)=0,1,'입력값'!C58*100+'입력값'!C59*100) | AJ19: =MIN(MAX(AJ16-('입력값'!C9*100+'입력값'!C62*100),0),'입력값'!C58*100+'입력값'!C59*100)*('입력값'!C59*100)/IF(('입력값'!C58*100+'입력값'!C59*100)=0,1,'입력값'!C58*100+'입력값'!C59*100) | AK19: =MIN(MAX(AK16-('입력값'!C9*100+'입력값'!C62*100),0),'입력값'!C58*100+'입력값'!C59*100)*('입력값'!C59*100)/IF(('입력값'!C58*100+'입력값'!C59*100)=0,1,'입력값'!C58*100+'입력값'!C59*100) | AL19: =MIN(MAX(AL16-('입력값'!C9*100+'입력값'!C62*100),0),'입력값'!C58*100+'입력값'!C59*100)*('입력값'!C59*100)/IF(('입력값'!C58*100+'입력값'!C59*100)=0,1,'입력값'!C58*100+'입력값'!C59*100) | AM19: =MIN(MAX(AM16-('입력값'!C9*100+'입력값'!C62*100),0),'입력값'!C58*100+'입력값'!C59*100)*('입력값'!C59*100)/IF(('입력값'!C58*100+'입력값'!C59*100)=0,1,'입력값'!C58*100+'입력값'!C59*100) | AN19: =MIN(MAX(AN16-('입력값'!C9*100+'입력값'!C62*100),0),'입력값'!C58*100+'입력값'!C59*100)*('입력값'!C59*100)/IF(('입력값'!C58*100+'입력값'!C59*100)=0,1,'입력값'!C58*100+'입력값'!C59*100) | AO19: =MIN(MAX(AO16-('입력값'!C9*100+'입력값'!C62*100),0),'입력값'!C58*100+'입력값'!C59*100)*('입력값'!C59*100)/IF(('입력값'!C58*100+'입력값'!C59*100)=0,1,'입력값'!C58*100+'입력값'!C59*100) | AP19: =MIN(MAX(AP16-('입력값'!C9*100+'입력값'!C62*100),0),'입력값'!C58*100+'입력값'!C59*100)*('입력값'!C59*100)/IF(('입력값'!C58*100+'입력값'!C59*100)=0,1,'입력값'!C58*100+'입력값'!C59*100) | AQ19: =MIN(MAX(AQ16-('입력값'!C9*100+'입력값'!C62*100),0),'입력값'!C58*100+'입력값'!C59*100)*('입력값'!C59*100)/IF(('입력값'!C58*100+'입력값'!C59*100)=0,1,'입력값'!C58*100+'입력값'!C59*100) | AR19: =MIN(MAX(AR16-('입력값'!C9*100+'입력값'!C62*100),0),'입력값'!C58*100+'입력값'!C59*100)*('입력값'!C59*100)/IF(('입력값'!C58*100+'입력값'!C59*100)=0,1,'입력값'!C58*100+'입력값'!C59*100) | AS19: =MIN(MAX(AS16-('입력값'!C9*100+'입력값'!C62*100),0),'입력값'!C58*100+'입력값'!C59*100)*('입력값'!C59*100)/IF(('입력값'!C58*100+'입력값'!C59*100)=0,1,'입력값'!C58*100+'입력값'!C59*100) | AT19: =MIN(MAX(AT16-('입력값'!C9*100+'입력값'!C62*100),0),'입력값'!C58*100+'입력값'!C59*100)*('입력값'!C59*100)/IF(('입력값'!C58*100+'입력값'!C59*100)=0,1,'입력값'!C58*100+'입력값'!C59*100) | AU19: =MIN(MAX(AU16-('입력값'!C9*100+'입력값'!C62*100),0),'입력값'!C58*100+'입력값'!C59*100)*('입력값'!C59*100)/IF(('입력값'!C58*100+'입력값'!C59*100)=0,1,'입력값'!C58*100+'입력값'!C59*100) | AV19: =MIN(MAX(AV16-('입력값'!C9*100+'입력값'!C62*100),0),'입력값'!C58*100+'입력값'!C59*100)*('입력값'!C59*100)/IF(('입력값'!C58*100+'입력값'!C59*100)=0,1,'입력값'!C58*100+'입력값'!C59*100) | AW19: =MIN(MAX(AW16-('입력값'!C9*100+'입력값'!C62*100),0),'입력값'!C58*100+'입력값'!C59*100)*('입력값'!C59*100)/IF(('입력값'!C58*100+'입력값'!C59*100)=0,1,'입력값'!C58*100+'입력값'!C59*100) | AX19: =MIN(MAX(AX16-('입력값'!C9*100+'입력값'!C62*100),0),'입력값'!C58*100+'입력값'!C59*100)*('입력값'!C59*100)/IF(('입력값'!C58*100+'입력값'!C59*100)=0,1,'입력값'!C58*100+'입력값'!C59*100) | AY19: =MIN(MAX(AY16-('입력값'!C9*100+'입력값'!C62*100),0),'입력값'!C58*100+'입력값'!C59*100)*('입력값'!C59*100)/IF(('입력값'!C58*100+'입력값'!C59*100)=0,1,'입력값'!C58*100+'입력값'!C59*100) | AZ19: =MIN(MAX(AZ16-('입력값'!C9*100+'입력값'!C62*100),0),'입력값'!C58*100+'입력값'!C59*100)*('입력값'!C59*100)/IF(('입력값'!C58*100+'입력값'!C59*100)=0,1,'입력값'!C58*100+'입력값'!C59*100) | BA19: =MIN(MAX(BA16-('입력값'!C9*100+'입력값'!C62*100),0),'입력값'!C58*100+'입력값'!C59*100)*('입력값'!C59*100)/IF(('입력값'!C58*100+'입력값'!C59*100)=0,1,'입력값'!C58*100+'입력값'!C59*100) | BB19: =MIN(MAX(BB16-('입력값'!C9*100+'입력값'!C62*100),0),'입력값'!C58*100+'입력값'!C59*100)*('입력값'!C59*100)/IF(('입력값'!C58*100+'입력값'!C59*100)=0,1,'입력값'!C58*100+'입력값'!C59*100) | BC19: =MIN(MAX(BC16-('입력값'!C9*100+'입력값'!C62*100),0),'입력값'!C58*100+'입력값'!C59*100)*('입력값'!C59*100)/IF(('입력값'!C58*100+'입력값'!C59*100)=0,1,'입력값'!C58*100+'입력값'!C59*100) | BD19: =MIN(MAX(BD16-('입력값'!C9*100+'입력값'!C62*100),0),'입력값'!C58*100+'입력값'!C59*100)*('입력값'!C59*100)/IF(('입력값'!C58*100+'입력값'!C59*100)=0,1,'입력값'!C58*100+'입력값'!C59*100) | BE19: =MIN(MAX(BE16-('입력값'!C9*100+'입력값'!C62*100),0),'입력값'!C58*100+'입력값'!C59*100)*('입력값'!C59*100)/IF(('입력값'!C58*100+'입력값'!C59*100)=0,1,'입력값'!C58*100+'입력값'!C59*100) | BF19: =MIN(MAX(BF16-('입력값'!C9*100+'입력값'!C62*100),0),'입력값'!C58*100+'입력값'!C59*100)*('입력값'!C59*100)/IF(('입력값'!C58*100+'입력값'!C59*100)=0,1,'입력값'!C58*100+'입력값'!C59*100) | BG19: =MIN(MAX(BG16-('입력값'!C9*100+'입력값'!C62*100),0),'입력값'!C58*100+'입력값'!C59*100)*('입력값'!C59*100)/IF(('입력값'!C58*100+'입력값'!C59*100)=0,1,'입력값'!C58*100+'입력값'!C59*100) | BH19: =MIN(MAX(BH16-('입력값'!C9*100+'입력값'!C62*100),0),'입력값'!C58*100+'입력값'!C59*100)*('입력값'!C59*100)/IF(('입력값'!C58*100+'입력값'!C59*100)=0,1,'입력값'!C58*100+'입력값'!C59*100) | BI19: =MIN(MAX(BI16-('입력값'!C9*100+'입력값'!C62*100),0),'입력값'!C58*100+'입력값'!C59*100)*('입력값'!C59*100)/IF(('입력값'!C58*100+'입력값'!C59*100)=0,1,'입력값'!C58*100+'입력값'!C59*100) | BJ19: =MIN(MAX(BJ16-('입력값'!C9*100+'입력값'!C62*100),0),'입력값'!C58*100+'입력값'!C59*100)*('입력값'!C59*100)/IF(('입력값'!C58*100+'입력값'!C59*100)=0,1,'입력값'!C58*100+'입력값'!C59*100) | BK19: =MIN(MAX(BK16-('입력값'!C9*100+'입력값'!C62*100),0),'입력값'!C58*100+'입력값'!C59*100)*('입력값'!C59*100)/IF(('입력값'!C58*100+'입력값'!C59*100)=0,1,'입력값'!C58*100+'입력값'!C59*100) | BL19: =MIN(MAX(BL16-('입력값'!C9*100+'입력값'!C62*100),0),'입력값'!C58*100+'입력값'!C59*100)*('입력값'!C59*100)/IF(('입력값'!C58*100+'입력값'!C59*100)=0,1,'입력값'!C58*100+'입력값'!C59*100) | BM19: =MIN(MAX(BM16-('입력값'!C9*100+'입력값'!C62*100),0),'입력값'!C58*100+'입력값'!C59*100)*('입력값'!C59*100)/IF(('입력값'!C58*100+'입력값'!C59*100)=0,1,'입력값'!C58*100+'입력값'!C59*100) | BN19: =MIN(MAX(BN16-('입력값'!C9*100+'입력값'!C62*100),0),'입력값'!C58*100+'입력값'!C59*100)*('입력값'!C59*100)/IF(('입력값'!C58*100+'입력값'!C59*100)=0,1,'입력값'!C58*100+'입력값'!C59*100) | BO19: =MIN(MAX(BO16-('입력값'!C9*100+'입력값'!C62*100),0),'입력값'!C58*100+'입력값'!C59*100)*('입력값'!C59*100)/IF(('입력값'!C58*100+'입력값'!C59*100)=0,1,'입력값'!C58*100+'입력값'!C59*100) | BP19: =MIN(MAX(BP16-('입력값'!C9*100+'입력값'!C62*100),0),'입력값'!C58*100+'입력값'!C59*100)*('입력값'!C59*100)/IF(('입력값'!C58*100+'입력값'!C59*100)=0,1,'입력값'!C58*100+'입력값'!C59*100) | BQ19: =MIN(MAX(BQ16-('입력값'!C9*100+'입력값'!C62*100),0),'입력값'!C58*100+'입력값'!C59*100)*('입력값'!C59*100)/IF(('입력값'!C58*100+'입력값'!C59*100)=0,1,'입력값'!C58*100+'입력값'!C59*100) | BR19: =MIN(MAX(BR16-('입력값'!C9*100+'입력값'!C62*100),0),'입력값'!C58*100+'입력값'!C59*100)*('입력값'!C59*100)/IF(('입력값'!C58*100+'입력값'!C59*100)=0,1,'입력값'!C58*100+'입력값'!C59*100) | BS19: =MIN(MAX(BS16-('입력값'!C9*100+'입력값'!C62*100),0),'입력값'!C58*100+'입력값'!C59*100)*('입력값'!C59*100)/IF(('입력값'!C58*100+'입력값'!C59*100)=0,1,'입력값'!C58*100+'입력값'!C59*100) | BT19: =MIN(MAX(BT16-('입력값'!C9*100+'입력값'!C62*100),0),'입력값'!C58*100+'입력값'!C59*100)*('입력값'!C59*100)/IF(('입력값'!C58*100+'입력값'!C59*100)=0,1,'입력값'!C58*100+'입력값'!C59*100) | BU19: =MIN(MAX(BU16-('입력값'!C9*100+'입력값'!C62*100),0),'입력값'!C58*100+'입력값'!C59*100)*('입력값'!C59*100)/IF(('입력값'!C58*100+'입력값'!C59*100)=0,1,'입력값'!C58*100+'입력값'!C59*100) | BV19: =MIN(MAX(BV16-('입력값'!C9*100+'입력값'!C62*100),0),'입력값'!C58*100+'입력값'!C59*100)*('입력값'!C59*100)/IF(('입력값'!C58*100+'입력값'!C59*100)=0,1,'입력값'!C58*100+'입력값'!C59*100) | BW19: =MIN(MAX(BW16-('입력값'!C9*100+'입력값'!C62*100),0),'입력값'!C58*100+'입력값'!C59*100)*('입력값'!C59*100)/IF(('입력값'!C58*100+'입력값'!C59*100)=0,1,'입력값'!C58*100+'입력값'!C59*100) | BX19: =MIN(MAX(BX16-('입력값'!C9*100+'입력값'!C62*100),0),'입력값'!C58*100+'입력값'!C59*100)*('입력값'!C59*100)/IF(('입력값'!C58*100+'입력값'!C59*100)=0,1,'입력값'!C58*100+'입력값'!C59*100) | BY19: =MIN(MAX(BY16-('입력값'!C9*100+'입력값'!C62*100),0),'입력값'!C58*100+'입력값'!C59*100)*('입력값'!C59*100)/IF(('입력값'!C58*100+'입력값'!C59*100)=0,1,'입력값'!C58*100+'입력값'!C59*100) | BZ19: =MIN(MAX(BZ16-('입력값'!C9*100+'입력값'!C62*100),0),'입력값'!C58*100+'입력값'!C59*100)*('입력값'!C59*100)/IF(('입력값'!C58*100+'입력값'!C59*100)=0,1,'입력값'!C58*100+'입력값'!C59*100) | CA19: =MIN(MAX(CA16-('입력값'!C9*100+'입력값'!C62*100),0),'입력값'!C58*100+'입력값'!C59*100)*('입력값'!C59*100)/IF(('입력값'!C58*100+'입력값'!C59*100)=0,1,'입력값'!C58*100+'입력값'!C59*100) | CB19: =MIN(MAX(CB16-('입력값'!C9*100+'입력값'!C62*100),0),'입력값'!C58*100+'입력값'!C59*100)*('입력값'!C59*100)/IF(('입력값'!C58*100+'입력값'!C59*100)=0,1,'입력값'!C58*100+'입력값'!C59*100) | CC19: =MIN(MAX(CC16-('입력값'!C9*100+'입력값'!C62*100),0),'입력값'!C58*100+'입력값'!C59*100)*('입력값'!C59*100)/IF(('입력값'!C58*100+'입력값'!C59*100)=0,1,'입력값'!C58*100+'입력값'!C59*100) | CD19: =MIN(MAX(CD16-('입력값'!C9*100+'입력값'!C62*100),0),'입력값'!C58*100+'입력값'!C59*100)*('입력값'!C59*100)/IF(('입력값'!C58*100+'입력값'!C59*100)=0,1,'입력값'!C58*100+'입력값'!C59*100) | CE19: =MIN(MAX(CE16-('입력값'!C9*100+'입력값'!C62*100),0),'입력값'!C58*100+'입력값'!C59*100)*('입력값'!C59*100)/IF(('입력값'!C58*100+'입력값'!C59*100)=0,1,'입력값'!C58*100+'입력값'!C59*100) | CF19: =MIN(MAX(CF16-('입력값'!C9*100+'입력값'!C62*100),0),'입력값'!C58*100+'입력값'!C59*100)*('입력값'!C59*100)/IF(('입력값'!C58*100+'입력값'!C59*100)=0,1,'입력값'!C58*100+'입력값'!C59*100) | CG19: =MIN(MAX(CG16-('입력값'!C9*100+'입력값'!C62*100),0),'입력값'!C58*100+'입력값'!C59*100)*('입력값'!C59*100)/IF(('입력값'!C58*100+'입력값'!C59*100)=0,1,'입력값'!C58*100+'입력값'!C59*100) | CH19: =MIN(MAX(CH16-('입력값'!C9*100+'입력값'!C62*100),0),'입력값'!C58*100+'입력값'!C59*100)*('입력값'!C59*100)/IF(('입력값'!C58*100+'입력값'!C59*100)=0,1,'입력값'!C58*100+'입력값'!C59*100) | CI19: =MIN(MAX(CI16-('입력값'!C9*100+'입력값'!C62*100),0),'입력값'!C58*100+'입력값'!C59*100)*('입력값'!C59*100)/IF(('입력값'!C58*100+'입력값'!C59*100)=0,1,'입력값'!C58*100+'입력값'!C59*100) | CJ19: =MIN(MAX(CJ16-('입력값'!C9*100+'입력값'!C62*100),0),'입력값'!C58*100+'입력값'!C59*100)*('입력값'!C59*100)/IF(('입력값'!C58*100+'입력값'!C59*100)=0,1,'입력값'!C58*100+'입력값'!C59*100) | CK19: =MIN(MAX(CK16-('입력값'!C9*100+'입력값'!C62*100),0),'입력값'!C58*100+'입력값'!C59*100)*('입력값'!C59*100)/IF(('입력값'!C58*100+'입력값'!C59*100)=0,1,'입력값'!C58*100+'입력값'!C59*100) | CL19: =MIN(MAX(CL16-('입력값'!C9*100+'입력값'!C62*100),0),'입력값'!C58*100+'입력값'!C59*100)*('입력값'!C59*100)/IF(('입력값'!C58*100+'입력값'!C59*100)=0,1,'입력값'!C58*100+'입력값'!C59*100)
B20: 선순위C 누적인출 | C20: [KRWm] | E20: =MIN(MAX(E16-('입력값'!C9*100+'입력값'!C58*100+'입력값'!C59*100+'입력값'!C61*100+'입력값'!C62*100),0),'입력값'!C60*100)*('입력값'!C60*100)/IF(('입력값'!C60*100)=0,1,'입력값'!C60*100) | F20: =MIN(MAX(F16-('입력값'!C9*100+'입력값'!C58*100+'입력값'!C59*100+'입력값'!C61*100+'입력값'!C62*100),0),'입력값'!C60*100)*('입력값'!C60*100)/IF(('입력값'!C60*100)=0,1,'입력값'!C60*100) | G20: =MIN(MAX(G16-('입력값'!C9*100+'입력값'!C58*100+'입력값'!C59*100+'입력값'!C61*100+'입력값'!C62*100),0),'입력값'!C60*100)*('입력값'!C60*100)/IF(('입력값'!C60*100)=0,1,'입력값'!C60*100) | H20: =MIN(MAX(H16-('입력값'!C9*100+'입력값'!C58*100+'입력값'!C59*100+'입력값'!C61*100+'입력값'!C62*100),0),'입력값'!C60*100)*('입력값'!C60*100)/IF(('입력값'!C60*100)=0,1,'입력값'!C60*100) | I20: =MIN(MAX(I16-('입력값'!C9*100+'입력값'!C58*100+'입력값'!C59*100+'입력값'!C61*100+'입력값'!C62*100),0),'입력값'!C60*100)*('입력값'!C60*100)/IF(('입력값'!C60*100)=0,1,'입력값'!C60*100) | J20: =MIN(MAX(J16-('입력값'!C9*100+'입력값'!C58*100+'입력값'!C59*100+'입력값'!C61*100+'입력값'!C62*100),0),'입력값'!C60*100)*('입력값'!C60*100)/IF(('입력값'!C60*100)=0,1,'입력값'!C60*100) | K20: =MIN(MAX(K16-('입력값'!C9*100+'입력값'!C58*100+'입력값'!C59*100+'입력값'!C61*100+'입력값'!C62*100),0),'입력값'!C60*100)*('입력값'!C60*100)/IF(('입력값'!C60*100)=0,1,'입력값'!C60*100) | L20: =MIN(MAX(L16-('입력값'!C9*100+'입력값'!C58*100+'입력값'!C59*100+'입력값'!C61*100+'입력값'!C62*100),0),'입력값'!C60*100)*('입력값'!C60*100)/IF(('입력값'!C60*100)=0,1,'입력값'!C60*100) | M20: =MIN(MAX(M16-('입력값'!C9*100+'입력값'!C58*100+'입력값'!C59*100+'입력값'!C61*100+'입력값'!C62*100),0),'입력값'!C60*100)*('입력값'!C60*100)/IF(('입력값'!C60*100)=0,1,'입력값'!C60*100) | N20: =MIN(MAX(N16-('입력값'!C9*100+'입력값'!C58*100+'입력값'!C59*100+'입력값'!C61*100+'입력값'!C62*100),0),'입력값'!C60*100)*('입력값'!C60*100)/IF(('입력값'!C60*100)=0,1,'입력값'!C60*100) | O20: =MIN(MAX(O16-('입력값'!C9*100+'입력값'!C58*100+'입력값'!C59*100+'입력값'!C61*100+'입력값'!C62*100),0),'입력값'!C60*100)*('입력값'!C60*100)/IF(('입력값'!C60*100)=0,1,'입력값'!C60*100) | P20: =MIN(MAX(P16-('입력값'!C9*100+'입력값'!C58*100+'입력값'!C59*100+'입력값'!C61*100+'입력값'!C62*100),0),'입력값'!C60*100)*('입력값'!C60*100)/IF(('입력값'!C60*100)=0,1,'입력값'!C60*100) | Q20: =MIN(MAX(Q16-('입력값'!C9*100+'입력값'!C58*100+'입력값'!C59*100+'입력값'!C61*100+'입력값'!C62*100),0),'입력값'!C60*100)*('입력값'!C60*100)/IF(('입력값'!C60*100)=0,1,'입력값'!C60*100) | R20: =MIN(MAX(R16-('입력값'!C9*100+'입력값'!C58*100+'입력값'!C59*100+'입력값'!C61*100+'입력값'!C62*100),0),'입력값'!C60*100)*('입력값'!C60*100)/IF(('입력값'!C60*100)=0,1,'입력값'!C60*100) | S20: =MIN(MAX(S16-('입력값'!C9*100+'입력값'!C58*100+'입력값'!C59*100+'입력값'!C61*100+'입력값'!C62*100),0),'입력값'!C60*100)*('입력값'!C60*100)/IF(('입력값'!C60*100)=0,1,'입력값'!C60*100) | T20: =MIN(MAX(T16-('입력값'!C9*100+'입력값'!C58*100+'입력값'!C59*100+'입력값'!C61*100+'입력값'!C62*100),0),'입력값'!C60*100)*('입력값'!C60*100)/IF(('입력값'!C60*100)=0,1,'입력값'!C60*100) | U20: =MIN(MAX(U16-('입력값'!C9*100+'입력값'!C58*100+'입력값'!C59*100+'입력값'!C61*100+'입력값'!C62*100),0),'입력값'!C60*100)*('입력값'!C60*100)/IF(('입력값'!C60*100)=0,1,'입력값'!C60*100) | V20: =MIN(MAX(V16-('입력값'!C9*100+'입력값'!C58*100+'입력값'!C59*100+'입력값'!C61*100+'입력값'!C62*100),0),'입력값'!C60*100)*('입력값'!C60*100)/IF(('입력값'!C60*100)=0,1,'입력값'!C60*100) | W20: =MIN(MAX(W16-('입력값'!C9*100+'입력값'!C58*100+'입력값'!C59*100+'입력값'!C61*100+'입력값'!C62*100),0),'입력값'!C60*100)*('입력값'!C60*100)/IF(('입력값'!C60*100)=0,1,'입력값'!C60*100) | X20: =MIN(MAX(X16-('입력값'!C9*100+'입력값'!C58*100+'입력값'!C59*100+'입력값'!C61*100+'입력값'!C62*100),0),'입력값'!C60*100)*('입력값'!C60*100)/IF(('입력값'!C60*100)=0,1,'입력값'!C60*100) | Y20: =MIN(MAX(Y16-('입력값'!C9*100+'입력값'!C58*100+'입력값'!C59*100+'입력값'!C61*100+'입력값'!C62*100),0),'입력값'!C60*100)*('입력값'!C60*100)/IF(('입력값'!C60*100)=0,1,'입력값'!C60*100) | Z20: =MIN(MAX(Z16-('입력값'!C9*100+'입력값'!C58*100+'입력값'!C59*100+'입력값'!C61*100+'입력값'!C62*100),0),'입력값'!C60*100)*('입력값'!C60*100)/IF(('입력값'!C60*100)=0,1,'입력값'!C60*100) | AA20: =MIN(MAX(AA16-('입력값'!C9*100+'입력값'!C58*100+'입력값'!C59*100+'입력값'!C61*100+'입력값'!C62*100),0),'입력값'!C60*100)*('입력값'!C60*100)/IF(('입력값'!C60*100)=0,1,'입력값'!C60*100) | AB20: =MIN(MAX(AB16-('입력값'!C9*100+'입력값'!C58*100+'입력값'!C59*100+'입력값'!C61*100+'입력값'!C62*100),0),'입력값'!C60*100)*('입력값'!C60*100)/IF(('입력값'!C60*100)=0,1,'입력값'!C60*100) | AC20: =MIN(MAX(AC16-('입력값'!C9*100+'입력값'!C58*100+'입력값'!C59*100+'입력값'!C61*100+'입력값'!C62*100),0),'입력값'!C60*100)*('입력값'!C60*100)/IF(('입력값'!C60*100)=0,1,'입력값'!C60*100) | AD20: =MIN(MAX(AD16-('입력값'!C9*100+'입력값'!C58*100+'입력값'!C59*100+'입력값'!C61*100+'입력값'!C62*100),0),'입력값'!C60*100)*('입력값'!C60*100)/IF(('입력값'!C60*100)=0,1,'입력값'!C60*100) | AE20: =MIN(MAX(AE16-('입력값'!C9*100+'입력값'!C58*100+'입력값'!C59*100+'입력값'!C61*100+'입력값'!C62*100),0),'입력값'!C60*100)*('입력값'!C60*100)/IF(('입력값'!C60*100)=0,1,'입력값'!C60*100) | AF20: =MIN(MAX(AF16-('입력값'!C9*100+'입력값'!C58*100+'입력값'!C59*100+'입력값'!C61*100+'입력값'!C62*100),0),'입력값'!C60*100)*('입력값'!C60*100)/IF(('입력값'!C60*100)=0,1,'입력값'!C60*100) | AG20: =MIN(MAX(AG16-('입력값'!C9*100+'입력값'!C58*100+'입력값'!C59*100+'입력값'!C61*100+'입력값'!C62*100),0),'입력값'!C60*100)*('입력값'!C60*100)/IF(('입력값'!C60*100)=0,1,'입력값'!C60*100) | AH20: =MIN(MAX(AH16-('입력값'!C9*100+'입력값'!C58*100+'입력값'!C59*100+'입력값'!C61*100+'입력값'!C62*100),0),'입력값'!C60*100)*('입력값'!C60*100)/IF(('입력값'!C60*100)=0,1,'입력값'!C60*100) | AI20: =MIN(MAX(AI16-('입력값'!C9*100+'입력값'!C58*100+'입력값'!C59*100+'입력값'!C61*100+'입력값'!C62*100),0),'입력값'!C60*100)*('입력값'!C60*100)/IF(('입력값'!C60*100)=0,1,'입력값'!C60*100) | AJ20: =MIN(MAX(AJ16-('입력값'!C9*100+'입력값'!C58*100+'입력값'!C59*100+'입력값'!C61*100+'입력값'!C62*100),0),'입력값'!C60*100)*('입력값'!C60*100)/IF(('입력값'!C60*100)=0,1,'입력값'!C60*100) | AK20: =MIN(MAX(AK16-('입력값'!C9*100+'입력값'!C58*100+'입력값'!C59*100+'입력값'!C61*100+'입력값'!C62*100),0),'입력값'!C60*100)*('입력값'!C60*100)/IF(('입력값'!C60*100)=0,1,'입력값'!C60*100) | AL20: =MIN(MAX(AL16-('입력값'!C9*100+'입력값'!C58*100+'입력값'!C59*100+'입력값'!C61*100+'입력값'!C62*100),0),'입력값'!C60*100)*('입력값'!C60*100)/IF(('입력값'!C60*100)=0,1,'입력값'!C60*100) | AM20: =MIN(MAX(AM16-('입력값'!C9*100+'입력값'!C58*100+'입력값'!C59*100+'입력값'!C61*100+'입력값'!C62*100),0),'입력값'!C60*100)*('입력값'!C60*100)/IF(('입력값'!C60*100)=0,1,'입력값'!C60*100) | AN20: =MIN(MAX(AN16-('입력값'!C9*100+'입력값'!C58*100+'입력값'!C59*100+'입력값'!C61*100+'입력값'!C62*100),0),'입력값'!C60*100)*('입력값'!C60*100)/IF(('입력값'!C60*100)=0,1,'입력값'!C60*100) | AO20: =MIN(MAX(AO16-('입력값'!C9*100+'입력값'!C58*100+'입력값'!C59*100+'입력값'!C61*100+'입력값'!C62*100),0),'입력값'!C60*100)*('입력값'!C60*100)/IF(('입력값'!C60*100)=0,1,'입력값'!C60*100) | AP20: =MIN(MAX(AP16-('입력값'!C9*100+'입력값'!C58*100+'입력값'!C59*100+'입력값'!C61*100+'입력값'!C62*100),0),'입력값'!C60*100)*('입력값'!C60*100)/IF(('입력값'!C60*100)=0,1,'입력값'!C60*100) | AQ20: =MIN(MAX(AQ16-('입력값'!C9*100+'입력값'!C58*100+'입력값'!C59*100+'입력값'!C61*100+'입력값'!C62*100),0),'입력값'!C60*100)*('입력값'!C60*100)/IF(('입력값'!C60*100)=0,1,'입력값'!C60*100) | AR20: =MIN(MAX(AR16-('입력값'!C9*100+'입력값'!C58*100+'입력값'!C59*100+'입력값'!C61*100+'입력값'!C62*100),0),'입력값'!C60*100)*('입력값'!C60*100)/IF(('입력값'!C60*100)=0,1,'입력값'!C60*100) | AS20: =MIN(MAX(AS16-('입력값'!C9*100+'입력값'!C58*100+'입력값'!C59*100+'입력값'!C61*100+'입력값'!C62*100),0),'입력값'!C60*100)*('입력값'!C60*100)/IF(('입력값'!C60*100)=0,1,'입력값'!C60*100) | AT20: =MIN(MAX(AT16-('입력값'!C9*100+'입력값'!C58*100+'입력값'!C59*100+'입력값'!C61*100+'입력값'!C62*100),0),'입력값'!C60*100)*('입력값'!C60*100)/IF(('입력값'!C60*100)=0,1,'입력값'!C60*100) | AU20: =MIN(MAX(AU16-('입력값'!C9*100+'입력값'!C58*100+'입력값'!C59*100+'입력값'!C61*100+'입력값'!C62*100),0),'입력값'!C60*100)*('입력값'!C60*100)/IF(('입력값'!C60*100)=0,1,'입력값'!C60*100) | AV20: =MIN(MAX(AV16-('입력값'!C9*100+'입력값'!C58*100+'입력값'!C59*100+'입력값'!C61*100+'입력값'!C62*100),0),'입력값'!C60*100)*('입력값'!C60*100)/IF(('입력값'!C60*100)=0,1,'입력값'!C60*100) | AW20: =MIN(MAX(AW16-('입력값'!C9*100+'입력값'!C58*100+'입력값'!C59*100+'입력값'!C61*100+'입력값'!C62*100),0),'입력값'!C60*100)*('입력값'!C60*100)/IF(('입력값'!C60*100)=0,1,'입력값'!C60*100) | AX20: =MIN(MAX(AX16-('입력값'!C9*100+'입력값'!C58*100+'입력값'!C59*100+'입력값'!C61*100+'입력값'!C62*100),0),'입력값'!C60*100)*('입력값'!C60*100)/IF(('입력값'!C60*100)=0,1,'입력값'!C60*100) | AY20: =MIN(MAX(AY16-('입력값'!C9*100+'입력값'!C58*100+'입력값'!C59*100+'입력값'!C61*100+'입력값'!C62*100),0),'입력값'!C60*100)*('입력값'!C60*100)/IF(('입력값'!C60*100)=0,1,'입력값'!C60*100) | AZ20: =MIN(MAX(AZ16-('입력값'!C9*100+'입력값'!C58*100+'입력값'!C59*100+'입력값'!C61*100+'입력값'!C62*100),0),'입력값'!C60*100)*('입력값'!C60*100)/IF(('입력값'!C60*100)=0,1,'입력값'!C60*100) | BA20: =MIN(MAX(BA16-('입력값'!C9*100+'입력값'!C58*100+'입력값'!C59*100+'입력값'!C61*100+'입력값'!C62*100),0),'입력값'!C60*100)*('입력값'!C60*100)/IF(('입력값'!C60*100)=0,1,'입력값'!C60*100) | BB20: =MIN(MAX(BB16-('입력값'!C9*100+'입력값'!C58*100+'입력값'!C59*100+'입력값'!C61*100+'입력값'!C62*100),0),'입력값'!C60*100)*('입력값'!C60*100)/IF(('입력값'!C60*100)=0,1,'입력값'!C60*100) | BC20: =MIN(MAX(BC16-('입력값'!C9*100+'입력값'!C58*100+'입력값'!C59*100+'입력값'!C61*100+'입력값'!C62*100),0),'입력값'!C60*100)*('입력값'!C60*100)/IF(('입력값'!C60*100)=0,1,'입력값'!C60*100) | BD20: =MIN(MAX(BD16-('입력값'!C9*100+'입력값'!C58*100+'입력값'!C59*100+'입력값'!C61*100+'입력값'!C62*100),0),'입력값'!C60*100)*('입력값'!C60*100)/IF(('입력값'!C60*100)=0,1,'입력값'!C60*100) | BE20: =MIN(MAX(BE16-('입력값'!C9*100+'입력값'!C58*100+'입력값'!C59*100+'입력값'!C61*100+'입력값'!C62*100),0),'입력값'!C60*100)*('입력값'!C60*100)/IF(('입력값'!C60*100)=0,1,'입력값'!C60*100) | BF20: =MIN(MAX(BF16-('입력값'!C9*100+'입력값'!C58*100+'입력값'!C59*100+'입력값'!C61*100+'입력값'!C62*100),0),'입력값'!C60*100)*('입력값'!C60*100)/IF(('입력값'!C60*100)=0,1,'입력값'!C60*100) | BG20: =MIN(MAX(BG16-('입력값'!C9*100+'입력값'!C58*100+'입력값'!C59*100+'입력값'!C61*100+'입력값'!C62*100),0),'입력값'!C60*100)*('입력값'!C60*100)/IF(('입력값'!C60*100)=0,1,'입력값'!C60*100) | BH20: =MIN(MAX(BH16-('입력값'!C9*100+'입력값'!C58*100+'입력값'!C59*100+'입력값'!C61*100+'입력값'!C62*100),0),'입력값'!C60*100)*('입력값'!C60*100)/IF(('입력값'!C60*100)=0,1,'입력값'!C60*100) | BI20: =MIN(MAX(BI16-('입력값'!C9*100+'입력값'!C58*100+'입력값'!C59*100+'입력값'!C61*100+'입력값'!C62*100),0),'입력값'!C60*100)*('입력값'!C60*100)/IF(('입력값'!C60*100)=0,1,'입력값'!C60*100) | BJ20: =MIN(MAX(BJ16-('입력값'!C9*100+'입력값'!C58*100+'입력값'!C59*100+'입력값'!C61*100+'입력값'!C62*100),0),'입력값'!C60*100)*('입력값'!C60*100)/IF(('입력값'!C60*100)=0,1,'입력값'!C60*100) | BK20: =MIN(MAX(BK16-('입력값'!C9*100+'입력값'!C58*100+'입력값'!C59*100+'입력값'!C61*100+'입력값'!C62*100),0),'입력값'!C60*100)*('입력값'!C60*100)/IF(('입력값'!C60*100)=0,1,'입력값'!C60*100) | BL20: =MIN(MAX(BL16-('입력값'!C9*100+'입력값'!C58*100+'입력값'!C59*100+'입력값'!C61*100+'입력값'!C62*100),0),'입력값'!C60*100)*('입력값'!C60*100)/IF(('입력값'!C60*100)=0,1,'입력값'!C60*100) | BM20: =MIN(MAX(BM16-('입력값'!C9*100+'입력값'!C58*100+'입력값'!C59*100+'입력값'!C61*100+'입력값'!C62*100),0),'입력값'!C60*100)*('입력값'!C60*100)/IF(('입력값'!C60*100)=0,1,'입력값'!C60*100) | BN20: =MIN(MAX(BN16-('입력값'!C9*100+'입력값'!C58*100+'입력값'!C59*100+'입력값'!C61*100+'입력값'!C62*100),0),'입력값'!C60*100)*('입력값'!C60*100)/IF(('입력값'!C60*100)=0,1,'입력값'!C60*100) | BO20: =MIN(MAX(BO16-('입력값'!C9*100+'입력값'!C58*100+'입력값'!C59*100+'입력값'!C61*100+'입력값'!C62*100),0),'입력값'!C60*100)*('입력값'!C60*100)/IF(('입력값'!C60*100)=0,1,'입력값'!C60*100) | BP20: =MIN(MAX(BP16-('입력값'!C9*100+'입력값'!C58*100+'입력값'!C59*100+'입력값'!C61*100+'입력값'!C62*100),0),'입력값'!C60*100)*('입력값'!C60*100)/IF(('입력값'!C60*100)=0,1,'입력값'!C60*100) | BQ20: =MIN(MAX(BQ16-('입력값'!C9*100+'입력값'!C58*100+'입력값'!C59*100+'입력값'!C61*100+'입력값'!C62*100),0),'입력값'!C60*100)*('입력값'!C60*100)/IF(('입력값'!C60*100)=0,1,'입력값'!C60*100) | BR20: =MIN(MAX(BR16-('입력값'!C9*100+'입력값'!C58*100+'입력값'!C59*100+'입력값'!C61*100+'입력값'!C62*100),0),'입력값'!C60*100)*('입력값'!C60*100)/IF(('입력값'!C60*100)=0,1,'입력값'!C60*100) | BS20: =MIN(MAX(BS16-('입력값'!C9*100+'입력값'!C58*100+'입력값'!C59*100+'입력값'!C61*100+'입력값'!C62*100),0),'입력값'!C60*100)*('입력값'!C60*100)/IF(('입력값'!C60*100)=0,1,'입력값'!C60*100) | BT20: =MIN(MAX(BT16-('입력값'!C9*100+'입력값'!C58*100+'입력값'!C59*100+'입력값'!C61*100+'입력값'!C62*100),0),'입력값'!C60*100)*('입력값'!C60*100)/IF(('입력값'!C60*100)=0,1,'입력값'!C60*100) | BU20: =MIN(MAX(BU16-('입력값'!C9*100+'입력값'!C58*100+'입력값'!C59*100+'입력값'!C61*100+'입력값'!C62*100),0),'입력값'!C60*100)*('입력값'!C60*100)/IF(('입력값'!C60*100)=0,1,'입력값'!C60*100) | BV20: =MIN(MAX(BV16-('입력값'!C9*100+'입력값'!C58*100+'입력값'!C59*100+'입력값'!C61*100+'입력값'!C62*100),0),'입력값'!C60*100)*('입력값'!C60*100)/IF(('입력값'!C60*100)=0,1,'입력값'!C60*100) | BW20: =MIN(MAX(BW16-('입력값'!C9*100+'입력값'!C58*100+'입력값'!C59*100+'입력값'!C61*100+'입력값'!C62*100),0),'입력값'!C60*100)*('입력값'!C60*100)/IF(('입력값'!C60*100)=0,1,'입력값'!C60*100) | BX20: =MIN(MAX(BX16-('입력값'!C9*100+'입력값'!C58*100+'입력값'!C59*100+'입력값'!C61*100+'입력값'!C62*100),0),'입력값'!C60*100)*('입력값'!C60*100)/IF(('입력값'!C60*100)=0,1,'입력값'!C60*100) | BY20: =MIN(MAX(BY16-('입력값'!C9*100+'입력값'!C58*100+'입력값'!C59*100+'입력값'!C61*100+'입력값'!C62*100),0),'입력값'!C60*100)*('입력값'!C60*100)/IF(('입력값'!C60*100)=0,1,'입력값'!C60*100) | BZ20: =MIN(MAX(BZ16-('입력값'!C9*100+'입력값'!C58*100+'입력값'!C59*100+'입력값'!C61*100+'입력값'!C62*100),0),'입력값'!C60*100)*('입력값'!C60*100)/IF(('입력값'!C60*100)=0,1,'입력값'!C60*100) | CA20: =MIN(MAX(CA16-('입력값'!C9*100+'입력값'!C58*100+'입력값'!C59*100+'입력값'!C61*100+'입력값'!C62*100),0),'입력값'!C60*100)*('입력값'!C60*100)/IF(('입력값'!C60*100)=0,1,'입력값'!C60*100) | CB20: =MIN(MAX(CB16-('입력값'!C9*100+'입력값'!C58*100+'입력값'!C59*100+'입력값'!C61*100+'입력값'!C62*100),0),'입력값'!C60*100)*('입력값'!C60*100)/IF(('입력값'!C60*100)=0,1,'입력값'!C60*100) | CC20: =MIN(MAX(CC16-('입력값'!C9*100+'입력값'!C58*100+'입력값'!C59*100+'입력값'!C61*100+'입력값'!C62*100),0),'입력값'!C60*100)*('입력값'!C60*100)/IF(('입력값'!C60*100)=0,1,'입력값'!C60*100) | CD20: =MIN(MAX(CD16-('입력값'!C9*100+'입력값'!C58*100+'입력값'!C59*100+'입력값'!C61*100+'입력값'!C62*100),0),'입력값'!C60*100)*('입력값'!C60*100)/IF(('입력값'!C60*100)=0,1,'입력값'!C60*100) | CE20: =MIN(MAX(CE16-('입력값'!C9*100+'입력값'!C58*100+'입력값'!C59*100+'입력값'!C61*100+'입력값'!C62*100),0),'입력값'!C60*100)*('입력값'!C60*100)/IF(('입력값'!C60*100)=0,1,'입력값'!C60*100) | CF20: =MIN(MAX(CF16-('입력값'!C9*100+'입력값'!C58*100+'입력값'!C59*100+'입력값'!C61*100+'입력값'!C62*100),0),'입력값'!C60*100)*('입력값'!C60*100)/IF(('입력값'!C60*100)=0,1,'입력값'!C60*100) | CG20: =MIN(MAX(CG16-('입력값'!C9*100+'입력값'!C58*100+'입력값'!C59*100+'입력값'!C61*100+'입력값'!C62*100),0),'입력값'!C60*100)*('입력값'!C60*100)/IF(('입력값'!C60*100)=0,1,'입력값'!C60*100) | CH20: =MIN(MAX(CH16-('입력값'!C9*100+'입력값'!C58*100+'입력값'!C59*100+'입력값'!C61*100+'입력값'!C62*100),0),'입력값'!C60*100)*('입력값'!C60*100)/IF(('입력값'!C60*100)=0,1,'입력값'!C60*100) | CI20: =MIN(MAX(CI16-('입력값'!C9*100+'입력값'!C58*100+'입력값'!C59*100+'입력값'!C61*100+'입력값'!C62*100),0),'입력값'!C60*100)*('입력값'!C60*100)/IF(('입력값'!C60*100)=0,1,'입력값'!C60*100) | CJ20: =MIN(MAX(CJ16-('입력값'!C9*100+'입력값'!C58*100+'입력값'!C59*100+'입력값'!C61*100+'입력값'!C62*100),0),'입력값'!C60*100)*('입력값'!C60*100)/IF(('입력값'!C60*100)=0,1,'입력값'!C60*100) | CK20: =MIN(MAX(CK16-('입력값'!C9*100+'입력값'!C58*100+'입력값'!C59*100+'입력값'!C61*100+'입력값'!C62*100),0),'입력값'!C60*100)*('입력값'!C60*100)/IF(('입력값'!C60*100)=0,1,'입력값'!C60*100) | CL20: =MIN(MAX(CL16-('입력값'!C9*100+'입력값'!C58*100+'입력값'!C59*100+'입력값'!C61*100+'입력값'!C62*100),0),'입력값'!C60*100)*('입력값'!C60*100)/IF(('입력값'!C60*100)=0,1,'입력값'!C60*100)
B21: 선순위D 누적인출 | C21: [KRWm] | E21: =MIN(MAX(E16-('입력값'!C9*100+'입력값'!C58*100+'입력값'!C59*100+'입력값'!C62*100),0),'입력값'!C61*100)*('입력값'!C61*100)/IF(('입력값'!C61*100)=0,1,'입력값'!C61*100) | F21: =MIN(MAX(F16-('입력값'!C9*100+'입력값'!C58*100+'입력값'!C59*100+'입력값'!C62*100),0),'입력값'!C61*100)*('입력값'!C61*100)/IF(('입력값'!C61*100)=0,1,'입력값'!C61*100) | G21: =MIN(MAX(G16-('입력값'!C9*100+'입력값'!C58*100+'입력값'!C59*100+'입력값'!C62*100),0),'입력값'!C61*100)*('입력값'!C61*100)/IF(('입력값'!C61*100)=0,1,'입력값'!C61*100) | H21: =MIN(MAX(H16-('입력값'!C9*100+'입력값'!C58*100+'입력값'!C59*100+'입력값'!C62*100),0),'입력값'!C61*100)*('입력값'!C61*100)/IF(('입력값'!C61*100)=0,1,'입력값'!C61*100) | I21: =MIN(MAX(I16-('입력값'!C9*100+'입력값'!C58*100+'입력값'!C59*100+'입력값'!C62*100),0),'입력값'!C61*100)*('입력값'!C61*100)/IF(('입력값'!C61*100)=0,1,'입력값'!C61*100) | J21: =MIN(MAX(J16-('입력값'!C9*100+'입력값'!C58*100+'입력값'!C59*100+'입력값'!C62*100),0),'입력값'!C61*100)*('입력값'!C61*100)/IF(('입력값'!C61*100)=0,1,'입력값'!C61*100) | K21: =MIN(MAX(K16-('입력값'!C9*100+'입력값'!C58*100+'입력값'!C59*100+'입력값'!C62*100),0),'입력값'!C61*100)*('입력값'!C61*100)/IF(('입력값'!C61*100)=0,1,'입력값'!C61*100) | L21: =MIN(MAX(L16-('입력값'!C9*100+'입력값'!C58*100+'입력값'!C59*100+'입력값'!C62*100),0),'입력값'!C61*100)*('입력값'!C61*100)/IF(('입력값'!C61*100)=0,1,'입력값'!C61*100) | M21: =MIN(MAX(M16-('입력값'!C9*100+'입력값'!C58*100+'입력값'!C59*100+'입력값'!C62*100),0),'입력값'!C61*100)*('입력값'!C61*100)/IF(('입력값'!C61*100)=0,1,'입력값'!C61*100) | N21: =MIN(MAX(N16-('입력값'!C9*100+'입력값'!C58*100+'입력값'!C59*100+'입력값'!C62*100),0),'입력값'!C61*100)*('입력값'!C61*100)/IF(('입력값'!C61*100)=0,1,'입력값'!C61*100) | O21: =MIN(MAX(O16-('입력값'!C9*100+'입력값'!C58*100+'입력값'!C59*100+'입력값'!C62*100),0),'입력값'!C61*100)*('입력값'!C61*100)/IF(('입력값'!C61*100)=0,1,'입력값'!C61*100) | P21: =MIN(MAX(P16-('입력값'!C9*100+'입력값'!C58*100+'입력값'!C59*100+'입력값'!C62*100),0),'입력값'!C61*100)*('입력값'!C61*100)/IF(('입력값'!C61*100)=0,1,'입력값'!C61*100) | Q21: =MIN(MAX(Q16-('입력값'!C9*100+'입력값'!C58*100+'입력값'!C59*100+'입력값'!C62*100),0),'입력값'!C61*100)*('입력값'!C61*100)/IF(('입력값'!C61*100)=0,1,'입력값'!C61*100) | R21: =MIN(MAX(R16-('입력값'!C9*100+'입력값'!C58*100+'입력값'!C59*100+'입력값'!C62*100),0),'입력값'!C61*100)*('입력값'!C61*100)/IF(('입력값'!C61*100)=0,1,'입력값'!C61*100) | S21: =MIN(MAX(S16-('입력값'!C9*100+'입력값'!C58*100+'입력값'!C59*100+'입력값'!C62*100),0),'입력값'!C61*100)*('입력값'!C61*100)/IF(('입력값'!C61*100)=0,1,'입력값'!C61*100) | T21: =MIN(MAX(T16-('입력값'!C9*100+'입력값'!C58*100+'입력값'!C59*100+'입력값'!C62*100),0),'입력값'!C61*100)*('입력값'!C61*100)/IF(('입력값'!C61*100)=0,1,'입력값'!C61*100) | U21: =MIN(MAX(U16-('입력값'!C9*100+'입력값'!C58*100+'입력값'!C59*100+'입력값'!C62*100),0),'입력값'!C61*100)*('입력값'!C61*100)/IF(('입력값'!C61*100)=0,1,'입력값'!C61*100) | V21: =MIN(MAX(V16-('입력값'!C9*100+'입력값'!C58*100+'입력값'!C59*100+'입력값'!C62*100),0),'입력값'!C61*100)*('입력값'!C61*100)/IF(('입력값'!C61*100)=0,1,'입력값'!C61*100) | W21: =MIN(MAX(W16-('입력값'!C9*100+'입력값'!C58*100+'입력값'!C59*100+'입력값'!C62*100),0),'입력값'!C61*100)*('입력값'!C61*100)/IF(('입력값'!C61*100)=0,1,'입력값'!C61*100) | X21: =MIN(MAX(X16-('입력값'!C9*100+'입력값'!C58*100+'입력값'!C59*100+'입력값'!C62*100),0),'입력값'!C61*100)*('입력값'!C61*100)/IF(('입력값'!C61*100)=0,1,'입력값'!C61*100) | Y21: =MIN(MAX(Y16-('입력값'!C9*100+'입력값'!C58*100+'입력값'!C59*100+'입력값'!C62*100),0),'입력값'!C61*100)*('입력값'!C61*100)/IF(('입력값'!C61*100)=0,1,'입력값'!C61*100) | Z21: =MIN(MAX(Z16-('입력값'!C9*100+'입력값'!C58*100+'입력값'!C59*100+'입력값'!C62*100),0),'입력값'!C61*100)*('입력값'!C61*100)/IF(('입력값'!C61*100)=0,1,'입력값'!C61*100) | AA21: =MIN(MAX(AA16-('입력값'!C9*100+'입력값'!C58*100+'입력값'!C59*100+'입력값'!C62*100),0),'입력값'!C61*100)*('입력값'!C61*100)/IF(('입력값'!C61*100)=0,1,'입력값'!C61*100) | AB21: =MIN(MAX(AB16-('입력값'!C9*100+'입력값'!C58*100+'입력값'!C59*100+'입력값'!C62*100),0),'입력값'!C61*100)*('입력값'!C61*100)/IF(('입력값'!C61*100)=0,1,'입력값'!C61*100) | AC21: =MIN(MAX(AC16-('입력값'!C9*100+'입력값'!C58*100+'입력값'!C59*100+'입력값'!C62*100),0),'입력값'!C61*100)*('입력값'!C61*100)/IF(('입력값'!C61*100)=0,1,'입력값'!C61*100) | AD21: =MIN(MAX(AD16-('입력값'!C9*100+'입력값'!C58*100+'입력값'!C59*100+'입력값'!C62*100),0),'입력값'!C61*100)*('입력값'!C61*100)/IF(('입력값'!C61*100)=0,1,'입력값'!C61*100) | AE21: =MIN(MAX(AE16-('입력값'!C9*100+'입력값'!C58*100+'입력값'!C59*100+'입력값'!C62*100),0),'입력값'!C61*100)*('입력값'!C61*100)/IF(('입력값'!C61*100)=0,1,'입력값'!C61*100) | AF21: =MIN(MAX(AF16-('입력값'!C9*100+'입력값'!C58*100+'입력값'!C59*100+'입력값'!C62*100),0),'입력값'!C61*100)*('입력값'!C61*100)/IF(('입력값'!C61*100)=0,1,'입력값'!C61*100) | AG21: =MIN(MAX(AG16-('입력값'!C9*100+'입력값'!C58*100+'입력값'!C59*100+'입력값'!C62*100),0),'입력값'!C61*100)*('입력값'!C61*100)/IF(('입력값'!C61*100)=0,1,'입력값'!C61*100) | AH21: =MIN(MAX(AH16-('입력값'!C9*100+'입력값'!C58*100+'입력값'!C59*100+'입력값'!C62*100),0),'입력값'!C61*100)*('입력값'!C61*100)/IF(('입력값'!C61*100)=0,1,'입력값'!C61*100) | AI21: =MIN(MAX(AI16-('입력값'!C9*100+'입력값'!C58*100+'입력값'!C59*100+'입력값'!C62*100),0),'입력값'!C61*100)*('입력값'!C61*100)/IF(('입력값'!C61*100)=0,1,'입력값'!C61*100) | AJ21: =MIN(MAX(AJ16-('입력값'!C9*100+'입력값'!C58*100+'입력값'!C59*100+'입력값'!C62*100),0),'입력값'!C61*100)*('입력값'!C61*100)/IF(('입력값'!C61*100)=0,1,'입력값'!C61*100) | AK21: =MIN(MAX(AK16-('입력값'!C9*100+'입력값'!C58*100+'입력값'!C59*100+'입력값'!C62*100),0),'입력값'!C61*100)*('입력값'!C61*100)/IF(('입력값'!C61*100)=0,1,'입력값'!C61*100) | AL21: =MIN(MAX(AL16-('입력값'!C9*100+'입력값'!C58*100+'입력값'!C59*100+'입력값'!C62*100),0),'입력값'!C61*100)*('입력값'!C61*100)/IF(('입력값'!C61*100)=0,1,'입력값'!C61*100) | AM21: =MIN(MAX(AM16-('입력값'!C9*100+'입력값'!C58*100+'입력값'!C59*100+'입력값'!C62*100),0),'입력값'!C61*100)*('입력값'!C61*100)/IF(('입력값'!C61*100)=0,1,'입력값'!C61*100) | AN21: =MIN(MAX(AN16-('입력값'!C9*100+'입력값'!C58*100+'입력값'!C59*100+'입력값'!C62*100),0),'입력값'!C61*100)*('입력값'!C61*100)/IF(('입력값'!C61*100)=0,1,'입력값'!C61*100) | AO21: =MIN(MAX(AO16-('입력값'!C9*100+'입력값'!C58*100+'입력값'!C59*100+'입력값'!C62*100),0),'입력값'!C61*100)*('입력값'!C61*100)/IF(('입력값'!C61*100)=0,1,'입력값'!C61*100) | AP21: =MIN(MAX(AP16-('입력값'!C9*100+'입력값'!C58*100+'입력값'!C59*100+'입력값'!C62*100),0),'입력값'!C61*100)*('입력값'!C61*100)/IF(('입력값'!C61*100)=0,1,'입력값'!C61*100) | AQ21: =MIN(MAX(AQ16-('입력값'!C9*100+'입력값'!C58*100+'입력값'!C59*100+'입력값'!C62*100),0),'입력값'!C61*100)*('입력값'!C61*100)/IF(('입력값'!C61*100)=0,1,'입력값'!C61*100) | AR21: =MIN(MAX(AR16-('입력값'!C9*100+'입력값'!C58*100+'입력값'!C59*100+'입력값'!C62*100),0),'입력값'!C61*100)*('입력값'!C61*100)/IF(('입력값'!C61*100)=0,1,'입력값'!C61*100) | AS21: =MIN(MAX(AS16-('입력값'!C9*100+'입력값'!C58*100+'입력값'!C59*100+'입력값'!C62*100),0),'입력값'!C61*100)*('입력값'!C61*100)/IF(('입력값'!C61*100)=0,1,'입력값'!C61*100) | AT21: =MIN(MAX(AT16-('입력값'!C9*100+'입력값'!C58*100+'입력값'!C59*100+'입력값'!C62*100),0),'입력값'!C61*100)*('입력값'!C61*100)/IF(('입력값'!C61*100)=0,1,'입력값'!C61*100) | AU21: =MIN(MAX(AU16-('입력값'!C9*100+'입력값'!C58*100+'입력값'!C59*100+'입력값'!C62*100),0),'입력값'!C61*100)*('입력값'!C61*100)/IF(('입력값'!C61*100)=0,1,'입력값'!C61*100) | AV21: =MIN(MAX(AV16-('입력값'!C9*100+'입력값'!C58*100+'입력값'!C59*100+'입력값'!C62*100),0),'입력값'!C61*100)*('입력값'!C61*100)/IF(('입력값'!C61*100)=0,1,'입력값'!C61*100) | AW21: =MIN(MAX(AW16-('입력값'!C9*100+'입력값'!C58*100+'입력값'!C59*100+'입력값'!C62*100),0),'입력값'!C61*100)*('입력값'!C61*100)/IF(('입력값'!C61*100)=0,1,'입력값'!C61*100) | AX21: =MIN(MAX(AX16-('입력값'!C9*100+'입력값'!C58*100+'입력값'!C59*100+'입력값'!C62*100),0),'입력값'!C61*100)*('입력값'!C61*100)/IF(('입력값'!C61*100)=0,1,'입력값'!C61*100) | AY21: =MIN(MAX(AY16-('입력값'!C9*100+'입력값'!C58*100+'입력값'!C59*100+'입력값'!C62*100),0),'입력값'!C61*100)*('입력값'!C61*100)/IF(('입력값'!C61*100)=0,1,'입력값'!C61*100) | AZ21: =MIN(MAX(AZ16-('입력값'!C9*100+'입력값'!C58*100+'입력값'!C59*100+'입력값'!C62*100),0),'입력값'!C61*100)*('입력값'!C61*100)/IF(('입력값'!C61*100)=0,1,'입력값'!C61*100) | BA21: =MIN(MAX(BA16-('입력값'!C9*100+'입력값'!C58*100+'입력값'!C59*100+'입력값'!C62*100),0),'입력값'!C61*100)*('입력값'!C61*100)/IF(('입력값'!C61*100)=0,1,'입력값'!C61*100) | BB21: =MIN(MAX(BB16-('입력값'!C9*100+'입력값'!C58*100+'입력값'!C59*100+'입력값'!C62*100),0),'입력값'!C61*100)*('입력값'!C61*100)/IF(('입력값'!C61*100)=0,1,'입력값'!C61*100) | BC21: =MIN(MAX(BC16-('입력값'!C9*100+'입력값'!C58*100+'입력값'!C59*100+'입력값'!C62*100),0),'입력값'!C61*100)*('입력값'!C61*100)/IF(('입력값'!C61*100)=0,1,'입력값'!C61*100) | BD21: =MIN(MAX(BD16-('입력값'!C9*100+'입력값'!C58*100+'입력값'!C59*100+'입력값'!C62*100),0),'입력값'!C61*100)*('입력값'!C61*100)/IF(('입력값'!C61*100)=0,1,'입력값'!C61*100) | BE21: =MIN(MAX(BE16-('입력값'!C9*100+'입력값'!C58*100+'입력값'!C59*100+'입력값'!C62*100),0),'입력값'!C61*100)*('입력값'!C61*100)/IF(('입력값'!C61*100)=0,1,'입력값'!C61*100) | BF21: =MIN(MAX(BF16-('입력값'!C9*100+'입력값'!C58*100+'입력값'!C59*100+'입력값'!C62*100),0),'입력값'!C61*100)*('입력값'!C61*100)/IF(('입력값'!C61*100)=0,1,'입력값'!C61*100) | BG21: =MIN(MAX(BG16-('입력값'!C9*100+'입력값'!C58*100+'입력값'!C59*100+'입력값'!C62*100),0),'입력값'!C61*100)*('입력값'!C61*100)/IF(('입력값'!C61*100)=0,1,'입력값'!C61*100) | BH21: =MIN(MAX(BH16-('입력값'!C9*100+'입력값'!C58*100+'입력값'!C59*100+'입력값'!C62*100),0),'입력값'!C61*100)*('입력값'!C61*100)/IF(('입력값'!C61*100)=0,1,'입력값'!C61*100) | BI21: =MIN(MAX(BI16-('입력값'!C9*100+'입력값'!C58*100+'입력값'!C59*100+'입력값'!C62*100),0),'입력값'!C61*100)*('입력값'!C61*100)/IF(('입력값'!C61*100)=0,1,'입력값'!C61*100) | BJ21: =MIN(MAX(BJ16-('입력값'!C9*100+'입력값'!C58*100+'입력값'!C59*100+'입력값'!C62*100),0),'입력값'!C61*100)*('입력값'!C61*100)/IF(('입력값'!C61*100)=0,1,'입력값'!C61*100) | BK21: =MIN(MAX(BK16-('입력값'!C9*100+'입력값'!C58*100+'입력값'!C59*100+'입력값'!C62*100),0),'입력값'!C61*100)*('입력값'!C61*100)/IF(('입력값'!C61*100)=0,1,'입력값'!C61*100) | BL21: =MIN(MAX(BL16-('입력값'!C9*100+'입력값'!C58*100+'입력값'!C59*100+'입력값'!C62*100),0),'입력값'!C61*100)*('입력값'!C61*100)/IF(('입력값'!C61*100)=0,1,'입력값'!C61*100) | BM21: =MIN(MAX(BM16-('입력값'!C9*100+'입력값'!C58*100+'입력값'!C59*100+'입력값'!C62*100),0),'입력값'!C61*100)*('입력값'!C61*100)/IF(('입력값'!C61*100)=0,1,'입력값'!C61*100) | BN21: =MIN(MAX(BN16-('입력값'!C9*100+'입력값'!C58*100+'입력값'!C59*100+'입력값'!C62*100),0),'입력값'!C61*100)*('입력값'!C61*100)/IF(('입력값'!C61*100)=0,1,'입력값'!C61*100) | BO21: =MIN(MAX(BO16-('입력값'!C9*100+'입력값'!C58*100+'입력값'!C59*100+'입력값'!C62*100),0),'입력값'!C61*100)*('입력값'!C61*100)/IF(('입력값'!C61*100)=0,1,'입력값'!C61*100) | BP21: =MIN(MAX(BP16-('입력값'!C9*100+'입력값'!C58*100+'입력값'!C59*100+'입력값'!C62*100),0),'입력값'!C61*100)*('입력값'!C61*100)/IF(('입력값'!C61*100)=0,1,'입력값'!C61*100) | BQ21: =MIN(MAX(BQ16-('입력값'!C9*100+'입력값'!C58*100+'입력값'!C59*100+'입력값'!C62*100),0),'입력값'!C61*100)*('입력값'!C61*100)/IF(('입력값'!C61*100)=0,1,'입력값'!C61*100) | BR21: =MIN(MAX(BR16-('입력값'!C9*100+'입력값'!C58*100+'입력값'!C59*100+'입력값'!C62*100),0),'입력값'!C61*100)*('입력값'!C61*100)/IF(('입력값'!C61*100)=0,1,'입력값'!C61*100) | BS21: =MIN(MAX(BS16-('입력값'!C9*100+'입력값'!C58*100+'입력값'!C59*100+'입력값'!C62*100),0),'입력값'!C61*100)*('입력값'!C61*100)/IF(('입력값'!C61*100)=0,1,'입력값'!C61*100) | BT21: =MIN(MAX(BT16-('입력값'!C9*100+'입력값'!C58*100+'입력값'!C59*100+'입력값'!C62*100),0),'입력값'!C61*100)*('입력값'!C61*100)/IF(('입력값'!C61*100)=0,1,'입력값'!C61*100) | BU21: =MIN(MAX(BU16-('입력값'!C9*100+'입력값'!C58*100+'입력값'!C59*100+'입력값'!C62*100),0),'입력값'!C61*100)*('입력값'!C61*100)/IF(('입력값'!C61*100)=0,1,'입력값'!C61*100) | BV21: =MIN(MAX(BV16-('입력값'!C9*100+'입력값'!C58*100+'입력값'!C59*100+'입력값'!C62*100),0),'입력값'!C61*100)*('입력값'!C61*100)/IF(('입력값'!C61*100)=0,1,'입력값'!C61*100) | BW21: =MIN(MAX(BW16-('입력값'!C9*100+'입력값'!C58*100+'입력값'!C59*100+'입력값'!C62*100),0),'입력값'!C61*100)*('입력값'!C61*100)/IF(('입력값'!C61*100)=0,1,'입력값'!C61*100) | BX21: =MIN(MAX(BX16-('입력값'!C9*100+'입력값'!C58*100+'입력값'!C59*100+'입력값'!C62*100),0),'입력값'!C61*100)*('입력값'!C61*100)/IF(('입력값'!C61*100)=0,1,'입력값'!C61*100) | BY21: =MIN(MAX(BY16-('입력값'!C9*100+'입력값'!C58*100+'입력값'!C59*100+'입력값'!C62*100),0),'입력값'!C61*100)*('입력값'!C61*100)/IF(('입력값'!C61*100)=0,1,'입력값'!C61*100) | BZ21: =MIN(MAX(BZ16-('입력값'!C9*100+'입력값'!C58*100+'입력값'!C59*100+'입력값'!C62*100),0),'입력값'!C61*100)*('입력값'!C61*100)/IF(('입력값'!C61*100)=0,1,'입력값'!C61*100) | CA21: =MIN(MAX(CA16-('입력값'!C9*100+'입력값'!C58*100+'입력값'!C59*100+'입력값'!C62*100),0),'입력값'!C61*100)*('입력값'!C61*100)/IF(('입력값'!C61*100)=0,1,'입력값'!C61*100) | CB21: =MIN(MAX(CB16-('입력값'!C9*100+'입력값'!C58*100+'입력값'!C59*100+'입력값'!C62*100),0),'입력값'!C61*100)*('입력값'!C61*100)/IF(('입력값'!C61*100)=0,1,'입력값'!C61*100) | CC21: =MIN(MAX(CC16-('입력값'!C9*100+'입력값'!C58*100+'입력값'!C59*100+'입력값'!C62*100),0),'입력값'!C61*100)*('입력값'!C61*100)/IF(('입력값'!C61*100)=0,1,'입력값'!C61*100) | CD21: =MIN(MAX(CD16-('입력값'!C9*100+'입력값'!C58*100+'입력값'!C59*100+'입력값'!C62*100),0),'입력값'!C61*100)*('입력값'!C61*100)/IF(('입력값'!C61*100)=0,1,'입력값'!C61*100) | CE21: =MIN(MAX(CE16-('입력값'!C9*100+'입력값'!C58*100+'입력값'!C59*100+'입력값'!C62*100),0),'입력값'!C61*100)*('입력값'!C61*100)/IF(('입력값'!C61*100)=0,1,'입력값'!C61*100) | CF21: =MIN(MAX(CF16-('입력값'!C9*100+'입력값'!C58*100+'입력값'!C59*100+'입력값'!C62*100),0),'입력값'!C61*100)*('입력값'!C61*100)/IF(('입력값'!C61*100)=0,1,'입력값'!C61*100) | CG21: =MIN(MAX(CG16-('입력값'!C9*100+'입력값'!C58*100+'입력값'!C59*100+'입력값'!C62*100),0),'입력값'!C61*100)*('입력값'!C61*100)/IF(('입력값'!C61*100)=0,1,'입력값'!C61*100) | CH21: =MIN(MAX(CH16-('입력값'!C9*100+'입력값'!C58*100+'입력값'!C59*100+'입력값'!C62*100),0),'입력값'!C61*100)*('입력값'!C61*100)/IF(('입력값'!C61*100)=0,1,'입력값'!C61*100) | CI21: =MIN(MAX(CI16-('입력값'!C9*100+'입력값'!C58*100+'입력값'!C59*100+'입력값'!C62*100),0),'입력값'!C61*100)*('입력값'!C61*100)/IF(('입력값'!C61*100)=0,1,'입력값'!C61*100) | CJ21: =MIN(MAX(CJ16-('입력값'!C9*100+'입력값'!C58*100+'입력값'!C59*100+'입력값'!C62*100),0),'입력값'!C61*100)*('입력값'!C61*100)/IF(('입력값'!C61*100)=0,1,'입력값'!C61*100) | CK21: =MIN(MAX(CK16-('입력값'!C9*100+'입력값'!C58*100+'입력값'!C59*100+'입력값'!C62*100),0),'입력값'!C61*100)*('입력값'!C61*100)/IF(('입력값'!C61*100)=0,1,'입력값'!C61*100) | CL21: =MIN(MAX(CL16-('입력값'!C9*100+'입력값'!C58*100+'입력값'!C59*100+'입력값'!C62*100),0),'입력값'!C61*100)*('입력값'!C61*100)/IF(('입력값'!C61*100)=0,1,'입력값'!C61*100)
B22: 후순위 누적인출 | C22: [KRWm] | E22: =MIN(MAX(E16-(0),0),'입력값'!C9*100+'입력값'!C62*100)*('입력값'!C62*100)/IF(('입력값'!C9*100+'입력값'!C62*100)=0,1,'입력값'!C9*100+'입력값'!C62*100) | F22: =MIN(MAX(F16-(0),0),'입력값'!C9*100+'입력값'!C62*100)*('입력값'!C62*100)/IF(('입력값'!C9*100+'입력값'!C62*100)=0,1,'입력값'!C9*100+'입력값'!C62*100) | G22: =MIN(MAX(G16-(0),0),'입력값'!C9*100+'입력값'!C62*100)*('입력값'!C62*100)/IF(('입력값'!C9*100+'입력값'!C62*100)=0,1,'입력값'!C9*100+'입력값'!C62*100) | H22: =MIN(MAX(H16-(0),0),'입력값'!C9*100+'입력값'!C62*100)*('입력값'!C62*100)/IF(('입력값'!C9*100+'입력값'!C62*100)=0,1,'입력값'!C9*100+'입력값'!C62*100) | I22: =MIN(MAX(I16-(0),0),'입력값'!C9*100+'입력값'!C62*100)*('입력값'!C62*100)/IF(('입력값'!C9*100+'입력값'!C62*100)=0,1,'입력값'!C9*100+'입력값'!C62*100) | J22: =MIN(MAX(J16-(0),0),'입력값'!C9*100+'입력값'!C62*100)*('입력값'!C62*100)/IF(('입력값'!C9*100+'입력값'!C62*100)=0,1,'입력값'!C9*100+'입력값'!C62*100) | K22: =MIN(MAX(K16-(0),0),'입력값'!C9*100+'입력값'!C62*100)*('입력값'!C62*100)/IF(('입력값'!C9*100+'입력값'!C62*100)=0,1,'입력값'!C9*100+'입력값'!C62*100) | L22: =MIN(MAX(L16-(0),0),'입력값'!C9*100+'입력값'!C62*100)*('입력값'!C62*100)/IF(('입력값'!C9*100+'입력값'!C62*100)=0,1,'입력값'!C9*100+'입력값'!C62*100) | M22: =MIN(MAX(M16-(0),0),'입력값'!C9*100+'입력값'!C62*100)*('입력값'!C62*100)/IF(('입력값'!C9*100+'입력값'!C62*100)=0,1,'입력값'!C9*100+'입력값'!C62*100) | N22: =MIN(MAX(N16-(0),0),'입력값'!C9*100+'입력값'!C62*100)*('입력값'!C62*100)/IF(('입력값'!C9*100+'입력값'!C62*100)=0,1,'입력값'!C9*100+'입력값'!C62*100) | O22: =MIN(MAX(O16-(0),0),'입력값'!C9*100+'입력값'!C62*100)*('입력값'!C62*100)/IF(('입력값'!C9*100+'입력값'!C62*100)=0,1,'입력값'!C9*100+'입력값'!C62*100) | P22: =MIN(MAX(P16-(0),0),'입력값'!C9*100+'입력값'!C62*100)*('입력값'!C62*100)/IF(('입력값'!C9*100+'입력값'!C62*100)=0,1,'입력값'!C9*100+'입력값'!C62*100) | Q22: =MIN(MAX(Q16-(0),0),'입력값'!C9*100+'입력값'!C62*100)*('입력값'!C62*100)/IF(('입력값'!C9*100+'입력값'!C62*100)=0,1,'입력값'!C9*100+'입력값'!C62*100) | R22: =MIN(MAX(R16-(0),0),'입력값'!C9*100+'입력값'!C62*100)*('입력값'!C62*100)/IF(('입력값'!C9*100+'입력값'!C62*100)=0,1,'입력값'!C9*100+'입력값'!C62*100) | S22: =MIN(MAX(S16-(0),0),'입력값'!C9*100+'입력값'!C62*100)*('입력값'!C62*100)/IF(('입력값'!C9*100+'입력값'!C62*100)=0,1,'입력값'!C9*100+'입력값'!C62*100) | T22: =MIN(MAX(T16-(0),0),'입력값'!C9*100+'입력값'!C62*100)*('입력값'!C62*100)/IF(('입력값'!C9*100+'입력값'!C62*100)=0,1,'입력값'!C9*100+'입력값'!C62*100) | U22: =MIN(MAX(U16-(0),0),'입력값'!C9*100+'입력값'!C62*100)*('입력값'!C62*100)/IF(('입력값'!C9*100+'입력값'!C62*100)=0,1,'입력값'!C9*100+'입력값'!C62*100) | V22: =MIN(MAX(V16-(0),0),'입력값'!C9*100+'입력값'!C62*100)*('입력값'!C62*100)/IF(('입력값'!C9*100+'입력값'!C62*100)=0,1,'입력값'!C9*100+'입력값'!C62*100) | W22: =MIN(MAX(W16-(0),0),'입력값'!C9*100+'입력값'!C62*100)*('입력값'!C62*100)/IF(('입력값'!C9*100+'입력값'!C62*100)=0,1,'입력값'!C9*100+'입력값'!C62*100) | X22: =MIN(MAX(X16-(0),0),'입력값'!C9*100+'입력값'!C62*100)*('입력값'!C62*100)/IF(('입력값'!C9*100+'입력값'!C62*100)=0,1,'입력값'!C9*100+'입력값'!C62*100) | Y22: =MIN(MAX(Y16-(0),0),'입력값'!C9*100+'입력값'!C62*100)*('입력값'!C62*100)/IF(('입력값'!C9*100+'입력값'!C62*100)=0,1,'입력값'!C9*100+'입력값'!C62*100) | Z22: =MIN(MAX(Z16-(0),0),'입력값'!C9*100+'입력값'!C62*100)*('입력값'!C62*100)/IF(('입력값'!C9*100+'입력값'!C62*100)=0,1,'입력값'!C9*100+'입력값'!C62*100) | AA22: =MIN(MAX(AA16-(0),0),'입력값'!C9*100+'입력값'!C62*100)*('입력값'!C62*100)/IF(('입력값'!C9*100+'입력값'!C62*100)=0,1,'입력값'!C9*100+'입력값'!C62*100) | AB22: =MIN(MAX(AB16-(0),0),'입력값'!C9*100+'입력값'!C62*100)*('입력값'!C62*100)/IF(('입력값'!C9*100+'입력값'!C62*100)=0,1,'입력값'!C9*100+'입력값'!C62*100) | AC22: =MIN(MAX(AC16-(0),0),'입력값'!C9*100+'입력값'!C62*100)*('입력값'!C62*100)/IF(('입력값'!C9*100+'입력값'!C62*100)=0,1,'입력값'!C9*100+'입력값'!C62*100) | AD22: =MIN(MAX(AD16-(0),0),'입력값'!C9*100+'입력값'!C62*100)*('입력값'!C62*100)/IF(('입력값'!C9*100+'입력값'!C62*100)=0,1,'입력값'!C9*100+'입력값'!C62*100) | AE22: =MIN(MAX(AE16-(0),0),'입력값'!C9*100+'입력값'!C62*100)*('입력값'!C62*100)/IF(('입력값'!C9*100+'입력값'!C62*100)=0,1,'입력값'!C9*100+'입력값'!C62*100) | AF22: =MIN(MAX(AF16-(0),0),'입력값'!C9*100+'입력값'!C62*100)*('입력값'!C62*100)/IF(('입력값'!C9*100+'입력값'!C62*100)=0,1,'입력값'!C9*100+'입력값'!C62*100) | AG22: =MIN(MAX(AG16-(0),0),'입력값'!C9*100+'입력값'!C62*100)*('입력값'!C62*100)/IF(('입력값'!C9*100+'입력값'!C62*100)=0,1,'입력값'!C9*100+'입력값'!C62*100) | AH22: =MIN(MAX(AH16-(0),0),'입력값'!C9*100+'입력값'!C62*100)*('입력값'!C62*100)/IF(('입력값'!C9*100+'입력값'!C62*100)=0,1,'입력값'!C9*100+'입력값'!C62*100) | AI22: =MIN(MAX(AI16-(0),0),'입력값'!C9*100+'입력값'!C62*100)*('입력값'!C62*100)/IF(('입력값'!C9*100+'입력값'!C62*100)=0,1,'입력값'!C9*100+'입력값'!C62*100) | AJ22: =MIN(MAX(AJ16-(0),0),'입력값'!C9*100+'입력값'!C62*100)*('입력값'!C62*100)/IF(('입력값'!C9*100+'입력값'!C62*100)=0,1,'입력값'!C9*100+'입력값'!C62*100) | AK22: =MIN(MAX(AK16-(0),0),'입력값'!C9*100+'입력값'!C62*100)*('입력값'!C62*100)/IF(('입력값'!C9*100+'입력값'!C62*100)=0,1,'입력값'!C9*100+'입력값'!C62*100) | AL22: =MIN(MAX(AL16-(0),0),'입력값'!C9*100+'입력값'!C62*100)*('입력값'!C62*100)/IF(('입력값'!C9*100+'입력값'!C62*100)=0,1,'입력값'!C9*100+'입력값'!C62*100) | AM22: =MIN(MAX(AM16-(0),0),'입력값'!C9*100+'입력값'!C62*100)*('입력값'!C62*100)/IF(('입력값'!C9*100+'입력값'!C62*100)=0,1,'입력값'!C9*100+'입력값'!C62*100) | AN22: =MIN(MAX(AN16-(0),0),'입력값'!C9*100+'입력값'!C62*100)*('입력값'!C62*100)/IF(('입력값'!C9*100+'입력값'!C62*100)=0,1,'입력값'!C9*100+'입력값'!C62*100) | AO22: =MIN(MAX(AO16-(0),0),'입력값'!C9*100+'입력값'!C62*100)*('입력값'!C62*100)/IF(('입력값'!C9*100+'입력값'!C62*100)=0,1,'입력값'!C9*100+'입력값'!C62*100) | AP22: =MIN(MAX(AP16-(0),0),'입력값'!C9*100+'입력값'!C62*100)*('입력값'!C62*100)/IF(('입력값'!C9*100+'입력값'!C62*100)=0,1,'입력값'!C9*100+'입력값'!C62*100) | AQ22: =MIN(MAX(AQ16-(0),0),'입력값'!C9*100+'입력값'!C62*100)*('입력값'!C62*100)/IF(('입력값'!C9*100+'입력값'!C62*100)=0,1,'입력값'!C9*100+'입력값'!C62*100) | AR22: =MIN(MAX(AR16-(0),0),'입력값'!C9*100+'입력값'!C62*100)*('입력값'!C62*100)/IF(('입력값'!C9*100+'입력값'!C62*100)=0,1,'입력값'!C9*100+'입력값'!C62*100) | AS22: =MIN(MAX(AS16-(0),0),'입력값'!C9*100+'입력값'!C62*100)*('입력값'!C62*100)/IF(('입력값'!C9*100+'입력값'!C62*100)=0,1,'입력값'!C9*100+'입력값'!C62*100) | AT22: =MIN(MAX(AT16-(0),0),'입력값'!C9*100+'입력값'!C62*100)*('입력값'!C62*100)/IF(('입력값'!C9*100+'입력값'!C62*100)=0,1,'입력값'!C9*100+'입력값'!C62*100) | AU22: =MIN(MAX(AU16-(0),0),'입력값'!C9*100+'입력값'!C62*100)*('입력값'!C62*100)/IF(('입력값'!C9*100+'입력값'!C62*100)=0,1,'입력값'!C9*100+'입력값'!C62*100) | AV22: =MIN(MAX(AV16-(0),0),'입력값'!C9*100+'입력값'!C62*100)*('입력값'!C62*100)/IF(('입력값'!C9*100+'입력값'!C62*100)=0,1,'입력값'!C9*100+'입력값'!C62*100) | AW22: =MIN(MAX(AW16-(0),0),'입력값'!C9*100+'입력값'!C62*100)*('입력값'!C62*100)/IF(('입력값'!C9*100+'입력값'!C62*100)=0,1,'입력값'!C9*100+'입력값'!C62*100) | AX22: =MIN(MAX(AX16-(0),0),'입력값'!C9*100+'입력값'!C62*100)*('입력값'!C62*100)/IF(('입력값'!C9*100+'입력값'!C62*100)=0,1,'입력값'!C9*100+'입력값'!C62*100) | AY22: =MIN(MAX(AY16-(0),0),'입력값'!C9*100+'입력값'!C62*100)*('입력값'!C62*100)/IF(('입력값'!C9*100+'입력값'!C62*100)=0,1,'입력값'!C9*100+'입력값'!C62*100) | AZ22: =MIN(MAX(AZ16-(0),0),'입력값'!C9*100+'입력값'!C62*100)*('입력값'!C62*100)/IF(('입력값'!C9*100+'입력값'!C62*100)=0,1,'입력값'!C9*100+'입력값'!C62*100) | BA22: =MIN(MAX(BA16-(0),0),'입력값'!C9*100+'입력값'!C62*100)*('입력값'!C62*100)/IF(('입력값'!C9*100+'입력값'!C62*100)=0,1,'입력값'!C9*100+'입력값'!C62*100) | BB22: =MIN(MAX(BB16-(0),0),'입력값'!C9*100+'입력값'!C62*100)*('입력값'!C62*100)/IF(('입력값'!C9*100+'입력값'!C62*100)=0,1,'입력값'!C9*100+'입력값'!C62*100) | BC22: =MIN(MAX(BC16-(0),0),'입력값'!C9*100+'입력값'!C62*100)*('입력값'!C62*100)/IF(('입력값'!C9*100+'입력값'!C62*100)=0,1,'입력값'!C9*100+'입력값'!C62*100) | BD22: =MIN(MAX(BD16-(0),0),'입력값'!C9*100+'입력값'!C62*100)*('입력값'!C62*100)/IF(('입력값'!C9*100+'입력값'!C62*100)=0,1,'입력값'!C9*100+'입력값'!C62*100) | BE22: =MIN(MAX(BE16-(0),0),'입력값'!C9*100+'입력값'!C62*100)*('입력값'!C62*100)/IF(('입력값'!C9*100+'입력값'!C62*100)=0,1,'입력값'!C9*100+'입력값'!C62*100) | BF22: =MIN(MAX(BF16-(0),0),'입력값'!C9*100+'입력값'!C62*100)*('입력값'!C62*100)/IF(('입력값'!C9*100+'입력값'!C62*100)=0,1,'입력값'!C9*100+'입력값'!C62*100) | BG22: =MIN(MAX(BG16-(0),0),'입력값'!C9*100+'입력값'!C62*100)*('입력값'!C62*100)/IF(('입력값'!C9*100+'입력값'!C62*100)=0,1,'입력값'!C9*100+'입력값'!C62*100) | BH22: =MIN(MAX(BH16-(0),0),'입력값'!C9*100+'입력값'!C62*100)*('입력값'!C62*100)/IF(('입력값'!C9*100+'입력값'!C62*100)=0,1,'입력값'!C9*100+'입력값'!C62*100) | BI22: =MIN(MAX(BI16-(0),0),'입력값'!C9*100+'입력값'!C62*100)*('입력값'!C62*100)/IF(('입력값'!C9*100+'입력값'!C62*100)=0,1,'입력값'!C9*100+'입력값'!C62*100) | BJ22: =MIN(MAX(BJ16-(0),0),'입력값'!C9*100+'입력값'!C62*100)*('입력값'!C62*100)/IF(('입력값'!C9*100+'입력값'!C62*100)=0,1,'입력값'!C9*100+'입력값'!C62*100) | BK22: =MIN(MAX(BK16-(0),0),'입력값'!C9*100+'입력값'!C62*100)*('입력값'!C62*100)/IF(('입력값'!C9*100+'입력값'!C62*100)=0,1,'입력값'!C9*100+'입력값'!C62*100) | BL22: =MIN(MAX(BL16-(0),0),'입력값'!C9*100+'입력값'!C62*100)*('입력값'!C62*100)/IF(('입력값'!C9*100+'입력값'!C62*100)=0,1,'입력값'!C9*100+'입력값'!C62*100) | BM22: =MIN(MAX(BM16-(0),0),'입력값'!C9*100+'입력값'!C62*100)*('입력값'!C62*100)/IF(('입력값'!C9*100+'입력값'!C62*100)=0,1,'입력값'!C9*100+'입력값'!C62*100) | BN22: =MIN(MAX(BN16-(0),0),'입력값'!C9*100+'입력값'!C62*100)*('입력값'!C62*100)/IF(('입력값'!C9*100+'입력값'!C62*100)=0,1,'입력값'!C9*100+'입력값'!C62*100) | BO22: =MIN(MAX(BO16-(0),0),'입력값'!C9*100+'입력값'!C62*100)*('입력값'!C62*100)/IF(('입력값'!C9*100+'입력값'!C62*100)=0,1,'입력값'!C9*100+'입력값'!C62*100) | BP22: =MIN(MAX(BP16-(0),0),'입력값'!C9*100+'입력값'!C62*100)*('입력값'!C62*100)/IF(('입력값'!C9*100+'입력값'!C62*100)=0,1,'입력값'!C9*100+'입력값'!C62*100) | BQ22: =MIN(MAX(BQ16-(0),0),'입력값'!C9*100+'입력값'!C62*100)*('입력값'!C62*100)/IF(('입력값'!C9*100+'입력값'!C62*100)=0,1,'입력값'!C9*100+'입력값'!C62*100) | BR22: =MIN(MAX(BR16-(0),0),'입력값'!C9*100+'입력값'!C62*100)*('입력값'!C62*100)/IF(('입력값'!C9*100+'입력값'!C62*100)=0,1,'입력값'!C9*100+'입력값'!C62*100) | BS22: =MIN(MAX(BS16-(0),0),'입력값'!C9*100+'입력값'!C62*100)*('입력값'!C62*100)/IF(('입력값'!C9*100+'입력값'!C62*100)=0,1,'입력값'!C9*100+'입력값'!C62*100) | BT22: =MIN(MAX(BT16-(0),0),'입력값'!C9*100+'입력값'!C62*100)*('입력값'!C62*100)/IF(('입력값'!C9*100+'입력값'!C62*100)=0,1,'입력값'!C9*100+'입력값'!C62*100) | BU22: =MIN(MAX(BU16-(0),0),'입력값'!C9*100+'입력값'!C62*100)*('입력값'!C62*100)/IF(('입력값'!C9*100+'입력값'!C62*100)=0,1,'입력값'!C9*100+'입력값'!C62*100) | BV22: =MIN(MAX(BV16-(0),0),'입력값'!C9*100+'입력값'!C62*100)*('입력값'!C62*100)/IF(('입력값'!C9*100+'입력값'!C62*100)=0,1,'입력값'!C9*100+'입력값'!C62*100) | BW22: =MIN(MAX(BW16-(0),0),'입력값'!C9*100+'입력값'!C62*100)*('입력값'!C62*100)/IF(('입력값'!C9*100+'입력값'!C62*100)=0,1,'입력값'!C9*100+'입력값'!C62*100) | BX22: =MIN(MAX(BX16-(0),0),'입력값'!C9*100+'입력값'!C62*100)*('입력값'!C62*100)/IF(('입력값'!C9*100+'입력값'!C62*100)=0,1,'입력값'!C9*100+'입력값'!C62*100) | BY22: =MIN(MAX(BY16-(0),0),'입력값'!C9*100+'입력값'!C62*100)*('입력값'!C62*100)/IF(('입력값'!C9*100+'입력값'!C62*100)=0,1,'입력값'!C9*100+'입력값'!C62*100) | BZ22: =MIN(MAX(BZ16-(0),0),'입력값'!C9*100+'입력값'!C62*100)*('입력값'!C62*100)/IF(('입력값'!C9*100+'입력값'!C62*100)=0,1,'입력값'!C9*100+'입력값'!C62*100) | CA22: =MIN(MAX(CA16-(0),0),'입력값'!C9*100+'입력값'!C62*100)*('입력값'!C62*100)/IF(('입력값'!C9*100+'입력값'!C62*100)=0,1,'입력값'!C9*100+'입력값'!C62*100) | CB22: =MIN(MAX(CB16-(0),0),'입력값'!C9*100+'입력값'!C62*100)*('입력값'!C62*100)/IF(('입력값'!C9*100+'입력값'!C62*100)=0,1,'입력값'!C9*100+'입력값'!C62*100) | CC22: =MIN(MAX(CC16-(0),0),'입력값'!C9*100+'입력값'!C62*100)*('입력값'!C62*100)/IF(('입력값'!C9*100+'입력값'!C62*100)=0,1,'입력값'!C9*100+'입력값'!C62*100) | CD22: =MIN(MAX(CD16-(0),0),'입력값'!C9*100+'입력값'!C62*100)*('입력값'!C62*100)/IF(('입력값'!C9*100+'입력값'!C62*100)=0,1,'입력값'!C9*100+'입력값'!C62*100) | CE22: =MIN(MAX(CE16-(0),0),'입력값'!C9*100+'입력값'!C62*100)*('입력값'!C62*100)/IF(('입력값'!C9*100+'입력값'!C62*100)=0,1,'입력값'!C9*100+'입력값'!C62*100) | CF22: =MIN(MAX(CF16-(0),0),'입력값'!C9*100+'입력값'!C62*100)*('입력값'!C62*100)/IF(('입력값'!C9*100+'입력값'!C62*100)=0,1,'입력값'!C9*100+'입력값'!C62*100) | CG22: =MIN(MAX(CG16-(0),0),'입력값'!C9*100+'입력값'!C62*100)*('입력값'!C62*100)/IF(('입력값'!C9*100+'입력값'!C62*100)=0,1,'입력값'!C9*100+'입력값'!C62*100) | CH22: =MIN(MAX(CH16-(0),0),'입력값'!C9*100+'입력값'!C62*100)*('입력값'!C62*100)/IF(('입력값'!C9*100+'입력값'!C62*100)=0,1,'입력값'!C9*100+'입력값'!C62*100) | CI22: =MIN(MAX(CI16-(0),0),'입력값'!C9*100+'입력값'!C62*100)*('입력값'!C62*100)/IF(('입력값'!C9*100+'입력값'!C62*100)=0,1,'입력값'!C9*100+'입력값'!C62*100) | CJ22: =MIN(MAX(CJ16-(0),0),'입력값'!C9*100+'입력값'!C62*100)*('입력값'!C62*100)/IF(('입력값'!C9*100+'입력값'!C62*100)=0,1,'입력값'!C9*100+'입력값'!C62*100) | CK22: =MIN(MAX(CK16-(0),0),'입력값'!C9*100+'입력값'!C62*100)*('입력값'!C62*100)/IF(('입력값'!C9*100+'입력값'!C62*100)=0,1,'입력값'!C9*100+'입력값'!C62*100) | CL22: =MIN(MAX(CL16-(0),0),'입력값'!C9*100+'입력값'!C62*100)*('입력값'!C62*100)/IF(('입력값'!C9*100+'입력값'!C62*100)=0,1,'입력값'!C9*100+'입력값'!C62*100)
B25: 트랜치별 인출/상환 + 전체 합계
B27: 구 분 | C27: unit | D27: 합 계 | E27: 2024-06-30 | F27: 2024-09-30 | G27: 2024-12-31 | H27: 2025-03-31 | I27: 2025-06-30 | J27: 2025-09-30 | K27: 2025-12-31 | L27: 2026-03-31 | M27: 2026-06-30 | N27: 2026-09-30 | O27: 2026-12-31 | P27: 2027-03-31 | Q27: 2027-06-30 | R27: 2027-09-30 | S27: 2027-12-31 | T27: 2028-03-31 | U27: 2028-06-30 | V27: 2028-09-30 | W27: 2028-12-31 | X27: 2029-03-31 | Y27: 2029-06-30 | Z27: 2029-09-30 | AA27: 2029-12-31 | AB27: 2030-03-31 | AC27: 2030-06-30 | AD27: 2030-09-30 | AE27: 2030-12-31 | AF27: 2031-03-31 | AG27: 2031-06-30 | AH27: 2031-09-30 | AI27: 2031-12-31 | AJ27: 2032-03-31 | AK27: 2032-06-30 | AL27: 2032-09-30 | AM27: 2032-12-31 | AN27: 2033-03-31 | AO27: 2033-06-30 | AP27: 2033-09-30 | AQ27: 2033-12-31 | AR27: 2034-03-31 | AS27: 2034-06-30 | AT27: 2034-09-30 | AU27: 2034-12-31 | AV27: 2035-03-31 | AW27: 2035-06-30 | AX27: 2035-09-30 | AY27: 2035-12-31 | AZ27: 2036-03-31 | BA27: 2036-06-30 | BB27: 2036-09-30 | BC27: 2036-12-31 | BD27: 2037-03-31 | BE27: 2037-06-30 | BF27: 2037-09-30 | BG27: 2037-12-31 | BH27: 2038-03-31 | BI27: 2038-06-30 | BJ27: 2038-09-30 | BK27: 2038-12-31 | BL27: 2039-03-31 | BM27: 2039-06-30 | BN27: 2039-09-30 | BO27: 2039-12-31 | BP27: 2040-03-31 | BQ27: 2040-06-30 | BR27: 2040-09-30 | BS27: 2040-12-31 | BT27: 2041-03-31 | BU27: 2041-06-30 | BV27: 2041-09-30 | BW27: 2041-12-31 | BX27: 2042-03-31 | BY27: 2042-06-30 | BZ27: 2042-09-30 | CA27: 2042-12-31 | CB27: 2043-03-31 | CC27: 2043-06-30 | CD27: 2043-09-30 | CE27: 2043-12-31 | CF27: 2044-03-31 | CG27: 2044-06-30 | CH27: 2044-09-30 | CI27: 2044-12-31 | CJ27: 2045-03-31 | CK27: 2045-06-30 | CL27: 2045-09-30
B29: 선순위A
B30: 기초잔액 | C30: [KRWm] | E30: 0 | F30: =E35 | G30: =F35 | H30: =G35 | I30: =H35 | J30: =I35 | K30: =J35 | L30: =K35 | M30: =L35 | ... CL30: =CK35
B31: 인출 | C31: [KRWm] | D31: =SUM(E31:CL31) | E31: =E18 | F31: =F18-E18 | G31: =G18-F18 | H31: =H18-G18 | I31: =I18-H18 | J31: =J18-I18 | K31: =K18-J18 | L31: =L18-K18 | M31: =M18-L18 | ... CL31: =CL18-CK18
B32: 건설이자(IDC) | C32: [KRWm] | D32: =SUM(E32:CL32) | E32: =E10 | F32: =F10 | G32: =G10 | H32: =H10 | I32: =I10 | J32: =J10 | K32: =K10 | L32: =L10 | ... CL32: =CL10
B33: 이자(운영) | C33: [KRWm] | D33: =SUM(E33:CL33) | E33: 0 | F33: 0 | G33: 0 | H33: 0 | I33: 0 | J33: 0 | K33: =K30*'입력값'!E58/4 | L33: =L30*'입력값'!E58/4 | M33: =M30*'입력값'!E58/4 | N33: =N30*'입력값'!E58/4 | O33: =O30*'입력값'!E58/4 | P33: =P30*'입력값'!E58/4 | Q33: =Q30*'입력값'!E58/4 | R33: =R30*'입력값'!E58/4 | S33: =S30*'입력값'!E58/4 | T33: =T30*'입력값'!E58/4 | U33: =U30*'입력값'!E58/4 | V33: =V30*'입력값'!E58/4 | W33: =W30*'입력값'!E58/4 | X33: =X30*'입력값'!E58/4 | Y33: =Y30*'입력값'!E58/4 | Z33: =Z30*'입력값'!E58/4 | AA33: =AA30*'입력값'!E58/4 | AB33: =AB30*'입력값'!E58/4 | AC33: =AC30*'입력값'!E58/4 | AD33: =AD30*'입력값'!E58/4 | AE33: =AE30*'입력값'!E58/4 | AF33: =AF30*'입력값'!E58/4 | AG33: =AG30*'입력값'!E58/4 | AH33: =AH30*'입력값'!E58/4 | AI33: =AI30*'입력값'!E58/4 | AJ33: =AJ30*'입력값'!E58/4 | AK33: =AK30*'입력값'!E58/4 | AL33: =AL30*'입력값'!E58/4 | AM33: =AM30*'입력값'!E58/4 | AN33: =AN30*'입력값'!E58/4 | AO33: =AO30*'입력값'!E58/4 | AP33: =AP30*'입력값'!E58/4 | AQ33: =AQ30*'입력값'!E58/4 | AR33: =AR30*'입력값'!E58/4 | AS33: =AS30*'입력값'!E58/4 | AT33: =AT30*'입력값'!E58/4 | AU33: =AU30*'입력값'!E58/4 | AV33: =AV30*'입력값'!E58/4 | AW33: =AW30*'입력값'!E58/4 | AX33: =AX30*'입력값'!E58/4 | AY33: =AY30*'입력값'!E58/4 | AZ33: =AZ30*'입력값'!E58/4 | BA33: =BA30*'입력값'!E58/4 | BB33: =BB30*'입력값'!E58/4 | BC33: =BC30*'입력값'!E58/4 | BD33: =BD30*'입력값'!E58/4 | BE33: =BE30*'입력값'!E58/4 | BF33: =BF30*'입력값'!E58/4 | BG33: =BG30*'입력값'!E58/4 | BH33: =BH30*'입력값'!E58/4 | BI33: =BI30*'입력값'!E58/4 | BJ33: =BJ30*'입력값'!E58/4 | BK33: =BK30*'입력값'!E58/4 | BL33: =BL30*'입력값'!E58/4 | BM33: =BM30*'입력값'!E58/4 | BN33: =BN30*'입력값'!E58/4 | BO33: =BO30*'입력값'!E58/4 | BP33: =BP30*'입력값'!E58/4 | BQ33: =BQ30*'입력값'!E58/4 | BR33: =BR30*'입력값'!E58/4 | BS33: =BS30*'입력값'!E58/4 | BT33: =BT30*'입력값'!E58/4 | BU33: =BU30*'입력값'!E58/4 | BV33: =BV30*'입력값'!E58/4 | BW33: =BW30*'입력값'!E58/4 | BX33: =BX30*'입력값'!E58/4 | BY33: =BY30*'입력값'!E58/4 | BZ33: =BZ30*'입력값'!E58/4 | CA33: =CA30*'입력값'!E58/4 | CB33: =CB30*'입력값'!E58/4 | CC33: =CC30*'입력값'!E58/4 | CD33: =CD30*'입력값'!E58/4 | CE33: =CE30*'입력값'!E58/4 | CF33: =CF30*'입력값'!E58/4 | CG33: =CG30*'입력값'!E58/4 | CH33: =CH30*'입력값'!E58/4 | CI33: =CI30*'입력값'!E58/4 | CJ33: =CJ30*'입력값'!E58/4 | CK33: =CK30*'입력값'!E58/4 | CL33: =CL30*'입력값'!E58/4
B34: 원금상환 | C34: [KRWm] | D34: =SUM(E34:CL34) | E34: 0 | F34: 0 | G34: 0 | H34: 0 | I34: 0 | J34: 0 | K34: 0 | L34: 0 | M34: 0 | N34: ='입력값'!N75*'입력값'!C58*100 | O34: ='입력값'!O75*'입력값'!C58*100 | P34: ='입력값'!P75*'입력값'!C58*100 | Q34: ='입력값'!Q75*'입력값'!C58*100 | R34: ='입력값'!R75*'입력값'!C58*100 | S34: ='입력값'!S75*'입력값'!C58*100 | T34: ='입력값'!T75*'입력값'!C58*100 | U34: ='입력값'!U75*'입력값'!C58*100 | V34: ='입력값'!V75*'입력값'!C58*100 | W34: ='입력값'!W75*'입력값'!C58*100 | X34: ='입력값'!X75*'입력값'!C58*100 | Y34: ='입력값'!Y75*'입력값'!C58*100 | Z34: ='입력값'!Z75*'입력값'!C58*100 | AA34: ='입력값'!AA75*'입력값'!C58*100 | AB34: ='입력값'!AB75*'입력값'!C58*100 | AC34: ='입력값'!AC75*'입력값'!C58*100 | AD34: ='입력값'!AD75*'입력값'!C58*100 | AE34: ='입력값'!AE75*'입력값'!C58*100 | AF34: ='입력값'!AF75*'입력값'!C58*100 | AG34: ='입력값'!AG75*'입력값'!C58*100 | AH34: ='입력값'!AH75*'입력값'!C58*100 | AI34: ='입력값'!AI75*'입력값'!C58*100 | AJ34: ='입력값'!AJ75*'입력값'!C58*100 | AK34: ='입력값'!AK75*'입력값'!C58*100 | AL34: ='입력값'!AL75*'입력값'!C58*100 | AM34: ='입력값'!AM75*'입력값'!C58*100 | AN34: ='입력값'!AN75*'입력값'!C58*100 | AO34: ='입력값'!AO75*'입력값'!C58*100 | AP34: ='입력값'!AP75*'입력값'!C58*100 | AQ34: ='입력값'!AQ75*'입력값'!C58*100 | AR34: ='입력값'!AR75*'입력값'!C58*100 | AS34: ='입력값'!AS75*'입력값'!C58*100 | AT34: ='입력값'!AT75*'입력값'!C58*100 | AU34: ='입력값'!AU75*'입력값'!C58*100 | AV34: ='입력값'!AV75*'입력값'!C58*100 | AW34: ='입력값'!AW75*'입력값'!C58*100 | AX34: ='입력값'!AX75*'입력값'!C58*100 | AY34: ='입력값'!AY75*'입력값'!C58*100 | AZ34: ='입력값'!AZ75*'입력값'!C58*100 | BA34: ='입력값'!BA75*'입력값'!C58*100 | BB34: ='입력값'!BB75*'입력값'!C58*100 | BC34: ='입력값'!BC75*'입력값'!C58*100 | BD34: ='입력값'!BD75*'입력값'!C58*100 | BE34: ='입력값'!BE75*'입력값'!C58*100 | BF34: ='입력값'!BF75*'입력값'!C58*100 | BG34: ='입력값'!BG75*'입력값'!C58*100 | BH34: ='입력값'!BH75*'입력값'!C58*100 | BI34: ='입력값'!BI75*'입력값'!C58*100 | BJ34: ='입력값'!BJ75*'입력값'!C58*100 | BK34: ='입력값'!BK75*'입력값'!C58*100 | BL34: ='입력값'!BL75*'입력값'!C58*100 | BM34: ='입력값'!BM75*'입력값'!C58*100 | BN34: ='입력값'!BN75*'입력값'!C58*100 | BO34: ='입력값'!BO75*'입력값'!C58*100 | BP34: ='입력값'!BP75*'입력값'!C58*100 | BQ34: ='입력값'!BQ75*'입력값'!C58*100 | BR34: ='입력값'!BR75*'입력값'!C58*100 | BS34: ='입력값'!BS75*'입력값'!C58*100 | BT34: ='입력값'!BT75*'입력값'!C58*100 | BU34: ='입력값'!BU75*'입력값'!C58*100 | BV34: ='입력값'!BV75*'입력값'!C58*100 | BW34: ='입력값'!BW75*'입력값'!C58*100 | BX34: ='입력값'!BX75*'입력값'!C58*100 | BY34: ='입력값'!BY75*'입력값'!C58*100 | BZ34: 0 | CA34: 0 | CB34: 0 | CC34: 0 | CD34: 0 | CE34: 0 | CF34: 0 | CG34: 0 | CH34: 0 | CI34: 0 | CJ34: 0 | CK34: 0 | CL34: 0
B35: 기말잔액 | C35: [KRWm] | E35: =E30+E31-E34 | F35: =F30+F31-F34 | G35: =G30+G31-G34 | H35: =H30+H31-H34 | I35: =I30+I31-I34 | J35: =J30+J31-J34 | K35: =K30+K31-K34 | L35: =L30+L31-L34 | ... CL35: =CL30+CL31-CL34
B36: 미상환 잔액(검증용) | C36: [KRWm] | D36: =CL35 | F36: =IF(ABS(D36)<1,"완전상환 확인 (OK)","경고: 미상환 잔액") | H36: ※ 방식 3(직접 키인) — 원금상환은 "입력값" 시트의 상환비율 표를 참조하는 수식
B38: 선순위B
B39: 기초잔액 | C39: [KRWm] | E39: 0 | F39: =E44 | G39: =F44 | H39: =G44 | I39: =H44 | J39: =I44 | K39: =J44 | L39: =K44 | M39: =L44 | ... CL39: =CK44
B40: 인출 | C40: [KRWm] | D40: =SUM(E40:CL40) | E40: =E19 | F40: =F19-E19 | G40: =G19-F19 | H40: =H19-G19 | I40: =I19-H19 | J40: =J19-I19 | K40: =K19-J19 | L40: =L19-K19 | M40: =M19-L19 | ... CL40: =CL19-CK19
B41: 건설이자(IDC) | C41: [KRWm] | D41: =SUM(E41:CL41) | E41: =E11 | F41: =F11 | G41: =G11 | H41: =H11 | I41: =I11 | J41: =J11 | K41: =K11 | L41: =L11 | ... CL41: =CL11
B42: 이자(운영) | C42: [KRWm] | D42: =SUM(E42:CL42) | E42: 0 | F42: 0 | G42: 0 | H42: 0 | I42: 0 | J42: 0 | K42: =K39*'입력값'!E59/4 | L42: =L39*'입력값'!E59/4 | M42: =M39*'입력값'!E59/4 | N42: =N39*'입력값'!E59/4 | O42: =O39*'입력값'!E59/4 | P42: =P39*'입력값'!E59/4 | Q42: =Q39*'입력값'!E59/4 | R42: =R39*'입력값'!E59/4 | S42: =S39*'입력값'!E59/4 | T42: =T39*'입력값'!E59/4 | U42: =U39*'입력값'!E59/4 | V42: =V39*'입력값'!E59/4 | W42: =W39*'입력값'!E59/4 | X42: =X39*'입력값'!E59/4 | Y42: =Y39*'입력값'!E59/4 | Z42: =Z39*'입력값'!E59/4 | AA42: =AA39*'입력값'!E59/4 | AB42: =AB39*'입력값'!E59/4 | AC42: =AC39*'입력값'!E59/4 | AD42: =AD39*'입력값'!E59/4 | AE42: =AE39*'입력값'!E59/4 | AF42: =AF39*'입력값'!E59/4 | AG42: =AG39*'입력값'!E59/4 | AH42: =AH39*'입력값'!E59/4 | AI42: =AI39*'입력값'!E59/4 | AJ42: =AJ39*'입력값'!E59/4 | AK42: =AK39*'입력값'!E59/4 | AL42: =AL39*'입력값'!E59/4 | AM42: =AM39*'입력값'!E59/4 | AN42: =AN39*'입력값'!E59/4 | AO42: =AO39*'입력값'!E59/4 | AP42: =AP39*'입력값'!E59/4 | AQ42: =AQ39*'입력값'!E59/4 | AR42: =AR39*'입력값'!E59/4 | AS42: =AS39*'입력값'!E59/4 | AT42: =AT39*'입력값'!E59/4 | AU42: =AU39*'입력값'!E59/4 | AV42: =AV39*'입력값'!E59/4 | AW42: =AW39*'입력값'!E59/4 | AX42: =AX39*'입력값'!E59/4 | AY42: =AY39*'입력값'!E59/4 | AZ42: =AZ39*'입력값'!E59/4 | BA42: =BA39*'입력값'!E59/4 | BB42: =BB39*'입력값'!E59/4 | BC42: =BC39*'입력값'!E59/4 | BD42: =BD39*'입력값'!E59/4 | BE42: =BE39*'입력값'!E59/4 | BF42: =BF39*'입력값'!E59/4 | BG42: =BG39*'입력값'!E59/4 | BH42: =BH39*'입력값'!E59/4 | BI42: =BI39*'입력값'!E59/4 | BJ42: =BJ39*'입력값'!E59/4 | BK42: =BK39*'입력값'!E59/4 | BL42: =BL39*'입력값'!E59/4 | BM42: =BM39*'입력값'!E59/4 | BN42: =BN39*'입력값'!E59/4 | BO42: =BO39*'입력값'!E59/4 | BP42: =BP39*'입력값'!E59/4 | BQ42: =BQ39*'입력값'!E59/4 | BR42: =BR39*'입력값'!E59/4 | BS42: =BS39*'입력값'!E59/4 | BT42: =BT39*'입력값'!E59/4 | BU42: =BU39*'입력값'!E59/4 | BV42: =BV39*'입력값'!E59/4 | BW42: =BW39*'입력값'!E59/4 | BX42: =BX39*'입력값'!E59/4 | BY42: =BY39*'입력값'!E59/4 | BZ42: =BZ39*'입력값'!E59/4 | CA42: =CA39*'입력값'!E59/4 | CB42: =CB39*'입력값'!E59/4 | CC42: =CC39*'입력값'!E59/4 | CD42: =CD39*'입력값'!E59/4 | CE42: =CE39*'입력값'!E59/4 | CF42: =CF39*'입력값'!E59/4 | CG42: =CG39*'입력값'!E59/4 | CH42: =CH39*'입력값'!E59/4 | CI42: =CI39*'입력값'!E59/4 | CJ42: =CJ39*'입력값'!E59/4 | CK42: =CK39*'입력값'!E59/4 | CL42: =CL39*'입력값'!E59/4
B43: 원금상환 | C43: [KRWm] | D43: =SUM(E43:CL43) | E43: 0 | F43: 0 | G43: 0 | H43: 0 | I43: 0 | J43: 0 | K43: 0 | L43: 0 | M43: 0 | N43: ='입력값'!N76*'입력값'!C59*100 | O43: ='입력값'!O76*'입력값'!C59*100 | P43: ='입력값'!P76*'입력값'!C59*100 | Q43: ='입력값'!Q76*'입력값'!C59*100 | R43: ='입력값'!R76*'입력값'!C59*100 | S43: ='입력값'!S76*'입력값'!C59*100 | T43: ='입력값'!T76*'입력값'!C59*100 | U43: ='입력값'!U76*'입력값'!C59*100 | V43: ='입력값'!V76*'입력값'!C59*100 | W43: ='입력값'!W76*'입력값'!C59*100 | X43: ='입력값'!X76*'입력값'!C59*100 | Y43: ='입력값'!Y76*'입력값'!C59*100 | Z43: ='입력값'!Z76*'입력값'!C59*100 | AA43: ='입력값'!AA76*'입력값'!C59*100 | AB43: ='입력값'!AB76*'입력값'!C59*100 | AC43: ='입력값'!AC76*'입력값'!C59*100 | AD43: ='입력값'!AD76*'입력값'!C59*100 | AE43: ='입력값'!AE76*'입력값'!C59*100 | AF43: ='입력값'!AF76*'입력값'!C59*100 | AG43: ='입력값'!AG76*'입력값'!C59*100 | AH43: ='입력값'!AH76*'입력값'!C59*100 | AI43: ='입력값'!AI76*'입력값'!C59*100 | AJ43: ='입력값'!AJ76*'입력값'!C59*100 | AK43: ='입력값'!AK76*'입력값'!C59*100 | AL43: ='입력값'!AL76*'입력값'!C59*100 | AM43: ='입력값'!AM76*'입력값'!C59*100 | AN43: ='입력값'!AN76*'입력값'!C59*100 | AO43: ='입력값'!AO76*'입력값'!C59*100 | AP43: ='입력값'!AP76*'입력값'!C59*100 | AQ43: ='입력값'!AQ76*'입력값'!C59*100 | AR43: ='입력값'!AR76*'입력값'!C59*100 | AS43: ='입력값'!AS76*'입력값'!C59*100 | AT43: ='입력값'!AT76*'입력값'!C59*100 | AU43: ='입력값'!AU76*'입력값'!C59*100 | AV43: ='입력값'!AV76*'입력값'!C59*100 | AW43: ='입력값'!AW76*'입력값'!C59*100 | AX43: ='입력값'!AX76*'입력값'!C59*100 | AY43: ='입력값'!AY76*'입력값'!C59*100 | AZ43: ='입력값'!AZ76*'입력값'!C59*100 | BA43: ='입력값'!BA76*'입력값'!C59*100 | BB43: ='입력값'!BB76*'입력값'!C59*100 | BC43: ='입력값'!BC76*'입력값'!C59*100 | BD43: ='입력값'!BD76*'입력값'!C59*100 | BE43: ='입력값'!BE76*'입력값'!C59*100 | BF43: ='입력값'!BF76*'입력값'!C59*100 | BG43: ='입력값'!BG76*'입력값'!C59*100 | BH43: ='입력값'!BH76*'입력값'!C59*100 | BI43: ='입력값'!BI76*'입력값'!C59*100 | BJ43: ='입력값'!BJ76*'입력값'!C59*100 | BK43: ='입력값'!BK76*'입력값'!C59*100 | BL43: ='입력값'!BL76*'입력값'!C59*100 | BM43: ='입력값'!BM76*'입력값'!C59*100 | BN43: ='입력값'!BN76*'입력값'!C59*100 | BO43: ='입력값'!BO76*'입력값'!C59*100 | BP43: ='입력값'!BP76*'입력값'!C59*100 | BQ43: ='입력값'!BQ76*'입력값'!C59*100 | BR43: ='입력값'!BR76*'입력값'!C59*100 | BS43: ='입력값'!BS76*'입력값'!C59*100 | BT43: ='입력값'!BT76*'입력값'!C59*100 | BU43: ='입력값'!BU76*'입력값'!C59*100 | BV43: ='입력값'!BV76*'입력값'!C59*100 | BW43: ='입력값'!BW76*'입력값'!C59*100 | BX43: ='입력값'!BX76*'입력값'!C59*100 | BY43: ='입력값'!BY76*'입력값'!C59*100 | BZ43: 0 | CA43: 0 | CB43: 0 | CC43: 0 | CD43: 0 | CE43: 0 | CF43: 0 | CG43: 0 | CH43: 0 | CI43: 0 | CJ43: 0 | CK43: 0 | CL43: 0
B44: 기말잔액 | C44: [KRWm] | E44: =E39+E40-E43 | F44: =F39+F40-F43 | G44: =G39+G40-G43 | H44: =H39+H40-H43 | I44: =I39+I40-I43 | J44: =J39+J40-J43 | K44: =K39+K40-K43 | L44: =L39+L40-L43 | ... CL44: =CL39+CL40-CL43
B45: 미상환 잔액(검증용) | C45: [KRWm] | D45: =CL44 | F45: =IF(ABS(D45)<1,"완전상환 확인 (OK)","경고: 미상환 잔액") | H45: ※ 방식 3(직접 키인) — 원금상환은 "입력값" 시트의 상환비율 표를 참조하는 수식
B47: 선순위C
B48: 기초잔액 | C48: [KRWm] | E48: 0 | F48: =E53 | G48: =F53 | H48: =G53 | I48: =H53 | J48: =I53 | K48: =J53 | L48: =K53 | M48: =L53 | ... CL48: =CK53
B49: 인출 | C49: [KRWm] | D49: =SUM(E49:CL49) | E49: =E20 | F49: =F20-E20 | G49: =G20-F20 | H49: =H20-G20 | I49: =I20-H20 | J49: =J20-I20 | K49: =K20-J20 | L49: =L20-K20 | M49: =M20-L20 | ... CL49: =CL20-CK20
B50: 건설이자(IDC) | C50: [KRWm] | D50: =SUM(E50:CL50) | E50: =E12 | F50: =F12 | G50: =G12 | H50: =H12 | I50: =I12 | J50: =J12 | K50: =K12 | L50: =L12 | ... CL50: =CL12
B51: 이자(운영) | C51: [KRWm] | D51: =SUM(E51:CL51) | E51: 0 | F51: 0 | G51: 0 | H51: 0 | I51: 0 | J51: 0 | K51: =K48*'입력값'!E60/4 | L51: =L48*'입력값'!E60/4 | M51: =M48*'입력값'!E60/4 | N51: =N48*'입력값'!E60/4 | O51: =O48*'입력값'!E60/4 | P51: =P48*'입력값'!E60/4 | Q51: =Q48*'입력값'!E60/4 | R51: =R48*'입력값'!E60/4 | S51: =S48*'입력값'!E60/4 | T51: =T48*'입력값'!E60/4 | U51: =U48*'입력값'!E60/4 | V51: =V48*'입력값'!E60/4 | W51: =W48*'입력값'!E60/4 | X51: =X48*'입력값'!E60/4 | Y51: =Y48*'입력값'!E60/4 | Z51: =Z48*'입력값'!E60/4 | AA51: =AA48*'입력값'!E60/4 | AB51: =AB48*'입력값'!E60/4 | AC51: =AC48*'입력값'!E60/4 | AD51: =AD48*'입력값'!E60/4 | AE51: =AE48*'입력값'!E60/4 | AF51: =AF48*'입력값'!E60/4 | AG51: =AG48*'입력값'!E60/4 | AH51: =AH48*'입력값'!E60/4 | AI51: =AI48*'입력값'!E60/4 | AJ51: =AJ48*'입력값'!E60/4 | AK51: =AK48*'입력값'!E60/4 | AL51: =AL48*'입력값'!E60/4 | AM51: =AM48*'입력값'!E60/4 | AN51: =AN48*'입력값'!E60/4 | AO51: =AO48*'입력값'!E60/4 | AP51: =AP48*'입력값'!E60/4 | AQ51: =AQ48*'입력값'!E60/4 | AR51: =AR48*'입력값'!E60/4 | AS51: =AS48*'입력값'!E60/4 | AT51: =AT48*'입력값'!E60/4 | AU51: =AU48*'입력값'!E60/4 | AV51: =AV48*'입력값'!E60/4 | AW51: =AW48*'입력값'!E60/4 | AX51: =AX48*'입력값'!E60/4 | AY51: =AY48*'입력값'!E60/4 | AZ51: =AZ48*'입력값'!E60/4 | BA51: =BA48*'입력값'!E60/4 | BB51: =BB48*'입력값'!E60/4 | BC51: =BC48*'입력값'!E60/4 | BD51: =BD48*'입력값'!E60/4 | BE51: =BE48*'입력값'!E60/4 | BF51: =BF48*'입력값'!E60/4 | BG51: =BG48*'입력값'!E60/4 | BH51: =BH48*'입력값'!E60/4 | BI51: =BI48*'입력값'!E60/4 | BJ51: =BJ48*'입력값'!E60/4 | BK51: =BK48*'입력값'!E60/4 | BL51: =BL48*'입력값'!E60/4 | BM51: =BM48*'입력값'!E60/4 | BN51: =BN48*'입력값'!E60/4 | BO51: =BO48*'입력값'!E60/4 | BP51: =BP48*'입력값'!E60/4 | BQ51: =BQ48*'입력값'!E60/4 | BR51: =BR48*'입력값'!E60/4 | BS51: =BS48*'입력값'!E60/4 | BT51: =BT48*'입력값'!E60/4 | BU51: =BU48*'입력값'!E60/4 | BV51: =BV48*'입력값'!E60/4 | BW51: =BW48*'입력값'!E60/4 | BX51: =BX48*'입력값'!E60/4 | BY51: =BY48*'입력값'!E60/4 | BZ51: =BZ48*'입력값'!E60/4 | CA51: =CA48*'입력값'!E60/4 | CB51: =CB48*'입력값'!E60/4 | CC51: =CC48*'입력값'!E60/4 | CD51: =CD48*'입력값'!E60/4 | CE51: =CE48*'입력값'!E60/4 | CF51: =CF48*'입력값'!E60/4 | CG51: =CG48*'입력값'!E60/4 | CH51: =CH48*'입력값'!E60/4 | CI51: =CI48*'입력값'!E60/4 | CJ51: =CJ48*'입력값'!E60/4 | CK51: =CK48*'입력값'!E60/4 | CL51: =CL48*'입력값'!E60/4
B52: 원금상환 | C52: [KRWm] | D52: =SUM(E52:CL52) | E52: 0 | F52: 0 | G52: 0 | H52: 0 | I52: 0 | J52: 0 | K52: 0 | L52: 0 | M52: 0 | N52: ='입력값'!N77*'입력값'!C60*100 | O52: ='입력값'!O77*'입력값'!C60*100 | P52: ='입력값'!P77*'입력값'!C60*100 | Q52: ='입력값'!Q77*'입력값'!C60*100 | R52: ='입력값'!R77*'입력값'!C60*100 | S52: ='입력값'!S77*'입력값'!C60*100 | T52: ='입력값'!T77*'입력값'!C60*100 | U52: ='입력값'!U77*'입력값'!C60*100 | V52: ='입력값'!V77*'입력값'!C60*100 | W52: ='입력값'!W77*'입력값'!C60*100 | X52: ='입력값'!X77*'입력값'!C60*100 | Y52: ='입력값'!Y77*'입력값'!C60*100 | Z52: ='입력값'!Z77*'입력값'!C60*100 | AA52: ='입력값'!AA77*'입력값'!C60*100 | AB52: ='입력값'!AB77*'입력값'!C60*100 | AC52: ='입력값'!AC77*'입력값'!C60*100 | AD52: ='입력값'!AD77*'입력값'!C60*100 | AE52: ='입력값'!AE77*'입력값'!C60*100 | AF52: ='입력값'!AF77*'입력값'!C60*100 | AG52: ='입력값'!AG77*'입력값'!C60*100 | AH52: ='입력값'!AH77*'입력값'!C60*100 | AI52: ='입력값'!AI77*'입력값'!C60*100 | AJ52: ='입력값'!AJ77*'입력값'!C60*100 | AK52: ='입력값'!AK77*'입력값'!C60*100 | AL52: ='입력값'!AL77*'입력값'!C60*100 | AM52: ='입력값'!AM77*'입력값'!C60*100 | AN52: ='입력값'!AN77*'입력값'!C60*100 | AO52: ='입력값'!AO77*'입력값'!C60*100 | AP52: ='입력값'!AP77*'입력값'!C60*100 | AQ52: ='입력값'!AQ77*'입력값'!C60*100 | AR52: ='입력값'!AR77*'입력값'!C60*100 | AS52: ='입력값'!AS77*'입력값'!C60*100 | AT52: ='입력값'!AT77*'입력값'!C60*100 | AU52: ='입력값'!AU77*'입력값'!C60*100 | AV52: ='입력값'!AV77*'입력값'!C60*100 | AW52: ='입력값'!AW77*'입력값'!C60*100 | AX52: ='입력값'!AX77*'입력값'!C60*100 | AY52: ='입력값'!AY77*'입력값'!C60*100 | AZ52: ='입력값'!AZ77*'입력값'!C60*100 | BA52: ='입력값'!BA77*'입력값'!C60*100 | BB52: ='입력값'!BB77*'입력값'!C60*100 | BC52: ='입력값'!BC77*'입력값'!C60*100 | BD52: ='입력값'!BD77*'입력값'!C60*100 | BE52: ='입력값'!BE77*'입력값'!C60*100 | BF52: ='입력값'!BF77*'입력값'!C60*100 | BG52: ='입력값'!BG77*'입력값'!C60*100 | BH52: ='입력값'!BH77*'입력값'!C60*100 | BI52: ='입력값'!BI77*'입력값'!C60*100 | BJ52: ='입력값'!BJ77*'입력값'!C60*100 | BK52: ='입력값'!BK77*'입력값'!C60*100 | BL52: ='입력값'!BL77*'입력값'!C60*100 | BM52: ='입력값'!BM77*'입력값'!C60*100 | BN52: ='입력값'!BN77*'입력값'!C60*100 | BO52: ='입력값'!BO77*'입력값'!C60*100 | BP52: ='입력값'!BP77*'입력값'!C60*100 | BQ52: ='입력값'!BQ77*'입력값'!C60*100 | BR52: ='입력값'!BR77*'입력값'!C60*100 | BS52: ='입력값'!BS77*'입력값'!C60*100 | BT52: ='입력값'!BT77*'입력값'!C60*100 | BU52: ='입력값'!BU77*'입력값'!C60*100 | BV52: ='입력값'!BV77*'입력값'!C60*100 | BW52: ='입력값'!BW77*'입력값'!C60*100 | BX52: ='입력값'!BX77*'입력값'!C60*100 | BY52: ='입력값'!BY77*'입력값'!C60*100 | BZ52: 0 | CA52: 0 | CB52: 0 | CC52: 0 | CD52: 0 | CE52: 0 | CF52: 0 | CG52: 0 | CH52: 0 | CI52: 0 | CJ52: 0 | CK52: 0 | CL52: 0
B53: 기말잔액 | C53: [KRWm] | E53: =E48+E49-E52 | F53: =F48+F49-F52 | G53: =G48+G49-G52 | H53: =H48+H49-H52 | I53: =I48+I49-I52 | J53: =J48+J49-J52 | K53: =K48+K49-K52 | L53: =L48+L49-L52 | ... CL53: =CL48+CL49-CL52
B54: 미상환 잔액(검증용) | C54: [KRWm] | D54: =CL53 | F54: =IF(ABS(D54)<1,"완전상환 확인 (OK)","경고: 미상환 잔액") | H54: ※ 방식 3(직접 키인) — 원금상환은 "입력값" 시트의 상환비율 표를 참조하는 수식
B56: 선순위D
B57: 기초잔액 | C57: [KRWm] | E57: 0 | F57: =E62 | G57: =F62 | H57: =G62 | I57: =H62 | J57: =I62 | K57: =J62 | L57: =K62 | M57: =L62 | ... CL57: =CK62
B58: 인출 | C58: [KRWm] | D58: =SUM(E58:CL58) | E58: =E21 | F58: =F21-E21 | G58: =G21-F21 | H58: =H21-G21 | I58: =I21-H21 | J58: =J21-I21 | K58: =K21-J21 | L58: =L21-K21 | M58: =M21-L21 | ... CL58: =CL21-CK21
B59: 건설이자(IDC) | C59: [KRWm] | D59: =SUM(E59:CL59) | E59: =E13 | F59: =F13 | G59: =G13 | H59: =H13 | I59: =I13 | J59: =J13 | K59: =K13 | L59: =L13 | ... CL59: =CL13
B60: 이자(운영) | C60: [KRWm] | D60: =SUM(E60:CL60) | E60: 0 | F60: 0 | G60: 0 | H60: 0 | I60: 0 | J60: 0 | K60: =K57*'입력값'!E61/4 | L60: =L57*'입력값'!E61/4 | M60: =M57*'입력값'!E61/4 | N60: =N57*'입력값'!E61/4 | O60: =O57*'입력값'!E61/4 | P60: =P57*'입력값'!E61/4 | Q60: =Q57*'입력값'!E61/4 | R60: =R57*'입력값'!E61/4 | S60: =S57*'입력값'!E61/4 | T60: =T57*'입력값'!E61/4 | U60: =U57*'입력값'!E61/4 | V60: =V57*'입력값'!E61/4 | W60: =W57*'입력값'!E61/4 | X60: =X57*'입력값'!E61/4 | Y60: =Y57*'입력값'!E61/4 | Z60: =Z57*'입력값'!E61/4 | AA60: =AA57*'입력값'!E61/4 | AB60: =AB57*'입력값'!E61/4 | AC60: =AC57*'입력값'!E61/4 | AD60: =AD57*'입력값'!E61/4 | AE60: =AE57*'입력값'!E61/4 | AF60: =AF57*'입력값'!E61/4 | AG60: =AG57*'입력값'!E61/4 | AH60: =AH57*'입력값'!E61/4 | AI60: =AI57*'입력값'!E61/4 | AJ60: =AJ57*'입력값'!E61/4 | AK60: =AK57*'입력값'!E61/4 | AL60: =AL57*'입력값'!E61/4 | AM60: =AM57*'입력값'!E61/4 | AN60: =AN57*'입력값'!E61/4 | AO60: =AO57*'입력값'!E61/4 | AP60: =AP57*'입력값'!E61/4 | AQ60: =AQ57*'입력값'!E61/4 | AR60: =AR57*'입력값'!E61/4 | AS60: =AS57*'입력값'!E61/4 | AT60: =AT57*'입력값'!E61/4 | AU60: =AU57*'입력값'!E61/4 | AV60: =AV57*'입력값'!E61/4 | AW60: =AW57*'입력값'!E61/4 | AX60: =AX57*'입력값'!E61/4 | AY60: =AY57*'입력값'!E61/4 | AZ60: =AZ57*'입력값'!E61/4 | BA60: =BA57*'입력값'!E61/4 | BB60: =BB57*'입력값'!E61/4 | BC60: =BC57*'입력값'!E61/4 | BD60: =BD57*'입력값'!E61/4 | BE60: =BE57*'입력값'!E61/4 | BF60: =BF57*'입력값'!E61/4 | BG60: =BG57*'입력값'!E61/4 | BH60: =BH57*'입력값'!E61/4 | BI60: =BI57*'입력값'!E61/4 | BJ60: =BJ57*'입력값'!E61/4 | BK60: =BK57*'입력값'!E61/4 | BL60: =BL57*'입력값'!E61/4 | BM60: =BM57*'입력값'!E61/4 | BN60: =BN57*'입력값'!E61/4 | BO60: =BO57*'입력값'!E61/4 | BP60: =BP57*'입력값'!E61/4 | BQ60: =BQ57*'입력값'!E61/4 | BR60: =BR57*'입력값'!E61/4 | BS60: =BS57*'입력값'!E61/4 | BT60: =BT57*'입력값'!E61/4 | BU60: =BU57*'입력값'!E61/4 | BV60: =BV57*'입력값'!E61/4 | BW60: =BW57*'입력값'!E61/4 | BX60: =BX57*'입력값'!E61/4 | BY60: =BY57*'입력값'!E61/4 | BZ60: =BZ57*'입력값'!E61/4 | CA60: =CA57*'입력값'!E61/4 | CB60: =CB57*'입력값'!E61/4 | CC60: =CC57*'입력값'!E61/4 | CD60: =CD57*'입력값'!E61/4 | CE60: =CE57*'입력값'!E61/4 | CF60: =CF57*'입력값'!E61/4 | CG60: =CG57*'입력값'!E61/4 | CH60: =CH57*'입력값'!E61/4 | CI60: =CI57*'입력값'!E61/4 | CJ60: =CJ57*'입력값'!E61/4 | CK60: =CK57*'입력값'!E61/4 | CL60: =CL57*'입력값'!E61/4
B61: 원금상환 | C61: [KRWm] | D61: =SUM(E61:CL61) | E61: 0 | F61: 0 | G61: 0 | H61: 0 | I61: 0 | J61: 0 | K61: 0 | L61: 0 | M61: 0 | N61: 0 | O61: 0 | P61: 0 | Q61: 0 | R61: 0 | S61: 0 | T61: 0 | U61: 0 | V61: 0 | W61: 0 | X61: 0 | Y61: 0 | Z61: 0 | AA61: 0 | AB61: 0 | AC61: 0 | AD61: 0 | AE61: 0 | AF61: 0 | AG61: 0 | AH61: 0 | AI61: 0 | AJ61: 0 | AK61: 0 | AL61: 0 | AM61: 0 | AN61: 0 | AO61: 0 | AP61: 0 | AQ61: 0 | AR61: 0 | AS61: 0 | AT61: 0 | AU61: 0 | AV61: 0 | AW61: 0 | AX61: 0 | AY61: 0 | AZ61: 0 | BA61: 0 | BB61: 0 | BC61: 0 | BD61: 0 | BE61: 0 | BF61: 0 | BG61: 0 | BH61: 0 | BI61: 0 | BJ61: 0 | BK61: 0 | BL61: 0 | BM61: 0 | BN61: 0 | BO61: 0 | BP61: 0 | BQ61: 0 | BR61: 0 | BS61: 0 | BT61: 0 | BU61: 0 | BV61: 0 | BW61: 0 | BX61: 0 | BY61: 0 | BZ61: 0 | CA61: 0 | CB61: 0 | CC61: 0 | CD61: 0 | CE61: 0 | CF61: 0 | CG61: 0 | CH61: 0 | CI61: 0 | CJ61: 0 | CK61: 0 | CL61: 0
B62: 기말잔액 | C62: [KRWm] | E62: =E57+E58-E61 | F62: =F57+F58-F61 | G62: =G57+G58-G61 | H62: =H57+H58-H61 | I62: =I57+I58-I61 | J62: =J57+J58-J61 | K62: =K57+K58-K61 | L62: =L57+L58-L61 | ... CL62: =CL57+CL58-CL61
B63: 미상환 잔액(검증용) | C63: [KRWm] | D63: =CL62 | F63: =IF(ABS(D63)<1,"완전상환 확인 (OK)","경고: 미상환 잔액") | H63: ※ 미사용 트랜치 — 값(baked) 기준
B65: 후순위
B66: 기초잔액 | C66: [KRWm] | E66: 0 | F66: =E71 | G66: =F71 | H66: =G71 | I66: =H71 | J66: =I71 | K66: =J71 | L66: =K71 | M66: =L71 | ... CL66: =CK71
B67: 인출 | C67: [KRWm] | D67: =SUM(E67:CL67) | E67: =E22 | F67: =F22-E22 | G67: =G22-F22 | H67: =H22-G22 | I67: =I22-H22 | J67: =J22-I22 | K67: =K22-J22 | L67: =L22-K22 | M67: =M22-L22 | ... CL67: =CL22-CK22
B68: 건설이자(IDC) | C68: [KRWm] | D68: =SUM(E68:CL68) | E68: =E14 | F68: =F14 | G68: =G14 | H68: =H14 | I68: =I14 | J68: =J14 | K68: =K14 | L68: =L14 | ... CL68: =CL14
B69: 이자(운영) | C69: [KRWm] | D69: =SUM(E69:CL69) | E69: 0 | F69: 0 | G69: 0 | H69: 0 | I69: 0 | J69: 0 | K69: =K66*'입력값'!E62/4 | L69: =L66*'입력값'!E62/4 | M69: =M66*'입력값'!E62/4 | N69: =N66*'입력값'!E62/4 | O69: =O66*'입력값'!E62/4 | P69: =P66*'입력값'!E62/4 | Q69: =Q66*'입력값'!E62/4 | R69: =R66*'입력값'!E62/4 | S69: =S66*'입력값'!E62/4 | T69: =T66*'입력값'!E62/4 | U69: =U66*'입력값'!E62/4 | V69: =V66*'입력값'!E62/4 | W69: =W66*'입력값'!E62/4 | X69: =X66*'입력값'!E62/4 | Y69: =Y66*'입력값'!E62/4 | Z69: =Z66*'입력값'!E62/4 | AA69: =AA66*'입력값'!E62/4 | AB69: =AB66*'입력값'!E62/4 | AC69: =AC66*'입력값'!E62/4 | AD69: =AD66*'입력값'!E62/4 | AE69: =AE66*'입력값'!E62/4 | AF69: =AF66*'입력값'!E62/4 | AG69: =AG66*'입력값'!E62/4 | AH69: =AH66*'입력값'!E62/4 | AI69: =AI66*'입력값'!E62/4 | AJ69: =AJ66*'입력값'!E62/4 | AK69: =AK66*'입력값'!E62/4 | AL69: =AL66*'입력값'!E62/4 | AM69: =AM66*'입력값'!E62/4 | AN69: =AN66*'입력값'!E62/4 | AO69: =AO66*'입력값'!E62/4 | AP69: =AP66*'입력값'!E62/4 | AQ69: =AQ66*'입력값'!E62/4 | AR69: =AR66*'입력값'!E62/4 | AS69: =AS66*'입력값'!E62/4 | AT69: =AT66*'입력값'!E62/4 | AU69: =AU66*'입력값'!E62/4 | AV69: =AV66*'입력값'!E62/4 | AW69: =AW66*'입력값'!E62/4 | AX69: =AX66*'입력값'!E62/4 | AY69: =AY66*'입력값'!E62/4 | AZ69: =AZ66*'입력값'!E62/4 | BA69: =BA66*'입력값'!E62/4 | BB69: =BB66*'입력값'!E62/4 | BC69: =BC66*'입력값'!E62/4 | BD69: =BD66*'입력값'!E62/4 | BE69: =BE66*'입력값'!E62/4 | BF69: =BF66*'입력값'!E62/4 | BG69: =BG66*'입력값'!E62/4 | BH69: =BH66*'입력값'!E62/4 | BI69: =BI66*'입력값'!E62/4 | BJ69: =BJ66*'입력값'!E62/4 | BK69: =BK66*'입력값'!E62/4 | BL69: =BL66*'입력값'!E62/4 | BM69: =BM66*'입력값'!E62/4 | BN69: =BN66*'입력값'!E62/4 | BO69: =BO66*'입력값'!E62/4 | BP69: =BP66*'입력값'!E62/4 | BQ69: =BQ66*'입력값'!E62/4 | BR69: =BR66*'입력값'!E62/4 | BS69: =BS66*'입력값'!E62/4 | BT69: =BT66*'입력값'!E62/4 | BU69: =BU66*'입력값'!E62/4 | BV69: =BV66*'입력값'!E62/4 | BW69: =BW66*'입력값'!E62/4 | BX69: =BX66*'입력값'!E62/4 | BY69: =BY66*'입력값'!E62/4 | BZ69: =BZ66*'입력값'!E62/4 | CA69: =CA66*'입력값'!E62/4 | CB69: =CB66*'입력값'!E62/4 | CC69: =CC66*'입력값'!E62/4 | CD69: =CD66*'입력값'!E62/4 | CE69: =CE66*'입력값'!E62/4 | CF69: =CF66*'입력값'!E62/4 | CG69: =CG66*'입력값'!E62/4 | CH69: =CH66*'입력값'!E62/4 | CI69: =CI66*'입력값'!E62/4 | CJ69: =CJ66*'입력값'!E62/4 | CK69: =CK66*'입력값'!E62/4 | CL69: =CL66*'입력값'!E62/4
B70: 원금상환 | C70: [KRWm] | D70: =SUM(E70:CL70) | E70: 0 | F70: 0 | G70: 0 | H70: 0 | I70: 0 | J70: 0 | K70: 0 | L70: 0 | M70: 0 | N70: 0 | O70: 0 | P70: 0 | Q70: 0 | R70: 0 | S70: 0 | T70: 0 | U70: 0 | V70: 0 | W70: 0 | X70: 0 | Y70: 0 | Z70: 0 | AA70: 0 | AB70: 0 | AC70: 0 | AD70: 0 | AE70: 0 | AF70: 0 | AG70: 0 | AH70: 0 | AI70: 0 | AJ70: 0 | AK70: 0 | AL70: 0 | AM70: 0 | AN70: 0 | AO70: 0 | AP70: 0 | AQ70: 0 | AR70: 0 | AS70: 0 | AT70: 0 | AU70: 0 | AV70: 0 | AW70: 0 | AX70: 0 | AY70: 0 | AZ70: 0 | BA70: 0 | BB70: 0 | BC70: 0 | BD70: 0 | BE70: 0 | BF70: 0 | BG70: 0 | BH70: 0 | BI70: 0 | BJ70: 0 | BK70: 0 | BL70: 0 | BM70: 0 | BN70: 0 | BO70: 0 | BP70: 0 | BQ70: 0 | BR70: 0 | BS70: 0 | BT70: 0 | BU70: 0 | BV70: 0 | BW70: 0 | BX70: 0 | BY70: 0 | BZ70: 0 | CA70: 0 | CB70: 0 | CC70: 0 | CD70: 0 | CE70: 0 | CF70: 0 | CG70: 0 | CH70: 0 | CI70: 0 | CJ70: 0 | CK70: 0 | CL70: 0
B71: 기말잔액 | C71: [KRWm] | E71: =E66+E67-E70 | F71: =F66+F67-F70 | G71: =G66+G67-G70 | H71: =H66+H67-H70 | I71: =I66+I67-I70 | J71: =J66+J67-J70 | K71: =K66+K67-K70 | L71: =L66+L67-L70 | ... CL71: =CL66+CL67-CL70
B72: 미상환 잔액(검증용) | C72: [KRWm] | D72: =CL71 | F72: =IF(ABS(D72)<1,"완전상환 확인 (OK)","경고: 미상환 잔액") | H72: ※ 미사용 트랜치 — 값(baked) 기준
B74: 전체 합계
B75: 기초잔액 | C75: [KRWm] | E75: =E30+E39+E48+E57+E66 | F75: =F30+F39+F48+F57+F66 | G75: =G30+G39+G48+G57+G66 | H75: =H30+H39+H48+H57+H66 | I75: =I30+I39+I48+I57+I66 | J75: =J30+J39+J48+J57+J66 | K75: =K30+K39+K48+K57+K66 | L75: =L30+L39+L48+L57+L66 | ... CL75: =CL30+CL39+CL48+CL57+CL66
B76: 이자 | C76: [KRWm] | D76: =SUM(E76:CL76) | E76: =E33+E42+E51+E60+E69 | F76: =F33+F42+F51+F60+F69 | G76: =G33+G42+G51+G60+G69 | H76: =H33+H42+H51+H60+H69 | I76: =I33+I42+I51+I60+I69 | J76: =J33+J42+J51+J60+J69 | K76: =K33+K42+K51+K60+K69 | L76: =L33+L42+L51+L60+L69 | ... CL76: =CL33+CL42+CL51+CL60+CL69
B77: 원금상환 | C77: [KRWm] | D77: =SUM(E77:CL77) | E77: =E34+E43+E52+E61+E70 | F77: =F34+F43+F52+F61+F70 | G77: =G34+G43+G52+G61+G70 | H77: =H34+H43+H52+H61+H70 | I77: =I34+I43+I52+I61+I70 | J77: =J34+J43+J52+J61+J70 | K77: =K34+K43+K52+K61+K70 | L77: =L34+L43+L52+L61+L70 | ... CL77: =CL34+CL43+CL52+CL61+CL70
B78: 원리금(DS) | C78: [KRWm] | D78: =SUM(E78:CL78) | E78: =E76+E77 | F78: =F76+F77 | G78: =G76+G77 | H78: =H76+H77 | I78: =I76+I77 | J78: =J76+J77 | K78: =K76+K77 | L78: =L76+L77 | ... CL78: =CL76+CL77
B79: 기말잔액 | C79: [KRWm] | E79: =E35+E44+E53+E62+E71 | F79: =F35+F44+F53+F62+F71 | G79: =G35+G44+G53+G62+G71 | H79: =H35+H44+H53+H62+H71 | I79: =I35+I44+I53+I62+I71 | J79: =J35+J44+J53+J62+J71 | K79: =K35+K44+K53+K62+K71 | L79: =L35+L44+L53+L62+L71 | ... CL79: =CL35+CL44+CL53+CL62+CL71
B81: DSRA 기초잔액 | C81: [KRWm] | E81: =0 | F81: =E82 | G81: =F82 | H81: =G82 | I81: =H82 | J81: ='입력값'!C20*100 | K81: =J82 | L81: =K82 | M81: =L82 | N81: =M82 | O81: =N82 | P81: =O82 | Q81: =P82 | R81: =Q82 | ... CL81: =CK82
B82: DSRA 기말잔액 | C82: [KRWm] | E82: =E81 | F82: =F81 | G82: =G81 | H82: =H81 | I82: =I81 | J82: =J81 | K82: =L78+M78 | L82: =M78+N78 | M82: =N78+O78 | N82: =O78+P78 | O82: =P78+Q78 | P82: =Q78+R78 | Q82: =R78+S78 | R82: =S78+T78 | ... CJ82: =CK78+CL78 | CK82: =CL78 | CL82: =0

Sheet Revenue
A1: 당진 태양광발전
A2: 영업수익 추정
B4: 발전량 및 매출
B6: 구 분 | C6: unit | D6: 합 계 | E6: 2024-06-30 | F6: 2024-09-30 | G6: 2024-12-31 | H6: 2025-03-31 | I6: 2025-06-30 | J6: 2025-09-30 | K6: 2025-12-31 | L6: 2026-03-31 | M6: 2026-06-30 | N6: 2026-09-30 | O6: 2026-12-31 | P6: 2027-03-31 | Q6: 2027-06-30 | R6: 2027-09-30 | S6: 2027-12-31 | T6: 2028-03-31 | U6: 2028-06-30 | V6: 2028-09-30 | W6: 2028-12-31 | X6: 2029-03-31 | Y6: 2029-06-30 | Z6: 2029-09-30 | AA6: 2029-12-31 | AB6: 2030-03-31 | AC6: 2030-06-30 | AD6: 2030-09-30 | AE6: 2030-12-31 | AF6: 2031-03-31 | AG6: 2031-06-30 | AH6: 2031-09-30 | AI6: 2031-12-31 | AJ6: 2032-03-31 | AK6: 2032-06-30 | AL6: 2032-09-30 | AM6: 2032-12-31 | AN6: 2033-03-31 | AO6: 2033-06-30 | AP6: 2033-09-30 | AQ6: 2033-12-31 | AR6: 2034-03-31 | AS6: 2034-06-30 | AT6: 2034-09-30 | AU6: 2034-12-31 | AV6: 2035-03-31 | AW6: 2035-06-30 | AX6: 2035-09-30 | AY6: 2035-12-31 | AZ6: 2036-03-31 | BA6: 2036-06-30 | BB6: 2036-09-30 | BC6: 2036-12-31 | BD6: 2037-03-31 | BE6: 2037-06-30 | BF6: 2037-09-30 | BG6: 2037-12-31 | BH6: 2038-03-31 | BI6: 2038-06-30 | BJ6: 2038-09-30 | BK6: 2038-12-31 | BL6: 2039-03-31 | BM6: 2039-06-30 | BN6: 2039-09-30 | BO6: 2039-12-31 | BP6: 2040-03-31 | BQ6: 2040-06-30 | BR6: 2040-09-30 | BS6: 2040-12-31 | BT6: 2041-03-31 | BU6: 2041-06-30 | BV6: 2041-09-30 | BW6: 2041-12-31 | BX6: 2042-03-31 | BY6: 2042-06-30 | BZ6: 2042-09-30 | CA6: 2042-12-31 | CB6: 2043-03-31 | CC6: 2043-06-30 | CD6: 2043-09-30 | CE6: 2043-12-31 | CF6: 2044-03-31 | CG6: 2044-06-30 | CH6: 2044-09-30 | CI6: 2044-12-31 | CJ6: 2045-03-31 | CK6: 2045-06-30 | CL6: 2045-09-30
B9: 발전량 | C9: [MWh] | D9: =SUM(E9:CL9) | E9: =('입력값'!C7*'입력값'!C14*365)*MAX(0,1-'입력값'!C12/100*0)*(1-'입력값'!C13/100)*0 | F9: =('입력값'!C7*'입력값'!C14*365)*MAX(0,1-'입력값'!C12/100*0)*(1-'입력값'!C13/100)*0 | G9: =('입력값'!C7*'입력값'!C14*365)*MAX(0,1-'입력값'!C12/100*0)*(1-'입력값'!C13/100)*0 | H9: =('입력값'!C7*'입력값'!C14*365)*MAX(0,1-'입력값'!C12/100*0)*(1-'입력값'!C13/100)*0 | I9: =('입력값'!C7*'입력값'!C14*365)*MAX(0,1-'입력값'!C12/100*0)*(1-'입력값'!C13/100)*0 | J9: =('입력값'!C7*'입력값'!C14*365)*MAX(0,1-'입력값'!C12/100*0)*(1-'입력값'!C13/100)*0 | K9: =('입력값'!C7*'입력값'!C14*365)*MAX(0,1-'입력값'!C12/100*0)*(1-'입력값'!C13/100)*0.2347 | L9: =('입력값'!C7*'입력값'!C14*365)*MAX(0,1-'입력값'!C12/100*0)*(1-'입력값'!C13/100)*0.2397 | M9: =('입력값'!C7*'입력값'!C14*365)*MAX(0,1-'입력값'!C12/100*0)*(1-'입력값'!C13/100)*0.3057 | N9: =('입력값'!C7*'입력값'!C14*365)*MAX(0,1-'입력값'!C12/100*0)*(1-'입력값'!C13/100)*0.2199 | O9: =('입력값'!C7*'입력값'!C14*365)*MAX(0,1-'입력값'!C12/100*1)*(1-'입력값'!C13/100)*0.2347 | P9: =('입력값'!C7*'입력값'!C14*365)*MAX(0,1-'입력값'!C12/100*1)*(1-'입력값'!C13/100)*0.2397 | Q9: =('입력값'!C7*'입력값'!C14*365)*MAX(0,1-'입력값'!C12/100*1)*(1-'입력값'!C13/100)*0.3057 | R9: =('입력값'!C7*'입력값'!C14*365)*MAX(0,1-'입력값'!C12/100*1)*(1-'입력값'!C13/100)*0.2199 | S9: =('입력값'!C7*'입력값'!C14*365)*MAX(0,1-'입력값'!C12/100*2)*(1-'입력값'!C13/100)*0.2347 | T9: =('입력값'!C7*'입력값'!C14*365)*MAX(0,1-'입력값'!C12/100*2)*(1-'입력값'!C13/100)*0.2397 | U9: =('입력값'!C7*'입력값'!C14*365)*MAX(0,1-'입력값'!C12/100*2)*(1-'입력값'!C13/100)*0.3057 | V9: =('입력값'!C7*'입력값'!C14*365)*MAX(0,1-'입력값'!C12/100*2)*(1-'입력값'!C13/100)*0.2199 | W9: =('입력값'!C7*'입력값'!C14*365)*MAX(0,1-'입력값'!C12/100*3)*(1-'입력값'!C13/100)*0.2347 | X9: =('입력값'!C7*'입력값'!C14*365)*MAX(0,1-'입력값'!C12/100*3)*(1-'입력값'!C13/100)*0.2397 | Y9: =('입력값'!C7*'입력값'!C14*365)*MAX(0,1-'입력값'!C12/100*3)*(1-'입력값'!C13/100)*0.3057 | Z9: =('입력값'!C7*'입력값'!C14*365)*MAX(0,1-'입력값'!C12/100*3)*(1-'입력값'!C13/100)*0.2199 | AA9: =('입력값'!C7*'입력값'!C14*365)*MAX(0,1-'입력값'!C12/100*4)*(1-'입력값'!C13/100)*0.2347 | AB9: =('입력값'!C7*'입력값'!C14*365)*MAX(0,1-'입력값'!C12/100*4)*(1-'입력값'!C13/100)*0.2397 | AC9: =('입력값'!C7*'입력값'!C14*365)*MAX(0,1-'입력값'!C12/100*4)*(1-'입력값'!C13/100)*0.3057 | AD9: =('입력값'!C7*'입력값'!C14*365)*MAX(0,1-'입력값'!C12/100*4)*(1-'입력값'!C13/100)*0.2199 | AE9: =('입력값'!C7*'입력값'!C14*365)*MAX(0,1-'입력값'!C12/100*5)*(1-'입력값'!C13/100)*0.2347 | AF9: =('입력값'!C7*'입력값'!C14*365)*MAX(0,1-'입력값'!C12/100*5)*(1-'입력값'!C13/100)*0.2397 | AG9: =('입력값'!C7*'입력값'!C14*365)*MAX(0,1-'입력값'!C12/100*5)*(1-'입력값'!C13/100)*0.3057 | AH9: =('입력값'!C7*'입력값'!C14*365)*MAX(0,1-'입력값'!C12/100*5)*(1-'입력값'!C13/100)*0.2199 | AI9: =('입력값'!C7*'입력값'!C14*365)*MAX(0,1-'입력값'!C12/100*6)*(1-'입력값'!C13/100)*0.2347 | AJ9: =('입력값'!C7*'입력값'!C14*365)*MAX(0,1-'입력값'!C12/100*6)*(1-'입력값'!C13/100)*0.2397 | AK9: =('입력값'!C7*'입력값'!C14*365)*MAX(0,1-'입력값'!C12/100*6)*(1-'입력값'!C13/100)*0.3057 | AL9: =('입력값'!C7*'입력값'!C14*365)*MAX(0,1-'입력값'!C12/100*6)*(1-'입력값'!C13/100)*0.2199 | AM9: =('입력값'!C7*'입력값'!C14*365)*MAX(0,1-'입력값'!C12/100*7)*(1-'입력값'!C13/100)*0.2347 | AN9: =('입력값'!C7*'입력값'!C14*365)*MAX(0,1-'입력값'!C12/100*7)*(1-'입력값'!C13/100)*0.2397 | AO9: =('입력값'!C7*'입력값'!C14*365)*MAX(0,1-'입력값'!C12/100*7)*(1-'입력값'!C13/100)*0.3057 | AP9: =('입력값'!C7*'입력값'!C14*365)*MAX(0,1-'입력값'!C12/100*7)*(1-'입력값'!C13/100)*0.2199 | AQ9: =('입력값'!C7*'입력값'!C14*365)*MAX(0,1-'입력값'!C12/100*8)*(1-'입력값'!C13/100)*0.2347 | AR9: =('입력값'!C7*'입력값'!C14*365)*MAX(0,1-'입력값'!C12/100*8)*(1-'입력값'!C13/100)*0.2397 | AS9: =('입력값'!C7*'입력값'!C14*365)*MAX(0,1-'입력값'!C12/100*8)*(1-'입력값'!C13/100)*0.3057 | AT9: =('입력값'!C7*'입력값'!C14*365)*MAX(0,1-'입력값'!C12/100*8)*(1-'입력값'!C13/100)*0.2199 | AU9: =('입력값'!C7*'입력값'!C14*365)*MAX(0,1-'입력값'!C12/100*9)*(1-'입력값'!C13/100)*0.2347 | AV9: =('입력값'!C7*'입력값'!C14*365)*MAX(0,1-'입력값'!C12/100*9)*(1-'입력값'!C13/100)*0.2397 | AW9: =('입력값'!C7*'입력값'!C14*365)*MAX(0,1-'입력값'!C12/100*9)*(1-'입력값'!C13/100)*0.3057 | AX9: =('입력값'!C7*'입력값'!C14*365)*MAX(0,1-'입력값'!C12/100*9)*(1-'입력값'!C13/100)*0.2199 | AY9: =('입력값'!C7*'입력값'!C14*365)*MAX(0,1-'입력값'!C12/100*10)*(1-'입력값'!C13/100)*0.2347 | AZ9: =('입력값'!C7*'입력값'!C14*365)*MAX(0,1-'입력값'!C12/100*10)*(1-'입력값'!C13/100)*0.2397 | BA9: =('입력값'!C7*'입력값'!C14*365)*MAX(0,1-'입력값'!C12/100*10)*(1-'입력값'!C13/100)*0.3057 | BB9: =('입력값'!C7*'입력값'!C14*365)*MAX(0,1-'입력값'!C12/100*10)*(1-'입력값'!C13/100)*0.2199 | BC9: =('입력값'!C7*'입력값'!C14*365)*MAX(0,1-'입력값'!C12/100*11)*(1-'입력값'!C13/100)*0.2347 | BD9: =('입력값'!C7*'입력값'!C14*365)*MAX(0,1-'입력값'!C12/100*11)*(1-'입력값'!C13/100)*0.2397 | BE9: =('입력값'!C7*'입력값'!C14*365)*MAX(0,1-'입력값'!C12/100*11)*(1-'입력값'!C13/100)*0.3057 | BF9: =('입력값'!C7*'입력값'!C14*365)*MAX(0,1-'입력값'!C12/100*11)*(1-'입력값'!C13/100)*0.2199 | BG9: =('입력값'!C7*'입력값'!C14*365)*MAX(0,1-'입력값'!C12/100*12)*(1-'입력값'!C13/100)*0.2347 | BH9: =('입력값'!C7*'입력값'!C14*365)*MAX(0,1-'입력값'!C12/100*12)*(1-'입력값'!C13/100)*0.2397 | BI9: =('입력값'!C7*'입력값'!C14*365)*MAX(0,1-'입력값'!C12/100*12)*(1-'입력값'!C13/100)*0.3057 | BJ9: =('입력값'!C7*'입력값'!C14*365)*MAX(0,1-'입력값'!C12/100*12)*(1-'입력값'!C13/100)*0.2199 | BK9: =('입력값'!C7*'입력값'!C14*365)*MAX(0,1-'입력값'!C12/100*13)*(1-'입력값'!C13/100)*0.2347 | BL9: =('입력값'!C7*'입력값'!C14*365)*MAX(0,1-'입력값'!C12/100*13)*(1-'입력값'!C13/100)*0.2397 | BM9: =('입력값'!C7*'입력값'!C14*365)*MAX(0,1-'입력값'!C12/100*13)*(1-'입력값'!C13/100)*0.3057 | BN9: =('입력값'!C7*'입력값'!C14*365)*MAX(0,1-'입력값'!C12/100*13)*(1-'입력값'!C13/100)*0.2199 | BO9: =('입력값'!C7*'입력값'!C14*365)*MAX(0,1-'입력값'!C12/100*14)*(1-'입력값'!C13/100)*0.2347 | BP9: =('입력값'!C7*'입력값'!C14*365)*MAX(0,1-'입력값'!C12/100*14)*(1-'입력값'!C13/100)*0.2397 | BQ9: =('입력값'!C7*'입력값'!C14*365)*MAX(0,1-'입력값'!C12/100*14)*(1-'입력값'!C13/100)*0.3057 | BR9: =('입력값'!C7*'입력값'!C14*365)*MAX(0,1-'입력값'!C12/100*14)*(1-'입력값'!C13/100)*0.2199 | BS9: =('입력값'!C7*'입력값'!C14*365)*MAX(0,1-'입력값'!C12/100*15)*(1-'입력값'!C13/100)*0.2347 | BT9: =('입력값'!C7*'입력값'!C14*365)*MAX(0,1-'입력값'!C12/100*15)*(1-'입력값'!C13/100)*0.2397 | BU9: =('입력값'!C7*'입력값'!C14*365)*MAX(0,1-'입력값'!C12/100*15)*(1-'입력값'!C13/100)*0.3057 | BV9: =('입력값'!C7*'입력값'!C14*365)*MAX(0,1-'입력값'!C12/100*15)*(1-'입력값'!C13/100)*0.2199 | BW9: =('입력값'!C7*'입력값'!C14*365)*MAX(0,1-'입력값'!C12/100*16)*(1-'입력값'!C13/100)*0.2347 | BX9: =('입력값'!C7*'입력값'!C14*365)*MAX(0,1-'입력값'!C12/100*16)*(1-'입력값'!C13/100)*0.2397 | BY9: =('입력값'!C7*'입력값'!C14*365)*MAX(0,1-'입력값'!C12/100*16)*(1-'입력값'!C13/100)*0.3057 | BZ9: =('입력값'!C7*'입력값'!C14*365)*MAX(0,1-'입력값'!C12/100*16)*(1-'입력값'!C13/100)*0.2199 | CA9: =('입력값'!C7*'입력값'!C14*365)*MAX(0,1-'입력값'!C12/100*17)*(1-'입력값'!C13/100)*0.2347 | CB9: =('입력값'!C7*'입력값'!C14*365)*MAX(0,1-'입력값'!C12/100*17)*(1-'입력값'!C13/100)*0.2397 | CC9: =('입력값'!C7*'입력값'!C14*365)*MAX(0,1-'입력값'!C12/100*17)*(1-'입력값'!C13/100)*0.3057 | CD9: =('입력값'!C7*'입력값'!C14*365)*MAX(0,1-'입력값'!C12/100*17)*(1-'입력값'!C13/100)*0.2199 | CE9: =('입력값'!C7*'입력값'!C14*365)*MAX(0,1-'입력값'!C12/100*18)*(1-'입력값'!C13/100)*0.2347 | CF9: =('입력값'!C7*'입력값'!C14*365)*MAX(0,1-'입력값'!C12/100*18)*(1-'입력값'!C13/100)*0.2397 | CG9: =('입력값'!C7*'입력값'!C14*365)*MAX(0,1-'입력값'!C12/100*18)*(1-'입력값'!C13/100)*0.3057 | CH9: =('입력값'!C7*'입력값'!C14*365)*MAX(0,1-'입력값'!C12/100*18)*(1-'입력값'!C13/100)*0.2199 | CI9: =('입력값'!C7*'입력값'!C14*365)*MAX(0,1-'입력값'!C12/100*19)*(1-'입력값'!C13/100)*0.2347 | CJ9: =('입력값'!C7*'입력값'!C14*365)*MAX(0,1-'입력값'!C12/100*19)*(1-'입력값'!C13/100)*0.2397 | CK9: =('입력값'!C7*'입력값'!C14*365)*MAX(0,1-'입력값'!C12/100*19)*(1-'입력값'!C13/100)*0.3057 | CL9: =('입력값'!C7*'입력값'!C14*365)*MAX(0,1-'입력값'!C12/100*19)*(1-'입력값'!C13/100)*0.2199
B10: 판매단가 | C10: [원/kWh] | K10: ='입력값'!K116 | L10: ='입력값'!L116 | M10: ='입력값'!M116 | N10: ='입력값'!N116 | O10: ='입력값'!O116 | P10: ='입력값'!P116 | Q10: ='입력값'!Q116 | R10: ='입력값'!R116 | ... CL10: ='입력값'!CL116
B12: 영업수익 | C12: [KRWm] | D12: =SUM(E12:CL12) | E12: 0 | F12: 0 | G12: 0 | H12: 0 | I12: 0 | J12: 0 | K12: =K9*K10/1000 | L12: =L9*L10/1000 | M12: =M9*M10/1000 | N12: =N9*N10/1000 | O12: =O9*O10/1000 | P12: =P9*P10/1000 | Q12: =Q9*Q10/1000 | R12: =R9*R10/1000 | ... CL12: =CL9*CL10/1000
B14: ※ 실측 오버라이드가 적용된 분기는 "판매단가"가 그 분기의 실제 정산단가(실측 사실, baked)이고, "영업수익"은 다른 분기와 동일하게 발전량×판매단가/1000 수식으로 계산됩니다(값은 원본과 그대로 일치).

Sheet Opex
A1: 당진 태양광발전
A2: 영업비용 추정
B4: 운영비용 (선순위/후순위 지급순위 반영)
B6: 구 분 | C6: unit | D6: 합 계 | E6: 2024-06-30 | F6: 2024-09-30 | G6: 2024-12-31 | H6: 2025-03-31 | I6: 2025-06-30 | J6: 2025-09-30 | K6: 2025-12-31 | L6: 2026-03-31 | M6: 2026-06-30 | N6: 2026-09-30 | O6: 2026-12-31 | P6: 2027-03-31 | Q6: 2027-06-30 | R6: 2027-09-30 | S6: 2027-12-31 | T6: 2028-03-31 | U6: 2028-06-30 | V6: 2028-09-30 | W6: 2028-12-31 | X6: 2029-03-31 | Y6: 2029-06-30 | Z6: 2029-09-30 | AA6: 2029-12-31 | AB6: 2030-03-31 | AC6: 2030-06-30 | AD6: 2030-09-30 | AE6: 2030-12-31 | AF6: 2031-03-31 | AG6: 2031-06-30 | AH6: 2031-09-30 | AI6: 2031-12-31 | AJ6: 2032-03-31 | AK6: 2032-06-30 | AL6: 2032-09-30 | AM6: 2032-12-31 | AN6: 2033-03-31 | AO6: 2033-06-30 | AP6: 2033-09-30 | AQ6: 2033-12-31 | AR6: 2034-03-31 | AS6: 2034-06-30 | AT6: 2034-09-30 | AU6: 2034-12-31 | AV6: 2035-03-31 | AW6: 2035-06-30 | AX6: 2035-09-30 | AY6: 2035-12-31 | AZ6: 2036-03-31 | BA6: 2036-06-30 | BB6: 2036-09-30 | BC6: 2036-12-31 | BD6: 2037-03-31 | BE6: 2037-06-30 | BF6: 2037-09-30 | BG6: 2037-12-31 | BH6: 2038-03-31 | BI6: 2038-06-30 | BJ6: 2038-09-30 | BK6: 2038-12-31 | BL6: 2039-03-31 | BM6: 2039-06-30 | BN6: 2039-09-30 | BO6: 2039-12-31 | BP6: 2040-03-31 | BQ6: 2040-06-30 | BR6: 2040-09-30 | BS6: 2040-12-31 | BT6: 2041-03-31 | BU6: 2041-06-30 | BV6: 2041-09-30 | BW6: 2041-12-31 | BX6: 2042-03-31 | BY6: 2042-06-30 | BZ6: 2042-09-30 | CA6: 2042-12-31 | CB6: 2043-03-31 | CC6: 2043-06-30 | CD6: 2043-09-30 | CE6: 2043-12-31 | CF6: 2044-03-31 | CG6: 2044-06-30 | CH6: 2044-09-30 | CI6: 2044-12-31 | CJ6: 2045-03-31 | CK6: 2045-06-30 | CL6: 2045-09-30
B8: 항목별 세부내역
