Workbook

Sheet 목차
B2: 태양광 발전사업
B3: 재무모델 v2 (분기·5트랜치) — 재생E AI Agent 자동생성 · 2026-08-26
B6: 시트 | C6: 내용
B7: Report | C7: Executive Summary — 핵심 KPI
B8: 입력값 | C8: 화면에서 입력한 원본 값 — Funding 등이 이 시트를 참조
B9: Funding | C9: 자금조달 — 자본금 + 5트랜치 조건
B10: Debt | C10: 트랜치별 상환 스케줄 (A/B/C/D/후순위) + 합계
B11: Revenue | C11: 발전량 · 매출
B12: Opex | C12: 운영비 (선순위/후순위)
B13: IS(Q) | C13: 분기 손익계산서
B14: CF(Q) | C14: 분기 현금흐름 · DSCR · 배당
B16: ※ Funding 시트의 트랜치 조건·총사업비 항목·사업자 지분은 "입력값" 시트를 참조하는 수식입니다(입력값 시트를 고치면 같이 바뀝니다). 그 외 계산 결과(세금·DSCR·배당 등)는 값(baked) 기준이라 가정을 바꾸려면 생성기에서 다시 뽑아야 합니다.

Sheet Report
A1: 태양광 발전사업
A2: Executive Summary (v2 · 분기 · 5트랜치)
B4: 사업 개요
B6: 사업명 | D6: 태양광 발전사업
B7: 설비용량 [MW] | D7: 99.998
B8: 총 기간 수(분기) | D8: 86
B9: 건설 개시 | D9: 2024-06
B11: 재원조달
B13: 총투자비(TIC) [KRWm] | D13: 145474.28
B14: 건설이자(IDC) [KRWm] | D14: 4405.2812
B15: 자기자본 [KRWm] | D15: 15000
B16: 차입금 합계 [KRWm] | D16: 126069
B18: 수익성 지표
B20: Project IRR 세전 [%] | D20: 0.11848488
B21: Project IRR 세후 [%] | D21: 0.10465735
B22: Equity IRR (FCFE) [%] | D22: 0.32982826
B23: Equity IRR (배당) [%] | D23: 0.29986257
B24: Investor IRR [%] | D24: 0.10770215
B25: 최소 단순DSCR(연 합산) [x] | D25: 1.2410853
B26: 최소 누적DSCR [x] | D26: 1.8119161
B27: 총영업수익(전체기간) [KRWm] | D27: 405780.77
B28: 총영업비용(전체기간) [KRWm] | D28: 28498.934
B29: 총선순위이자 [KRWm] | D29: 58070.533
B30: 총법인세 [KRWm] | D30: 36951.244
B31: 총배당(연차+청산) [KRWm] | D31: 159191.06

Sheet 입력값
A1: 태양광 발전사업
A2: 입력값 — 화면에서 입력한 값 (다른 시트가 이 시트를 참조)
B4: 사업 기본 가정
B6: 사업명 | C6: 태양광 발전사업
B7: 설비용량[MW] | C7: 99.998
B8: 총사업비[억원] | C8: 1410.69
B9: 자기자본[억원] | C9: 150
B10: 판매단가[원/kWh] | C10: 154.8
B11: 판매단가 에스컬레이션[%/yr] | C11: 0
B12: 발전량 열화율[%/yr] | C12: 0.5
B13: 소내소비율[%] | C13: 0
B14: 일조시간[h/day] | C14: 3.77
B16: 트랜치 조건
B18: 트랜치 | C18: 금액[억원] | D18: 건설금리[%] | E18: 운영금리[%] | F18: 거치(yr) | G18: 상환(yr) | H18: 방식
B19: 선순위A | C19: 1260.69 | D19: 0.055 | E19: 0.055 | F19: 2 | G19: 15 | H19: 1
B20: 선순위B | C20: 0 | D20: 0.055 | E20: 0.055 | F20: 2 | G20: 15 | H20: 1
B21: 선순위C | C21: 0 | D21: 0.055 | E21: 0.055 | F21: 2 | G21: 15 | H21: 1
B22: 선순위D | C22: 0 | D22: 0.055 | E22: 0.055 | F22: 2 | G22: 15 | H22: 1
B23: 후순위 | C23: 0 | D23: 0.055 | E23: 0.055 | F23: 2 | G23: 15 | H23: 1
B25: 총사업비 항목
B27: 항목 | C27: 금액[억원]
B28: EPC
B29: 감리비
B30: 공사보험료
B31: 토지임대료(선납)
B32: 토지임대료(분납)
B33: 사업개발비
B34: 민원처리비
B35: 사업성자문비
B36: 법인운영비
B37: 기타예비비
B38: 신주발행비용
B39: 금융부대비용
B41: 운영비 항목
B43: 항목 | C43: 연간금액[억원/yr] | D43: 에스컬레이션[%/yr]
B44: 부지임대료 | C44: 5 | D44: 0
B45: O&M | C45: 8 | D45: 1.5
B46: 보험료 | C46: 0 | D46: 0
B47: 환경모니터링비용 | C47: 0 | D47: 0
B48: 소내전력비 | C48: 0 | D48: 2
B49: 인건비 | C49: 0 | D49: 2
B50: 법인운영비 | C50: 0 | D50: 2
B51: 주민보상비 | C51: 0 | D51: 0
B52: 도로점용료 | C52: 0 | D52: 0
B53: 예비비 | C53: 0 | D53: 0
B54: 전력거래수수료 | C54: 0 | D54: 0
B55: 관리운영비 성과보수 | C55: 0 | D55: 0
B58: ※ 노란색 셀 = 화면에서 직접 key-in한 입력값(재무모델링 관례). 세금·최저한세·배당가능이익 캡 등 IS(Q)/CF(Q)의 계산 결과는 반복계산·조건부 누적 로직이 얽혀 있어 여기 대상이 아니며 값(baked) 기준입니다. "예시 불러오기"로 채운 실측 오버라이드 분기도 공식이 아니라 실측 사실이라 수식화 대상이 아닙니다.

Sheet Funding
A1: 태양광 발전사업
A2: 자금조달 — 자본금 + 5개 트랜치
B4: 트랜치 조건
B6: 트랜치 | C6: 금액[KRWm] | D6: 투입순서 | E6: 건설금리 | F6: 운영금리 | G6: 거치(yr) | H6: 상환(yr) | I6: 방식 | J6: 상환개시
B7: 자본금 | C7: ='입력값'!C9*100
B8: 선순위A | C8: ='입력값'!C19*100 | E8: ='입력값'!D19 | F8: ='입력값'!E19 | G8: ='입력값'!F19 | H8: ='입력값'!G19 | I8: ='입력값'!H19 | J8: 2026-09-30
B9: 선순위B | C9: ='입력값'!C20*100 | E9: ='입력값'!D20 | F9: ='입력값'!E20 | G9: ='입력값'!F20 | H9: ='입력값'!G20 | I9: ='입력값'!H20 | J9: -
B10: 선순위C | C10: ='입력값'!C21*100 | E10: ='입력값'!D21 | F10: ='입력값'!E21 | G10: ='입력값'!F21 | H10: ='입력값'!G21 | I10: ='입력값'!H21 | J10: -
B11: 선순위D | C11: ='입력값'!C22*100 | E11: ='입력값'!D22 | F11: ='입력값'!E22 | G11: ='입력값'!F22 | H11: ='입력값'!G22 | I11: ='입력값'!H22 | J11: -
B12: 후순위 | C12: ='입력값'!C23*100 | E12: ='입력값'!D23 | F12: ='입력값'!E23 | G12: ='입력값'!F23 | H12: ='입력값'!G23 | I12: ='입력값'!H23 | J12: -
B14: 건설이자(IDC)
B16: IDC 합계[KRWm] | C16: 4405.2812
B17: 총투자비(TIC)[KRWm] | C17: 145474.28
B18: 총사업비(건설이자 제외)[KRWm] | C18: ='입력값'!C8*100
B20: 총사업비 세부내역
B22: 항목 | C22: 금액[KRWm]
B23: ='입력값'!B28
B24: ='입력값'!B29
B25: ='입력값'!B30
B26: ='입력값'!B31
B27: ='입력값'!B32
B28: ='입력값'!B33
B29: ='입력값'!B34
B30: ='입력값'!B35
B31: ='입력값'!B36
B32: ='입력값'!B37
B33: ='입력값'!B38
B34: ='입력값'!B39
B35: 합계 | C35: ='입력값'!C8*100

Sheet Debt
A1: 태양광 발전사업
A2: 차입금 상환 스케줄 — 트랜치별 + 합계
B4: 트랜치별 인출/상환 + 전체 합계
B6: 구 분 | C6: unit | D6: 합 계 | E6: 2024-06-30 | F6: 2024-09-30 | G6: 2024-12-31 | H6: 2025-03-31 | I6: 2025-06-30 | J6: 2025-09-30 | K6: 2025-12-31 | L6: 2026-03-31 | M6: 2026-06-30 | N6: 2026-09-30 | O6: 2026-12-31 | P6: 2027-03-31 | Q6: 2027-06-30 | R6: 2027-09-30 | S6: 2027-12-31 | T6: 2028-03-31 | U6: 2028-06-30 | V6: 2028-09-30 | W6: 2028-12-31 | X6: 2029-03-31 | Y6: 2029-06-30 | Z6: 2029-09-30 | AA6: 2029-12-31 | AB6: 2030-03-31 | AC6: 2030-06-30 | AD6: 2030-09-30 | AE6: 2030-12-31 | AF6: 2031-03-31 | AG6: 2031-06-30 | AH6: 2031-09-30 | AI6: 2031-12-31 | AJ6: 2032-03-31 | AK6: 2032-06-30 | AL6: 2032-09-30 | AM6: 2032-12-31 | AN6: 2033-03-31 | AO6: 2033-06-30 | AP6: 2033-09-30 | AQ6: 2033-12-31 | AR6: 2034-03-31 | AS6: 2034-06-30 | AT6: 2034-09-30 | AU6: 2034-12-31 | AV6: 2035-03-31 | AW6: 2035-06-30 | AX6: 2035-09-30 | AY6: 2035-12-31 | AZ6: 2036-03-31 | BA6: 2036-06-30 | BB6: 2036-09-30 | BC6: 2036-12-31 | BD6: 2037-03-31 | BE6: 2037-06-30 | BF6: 2037-09-30 | BG6: 2037-12-31 | BH6: 2038-03-31 | BI6: 2038-06-30 | BJ6: 2038-09-30 | BK6: 2038-12-31 | BL6: 2039-03-31 | BM6: 2039-06-30 | BN6: 2039-09-30 | BO6: 2039-12-31 | BP6: 2040-03-31 | BQ6: 2040-06-30 | BR6: 2040-09-30 | BS6: 2040-12-31 | BT6: 2041-03-31 | BU6: 2041-06-30 | BV6: 2041-09-30 | BW6: 2041-12-31 | BX6: 2042-03-31 | BY6: 2042-06-30 | BZ6: 2042-09-30 | CA6: 2042-12-31 | CB6: 2043-03-31 | CC6: 2043-06-30 | CD6: 2043-09-30 | CE6: 2043-12-31 | CF6: 2044-03-31 | CG6: 2044-06-30 | CH6: 2044-09-30 | CI6: 2044-12-31 | CJ6: 2045-03-31 | CK6: 2045-06-30 | CL6: 2045-09-30
B8: 선순위A
B9: 기초잔액 | C9: [KRWm] | E9: 0 | F9: =E14 | G9: =F14 | H9: =G14 | I9: =H14 | J9: =I14 | K9: =J14 | L9: =K14 | M9: =L14 | ... CL9: =CK14
B10: 인출 | C10: [KRWm] | D10: 126069 | E10: 21011.5 | F10: 21269.688 | G10: 21531.049 | H10: 21795.622 | I10: 22063.445 | J10: 18397.696 | K10: 0 | L10: 0 | M10: 0 | N10: 0 | O10: 0 | P10: 0 | Q10: 0 | R10: 0 | S10: 0 | T10: 0 | U10: 0 | V10: 0 | W10: 0 | X10: 0 | Y10: 0 | Z10: 0 | AA10: 0 | AB10: 0 | AC10: 0 | AD10: 0 | AE10: 0 | AF10: 0 | AG10: 0 | AH10: 0 | AI10: 0 | AJ10: 0 | AK10: 0 | AL10: 0 | AM10: 0 | AN10: 0 | AO10: 0 | AP10: 0 | AQ10: 0 | AR10: 0 | AS10: 0 | AT10: 0 | AU10: 0 | AV10: 0 | AW10: 0 | AX10: 0 | AY10: 0 | AZ10: 0 | BA10: 0 | BB10: 0 | BC10: 0 | BD10: 0 | BE10: 0 | BF10: 0 | BG10: 0 | BH10: 0 | BI10: 0 | BJ10: 0 | BK10: 0 | BL10: 0 | BM10: 0 | BN10: 0 | BO10: 0 | BP10: 0 | BQ10: 0 | BR10: 0 | BS10: 0 | BT10: 0 | BU10: 0 | BV10: 0 | BW10: 0 | BX10: 0 | BY10: 0 | BZ10: 0 | CA10: 0 | CB10: 0 | CC10: 0 | CD10: 0 | CE10: 0 | CF10: 0 | CG10: 0 | CH10: 0 | CI10: 0 | CJ10: 0 | CK10: 0 | CL10: 0
B11: 건설이자(IDC) | C11: [KRWm] | D11: 4405.2812 | E11: 0 | F11: 288.90813 | G11: 581.36634 | H11: 877.41826 | I11: 1177.1081 | J11: 1480.4804 | K11: 0 | L11: 0 | M11: 0 | N11: 0 | O11: 0 | P11: 0 | Q11: 0 | R11: 0 | S11: 0 | T11: 0 | U11: 0 | V11: 0 | W11: 0 | X11: 0 | Y11: 0 | Z11: 0 | AA11: 0 | AB11: 0 | AC11: 0 | AD11: 0 | AE11: 0 | AF11: 0 | AG11: 0 | AH11: 0 | AI11: 0 | AJ11: 0 | AK11: 0 | AL11: 0 | AM11: 0 | AN11: 0 | AO11: 0 | AP11: 0 | AQ11: 0 | AR11: 0 | AS11: 0 | AT11: 0 | AU11: 0 | AV11: 0 | AW11: 0 | AX11: 0 | AY11: 0 | AZ11: 0 | BA11: 0 | BB11: 0 | BC11: 0 | BD11: 0 | BE11: 0 | BF11: 0 | BG11: 0 | BH11: 0 | BI11: 0 | BJ11: 0 | BK11: 0 | BL11: 0 | BM11: 0 | BN11: 0 | BO11: 0 | BP11: 0 | BQ11: 0 | BR11: 0 | BS11: 0 | BT11: 0 | BU11: 0 | BV11: 0 | BW11: 0 | BX11: 0 | BY11: 0 | BZ11: 0 | CA11: 0 | CB11: 0 | CC11: 0 | CD11: 0 | CE11: 0 | CF11: 0 | CG11: 0 | CH11: 0 | CI11: 0 | CJ11: 0 | CK11: 0 | CL11: 0
B12: 이자(운영) | C12: [KRWm] | D12: 58070.533 | E12: 0 | F12: 0 | G12: 0 | H12: 0 | I12: 0 | J12: 0 | K12: =K9*'입력값'!E19/4 | L12: =L9*'입력값'!E19/4 | M12: =M9*'입력값'!E19/4 | N12: =N9*'입력값'!E19/4 | O12: =O9*'입력값'!E19/4 | P12: =P9*'입력값'!E19/4 | Q12: =Q9*'입력값'!E19/4 | R12: =R9*'입력값'!E19/4 | S12: =S9*'입력값'!E19/4 | T12: =T9*'입력값'!E19/4 | U12: =U9*'입력값'!E19/4 | V12: =V9*'입력값'!E19/4 | W12: =W9*'입력값'!E19/4 | X12: =X9*'입력값'!E19/4 | Y12: =Y9*'입력값'!E19/4 | Z12: =Z9*'입력값'!E19/4 | AA12: =AA9*'입력값'!E19/4 | AB12: =AB9*'입력값'!E19/4 | AC12: =AC9*'입력값'!E19/4 | AD12: =AD9*'입력값'!E19/4 | AE12: =AE9*'입력값'!E19/4 | AF12: =AF9*'입력값'!E19/4 | AG12: =AG9*'입력값'!E19/4 | AH12: =AH9*'입력값'!E19/4 | AI12: =AI9*'입력값'!E19/4 | AJ12: =AJ9*'입력값'!E19/4 | AK12: =AK9*'입력값'!E19/4 | AL12: =AL9*'입력값'!E19/4 | AM12: =AM9*'입력값'!E19/4 | AN12: =AN9*'입력값'!E19/4 | AO12: =AO9*'입력값'!E19/4 | AP12: =AP9*'입력값'!E19/4 | AQ12: =AQ9*'입력값'!E19/4 | AR12: =AR9*'입력값'!E19/4 | AS12: =AS9*'입력값'!E19/4 | AT12: =AT9*'입력값'!E19/4 | AU12: =AU9*'입력값'!E19/4 | AV12: =AV9*'입력값'!E19/4 | AW12: =AW9*'입력값'!E19/4 | AX12: =AX9*'입력값'!E19/4 | AY12: =AY9*'입력값'!E19/4 | AZ12: =AZ9*'입력값'!E19/4 | BA12: =BA9*'입력값'!E19/4 | BB12: =BB9*'입력값'!E19/4 | BC12: =BC9*'입력값'!E19/4 | BD12: =BD9*'입력값'!E19/4 | BE12: =BE9*'입력값'!E19/4 | BF12: =BF9*'입력값'!E19/4 | BG12: =BG9*'입력값'!E19/4 | BH12: =BH9*'입력값'!E19/4 | BI12: =BI9*'입력값'!E19/4 | BJ12: =BJ9*'입력값'!E19/4 | BK12: =BK9*'입력값'!E19/4 | BL12: =BL9*'입력값'!E19/4 | BM12: =BM9*'입력값'!E19/4 | BN12: =BN9*'입력값'!E19/4 | BO12: =BO9*'입력값'!E19/4 | BP12: =BP9*'입력값'!E19/4 | BQ12: =BQ9*'입력값'!E19/4 | BR12: =BR9*'입력값'!E19/4 | BS12: =BS9*'입력값'!E19/4 | BT12: =BT9*'입력값'!E19/4 | BU12: =BU9*'입력값'!E19/4 | BV12: =BV9*'입력값'!E19/4 | BW12: =BW9*'입력값'!E19/4 | BX12: =BX9*'입력값'!E19/4 | BY12: =BY9*'입력값'!E19/4 | BZ12: =BZ9*'입력값'!E19/4 | CA12: =CA9*'입력값'!E19/4 | CB12: =CB9*'입력값'!E19/4 | CC12: =CC9*'입력값'!E19/4 | CD12: =CD9*'입력값'!E19/4 | CE12: =CE9*'입력값'!E19/4 | CF12: =CF9*'입력값'!E19/4 | CG12: =CG9*'입력값'!E19/4 | CH12: =CH9*'입력값'!E19/4 | CI12: =CI9*'입력값'!E19/4 | CJ12: =CJ9*'입력값'!E19/4 | CK12: =CK9*'입력값'!E19/4 | CL12: =CL9*'입력값'!E19/4
B13: 원금상환 | C13: [KRWm] | D13: 126069 | E13: 0 | F13: 0 | G13: 0 | H13: 0 | I13: 0 | J13: 0 | K13: 0 | L13: 0 | M13: 0 | N13: ='입력값'!C19*100/60 | O13: ='입력값'!C19*100/60 | P13: ='입력값'!C19*100/60 | Q13: ='입력값'!C19*100/60 | R13: ='입력값'!C19*100/60 | S13: ='입력값'!C19*100/60 | T13: ='입력값'!C19*100/60 | U13: ='입력값'!C19*100/60 | V13: ='입력값'!C19*100/60 | W13: ='입력값'!C19*100/60 | X13: ='입력값'!C19*100/60 | Y13: ='입력값'!C19*100/60 | Z13: ='입력값'!C19*100/60 | AA13: ='입력값'!C19*100/60 | AB13: ='입력값'!C19*100/60 | AC13: ='입력값'!C19*100/60 | AD13: ='입력값'!C19*100/60 | AE13: ='입력값'!C19*100/60 | AF13: ='입력값'!C19*100/60 | AG13: ='입력값'!C19*100/60 | AH13: ='입력값'!C19*100/60 | AI13: ='입력값'!C19*100/60 | AJ13: ='입력값'!C19*100/60 | AK13: ='입력값'!C19*100/60 | AL13: ='입력값'!C19*100/60 | AM13: ='입력값'!C19*100/60 | AN13: ='입력값'!C19*100/60 | AO13: ='입력값'!C19*100/60 | AP13: ='입력값'!C19*100/60 | AQ13: ='입력값'!C19*100/60 | AR13: ='입력값'!C19*100/60 | AS13: ='입력값'!C19*100/60 | AT13: ='입력값'!C19*100/60 | AU13: ='입력값'!C19*100/60 | AV13: ='입력값'!C19*100/60 | AW13: ='입력값'!C19*100/60 | AX13: ='입력값'!C19*100/60 | AY13: ='입력값'!C19*100/60 | AZ13: ='입력값'!C19*100/60 | BA13: ='입력값'!C19*100/60 | BB13: ='입력값'!C19*100/60 | BC13: ='입력값'!C19*100/60 | BD13: ='입력값'!C19*100/60 | BE13: ='입력값'!C19*100/60 | BF13: ='입력값'!C19*100/60 | BG13: ='입력값'!C19*100/60 | BH13: ='입력값'!C19*100/60 | BI13: ='입력값'!C19*100/60 | BJ13: ='입력값'!C19*100/60 | BK13: ='입력값'!C19*100/60 | BL13: ='입력값'!C19*100/60 | BM13: ='입력값'!C19*100/60 | BN13: ='입력값'!C19*100/60 | BO13: ='입력값'!C19*100/60 | BP13: ='입력값'!C19*100/60 | BQ13: ='입력값'!C19*100/60 | BR13: ='입력값'!C19*100/60 | BS13: ='입력값'!C19*100/60 | BT13: ='입력값'!C19*100/60 | BU13: ='입력값'!C19*100/60 | BV13: 0 | BW13: 0 | BX13: 0 | BY13: 0 | BZ13: 0 | CA13: 0 | CB13: 0 | CC13: 0 | CD13: 0 | CE13: 0 | CF13: 0 | CG13: 0 | CH13: 0 | CI13: 0 | CJ13: 0 | CK13: 0 | CL13: 0
B14: 기말잔액 | C14: [KRWm] | E14: =E9+E10-E13 | F14: =F9+F10-F13 | G14: =G9+G10-G13 | H14: =H9+H10-H13 | I14: =I9+I10-I13 | J14: =J9+J10-J13 | K14: =K9+K10-K13 | L14: =L9+L10-L13 | ... CL14: =CL9+CL10-CL13
B15: 미상환 잔액(검증용) | C15: [KRWm] | D15: 1.3005774e-10 | F15: 완전상환 확인 (OK)
B17: 선순위B
B18: 기초잔액 | C18: [KRWm] | E18: 0 | F18: =E23 | G18: =F23 | H18: =G23 | I18: =H23 | J18: =I23 | K18: =J23 | L18: =K23 | M18: =L23 | ... CL18: =CK23
B19: 인출 | C19: [KRWm] | D19: 0 | E19: 0 | F19: 0 | G19: 0 | H19: 0 | I19: 0 | J19: 0 | K19: 0 | L19: 0 | M19: 0 | N19: 0 | O19: 0 | P19: 0 | Q19: 0 | R19: 0 | S19: 0 | T19: 0 | U19: 0 | V19: 0 | W19: 0 | X19: 0 | Y19: 0 | Z19: 0 | AA19: 0 | AB19: 0 | AC19: 0 | AD19: 0 | AE19: 0 | AF19: 0 | AG19: 0 | AH19: 0 | AI19: 0 | AJ19: 0 | AK19: 0 | AL19: 0 | AM19: 0 | AN19: 0 | AO19: 0 | AP19: 0 | AQ19: 0 | AR19: 0 | AS19: 0 | AT19: 0 | AU19: 0 | AV19: 0 | AW19: 0 | AX19: 0 | AY19: 0 | AZ19: 0 | BA19: 0 | BB19: 0 | BC19: 0 | BD19: 0 | BE19: 0 | BF19: 0 | BG19: 0 | BH19: 0 | BI19: 0 | BJ19: 0 | BK19: 0 | BL19: 0 | BM19: 0 | BN19: 0 | BO19: 0 | BP19: 0 | BQ19: 0 | BR19: 0 | BS19: 0 | BT19: 0 | BU19: 0 | BV19: 0 | BW19: 0 | BX19: 0 | BY19: 0 | BZ19: 0 | CA19: 0 | CB19: 0 | CC19: 0 | CD19: 0 | CE19: 0 | CF19: 0 | CG19: 0 | CH19: 0 | CI19: 0 | CJ19: 0 | CK19: 0 | CL19: 0
B20: 건설이자(IDC) | C20: [KRWm] | D20: 0 | E20: 0 | F20: 0 | G20: 0 | H20: 0 | I20: 0 | J20: 0 | K20: 0 | L20: 0 | M20: 0 | N20: 0 | O20: 0 | P20: 0 | Q20: 0 | R20: 0 | S20: 0 | T20: 0 | U20: 0 | V20: 0 | W20: 0 | X20: 0 | Y20: 0 | Z20: 0 | AA20: 0 | AB20: 0 | AC20: 0 | AD20: 0 | AE20: 0 | AF20: 0 | AG20: 0 | AH20: 0 | AI20: 0 | AJ20: 0 | AK20: 0 | AL20: 0 | AM20: 0 | AN20: 0 | AO20: 0 | AP20: 0 | AQ20: 0 | AR20: 0 | AS20: 0 | AT20: 0 | AU20: 0 | AV20: 0 | AW20: 0 | AX20: 0 | AY20: 0 | AZ20: 0 | BA20: 0 | BB20: 0 | BC20: 0 | BD20: 0 | BE20: 0 | BF20: 0 | BG20: 0 | BH20: 0 | BI20: 0 | BJ20: 0 | BK20: 0 | BL20: 0 | BM20: 0 | BN20: 0 | BO20: 0 | BP20: 0 | BQ20: 0 | BR20: 0 | BS20: 0 | BT20: 0 | BU20: 0 | BV20: 0 | BW20: 0 | BX20: 0 | BY20: 0 | BZ20: 0 | CA20: 0 | CB20: 0 | CC20: 0 | CD20: 0 | CE20: 0 | CF20: 0 | CG20: 0 | CH20: 0 | CI20: 0 | CJ20: 0 | CK20: 0 | CL20: 0
B21: 이자(운영) | C21: [KRWm] | D21: 0 | E21: 0 | F21: 0 | G21: 0 | H21: 0 | I21: 0 | J21: 0 | K21: =K18*'입력값'!E20/4 | L21: =L18*'입력값'!E20/4 | M21: =M18*'입력값'!E20/4 | N21: =N18*'입력값'!E20/4 | O21: =O18*'입력값'!E20/4 | P21: =P18*'입력값'!E20/4 | Q21: =Q18*'입력값'!E20/4 | R21: =R18*'입력값'!E20/4 | S21: =S18*'입력값'!E20/4 | T21: =T18*'입력값'!E20/4 | U21: =U18*'입력값'!E20/4 | V21: =V18*'입력값'!E20/4 | W21: =W18*'입력값'!E20/4 | X21: =X18*'입력값'!E20/4 | Y21: =Y18*'입력값'!E20/4 | Z21: =Z18*'입력값'!E20/4 | AA21: =AA18*'입력값'!E20/4 | AB21: =AB18*'입력값'!E20/4 | AC21: =AC18*'입력값'!E20/4 | AD21: =AD18*'입력값'!E20/4 | AE21: =AE18*'입력값'!E20/4 | AF21: =AF18*'입력값'!E20/4 | AG21: =AG18*'입력값'!E20/4 | AH21: =AH18*'입력값'!E20/4 | AI21: =AI18*'입력값'!E20/4 | AJ21: =AJ18*'입력값'!E20/4 | AK21: =AK18*'입력값'!E20/4 | AL21: =AL18*'입력값'!E20/4 | AM21: =AM18*'입력값'!E20/4 | AN21: =AN18*'입력값'!E20/4 | AO21: =AO18*'입력값'!E20/4 | AP21: =AP18*'입력값'!E20/4 | AQ21: =AQ18*'입력값'!E20/4 | AR21: =AR18*'입력값'!E20/4 | AS21: =AS18*'입력값'!E20/4 | AT21: =AT18*'입력값'!E20/4 | AU21: =AU18*'입력값'!E20/4 | AV21: =AV18*'입력값'!E20/4 | AW21: =AW18*'입력값'!E20/4 | AX21: =AX18*'입력값'!E20/4 | AY21: =AY18*'입력값'!E20/4 | AZ21: =AZ18*'입력값'!E20/4 | BA21: =BA18*'입력값'!E20/4 | BB21: =BB18*'입력값'!E20/4 | BC21: =BC18*'입력값'!E20/4 | BD21: =BD18*'입력값'!E20/4 | BE21: =BE18*'입력값'!E20/4 | BF21: =BF18*'입력값'!E20/4 | BG21: =BG18*'입력값'!E20/4 | BH21: =BH18*'입력값'!E20/4 | BI21: =BI18*'입력값'!E20/4 | BJ21: =BJ18*'입력값'!E20/4 | BK21: =BK18*'입력값'!E20/4 | BL21: =BL18*'입력값'!E20/4 | BM21: =BM18*'입력값'!E20/4 | BN21: =BN18*'입력값'!E20/4 | BO21: =BO18*'입력값'!E20/4 | BP21: =BP18*'입력값'!E20/4 | BQ21: =BQ18*'입력값'!E20/4 | BR21: =BR18*'입력값'!E20/4 | BS21: =BS18*'입력값'!E20/4 | BT21: =BT18*'입력값'!E20/4 | BU21: =BU18*'입력값'!E20/4 | BV21: =BV18*'입력값'!E20/4 | BW21: =BW18*'입력값'!E20/4 | BX21: =BX18*'입력값'!E20/4 | BY21: =BY18*'입력값'!E20/4 | BZ21: =BZ18*'입력값'!E20/4 | CA21: =CA18*'입력값'!E20/4 | CB21: =CB18*'입력값'!E20/4 | CC21: =CC18*'입력값'!E20/4 | CD21: =CD18*'입력값'!E20/4 | CE21: =CE18*'입력값'!E20/4 | CF21: =CF18*'입력값'!E20/4 | CG21: =CG18*'입력값'!E20/4 | CH21: =CH18*'입력값'!E20/4 | CI21: =CI18*'입력값'!E20/4 | CJ21: =CJ18*'입력값'!E20/4 | CK21: =CK18*'입력값'!E20/4 | CL21: =CL18*'입력값'!E20/4
B22: 원금상환 | C22: [KRWm] | D22: 0 | E22: 0 | F22: 0 | G22: 0 | H22: 0 | I22: 0 | J22: 0 | K22: 0 | L22: 0 | M22: 0 | N22: 0 | O22: 0 | P22: 0 | Q22: 0 | R22: 0 | S22: 0 | T22: 0 | U22: 0 | V22: 0 | W22: 0 | X22: 0 | Y22: 0 | Z22: 0 | AA22: 0 | AB22: 0 | AC22: 0 | AD22: 0 | AE22: 0 | AF22: 0 | AG22: 0 | AH22: 0 | AI22: 0 | AJ22: 0 | AK22: 0 | AL22: 0 | AM22: 0 | AN22: 0 | AO22: 0 | AP22: 0 | AQ22: 0 | AR22: 0 | AS22: 0 | AT22: 0 | AU22: 0 | AV22: 0 | AW22: 0 | AX22: 0 | AY22: 0 | AZ22: 0 | BA22: 0 | BB22: 0 | BC22: 0 | BD22: 0 | BE22: 0 | BF22: 0 | BG22: 0 | BH22: 0 | BI22: 0 | BJ22: 0 | BK22: 0 | BL22: 0 | BM22: 0 | BN22: 0 | BO22: 0 | BP22: 0 | BQ22: 0 | BR22: 0 | BS22: 0 | BT22: 0 | BU22: 0 | BV22: 0 | BW22: 0 | BX22: 0 | BY22: 0 | BZ22: 0 | CA22: 0 | CB22: 0 | CC22: 0 | CD22: 0 | CE22: 0 | CF22: 0 | CG22: 0 | CH22: 0 | CI22: 0 | CJ22: 0 | CK22: 0 | CL22: 0
B23: 기말잔액 | C23: [KRWm] | E23: =E18+E19-E22 | F23: =F18+F19-F22 | G23: =G18+G19-G22 | H23: =H18+H19-H22 | I23: =I18+I19-I22 | J23: =J18+J19-J22 | K23: =K18+K19-K22 | L23: =L18+L19-L22 | ... CL23: =CL18+CL19-CL22
B24: 미상환 잔액(검증용) | C24: [KRWm] | D24: 0 | F24: 완전상환 확인 (OK) | H24: ※ 방식 3(직접 키인) 또는 미사용 트랜치 — 값(baked) 기준
B26: 선순위C
B27: 기초잔액 | C27: [KRWm] | E27: 0 | F27: =E32 | G27: =F32 | H27: =G32 | I27: =H32 | J27: =I32 | K27: =J32 | L27: =K32 | M27: =L32 | ... CL27: =CK32
B28: 인출 | C28: [KRWm] | D28: 0 | E28: 0 | F28: 0 | G28: 0 | H28: 0 | I28: 0 | J28: 0 | K28: 0 | L28: 0 | M28: 0 | N28: 0 | O28: 0 | P28: 0 | Q28: 0 | R28: 0 | S28: 0 | T28: 0 | U28: 0 | V28: 0 | W28: 0 | X28: 0 | Y28: 0 | Z28: 0 | AA28: 0 | AB28: 0 | AC28: 0 | AD28: 0 | AE28: 0 | AF28: 0 | AG28: 0 | AH28: 0 | AI28: 0 | AJ28: 0 | AK28: 0 | AL28: 0 | AM28: 0 | AN28: 0 | AO28: 0 | AP28: 0 | AQ28: 0 | AR28: 0 | AS28: 0 | AT28: 0 | AU28: 0 | AV28: 0 | AW28: 0 | AX28: 0 | AY28: 0 | AZ28: 0 | BA28: 0 | BB28: 0 | BC28: 0 | BD28: 0 | BE28: 0 | BF28: 0 | BG28: 0 | BH28: 0 | BI28: 0 | BJ28: 0 | BK28: 0 | BL28: 0 | BM28: 0 | BN28: 0 | BO28: 0 | BP28: 0 | BQ28: 0 | BR28: 0 | BS28: 0 | BT28: 0 | BU28: 0 | BV28: 0 | BW28: 0 | BX28: 0 | BY28: 0 | BZ28: 0 | CA28: 0 | CB28: 0 | CC28: 0 | CD28: 0 | CE28: 0 | CF28: 0 | CG28: 0 | CH28: 0 | CI28: 0 | CJ28: 0 | CK28: 0 | CL28: 0
B29: 건설이자(IDC) | C29: [KRWm] | D29: 0 | E29: 0 | F29: 0 | G29: 0 | H29: 0 | I29: 0 | J29: 0 | K29: 0 | L29: 0 | M29: 0 | N29: 0 | O29: 0 | P29: 0 | Q29: 0 | R29: 0 | S29: 0 | T29: 0 | U29: 0 | V29: 0 | W29: 0 | X29: 0 | Y29: 0 | Z29: 0 | AA29: 0 | AB29: 0 | AC29: 0 | AD29: 0 | AE29: 0 | AF29: 0 | AG29: 0 | AH29: 0 | AI29: 0 | AJ29: 0 | AK29: 0 | AL29: 0 | AM29: 0 | AN29: 0 | AO29: 0 | AP29: 0 | AQ29: 0 | AR29: 0 | AS29: 0 | AT29: 0 | AU29: 0 | AV29: 0 | AW29: 0 | AX29: 0 | AY29: 0 | AZ29: 0 | BA29: 0 | BB29: 0 | BC29: 0 | BD29: 0 | BE29: 0 | BF29: 0 | BG29: 0 | BH29: 0 | BI29: 0 | BJ29: 0 | BK29: 0 | BL29: 0 | BM29: 0 | BN29: 0 | BO29: 0 | BP29: 0 | BQ29: 0 | BR29: 0 | BS29: 0 | BT29: 0 | BU29: 0 | BV29: 0 | BW29: 0 | BX29: 0 | BY29: 0 | BZ29: 0 | CA29: 0 | CB29: 0 | CC29: 0 | CD29: 0 | CE29: 0 | CF29: 0 | CG29: 0 | CH29: 0 | CI29: 0 | CJ29: 0 | CK29: 0 | CL29: 0
B30: 이자(운영) | C30: [KRWm] | D30: 0 | E30: 0 | F30: 0 | G30: 0 | H30: 0 | I30: 0 | J30: 0 | K30: =K27*'입력값'!E21/4 | L30: =L27*'입력값'!E21/4 | M30: =M27*'입력값'!E21/4 | N30: =N27*'입력값'!E21/4 | O30: =O27*'입력값'!E21/4 | P30: =P27*'입력값'!E21/4 | Q30: =Q27*'입력값'!E21/4 | R30: =R27*'입력값'!E21/4 | S30: =S27*'입력값'!E21/4 | T30: =T27*'입력값'!E21/4 | U30: =U27*'입력값'!E21/4 | V30: =V27*'입력값'!E21/4 | W30: =W27*'입력값'!E21/4 | X30: =X27*'입력값'!E21/4 | Y30: =Y27*'입력값'!E21/4 | Z30: =Z27*'입력값'!E21/4 | AA30: =AA27*'입력값'!E21/4 | AB30: =AB27*'입력값'!E21/4 | AC30: =AC27*'입력값'!E21/4 | AD30: =AD27*'입력값'!E21/4 | AE30: =AE27*'입력값'!E21/4 | AF30: =AF27*'입력값'!E21/4 | AG30: =AG27*'입력값'!E21/4 | AH30: =AH27*'입력값'!E21/4 | AI30: =AI27*'입력값'!E21/4 | AJ30: =AJ27*'입력값'!E21/4 | AK30: =AK27*'입력값'!E21/4 | AL30: =AL27*'입력값'!E21/4 | AM30: =AM27*'입력값'!E21/4 | AN30: =AN27*'입력값'!E21/4 | AO30: =AO27*'입력값'!E21/4 | AP30: =AP27*'입력값'!E21/4 | AQ30: =AQ27*'입력값'!E21/4 | AR30: =AR27*'입력값'!E21/4 | AS30: =AS27*'입력값'!E21/4 | AT30: =AT27*'입력값'!E21/4 | AU30: =AU27*'입력값'!E21/4 | AV30: =AV27*'입력값'!E21/4 | AW30: =AW27*'입력값'!E21/4 | AX30: =AX27*'입력값'!E21/4 | AY30: =AY27*'입력값'!E21/4 | AZ30: =AZ27*'입력값'!E21/4 | BA30: =BA27*'입력값'!E21/4 | BB30: =BB27*'입력값'!E21/4 | BC30: =BC27*'입력값'!E21/4 | BD30: =BD27*'입력값'!E21/4 | BE30: =BE27*'입력값'!E21/4 | BF30: =BF27*'입력값'!E21/4 | BG30: =BG27*'입력값'!E21/4 | BH30: =BH27*'입력값'!E21/4 | BI30: =BI27*'입력값'!E21/4 | BJ30: =BJ27*'입력값'!E21/4 | BK30: =BK27*'입력값'!E21/4 | BL30: =BL27*'입력값'!E21/4 | BM30: =BM27*'입력값'!E21/4 | BN30: =BN27*'입력값'!E21/4 | BO30: =BO27*'입력값'!E21/4 | BP30: =BP27*'입력값'!E21/4 | BQ30: =BQ27*'입력값'!E21/4 | BR30: =BR27*'입력값'!E21/4 | BS30: =BS27*'입력값'!E21/4 | BT30: =BT27*'입력값'!E21/4 | BU30: =BU27*'입력값'!E21/4 | BV30: =BV27*'입력값'!E21/4 | BW30: =BW27*'입력값'!E21/4 | BX30: =BX27*'입력값'!E21/4 | BY30: =BY27*'입력값'!E21/4 | BZ30: =BZ27*'입력값'!E21/4 | CA30: =CA27*'입력값'!E21/4 | CB30: =CB27*'입력값'!E21/4 | CC30: =CC27*'입력값'!E21/4 | CD30: =CD27*'입력값'!E21/4 | CE30: =CE27*'입력값'!E21/4 | CF30: =CF27*'입력값'!E21/4 | CG30: =CG27*'입력값'!E21/4 | CH30: =CH27*'입력값'!E21/4 | CI30: =CI27*'입력값'!E21/4 | CJ30: =CJ27*'입력값'!E21/4 | CK30: =CK27*'입력값'!E21/4 | CL30: =CL27*'입력값'!E21/4
B31: 원금상환 | C31: [KRWm] | D31: 0 | E31: 0 | F31: 0 | G31: 0 | H31: 0 | I31: 0 | J31: 0 | K31: 0 | L31: 0 | M31: 0 | N31: 0 | O31: 0 | P31: 0 | Q31: 0 | R31: 0 | S31: 0 | T31: 0 | U31: 0 | V31: 0 | W31: 0 | X31: 0 | Y31: 0 | Z31: 0 | AA31: 0 | AB31: 0 | AC31: 0 | AD31: 0 | AE31: 0 | AF31: 0 | AG31: 0 | AH31: 0 | AI31: 0 | AJ31: 0 | AK31: 0 | AL31: 0 | AM31: 0 | AN31: 0 | AO31: 0 | AP31: 0 | AQ31: 0 | AR31: 0 | AS31: 0 | AT31: 0 | AU31: 0 | AV31: 0 | AW31: 0 | AX31: 0 | AY31: 0 | AZ31: 0 | BA31: 0 | BB31: 0 | BC31: 0 | BD31: 0 | BE31: 0 | BF31: 0 | BG31: 0 | BH31: 0 | BI31: 0 | BJ31: 0 | BK31: 0 | BL31: 0 | BM31: 0 | BN31: 0 | BO31: 0 | BP31: 0 | BQ31: 0 | BR31: 0 | BS31: 0 | BT31: 0 | BU31: 0 | BV31: 0 | BW31: 0 | BX31: 0 | BY31: 0 | BZ31: 0 | CA31: 0 | CB31: 0 | CC31: 0 | CD31: 0 | CE31: 0 | CF31: 0 | CG31: 0 | CH31: 0 | CI31: 0 | CJ31: 0 | CK31: 0 | CL31: 0
B32: 기말잔액 | C32: [KRWm] | E32: =E27+E28-E31 | F32: =F27+F28-F31 | G32: =G27+G28-G31 | H32: =H27+H28-H31 | I32: =I27+I28-I31 | J32: =J27+J28-J31 | K32: =K27+K28-K31 | L32: =L27+L28-L31 | ... CL32: =CL27+CL28-CL31
B33: 미상환 잔액(검증용) | C33: [KRWm] | D33: 0 | F33: 완전상환 확인 (OK) | H33: ※ 방식 3(직접 키인) 또는 미사용 트랜치 — 값(baked) 기준
B35: 선순위D
B36: 기초잔액 | C36: [KRWm] | E36: 0 | F36: =E41 | G36: =F41 | H36: =G41 | I36: =H41 | J36: =I41 | K36: =J41 | L36: =K41 | M36: =L41 | ... CL36: =CK41
B37: 인출 | C37: [KRWm] | D37: 0 | E37: 0 | F37: 0 | G37: 0 | H37: 0 | I37: 0 | J37: 0 | K37: 0 | L37: 0 | M37: 0 | N37: 0 | O37: 0 | P37: 0 | Q37: 0 | R37: 0 | S37: 0 | T37: 0 | U37: 0 | V37: 0 | W37: 0 | X37: 0 | Y37: 0 | Z37: 0 | AA37: 0 | AB37: 0 | AC37: 0 | AD37: 0 | AE37: 0 | AF37: 0 | AG37: 0 | AH37: 0 | AI37: 0 | AJ37: 0 | AK37: 0 | AL37: 0 | AM37: 0 | AN37: 0 | AO37: 0 | AP37: 0 | AQ37: 0 | AR37: 0 | AS37: 0 | AT37: 0 | AU37: 0 | AV37: 0 | AW37: 0 | AX37: 0 | AY37: 0 | AZ37: 0 | BA37: 0 | BB37: 0 | BC37: 0 | BD37: 0 | BE37: 0 | BF37: 0 | BG37: 0 | BH37: 0 | BI37: 0 | BJ37: 0 | BK37: 0 | BL37: 0 | BM37: 0 | BN37: 0 | BO37: 0 | BP37: 0 | BQ37: 0 | BR37: 0 | BS37: 0 | BT37: 0 | BU37: 0 | BV37: 0 | BW37: 0 | BX37: 0 | BY37: 0 | BZ37: 0 | CA37: 0 | CB37: 0 | CC37: 0 | CD37: 0 | CE37: 0 | CF37: 0 | CG37: 0 | CH37: 0 | CI37: 0 | CJ37: 0 | CK37: 0 | CL37: 0
B38: 건설이자(IDC) | C38: [KRWm] | D38: 0 | E38: 0 | F38: 0 | G38: 0 | H38: 0 | I38: 0 | J38: 0 | K38: 0 | L38: 0 | M38: 0 | N38: 0 | O38: 0 | P38: 0 | Q38: 0 | R38: 0 | S38: 0 | T38: 0 | U38: 0 | V38: 0 | W38: 0 | X38: 0 | Y38: 0 | Z38: 0 | AA38: 0 | AB38: 0 | AC38: 0 | AD38: 0 | AE38: 0 | AF38: 0 | AG38: 0 | AH38: 0 | AI38: 0 | AJ38: 0 | AK38: 0 | AL38: 0 | AM38: 0 | AN38: 0 | AO38: 0 | AP38: 0 | AQ38: 0 | AR38: 0 | AS38: 0 | AT38: 0 | AU38: 0 | AV38: 0 | AW38: 0 | AX38: 0 | AY38: 0 | AZ38: 0 | BA38: 0 | BB38: 0 | BC38: 0 | BD38: 0 | BE38: 0 | BF38: 0 | BG38: 0 | BH38: 0 | BI38: 0 | BJ38: 0 | BK38: 0 | BL38: 0 | BM38: 0 | BN38: 0 | BO38: 0 | BP38: 0 | BQ38: 0 | BR38: 0 | BS38: 0 | BT38: 0 | BU38: 0 | BV38: 0 | BW38: 0 | BX38: 0 | BY38: 0 | BZ38: 0 | CA38: 0 | CB38: 0 | CC38: 0 | CD38: 0 | CE38: 0 | CF38: 0 | CG38: 0 | CH38: 0 | CI38: 0 | CJ38: 0 | CK38: 0 | CL38: 0
B39: 이자(운영) | C39: [KRWm] | D39: 0 | E39: 0 | F39: 0 | G39: 0 | H39: 0 | I39: 0 | J39: 0 | K39: =K36*'입력값'!E22/4 | L39: =L36*'입력값'!E22/4 | M39: =M36*'입력값'!E22/4 | N39: =N36*'입력값'!E22/4 | O39: =O36*'입력값'!E22/4 | P39: =P36*'입력값'!E22/4 | Q39: =Q36*'입력값'!E22/4 | R39: =R36*'입력값'!E22/4 | S39: =S36*'입력값'!E22/4 | T39: =T36*'입력값'!E22/4 | U39: =U36*'입력값'!E22/4 | V39: =V36*'입력값'!E22/4 | W39: =W36*'입력값'!E22/4 | X39: =X36*'입력값'!E22/4 | Y39: =Y36*'입력값'!E22/4 | Z39: =Z36*'입력값'!E22/4 | AA39: =AA36*'입력값'!E22/4 | AB39: =AB36*'입력값'!E22/4 | AC39: =AC36*'입력값'!E22/4 | AD39: =AD36*'입력값'!E22/4 | AE39: =AE36*'입력값'!E22/4 | AF39: =AF36*'입력값'!E22/4 | AG39: =AG36*'입력값'!E22/4 | AH39: =AH36*'입력값'!E22/4 | AI39: =AI36*'입력값'!E22/4 | AJ39: =AJ36*'입력값'!E22/4 | AK39: =AK36*'입력값'!E22/4 | AL39: =AL36*'입력값'!E22/4 | AM39: =AM36*'입력값'!E22/4 | AN39: =AN36*'입력값'!E22/4 | AO39: =AO36*'입력값'!E22/4 | AP39: =AP36*'입력값'!E22/4 | AQ39: =AQ36*'입력값'!E22/4 | AR39: =AR36*'입력값'!E22/4 | AS39: =AS36*'입력값'!E22/4 | AT39: =AT36*'입력값'!E22/4 | AU39: =AU36*'입력값'!E22/4 | AV39: =AV36*'입력값'!E22/4 | AW39: =AW36*'입력값'!E22/4 | AX39: =AX36*'입력값'!E22/4 | AY39: =AY36*'입력값'!E22/4 | AZ39: =AZ36*'입력값'!E22/4 | BA39: =BA36*'입력값'!E22/4 | BB39: =BB36*'입력값'!E22/4 | BC39: =BC36*'입력값'!E22/4 | BD39: =BD36*'입력값'!E22/4 | BE39: =BE36*'입력값'!E22/4 | BF39: =BF36*'입력값'!E22/4 | BG39: =BG36*'입력값'!E22/4 | BH39: =BH36*'입력값'!E22/4 | BI39: =BI36*'입력값'!E22/4 | BJ39: =BJ36*'입력값'!E22/4 | BK39: =BK36*'입력값'!E22/4 | BL39: =BL36*'입력값'!E22/4 | BM39: =BM36*'입력값'!E22/4 | BN39: =BN36*'입력값'!E22/4 | BO39: =BO36*'입력값'!E22/4 | BP39: =BP36*'입력값'!E22/4 | BQ39: =BQ36*'입력값'!E22/4 | BR39: =BR36*'입력값'!E22/4 | BS39: =BS36*'입력값'!E22/4 | BT39: =BT36*'입력값'!E22/4 | BU39: =BU36*'입력값'!E22/4 | BV39: =BV36*'입력값'!E22/4 | BW39: =BW36*'입력값'!E22/4 | BX39: =BX36*'입력값'!E22/4 | BY39: =BY36*'입력값'!E22/4 | BZ39: =BZ36*'입력값'!E22/4 | CA39: =CA36*'입력값'!E22/4 | CB39: =CB36*'입력값'!E22/4 | CC39: =CC36*'입력값'!E22/4 | CD39: =CD36*'입력값'!E22/4 | CE39: =CE36*'입력값'!E22/4 | CF39: =CF36*'입력값'!E22/4 | CG39: =CG36*'입력값'!E22/4 | CH39: =CH36*'입력값'!E22/4 | CI39: =CI36*'입력값'!E22/4 | CJ39: =CJ36*'입력값'!E22/4 | CK39: =CK36*'입력값'!E22/4 | CL39: =CL36*'입력값'!E22/4
B40: 원금상환 | C40: [KRWm] | D40: 0 | E40: 0 | F40: 0 | G40: 0 | H40: 0 | I40: 0 | J40: 0 | K40: 0 | L40: 0 | M40: 0 | N40: 0 | O40: 0 | P40: 0 | Q40: 0 | R40: 0 | S40: 0 | T40: 0 | U40: 0 | V40: 0 | W40: 0 | X40: 0 | Y40: 0 | Z40: 0 | AA40: 0 | AB40: 0 | AC40: 0 | AD40: 0 | AE40: 0 | AF40: 0 | AG40: 0 | AH40: 0 | AI40: 0 | AJ40: 0 | AK40: 0 | AL40: 0 | AM40: 0 | AN40: 0 | AO40: 0 | AP40: 0 | AQ40: 0 | AR40: 0 | AS40: 0 | AT40: 0 | AU40: 0 | AV40: 0 | AW40: 0 | AX40: 0 | AY40: 0 | AZ40: 0 | BA40: 0 | BB40: 0 | BC40: 0 | BD40: 0 | BE40: 0 | BF40: 0 | BG40: 0 | BH40: 0 | BI40: 0 | BJ40: 0 | BK40: 0 | BL40: 0 | BM40: 0 | BN40: 0 | BO40: 0 | BP40: 0 | BQ40: 0 | BR40: 0 | BS40: 0 | BT40: 0 | BU40: 0 | BV40: 0 | BW40: 0 | BX40: 0 | BY40: 0 | BZ40: 0 | CA40: 0 | CB40: 0 | CC40: 0 | CD40: 0 | CE40: 0 | CF40: 0 | CG40: 0 | CH40: 0 | CI40: 0 | CJ40: 0 | CK40: 0 | CL40: 0
B41: 기말잔액 | C41: [KRWm] | E41: =E36+E37-E40 | F41: =F36+F37-F40 | G41: =G36+G37-G40 | H41: =H36+H37-H40 | I41: =I36+I37-I40 | J41: =J36+J37-J40 | K41: =K36+K37-K40 | L41: =L36+L37-L40 | ... CL41: =CL36+CL37-CL40
B42: 미상환 잔액(검증용) | C42: [KRWm] | D42: 0 | F42: 완전상환 확인 (OK) | H42: ※ 방식 3(직접 키인) 또는 미사용 트랜치 — 값(baked) 기준
B44: 후순위
B45: 기초잔액 | C45: [KRWm] | E45: 0 | F45: =E50 | G45: =F50 | H45: =G50 | I45: =H50 | J45: =I50 | K45: =J50 | L45: =K50 | M45: =L50 | ... CL45: =CK50
B46: 인출 | C46: [KRWm] | D46: 0 | E46: 0 | F46: 0 | G46: 0 | H46: 0 | I46: 0 | J46: 0 | K46: 0 | L46: 0 | M46: 0 | N46: 0 | O46: 0 | P46: 0 | Q46: 0 | R46: 0 | S46: 0 | T46: 0 | U46: 0 | V46: 0 | W46: 0 | X46: 0 | Y46: 0 | Z46: 0 | AA46: 0 | AB46: 0 | AC46: 0 | AD46: 0 | AE46: 0 | AF46: 0 | AG46: 0 | AH46: 0 | AI46: 0 | AJ46: 0 | AK46: 0 | AL46: 0 | AM46: 0 | AN46: 0 | AO46: 0 | AP46: 0 | AQ46: 0 | AR46: 0 | AS46: 0 | AT46: 0 | AU46: 0 | AV46: 0 | AW46: 0 | AX46: 0 | AY46: 0 | AZ46: 0 | BA46: 0 | BB46: 0 | BC46: 0 | BD46: 0 | BE46: 0 | BF46: 0 | BG46: 0 | BH46: 0 | BI46: 0 | BJ46: 0 | BK46: 0 | BL46: 0 | BM46: 0 | BN46: 0 | BO46: 0 | BP46: 0 | BQ46: 0 | BR46: 0 | BS46: 0 | BT46: 0 | BU46: 0 | BV46: 0 | BW46: 0 | BX46: 0 | BY46: 0 | BZ46: 0 | CA46: 0 | CB46: 0 | CC46: 0 | CD46: 0 | CE46: 0 | CF46: 0 | CG46: 0 | CH46: 0 | CI46: 0 | CJ46: 0 | CK46: 0 | CL46: 0
B47: 건설이자(IDC) | C47: [KRWm] | D47: 0 | E47: 0 | F47: 0 | G47: 0 | H47: 0 | I47: 0 | J47: 0 | K47: 0 | L47: 0 | M47: 0 | N47: 0 | O47: 0 | P47: 0 | Q47: 0 | R47: 0 | S47: 0 | T47: 0 | U47: 0 | V47: 0 | W47: 0 | X47: 0 | Y47: 0 | Z47: 0 | AA47: 0 | AB47: 0 | AC47: 0 | AD47: 0 | AE47: 0 | AF47: 0 | AG47: 0 | AH47: 0 | AI47: 0 | AJ47: 0 | AK47: 0 | AL47: 0 | AM47: 0 | AN47: 0 | AO47: 0 | AP47: 0 | AQ47: 0 | AR47: 0 | AS47: 0 | AT47: 0 | AU47: 0 | AV47: 0 | AW47: 0 | AX47: 0 | AY47: 0 | AZ47: 0 | BA47: 0 | BB47: 0 | BC47: 0 | BD47: 0 | BE47: 0 | BF47: 0 | BG47: 0 | BH47: 0 | BI47: 0 | BJ47: 0 | BK47: 0 | BL47: 0 | BM47: 0 | BN47: 0 | BO47: 0 | BP47: 0 | BQ47: 0 | BR47: 0 | BS47: 0 | BT47: 0 | BU47: 0 | BV47: 0 | BW47: 0 | BX47: 0 | BY47: 0 | BZ47: 0 | CA47: 0 | CB47: 0 | CC47: 0 | CD47: 0 | CE47: 0 | CF47: 0 | CG47: 0 | CH47: 0 | CI47: 0 | CJ47: 0 | CK47: 0 | CL47: 0
B48: 이자(운영) | C48: [KRWm] | D48: 0 | E48: 0 | F48: 0 | G48: 0 | H48: 0 | I48: 0 | J48: 0 | K48: =K45*'입력값'!E23/4 | L48: =L45*'입력값'!E23/4 | M48: =M45*'입력값'!E23/4 | N48: =N45*'입력값'!E23/4 | O48: =O45*'입력값'!E23/4 | P48: =P45*'입력값'!E23/4 | Q48: =Q45*'입력값'!E23/4 | R48: =R45*'입력값'!E23/4 | S48: =S45*'입력값'!E23/4 | T48: =T45*'입력값'!E23/4 | U48: =U45*'입력값'!E23/4 | V48: =V45*'입력값'!E23/4 | W48: =W45*'입력값'!E23/4 | X48: =X45*'입력값'!E23/4 | Y48: =Y45*'입력값'!E23/4 | Z48: =Z45*'입력값'!E23/4 | AA48: =AA45*'입력값'!E23/4 | AB48: =AB45*'입력값'!E23/4 | AC48: =AC45*'입력값'!E23/4 | AD48: =AD45*'입력값'!E23/4 | AE48: =AE45*'입력값'!E23/4 | AF48: =AF45*'입력값'!E23/4 | AG48: =AG45*'입력값'!E23/4 | AH48: =AH45*'입력값'!E23/4 | AI48: =AI45*'입력값'!E23/4 | AJ48: =AJ45*'입력값'!E23/4 | AK48: =AK45*'입력값'!E23/4 | AL48: =AL45*'입력값'!E23/4 | AM48: =AM45*'입력값'!E23/4 | AN48: =AN45*'입력값'!E23/4 | AO48: =AO45*'입력값'!E23/4 | AP48: =AP45*'입력값'!E23/4 | AQ48: =AQ45*'입력값'!E23/4 | AR48: =AR45*'입력값'!E23/4 | AS48: =AS45*'입력값'!E23/4 | AT48: =AT45*'입력값'!E23/4 | AU48: =AU45*'입력값'!E23/4 | AV48: =AV45*'입력값'!E23/4 | AW48: =AW45*'입력값'!E23/4 | AX48: =AX45*'입력값'!E23/4 | AY48: =AY45*'입력값'!E23/4 | AZ48: =AZ45*'입력값'!E23/4 | BA48: =BA45*'입력값'!E23/4 | BB48: =BB45*'입력값'!E23/4 | BC48: =BC45*'입력값'!E23/4 | BD48: =BD45*'입력값'!E23/4 | BE48: =BE45*'입력값'!E23/4 | BF48: =BF45*'입력값'!E23/4 | BG48: =BG45*'입력값'!E23/4 | BH48: =BH45*'입력값'!E23/4 | BI48: =BI45*'입력값'!E23/4 | BJ48: =BJ45*'입력값'!E23/4 | BK48: =BK45*'입력값'!E23/4 | BL48: =BL45*'입력값'!E23/4 | BM48: =BM45*'입력값'!E23/4 | BN48: =BN45*'입력값'!E23/4 | BO48: =BO45*'입력값'!E23/4 | BP48: =BP45*'입력값'!E23/4 | BQ48: =BQ45*'입력값'!E23/4 | BR48: =BR45*'입력값'!E23/4 | BS48: =BS45*'입력값'!E23/4 | BT48: =BT45*'입력값'!E23/4 | BU48: =BU45*'입력값'!E23/4 | BV48: =BV45*'입력값'!E23/4 | BW48: =BW45*'입력값'!E23/4 | BX48: =BX45*'입력값'!E23/4 | BY48: =BY45*'입력값'!E23/4 | BZ48: =BZ45*'입력값'!E23/4 | CA48: =CA45*'입력값'!E23/4 | CB48: =CB45*'입력값'!E23/4 | CC48: =CC45*'입력값'!E23/4 | CD48: =CD45*'입력값'!E23/4 | CE48: =CE45*'입력값'!E23/4 | CF48: =CF45*'입력값'!E23/4 | CG48: =CG45*'입력값'!E23/4 | CH48: =CH45*'입력값'!E23/4 | CI48: =CI45*'입력값'!E23/4 | CJ48: =CJ45*'입력값'!E23/4 | CK48: =CK45*'입력값'!E23/4 | CL48: =CL45*'입력값'!E23/4
B49: 원금상환 | C49: [KRWm] | D49: 0 | E49: 0 | F49: 0 | G49: 0 | H49: 0 | I49: 0 | J49: 0 | K49: 0 | L49: 0 | M49: 0 | N49: 0 | O49: 0 | P49: 0 | Q49: 0 | R49: 0 | S49: 0 | T49: 0 | U49: 0 | V49: 0 | W49: 0 | X49: 0 | Y49: 0 | Z49: 0 | AA49: 0 | AB49: 0 | AC49: 0 | AD49: 0 | AE49: 0 | AF49: 0 | AG49: 0 | AH49: 0 | AI49: 0 | AJ49: 0 | AK49: 0 | AL49: 0 | AM49: 0 | AN49: 0 | AO49: 0 | AP49: 0 | AQ49: 0 | AR49: 0 | AS49: 0 | AT49: 0 | AU49: 0 | AV49: 0 | AW49: 0 | AX49: 0 | AY49: 0 | AZ49: 0 | BA49: 0 | BB49: 0 | BC49: 0 | BD49: 0 | BE49: 0 | BF49: 0 | BG49: 0 | BH49: 0 | BI49: 0 | BJ49: 0 | BK49: 0 | BL49: 0 | BM49: 0 | BN49: 0 | BO49: 0 | BP49: 0 | BQ49: 0 | BR49: 0 | BS49: 0 | BT49: 0 | BU49: 0 | BV49: 0 | BW49: 0 | BX49: 0 | BY49: 0 | BZ49: 0 | CA49: 0 | CB49: 0 | CC49: 0 | CD49: 0 | CE49: 0 | CF49: 0 | CG49: 0 | CH49: 0 | CI49: 0 | CJ49: 0 | CK49: 0 | CL49: 0
B50: 기말잔액 | C50: [KRWm] | E50: =E45+E46-E49 | F50: =F45+F46-F49 | G50: =G45+G46-G49 | H50: =H45+H46-H49 | I50: =I45+I46-I49 | J50: =J45+J46-J49 | K50: =K45+K46-K49 | L50: =L45+L46-L49 | ... CL50: =CL45+CL46-CL49
B51: 미상환 잔액(검증용) | C51: [KRWm] | D51: 0 | F51: 완전상환 확인 (OK) | H51: ※ 방식 3(직접 키인) 또는 미사용 트랜치 — 값(baked) 기준
B53: 전체 합계
B54: 기초잔액 | C54: [KRWm] | E54: 0 | F54: 21011.5 | G54: 42281.188 | H54: 63812.237 | I54: 85607.859 | J54: 107671.3 | K54: 126069 | L54: 126069 | M54: 126069 | N54: 126069 | O54: 123967.85 | P54: 121866.7 | Q54: 119765.55 | R54: 117664.4 | S54: 115563.25 | T54: 113462.1 | U54: 111360.95 | V54: 109259.8 | W54: 107158.65 | X54: 105057.5 | Y54: 102956.35 | Z54: 100855.2 | AA54: 98754.05 | AB54: 96652.9 | AC54: 94551.75 | AD54: 92450.6 | AE54: 90349.45 | AF54: 88248.3 | AG54: 86147.15 | AH54: 84046 | AI54: 81944.85 | AJ54: 79843.7 | AK54: 77742.55 | AL54: 75641.4 | AM54: 73540.25 | AN54: 71439.1 | AO54: 69337.95 | AP54: 67236.8 | AQ54: 65135.65 | AR54: 63034.5 | AS54: 60933.35 | AT54: 58832.2 | AU54: 56731.05 | AV54: 54629.9 | AW54: 52528.75 | AX54: 50427.6 | AY54: 48326.45 | AZ54: 46225.3 | BA54: 44124.15 | BB54: 42023 | BC54: 39921.85 | BD54: 37820.7 | BE54: 35719.55 | BF54: 33618.4 | BG54: 31517.25 | BH54: 29416.1 | BI54: 27314.95 | BJ54: 25213.8 | BK54: 23112.65 | BL54: 21011.5 | BM54: 18910.35 | BN54: 16809.2 | BO54: 14708.05 | BP54: 12606.9 | BQ54: 10505.75 | BR54: 8404.6 | BS54: 6303.45 | BT54: 4202.3 | BU54: 2101.15 | BV54: 1.3005774e-10 | BW54: 1.3005774e-10 | BX54: 1.3005774e-10 | BY54: 1.3005774e-10 | BZ54: 1.3005774e-10 | CA54: 1.3005774e-10 | CB54: 1.3005774e-10 | CC54: 1.3005774e-10 | CD54: 1.3005774e-10 | CE54: 1.3005774e-10 | CF54: 1.3005774e-10 | CG54: 1.3005774e-10 | CH54: 1.3005774e-10 | CI54: 1.3005774e-10 | CJ54: 1.3005774e-10 | CK54: 1.3005774e-10 | CL54: 1.3005774e-10
B55: 이자 | C55: [KRWm] | D55: 58070.533 | E55: =E12+E21+E30+E39+E48 | F55: =F12+F21+F30+F39+F48 | G55: =G12+G21+G30+G39+G48 | H55: =H12+H21+H30+H39+H48 | I55: =I12+I21+I30+I39+I48 | J55: =J12+J21+J30+J39+J48 | K55: =K12+K21+K30+K39+K48 | L55: =L12+L21+L30+L39+L48 | ... CL55: =CL12+CL21+CL30+CL39+CL48
B56: 원금상환 | C56: [KRWm] | D56: 126069 | E56: =E13+E22+E31+E40+E49 | F56: =F13+F22+F31+F40+F49 | G56: =G13+G22+G31+G40+G49 | H56: =H13+H22+H31+H40+H49 | I56: =I13+I22+I31+I40+I49 | J56: =J13+J22+J31+J40+J49 | K56: =K13+K22+K31+K40+K49 | L56: =L13+L22+L31+L40+L49 | ... CL56: =CL13+CL22+CL31+CL40+CL49
B57: 원리금(DS) | C57: [KRWm] | D57: 184139.53 | E57: =E55+E56 | F57: =F55+F56 | G57: =G55+G56 | H57: =H55+H56 | I57: =I55+I56 | J57: =J55+J56 | K57: =K55+K56 | L57: =L55+L56 | ... CL57: =CL55+CL56
B58: 기말잔액 | C58: [KRWm] | E58: =E14+E23+E32+E41+E50 | F58: =F14+F23+F32+F41+F50 | G58: =G14+G23+G32+G41+G50 | H58: =H14+H23+H32+H41+H50 | I58: =I14+I23+I32+I41+I50 | J58: =J14+J23+J32+J41+J50 | K58: =K14+K23+K32+K41+K50 | L58: =L14+L23+L32+L41+L50 | ... CL58: =CL14+CL23+CL32+CL41+CL50
B60: DSRA 기말잔액 | C60: [KRWm] | E60: 0 | F60: 0 | G60: 0 | H60: 0 | I60: 0 | J60: 5000 | K60: 3466.8975 | L60: 5568.0475 | M60: 7640.3067 | N60: 7582.5251 | O60: 7524.7434 | P60: 7466.9618 | Q60: 7409.1802 | R60: 7351.3986 | S60: 7293.6169 | T60: 7235.8353 | U60: 7178.0537 | V60: 7120.2721 | W60: 7062.4904 | X60: 7004.7088 | Y60: 6946.9272 | Z60: 6889.1456 | AA60: 6831.3639 | AB60: 6773.5823 | AC60: 6715.8007 | AD60: 6658.0191 | AE60: 6600.2374 | AF60: 6542.4558 | AG60: 6484.6742 | AH60: 6426.8926 | AI60: 6369.1109 | AJ60: 6311.3293 | AK60: 6253.5477 | AL60: 6195.7661 | AM60: 6137.9844 | AN60: 6080.2028 | AO60: 6022.4212 | AP60: 5964.6396 | AQ60: 5906.8579 | AR60: 5849.0763 | AS60: 5791.2947 | AT60: 5733.5131 | AU60: 5675.7314 | AV60: 5617.9498 | AW60: 5560.1682 | AX60: 5502.3866 | AY60: 5444.6049 | AZ60: 5386.8233 | BA60: 5329.0417 | BB60: 5271.2601 | BC60: 5213.4784 | BD60: 5155.6968 | BE60: 5097.9152 | BF60: 5040.1336 | BG60: 4982.3519 | BH60: 4924.5703 | BI60: 4866.7887 | BJ60: 4809.0071 | BK60: 4751.2254 | BL60: 4693.4438 | BM60: 4635.6622 | BN60: 4577.8806 | BO60: 4520.0989 | BP60: 4462.3173 | BQ60: 4404.5357 | BR60: 4346.7541 | BS60: 4288.9724 | BT60: 2130.0408 | BU60: 3.5765879e-12 | BV60: 3.5765879e-12 | BW60: 3.5765879e-12 | BX60: 3.5765879e-12 | BY60: 3.5765879e-12 | BZ60: 3.5765879e-12 | CA60: 3.5765879e-12 | CB60: 3.5765879e-12 | CC60: 3.5765879e-12 | CD60: 3.5765879e-12 | CE60: 3.5765879e-12 | CF60: 3.5765879e-12 | CG60: 3.5765879e-12 | CH60: 3.5765879e-12 | CI60: 3.5765879e-12 | CJ60: 3.5765879e-12 | CK60: 1.788294e-12 | CL60: 0

Sheet Revenue
A1: 태양광 발전사업
A2: 영업수익 추정
B4: 발전량 및 매출
B6: 구 분 | C6: unit | D6: 합 계 | E6: 2024-06-30 | F6: 2024-09-30 | G6: 2024-12-31 | H6: 2025-03-31 | I6: 2025-06-30 | J6: 2025-09-30 | K6: 2025-12-31 | L6: 2026-03-31 | M6: 2026-06-30 | N6: 2026-09-30 | O6: 2026-12-31 | P6: 2027-03-31 | Q6: 2027-06-30 | R6: 2027-09-30 | S6: 2027-12-31 | T6: 2028-03-31 | U6: 2028-06-30 | V6: 2028-09-30 | W6: 2028-12-31 | X6: 2029-03-31 | Y6: 2029-06-30 | Z6: 2029-09-30 | AA6: 2029-12-31 | AB6: 2030-03-31 | AC6: 2030-06-30 | AD6: 2030-09-30 | AE6: 2030-12-31 | AF6: 2031-03-31 | AG6: 2031-06-30 | AH6: 2031-09-30 | AI6: 2031-12-31 | AJ6: 2032-03-31 | AK6: 2032-06-30 | AL6: 2032-09-30 | AM6: 2032-12-31 | AN6: 2033-03-31 | AO6: 2033-06-30 | AP6: 2033-09-30 | AQ6: 2033-12-31 | AR6: 2034-03-31 | AS6: 2034-06-30 | AT6: 2034-09-30 | AU6: 2034-12-31 | AV6: 2035-03-31 | AW6: 2035-06-30 | AX6: 2035-09-30 | AY6: 2035-12-31 | AZ6: 2036-03-31 | BA6: 2036-06-30 | BB6: 2036-09-30 | BC6: 2036-12-31 | BD6: 2037-03-31 | BE6: 2037-06-30 | BF6: 2037-09-30 | BG6: 2037-12-31 | BH6: 2038-03-31 | BI6: 2038-06-30 | BJ6: 2038-09-30 | BK6: 2038-12-31 | BL6: 2039-03-31 | BM6: 2039-06-30 | BN6: 2039-09-30 | BO6: 2039-12-31 | BP6: 2040-03-31 | BQ6: 2040-06-30 | BR6: 2040-09-30 | BS6: 2040-12-31 | BT6: 2041-03-31 | BU6: 2041-06-30 | BV6: 2041-09-30 | BW6: 2041-12-31 | BX6: 2042-03-31 | BY6: 2042-06-30 | BZ6: 2042-09-30 | CA6: 2042-12-31 | CB6: 2043-03-31 | CC6: 2043-06-30 | CD6: 2043-09-30 | CE6: 2043-12-31 | CF6: 2044-03-31 | CG6: 2044-06-30 | CH6: 2044-09-30 | CI6: 2044-12-31 | CJ6: 2045-03-31 | CK6: 2045-06-30 | CL6: 2045-09-30
B9: 발전량 | C9: [MWh] | D9: 2621322.8 | E9: =('입력값'!C7*'입력값'!C14*365)*MAX(0,1-'입력값'!C12/100*0)*(1-'입력값'!C13/100)*0 | F9: =('입력값'!C7*'입력값'!C14*365)*MAX(0,1-'입력값'!C12/100*0)*(1-'입력값'!C13/100)*0 | G9: =('입력값'!C7*'입력값'!C14*365)*MAX(0,1-'입력값'!C12/100*0)*(1-'입력값'!C13/100)*0 | H9: =('입력값'!C7*'입력값'!C14*365)*MAX(0,1-'입력값'!C12/100*0)*(1-'입력값'!C13/100)*0 | I9: =('입력값'!C7*'입력값'!C14*365)*MAX(0,1-'입력값'!C12/100*0)*(1-'입력값'!C13/100)*0 | J9: =('입력값'!C7*'입력값'!C14*365)*MAX(0,1-'입력값'!C12/100*0)*(1-'입력값'!C13/100)*0 | K9: =('입력값'!C7*'입력값'!C14*365)*MAX(0,1-'입력값'!C12/100*0)*(1-'입력값'!C13/100)*0.25 | L9: =('입력값'!C7*'입력값'!C14*365)*MAX(0,1-'입력값'!C12/100*0)*(1-'입력값'!C13/100)*0.25 | M9: =('입력값'!C7*'입력값'!C14*365)*MAX(0,1-'입력값'!C12/100*0)*(1-'입력값'!C13/100)*0.25 | N9: =('입력값'!C7*'입력값'!C14*365)*MAX(0,1-'입력값'!C12/100*0)*(1-'입력값'!C13/100)*0.25 | O9: =('입력값'!C7*'입력값'!C14*365)*MAX(0,1-'입력값'!C12/100*1)*(1-'입력값'!C13/100)*0.25 | P9: =('입력값'!C7*'입력값'!C14*365)*MAX(0,1-'입력값'!C12/100*1)*(1-'입력값'!C13/100)*0.25 | Q9: =('입력값'!C7*'입력값'!C14*365)*MAX(0,1-'입력값'!C12/100*1)*(1-'입력값'!C13/100)*0.25 | R9: =('입력값'!C7*'입력값'!C14*365)*MAX(0,1-'입력값'!C12/100*1)*(1-'입력값'!C13/100)*0.25 | S9: =('입력값'!C7*'입력값'!C14*365)*MAX(0,1-'입력값'!C12/100*2)*(1-'입력값'!C13/100)*0.25 | T9: =('입력값'!C7*'입력값'!C14*365)*MAX(0,1-'입력값'!C12/100*2)*(1-'입력값'!C13/100)*0.25 | U9: =('입력값'!C7*'입력값'!C14*365)*MAX(0,1-'입력값'!C12/100*2)*(1-'입력값'!C13/100)*0.25 | V9: =('입력값'!C7*'입력값'!C14*365)*MAX(0,1-'입력값'!C12/100*2)*(1-'입력값'!C13/100)*0.25 | W9: =('입력값'!C7*'입력값'!C14*365)*MAX(0,1-'입력값'!C12/100*3)*(1-'입력값'!C13/100)*0.25 | X9: =('입력값'!C7*'입력값'!C14*365)*MAX(0,1-'입력값'!C12/100*3)*(1-'입력값'!C13/100)*0.25 | Y9: =('입력값'!C7*'입력값'!C14*365)*MAX(0,1-'입력값'!C12/100*3)*(1-'입력값'!C13/100)*0.25 | Z9: =('입력값'!C7*'입력값'!C14*365)*MAX(0,1-'입력값'!C12/100*3)*(1-'입력값'!C13/100)*0.25 | AA9: =('입력값'!C7*'입력값'!C14*365)*MAX(0,1-'입력값'!C12/100*4)*(1-'입력값'!C13/100)*0.25 | AB9: =('입력값'!C7*'입력값'!C14*365)*MAX(0,1-'입력값'!C12/100*4)*(1-'입력값'!C13/100)*0.25 | AC9: =('입력값'!C7*'입력값'!C14*365)*MAX(0,1-'입력값'!C12/100*4)*(1-'입력값'!C13/100)*0.25 | AD9: =('입력값'!C7*'입력값'!C14*365)*MAX(0,1-'입력값'!C12/100*4)*(1-'입력값'!C13/100)*0.25 | AE9: =('입력값'!C7*'입력값'!C14*365)*MAX(0,1-'입력값'!C12/100*5)*(1-'입력값'!C13/100)*0.25 | AF9: =('입력값'!C7*'입력값'!C14*365)*MAX(0,1-'입력값'!C12/100*5)*(1-'입력값'!C13/100)*0.25 | AG9: =('입력값'!C7*'입력값'!C14*365)*MAX(0,1-'입력값'!C12/100*5)*(1-'입력값'!C13/100)*0.25 | AH9: =('입력값'!C7*'입력값'!C14*365)*MAX(0,1-'입력값'!C12/100*5)*(1-'입력값'!C13/100)*0.25 | AI9: =('입력값'!C7*'입력값'!C14*365)*MAX(0,1-'입력값'!C12/100*6)*(1-'입력값'!C13/100)*0.25 | AJ9: =('입력값'!C7*'입력값'!C14*365)*MAX(0,1-'입력값'!C12/100*6)*(1-'입력값'!C13/100)*0.25 | AK9: =('입력값'!C7*'입력값'!C14*365)*MAX(0,1-'입력값'!C12/100*6)*(1-'입력값'!C13/100)*0.25 | AL9: =('입력값'!C7*'입력값'!C14*365)*MAX(0,1-'입력값'!C12/100*6)*(1-'입력값'!C13/100)*0.25 | AM9: =('입력값'!C7*'입력값'!C14*365)*MAX(0,1-'입력값'!C12/100*7)*(1-'입력값'!C13/100)*0.25 | AN9: =('입력값'!C7*'입력값'!C14*365)*MAX(0,1-'입력값'!C12/100*7)*(1-'입력값'!C13/100)*0.25 | AO9: =('입력값'!C7*'입력값'!C14*365)*MAX(0,1-'입력값'!C12/100*7)*(1-'입력값'!C13/100)*0.25 | AP9: =('입력값'!C7*'입력값'!C14*365)*MAX(0,1-'입력값'!C12/100*7)*(1-'입력값'!C13/100)*0.25 | AQ9: =('입력값'!C7*'입력값'!C14*365)*MAX(0,1-'입력값'!C12/100*8)*(1-'입력값'!C13/100)*0.25 | AR9: =('입력값'!C7*'입력값'!C14*365)*MAX(0,1-'입력값'!C12/100*8)*(1-'입력값'!C13/100)*0.25 | AS9: =('입력값'!C7*'입력값'!C14*365)*MAX(0,1-'입력값'!C12/100*8)*(1-'입력값'!C13/100)*0.25 | AT9: =('입력값'!C7*'입력값'!C14*365)*MAX(0,1-'입력값'!C12/100*8)*(1-'입력값'!C13/100)*0.25 | AU9: =('입력값'!C7*'입력값'!C14*365)*MAX(0,1-'입력값'!C12/100*9)*(1-'입력값'!C13/100)*0.25 | AV9: =('입력값'!C7*'입력값'!C14*365)*MAX(0,1-'입력값'!C12/100*9)*(1-'입력값'!C13/100)*0.25 | AW9: =('입력값'!C7*'입력값'!C14*365)*MAX(0,1-'입력값'!C12/100*9)*(1-'입력값'!C13/100)*0.25 | AX9: =('입력값'!C7*'입력값'!C14*365)*MAX(0,1-'입력값'!C12/100*9)*(1-'입력값'!C13/100)*0.25 | AY9: =('입력값'!C7*'입력값'!C14*365)*MAX(0,1-'입력값'!C12/100*10)*(1-'입력값'!C13/100)*0.25 | AZ9: =('입력값'!C7*'입력값'!C14*365)*MAX(0,1-'입력값'!C12/100*10)*(1-'입력값'!C13/100)*0.25 | BA9: =('입력값'!C7*'입력값'!C14*365)*MAX(0,1-'입력값'!C12/100*10)*(1-'입력값'!C13/100)*0.25 | BB9: =('입력값'!C7*'입력값'!C14*365)*MAX(0,1-'입력값'!C12/100*10)*(1-'입력값'!C13/100)*0.25 | BC9: =('입력값'!C7*'입력값'!C14*365)*MAX(0,1-'입력값'!C12/100*11)*(1-'입력값'!C13/100)*0.25 | BD9: =('입력값'!C7*'입력값'!C14*365)*MAX(0,1-'입력값'!C12/100*11)*(1-'입력값'!C13/100)*0.25 | BE9: =('입력값'!C7*'입력값'!C14*365)*MAX(0,1-'입력값'!C12/100*11)*(1-'입력값'!C13/100)*0.25 | BF9: =('입력값'!C7*'입력값'!C14*365)*MAX(0,1-'입력값'!C12/100*11)*(1-'입력값'!C13/100)*0.25 | BG9: =('입력값'!C7*'입력값'!C14*365)*MAX(0,1-'입력값'!C12/100*12)*(1-'입력값'!C13/100)*0.25 | BH9: =('입력값'!C7*'입력값'!C14*365)*MAX(0,1-'입력값'!C12/100*12)*(1-'입력값'!C13/100)*0.25 | BI9: =('입력값'!C7*'입력값'!C14*365)*MAX(0,1-'입력값'!C12/100*12)*(1-'입력값'!C13/100)*0.25 | BJ9: =('입력값'!C7*'입력값'!C14*365)*MAX(0,1-'입력값'!C12/100*12)*(1-'입력값'!C13/100)*0.25 | BK9: =('입력값'!C7*'입력값'!C14*365)*MAX(0,1-'입력값'!C12/100*13)*(1-'입력값'!C13/100)*0.25 | BL9: =('입력값'!C7*'입력값'!C14*365)*MAX(0,1-'입력값'!C12/100*13)*(1-'입력값'!C13/100)*0.25 | BM9: =('입력값'!C7*'입력값'!C14*365)*MAX(0,1-'입력값'!C12/100*13)*(1-'입력값'!C13/100)*0.25 | BN9: =('입력값'!C7*'입력값'!C14*365)*MAX(0,1-'입력값'!C12/100*13)*(1-'입력값'!C13/100)*0.25 | BO9: =('입력값'!C7*'입력값'!C14*365)*MAX(0,1-'입력값'!C12/100*14)*(1-'입력값'!C13/100)*0.25 | BP9: =('입력값'!C7*'입력값'!C14*365)*MAX(0,1-'입력값'!C12/100*14)*(1-'입력값'!C13/100)*0.25 | BQ9: =('입력값'!C7*'입력값'!C14*365)*MAX(0,1-'입력값'!C12/100*14)*(1-'입력값'!C13/100)*0.25 | BR9: =('입력값'!C7*'입력값'!C14*365)*MAX(0,1-'입력값'!C12/100*14)*(1-'입력값'!C13/100)*0.25 | BS9: =('입력값'!C7*'입력값'!C14*365)*MAX(0,1-'입력값'!C12/100*15)*(1-'입력값'!C13/100)*0.25 | BT9: =('입력값'!C7*'입력값'!C14*365)*MAX(0,1-'입력값'!C12/100*15)*(1-'입력값'!C13/100)*0.25 | BU9: =('입력값'!C7*'입력값'!C14*365)*MAX(0,1-'입력값'!C12/100*15)*(1-'입력값'!C13/100)*0.25 | BV9: =('입력값'!C7*'입력값'!C14*365)*MAX(0,1-'입력값'!C12/100*15)*(1-'입력값'!C13/100)*0.25 | BW9: =('입력값'!C7*'입력값'!C14*365)*MAX(0,1-'입력값'!C12/100*16)*(1-'입력값'!C13/100)*0.25 | BX9: =('입력값'!C7*'입력값'!C14*365)*MAX(0,1-'입력값'!C12/100*16)*(1-'입력값'!C13/100)*0.25 | BY9: =('입력값'!C7*'입력값'!C14*365)*MAX(0,1-'입력값'!C12/100*16)*(1-'입력값'!C13/100)*0.25 | BZ9: =('입력값'!C7*'입력값'!C14*365)*MAX(0,1-'입력값'!C12/100*16)*(1-'입력값'!C13/100)*0.25 | CA9: =('입력값'!C7*'입력값'!C14*365)*MAX(0,1-'입력값'!C12/100*17)*(1-'입력값'!C13/100)*0.25 | CB9: =('입력값'!C7*'입력값'!C14*365)*MAX(0,1-'입력값'!C12/100*17)*(1-'입력값'!C13/100)*0.25 | CC9: =('입력값'!C7*'입력값'!C14*365)*MAX(0,1-'입력값'!C12/100*17)*(1-'입력값'!C13/100)*0.25 | CD9: =('입력값'!C7*'입력값'!C14*365)*MAX(0,1-'입력값'!C12/100*17)*(1-'입력값'!C13/100)*0.25 | CE9: =('입력값'!C7*'입력값'!C14*365)*MAX(0,1-'입력값'!C12/100*18)*(1-'입력값'!C13/100)*0.25 | CF9: =('입력값'!C7*'입력값'!C14*365)*MAX(0,1-'입력값'!C12/100*18)*(1-'입력값'!C13/100)*0.25 | CG9: =('입력값'!C7*'입력값'!C14*365)*MAX(0,1-'입력값'!C12/100*18)*(1-'입력값'!C13/100)*0.25 | CH9: =('입력값'!C7*'입력값'!C14*365)*MAX(0,1-'입력값'!C12/100*18)*(1-'입력값'!C13/100)*0.25 | CI9: =('입력값'!C7*'입력값'!C14*365)*MAX(0,1-'입력값'!C12/100*19)*(1-'입력값'!C13/100)*0.25 | CJ9: =('입력값'!C7*'입력값'!C14*365)*MAX(0,1-'입력값'!C12/100*19)*(1-'입력값'!C13/100)*0.25 | CK9: =('입력값'!C7*'입력값'!C14*365)*MAX(0,1-'입력값'!C12/100*19)*(1-'입력값'!C13/100)*0.25 | CL9: =('입력값'!C7*'입력값'!C14*365)*MAX(0,1-'입력값'!C12/100*19)*(1-'입력값'!C13/100)*0.25
B10: 판매단가 | C10: [원/kWh] | K10: ='입력값'!C10*(1+'입력값'!C11/100)^0 | L10: ='입력값'!C10*(1+'입력값'!C11/100)^0 | M10: ='입력값'!C10*(1+'입력값'!C11/100)^0 | N10: ='입력값'!C10*(1+'입력값'!C11/100)^0 | O10: ='입력값'!C10*(1+'입력값'!C11/100)^1 | P10: ='입력값'!C10*(1+'입력값'!C11/100)^1 | Q10: ='입력값'!C10*(1+'입력값'!C11/100)^1 | R10: ='입력값'!C10*(1+'입력값'!C11/100)^1 | S10: ='입력값'!C10*(1+'입력값'!C11/100)^2 | T10: ='입력값'!C10*(1+'입력값'!C11/100)^2 | U10: ='입력값'!C10*(1+'입력값'!C11/100)^2 | V10: ='입력값'!C10*(1+'입력값'!C11/100)^2 | W10: ='입력값'!C10*(1+'입력값'!C11/100)^3 | X10: ='입력값'!C10*(1+'입력값'!C11/100)^3 | Y10: ='입력값'!C10*(1+'입력값'!C11/100)^3 | Z10: ='입력값'!C10*(1+'입력값'!C11/100)^3 | AA10: ='입력값'!C10*(1+'입력값'!C11/100)^4 | AB10: ='입력값'!C10*(1+'입력값'!C11/100)^4 | AC10: ='입력값'!C10*(1+'입력값'!C11/100)^4 | AD10: ='입력값'!C10*(1+'입력값'!C11/100)^4 | AE10: ='입력값'!C10*(1+'입력값'!C11/100)^5 | AF10: ='입력값'!C10*(1+'입력값'!C11/100)^5 | AG10: ='입력값'!C10*(1+'입력값'!C11/100)^5 | AH10: ='입력값'!C10*(1+'입력값'!C11/100)^5 | AI10: ='입력값'!C10*(1+'입력값'!C11/100)^6 | AJ10: ='입력값'!C10*(1+'입력값'!C11/100)^6 | AK10: ='입력값'!C10*(1+'입력값'!C11/100)^6 | AL10: ='입력값'!C10*(1+'입력값'!C11/100)^6 | AM10: ='입력값'!C10*(1+'입력값'!C11/100)^7 | AN10: ='입력값'!C10*(1+'입력값'!C11/100)^7 | AO10: ='입력값'!C10*(1+'입력값'!C11/100)^7 | AP10: ='입력값'!C10*(1+'입력값'!C11/100)^7 | AQ10: ='입력값'!C10*(1+'입력값'!C11/100)^8 | AR10: ='입력값'!C10*(1+'입력값'!C11/100)^8 | AS10: ='입력값'!C10*(1+'입력값'!C11/100)^8 | AT10: ='입력값'!C10*(1+'입력값'!C11/100)^8 | AU10: ='입력값'!C10*(1+'입력값'!C11/100)^9 | AV10: ='입력값'!C10*(1+'입력값'!C11/100)^9 | AW10: ='입력값'!C10*(1+'입력값'!C11/100)^9 | AX10: ='입력값'!C10*(1+'입력값'!C11/100)^9 | AY10: ='입력값'!C10*(1+'입력값'!C11/100)^10 | AZ10: ='입력값'!C10*(1+'입력값'!C11/100)^10 | BA10: ='입력값'!C10*(1+'입력값'!C11/100)^10 | BB10: ='입력값'!C10*(1+'입력값'!C11/100)^10 | BC10: ='입력값'!C10*(1+'입력값'!C11/100)^11 | BD10: ='입력값'!C10*(1+'입력값'!C11/100)^11 | BE10: ='입력값'!C10*(1+'입력값'!C11/100)^11 | BF10: ='입력값'!C10*(1+'입력값'!C11/100)^11 | BG10: ='입력값'!C10*(1+'입력값'!C11/100)^12 | BH10: ='입력값'!C10*(1+'입력값'!C11/100)^12 | BI10: ='입력값'!C10*(1+'입력값'!C11/100)^12 | BJ10: ='입력값'!C10*(1+'입력값'!C11/100)^12 | BK10: ='입력값'!C10*(1+'입력값'!C11/100)^13 | BL10: ='입력값'!C10*(1+'입력값'!C11/100)^13 | BM10: ='입력값'!C10*(1+'입력값'!C11/100)^13 | BN10: ='입력값'!C10*(1+'입력값'!C11/100)^13 | BO10: ='입력값'!C10*(1+'입력값'!C11/100)^14 | BP10: ='입력값'!C10*(1+'입력값'!C11/100)^14 | BQ10: ='입력값'!C10*(1+'입력값'!C11/100)^14 | BR10: ='입력값'!C10*(1+'입력값'!C11/100)^14 | BS10: ='입력값'!C10*(1+'입력값'!C11/100)^15 | BT10: ='입력값'!C10*(1+'입력값'!C11/100)^15 | BU10: ='입력값'!C10*(1+'입력값'!C11/100)^15 | BV10: ='입력값'!C10*(1+'입력값'!C11/100)^15 | BW10: ='입력값'!C10*(1+'입력값'!C11/100)^16 | BX10: ='입력값'!C10*(1+'입력값'!C11/100)^16 | BY10: ='입력값'!C10*(1+'입력값'!C11/100)^16 | BZ10: ='입력값'!C10*(1+'입력값'!C11/100)^16 | CA10: ='입력값'!C10*(1+'입력값'!C11/100)^17 | CB10: ='입력값'!C10*(1+'입력값'!C11/100)^17 | CC10: ='입력값'!C10*(1+'입력값'!C11/100)^17 | CD10: ='입력값'!C10*(1+'입력값'!C11/100)^17 | CE10: ='입력값'!C10*(1+'입력값'!C11/100)^18 | CF10: ='입력값'!C10*(1+'입력값'!C11/100)^18 | CG10: ='입력값'!C10*(1+'입력값'!C11/100)^18 | CH10: ='입력값'!C10*(1+'입력값'!C11/100)^18 | CI10: ='입력값'!C10*(1+'입력값'!C11/100)^19 | CJ10: ='입력값'!C10*(1+'입력값'!C11/100)^19 | CK10: ='입력값'!C10*(1+'입력값'!C11/100)^19 | CL10: ='입력값'!C10*(1+'입력값'!C11/100)^19
B12: 영업수익 | C12: [KRWm] | D12: 405780.77 | E12: 0 | F12: 0 | G12: 0 | H12: 0 | I12: 0 | J12: 0 | K12: =K9*K10/1000 | L12: =L9*L10/1000 | M12: =M9*M10/1000 | N12: =N9*N10/1000 | O12: =O9*O10/1000 | P12: =P9*P10/1000 | Q12: =Q9*Q10/1000 | R12: =R9*R10/1000 | ... CL12: =CL9*CL10/1000

Sheet Opex
A1: 태양광 발전사업
A2: 영업비용 추정
B4: 운영비용 (선순위/후순위 지급순위 반영)
B6: 구 분 | C6: unit | D6: 합 계 | E6: 2024-06-30 | F6: 2024-09-30 | G6: 2024-12-31 | H6: 2025-03-31 | I6: 2025-06-30 | J6: 2025-09-30 | K6: 2025-12-31 | L6: 2026-03-31 | M6: 2026-06-30 | N6: 2026-09-30 | O6: 2026-12-31 | P6: 2027-03-31 | Q6: 2027-06-30 | R6: 2027-09-30 | S6: 2027-12-31 | T6: 2028-03-31 | U6: 2028-06-30 | V6: 2028-09-30 | W6: 2028-12-31 | X6: 2029-03-31 | Y6: 2029-06-30 | Z6: 2029-09-30 | AA6: 2029-12-31 | AB6: 2030-03-31 | AC6: 2030-06-30 | AD6: 2030-09-30 | AE6: 2030-12-31 | AF6: 2031-03-31 | AG6: 2031-06-30 | AH6: 2031-09-30 | AI6: 2031-12-31 | AJ6: 2032-03-31 | AK6: 2032-06-30 | AL6: 2032-09-30 | AM6: 2032-12-31 | AN6: 2033-03-31 | AO6: 2033-06-30 | AP6: 2033-09-30 | AQ6: 2033-12-31 | AR6: 2034-03-31 | AS6: 2034-06-30 | AT6: 2034-09-30 | AU6: 2034-12-31 | AV6: 2035-03-31 | AW6: 2035-06-30 | AX6: 2035-09-30 | AY6: 2035-12-31 | AZ6: 2036-03-31 | BA6: 2036-06-30 | BB6: 2036-09-30 | BC6: 2036-12-31 | BD6: 2037-03-31 | BE6: 2037-06-30 | BF6: 2037-09-30 | BG6: 2037-12-31 | BH6: 2038-03-31 | BI6: 2038-06-30 | BJ6: 2038-09-30 | BK6: 2038-12-31 | BL6: 2039-03-31 | BM6: 2039-06-30 | BN6: 2039-09-30 | BO6: 2039-12-31 | BP6: 2040-03-31 | BQ6: 2040-06-30 | BR6: 2040-09-30 | BS6: 2040-12-31 | BT6: 2041-03-31 | BU6: 2041-06-30 | BV6: 2041-09-30 | BW6: 2041-12-31 | BX6: 2042-03-31 | BY6: 2042-06-30 | BZ6: 2042-09-30 | CA6: 2042-12-31 | CB6: 2043-03-31 | CC6: 2043-06-30 | CD6: 2043-09-30 | CE6: 2043-12-31 | CF6: 2044-03-31 | CG6: 2044-06-30 | CH6: 2044-09-30 | CI6: 2044-12-31 | CJ6: 2045-03-31 | CK6: 2045-06-30 | CL6: 2045-09-30
B8: 항목별 세부내역
B9: 부지임대료 | C9: [KRWm] | D9: -10000 | E9: 0 | F9: 0 | G9: 0 | H9: 0 | I9: 0 | J9: 0 | K9: =-('입력값'!C44*100*(3/12)) | L9: =-('입력값'!C44*100*(3/12)) | M9: =-('입력값'!C44*100*(3/12)) | N9: =-('입력값'!C44*100*(3/12)) | O9: =-('입력값'!C44*100*(3/12)) | P9: =-('입력값'!C44*100*(3/12)) | Q9: =-('입력값'!C44*100*(3/12)) | R9: =-('입력값'!C44*100*(3/12)) | S9: =-('입력값'!C44*100*(3/12)) | T9: =-('입력값'!C44*100*(3/12)) | U9: =-('입력값'!C44*100*(3/12)) | V9: =-('입력값'!C44*100*(3/12)) | W9: =-('입력값'!C44*100*(3/12)) | X9: =-('입력값'!C44*100*(3/12)) | Y9: =-('입력값'!C44*100*(3/12)) | Z9: =-('입력값'!C44*100*(3/12)) | AA9: =-('입력값'!C44*100*(3/12)) | AB9: =-('입력값'!C44*100*(3/12)) | AC9: =-('입력값'!C44*100*(3/12)) | AD9: =-('입력값'!C44*100*(3/12)) | AE9: =-('입력값'!C44*100*(3/12)) | AF9: =-('입력값'!C44*100*(3/12)) | AG9: =-('입력값'!C44*100*(3/12)) | AH9: =-('입력값'!C44*100*(3/12)) | AI9: =-('입력값'!C44*100*(3/12)) | AJ9: =-('입력값'!C44*100*(3/12)) | AK9: =-('입력값'!C44*100*(3/12)) | AL9: =-('입력값'!C44*100*(3/12)) | AM9: =-('입력값'!C44*100*(3/12)) | AN9: =-('입력값'!C44*100*(3/12)) | AO9: =-('입력값'!C44*100*(3/12)) | AP9: =-('입력값'!C44*100*(3/12)) | AQ9: =-('입력값'!C44*100*(3/12)) | AR9: =-('입력값'!C44*100*(3/12)) | AS9: =-('입력값'!C44*100*(3/12)) | AT9: =-('입력값'!C44*100*(3/12)) | AU9: =-('입력값'!C44*100*(3/12)) | AV9: =-('입력값'!C44*100*(3/12)) | AW9: =-('입력값'!C44*100*(3/12)) | AX9: =-('입력값'!C44*100*(3/12)) | AY9: =-('입력값'!C44*100*(3/12)) | AZ9: =-('입력값'!C44*100*(3/12)) | BA9: =-('입력값'!C44*100*(3/12)) | BB9: =-('입력값'!C44*100*(3/12)) | BC9: =-('입력값'!C44*100*(3/12)) | BD9: =-('입력값'!C44*100*(3/12)) | BE9: =-('입력값'!C44*100*(3/12)) | BF9: =-('입력값'!C44*100*(3/12)) | BG9: =-('입력값'!C44*100*(3/12)) | BH9: =-('입력값'!C44*100*(3/12)) | BI9: =-('입력값'!C44*100*(3/12)) | BJ9: =-('입력값'!C44*100*(3/12)) | BK9: =-('입력값'!C44*100*(3/12)) | BL9: =-('입력값'!C44*100*(3/12)) | BM9: =-('입력값'!C44*100*(3/12)) | BN9: =-('입력값'!C44*100*(3/12)) | BO9: =-('입력값'!C44*100*(3/12)) | BP9: =-('입력값'!C44*100*(3/12)) | BQ9: =-('입력값'!C44*100*(3/12)) | BR9: =-('입력값'!C44*100*(3/12)) | BS9: =-('입력값'!C44*100*(3/12)) | BT9: =-('입력값'!C44*100*(3/12)) | BU9: =-('입력값'!C44*100*(3/12)) | BV9: =-('입력값'!C44*100*(3/12)) | BW9: =-('입력값'!C44*100*(3/12)) | BX9: =-('입력값'!C44*100*(3/12)) | BY9: =-('입력값'!C44*100*(3/12)) | BZ9: =-('입력값'!C44*100*(3/12)) | CA9: =-('입력값'!C44*100*(3/12)) | CB9: =-('입력값'!C44*100*(3/12)) | CC9: =-('입력값'!C44*100*(3/12)) | CD9: =-('입력값'!C44*100*(3/12)) | CE9: =-('입력값'!C44*100*(3/12)) | CF9: =-('입력값'!C44*100*(3/12)) | CG9: =-('입력값'!C44*100*(3/12)) | CH9: =-('입력값'!C44*100*(3/12)) | CI9: =-('입력값'!C44*100*(3/12)) | CJ9: =-('입력값'!C44*100*(3/12)) | CK9: =-('입력값'!C44*100*(3/12)) | CL9: =-('입력값'!C44*100*(3/12))
B10: O&M | C10: [KRWm] | D10: -18498.934 | E10: 0 | F10: 0 | G10: 0 | H10: 0 | I10: 0 | J10: 0 | K10: =-('입력값'!C45*100*(3/12)*(1+'입력값'!D45/100)^0) | L10: =-('입력값'!C45*100*(3/12)*(1+'입력값'!D45/100)^0) | M10: =-('입력값'!C45*100*(3/12)*(1+'입력값'!D45/100)^0) | N10: =-('입력값'!C45*100*(3/12)*(1+'입력값'!D45/100)^0) | O10: =-('입력값'!C45*100*(3/12)*(1+'입력값'!D45/100)^1) | P10: =-('입력값'!C45*100*(3/12)*(1+'입력값'!D45/100)^1) | Q10: =-('입력값'!C45*100*(3/12)*(1+'입력값'!D45/100)^1) | R10: =-('입력값'!C45*100*(3/12)*(1+'입력값'!D45/100)^1) | S10: =-('입력값'!C45*100*(3/12)*(1+'입력값'!D45/100)^2) | T10: =-('입력값'!C45*100*(3/12)*(1+'입력값'!D45/100)^2) | U10: =-('입력값'!C45*100*(3/12)*(1+'입력값'!D45/100)^2) | V10: =-('입력값'!C45*100*(3/12)*(1+'입력값'!D45/100)^2) | W10: =-('입력값'!C45*100*(3/12)*(1+'입력값'!D45/100)^3) | X10: =-('입력값'!C45*100*(3/12)*(1+'입력값'!D45/100)^3) | Y10: =-('입력값'!C45*100*(3/12)*(1+'입력값'!D45/100)^3) | Z10: =-('입력값'!C45*100*(3/12)*(1+'입력값'!D45/100)^3) | AA10: =-('입력값'!C45*100*(3/12)*(1+'입력값'!D45/100)^4) | AB10: =-('입력값'!C45*100*(3/12)*(1+'입력값'!D45/100)^4) | AC10: =-('입력값'!C45*100*(3/12)*(1+'입력값'!D45/100)^4) | AD10: =-('입력값'!C45*100*(3/12)*(1+'입력값'!D45/100)^4) | AE10: =-('입력값'!C45*100*(3/12)*(1+'입력값'!D45/100)^5) | AF10: =-('입력값'!C45*100*(3/12)*(1+'입력값'!D45/100)^5) | AG10: =-('입력값'!C45*100*(3/12)*(1+'입력값'!D45/100)^5) | AH10: =-('입력값'!C45*100*(3/12)*(1+'입력값'!D45/100)^5) | AI10: =-('입력값'!C45*100*(3/12)*(1+'입력값'!D45/100)^6) | AJ10: =-('입력값'!C45*100*(3/12)*(1+'입력값'!D45/100)^6) | AK10: =-('입력값'!C45*100*(3/12)*(1+'입력값'!D45/100)^6) | AL10: =-('입력값'!C45*100*(3/12)*(1+'입력값'!D45/100)^6) | AM10: =-('입력값'!C45*100*(3/12)*(1+'입력값'!D45/100)^7) | AN10: =-('입력값'!C45*100*(3/12)*(1+'입력값'!D45/100)^7) | AO10: =-('입력값'!C45*100*(3/12)*(1+'입력값'!D45/100)^7) | AP10: =-('입력값'!C45*100*(3/12)*(1+'입력값'!D45/100)^7) | AQ10: =-('입력값'!C45*100*(3/12)*(1+'입력값'!D45/100)^8) | AR10: =-('입력값'!C45*100*(3/12)*(1+'입력값'!D45/100)^8) | AS10: =-('입력값'!C45*100*(3/12)*(1+'입력값'!D45/100)^8) | AT10: =-('입력값'!C45*100*(3/12)*(1+'입력값'!D45/100)^8) | AU10: =-('입력값'!C45*100*(3/12)*(1+'입력값'!D45/100)^9) | AV10: =-('입력값'!C45*100*(3/12)*(1+'입력값'!D45/100)^9) | AW10: =-('입력값'!C45*100*(3/12)*(1+'입력값'!D45/100)^9) | AX10: =-('입력값'!C45*100*(3/12)*(1+'입력값'!D45/100)^9) | AY10: =-('입력값'!C45*100*(3/12)*(1+'입력값'!D45/100)^10) | AZ10: =-('입력값'!C45*100*(3/12)*(1+'입력값'!D45/100)^10) | BA10: =-('입력값'!C45*100*(3/12)*(1+'입력값'!D45/100)^10) | BB10: =-('입력값'!C45*100*(3/12)*(1+'입력값'!D45/100)^10) | BC10: =-('입력값'!C45*100*(3/12)*(1+'입력값'!D45/100)^11) | BD10: =-('입력값'!C45*100*(3/12)*(1+'입력값'!D45/100)^11) | BE10: =-('입력값'!C45*100*(3/12)*(1+'입력값'!D45/100)^11) | BF10: =-('입력값'!C45*100*(3/12)*(1+'입력값'!D45/100)^11) | BG10: =-('입력값'!C45*100*(3/12)*(1+'입력값'!D45/100)^12) | BH10: =-('입력값'!C45*100*(3/12)*(1+'입력값'!D45/100)^12) | BI10: =-('입력값'!C45*100*(3/12)*(1+'입력값'!D45/100)^12) | BJ10: =-('입력값'!C45*100*(3/12)*(1+'입력값'!D45/100)^12) | BK10: =-('입력값'!C45*100*(3/12)*(1+'입력값'!D45/100)^13) | BL10: =-('입력값'!C45*100*(3/12)*(1+'입력값'!D45/100)^13) | BM10: =-('입력값'!C45*100*(3/12)*(1+'입력값'!D45/100)^13) | BN10: =-('입력값'!C45*100*(3/12)*(1+'입력값'!D45/100)^13) | BO10: =-('입력값'!C45*100*(3/12)*(1+'입력값'!D45/100)^14) | BP10: =-('입력값'!C45*100*(3/12)*(1+'입력값'!D45/100)^14) | BQ10: =-('입력값'!C45*100*(3/12)*(1+'입력값'!D45/100)^14) | BR10: =-('입력값'!C45*100*(3/12)*(1+'입력값'!D45/100)^14) | BS10: =-('입력값'!C45*100*(3/12)*(1+'입력값'!D45/100)^15) | BT10: =-('입력값'!C45*100*(3/12)*(1+'입력값'!D45/100)^15) | BU10: =-('입력값'!C45*100*(3/12)*(1+'입력값'!D45/100)^15) | BV10: =-('입력값'!C45*100*(3/12)*(1+'입력값'!D45/100)^15) | BW10: =-('입력값'!C45*100*(3/12)*(1+'입력값'!D45/100)^16) | BX10: =-('입력값'!C45*100*(3/12)*(1+'입력값'!D45/100)^16) | BY10: =-('입력값'!C45*100*(3/12)*(1+'입력값'!D45/100)^16) | BZ10: =-('입력값'!C45*100*(3/12)*(1+'입력값'!D45/100)^16) | CA10: =-('입력값'!C45*100*(3/12)*(1+'입력값'!D45/100)^17) | CB10: =-('입력값'!C45*100*(3/12)*(1+'입력값'!D45/100)^17) | CC10: =-('입력값'!C45*100*(3/12)*(1+'입력값'!D45/100)^17) | CD10: =-('입력값'!C45*100*(3/12)*(1+'입력값'!D45/100)^17) | CE10: =-('입력값'!C45*100*(3/12)*(1+'입력값'!D45/100)^18) | CF10: =-('입력값'!C45*100*(3/12)*(1+'입력값'!D45/100)^18) | CG10: =-('입력값'!C45*100*(3/12)*(1+'입력값'!D45/100)^18) | CH10: =-('입력값'!C45*100*(3/12)*(1+'입력값'!D45/100)^18) | CI10: =-('입력값'!C45*100*(3/12)*(1+'입력값'!D45/100)^19) | CJ10: =-('입력값'!C45*100*(3/12)*(1+'입력값'!D45/100)^19) | CK10: =-('입력값'!C45*100*(3/12)*(1+'입력값'!D45/100)^19) | CL10: =-('입력값'!C45*100*(3/12)*(1+'입력값'!D45/100)^19)
B11: 보험료 | C11: [KRWm] | D11: 0 | E11: 0 | F11: 0 | G11: 0 | H11: 0 | I11: 0 | J11: 0 | K11: =-('입력값'!C46*100*(3/12)) | L11: =-('입력값'!C46*100*(3/12)) | M11: =-('입력값'!C46*100*(3/12)) | N11: =-('입력값'!C46*100*(3/12)) | O11: =-('입력값'!C46*100*(3/12)) | P11: =-('입력값'!C46*100*(3/12)) | Q11: =-('입력값'!C46*100*(3/12)) | R11: =-('입력값'!C46*100*(3/12)) | S11: =-('입력값'!C46*100*(3/12)) | T11: =-('입력값'!C46*100*(3/12)) | U11: =-('입력값'!C46*100*(3/12)) | V11: =-('입력값'!C46*100*(3/12)) | W11: =-('입력값'!C46*100*(3/12)) | X11: =-('입력값'!C46*100*(3/12)) | Y11: =-('입력값'!C46*100*(3/12)) | Z11: =-('입력값'!C46*100*(3/12)) | AA11: =-('입력값'!C46*100*(3/12)) | AB11: =-('입력값'!C46*100*(3/12)) | AC11: =-('입력값'!C46*100*(3/12)) | AD11: =-('입력값'!C46*100*(3/12)) | AE11: =-('입력값'!C46*100*(3/12)) | AF11: =-('입력값'!C46*100*(3/12)) | AG11: =-('입력값'!C46*100*(3/12)) | AH11: =-('입력값'!C46*100*(3/12)) | AI11: =-('입력값'!C46*100*(3/12)) | AJ11: =-('입력값'!C46*100*(3/12)) | AK11: =-('입력값'!C46*100*(3/12)) | AL11: =-('입력값'!C46*100*(3/12)) | AM11: =-('입력값'!C46*100*(3/12)) | AN11: =-('입력값'!C46*100*(3/12)) | AO11: =-('입력값'!C46*100*(3/12)) | AP11: =-('입력값'!C46*100*(3/12)) | AQ11: =-('입력값'!C46*100*(3/12)) | AR11: =-('입력값'!C46*100*(3/12)) | AS11: =-('입력값'!C46*100*(3/12)) | AT11: =-('입력값'!C46*100*(3/12)) | AU11: =-('입력값'!C46*100*(3/12)) | AV11: =-('입력값'!C46*100*(3/12)) | AW11: =-('입력값'!C46*100*(3/12)) | AX11: =-('입력값'!C46*100*(3/12)) | AY11: =-('입력값'!C46*100*(3/12)) | AZ11: =-('입력값'!C46*100*(3/12)) | BA11: =-('입력값'!C46*100*(3/12)) | BB11: =-('입력값'!C46*100*(3/12)) | BC11: =-('입력값'!C46*100*(3/12)) | BD11: =-('입력값'!C46*100*(3/12)) | BE11: =-('입력값'!C46*100*(3/12)) | BF11: =-('입력값'!C46*100*(3/12)) | BG11: =-('입력값'!C46*100*(3/12)) | BH11: =-('입력값'!C46*100*(3/12)) | BI11: =-('입력값'!C46*100*(3/12)) | BJ11: =-('입력값'!C46*100*(3/12)) | BK11: =-('입력값'!C46*100*(3/12)) | BL11: =-('입력값'!C46*100*(3/12)) | BM11: =-('입력값'!C46*100*(3/12)) | BN11: =-('입력값'!C46*100*(3/12)) | BO11: =-('입력값'!C46*100*(3/12)) | BP11: =-('입력값'!C46*100*(3/12)) | BQ11: =-('입력값'!C46*100*(3/12)) | BR11: =-('입력값'!C46*100*(3/12)) | BS11: =-('입력값'!C46*100*(3/12)) | BT11: =-('입력값'!C46*100*(3/12)) | BU11: =-('입력값'!C46*100*(3/12)) | BV11: =-('입력값'!C46*100*(3/12)) | BW11: =-('입력값'!C46*100*(3/12)) | BX11: =-('입력값'!C46*100*(3/12)) | BY11: =-('입력값'!C46*100*(3/12)) | BZ11: =-('입력값'!C46*100*(3/12)) | CA11: =-('입력값'!C46*100*(3/12)) | CB11: =-('입력값'!C46*100*(3/12)) | CC11: =-('입력값'!C46*100*(3/12)) | CD11: =-('입력값'!C46*100*(3/12)) | CE11: =-('입력값'!C46*100*(3/12)) | CF11: =-('입력값'!C46*100*(3/12)) | CG11: =-('입력값'!C46*100*(3/12)) | CH11: =-('입력값'!C46*100*(3/12)) | CI11: =-('입력값'!C46*100*(3/12)) | CJ11: =-('입력값'!C46*100*(3/12)) | CK11: =-('입력값'!C46*100*(3/12)) | CL11: =-('입력값'!C46*100*(3/12))
B12: 환경모니터링비용 | C12: [KRWm] | D12: 0 | E12: 0 | F12: 0 | G12: 0 | H12: 0 | I12: 0 | J12: 0 | K12: =-('입력값'!C47*100*(3/12)) | L12: =-('입력값'!C47*100*(3/12)) | M12: =-('입력값'!C47*100*(3/12)) | N12: =-('입력값'!C47*100*(3/12)) | O12: =-('입력값'!C47*100*(3/12)) | P12: =-('입력값'!C47*100*(3/12)) | Q12: =-('입력값'!C47*100*(3/12)) | R12: =-('입력값'!C47*100*(3/12)) | S12: =-('입력값'!C47*100*(3/12)) | T12: =-('입력값'!C47*100*(3/12)) | U12: =-('입력값'!C47*100*(3/12)) | V12: =-('입력값'!C47*100*(3/12)) | W12: =-('입력값'!C47*100*(3/12)) | X12: =-('입력값'!C47*100*(3/12)) | Y12: =-('입력값'!C47*100*(3/12)) | Z12: =-('입력값'!C47*100*(3/12)) | AA12: =-('입력값'!C47*100*(3/12)) | AB12: =-('입력값'!C47*100*(3/12)) | AC12: =-('입력값'!C47*100*(3/12)) | AD12: =-('입력값'!C47*100*(3/12)) | AE12: =-('입력값'!C47*100*(3/12)) | AF12: =-('입력값'!C47*100*(3/12)) | AG12: =-('입력값'!C47*100*(3/12)) | AH12: =-('입력값'!C47*100*(3/12)) | AI12: =-('입력값'!C47*100*(3/12)) | AJ12: =-('입력값'!C47*100*(3/12)) | AK12: =-('입력값'!C47*100*(3/12)) | AL12: =-('입력값'!C47*100*(3/12)) | AM12: =-('입력값'!C47*100*(3/12)) | AN12: =-('입력값'!C47*100*(3/12)) | AO12: =-('입력값'!C47*100*(3/12)) | AP12: =-('입력값'!C47*100*(3/12)) | AQ12: =-('입력값'!C47*100*(3/12)) | AR12: =-('입력값'!C47*100*(3/12)) | AS12: =-('입력값'!C47*100*(3/12)) | AT12: =-('입력값'!C47*100*(3/12)) | AU12: =-('입력값'!C47*100*(3/12)) | AV12: =-('입력값'!C47*100*(3/12)) | AW12: =-('입력값'!C47*100*(3/12)) | AX12: =-('입력값'!C47*100*(3/12)) | AY12: =-('입력값'!C47*100*(3/12)) | AZ12: =-('입력값'!C47*100*(3/12)) | BA12: =-('입력값'!C47*100*(3/12)) | BB12: =-('입력값'!C47*100*(3/12)) | BC12: =-('입력값'!C47*100*(3/12)) | BD12: =-('입력값'!C47*100*(3/12)) | BE12: =-('입력값'!C47*100*(3/12)) | BF12: =-('입력값'!C47*100*(3/12)) | BG12: =-('입력값'!C47*100*(3/12)) | BH12: =-('입력값'!C47*100*(3/12)) | BI12: =-('입력값'!C47*100*(3/12)) | BJ12: =-('입력값'!C47*100*(3/12)) | BK12: =-('입력값'!C47*100*(3/12)) | BL12: =-('입력값'!C47*100*(3/12)) | BM12: =-('입력값'!C47*100*(3/12)) | BN12: =-('입력값'!C47*100*(3/12)) | BO12: =-('입력값'!C47*100*(3/12)) | BP12: =-('입력값'!C47*100*(3/12)) | BQ12: =-('입력값'!C47*100*(3/12)) | BR12: =-('입력값'!C47*100*(3/12)) | BS12: =-('입력값'!C47*100*(3/12)) | BT12: =-('입력값'!C47*100*(3/12)) | BU12: =-('입력값'!C47*100*(3/12)) | BV12: =-('입력값'!C47*100*(3/12)) | BW12: =-('입력값'!C47*100*(3/12)) | BX12: =-('입력값'!C47*100*(3/12)) | BY12: =-('입력값'!C47*100*(3/12)) | BZ12: =-('입력값'!C47*100*(3/12)) | CA12: =-('입력값'!C47*100*(3/12)) | CB12: =-('입력값'!C47*100*(3/12)) | CC12: =-('입력값'!C47*100*(3/12)) | CD12: =-('입력값'!C47*100*(3/12)) | CE12: =-('입력값'!C47*100*(3/12)) | CF12: =-('입력값'!C47*100*(3/12)) | CG12: =-('입력값'!C47*100*(3/12)) | CH12: =-('입력값'!C47*100*(3/12)) | CI12: =-('입력값'!C47*100*(3/12)) | CJ12: =-('입력값'!C47*100*(3/12)) | CK12: =-('입력값'!C47*100*(3/12)) | CL12: =-('입력값'!C47*100*(3/12))
B13: 소내전력비 | C13: [KRWm] | D13: 0 | E13: 0 | F13: 0 | G13: 0 | H13: 0 | I13: 0 | J13: 0 | K13: =-('입력값'!C48*100*(3/12)*(1+'입력값'!D48/100)^0) | L13: =-('입력값'!C48*100*(3/12)*(1+'입력값'!D48/100)^0) | M13: =-('입력값'!C48*100*(3/12)*(1+'입력값'!D48/100)^0) | N13: =-('입력값'!C48*100*(3/12)*(1+'입력값'!D48/100)^0) | O13: =-('입력값'!C48*100*(3/12)*(1+'입력값'!D48/100)^1) | P13: =-('입력값'!C48*100*(3/12)*(1+'입력값'!D48/100)^1) | Q13: =-('입력값'!C48*100*(3/12)*(1+'입력값'!D48/100)^1) | R13: =-('입력값'!C48*100*(3/12)*(1+'입력값'!D48/100)^1) | S13: =-('입력값'!C48*100*(3/12)*(1+'입력값'!D48/100)^2) | T13: =-('입력값'!C48*100*(3/12)*(1+'입력값'!D48/100)^2) | U13: =-('입력값'!C48*100*(3/12)*(1+'입력값'!D48/100)^2) | V13: =-('입력값'!C48*100*(3/12)*(1+'입력값'!D48/100)^2) | W13: =-('입력값'!C48*100*(3/12)*(1+'입력값'!D48/100)^3) | X13: =-('입력값'!C48*100*(3/12)*(1+'입력값'!D48/100)^3) | Y13: =-('입력값'!C48*100*(3/12)*(1+'입력값'!D48/100)^3) | Z13: =-('입력값'!C48*100*(3/12)*(1+'입력값'!D48/100)^3) | AA13: =-('입력값'!C48*100*(3/12)*(1+'입력값'!D48/100)^4) | AB13: =-('입력값'!C48*100*(3/12)*(1+'입력값'!D48/100)^4) | AC13: =-('입력값'!C48*100*(3/12)*(1+'입력값'!D48/100)^4) | AD13: =-('입력값'!C48*100*(3/12)*(1+'입력값'!D48/100)^4) | AE13: =-('입력값'!C48*100*(3/12)*(1+'입력값'!D48/100)^5) | AF13: =-('입력값'!C48*100*(3/12)*(1+'입력값'!D48/100)^5) | AG13: =-('입력값'!C48*100*(3/12)*(1+'입력값'!D48/100)^5) | AH13: =-('입력값'!C48*100*(3/12)*(1+'입력값'!D48/100)^5) | AI13: =-('입력값'!C48*100*(3/12)*(1+'입력값'!D48/100)^6) | AJ13: =-('입력값'!C48*100*(3/12)*(1+'입력값'!D48/100)^6) | AK13: =-('입력값'!C48*100*(3/12)*(1+'입력값'!D48/100)^6) | AL13: =-('입력값'!C48*100*(3/12)*(1+'입력값'!D48/100)^6) | AM13: =-('입력값'!C48*100*(3/12)*(1+'입력값'!D48/100)^7) | AN13: =-('입력값'!C48*100*(3/12)*(1+'입력값'!D48/100)^7) | AO13: =-('입력값'!C48*100*(3/12)*(1+'입력값'!D48/100)^7) | AP13: =-('입력값'!C48*100*(3/12)*(1+'입력값'!D48/100)^7) | AQ13: =-('입력값'!C48*100*(3/12)*(1+'입력값'!D48/100)^8) | AR13: =-('입력값'!C48*100*(3/12)*(1+'입력값'!D48/100)^8) | AS13: =-('입력값'!C48*100*(3/12)*(1+'입력값'!D48/100)^8) | AT13: =-('입력값'!C48*100*(3/12)*(1+'입력값'!D48/100)^8) | AU13: =-('입력값'!C48*100*(3/12)*(1+'입력값'!D48/100)^9) | AV13: =-('입력값'!C48*100*(3/12)*(1+'입력값'!D48/100)^9) | AW13: =-('입력값'!C48*100*(3/12)*(1+'입력값'!D48/100)^9) | AX13: =-('입력값'!C48*100*(3/12)*(1+'입력값'!D48/100)^9) | AY13: =-('입력값'!C48*100*(3/12)*(1+'입력값'!D48/100)^10) | AZ13: =-('입력값'!C48*100*(3/12)*(1+'입력값'!D48/100)^10) | BA13: =-('입력값'!C48*100*(3/12)*(1+'입력값'!D48/100)^10) | BB13: =-('입력값'!C48*100*(3/12)*(1+'입력값'!D48/100)^10) | BC13: =-('입력값'!C48*100*(3/12)*(1+'입력값'!D48/100)^11) | BD13: =-('입력값'!C48*100*(3/12)*(1+'입력값'!D48/100)^11) | BE13: =-('입력값'!C48*100*(3/12)*(1+'입력값'!D48/100)^11) | BF13: =-('입력값'!C48*100*(3/12)*(1+'입력값'!D48/100)^11) | BG13: =-('입력값'!C48*100*(3/12)*(1+'입력값'!D48/100)^12) | BH13: =-('입력값'!C48*100*(3/12)*(1+'입력값'!D48/100)^12) | BI13: =-('입력값'!C48*100*(3/12)*(1+'입력값'!D48/100)^12) | BJ13: =-('입력값'!C48*100*(3/12)*(1+'입력값'!D48/100)^12) | BK13: =-('입력값'!C48*100*(3/12)*(1+'입력값'!D48/100)^13) | BL13: =-('입력값'!C48*100*(3/12)*(1+'입력값'!D48/100)^13) | BM13: =-('입력값'!C48*100*(3/12)*(1+'입력값'!D48/100)^13) | BN13: =-('입력값'!C48*100*(3/12)*(1+'입력값'!D48/100)^13) | BO13: =-('입력값'!C48*100*(3/12)*(1+'입력값'!D48/100)^14) | BP13: =-('입력값'!C48*100*(3/12)*(1+'입력값'!D48/100)^14) | BQ13: =-('입력값'!C48*100*(3/12)*(1+'입력값'!D48/100)^14) | BR13: =-('입력값'!C48*100*(3/12)*(1+'입력값'!D48/100)^14) | BS13: =-('입력값'!C48*100*(3/12)*(1+'입력값'!D48/100)^15) | BT13: =-('입력값'!C48*100*(3/12)*(1+'입력값'!D48/100)^15) | BU13: =-('입력값'!C48*100*(3/12)*(1+'입력값'!D48/100)^15) | BV13: =-('입력값'!C48*100*(3/12)*(1+'입력값'!D48/100)^15) | BW13: =-('입력값'!C48*100*(3/12)*(1+'입력값'!D48/100)^16) | BX13: =-('입력값'!C48*100*(3/12)*(1+'입력값'!D48/100)^16) | BY13: =-('입력값'!C48*100*(3/12)*(1+'입력값'!D48/100)^16) | BZ13: =-('입력값'!C48*100*(3/12)*(1+'입력값'!D48/100)^16) | CA13: =-('입력값'!C48*100*(3/12)*(1+'입력값'!D48/100)^17) | CB13: =-('입력값'!C48*100*(3/12)*(1+'입력값'!D48/100)^17) | CC13: =-('입력값'!C48*100*(3/12)*(1+'입력값'!D48/100)^17) | CD13: =-('입력값'!C48*100*(3/12)*(1+'입력값'!D48/100)^17) | CE13: =-('입력값'!C48*100*(3/12)*(1+'입력값'!D48/100)^18) | CF13: =-('입력값'!C48*100*(3/12)*(1+'입력값'!D48/100)^18) | CG13: =-('입력값'!C48*100*(3/12)*(1+'입력값'!D48/100)^18) | CH13: =-('입력값'!C48*100*(3/12)*(1+'입력값'!D48/100)^18) | CI13: =-('입력값'!C48*100*(3/12)*(1+'입력값'!D48/100)^19) | CJ13: =-('입력값'!C48*100*(3/12)*(1+'입력값'!D48/100)^19) | CK13: =-('입력값'!C48*100*(3/12)*(1+'입력값'!D48/100)^19) | CL13: =-('입력값'!C48*100*(3/12)*(1+'입력값'!D48/100)^19)
B14: 인건비 | C14: [KRWm] | D14: 0 | E14: 0 | F14: 0 | G14: 0 | H14: 0 | I14: 0 | J14: 0 | K14: =-('입력값'!C49*100*(3/12)*(1+'입력값'!D49/100)^0) | L14: =-('입력값'!C49*100*(3/12)*(1+'입력값'!D49/100)^0) | M14: =-('입력값'!C49*100*(3/12)*(1+'입력값'!D49/100)^0) | N14: =-('입력값'!C49*100*(3/12)*(1+'입력값'!D49/100)^0) | O14: =-('입력값'!C49*100*(3/12)*(1+'입력값'!D49/100)^1) | P14: =-('입력값'!C49*100*(3/12)*(1+'입력값'!D49/100)^1) | Q14: =-('입력값'!C49*100*(3/12)*(1+'입력값'!D49/100)^1) | R14: =-('입력값'!C49*100*(3/12)*(1+'입력값'!D49/100)^1) | S14: =-('입력값'!C49*100*(3/12)*(1+'입력값'!D49/100)^2) | T14: =-('입력값'!C49*100*(3/12)*(1+'입력값'!D49/100)^2) | U14: =-('입력값'!C49*100*(3/12)*(1+'입력값'!D49/100)^2) | V14: =-('입력값'!C49*100*(3/12)*(1+'입력값'!D49/100)^2) | W14: =-('입력값'!C49*100*(3/12)*(1+'입력값'!D49/100)^3) | X14: =-('입력값'!C49*100*(3/12)*(1+'입력값'!D49/100)^3) | Y14: =-('입력값'!C49*100*(3/12)*(1+'입력값'!D49/100)^3) | Z14: =-('입력값'!C49*100*(3/12)*(1+'입력값'!D49/100)^3) | AA14: =-('입력값'!C49*100*(3/12)*(1+'입력값'!D49/100)^4) | AB14: =-('입력값'!C49*100*(3/12)*(1+'입력값'!D49/100)^4) | AC14: =-('입력값'!C49*100*(3/12)*(1+'입력값'!D49/100)^4) | AD14: =-('입력값'!C49*100*(3/12)*(1+'입력값'!D49/100)^4) | AE14: =-('입력값'!C49*100*(3/12)*(1+'입력값'!D49/100)^5) | AF14: =-('입력값'!C49*100*(3/12)*(1+'입력값'!D49/100)^5) | AG14: =-('입력값'!C49*100*(3/12)*(1+'입력값'!D49/100)^5) | AH14: =-('입력값'!C49*100*(3/12)*(1+'입력값'!D49/100)^5) | AI14: =-('입력값'!C49*100*(3/12)*(1+'입력값'!D49/100)^6) | AJ14: =-('입력값'!C49*100*(3/12)*(1+'입력값'!D49/100)^6) | AK14: =-('입력값'!C49*100*(3/12)*(1+'입력값'!D49/100)^6) | AL14: =-('입력값'!C49*100*(3/12)*(1+'입력값'!D49/100)^6) | AM14: =-('입력값'!C49*100*(3/12)*(1+'입력값'!D49/100)^7) | AN14: =-('입력값'!C49*100*(3/12)*(1+'입력값'!D49/100)^7) | AO14: =-('입력값'!C49*100*(3/12)*(1+'입력값'!D49/100)^7) | AP14: =-('입력값'!C49*100*(3/12)*(1+'입력값'!D49/100)^7) | AQ14: =-('입력값'!C49*100*(3/12)*(1+'입력값'!D49/100)^8) | AR14: =-('입력값'!C49*100*(3/12)*(1+'입력값'!D49/100)^8) | AS14: =-('입력값'!C49*100*(3/12)*(1+'입력값'!D49/100)^8) | AT14: =-('입력값'!C49*100*(3/12)*(1+'입력값'!D49/100)^8) | AU14: =-('입력값'!C49*100*(3/12)*(1+'입력값'!D49/100)^9) | AV14: =-('입력값'!C49*100*(3/12)*(1+'입력값'!D49/100)^9) | AW14: =-('입력값'!C49*100*(3/12)*(1+'입력값'!D49/100)^9) | AX14: =-('입력값'!C49*100*(3/12)*(1+'입력값'!D49/100)^9) | AY14: =-('입력값'!C49*100*(3/12)*(1+'입력값'!D49/100)^10) | AZ14: =-('입력값'!C49*100*(3/12)*(1+'입력값'!D49/100)^10) | BA14: =-('입력값'!C49*100*(3/12)*(1+'입력값'!D49/100)^10) | BB14: =-('입력값'!C49*100*(3/12)*(1+'입력값'!D49/100)^10) | BC14: =-('입력값'!C49*100*(3/12)*(1+'입력값'!D49/100)^11) | BD14: =-('입력값'!C49*100*(3/12)*(1+'입력값'!D49/100)^11) | BE14: =-('입력값'!C49*100*(3/12)*(1+'입력값'!D49/100)^11) | BF14: =-('입력값'!C49*100*(3/12)*(1+'입력값'!D49/100)^11) | BG14: =-('입력값'!C49*100*(3/12)*(1+'입력값'!D49/100)^12) | BH14: =-('입력값'!C49*100*(3/12)*(1+'입력값'!D49/100)^12) | BI14: =-('입력값'!C49*100*(3/12)*(1+'입력값'!D49/100)^12) | BJ14: =-('입력값'!C49*100*(3/12)*(1+'입력값'!D49/100)^12) | BK14: =-('입력값'!C49*100*(3/12)*(1+'입력값'!D49/100)^13) | BL14: =-('입력값'!C49*100*(3/12)*(1+'입력값'!D49/100)^13) | BM14: =-('입력값'!C49*100*(3/12)*(1+'입력값'!D49/100)^13) | BN14: =-('입력값'!C49*100*(3/12)*(1+'입력값'!D49/100)^13) | BO14: =-('입력값'!C49*100*(3/12)*(1+'입력값'!D49/100)^14) | BP14: =-('입력값'!C49*100*(3/12)*(1+'입력값'!D49/100)^14) | BQ14: =-('입력값'!C49*100*(3/12)*(1+'입력값'!D49/100)^14) | BR14: =-('입력값'!C49*100*(3/12)*(1+'입력값'!D49/100)^14) | BS14: =-('입력값'!C49*100*(3/12)*(1+'입력값'!D49/100)^15) | BT14: =-('입력값'!C49*100*(3/12)*(1+'입력값'!D49/100)^15) | BU14: =-('입력값'!C49*100*(3/12)*(1+'입력값'!D49/100)^15) | BV14: =-('입력값'!C49*100*(3/12)*(1+'입력값'!D49/100)^15) | BW14: =-('입력값'!C49*100*(3/12)*(1+'입력값'!D49/100)^16) | BX14: =-('입력값'!C49*100*(3/12)*(1+'입력값'!D49/100)^16) | BY14: =-('입력값'!C49*100*(3/12)*(1+'입력값'!D49/100)^16) | BZ14: =-('입력값'!C49*100*(3/12)*(1+'입력값'!D49/100)^16) | CA14: =-('입력값'!C49*100*(3/12)*(1+'입력값'!D49/100)^17) | CB14: =-('입력값'!C49*100*(3/12)*(1+'입력값'!D49/100)^17) | CC14: =-('입력값'!C49*100*(3/12)*(1+'입력값'!D49/100)^17) | CD14: =-('입력값'!C49*100*(3/12)*(1+'입력값'!D49/100)^17) | CE14: =-('입력값'!C49*100*(3/12)*(1+'입력값'!D49/100)^18) | CF14: =-('입력값'!C49*100*(3/12)*(1+'입력값'!D49/100)^18) | CG14: =-('입력값'!C49*100*(3/12)*(1+'입력값'!D49/100)^18) | CH14: =-('입력값'!C49*100*(3/12)*(1+'입력값'!D49/100)^18) | CI14: =-('입력값'!C49*100*(3/12)*(1+'입력값'!D49/100)^19) | CJ14: =-('입력값'!C49*100*(3/12)*(1+'입력값'!D49/100)^19) | CK14: =-('입력값'!C49*100*(3/12)*(1+'입력값'!D49/100)^19) | CL14: =-('입력값'!C49*100*(3/12)*(1+'입력값'!D49/100)^19)
B15: 법인운영비 | C15: [KRWm] | D15: 0 | E15: 0 | F15: 0 | G15: 0 | H15: 0 | I15: 0 | J15: 0 | K15: =-('입력값'!C50*100*(3/12)*(1+'입력값'!D50/100)^0) | L15: =-('입력값'!C50*100*(3/12)*(1+'입력값'!D50/100)^0) | M15: =-('입력값'!C50*100*(3/12)*(1+'입력값'!D50/100)^0) | N15: =-('입력값'!C50*100*(3/12)*(1+'입력값'!D50/100)^0) | O15: =-('입력값'!C50*100*(3/12)*(1+'입력값'!D50/100)^1) | P15: =-('입력값'!C50*100*(3/12)*(1+'입력값'!D50/100)^1) | Q15: =-('입력값'!C50*100*(3/12)*(1+'입력값'!D50/100)^1) | R15: =-('입력값'!C50*100*(3/12)*(1+'입력값'!D50/100)^1) | S15: =-('입력값'!C50*100*(3/12)*(1+'입력값'!D50/100)^2) | T15: =-('입력값'!C50*100*(3/12)*(1+'입력값'!D50/100)^2) | U15: =-('입력값'!C50*100*(3/12)*(1+'입력값'!D50/100)^2) | V15: =-('입력값'!C50*100*(3/12)*(1+'입력값'!D50/100)^2) | W15: =-('입력값'!C50*100*(3/12)*(1+'입력값'!D50/100)^3) | X15: =-('입력값'!C50*100*(3/12)*(1+'입력값'!D50/100)^3) | Y15: =-('입력값'!C50*100*(3/12)*(1+'입력값'!D50/100)^3) | Z15: =-('입력값'!C50*100*(3/12)*(1+'입력값'!D50/100)^3) | AA15: =-('입력값'!C50*100*(3/12)*(1+'입력값'!D50/100)^4) | AB15: =-('입력값'!C50*100*(3/12)*(1+'입력값'!D50/100)^4) | AC15: =-('입력값'!C50*100*(3/12)*(1+'입력값'!D50/100)^4) | AD15: =-('입력값'!C50*100*(3/12)*(1+'입력값'!D50/100)^4) | AE15: =-('입력값'!C50*100*(3/12)*(1+'입력값'!D50/100)^5) | AF15: =-('입력값'!C50*100*(3/12)*(1+'입력값'!D50/100)^5) | AG15: =-('입력값'!C50*100*(3/12)*(1+'입력값'!D50/100)^5) | AH15: =-('입력값'!C50*100*(3/12)*(1+'입력값'!D50/100)^5) | AI15: =-('입력값'!C50*100*(3/12)*(1+'입력값'!D50/100)^6) | AJ15: =-('입력값'!C50*100*(3/12)*(1+'입력값'!D50/100)^6) | AK15: =-('입력값'!C50*100*(3/12)*(1+'입력값'!D50/100)^6) | AL15: =-('입력값'!C50*100*(3/12)*(1+'입력값'!D50/100)^6) | AM15: =-('입력값'!C50*100*(3/12)*(1+'입력값'!D50/100)^7) | AN15: =-('입력값'!C50*100*(3/12)*(1+'입력값'!D50/100)^7) | AO15: =-('입력값'!C50*100*(3/12)*(1+'입력값'!D50/100)^7) | AP15: =-('입력값'!C50*100*(3/12)*(1+'입력값'!D50/100)^7) | AQ15: =-('입력값'!C50*100*(3/12)*(1+'입력값'!D50/100)^8) | AR15: =-('입력값'!C50*100*(3/12)*(1+'입력값'!D50/100)^8) | AS15: =-('입력값'!C50*100*(3/12)*(1+'입력값'!D50/100)^8) | AT15: =-('입력값'!C50*100*(3/12)*(1+'입력값'!D50/100)^8) | AU15: =-('입력값'!C50*100*(3/12)*(1+'입력값'!D50/100)^9) | AV15: =-('입력값'!C50*100*(3/12)*(1+'입력값'!D50/100)^9) | AW15: =-('입력값'!C50*100*(3/12)*(1+'입력값'!D50/100)^9) | AX15: =-('입력값'!C50*100*(3/12)*(1+'입력값'!D50/100)^9) | AY15: =-('입력값'!C50*100*(3/12)*(1+'입력값'!D50/100)^10) | AZ15: =-('입력값'!C50*100*(3/12)*(1+'입력값'!D50/100)^10) | BA15: =-('입력값'!C50*100*(3/12)*(1+'입력값'!D50/100)^10) | BB15: =-('입력값'!C50*100*(3/12)*(1+'입력값'!D50/100)^10) | BC15: =-('입력값'!C50*100*(3/12)*(1+'입력값'!D50/100)^11) | BD15: =-('입력값'!C50*100*(3/12)*(1+'입력값'!D50/100)^11) | BE15: =-('입력값'!C50*100*(3/12)*(1+'입력값'!D50/100)^11) | BF15: =-('입력값'!C50*100*(3/12)*(1+'입력값'!D50/100)^11) | BG15: =-('입력값'!C50*100*(3/12)*(1+'입력값'!D50/100)^12) | BH15: =-('입력값'!C50*100*(3/12)*(1+'입력값'!D50/100)^12) | BI15: =-('입력값'!C50*100*(3/12)*(1+'입력값'!D50/100)^12) | BJ15: =-('입력값'!C50*100*(3/12)*(1+'입력값'!D50/100)^12) | BK15: =-('입력값'!C50*100*(3/12)*(1+'입력값'!D50/100)^13) | BL15: =-('입력값'!C50*100*(3/12)*(1+'입력값'!D50/100)^13) | BM15: =-('입력값'!C50*100*(3/12)*(1+'입력값'!D50/100)^13) | BN15: =-('입력값'!C50*100*(3/12)*(1+'입력값'!D50/100)^13) | BO15: =-('입력값'!C50*100*(3/12)*(1+'입력값'!D50/100)^14) | BP15: =-('입력값'!C50*100*(3/12)*(1+'입력값'!D50/100)^14) | BQ15: =-('입력값'!C50*100*(3/12)*(1+'입력값'!D50/100)^14) | BR15: =-('입력값'!C50*100*(3/12)*(1+'입력값'!D50/100)^14) | BS15: =-('입력값'!C50*100*(3/12)*(1+'입력값'!D50/100)^15) | BT15: =-('입력값'!C50*100*(3/12)*(1+'입력값'!D50/100)^15) | BU15: =-('입력값'!C50*100*(3/12)*(1+'입력값'!D50/100)^15) | BV15: =-('입력값'!C50*100*(3/12)*(1+'입력값'!D50/100)^15) | BW15: =-('입력값'!C50*100*(3/12)*(1+'입력값'!D50/100)^16) | BX15: =-('입력값'!C50*100*(3/12)*(1+'입력값'!D50/100)^16) | BY15: =-('입력값'!C50*100*(3/12)*(1+'입력값'!D50/100)^16) | BZ15: =-('입력값'!C50*100*(3/12)*(1+'입력값'!D50/100)^16) | CA15: =-('입력값'!C50*100*(3/12)*(1+'입력값'!D50/100)^17) | CB15: =-('입력값'!C50*100*(3/12)*(1+'입력값'!D50/100)^17) | CC15: =-('입력값'!C50*100*(3/12)*(1+'입력값'!D50/100)^17) | CD15: =-('입력값'!C50*100*(3/12)*(1+'입력값'!D50/100)^17) | CE15: =-('입력값'!C50*100*(3/12)*(1+'입력값'!D50/100)^18) | CF15: =-('입력값'!C50*100*(3/12)*(1+'입력값'!D50/100)^18) | CG15: =-('입력값'!C50*100*(3/12)*(1+'입력값'!D50/100)^18) | CH15: =-('입력값'!C50*100*(3/12)*(1+'입력값'!D50/100)^18) | CI15: =-('입력값'!C50*100*(3/12)*(1+'입력값'!D50/100)^19) | CJ15: =-('입력값'!C50*100*(3/12)*(1+'입력값'!D50/100)^19) | CK15: =-('입력값'!C50*100*(3/12)*(1+'입력값'!D50/100)^19) | CL15: =-('입력값'!C50*100*(3/12)*(1+'입력값'!D50/100)^19)
B16: 주민보상비 | C16: [KRWm] | D16: 0 | E16: 0 | F16: 0 | G16: 0 | H16: 0 | I16: 0 | J16: 0 | K16: =-('입력값'!C51*100*(3/12)) | L16: =-('입력값'!C51*100*(3/12)) | M16: =-('입력값'!C51*100*(3/12)) | N16: =-('입력값'!C51*100*(3/12)) | O16: =-('입력값'!C51*100*(3/12)) | P16: =-('입력값'!C51*100*(3/12)) | Q16: =-('입력값'!C51*100*(3/12)) | R16: =-('입력값'!C51*100*(3/12)) | S16: =-('입력값'!C51*100*(3/12)) | T16: =-('입력값'!C51*100*(3/12)) | U16: =-('입력값'!C51*100*(3/12)) | V16: =-('입력값'!C51*100*(3/12)) | W16: =-('입력값'!C51*100*(3/12)) | X16: =-('입력값'!C51*100*(3/12)) | Y16: =-('입력값'!C51*100*(3/12)) | Z16: =-('입력값'!C51*100*(3/12)) | AA16: =-('입력값'!C51*100*(3/12)) | AB16: =-('입력값'!C51*100*(3/12)) | AC16: =-('입력값'!C51*100*(3/12)) | AD16: =-('입력값'!C51*100*(3/12)) | AE16: =-('입력값'!C51*100*(3/12)) | AF16: =-('입력값'!C51*100*(3/12)) | AG16: =-('입력값'!C51*100*(3/12)) | AH16: =-('입력값'!C51*100*(3/12)) | AI16: =-('입력값'!C51*100*(3/12)) | AJ16: =-('입력값'!C51*100*(3/12)) | AK16: =-('입력값'!C51*100*(3/12)) | AL16: =-('입력값'!C51*100*(3/12)) | AM16: =-('입력값'!C51*100*(3/12)) | AN16: =-('입력값'!C51*100*(3/12)) | AO16: =-('입력값'!C51*100*(3/12)) | AP16: =-('입력값'!C51*100*(3/12)) | AQ16: =-('입력값'!C51*100*(3/12)) | AR16: =-('입력값'!C51*100*(3/12)) | AS16: =-('입력값'!C51*100*(3/12)) | AT16: =-('입력값'!C51*100*(3/12)) | AU16: =-('입력값'!C51*100*(3/12)) | AV16: =-('입력값'!C51*100*(3/12)) | AW16: =-('입력값'!C51*100*(3/12)) | AX16: =-('입력값'!C51*100*(3/12)) | AY16: =-('입력값'!C51*100*(3/12)) | AZ16: =-('입력값'!C51*100*(3/12)) | BA16: =-('입력값'!C51*100*(3/12)) | BB16: =-('입력값'!C51*100*(3/12)) | BC16: =-('입력값'!C51*100*(3/12)) | BD16: =-('입력값'!C51*100*(3/12)) | BE16: =-('입력값'!C51*100*(3/12)) | BF16: =-('입력값'!C51*100*(3/12)) | BG16: =-('입력값'!C51*100*(3/12)) | BH16: =-('입력값'!C51*100*(3/12)) | BI16: =-('입력값'!C51*100*(3/12)) | BJ16: =-('입력값'!C51*100*(3/12)) | BK16: =-('입력값'!C51*100*(3/12)) | BL16: =-('입력값'!C51*100*(3/12)) | BM16: =-('입력값'!C51*100*(3/12)) | BN16: =-('입력값'!C51*100*(3/12)) | BO16: =-('입력값'!C51*100*(3/12)) | BP16: =-('입력값'!C51*100*(3/12)) | BQ16: =-('입력값'!C51*100*(3/12)) | BR16: =-('입력값'!C51*100*(3/12)) | BS16: =-('입력값'!C51*100*(3/12)) | BT16: =-('입력값'!C51*100*(3/12)) | BU16: =-('입력값'!C51*100*(3/12)) | BV16: =-('입력값'!C51*100*(3/12)) | BW16: =-('입력값'!C51*100*(3/12)) | BX16: =-('입력값'!C51*100*(3/12)) | BY16: =-('입력값'!C51*100*(3/12)) | BZ16: =-('입력값'!C51*100*(3/12)) | CA16: =-('입력값'!C51*100*(3/12)) | CB16: =-('입력값'!C51*100*(3/12)) | CC16: =-('입력값'!C51*100*(3/12)) | CD16: =-('입력값'!C51*100*(3/12)) | CE16: =-('입력값'!C51*100*(3/12)) | CF16: =-('입력값'!C51*100*(3/12)) | CG16: =-('입력값'!C51*100*(3/12)) | CH16: =-('입력값'!C51*100*(3/12)) | CI16: =-('입력값'!C51*100*(3/12)) | CJ16: =-('입력값'!C51*100*(3/12)) | CK16: =-('입력값'!C51*100*(3/12)) | CL16: =-('입력값'!C51*100*(3/12))
B17: 도로점용료 | C17: [KRWm] | D17: 0 | E17: 0 | F17: 0 | G17: 0 | H17: 0 | I17: 0 | J17: 0 | K17: =-('입력값'!C52*100*(3/12)) | L17: =-('입력값'!C52*100*(3/12)) | M17: =-('입력값'!C52*100*(3/12)) | N17: =-('입력값'!C52*100*(3/12)) | O17: =-('입력값'!C52*100*(3/12)) | P17: =-('입력값'!C52*100*(3/12)) | Q17: =-('입력값'!C52*100*(3/12)) | R17: =-('입력값'!C52*100*(3/12)) | S17: =-('입력값'!C52*100*(3/12)) | T17: =-('입력값'!C52*100*(3/12)) | U17: =-('입력값'!C52*100*(3/12)) | V17: =-('입력값'!C52*100*(3/12)) | W17: =-('입력값'!C52*100*(3/12)) | X17: =-('입력값'!C52*100*(3/12)) | Y17: =-('입력값'!C52*100*(3/12)) | Z17: =-('입력값'!C52*100*(3/12)) | AA17: =-('입력값'!C52*100*(3/12)) | AB17: =-('입력값'!C52*100*(3/12)) | AC17: =-('입력값'!C52*100*(3/12)) | AD17: =-('입력값'!C52*100*(3/12)) | AE17: =-('입력값'!C52*100*(3/12)) | AF17: =-('입력값'!C52*100*(3/12)) | AG17: =-('입력값'!C52*100*(3/12)) | AH17: =-('입력값'!C52*100*(3/12)) | AI17: =-('입력값'!C52*100*(3/12)) | AJ17: =-('입력값'!C52*100*(3/12)) | AK17: =-('입력값'!C52*100*(3/12)) | AL17: =-('입력값'!C52*100*(3/12)) | AM17: =-('입력값'!C52*100*(3/12)) | AN17: =-('입력값'!C52*100*(3/12)) | AO17: =-('입력값'!C52*100*(3/12)) | AP17: =-('입력값'!C52*100*(3/12)) | AQ17: =-('입력값'!C52*100*(3/12)) | AR17: =-('입력값'!C52*100*(3/12)) | AS17: =-('입력값'!C52*100*(3/12)) | AT17: =-('입력값'!C52*100*(3/12)) | AU17: =-('입력값'!C52*100*(3/12)) | AV17: =-('입력값'!C52*100*(3/12)) | AW17: =-('입력값'!C52*100*(3/12)) | AX17: =-('입력값'!C52*100*(3/12)) | AY17: =-('입력값'!C52*100*(3/12)) | AZ17: =-('입력값'!C52*100*(3/12)) | BA17: =-('입력값'!C52*100*(3/12)) | BB17: =-('입력값'!C52*100*(3/12)) | BC17: =-('입력값'!C52*100*(3/12)) | BD17: =-('입력값'!C52*100*(3/12)) | BE17: =-('입력값'!C52*100*(3/12)) | BF17: =-('입력값'!C52*100*(3/12)) | BG17: =-('입력값'!C52*100*(3/12)) | BH17: =-('입력값'!C52*100*(3/12)) | BI17: =-('입력값'!C52*100*(3/12)) | BJ17: =-('입력값'!C52*100*(3/12)) | BK17: =-('입력값'!C52*100*(3/12)) | BL17: =-('입력값'!C52*100*(3/12)) | BM17: =-('입력값'!C52*100*(3/12)) | BN17: =-('입력값'!C52*100*(3/12)) | BO17: =-('입력값'!C52*100*(3/12)) | BP17: =-('입력값'!C52*100*(3/12)) | BQ17: =-('입력값'!C52*100*(3/12)) | BR17: =-('입력값'!C52*100*(3/12)) | BS17: =-('입력값'!C52*100*(3/12)) | BT17: =-('입력값'!C52*100*(3/12)) | BU17: =-('입력값'!C52*100*(3/12)) | BV17: =-('입력값'!C52*100*(3/12)) | BW17: =-('입력값'!C52*100*(3/12)) | BX17: =-('입력값'!C52*100*(3/12)) | BY17: =-('입력값'!C52*100*(3/12)) | BZ17: =-('입력값'!C52*100*(3/12)) | CA17: =-('입력값'!C52*100*(3/12)) | CB17: =-('입력값'!C52*100*(3/12)) | CC17: =-('입력값'!C52*100*(3/12)) | CD17: =-('입력값'!C52*100*(3/12)) | CE17: =-('입력값'!C52*100*(3/12)) | CF17: =-('입력값'!C52*100*(3/12)) | CG17: =-('입력값'!C52*100*(3/12)) | CH17: =-('입력값'!C52*100*(3/12)) | CI17: =-('입력값'!C52*100*(3/12)) | CJ17: =-('입력값'!C52*100*(3/12)) | CK17: =-('입력값'!C52*100*(3/12)) | CL17: =-('입력값'!C52*100*(3/12))
B18: 예비비 | C18: [KRWm] | D18: 0 | E18: 0 | F18: 0 | G18: 0 | H18: 0 | I18: 0 | J18: 0 | K18: =-('입력값'!C53*100*(3/12)) | L18: =-('입력값'!C53*100*(3/12)) | M18: =-('입력값'!C53*100*(3/12)) | N18: =-('입력값'!C53*100*(3/12)) | O18: =-('입력값'!C53*100*(3/12)) | P18: =-('입력값'!C53*100*(3/12)) | Q18: =-('입력값'!C53*100*(3/12)) | R18: =-('입력값'!C53*100*(3/12)) | S18: =-('입력값'!C53*100*(3/12)) | T18: =-('입력값'!C53*100*(3/12)) | U18: =-('입력값'!C53*100*(3/12)) | V18: =-('입력값'!C53*100*(3/12)) | W18: =-('입력값'!C53*100*(3/12)) | X18: =-('입력값'!C53*100*(3/12)) | Y18: =-('입력값'!C53*100*(3/12)) | Z18: =-('입력값'!C53*100*(3/12)) | AA18: =-('입력값'!C53*100*(3/12)) | AB18: =-('입력값'!C53*100*(3/12)) | AC18: =-('입력값'!C53*100*(3/12)) | AD18: =-('입력값'!C53*100*(3/12)) | AE18: =-('입력값'!C53*100*(3/12)) | AF18: =-('입력값'!C53*100*(3/12)) | AG18: =-('입력값'!C53*100*(3/12)) | AH18: =-('입력값'!C53*100*(3/12)) | AI18: =-('입력값'!C53*100*(3/12)) | AJ18: =-('입력값'!C53*100*(3/12)) | AK18: =-('입력값'!C53*100*(3/12)) | AL18: =-('입력값'!C53*100*(3/12)) | AM18: =-('입력값'!C53*100*(3/12)) | AN18: =-('입력값'!C53*100*(3/12)) | AO18: =-('입력값'!C53*100*(3/12)) | AP18: =-('입력값'!C53*100*(3/12)) | AQ18: =-('입력값'!C53*100*(3/12)) | AR18: =-('입력값'!C53*100*(3/12)) | AS18: =-('입력값'!C53*100*(3/12)) | AT18: =-('입력값'!C53*100*(3/12)) | AU18: =-('입력값'!C53*100*(3/12)) | AV18: =-('입력값'!C53*100*(3/12)) | AW18: =-('입력값'!C53*100*(3/12)) | AX18: =-('입력값'!C53*100*(3/12)) | AY18: =-('입력값'!C53*100*(3/12)) | AZ18: =-('입력값'!C53*100*(3/12)) | BA18: =-('입력값'!C53*100*(3/12)) | BB18: =-('입력값'!C53*100*(3/12)) | BC18: =-('입력값'!C53*100*(3/12)) | BD18: =-('입력값'!C53*100*(3/12)) | BE18: =-('입력값'!C53*100*(3/12)) | BF18: =-('입력값'!C53*100*(3/12)) | BG18: =-('입력값'!C53*100*(3/12)) | BH18: =-('입력값'!C53*100*(3/12)) | BI18: =-('입력값'!C53*100*(3/12)) | BJ18: =-('입력값'!C53*100*(3/12)) | BK18: =-('입력값'!C53*100*(3/12)) | BL18: =-('입력값'!C53*100*(3/12)) | BM18: =-('입력값'!C53*100*(3/12)) | BN18: =-('입력값'!C53*100*(3/12)) | BO18: =-('입력값'!C53*100*(3/12)) | BP18: =-('입력값'!C53*100*(3/12)) | BQ18: =-('입력값'!C53*100*(3/12)) | BR18: =-('입력값'!C53*100*(3/12)) | BS18: =-('입력값'!C53*100*(3/12)) | BT18: =-('입력값'!C53*100*(3/12)) | BU18: =-('입력값'!C53*100*(3/12)) | BV18: =-('입력값'!C53*100*(3/12)) | BW18: =-('입력값'!C53*100*(3/12)) | BX18: =-('입력값'!C53*100*(3/12)) | BY18: =-('입력값'!C53*100*(3/12)) | BZ18: =-('입력값'!C53*100*(3/12)) | CA18: =-('입력값'!C53*100*(3/12)) | CB18: =-('입력값'!C53*100*(3/12)) | CC18: =-('입력값'!C53*100*(3/12)) | CD18: =-('입력값'!C53*100*(3/12)) | CE18: =-('입력값'!C53*100*(3/12)) | CF18: =-('입력값'!C53*100*(3/12)) | CG18: =-('입력값'!C53*100*(3/12)) | CH18: =-('입력값'!C53*100*(3/12)) | CI18: =-('입력값'!C53*100*(3/12)) | CJ18: =-('입력값'!C53*100*(3/12)) | CK18: =-('입력값'!C53*100*(3/12)) | CL18: =-('입력값'!C53*100*(3/12))
B19: 전력거래수수료 | C19: [KRWm] | D19: 0 | E19: 0 | F19: 0 | G19: 0 | H19: 0 | I19: 0 | J19: 0 | K19: =-('입력값'!C54*100*(3/12)) | L19: =-('입력값'!C54*100*(3/12)) | M19: =-('입력값'!C54*100*(3/12)) | N19: =-('입력값'!C54*100*(3/12)) | O19: =-('입력값'!C54*100*(3/12)) | P19: =-('입력값'!C54*100*(3/12)) | Q19: =-('입력값'!C54*100*(3/12)) | R19: =-('입력값'!C54*100*(3/12)) | S19: =-('입력값'!C54*100*(3/12)) | T19: =-('입력값'!C54*100*(3/12)) | U19: =-('입력값'!C54*100*(3/12)) | V19: =-('입력값'!C54*100*(3/12)) | W19: =-('입력값'!C54*100*(3/12)) | X19: =-('입력값'!C54*100*(3/12)) | Y19: =-('입력값'!C54*100*(3/12)) | Z19: =-('입력값'!C54*100*(3/12)) | AA19: =-('입력값'!C54*100*(3/12)) | AB19: =-('입력값'!C54*100*(3/12)) | AC19: =-('입력값'!C54*100*(3/12)) | AD19: =-('입력값'!C54*100*(3/12)) | AE19: =-('입력값'!C54*100*(3/12)) | AF19: =-('입력값'!C54*100*(3/12)) | AG19: =-('입력값'!C54*100*(3/12)) | AH19: =-('입력값'!C54*100*(3/12)) | AI19: =-('입력값'!C54*100*(3/12)) | AJ19: =-('입력값'!C54*100*(3/12)) | AK19: =-('입력값'!C54*100*(3/12)) | AL19: =-('입력값'!C54*100*(3/12)) | AM19: =-('입력값'!C54*100*(3/12)) | AN19: =-('입력값'!C54*100*(3/12)) | AO19: =-('입력값'!C54*100*(3/12)) | AP19: =-('입력값'!C54*100*(3/12)) | AQ19: =-('입력값'!C54*100*(3/12)) | AR19: =-('입력값'!C54*100*(3/12)) | AS19: =-('입력값'!C54*100*(3/12)) | AT19: =-('입력값'!C54*100*(3/12)) | AU19: =-('입력값'!C54*100*(3/12)) | AV19: =-('입력값'!C54*100*(3/12)) | AW19: =-('입력값'!C54*100*(3/12)) | AX19: =-('입력값'!C54*100*(3/12)) | AY19: =-('입력값'!C54*100*(3/12)) | AZ19: =-('입력값'!C54*100*(3/12)) | BA19: =-('입력값'!C54*100*(3/12)) | BB19: =-('입력값'!C54*100*(3/12)) | BC19: =-('입력값'!C54*100*(3/12)) | BD19: =-('입력값'!C54*100*(3/12)) | BE19: =-('입력값'!C54*100*(3/12)) | BF19: =-('입력값'!C54*100*(3/12)) | BG19: =-('입력값'!C54*100*(3/12)) | BH19: =-('입력값'!C54*100*(3/12)) | BI19: =-('입력값'!C54*100*(3/12)) | BJ19: =-('입력값'!C54*100*(3/12)) | BK19: =-('입력값'!C54*100*(3/12)) | BL19: =-('입력값'!C54*100*(3/12)) | BM19: =-('입력값'!C54*100*(3/12)) | BN19: =-('입력값'!C54*100*(3/12)) | BO19: =-('입력값'!C54*100*(3/12)) | BP19: =-('입력값'!C54*100*(3/12)) | BQ19: =-('입력값'!C54*100*(3/12)) | BR19: =-('입력값'!C54*100*(3/12)) | BS19: =-('입력값'!C54*100*(3/12)) | BT19: =-('입력값'!C54*100*(3/12)) | BU19: =-('입력값'!C54*100*(3/12)) | BV19: =-('입력값'!C54*100*(3/12)) | BW19: =-('입력값'!C54*100*(3/12)) | BX19: =-('입력값'!C54*100*(3/12)) | BY19: =-('입력값'!C54*100*(3/12)) | BZ19: =-('입력값'!C54*100*(3/12)) | CA19: =-('입력값'!C54*100*(3/12)) | CB19: =-('입력값'!C54*100*(3/12)) | CC19: =-('입력값'!C54*100*(3/12)) | CD19: =-('입력값'!C54*100*(3/12)) | CE19: =-('입력값'!C54*100*(3/12)) | CF19: =-('입력값'!C54*100*(3/12)) | CG19: =-('입력값'!C54*100*(3/12)) | CH19: =-('입력값'!C54*100*(3/12)) | CI19: =-('입력값'!C54*100*(3/12)) | CJ19: =-('입력값'!C54*100*(3/12)) | CK19: =-('입력값'!C54*100*(3/12)) | CL19: =-('입력값'!C54*100*(3/12))
B20: 관리운영비 성과보수 | C20: [KRWm] | D20: 0 | E20: 0 | F20: 0 | G20: 0 | H20: 0 | I20: 0 | J20: 0 | K20: =-('입력값'!C55*100*(3/12)) | L20: =-('입력값'!C55*100*(3/12)) | M20: =-('입력값'!C55*100*(3/12)) | N20: =-('입력값'!C55*100*(3/12)) | O20: =-('입력값'!C55*100*(3/12)) | P20: =-('입력값'!C55*100*(3/12)) | Q20: =-('입력값'!C55*100*(3/12)) | R20: =-('입력값'!C55*100*(3/12)) | S20: =-('입력값'!C55*100*(3/12)) | T20: =-('입력값'!C55*100*(3/12)) | U20: =-('입력값'!C55*100*(3/12)) | V20: =-('입력값'!C55*100*(3/12)) | W20: =-('입력값'!C55*100*(3/12)) | X20: =-('입력값'!C55*100*(3/12)) | Y20: =-('입력값'!C55*100*(3/12)) | Z20: =-('입력값'!C55*100*(3/12)) | AA20: =-('입력값'!C55*100*(3/12)) | AB20: =-('입력값'!C55*100*(3/12)) | AC20: =-('입력값'!C55*100*(3/12)) | AD20: =-('입력값'!C55*100*(3/12)) | AE20: =-('입력값'!C55*100*(3/12)) | AF20: =-('입력값'!C55*100*(3/12)) | AG20: =-('입력값'!C55*100*(3/12)) | AH20: =-('입력값'!C55*100*(3/12)) | AI20: =-('입력값'!C55*100*(3/12)) | AJ20: =-('입력값'!C55*100*(3/12)) | AK20: =-('입력값'!C55*100*(3/12)) | AL20: =-('입력값'!C55*100*(3/12)) | AM20: =-('입력값'!C55*100*(3/12)) | AN20: =-('입력값'!C55*100*(3/12)) | AO20: =-('입력값'!C55*100*(3/12)) | AP20: =-('입력값'!C55*100*(3/12)) | AQ20: =-('입력값'!C55*100*(3/12)) | AR20: =-('입력값'!C55*100*(3/12)) | AS20: =-('입력값'!C55*100*(3/12)) | AT20: =-('입력값'!C55*100*(3/12)) | AU20: =-('입력값'!C55*100*(3/12)) | AV20: =-('입력값'!C55*100*(3/12)) | AW20: =-('입력값'!C55*100*(3/12)) | AX20: =-('입력값'!C55*100*(3/12)) | AY20: =-('입력값'!C55*100*(3/12)) | AZ20: =-('입력값'!C55*100*(3/12)) | BA20: =-('입력값'!C55*100*(3/12)) | BB20: =-('입력값'!C55*100*(3/12)) | BC20: =-('입력값'!C55*100*(3/12)) | BD20: =-('입력값'!C55*100*(3/12)) | BE20: =-('입력값'!C55*100*(3/12)) | BF20: =-('입력값'!C55*100*(3/12)) | BG20: =-('입력값'!C55*100*(3/12)) | BH20: =-('입력값'!C55*100*(3/12)) | BI20: =-('입력값'!C55*100*(3/12)) | BJ20: =-('입력값'!C55*100*(3/12)) | BK20: =-('입력값'!C55*100*(3/12)) | BL20: =-('입력값'!C55*100*(3/12)) | BM20: =-('입력값'!C55*100*(3/12)) | BN20: =-('입력값'!C55*100*(3/12)) | BO20: =-('입력값'!C55*100*(3/12)) | BP20: =-('입력값'!C55*100*(3/12)) | BQ20: =-('입력값'!C55*100*(3/12)) | BR20: =-('입력값'!C55*100*(3/12)) | BS20: =-('입력값'!C55*100*(3/12)) | BT20: =-('입력값'!C55*100*(3/12)) | BU20: =-('입력값'!C55*100*(3/12)) | BV20: =-('입력값'!C55*100*(3/12)) | BW20: =-('입력값'!C55*100*(3/12)) | BX20: =-('입력값'!C55*100*(3/12)) | BY20: =-('입력값'!C55*100*(3/12)) | BZ20: =-('입력값'!C55*100*(3/12)) | CA20: =-('입력값'!C55*100*(3/12)) | CB20: =-('입력값'!C55*100*(3/12)) | CC20: =-('입력값'!C55*100*(3/12)) | CD20: =-('입력값'!C55*100*(3/12)) | CE20: =-('입력값'!C55*100*(3/12)) | CF20: =-('입력값'!C55*100*(3/12)) | CG20: =-('입력값'!C55*100*(3/12)) | CH20: =-('입력값'!C55*100*(3/12)) | CI20: =-('입력값'!C55*100*(3/12)) | CJ20: =-('입력값'!C55*100*(3/12)) | CK20: =-('입력값'!C55*100*(3/12)) | CL20: =-('입력값'!C55*100*(3/12))
B22: 선순위운영비 | C22: [KRWm] | D22: 28498.934 | E22: 0 | F22: 0 | G22: 0 | H22: 0 | I22: 0 | J22: 0 | K22: =-K9+-K10+-K11+-K12+-K13+-K14+-K15+-K16+-K17+-K18+-K19+-K20 | L22: =-L9+-L10+-L11+-L12+-L13+-L14+-L15+-L16+-L17+-L18+-L19+-L20 | M22: =-M9+-M10+-M11+-M12+-M13+-M14+-M15+-M16+-M17+-M18+-M19+-M20 | N22: =-N9+-N10+-N11+-N12+-N13+-N14+-N15+-N16+-N17+-N18+-N19+-N20 | O22: =-O9+-O10+-O11+-O12+-O13+-O14+-O15+-O16+-O17+-O18+-O19+-O20 | P22: =-P9+-P10+-P11+-P12+-P13+-P14+-P15+-P16+-P17+-P18+-P19+-P20 | Q22: =-Q9+-Q10+-Q11+-Q12+-Q13+-Q14+-Q15+-Q16+-Q17+-Q18+-Q19+-Q20 | R22: =-R9+-R10+-R11+-R12+-R13+-R14+-R15+-R16+-R17+-R18+-R19+-R20 | ... CL22: =-CL9+-CL10+-CL11+-CL12+-CL13+-CL14+-CL15+-CL16+-CL17+-CL18+-CL19+-CL20
B23: 후순위운영비 | C23: [KRWm] | D23: 0 | E23: 0 | F23: 0 | G23: 0 | H23: 0 | I23: 0 | J23: 0 | K23: 0 | L23: 0 | M23: 0 | N23: 0 | O23: 0 | P23: 0 | Q23: 0 | R23: 0 | S23: 0 | T23: 0 | U23: 0 | V23: 0 | W23: 0 | X23: 0 | Y23: 0 | Z23: 0 | AA23: 0 | AB23: 0 | AC23: 0 | AD23: 0 | AE23: 0 | AF23: 0 | AG23: 0 | AH23: 0 | AI23: 0 | AJ23: 0 | AK23: 0 | AL23: 0 | AM23: 0 | AN23: 0 | AO23: 0 | AP23: 0 | AQ23: 0 | AR23: 0 | AS23: 0 | AT23: 0 | AU23: 0 | AV23: 0 | AW23: 0 | AX23: 0 | AY23: 0 | AZ23: 0 | BA23: 0 | BB23: 0 | BC23: 0 | BD23: 0 | BE23: 0 | BF23: 0 | BG23: 0 | BH23: 0 | BI23: 0 | BJ23: 0 | BK23: 0 | BL23: 0 | BM23: 0 | BN23: 0 | BO23: 0 | BP23: 0 | BQ23: 0 | BR23: 0 | BS23: 0 | BT23: 0 | BU23: 0 | BV23: 0 | BW23: 0 | BX23: 0 | BY23: 0 | BZ23: 0 | CA23: 0 | CB23: 0 | CC23: 0 | CD23: 0 | CE23: 0 | CF23: 0 | CG23: 0 | CH23: 0 | CI23: 0 | CJ23: 0 | CK23: 0 | CL23: 0
B24: 영업비용 합계 | C24: [KRWm] | D24: 28498.934 | E24: 0 | F24: 0 | G24: 0 | H24: 0 | I24: 0 | J24: 0 | K24: =K22+K23 | L24: =L22+L23 | M24: =M22+M23 | N24: =N22+N23 | O24: =O22+O23 | P24: =P22+P23 | Q24: =Q22+Q23 | R24: =R22+R23 | ... CL24: =CL22+CL23
B26: ※ 실측 오버라이드가 적용된 분기(있다면)는 항목별 실제값이 아니라 공식 기준 비중을 실제 합계에 비례 배분한 근사치(baked)이고, 그 외 분기는 "입력값" 시트를 참조하는 수식입니다.

Sheet IS(Q)
A1: 태양광 발전사업
A2: 추정 손익계산서 (분기)
B4: 손익계산서
B6: 구 분 | C6: unit | D6: 합 계 | E6: 2024-06-30 | F6: 2024-09-30 | G6: 2024-12-31 | H6: 2025-03-31 | I6: 2025-06-30 | J6: 2025-09-30 | K6: 2025-12-31 | L6: 2026-03-31 | M6: 2026-06-30 | N6: 2026-09-30 | O6: 2026-12-31 | P6: 2027-03-31 | Q6: 2027-06-30 | R6: 2027-09-30 | S6: 2027-12-31 | T6: 2028-03-31 | U6: 2028-06-30 | V6: 2028-09-30 | W6: 2028-12-31 | X6: 2029-03-31 | Y6: 2029-06-30 | Z6: 2029-09-30 | AA6: 2029-12-31 | AB6: 2030-03-31 | AC6: 2030-06-30 | AD6: 2030-09-30 | AE6: 2030-12-31 | AF6: 2031-03-31 | AG6: 2031-06-30 | AH6: 2031-09-30 | AI6: 2031-12-31 | AJ6: 2032-03-31 | AK6: 2032-06-30 | AL6: 2032-09-30 | AM6: 2032-12-31 | AN6: 2033-03-31 | AO6: 2033-06-30 | AP6: 2033-09-30 | AQ6: 2033-12-31 | AR6: 2034-03-31 | AS6: 2034-06-30 | AT6: 2034-09-30 | AU6: 2034-12-31 | AV6: 2035-03-31 | AW6: 2035-06-30 | AX6: 2035-09-30 | AY6: 2035-12-31 | AZ6: 2036-03-31 | BA6: 2036-06-30 | BB6: 2036-09-30 | BC6: 2036-12-31 | BD6: 2037-03-31 | BE6: 2037-06-30 | BF6: 2037-09-30 | BG6: 2037-12-31 | BH6: 2038-03-31 | BI6: 2038-06-30 | BJ6: 2038-09-30 | BK6: 2038-12-31 | BL6: 2039-03-31 | BM6: 2039-06-30 | BN6: 2039-09-30 | BO6: 2039-12-31 | BP6: 2040-03-31 | BQ6: 2040-06-30 | BR6: 2040-09-30 | BS6: 2040-12-31 | BT6: 2041-03-31 | BU6: 2041-06-30 | BV6: 2041-09-30 | BW6: 2041-12-31 | BX6: 2042-03-31 | BY6: 2042-06-30 | BZ6: 2042-09-30 | CA6: 2042-12-31 | CB6: 2043-03-31 | CC6: 2043-06-30 | CD6: 2043-09-30 | CE6: 2043-12-31 | CF6: 2044-03-31 | CG6: 2044-06-30 | CH6: 2044-09-30 | CI6: 2044-12-31 | CJ6: 2045-03-31 | CK6: 2045-06-30 | CL6: 2045-09-30
B8: 영업수익 | C8: [KRWm] | D8: 405780.77 | E8: 0 | F8: 0 | G8: 0 | H8: 0 | I8: 0 | J8: 0 | K8: 5325.207 | L8: 5325.207 | M8: 5325.207 | N8: 5325.207 | O8: 5298.581 | P8: 5298.581 | Q8: 5298.581 | R8: 5298.581 | S8: 5271.9549 | T8: 5271.9549 | U8: 5271.9549 | V8: 5271.9549 | W8: 5245.3289 | X8: 5245.3289 | Y8: 5245.3289 | Z8: 5245.3289 | AA8: 5218.7029 | AB8: 5218.7029 | AC8: 5218.7029 | AD8: 5218.7029 | AE8: 5192.0768 | AF8: 5192.0768 | AG8: 5192.0768 | AH8: 5192.0768 | AI8: 5165.4508 | AJ8: 5165.4508 | AK8: 5165.4508 | AL8: 5165.4508 | AM8: 5138.8247 | AN8: 5138.8247 | AO8: 5138.8247 | AP8: 5138.8247 | AQ8: 5112.1987 | AR8: 5112.1987 | AS8: 5112.1987 | AT8: 5112.1987 | AU8: 5085.5727 | AV8: 5085.5727 | AW8: 5085.5727 | AX8: 5085.5727 | AY8: 5058.9466 | AZ8: 5058.9466 | BA8: 5058.9466 | BB8: 5058.9466 | BC8: 5032.3206 | BD8: 5032.3206 | BE8: 5032.3206 | BF8: 5032.3206 | BG8: 5005.6946 | BH8: 5005.6946 | BI8: 5005.6946 | BJ8: 5005.6946 | BK8: 4979.0685 | BL8: 4979.0685 | BM8: 4979.0685 | BN8: 4979.0685 | BO8: 4952.4425 | BP8: 4952.4425 | BQ8: 4952.4425 | BR8: 4952.4425 | BS8: 4925.8165 | BT8: 4925.8165 | BU8: 4925.8165 | BV8: 4925.8165 | BW8: 4899.1904 | BX8: 4899.1904 | BY8: 4899.1904 | BZ8: 4899.1904 | CA8: 4872.5644 | CB8: 4872.5644 | CC8: 4872.5644 | CD8: 4872.5644 | CE8: 4845.9384 | CF8: 4845.9384 | CG8: 4845.9384 | CH8: 4845.9384 | CI8: 4819.3123 | CJ8: 4819.3123 | CK8: 4819.3123 | CL8: 4819.3123
B10: 영업비용 세부내역
B11: 부지임대료 | C11: [KRWm] | D11: -10000 | E11: 0 | F11: 0 | G11: 0 | H11: 0 | I11: 0 | J11: 0 | K11: =-('입력값'!C44*100*(3/12)) | L11: =-('입력값'!C44*100*(3/12)) | M11: =-('입력값'!C44*100*(3/12)) | N11: =-('입력값'!C44*100*(3/12)) | O11: =-('입력값'!C44*100*(3/12)) | P11: =-('입력값'!C44*100*(3/12)) | Q11: =-('입력값'!C44*100*(3/12)) | R11: =-('입력값'!C44*100*(3/12)) | S11: =-('입력값'!C44*100*(3/12)) | T11: =-('입력값'!C44*100*(3/12)) | U11: =-('입력값'!C44*100*(3/12)) | V11: =-('입력값'!C44*100*(3/12)) | W11: =-('입력값'!C44*100*(3/12)) | X11: =-('입력값'!C44*100*(3/12)) | Y11: =-('입력값'!C44*100*(3/12)) | Z11: =-('입력값'!C44*100*(3/12)) | AA11: =-('입력값'!C44*100*(3/12)) | AB11: =-('입력값'!C44*100*(3/12)) | AC11: =-('입력값'!C44*100*(3/12)) | AD11: =-('입력값'!C44*100*(3/12)) | AE11: =-('입력값'!C44*100*(3/12)) | AF11: =-('입력값'!C44*100*(3/12)) | AG11: =-('입력값'!C44*100*(3/12)) | AH11: =-('입력값'!C44*100*(3/12)) | AI11: =-('입력값'!C44*100*(3/12)) | AJ11: =-('입력값'!C44*100*(3/12)) | AK11: =-('입력값'!C44*100*(3/12)) | AL11: =-('입력값'!C44*100*(3/12)) | AM11: =-('입력값'!C44*100*(3/12)) | AN11: =-('입력값'!C44*100*(3/12)) | AO11: =-('입력값'!C44*100*(3/12)) | AP11: =-('입력값'!C44*100*(3/12)) | AQ11: =-('입력값'!C44*100*(3/12)) | AR11: =-('입력값'!C44*100*(3/12)) | AS11: =-('입력값'!C44*100*(3/12)) | AT11: =-('입력값'!C44*100*(3/12)) | AU11: =-('입력값'!C44*100*(3/12)) | AV11: =-('입력값'!C44*100*(3/12)) | AW11: =-('입력값'!C44*100*(3/12)) | AX11: =-('입력값'!C44*100*(3/12)) | AY11: =-('입력값'!C44*100*(3/12)) | AZ11: =-('입력값'!C44*100*(3/12)) | BA11: =-('입력값'!C44*100*(3/12)) | BB11: =-('입력값'!C44*100*(3/12)) | BC11: =-('입력값'!C44*100*(3/12)) | BD11: =-('입력값'!C44*100*(3/12)) | BE11: =-('입력값'!C44*100*(3/12)) | BF11: =-('입력값'!C44*100*(3/12)) | BG11: =-('입력값'!C44*100*(3/12)) | BH11: =-('입력값'!C44*100*(3/12)) | BI11: =-('입력값'!C44*100*(3/12)) | BJ11: =-('입력값'!C44*100*(3/12)) | BK11: =-('입력값'!C44*100*(3/12)) | BL11: =-('입력값'!C44*100*(3/12)) | BM11: =-('입력값'!C44*100*(3/12)) | BN11: =-('입력값'!C44*100*(3/12)) | BO11: =-('입력값'!C44*100*(3/12)) | BP11: =-('입력값'!C44*100*(3/12)) | BQ11: =-('입력값'!C44*100*(3/12)) | BR11: =-('입력값'!C44*100*(3/12)) | BS11: =-('입력값'!C44*100*(3/12)) | BT11: =-('입력값'!C44*100*(3/12)) | BU11: =-('입력값'!C44*100*(3/12)) | BV11: =-('입력값'!C44*100*(3/12)) | BW11: =-('입력값'!C44*100*(3/12)) | BX11: =-('입력값'!C44*100*(3/12)) | BY11: =-('입력값'!C44*100*(3/12)) | BZ11: =-('입력값'!C44*100*(3/12)) | CA11: =-('입력값'!C44*100*(3/12)) | CB11: =-('입력값'!C44*100*(3/12)) | CC11: =-('입력값'!C44*100*(3/12)) | CD11: =-('입력값'!C44*100*(3/12)) | CE11: =-('입력값'!C44*100*(3/12)) | CF11: =-('입력값'!C44*100*(3/12)) | CG11: =-('입력값'!C44*100*(3/12)) | CH11: =-('입력값'!C44*100*(3/12)) | CI11: =-('입력값'!C44*100*(3/12)) | CJ11: =-('입력값'!C44*100*(3/12)) | CK11: =-('입력값'!C44*100*(3/12)) | CL11: =-('입력값'!C44*100*(3/12))
B12: O&M | C12: [KRWm] | D12: -18498.934 | E12: 0 | F12: 0 | G12: 0 | H12: 0 | I12: 0 | J12: 0 | K12: =-('입력값'!C45*100*(3/12)*(1+'입력값'!D45/100)^0) | L12: =-('입력값'!C45*100*(3/12)*(1+'입력값'!D45/100)^0) | M12: =-('입력값'!C45*100*(3/12)*(1+'입력값'!D45/100)^0) | N12: =-('입력값'!C45*100*(3/12)*(1+'입력값'!D45/100)^0) | O12: =-('입력값'!C45*100*(3/12)*(1+'입력값'!D45/100)^1) | P12: =-('입력값'!C45*100*(3/12)*(1+'입력값'!D45/100)^1) | Q12: =-('입력값'!C45*100*(3/12)*(1+'입력값'!D45/100)^1) | R12: =-('입력값'!C45*100*(3/12)*(1+'입력값'!D45/100)^1) | S12: =-('입력값'!C45*100*(3/12)*(1+'입력값'!D45/100)^2) | T12: =-('입력값'!C45*100*(3/12)*(1+'입력값'!D45/100)^2) | U12: =-('입력값'!C45*100*(3/12)*(1+'입력값'!D45/100)^2) | V12: =-('입력값'!C45*100*(3/12)*(1+'입력값'!D45/100)^2) | W12: =-('입력값'!C45*100*(3/12)*(1+'입력값'!D45/100)^3) | X12: =-('입력값'!C45*100*(3/12)*(1+'입력값'!D45/100)^3) | Y12: =-('입력값'!C45*100*(3/12)*(1+'입력값'!D45/100)^3) | Z12: =-('입력값'!C45*100*(3/12)*(1+'입력값'!D45/100)^3) | AA12: =-('입력값'!C45*100*(3/12)*(1+'입력값'!D45/100)^4) | AB12: =-('입력값'!C45*100*(3/12)*(1+'입력값'!D45/100)^4) | AC12: =-('입력값'!C45*100*(3/12)*(1+'입력값'!D45/100)^4) | AD12: =-('입력값'!C45*100*(3/12)*(1+'입력값'!D45/100)^4) | AE12: =-('입력값'!C45*100*(3/12)*(1+'입력값'!D45/100)^5) | AF12: =-('입력값'!C45*100*(3/12)*(1+'입력값'!D45/100)^5) | AG12: =-('입력값'!C45*100*(3/12)*(1+'입력값'!D45/100)^5) | AH12: =-('입력값'!C45*100*(3/12)*(1+'입력값'!D45/100)^5) | AI12: =-('입력값'!C45*100*(3/12)*(1+'입력값'!D45/100)^6) | AJ12: =-('입력값'!C45*100*(3/12)*(1+'입력값'!D45/100)^6) | AK12: =-('입력값'!C45*100*(3/12)*(1+'입력값'!D45/100)^6) | AL12: =-('입력값'!C45*100*(3/12)*(1+'입력값'!D45/100)^6) | AM12: =-('입력값'!C45*100*(3/12)*(1+'입력값'!D45/100)^7) | AN12: =-('입력값'!C45*100*(3/12)*(1+'입력값'!D45/100)^7) | AO12: =-('입력값'!C45*100*(3/12)*(1+'입력값'!D45/100)^7) | AP12: =-('입력값'!C45*100*(3/12)*(1+'입력값'!D45/100)^7) | AQ12: =-('입력값'!C45*100*(3/12)*(1+'입력값'!D45/100)^8) | AR12: =-('입력값'!C45*100*(3/12)*(1+'입력값'!D45/100)^8) | AS12: =-('입력값'!C45*100*(3/12)*(1+'입력값'!D45/100)^8) | AT12: =-('입력값'!C45*100*(3/12)*(1+'입력값'!D45/100)^8) | AU12: =-('입력값'!C45*100*(3/12)*(1+'입력값'!D45/100)^9) | AV12: =-('입력값'!C45*100*(3/12)*(1+'입력값'!D45/100)^9) | AW12: =-('입력값'!C45*100*(3/12)*(1+'입력값'!D45/100)^9) | AX12: =-('입력값'!C45*100*(3/12)*(1+'입력값'!D45/100)^9) | AY12: =-('입력값'!C45*100*(3/12)*(1+'입력값'!D45/100)^10) | AZ12: =-('입력값'!C45*100*(3/12)*(1+'입력값'!D45/100)^10) | BA12: =-('입력값'!C45*100*(3/12)*(1+'입력값'!D45/100)^10) | BB12: =-('입력값'!C45*100*(3/12)*(1+'입력값'!D45/100)^10) | BC12: =-('입력값'!C45*100*(3/12)*(1+'입력값'!D45/100)^11) | BD12: =-('입력값'!C45*100*(3/12)*(1+'입력값'!D45/100)^11) | BE12: =-('입력값'!C45*100*(3/12)*(1+'입력값'!D45/100)^11) | BF12: =-('입력값'!C45*100*(3/12)*(1+'입력값'!D45/100)^11) | BG12: =-('입력값'!C45*100*(3/12)*(1+'입력값'!D45/100)^12) | BH12: =-('입력값'!C45*100*(3/12)*(1+'입력값'!D45/100)^12) | BI12: =-('입력값'!C45*100*(3/12)*(1+'입력값'!D45/100)^12) | BJ12: =-('입력값'!C45*100*(3/12)*(1+'입력값'!D45/100)^12) | BK12: =-('입력값'!C45*100*(3/12)*(1+'입력값'!D45/100)^13) | BL12: =-('입력값'!C45*100*(3/12)*(1+'입력값'!D45/100)^13) | BM12: =-('입력값'!C45*100*(3/12)*(1+'입력값'!D45/100)^13) | BN12: =-('입력값'!C45*100*(3/12)*(1+'입력값'!D45/100)^13) | BO12: =-('입력값'!C45*100*(3/12)*(1+'입력값'!D45/100)^14) | BP12: =-('입력값'!C45*100*(3/12)*(1+'입력값'!D45/100)^14) | BQ12: =-('입력값'!C45*100*(3/12)*(1+'입력값'!D45/100)^14) | BR12: =-('입력값'!C45*100*(3/12)*(1+'입력값'!D45/100)^14) | BS12: =-('입력값'!C45*100*(3/12)*(1+'입력값'!D45/100)^15) | BT12: =-('입력값'!C45*100*(3/12)*(1+'입력값'!D45/100)^15) | BU12: =-('입력값'!C45*100*(3/12)*(1+'입력값'!D45/100)^15) | BV12: =-('입력값'!C45*100*(3/12)*(1+'입력값'!D45/100)^15) | BW12: =-('입력값'!C45*100*(3/12)*(1+'입력값'!D45/100)^16) | BX12: =-('입력값'!C45*100*(3/12)*(1+'입력값'!D45/100)^16) | BY12: =-('입력값'!C45*100*(3/12)*(1+'입력값'!D45/100)^16) | BZ12: =-('입력값'!C45*100*(3/12)*(1+'입력값'!D45/100)^16) | CA12: =-('입력값'!C45*100*(3/12)*(1+'입력값'!D45/100)^17) | CB12: =-('입력값'!C45*100*(3/12)*(1+'입력값'!D45/100)^17) | CC12: =-('입력값'!C45*100*(3/12)*(1+'입력값'!D45/100)^17) | CD12: =-('입력값'!C45*100*(3/12)*(1+'입력값'!D45/100)^17) | CE12: =-('입력값'!C45*100*(3/12)*(1+'입력값'!D45/100)^18) | CF12: =-('입력값'!C45*100*(3/12)*(1+'입력값'!D45/100)^18) | CG12: =-('입력값'!C45*100*(3/12)*(1+'입력값'!D45/100)^18) | CH12: =-('입력값'!C45*100*(3/12)*(1+'입력값'!D45/100)^18) | CI12: =-('입력값'!C45*100*(3/12)*(1+'입력값'!D45/100)^19) | CJ12: =-('입력값'!C45*100*(3/12)*(1+'입력값'!D45/100)^19) | CK12: =-('입력값'!C45*100*(3/12)*(1+'입력값'!D45/100)^19) | CL12: =-('입력값'!C45*100*(3/12)*(1+'입력값'!D45/100)^19)
B13: 보험료 | C13: [KRWm] | D13: 0 | E13: 0 | F13: 0 | G13: 0 | H13: 0 | I13: 0 | J13: 0 | K13: =-('입력값'!C46*100*(3/12)) | L13: =-('입력값'!C46*100*(3/12)) | M13: =-('입력값'!C46*100*(3/12)) | N13: =-('입력값'!C46*100*(3/12)) | O13: =-('입력값'!C46*100*(3/12)) | P13: =-('입력값'!C46*100*(3/12)) | Q13: =-('입력값'!C46*100*(3/12)) | R13: =-('입력값'!C46*100*(3/12)) | S13: =-('입력값'!C46*100*(3/12)) | T13: =-('입력값'!C46*100*(3/12)) | U13: =-('입력값'!C46*100*(3/12)) | V13: =-('입력값'!C46*100*(3/12)) | W13: =-('입력값'!C46*100*(3/12)) | X13: =-('입력값'!C46*100*(3/12)) | Y13: =-('입력값'!C46*100*(3/12)) | Z13: =-('입력값'!C46*100*(3/12)) | AA13: =-('입력값'!C46*100*(3/12)) | AB13: =-('입력값'!C46*100*(3/12)) | AC13: =-('입력값'!C46*100*(3/12)) | AD13: =-('입력값'!C46*100*(3/12)) | AE13: =-('입력값'!C46*100*(3/12)) | AF13: =-('입력값'!C46*100*(3/12)) | AG13: =-('입력값'!C46*100*(3/12)) | AH13: =-('입력값'!C46*100*(3/12)) | AI13: =-('입력값'!C46*100*(3/12)) | AJ13: =-('입력값'!C46*100*(3/12)) | AK13: =-('입력값'!C46*100*(3/12)) | AL13: =-('입력값'!C46*100*(3/12)) | AM13: =-('입력값'!C46*100*(3/12)) | AN13: =-('입력값'!C46*100*(3/12)) | AO13: =-('입력값'!C46*100*(3/12)) | AP13: =-('입력값'!C46*100*(3/12)) | AQ13: =-('입력값'!C46*100*(3/12)) | AR13: =-('입력값'!C46*100*(3/12)) | AS13: =-('입력값'!C46*100*(3/12)) | AT13: =-('입력값'!C46*100*(3/12)) | AU13: =-('입력값'!C46*100*(3/12)) | AV13: =-('입력값'!C46*100*(3/12)) | AW13: =-('입력값'!C46*100*(3/12)) | AX13: =-('입력값'!C46*100*(3/12)) | AY13: =-('입력값'!C46*100*(3/12)) | AZ13: =-('입력값'!C46*100*(3/12)) | BA13: =-('입력값'!C46*100*(3/12)) | BB13: =-('입력값'!C46*100*(3/12)) | BC13: =-('입력값'!C46*100*(3/12)) | BD13: =-('입력값'!C46*100*(3/12)) | BE13: =-('입력값'!C46*100*(3/12)) | BF13: =-('입력값'!C46*100*(3/12)) | BG13: =-('입력값'!C46*100*(3/12)) | BH13: =-('입력값'!C46*100*(3/12)) | BI13: =-('입력값'!C46*100*(3/12)) | BJ13: =-('입력값'!C46*100*(3/12)) | BK13: =-('입력값'!C46*100*(3/12)) | BL13: =-('입력값'!C46*100*(3/12)) | BM13: =-('입력값'!C46*100*(3/12)) | BN13: =-('입력값'!C46*100*(3/12)) | BO13: =-('입력값'!C46*100*(3/12)) | BP13: =-('입력값'!C46*100*(3/12)) | BQ13: =-('입력값'!C46*100*(3/12)) | BR13: =-('입력값'!C46*100*(3/12)) | BS13: =-('입력값'!C46*100*(3/12)) | BT13: =-('입력값'!C46*100*(3/12)) | BU13: =-('입력값'!C46*100*(3/12)) | BV13: =-('입력값'!C46*100*(3/12)) | BW13: =-('입력값'!C46*100*(3/12)) | BX13: =-('입력값'!C46*100*(3/12)) | BY13: =-('입력값'!C46*100*(3/12)) | BZ13: =-('입력값'!C46*100*(3/12)) | CA13: =-('입력값'!C46*100*(3/12)) | CB13: =-('입력값'!C46*100*(3/12)) | CC13: =-('입력값'!C46*100*(3/12)) | CD13: =-('입력값'!C46*100*(3/12)) | CE13: =-('입력값'!C46*100*(3/12)) | CF13: =-('입력값'!C46*100*(3/12)) | CG13: =-('입력값'!C46*100*(3/12)) | CH13: =-('입력값'!C46*100*(3/12)) | CI13: =-('입력값'!C46*100*(3/12)) | CJ13: =-('입력값'!C46*100*(3/12)) | CK13: =-('입력값'!C46*100*(3/12)) | CL13: =-('입력값'!C46*100*(3/12))
B14: 환경모니터링비용 | C14: [KRWm] | D14: 0 | E14: 0 | F14: 0 | G14: 0 | H14: 0 | I14: 0 | J14: 0 | K14: =-('입력값'!C47*100*(3/12)) | L14: =-('입력값'!C47*100*(3/12)) | M14: =-('입력값'!C47*100*(3/12)) | N14: =-('입력값'!C47*100*(3/12)) | O14: =-('입력값'!C47*100*(3/12)) | P14: =-('입력값'!C47*100*(3/12)) | Q14: =-('입력값'!C47*100*(3/12)) | R14: =-('입력값'!C47*100*(3/12)) | S14: =-('입력값'!C47*100*(3/12)) | T14: =-('입력값'!C47*100*(3/12)) | U14: =-('입력값'!C47*100*(3/12)) | V14: =-('입력값'!C47*100*(3/12)) | W14: =-('입력값'!C47*100*(3/12)) | X14: =-('입력값'!C47*100*(3/12)) | Y14: =-('입력값'!C47*100*(3/12)) | Z14: =-('입력값'!C47*100*(3/12)) | AA14: =-('입력값'!C47*100*(3/12)) | AB14: =-('입력값'!C47*100*(3/12)) | AC14: =-('입력값'!C47*100*(3/12)) | AD14: =-('입력값'!C47*100*(3/12)) | AE14: =-('입력값'!C47*100*(3/12)) | AF14: =-('입력값'!C47*100*(3/12)) | AG14: =-('입력값'!C47*100*(3/12)) | AH14: =-('입력값'!C47*100*(3/12)) | AI14: =-('입력값'!C47*100*(3/12)) | AJ14: =-('입력값'!C47*100*(3/12)) | AK14: =-('입력값'!C47*100*(3/12)) | AL14: =-('입력값'!C47*100*(3/12)) | AM14: =-('입력값'!C47*100*(3/12)) | AN14: =-('입력값'!C47*100*(3/12)) | AO14: =-('입력값'!C47*100*(3/12)) | AP14: =-('입력값'!C47*100*(3/12)) | AQ14: =-('입력값'!C47*100*(3/12)) | AR14: =-('입력값'!C47*100*(3/12)) | AS14: =-('입력값'!C47*100*(3/12)) | AT14: =-('입력값'!C47*100*(3/12)) | AU14: =-('입력값'!C47*100*(3/12)) | AV14: =-('입력값'!C47*100*(3/12)) | AW14: =-('입력값'!C47*100*(3/12)) | AX14: =-('입력값'!C47*100*(3/12)) | AY14: =-('입력값'!C47*100*(3/12)) | AZ14: =-('입력값'!C47*100*(3/12)) | BA14: =-('입력값'!C47*100*(3/12)) | BB14: =-('입력값'!C47*100*(3/12)) | BC14: =-('입력값'!C47*100*(3/12)) | BD14: =-('입력값'!C47*100*(3/12)) | BE14: =-('입력값'!C47*100*(3/12)) | BF14: =-('입력값'!C47*100*(3/12)) | BG14: =-('입력값'!C47*100*(3/12)) | BH14: =-('입력값'!C47*100*(3/12)) | BI14: =-('입력값'!C47*100*(3/12)) | BJ14: =-('입력값'!C47*100*(3/12)) | BK14: =-('입력값'!C47*100*(3/12)) | BL14: =-('입력값'!C47*100*(3/12)) | BM14: =-('입력값'!C47*100*(3/12)) | BN14: =-('입력값'!C47*100*(3/12)) | BO14: =-('입력값'!C47*100*(3/12)) | BP14: =-('입력값'!C47*100*(3/12)) | BQ14: =-('입력값'!C47*100*(3/12)) | BR14: =-('입력값'!C47*100*(3/12)) | BS14: =-('입력값'!C47*100*(3/12)) | BT14: =-('입력값'!C47*100*(3/12)) | BU14: =-('입력값'!C47*100*(3/12)) | BV14: =-('입력값'!C47*100*(3/12)) | BW14: =-('입력값'!C47*100*(3/12)) | BX14: =-('입력값'!C47*100*(3/12)) | BY14: =-('입력값'!C47*100*(3/12)) | BZ14: =-('입력값'!C47*100*(3/12)) | CA14: =-('입력값'!C47*100*(3/12)) | CB14: =-('입력값'!C47*100*(3/12)) | CC14: =-('입력값'!C47*100*(3/12)) | CD14: =-('입력값'!C47*100*(3/12)) | CE14: =-('입력값'!C47*100*(3/12)) | CF14: =-('입력값'!C47*100*(3/12)) | CG14: =-('입력값'!C47*100*(3/12)) | CH14: =-('입력값'!C47*100*(3/12)) | CI14: =-('입력값'!C47*100*(3/12)) | CJ14: =-('입력값'!C47*100*(3/12)) | CK14: =-('입력값'!C47*100*(3/12)) | CL14: =-('입력값'!C47*100*(3/12))
B15: 소내전력비 | C15: [KRWm] | D15: 0 | E15: 0 | F15: 0 | G15: 0 | H15: 0 | I15: 0 | J15: 0 | K15: =-('입력값'!C48*100*(3/12)*(1+'입력값'!D48/100)^0) | L15: =-('입력값'!C48*100*(3/12)*(1+'입력값'!D48/100)^0) | M15: =-('입력값'!C48*100*(3/12)*(1+'입력값'!D48/100)^0) | N15: =-('입력값'!C48*100*(3/12)*(1+'입력값'!D48/100)^0) | O15: =-('입력값'!C48*100*(3/12)*(1+'입력값'!D48/100)^1) | P15: =-('입력값'!C48*100*(3/12)*(1+'입력값'!D48/100)^1) | Q15: =-('입력값'!C48*100*(3/12)*(1+'입력값'!D48/100)^1) | R15: =-('입력값'!C48*100*(3/12)*(1+'입력값'!D48/100)^1) | S15: =-('입력값'!C48*100*(3/12)*(1+'입력값'!D48/100)^2) | T15: =-('입력값'!C48*100*(3/12)*(1+'입력값'!D48/100)^2) | U15: =-('입력값'!C48*100*(3/12)*(1+'입력값'!D48/100)^2) | V15: =-('입력값'!C48*100*(3/12)*(1+'입력값'!D48/100)^2) | W15: =-('입력값'!C48*100*(3/12)*(1+'입력값'!D48/100)^3) | X15: =-('입력값'!C48*100*(3/12)*(1+'입력값'!D48/100)^3) | Y15: =-('입력값'!C48*100*(3/12)*(1+'입력값'!D48/100)^3) | Z15: =-('입력값'!C48*100*(3/12)*(1+'입력값'!D48/100)^3) | AA15: =-('입력값'!C48*100*(3/12)*(1+'입력값'!D48/100)^4) | AB15: =-('입력값'!C48*100*(3/12)*(1+'입력값'!D48/100)^4) | AC15: =-('입력값'!C48*100*(3/12)*(1+'입력값'!D48/100)^4) | AD15: =-('입력값'!C48*100*(3/12)*(1+'입력값'!D48/100)^4) | AE15: =-('입력값'!C48*100*(3/12)*(1+'입력값'!D48/100)^5) | AF15: =-('입력값'!C48*100*(3/12)*(1+'입력값'!D48/100)^5) | AG15: =-('입력값'!C48*100*(3/12)*(1+'입력값'!D48/100)^5) | AH15: =-('입력값'!C48*100*(3/12)*(1+'입력값'!D48/100)^5) | AI15: =-('입력값'!C48*100*(3/12)*(1+'입력값'!D48/100)^6) | AJ15: =-('입력값'!C48*100*(3/12)*(1+'입력값'!D48/100)^6) | AK15: =-('입력값'!C48*100*(3/12)*(1+'입력값'!D48/100)^6) | AL15: =-('입력값'!C48*100*(3/12)*(1+'입력값'!D48/100)^6) | AM15: =-('입력값'!C48*100*(3/12)*(1+'입력값'!D48/100)^7) | AN15: =-('입력값'!C48*100*(3/12)*(1+'입력값'!D48/100)^7) | AO15: =-('입력값'!C48*100*(3/12)*(1+'입력값'!D48/100)^7) | AP15: =-('입력값'!C48*100*(3/12)*(1+'입력값'!D48/100)^7) | AQ15: =-('입력값'!C48*100*(3/12)*(1+'입력값'!D48/100)^8) | AR15: =-('입력값'!C48*100*(3/12)*(1+'입력값'!D48/100)^8) | AS15: =-('입력값'!C48*100*(3/12)*(1+'입력값'!D48/100)^8) | AT15: =-('입력값'!C48*100*(3/12)*(1+'입력값'!D48/100)^8) | AU15: =-('입력값'!C48*100*(3/12)*(1+'입력값'!D48/100)^9) | AV15: =-('입력값'!C48*100*(3/12)*(1+'입력값'!D48/100)^9) | AW15: =-('입력값'!C48*100*(3/12)*(1+'입력값'!D48/100)^9) | AX15: =-('입력값'!C48*100*(3/12)*(1+'입력값'!D48/100)^9) | AY15: =-('입력값'!C48*100*(3/12)*(1+'입력값'!D48/100)^10) | AZ15: =-('입력값'!C48*100*(3/12)*(1+'입력값'!D48/100)^10) | BA15: =-('입력값'!C48*100*(3/12)*(1+'입력값'!D48/100)^10) | BB15: =-('입력값'!C48*100*(3/12)*(1+'입력값'!D48/100)^10) | BC15: =-('입력값'!C48*100*(3/12)*(1+'입력값'!D48/100)^11) | BD15: =-('입력값'!C48*100*(3/12)*(1+'입력값'!D48/100)^11) | BE15: =-('입력값'!C48*100*(3/12)*(1+'입력값'!D48/100)^11) | BF15: =-('입력값'!C48*100*(3/12)*(1+'입력값'!D48/100)^11) | BG15: =-('입력값'!C48*100*(3/12)*(1+'입력값'!D48/100)^12) | BH15: =-('입력값'!C48*100*(3/12)*(1+'입력값'!D48/100)^12) | BI15: =-('입력값'!C48*100*(3/12)*(1+'입력값'!D48/100)^12) | BJ15: =-('입력값'!C48*100*(3/12)*(1+'입력값'!D48/100)^12) | BK15: =-('입력값'!C48*100*(3/12)*(1+'입력값'!D48/100)^13) | BL15: =-('입력값'!C48*100*(3/12)*(1+'입력값'!D48/100)^13) | BM15: =-('입력값'!C48*100*(3/12)*(1+'입력값'!D48/100)^13) | BN15: =-('입력값'!C48*100*(3/12)*(1+'입력값'!D48/100)^13) | BO15: =-('입력값'!C48*100*(3/12)*(1+'입력값'!D48/100)^14) | BP15: =-('입력값'!C48*100*(3/12)*(1+'입력값'!D48/100)^14) | BQ15: =-('입력값'!C48*100*(3/12)*(1+'입력값'!D48/100)^14) | BR15: =-('입력값'!C48*100*(3/12)*(1+'입력값'!D48/100)^14) | BS15: =-('입력값'!C48*100*(3/12)*(1+'입력값'!D48/100)^15) | BT15: =-('입력값'!C48*100*(3/12)*(1+'입력값'!D48/100)^15) | BU15: =-('입력값'!C48*100*(3/12)*(1+'입력값'!D48/100)^15) | BV15: =-('입력값'!C48*100*(3/12)*(1+'입력값'!D48/100)^15) | BW15: =-('입력값'!C48*100*(3/12)*(1+'입력값'!D48/100)^16) | BX15: =-('입력값'!C48*100*(3/12)*(1+'입력값'!D48/100)^16) | BY15: =-('입력값'!C48*100*(3/12)*(1+'입력값'!D48/100)^16) | BZ15: =-('입력값'!C48*100*(3/12)*(1+'입력값'!D48/100)^16) | CA15: =-('입력값'!C48*100*(3/12)*(1+'입력값'!D48/100)^17) | CB15: =-('입력값'!C48*100*(3/12)*(1+'입력값'!D48/100)^17) | CC15: =-('입력값'!C48*100*(3/12)*(1+'입력값'!D48/100)^17) | CD15: =-('입력값'!C48*100*(3/12)*(1+'입력값'!D48/100)^17) | CE15: =-('입력값'!C48*100*(3/12)*(1+'입력값'!D48/100)^18) | CF15: =-('입력값'!C48*100*(3/12)*(1+'입력값'!D48/100)^18) | CG15: =-('입력값'!C48*100*(3/12)*(1+'입력값'!D48/100)^18) | CH15: =-('입력값'!C48*100*(3/12)*(1+'입력값'!D48/100)^18) | CI15: =-('입력값'!C48*100*(3/12)*(1+'입력값'!D48/100)^19) | CJ15: =-('입력값'!C48*100*(3/12)*(1+'입력값'!D48/100)^19) | CK15: =-('입력값'!C48*100*(3/12)*(1+'입력값'!D48/100)^19) | CL15: =-('입력값'!C48*100*(3/12)*(1+'입력값'!D48/100)^19)
B16: 인건비 | C16: [KRWm] | D16: 0 | E16: 0 | F16: 0 | G16: 0 | H16: 0 | I16: 0 | J16: 0 | K16: =-('입력값'!C49*100*(3/12)*(1+'입력값'!D49/100)^0) | L16: =-('입력값'!C49*100*(3/12)*(1+'입력값'!D49/100)^0) | M16: =-('입력값'!C49*100*(3/12)*(1+'입력값'!D49/100)^0) | N16: =-('입력값'!C49*100*(3/12)*(1+'입력값'!D49/100)^0) | O16: =-('입력값'!C49*100*(3/12)*(1+'입력값'!D49/100)^1) | P16: =-('입력값'!C49*100*(3/12)*(1+'입력값'!D49/100)^1) | Q16: =-('입력값'!C49*100*(3/12)*(1+'입력값'!D49/100)^1) | R16: =-('입력값'!C49*100*(3/12)*(1+'입력값'!D49/100)^1) | S16: =-('입력값'!C49*100*(3/12)*(1+'입력값'!D49/100)^2) | T16: =-('입력값'!C49*100*(3/12)*(1+'입력값'!D49/100)^2) | U16: =-('입력값'!C49*100*(3/12)*(1+'입력값'!D49/100)^2) | V16: =-('입력값'!C49*100*(3/12)*(1+'입력값'!D49/100)^2) | W16: =-('입력값'!C49*100*(3/12)*(1+'입력값'!D49/100)^3) | X16: =-('입력값'!C49*100*(3/12)*(1+'입력값'!D49/100)^3) | Y16: =-('입력값'!C49*100*(3/12)*(1+'입력값'!D49/100)^3) | Z16: =-('입력값'!C49*100*(3/12)*(1+'입력값'!D49/100)^3) | AA16: =-('입력값'!C49*100*(3/12)*(1+'입력값'!D49/100)^4) | AB16: =-('입력값'!C49*100*(3/12)*(1+'입력값'!D49/100)^4) | AC16: =-('입력값'!C49*100*(3/12)*(1+'입력값'!D49/100)^4) | AD16: =-('입력값'!C49*100*(3/12)*(1+'입력값'!D49/100)^4) | AE16: =-('입력값'!C49*100*(3/12)*(1+'입력값'!D49/100)^5) | AF16: =-('입력값'!C49*100*(3/12)*(1+'입력값'!D49/100)^5) | AG16: =-('입력값'!C49*100*(3/12)*(1+'입력값'!D49/100)^5) | AH16: =-('입력값'!C49*100*(3/12)*(1+'입력값'!D49/100)^5) | AI16: =-('입력값'!C49*100*(3/12)*(1+'입력값'!D49/100)^6) | AJ16: =-('입력값'!C49*100*(3/12)*(1+'입력값'!D49/100)^6) | AK16: =-('입력값'!C49*100*(3/12)*(1+'입력값'!D49/100)^6) | AL16: =-('입력값'!C49*100*(3/12)*(1+'입력값'!D49/100)^6) | AM16: =-('입력값'!C49*100*(3/12)*(1+'입력값'!D49/100)^7) | AN16: =-('입력값'!C49*100*(3/12)*(1+'입력값'!D49/100)^7) | AO16: =-('입력값'!C49*100*(3/12)*(1+'입력값'!D49/100)^7) | AP16: =-('입력값'!C49*100*(3/12)*(1+'입력값'!D49/100)^7) | AQ16: =-('입력값'!C49*100*(3/12)*(1+'입력값'!D49/100)^8) | AR16: =-('입력값'!C49*100*(3/12)*(1+'입력값'!D49/100)^8) | AS16: =-('입력값'!C49*100*(3/12)*(1+'입력값'!D49/100)^8) | AT16: =-('입력값'!C49*100*(3/12)*(1+'입력값'!D49/100)^8) | AU16: =-('입력값'!C49*100*(3/12)*(1+'입력값'!D49/100)^9) | AV16: =-('입력값'!C49*100*(3/12)*(1+'입력값'!D49/100)^9) | AW16: =-('입력값'!C49*100*(3/12)*(1+'입력값'!D49/100)^9) | AX16: =-('입력값'!C49*100*(3/12)*(1+'입력값'!D49/100)^9) | AY16: =-('입력값'!C49*100*(3/12)*(1+'입력값'!D49/100)^10) | AZ16: =-('입력값'!C49*100*(3/12)*(1+'입력값'!D49/100)^10) | BA16: =-('입력값'!C49*100*(3/12)*(1+'입력값'!D49/100)^10) | BB16: =-('입력값'!C49*100*(3/12)*(1+'입력값'!D49/100)^10) | BC16: =-('입력값'!C49*100*(3/12)*(1+'입력값'!D49/100)^11) | BD16: =-('입력값'!C49*100*(3/12)*(1+'입력값'!D49/100)^11) | BE16: =-('입력값'!C49*100*(3/12)*(1+'입력값'!D49/100)^11) | BF16: =-('입력값'!C49*100*(3/12)*(1+'입력값'!D49/100)^11) | BG16: =-('입력값'!C49*100*(3/12)*(1+'입력값'!D49/100)^12) | BH16: =-('입력값'!C49*100*(3/12)*(1+'입력값'!D49/100)^12) | BI16: =-('입력값'!C49*100*(3/12)*(1+'입력값'!D49/100)^12) | BJ16: =-('입력값'!C49*100*(3/12)*(1+'입력값'!D49/100)^12) | BK16: =-('입력값'!C49*100*(3/12)*(1+'입력값'!D49/100)^13) | BL16: =-('입력값'!C49*100*(3/12)*(1+'입력값'!D49/100)^13) | BM16: =-('입력값'!C49*100*(3/12)*(1+'입력값'!D49/100)^13) | BN16: =-('입력값'!C49*100*(3/12)*(1+'입력값'!D49/100)^13) | BO16: =-('입력값'!C49*100*(3/12)*(1+'입력값'!D49/100)^14) | BP16: =-('입력값'!C49*100*(3/12)*(1+'입력값'!D49/100)^14) | BQ16: =-('입력값'!C49*100*(3/12)*(1+'입력값'!D49/100)^14) | BR16: =-('입력값'!C49*100*(3/12)*(1+'입력값'!D49/100)^14) | BS16: =-('입력값'!C49*100*(3/12)*(1+'입력값'!D49/100)^15) | BT16: =-('입력값'!C49*100*(3/12)*(1+'입력값'!D49/100)^15) | BU16: =-('입력값'!C49*100*(3/12)*(1+'입력값'!D49/100)^15) | BV16: =-('입력값'!C49*100*(3/12)*(1+'입력값'!D49/100)^15) | BW16: =-('입력값'!C49*100*(3/12)*(1+'입력값'!D49/100)^16) | BX16: =-('입력값'!C49*100*(3/12)*(1+'입력값'!D49/100)^16) | BY16: =-('입력값'!C49*100*(3/12)*(1+'입력값'!D49/100)^16) | BZ16: =-('입력값'!C49*100*(3/12)*(1+'입력값'!D49/100)^16) | CA16: =-('입력값'!C49*100*(3/12)*(1+'입력값'!D49/100)^17) | CB16: =-('입력값'!C49*100*(3/12)*(1+'입력값'!D49/100)^17) | CC16: =-('입력값'!C49*100*(3/12)*(1+'입력값'!D49/100)^17) | CD16: =-('입력값'!C49*100*(3/12)*(1+'입력값'!D49/100)^17) | CE16: =-('입력값'!C49*100*(3/12)*(1+'입력값'!D49/100)^18) | CF16: =-('입력값'!C49*100*(3/12)*(1+'입력값'!D49/100)^18) | CG16: =-('입력값'!C49*100*(3/12)*(1+'입력값'!D49/100)^18) | CH16: =-('입력값'!C49*100*(3/12)*(1+'입력값'!D49/100)^18) | CI16: =-('입력값'!C49*100*(3/12)*(1+'입력값'!D49/100)^19) | CJ16: =-('입력값'!C49*100*(3/12)*(1+'입력값'!D49/100)^19) | CK16: =-('입력값'!C49*100*(3/12)*(1+'입력값'!D49/100)^19) | CL16: =-('입력값'!C49*100*(3/12)*(1+'입력값'!D49/100)^19)
B17: 법인운영비 | C17: [KRWm] | D17: 0 | E17: 0 | F17: 0 | G17: 0 | H17: 0 | I17: 0 | J17: 0 | K17: =-('입력값'!C50*100*(3/12)*(1+'입력값'!D50/100)^0) | L17: =-('입력값'!C50*100*(3/12)*(1+'입력값'!D50/100)^0) | M17: =-('입력값'!C50*100*(3/12)*(1+'입력값'!D50/100)^0) | N17: =-('입력값'!C50*100*(3/12)*(1+'입력값'!D50/100)^0) | O17: =-('입력값'!C50*100*(3/12)*(1+'입력값'!D50/100)^1) | P17: =-('입력값'!C50*100*(3/12)*(1+'입력값'!D50/100)^1) | Q17: =-('입력값'!C50*100*(3/12)*(1+'입력값'!D50/100)^1) | R17: =-('입력값'!C50*100*(3/12)*(1+'입력값'!D50/100)^1) | S17: =-('입력값'!C50*100*(3/12)*(1+'입력값'!D50/100)^2) | T17: =-('입력값'!C50*100*(3/12)*(1+'입력값'!D50/100)^2) | U17: =-('입력값'!C50*100*(3/12)*(1+'입력값'!D50/100)^2) | V17: =-('입력값'!C50*100*(3/12)*(1+'입력값'!D50/100)^2) | W17: =-('입력값'!C50*100*(3/12)*(1+'입력값'!D50/100)^3) | X17: =-('입력값'!C50*100*(3/12)*(1+'입력값'!D50/100)^3) | Y17: =-('입력값'!C50*100*(3/12)*(1+'입력값'!D50/100)^3) | Z17: =-('입력값'!C50*100*(3/12)*(1+'입력값'!D50/100)^3) | AA17: =-('입력값'!C50*100*(3/12)*(1+'입력값'!D50/100)^4) | AB17: =-('입력값'!C50*100*(3/12)*(1+'입력값'!D50/100)^4) | AC17: =-('입력값'!C50*100*(3/12)*(1+'입력값'!D50/100)^4) | AD17: =-('입력값'!C50*100*(3/12)*(1+'입력값'!D50/100)^4) | AE17: =-('입력값'!C50*100*(3/12)*(1+'입력값'!D50/100)^5) | AF17: =-('입력값'!C50*100*(3/12)*(1+'입력값'!D50/100)^5) | AG17: =-('입력값'!C50*100*(3/12)*(1+'입력값'!D50/100)^5) | AH17: =-('입력값'!C50*100*(3/12)*(1+'입력값'!D50/100)^5) | AI17: =-('입력값'!C50*100*(3/12)*(1+'입력값'!D50/100)^6) | AJ17: =-('입력값'!C50*100*(3/12)*(1+'입력값'!D50/100)^6) | AK17: =-('입력값'!C50*100*(3/12)*(1+'입력값'!D50/100)^6) | AL17: =-('입력값'!C50*100*(3/12)*(1+'입력값'!D50/100)^6) | AM17: =-('입력값'!C50*100*(3/12)*(1+'입력값'!D50/100)^7) | AN17: =-('입력값'!C50*100*(3/12)*(1+'입력값'!D50/100)^7) | AO17: =-('입력값'!C50*100*(3/12)*(1+'입력값'!D50/100)^7) | AP17: =-('입력값'!C50*100*(3/12)*(1+'입력값'!D50/100)^7) | AQ17: =-('입력값'!C50*100*(3/12)*(1+'입력값'!D50/100)^8) | AR17: =-('입력값'!C50*100*(3/12)*(1+'입력값'!D50/100)^8) | AS17: =-('입력값'!C50*100*(3/12)*(1+'입력값'!D50/100)^8) | AT17: =-('입력값'!C50*100*(3/12)*(1+'입력값'!D50/100)^8) | AU17: =-('입력값'!C50*100*(3/12)*(1+'입력값'!D50/100)^9) | AV17: =-('입력값'!C50*100*(3/12)*(1+'입력값'!D50/100)^9) | AW17: =-('입력값'!C50*100*(3/12)*(1+'입력값'!D50/100)^9) | AX17: =-('입력값'!C50*100*(3/12)*(1+'입력값'!D50/100)^9) | AY17: =-('입력값'!C50*100*(3/12)*(1+'입력값'!D50/100)^10) | AZ17: =-('입력값'!C50*100*(3/12)*(1+'입력값'!D50/100)^10) | BA17: =-('입력값'!C50*100*(3/12)*(1+'입력값'!D50/100)^10) | BB17: =-('입력값'!C50*100*(3/12)*(1+'입력값'!D50/100)^10) | BC17: =-('입력값'!C50*100*(3/12)*(1+'입력값'!D50/100)^11) | BD17: =-('입력값'!C50*100*(3/12)*(1+'입력값'!D50/100)^11) | BE17: =-('입력값'!C50*100*(3/12)*(1+'입력값'!D50/100)^11) | BF17: =-('입력값'!C50*100*(3/12)*(1+'입력값'!D50/100)^11) | BG17: =-('입력값'!C50*100*(3/12)*(1+'입력값'!D50/100)^12) | BH17: =-('입력값'!C50*100*(3/12)*(1+'입력값'!D50/100)^12) | BI17: =-('입력값'!C50*100*(3/12)*(1+'입력값'!D50/100)^12) | BJ17: =-('입력값'!C50*100*(3/12)*(1+'입력값'!D50/100)^12) | BK17: =-('입력값'!C50*100*(3/12)*(1+'입력값'!D50/100)^13) | BL17: =-('입력값'!C50*100*(3/12)*(1+'입력값'!D50/100)^13) | BM17: =-('입력값'!C50*100*(3/12)*(1+'입력값'!D50/100)^13) | BN17: =-('입력값'!C50*100*(3/12)*(1+'입력값'!D50/100)^13) | BO17: =-('입력값'!C50*100*(3/12)*(1+'입력값'!D50/100)^14) | BP17: =-('입력값'!C50*100*(3/12)*(1+'입력값'!D50/100)^14) | BQ17: =-('입력값'!C50*100*(3/12)*(1+'입력값'!D50/100)^14) | BR17: =-('입력값'!C50*100*(3/12)*(1+'입력값'!D50/100)^14) | BS17: =-('입력값'!C50*100*(3/12)*(1+'입력값'!D50/100)^15) | BT17: =-('입력값'!C50*100*(3/12)*(1+'입력값'!D50/100)^15) | BU17: =-('입력값'!C50*100*(3/12)*(1+'입력값'!D50/100)^15) | BV17: =-('입력값'!C50*100*(3/12)*(1+'입력값'!D50/100)^15) | BW17: =-('입력값'!C50*100*(3/12)*(1+'입력값'!D50/100)^16) | BX17: =-('입력값'!C50*100*(3/12)*(1+'입력값'!D50/100)^16) | BY17: =-('입력값'!C50*100*(3/12)*(1+'입력값'!D50/100)^16) | BZ17: =-('입력값'!C50*100*(3/12)*(1+'입력값'!D50/100)^16) | CA17: =-('입력값'!C50*100*(3/12)*(1+'입력값'!D50/100)^17) | CB17: =-('입력값'!C50*100*(3/12)*(1+'입력값'!D50/100)^17) | CC17: =-('입력값'!C50*100*(3/12)*(1+'입력값'!D50/100)^17) | CD17: =-('입력값'!C50*100*(3/12)*(1+'입력값'!D50/100)^17) | CE17: =-('입력값'!C50*100*(3/12)*(1+'입력값'!D50/100)^18) | CF17: =-('입력값'!C50*100*(3/12)*(1+'입력값'!D50/100)^18) | CG17: =-('입력값'!C50*100*(3/12)*(1+'입력값'!D50/100)^18) | CH17: =-('입력값'!C50*100*(3/12)*(1+'입력값'!D50/100)^18) | CI17: =-('입력값'!C50*100*(3/12)*(1+'입력값'!D50/100)^19) | CJ17: =-('입력값'!C50*100*(3/12)*(1+'입력값'!D50/100)^19) | CK17: =-('입력값'!C50*100*(3/12)*(1+'입력값'!D50/100)^19) | CL17: =-('입력값'!C50*100*(3/12)*(1+'입력값'!D50/100)^19)
B18: 주민보상비 | C18: [KRWm] | D18: 0 | E18: 0 | F18: 0 | G18: 0 | H18: 0 | I18: 0 | J18: 0 | K18: =-('입력값'!C51*100*(3/12)) | L18: =-('입력값'!C51*100*(3/12)) | M18: =-('입력값'!C51*100*(3/12)) | N18: =-('입력값'!C51*100*(3/12)) | O18: =-('입력값'!C51*100*(3/12)) | P18: =-('입력값'!C51*100*(3/12)) | Q18: =-('입력값'!C51*100*(3/12)) | R18: =-('입력값'!C51*100*(3/12)) | S18: =-('입력값'!C51*100*(3/12)) | T18: =-('입력값'!C51*100*(3/12)) | U18: =-('입력값'!C51*100*(3/12)) | V18: =-('입력값'!C51*100*(3/12)) | W18: =-('입력값'!C51*100*(3/12)) | X18: =-('입력값'!C51*100*(3/12)) | Y18: =-('입력값'!C51*100*(3/12)) | Z18: =-('입력값'!C51*100*(3/12)) | AA18: =-('입력값'!C51*100*(3/12)) | AB18: =-('입력값'!C51*100*(3/12)) | AC18: =-('입력값'!C51*100*(3/12)) | AD18: =-('입력값'!C51*100*(3/12)) | AE18: =-('입력값'!C51*100*(3/12)) | AF18: =-('입력값'!C51*100*(3/12)) | AG18: =-('입력값'!C51*100*(3/12)) | AH18: =-('입력값'!C51*100*(3/12)) | AI18: =-('입력값'!C51*100*(3/12)) | AJ18: =-('입력값'!C51*100*(3/12)) | AK18: =-('입력값'!C51*100*(3/12)) | AL18: =-('입력값'!C51*100*(3/12)) | AM18: =-('입력값'!C51*100*(3/12)) | AN18: =-('입력값'!C51*100*(3/12)) | AO18: =-('입력값'!C51*100*(3/12)) | AP18: =-('입력값'!C51*100*(3/12)) | AQ18: =-('입력값'!C51*100*(3/12)) | AR18: =-('입력값'!C51*100*(3/12)) | AS18: =-('입력값'!C51*100*(3/12)) | AT18: =-('입력값'!C51*100*(3/12)) | AU18: =-('입력값'!C51*100*(3/12)) | AV18: =-('입력값'!C51*100*(3/12)) | AW18: =-('입력값'!C51*100*(3/12)) | AX18: =-('입력값'!C51*100*(3/12)) | AY18: =-('입력값'!C51*100*(3/12)) | AZ18: =-('입력값'!C51*100*(3/12)) | BA18: =-('입력값'!C51*100*(3/12)) | BB18: =-('입력값'!C51*100*(3/12)) | BC18: =-('입력값'!C51*100*(3/12)) | BD18: =-('입력값'!C51*100*(3/12)) | BE18: =-('입력값'!C51*100*(3/12)) | BF18: =-('입력값'!C51*100*(3/12)) | BG18: =-('입력값'!C51*100*(3/12)) | BH18: =-('입력값'!C51*100*(3/12)) | BI18: =-('입력값'!C51*100*(3/12)) | BJ18: =-('입력값'!C51*100*(3/12)) | BK18: =-('입력값'!C51*100*(3/12)) | BL18: =-('입력값'!C51*100*(3/12)) | BM18: =-('입력값'!C51*100*(3/12)) | BN18: =-('입력값'!C51*100*(3/12)) | BO18: =-('입력값'!C51*100*(3/12)) | BP18: =-('입력값'!C51*100*(3/12)) | BQ18: =-('입력값'!C51*100*(3/12)) | BR18: =-('입력값'!C51*100*(3/12)) | BS18: =-('입력값'!C51*100*(3/12)) | BT18: =-('입력값'!C51*100*(3/12)) | BU18: =-('입력값'!C51*100*(3/12)) | BV18: =-('입력값'!C51*100*(3/12)) | BW18: =-('입력값'!C51*100*(3/12)) | BX18: =-('입력값'!C51*100*(3/12)) | BY18: =-('입력값'!C51*100*(3/12)) | BZ18: =-('입력값'!C51*100*(3/12)) | CA18: =-('입력값'!C51*100*(3/12)) | CB18: =-('입력값'!C51*100*(3/12)) | CC18: =-('입력값'!C51*100*(3/12)) | CD18: =-('입력값'!C51*100*(3/12)) | CE18: =-('입력값'!C51*100*(3/12)) | CF18: =-('입력값'!C51*100*(3/12)) | CG18: =-('입력값'!C51*100*(3/12)) | CH18: =-('입력값'!C51*100*(3/12)) | CI18: =-('입력값'!C51*100*(3/12)) | CJ18: =-('입력값'!C51*100*(3/12)) | CK18: =-('입력값'!C51*100*(3/12)) | CL18: =-('입력값'!C51*100*(3/12))
B19: 도로점용료 | C19: [KRWm] | D19: 0 | E19: 0 | F19: 0 | G19: 0 | H19: 0 | I19: 0 | J19: 0 | K19: =-('입력값'!C52*100*(3/12)) | L19: =-('입력값'!C52*100*(3/12)) | M19: =-('입력값'!C52*100*(3/12)) | N19: =-('입력값'!C52*100*(3/12)) | O19: =-('입력값'!C52*100*(3/12)) | P19: =-('입력값'!C52*100*(3/12)) | Q19: =-('입력값'!C52*100*(3/12)) | R19: =-('입력값'!C52*100*(3/12)) | S19: =-('입력값'!C52*100*(3/12)) | T19: =-('입력값'!C52*100*(3/12)) | U19: =-('입력값'!C52*100*(3/12)) | V19: =-('입력값'!C52*100*(3/12)) | W19: =-('입력값'!C52*100*(3/12)) | X19: =-('입력값'!C52*100*(3/12)) | Y19: =-('입력값'!C52*100*(3/12)) | Z19: =-('입력값'!C52*100*(3/12)) | AA19: =-('입력값'!C52*100*(3/12)) | AB19: =-('입력값'!C52*100*(3/12)) | AC19: =-('입력값'!C52*100*(3/12)) | AD19: =-('입력값'!C52*100*(3/12)) | AE19: =-('입력값'!C52*100*(3/12)) | AF19: =-('입력값'!C52*100*(3/12)) | AG19: =-('입력값'!C52*100*(3/12)) | AH19: =-('입력값'!C52*100*(3/12)) | AI19: =-('입력값'!C52*100*(3/12)) | AJ19: =-('입력값'!C52*100*(3/12)) | AK19: =-('입력값'!C52*100*(3/12)) | AL19: =-('입력값'!C52*100*(3/12)) | AM19: =-('입력값'!C52*100*(3/12)) | AN19: =-('입력값'!C52*100*(3/12)) | AO19: =-('입력값'!C52*100*(3/12)) | AP19: =-('입력값'!C52*100*(3/12)) | AQ19: =-('입력값'!C52*100*(3/12)) | AR19: =-('입력값'!C52*100*(3/12)) | AS19: =-('입력값'!C52*100*(3/12)) | AT19: =-('입력값'!C52*100*(3/12)) | AU19: =-('입력값'!C52*100*(3/12)) | AV19: =-('입력값'!C52*100*(3/12)) | AW19: =-('입력값'!C52*100*(3/12)) | AX19: =-('입력값'!C52*100*(3/12)) | AY19: =-('입력값'!C52*100*(3/12)) | AZ19: =-('입력값'!C52*100*(3/12)) | BA19: =-('입력값'!C52*100*(3/12)) | BB19: =-('입력값'!C52*100*(3/12)) | BC19: =-('입력값'!C52*100*(3/12)) | BD19: =-('입력값'!C52*100*(3/12)) | BE19: =-('입력값'!C52*100*(3/12)) | BF19: =-('입력값'!C52*100*(3/12)) | BG19: =-('입력값'!C52*100*(3/12)) | BH19: =-('입력값'!C52*100*(3/12)) | BI19: =-('입력값'!C52*100*(3/12)) | BJ19: =-('입력값'!C52*100*(3/12)) | BK19: =-('입력값'!C52*100*(3/12)) | BL19: =-('입력값'!C52*100*(3/12)) | BM19: =-('입력값'!C52*100*(3/12)) | BN19: =-('입력값'!C52*100*(3/12)) | BO19: =-('입력값'!C52*100*(3/12)) | BP19: =-('입력값'!C52*100*(3/12)) | BQ19: =-('입력값'!C52*100*(3/12)) | BR19: =-('입력값'!C52*100*(3/12)) | BS19: =-('입력값'!C52*100*(3/12)) | BT19: =-('입력값'!C52*100*(3/12)) | BU19: =-('입력값'!C52*100*(3/12)) | BV19: =-('입력값'!C52*100*(3/12)) | BW19: =-('입력값'!C52*100*(3/12)) | BX19: =-('입력값'!C52*100*(3/12)) | BY19: =-('입력값'!C52*100*(3/12)) | BZ19: =-('입력값'!C52*100*(3/12)) | CA19: =-('입력값'!C52*100*(3/12)) | CB19: =-('입력값'!C52*100*(3/12)) | CC19: =-('입력값'!C52*100*(3/12)) | CD19: =-('입력값'!C52*100*(3/12)) | CE19: =-('입력값'!C52*100*(3/12)) | CF19: =-('입력값'!C52*100*(3/12)) | CG19: =-('입력값'!C52*100*(3/12)) | CH19: =-('입력값'!C52*100*(3/12)) | CI19: =-('입력값'!C52*100*(3/12)) | CJ19: =-('입력값'!C52*100*(3/12)) | CK19: =-('입력값'!C52*100*(3/12)) | CL19: =-('입력값'!C52*100*(3/12))
B20: 예비비 | C20: [KRWm] | D20: 0 | E20: 0 | F20: 0 | G20: 0 | H20: 0 | I20: 0 | J20: 0 | K20: =-('입력값'!C53*100*(3/12)) | L20: =-('입력값'!C53*100*(3/12)) | M20: =-('입력값'!C53*100*(3/12)) | N20: =-('입력값'!C53*100*(3/12)) | O20: =-('입력값'!C53*100*(3/12)) | P20: =-('입력값'!C53*100*(3/12)) | Q20: =-('입력값'!C53*100*(3/12)) | R20: =-('입력값'!C53*100*(3/12)) | S20: =-('입력값'!C53*100*(3/12)) | T20: =-('입력값'!C53*100*(3/12)) | U20: =-('입력값'!C53*100*(3/12)) | V20: =-('입력값'!C53*100*(3/12)) | W20: =-('입력값'!C53*100*(3/12)) | X20: =-('입력값'!C53*100*(3/12)) | Y20: =-('입력값'!C53*100*(3/12)) | Z20: =-('입력값'!C53*100*(3/12)) | AA20: =-('입력값'!C53*100*(3/12)) | AB20: =-('입력값'!C53*100*(3/12)) | AC20: =-('입력값'!C53*100*(3/12)) | AD20: =-('입력값'!C53*100*(3/12)) | AE20: =-('입력값'!C53*100*(3/12)) | AF20: =-('입력값'!C53*100*(3/12)) | AG20: =-('입력값'!C53*100*(3/12)) | AH20: =-('입력값'!C53*100*(3/12)) | AI20: =-('입력값'!C53*100*(3/12)) | AJ20: =-('입력값'!C53*100*(3/12)) | AK20: =-('입력값'!C53*100*(3/12)) | AL20: =-('입력값'!C53*100*(3/12)) | AM20: =-('입력값'!C53*100*(3/12)) | AN20: =-('입력값'!C53*100*(3/12)) | AO20: =-('입력값'!C53*100*(3/12)) | AP20: =-('입력값'!C53*100*(3/12)) | AQ20: =-('입력값'!C53*100*(3/12)) | AR20: =-('입력값'!C53*100*(3/12)) | AS20: =-('입력값'!C53*100*(3/12)) | AT20: =-('입력값'!C53*100*(3/12)) | AU20: =-('입력값'!C53*100*(3/12)) | AV20: =-('입력값'!C53*100*(3/12)) | AW20: =-('입력값'!C53*100*(3/12)) | AX20: =-('입력값'!C53*100*(3/12)) | AY20: =-('입력값'!C53*100*(3/12)) | AZ20: =-('입력값'!C53*100*(3/12)) | BA20: =-('입력값'!C53*100*(3/12)) | BB20: =-('입력값'!C53*100*(3/12)) | BC20: =-('입력값'!C53*100*(3/12)) | BD20: =-('입력값'!C53*100*(3/12)) | BE20: =-('입력값'!C53*100*(3/12)) | BF20: =-('입력값'!C53*100*(3/12)) | BG20: =-('입력값'!C53*100*(3/12)) | BH20: =-('입력값'!C53*100*(3/12)) | BI20: =-('입력값'!C53*100*(3/12)) | BJ20: =-('입력값'!C53*100*(3/12)) | BK20: =-('입력값'!C53*100*(3/12)) | BL20: =-('입력값'!C53*100*(3/12)) | BM20: =-('입력값'!C53*100*(3/12)) | BN20: =-('입력값'!C53*100*(3/12)) | BO20: =-('입력값'!C53*100*(3/12)) | BP20: =-('입력값'!C53*100*(3/12)) | BQ20: =-('입력값'!C53*100*(3/12)) | BR20: =-('입력값'!C53*100*(3/12)) | BS20: =-('입력값'!C53*100*(3/12)) | BT20: =-('입력값'!C53*100*(3/12)) | BU20: =-('입력값'!C53*100*(3/12)) | BV20: =-('입력값'!C53*100*(3/12)) | BW20: =-('입력값'!C53*100*(3/12)) | BX20: =-('입력값'!C53*100*(3/12)) | BY20: =-('입력값'!C53*100*(3/12)) | BZ20: =-('입력값'!C53*100*(3/12)) | CA20: =-('입력값'!C53*100*(3/12)) | CB20: =-('입력값'!C53*100*(3/12)) | CC20: =-('입력값'!C53*100*(3/12)) | CD20: =-('입력값'!C53*100*(3/12)) | CE20: =-('입력값'!C53*100*(3/12)) | CF20: =-('입력값'!C53*100*(3/12)) | CG20: =-('입력값'!C53*100*(3/12)) | CH20: =-('입력값'!C53*100*(3/12)) | CI20: =-('입력값'!C53*100*(3/12)) | CJ20: =-('입력값'!C53*100*(3/12)) | CK20: =-('입력값'!C53*100*(3/12)) | CL20: =-('입력값'!C53*100*(3/12))
B21: 전력거래수수료 | C21: [KRWm] | D21: 0 | E21: 0 | F21: 0 | G21: 0 | H21: 0 | I21: 0 | J21: 0 | K21: =-('입력값'!C54*100*(3/12)) | L21: =-('입력값'!C54*100*(3/12)) | M21: =-('입력값'!C54*100*(3/12)) | N21: =-('입력값'!C54*100*(3/12)) | O21: =-('입력값'!C54*100*(3/12)) | P21: =-('입력값'!C54*100*(3/12)) | Q21: =-('입력값'!C54*100*(3/12)) | R21: =-('입력값'!C54*100*(3/12)) | S21: =-('입력값'!C54*100*(3/12)) | T21: =-('입력값'!C54*100*(3/12)) | U21: =-('입력값'!C54*100*(3/12)) | V21: =-('입력값'!C54*100*(3/12)) | W21: =-('입력값'!C54*100*(3/12)) | X21: =-('입력값'!C54*100*(3/12)) | Y21: =-('입력값'!C54*100*(3/12)) | Z21: =-('입력값'!C54*100*(3/12)) | AA21: =-('입력값'!C54*100*(3/12)) | AB21: =-('입력값'!C54*100*(3/12)) | AC21: =-('입력값'!C54*100*(3/12)) | AD21: =-('입력값'!C54*100*(3/12)) | AE21: =-('입력값'!C54*100*(3/12)) | AF21: =-('입력값'!C54*100*(3/12)) | AG21: =-('입력값'!C54*100*(3/12)) | AH21: =-('입력값'!C54*100*(3/12)) | AI21: =-('입력값'!C54*100*(3/12)) | AJ21: =-('입력값'!C54*100*(3/12)) | AK21: =-('입력값'!C54*100*(3/12)) | AL21: =-('입력값'!C54*100*(3/12)) | AM21: =-('입력값'!C54*100*(3/12)) | AN21: =-('입력값'!C54*100*(3/12)) | AO21: =-('입력값'!C54*100*(3/12)) | AP21: =-('입력값'!C54*100*(3/12)) | AQ21: =-('입력값'!C54*100*(3/12)) | AR21: =-('입력값'!C54*100*(3/12)) | AS21: =-('입력값'!C54*100*(3/12)) | AT21: =-('입력값'!C54*100*(3/12)) | AU21: =-('입력값'!C54*100*(3/12)) | AV21: =-('입력값'!C54*100*(3/12)) | AW21: =-('입력값'!C54*100*(3/12)) | AX21: =-('입력값'!C54*100*(3/12)) | AY21: =-('입력값'!C54*100*(3/12)) | AZ21: =-('입력값'!C54*100*(3/12)) | BA21: =-('입력값'!C54*100*(3/12)) | BB21: =-('입력값'!C54*100*(3/12)) | BC21: =-('입력값'!C54*100*(3/12)) | BD21: =-('입력값'!C54*100*(3/12)) | BE21: =-('입력값'!C54*100*(3/12)) | BF21: =-('입력값'!C54*100*(3/12)) | BG21: =-('입력값'!C54*100*(3/12)) | BH21: =-('입력값'!C54*100*(3/12)) | BI21: =-('입력값'!C54*100*(3/12)) | BJ21: =-('입력값'!C54*100*(3/12)) | BK21: =-('입력값'!C54*100*(3/12)) | BL21: =-('입력값'!C54*100*(3/12)) | BM21: =-('입력값'!C54*100*(3/12)) | BN21: =-('입력값'!C54*100*(3/12)) | BO21: =-('입력값'!C54*100*(3/12)) | BP21: =-('입력값'!C54*100*(3/12)) | BQ21: =-('입력값'!C54*100*(3/12)) | BR21: =-('입력값'!C54*100*(3/12)) | BS21: =-('입력값'!C54*100*(3/12)) | BT21: =-('입력값'!C54*100*(3/12)) | BU21: =-('입력값'!C54*100*(3/12)) | BV21: =-('입력값'!C54*100*(3/12)) | BW21: =-('입력값'!C54*100*(3/12)) | BX21: =-('입력값'!C54*100*(3/12)) | BY21: =-('입력값'!C54*100*(3/12)) | BZ21: =-('입력값'!C54*100*(3/12)) | CA21: =-('입력값'!C54*100*(3/12)) | CB21: =-('입력값'!C54*100*(3/12)) | CC21: =-('입력값'!C54*100*(3/12)) | CD21: =-('입력값'!C54*100*(3/12)) | CE21: =-('입력값'!C54*100*(3/12)) | CF21: =-('입력값'!C54*100*(3/12)) | CG21: =-('입력값'!C54*100*(3/12)) | CH21: =-('입력값'!C54*100*(3/12)) | CI21: =-('입력값'!C54*100*(3/12)) | CJ21: =-('입력값'!C54*100*(3/12)) | CK21: =-('입력값'!C54*100*(3/12)) | CL21: =-('입력값'!C54*100*(3/12))
B22: 관리운영비 성과보수 | C22: [KRWm] | D22: 0 | E22: 0 | F22: 0 | G22: 0 | H22: 0 | I22: 0 | J22: 0 | K22: =-('입력값'!C55*100*(3/12)) | L22: =-('입력값'!C55*100*(3/12)) | M22: =-('입력값'!C55*100*(3/12)) | N22: =-('입력값'!C55*100*(3/12)) | O22: =-('입력값'!C55*100*(3/12)) | P22: =-('입력값'!C55*100*(3/12)) | Q22: =-('입력값'!C55*100*(3/12)) | R22: =-('입력값'!C55*100*(3/12)) | S22: =-('입력값'!C55*100*(3/12)) | T22: =-('입력값'!C55*100*(3/12)) | U22: =-('입력값'!C55*100*(3/12)) | V22: =-('입력값'!C55*100*(3/12)) | W22: =-('입력값'!C55*100*(3/12)) | X22: =-('입력값'!C55*100*(3/12)) | Y22: =-('입력값'!C55*100*(3/12)) | Z22: =-('입력값'!C55*100*(3/12)) | AA22: =-('입력값'!C55*100*(3/12)) | AB22: =-('입력값'!C55*100*(3/12)) | AC22: =-('입력값'!C55*100*(3/12)) | AD22: =-('입력값'!C55*100*(3/12)) | AE22: =-('입력값'!C55*100*(3/12)) | AF22: =-('입력값'!C55*100*(3/12)) | AG22: =-('입력값'!C55*100*(3/12)) | AH22: =-('입력값'!C55*100*(3/12)) | AI22: =-('입력값'!C55*100*(3/12)) | AJ22: =-('입력값'!C55*100*(3/12)) | AK22: =-('입력값'!C55*100*(3/12)) | AL22: =-('입력값'!C55*100*(3/12)) | AM22: =-('입력값'!C55*100*(3/12)) | AN22: =-('입력값'!C55*100*(3/12)) | AO22: =-('입력값'!C55*100*(3/12)) | AP22: =-('입력값'!C55*100*(3/12)) | AQ22: =-('입력값'!C55*100*(3/12)) | AR22: =-('입력값'!C55*100*(3/12)) | AS22: =-('입력값'!C55*100*(3/12)) | AT22: =-('입력값'!C55*100*(3/12)) | AU22: =-('입력값'!C55*100*(3/12)) | AV22: =-('입력값'!C55*100*(3/12)) | AW22: =-('입력값'!C55*100*(3/12)) | AX22: =-('입력값'!C55*100*(3/12)) | AY22: =-('입력값'!C55*100*(3/12)) | AZ22: =-('입력값'!C55*100*(3/12)) | BA22: =-('입력값'!C55*100*(3/12)) | BB22: =-('입력값'!C55*100*(3/12)) | BC22: =-('입력값'!C55*100*(3/12)) | BD22: =-('입력값'!C55*100*(3/12)) | BE22: =-('입력값'!C55*100*(3/12)) | BF22: =-('입력값'!C55*100*(3/12)) | BG22: =-('입력값'!C55*100*(3/12)) | BH22: =-('입력값'!C55*100*(3/12)) | BI22: =-('입력값'!C55*100*(3/12)) | BJ22: =-('입력값'!C55*100*(3/12)) | BK22: =-('입력값'!C55*100*(3/12)) | BL22: =-('입력값'!C55*100*(3/12)) | BM22: =-('입력값'!C55*100*(3/12)) | BN22: =-('입력값'!C55*100*(3/12)) | BO22: =-('입력값'!C55*100*(3/12)) | BP22: =-('입력값'!C55*100*(3/12)) | BQ22: =-('입력값'!C55*100*(3/12)) | BR22: =-('입력값'!C55*100*(3/12)) | BS22: =-('입력값'!C55*100*(3/12)) | BT22: =-('입력값'!C55*100*(3/12)) | BU22: =-('입력값'!C55*100*(3/12)) | BV22: =-('입력값'!C55*100*(3/12)) | BW22: =-('입력값'!C55*100*(3/12)) | BX22: =-('입력값'!C55*100*(3/12)) | BY22: =-('입력값'!C55*100*(3/12)) | BZ22: =-('입력값'!C55*100*(3/12)) | CA22: =-('입력값'!C55*100*(3/12)) | CB22: =-('입력값'!C55*100*(3/12)) | CC22: =-('입력값'!C55*100*(3/12)) | CD22: =-('입력값'!C55*100*(3/12)) | CE22: =-('입력값'!C55*100*(3/12)) | CF22: =-('입력값'!C55*100*(3/12)) | CG22: =-('입력값'!C55*100*(3/12)) | CH22: =-('입력값'!C55*100*(3/12)) | CI22: =-('입력값'!C55*100*(3/12)) | CJ22: =-('입력값'!C55*100*(3/12)) | CK22: =-('입력값'!C55*100*(3/12)) | CL22: =-('입력값'!C55*100*(3/12))
B23: 영업비용 합계 | C23: [KRWm] | D23: -28498.934 | E23: 0 | F23: 0 | G23: 0 | H23: 0 | I23: 0 | J23: 0 | K23: -325 | L23: -325 | M23: -325 | N23: -325 | O23: -328 | P23: -328 | Q23: -328 | R23: -328 | S23: -331.045 | T23: -331.045 | U23: -331.045 | V23: -331.045 | W23: -334.13567 | X23: -334.13567 | Y23: -334.13567 | Z23: -334.13567 | AA23: -337.27271 | AB23: -337.27271 | AC23: -337.27271 | AD23: -337.27271 | AE23: -340.4568 | AF23: -340.4568 | AG23: -340.4568 | AH23: -340.4568 | AI23: -343.68865 | AJ23: -343.68865 | AK23: -343.68865 | AL23: -343.68865 | AM23: -346.96898 | AN23: -346.96898 | AO23: -346.96898 | AP23: -346.96898 | AQ23: -350.29852 | AR23: -350.29852 | AS23: -350.29852 | AT23: -350.29852 | AU23: -353.678 | AV23: -353.678 | AW23: -353.678 | AX23: -353.678 | AY23: -357.10817 | AZ23: -357.10817 | BA23: -357.10817 | BB23: -357.10817 | BC23: -360.58979 | BD23: -360.58979 | BE23: -360.58979 | BF23: -360.58979 | BG23: -364.12363 | BH23: -364.12363 | BI23: -364.12363 | BJ23: -364.12363 | BK23: -367.71049 | BL23: -367.71049 | BM23: -367.71049 | BN23: -367.71049 | BO23: -371.35115 | BP23: -371.35115 | BQ23: -371.35115 | BR23: -371.35115 | BS23: -375.04641 | BT23: -375.04641 | BU23: -375.04641 | BV23: -375.04641 | BW23: -378.79711 | BX23: -378.79711 | BY23: -378.79711 | BZ23: -378.79711 | CA23: -382.60407 | CB23: -382.60407 | CC23: -382.60407 | CD23: -382.60407 | CE23: -386.46813 | CF23: -386.46813 | CG23: -386.46813 | CH23: -386.46813 | CI23: -390.39015 | CJ23: -390.39015 | CK23: -390.39015 | CL23: -390.39015
B25: EBITDA | C25: [KRWm] | D25: 377281.84 | E25: 0 | F25: 0 | G25: 0 | H25: 0 | I25: 0 | J25: 0 | K25: 5000.207 | L25: 5000.207 | M25: 5000.207 | N25: 5000.207 | O25: 4970.581 | P25: 4970.581 | Q25: 4970.581 | R25: 4970.581 | S25: 4940.9099 | T25: 4940.9099 | U25: 4940.9099 | V25: 4940.9099 | W25: 4911.1932 | X25: 4911.1932 | Y25: 4911.1932 | Z25: 4911.1932 | AA25: 4881.4301 | AB25: 4881.4301 | AC25: 4881.4301 | AD25: 4881.4301 | AE25: 4851.62 | AF25: 4851.62 | AG25: 4851.62 | AH25: 4851.62 | AI25: 4821.7621 | AJ25: 4821.7621 | AK25: 4821.7621 | AL25: 4821.7621 | AM25: 4791.8558 | AN25: 4791.8558 | AO25: 4791.8558 | AP25: 4791.8558 | AQ25: 4761.9002 | AR25: 4761.9002 | AS25: 4761.9002 | AT25: 4761.9002 | AU25: 4731.8947 | AV25: 4731.8947 | AW25: 4731.8947 | AX25: 4731.8947 | AY25: 4701.8385 | AZ25: 4701.8385 | BA25: 4701.8385 | BB25: 4701.8385 | BC25: 4671.7308 | BD25: 4671.7308 | BE25: 4671.7308 | BF25: 4671.7308 | BG25: 4641.5709 | BH25: 4641.5709 | BI25: 4641.5709 | BJ25: 4641.5709 | BK25: 4611.3581 | BL25: 4611.3581 | BM25: 4611.3581 | BN25: 4611.3581 | BO25: 4581.0914 | BP25: 4581.0914 | BQ25: 4581.0914 | BR25: 4581.0914 | BS25: 4550.7701 | BT25: 4550.7701 | BU25: 4550.7701 | BV25: 4550.7701 | BW25: 4520.3933 | BX25: 4520.3933 | BY25: 4520.3933 | BZ25: 4520.3933 | CA25: 4489.9603 | CB25: 4489.9603 | CC25: 4489.9603 | CD25: 4489.9603 | CE25: 4459.4702 | CF25: 4459.4702 | CG25: 4459.4702 | CH25: 4459.4702 | CI25: 4428.9222 | CJ25: 4428.9222 | CK25: 4428.9222 | CL25: 4428.9222
B26: EBITDA 마진 | C26: [%] | K26: 0.93896951 | L26: 0.93896951 | M26: 0.93896951 | N26: 0.93896951 | O26: 0.93809663 | P26: 0.93809663 | Q26: 0.93809663 | R26: 0.93809663 | S26: 0.93720641 | T26: 0.93720641 | U26: 0.93720641 | V26: 0.93720641 | W26: 0.93629843 | X26: 0.93629843 | Y26: 0.93629843 | Z26: 0.93629843 | AA26: 0.93537231 | AB26: 0.93537231 | AC26: 0.93537231 | AD26: 0.93537231 | AE26: 0.93442763 | AF26: 0.93442763 | AG26: 0.93442763 | AH26: 0.93442763 | AI26: 0.93346396 | AJ26: 0.93346396 | AK26: 0.93346396 | AL26: 0.93346396 | AM26: 0.93248087 | AN26: 0.93248087 | AO26: 0.93248087 | AP26: 0.93248087 | AQ26: 0.93147791 | AR26: 0.93147791 | AS26: 0.93147791 | AT26: 0.93147791 | AU26: 0.93045464 | AV26: 0.93045464 | AW26: 0.93045464 | AX26: 0.93045464 | AY26: 0.92941057 | AZ26: 0.92941057 | BA26: 0.92941057 | BB26: 0.92941057 | BC26: 0.92834523 | BD26: 0.92834523 | BE26: 0.92834523 | BF26: 0.92834523 | BG26: 0.92725812 | BH26: 0.92725812 | BI26: 0.92725812 | BJ26: 0.92725812 | BK26: 0.92614874 | BL26: 0.92614874 | BM26: 0.92614874 | BN26: 0.92614874 | BO26: 0.92501657 | BP26: 0.92501657 | BQ26: 0.92501657 | BR26: 0.92501657 | BS26: 0.92386107 | BT26: 0.92386107 | BU26: 0.92386107 | BV26: 0.92386107 | BW26: 0.92268169 | BX26: 0.92268169 | BY26: 0.92268169 | BZ26: 0.92268169 | CA26: 0.92147788 | CB26: 0.92147788 | CC26: 0.92147788 | CD26: 0.92147788 | CE26: 0.92024906 | CF26: 0.92024906 | CG26: 0.92024906 | CH26: 0.92024906 | CI26: 0.91899464 | CJ26: 0.91899464 | CK26: 0.91899464 | CL26: 0.91899464
B28: 감가상각비 | C28: [KRWm] | D28: -138200.57 | E28: 0 | F28: 0 | G28: 0 | H28: 0 | I28: 0 | J28: 0 | K28: -1727.5071 | L28: -1727.5071 | M28: -1727.5071 | N28: -1727.5071 | O28: -1727.5071 | P28: -1727.5071 | Q28: -1727.5071 | R28: -1727.5071 | S28: -1727.5071 | T28: -1727.5071 | U28: -1727.5071 | V28: -1727.5071 | W28: -1727.5071 | X28: -1727.5071 | Y28: -1727.5071 | Z28: -1727.5071 | AA28: -1727.5071 | AB28: -1727.5071 | AC28: -1727.5071 | AD28: -1727.5071 | AE28: -1727.5071 | AF28: -1727.5071 | AG28: -1727.5071 | AH28: -1727.5071 | AI28: -1727.5071 | AJ28: -1727.5071 | AK28: -1727.5071 | AL28: -1727.5071 | AM28: -1727.5071 | AN28: -1727.5071 | AO28: -1727.5071 | AP28: -1727.5071 | AQ28: -1727.5071 | AR28: -1727.5071 | AS28: -1727.5071 | AT28: -1727.5071 | AU28: -1727.5071 | AV28: -1727.5071 | AW28: -1727.5071 | AX28: -1727.5071 | AY28: -1727.5071 | AZ28: -1727.5071 | BA28: -1727.5071 | BB28: -1727.5071 | BC28: -1727.5071 | BD28: -1727.5071 | BE28: -1727.5071 | BF28: -1727.5071 | BG28: -1727.5071 | BH28: -1727.5071 | BI28: -1727.5071 | BJ28: -1727.5071 | BK28: -1727.5071 | BL28: -1727.5071 | BM28: -1727.5071 | BN28: -1727.5071 | BO28: -1727.5071 | BP28: -1727.5071 | BQ28: -1727.5071 | BR28: -1727.5071 | BS28: -1727.5071 | BT28: -1727.5071 | BU28: -1727.5071 | BV28: -1727.5071 | BW28: -1727.5071 | BX28: -1727.5071 | BY28: -1727.5071 | BZ28: -1727.5071 | CA28: -1727.5071 | CB28: -1727.5071 | CC28: -1727.5071 | CD28: -1727.5071 | CE28: -1727.5071 | CF28: -1727.5071 | CG28: -1727.5071 | CH28: -1727.5071 | CI28: -1727.5071 | CJ28: -1727.5071 | CK28: -1727.5071 | CL28: -1727.5071
B29: 복구충당부채 전입액 | C29: [KRWm] | D29: -2000 | E29: 0 | F29: 0 | G29: 0 | H29: 0 | I29: 0 | J29: 0 | K29: -25 | L29: -25 | M29: -25 | N29: -25 | O29: -25 | P29: -25 | Q29: -25 | R29: -25 | S29: -25 | T29: -25 | U29: -25 | V29: -25 | W29: -25 | X29: -25 | Y29: -25 | Z29: -25 | AA29: -25 | AB29: -25 | AC29: -25 | AD29: -25 | AE29: -25 | AF29: -25 | AG29: -25 | AH29: -25 | AI29: -25 | AJ29: -25 | AK29: -25 | AL29: -25 | AM29: -25 | AN29: -25 | AO29: -25 | AP29: -25 | AQ29: -25 | AR29: -25 | AS29: -25 | AT29: -25 | AU29: -25 | AV29: -25 | AW29: -25 | AX29: -25 | AY29: -25 | AZ29: -25 | BA29: -25 | BB29: -25 | BC29: -25 | BD29: -25 | BE29: -25 | BF29: -25 | BG29: -25 | BH29: -25 | BI29: -25 | BJ29: -25 | BK29: -25 | BL29: -25 | BM29: -25 | BN29: -25 | BO29: -25 | BP29: -25 | BQ29: -25 | BR29: -25 | BS29: -25 | BT29: -25 | BU29: -25 | BV29: -25 | BW29: -25 | BX29: -25 | BY29: -25 | BZ29: -25 | CA29: -25 | CB29: -25 | CC29: -25 | CD29: -25 | CE29: -25 | CF29: -25 | CG29: -25 | CH29: -25 | CI29: -25 | CJ29: -25 | CK29: -25 | CL29: -25
B30: 영업이익(EBIT) | C30: [KRWm] | D30: 237081.27 | E30: 0 | F30: 0 | G30: 0 | H30: 0 | I30: 0 | J30: 0 | K30: 3247.6999 | L30: 3247.6999 | M30: 3247.6999 | N30: 3247.6999 | O30: 3218.0739 | P30: 3218.0739 | Q30: 3218.0739 | R30: 3218.0739 | S30: 3188.4028 | T30: 3188.4028 | U30: 3188.4028 | V30: 3188.4028 | W30: 3158.6861 | X30: 3158.6861 | Y30: 3158.6861 | Z30: 3158.6861 | AA30: 3128.9231 | AB30: 3128.9231 | AC30: 3128.9231 | AD30: 3128.9231 | AE30: 3099.1129 | AF30: 3099.1129 | AG30: 3099.1129 | AH30: 3099.1129 | AI30: 3069.255 | AJ30: 3069.255 | AK30: 3069.255 | AL30: 3069.255 | AM30: 3039.3487 | AN30: 3039.3487 | AO30: 3039.3487 | AP30: 3039.3487 | AQ30: 3009.3931 | AR30: 3009.3931 | AS30: 3009.3931 | AT30: 3009.3931 | AU30: 2979.3876 | AV30: 2979.3876 | AW30: 2979.3876 | AX30: 2979.3876 | AY30: 2949.3314 | AZ30: 2949.3314 | BA30: 2949.3314 | BB30: 2949.3314 | BC30: 2919.2237 | BD30: 2919.2237 | BE30: 2919.2237 | BF30: 2919.2237 | BG30: 2889.0639 | BH30: 2889.0639 | BI30: 2889.0639 | BJ30: 2889.0639 | BK30: 2858.851 | BL30: 2858.851 | BM30: 2858.851 | BN30: 2858.851 | BO30: 2828.5843 | BP30: 2828.5843 | BQ30: 2828.5843 | BR30: 2828.5843 | BS30: 2798.263 | BT30: 2798.263 | BU30: 2798.263 | BV30: 2798.263 | BW30: 2767.8862 | BX30: 2767.8862 | BY30: 2767.8862 | BZ30: 2767.8862 | CA30: 2737.4532 | CB30: 2737.4532 | CC30: 2737.4532 | CD30: 2737.4532 | CE30: 2706.9631 | CF30: 2706.9631 | CG30: 2706.9631 | CH30: 2706.9631 | CI30: 2676.4151 | CJ30: 2676.4151 | CK30: 2676.4151 | CL30: 2676.4151
B31: 영업이익률 | C31: [%] | K31: 0.60987299 | L31: 0.60987299 | M31: 0.60987299 | N31: 0.60987299 | O31: 0.60734636 | P31: 0.60734636 | Q31: 0.60734636 | R31: 0.60734636 | S31: 0.60478568 | T31: 0.60478568 | U31: 0.60478568 | V31: 0.60478568 | W31: 0.60219029 | X31: 0.60219029 | Y31: 0.60219029 | Z31: 0.60219029 | AA31: 0.59955953 | AB31: 0.59955953 | AC31: 0.59955953 | AD31: 0.59955953 | AE31: 0.59689273 | AF31: 0.59689273 | AG31: 0.59689273 | AH31: 0.59689273 | AI31: 0.59418919 | AJ31: 0.59418919 | AK31: 0.59418919 | AL31: 0.59418919 | AM31: 0.59144821 | AN31: 0.59144821 | AO31: 0.59144821 | AP31: 0.59144821 | AQ31: 0.58866904 | AR31: 0.58866904 | AS31: 0.58866904 | AT31: 0.58866904 | AU31: 0.58585095 | AV31: 0.58585095 | AW31: 0.58585095 | AX31: 0.58585095 | AY31: 0.58299318 | AZ31: 0.58299318 | BA31: 0.58299318 | BB31: 0.58299318 | BC31: 0.58009494 | BD31: 0.58009494 | BE31: 0.58009494 | BF31: 0.58009494 | BG31: 0.57715544 | BH31: 0.57715544 | BI31: 0.57715544 | BJ31: 0.57715544 | BK31: 0.57417385 | BL31: 0.57417385 | BM31: 0.57417385 | BN31: 0.57417385 | BO31: 0.57114934 | BP31: 0.57114934 | BQ31: 0.57114934 | BR31: 0.57114934 | BS31: 0.56808104 | BT31: 0.56808104 | BU31: 0.56808104 | BV31: 0.56808104 | BW31: 0.56496808 | BX31: 0.56496808 | BY31: 0.56496808 | BZ31: 0.56496808 | CA31: 0.56180956 | CB31: 0.56180956 | CC31: 0.56180956 | CD31: 0.56180956 | CE31: 0.55860454 | CF31: 0.55860454 | CG31: 0.55860454 | CH31: 0.55860454 | CI31: 0.55535207 | CJ31: 0.55535207 | CK31: 0.55535207 | CL31: 0.55535207
B33: 이자비용 세부내역
B34: 선순위A 이자 | C34: [KRWm] | D34: -58070.533 | E34: 0 | F34: 0 | G34: 0 | H34: 0 | I34: 0 | J34: 0 | K34: -1733.4488 | L34: -1733.4488 | M34: -1733.4488 | N34: -1733.4488 | O34: -1704.5579 | P34: -1675.6671 | Q34: -1646.7763 | R34: -1617.8855 | S34: -1588.9947 | T34: -1560.1039 | U34: -1531.2131 | V34: -1502.3223 | W34: -1473.4314 | X34: -1444.5406 | Y34: -1415.6498 | Z34: -1386.759 | AA34: -1357.8682 | AB34: -1328.9774 | AC34: -1300.0866 | AD34: -1271.1958 | AE34: -1242.3049 | AF34: -1213.4141 | AG34: -1184.5233 | AH34: -1155.6325 | AI34: -1126.7417 | AJ34: -1097.8509 | AK34: -1068.9601 | AL34: -1040.0693 | AM34: -1011.1784 | AN34: -982.28763 | AO34: -953.39681 | AP34: -924.506 | AQ34: -895.61519 | AR34: -866.72438 | AS34: -837.83356 | AT34: -808.94275 | AU34: -780.05194 | AV34: -751.16113 | AW34: -722.27031 | AX34: -693.3795 | AY34: -664.48869 | AZ34: -635.59788 | BA34: -606.70706 | BB34: -577.81625 | BC34: -548.92544 | BD34: -520.03463 | BE34: -491.14381 | BF34: -462.253 | BG34: -433.36219 | BH34: -404.47138 | BI34: -375.58056 | BJ34: -346.68975 | BK34: -317.79894 | BL34: -288.90813 | BM34: -260.01731 | BN34: -231.1265 | BO34: -202.23569 | BP34: -173.34488 | BQ34: -144.45406 | BR34: -115.56325 | BS34: -86.672438 | BT34: -57.781625 | BU34: -28.890813 | BV34: -1.788294e-12 | BW34: -1.788294e-12 | BX34: -1.788294e-12 | BY34: -1.788294e-12 | BZ34: -1.788294e-12 | CA34: -1.788294e-12 | CB34: -1.788294e-12 | CC34: -1.788294e-12 | CD34: -1.788294e-12 | CE34: -1.788294e-12 | CF34: -1.788294e-12 | CG34: -1.788294e-12 | CH34: -1.788294e-12 | CI34: -1.788294e-12 | CJ34: -1.788294e-12 | CK34: -1.788294e-12 | CL34: -1.788294e-12
B35: 선순위B 이자 | C35: [KRWm] | D35: 0 | E35: 0 | F35: 0 | G35: 0 | H35: 0 | I35: 0 | J35: 0 | K35: 0 | L35: 0 | M35: 0 | N35: 0 | O35: 0 | P35: 0 | Q35: 0 | R35: 0 | S35: 0 | T35: 0 | U35: 0 | V35: 0 | W35: 0 | X35: 0 | Y35: 0 | Z35: 0 | AA35: 0 | AB35: 0 | AC35: 0 | AD35: 0 | AE35: 0 | AF35: 0 | AG35: 0 | AH35: 0 | AI35: 0 | AJ35: 0 | AK35: 0 | AL35: 0 | AM35: 0 | AN35: 0 | AO35: 0 | AP35: 0 | AQ35: 0 | AR35: 0 | AS35: 0 | AT35: 0 | AU35: 0 | AV35: 0 | AW35: 0 | AX35: 0 | AY35: 0 | AZ35: 0 | BA35: 0 | BB35: 0 | BC35: 0 | BD35: 0 | BE35: 0 | BF35: 0 | BG35: 0 | BH35: 0 | BI35: 0 | BJ35: 0 | BK35: 0 | BL35: 0 | BM35: 0 | BN35: 0 | BO35: 0 | BP35: 0 | BQ35: 0 | BR35: 0 | BS35: 0 | BT35: 0 | BU35: 0 | BV35: 0 | BW35: 0 | BX35: 0 | BY35: 0 | BZ35: 0 | CA35: 0 | CB35: 0 | CC35: 0 | CD35: 0 | CE35: 0 | CF35: 0 | CG35: 0 | CH35: 0 | CI35: 0 | CJ35: 0 | CK35: 0 | CL35: 0
B36: 선순위C 이자 | C36: [KRWm] | D36: 0 | E36: 0 | F36: 0 | G36: 0 | H36: 0 | I36: 0 | J36: 0 | K36: 0 | L36: 0 | M36: 0 | N36: 0 | O36: 0 | P36: 0 | Q36: 0 | R36: 0 | S36: 0 | T36: 0 | U36: 0 | V36: 0 | W36: 0 | X36: 0 | Y36: 0 | Z36: 0 | AA36: 0 | AB36: 0 | AC36: 0 | AD36: 0 | AE36: 0 | AF36: 0 | AG36: 0 | AH36: 0 | AI36: 0 | AJ36: 0 | AK36: 0 | AL36: 0 | AM36: 0 | AN36: 0 | AO36: 0 | AP36: 0 | AQ36: 0 | AR36: 0 | AS36: 0 | AT36: 0 | AU36: 0 | AV36: 0 | AW36: 0 | AX36: 0 | AY36: 0 | AZ36: 0 | BA36: 0 | BB36: 0 | BC36: 0 | BD36: 0 | BE36: 0 | BF36: 0 | BG36: 0 | BH36: 0 | BI36: 0 | BJ36: 0 | BK36: 0 | BL36: 0 | BM36: 0 | BN36: 0 | BO36: 0 | BP36: 0 | BQ36: 0 | BR36: 0 | BS36: 0 | BT36: 0 | BU36: 0 | BV36: 0 | BW36: 0 | BX36: 0 | BY36: 0 | BZ36: 0 | CA36: 0 | CB36: 0 | CC36: 0 | CD36: 0 | CE36: 0 | CF36: 0 | CG36: 0 | CH36: 0 | CI36: 0 | CJ36: 0 | CK36: 0 | CL36: 0
B37: 선순위D 이자 | C37: [KRWm] | D37: 0 | E37: 0 | F37: 0 | G37: 0 | H37: 0 | I37: 0 | J37: 0 | K37: 0 | L37: 0 | M37: 0 | N37: 0 | O37: 0 | P37: 0 | Q37: 0 | R37: 0 | S37: 0 | T37: 0 | U37: 0 | V37: 0 | W37: 0 | X37: 0 | Y37: 0 | Z37: 0 | AA37: 0 | AB37: 0 | AC37: 0 | AD37: 0 | AE37: 0 | AF37: 0 | AG37: 0 | AH37: 0 | AI37: 0 | AJ37: 0 | AK37: 0 | AL37: 0 | AM37: 0 | AN37: 0 | AO37: 0 | AP37: 0 | AQ37: 0 | AR37: 0 | AS37: 0 | AT37: 0 | AU37: 0 | AV37: 0 | AW37: 0 | AX37: 0 | AY37: 0 | AZ37: 0 | BA37: 0 | BB37: 0 | BC37: 0 | BD37: 0 | BE37: 0 | BF37: 0 | BG37: 0 | BH37: 0 | BI37: 0 | BJ37: 0 | BK37: 0 | BL37: 0 | BM37: 0 | BN37: 0 | BO37: 0 | BP37: 0 | BQ37: 0 | BR37: 0 | BS37: 0 | BT37: 0 | BU37: 0 | BV37: 0 | BW37: 0 | BX37: 0 | BY37: 0 | BZ37: 0 | CA37: 0 | CB37: 0 | CC37: 0 | CD37: 0 | CE37: 0 | CF37: 0 | CG37: 0 | CH37: 0 | CI37: 0 | CJ37: 0 | CK37: 0 | CL37: 0
B38: 후순위 이자 | C38: [KRWm] | D38: 0 | E38: 0 | F38: 0 | G38: 0 | H38: 0 | I38: 0 | J38: 0 | K38: 0 | L38: 0 | M38: 0 | N38: 0 | O38: 0 | P38: 0 | Q38: 0 | R38: 0 | S38: 0 | T38: 0 | U38: 0 | V38: 0 | W38: 0 | X38: 0 | Y38: 0 | Z38: 0 | AA38: 0 | AB38: 0 | AC38: 0 | AD38: 0 | AE38: 0 | AF38: 0 | AG38: 0 | AH38: 0 | AI38: 0 | AJ38: 0 | AK38: 0 | AL38: 0 | AM38: 0 | AN38: 0 | AO38: 0 | AP38: 0 | AQ38: 0 | AR38: 0 | AS38: 0 | AT38: 0 | AU38: 0 | AV38: 0 | AW38: 0 | AX38: 0 | AY38: 0 | AZ38: 0 | BA38: 0 | BB38: 0 | BC38: 0 | BD38: 0 | BE38: 0 | BF38: 0 | BG38: 0 | BH38: 0 | BI38: 0 | BJ38: 0 | BK38: 0 | BL38: 0 | BM38: 0 | BN38: 0 | BO38: 0 | BP38: 0 | BQ38: 0 | BR38: 0 | BS38: 0 | BT38: 0 | BU38: 0 | BV38: 0 | BW38: 0 | BX38: 0 | BY38: 0 | BZ38: 0 | CA38: 0 | CB38: 0 | CC38: 0 | CD38: 0 | CE38: 0 | CF38: 0 | CG38: 0 | CH38: 0 | CI38: 0 | CJ38: 0 | CK38: 0 | CL38: 0
B39: 이자비용 합계 | C39: [KRWm] | D39: -58070.533 | E39: 0 | F39: 0 | G39: 0 | H39: 0 | I39: 0 | J39: 0 | K39: -1733.4488 | L39: -1733.4488 | M39: -1733.4488 | N39: -1733.4488 | O39: -1704.5579 | P39: -1675.6671 | Q39: -1646.7763 | R39: -1617.8855 | S39: -1588.9947 | T39: -1560.1039 | U39: -1531.2131 | V39: -1502.3223 | W39: -1473.4314 | X39: -1444.5406 | Y39: -1415.6498 | Z39: -1386.759 | AA39: -1357.8682 | AB39: -1328.9774 | AC39: -1300.0866 | AD39: -1271.1958 | AE39: -1242.3049 | AF39: -1213.4141 | AG39: -1184.5233 | AH39: -1155.6325 | AI39: -1126.7417 | AJ39: -1097.8509 | AK39: -1068.9601 | AL39: -1040.0693 | AM39: -1011.1784 | AN39: -982.28763 | AO39: -953.39681 | AP39: -924.506 | AQ39: -895.61519 | AR39: -866.72438 | AS39: -837.83356 | AT39: -808.94275 | AU39: -780.05194 | AV39: -751.16113 | AW39: -722.27031 | AX39: -693.3795 | AY39: -664.48869 | AZ39: -635.59788 | BA39: -606.70706 | BB39: -577.81625 | BC39: -548.92544 | BD39: -520.03463 | BE39: -491.14381 | BF39: -462.253 | BG39: -433.36219 | BH39: -404.47138 | BI39: -375.58056 | BJ39: -346.68975 | BK39: -317.79894 | BL39: -288.90813 | BM39: -260.01731 | BN39: -231.1265 | BO39: -202.23569 | BP39: -173.34488 | BQ39: -144.45406 | BR39: -115.56325 | BS39: -86.672438 | BT39: -57.781625 | BU39: -28.890813 | BV39: -1.788294e-12 | BW39: -1.788294e-12 | BX39: -1.788294e-12 | BY39: -1.788294e-12 | BZ39: -1.788294e-12 | CA39: -1.788294e-12 | CB39: -1.788294e-12 | CC39: -1.788294e-12 | CD39: -1.788294e-12 | CE39: -1.788294e-12 | CF39: -1.788294e-12 | CG39: -1.788294e-12 | CH39: -1.788294e-12 | CI39: -1.788294e-12 | CJ39: -1.788294e-12 | CK39: -1.788294e-12 | CL39: -1.788294e-12
B40: 대리은행수수료 | C40: [KRWm] | D40: 0 | E40: 0 | F40: 0 | G40: 0 | H40: 0 | I40: 0 | J40: 0 | K40: 0 | L40: 0 | M40: 0 | N40: 0 | O40: 0 | P40: 0 | Q40: 0 | R40: 0 | S40: 0 | T40: 0 | U40: 0 | V40: 0 | W40: 0 | X40: 0 | Y40: 0 | Z40: 0 | AA40: 0 | AB40: 0 | AC40: 0 | AD40: 0 | AE40: 0 | AF40: 0 | AG40: 0 | AH40: 0 | AI40: 0 | AJ40: 0 | AK40: 0 | AL40: 0 | AM40: 0 | AN40: 0 | AO40: 0 | AP40: 0 | AQ40: 0 | AR40: 0 | AS40: 0 | AT40: 0 | AU40: 0 | AV40: 0 | AW40: 0 | AX40: 0 | AY40: 0 | AZ40: 0 | BA40: 0 | BB40: 0 | BC40: 0 | BD40: 0 | BE40: 0 | BF40: 0 | BG40: 0 | BH40: 0 | BI40: 0 | BJ40: 0 | BK40: 0 | BL40: 0 | BM40: 0 | BN40: 0 | BO40: 0 | BP40: 0 | BQ40: 0 | BR40: 0 | BS40: 0 | BT40: 0 | BU40: 0 | BV40: 0 | BW40: 0 | BX40: 0 | BY40: 0 | BZ40: 0 | CA40: 0 | CB40: 0 | CC40: 0 | CD40: 0 | CE40: 0 | CF40: 0 | CG40: 0 | CH40: 0 | CI40: 0 | CJ40: 0 | CK40: 0 | CL40: 0
B42: 법인세차감전순이익 | C42: [KRWm] | D42: 179010.74 | E42: 0 | F42: 0 | G42: 0 | H42: 0 | I42: 0 | J42: 0 | K42: 1514.2512 | L42: 1514.2512 | M42: 1514.2512 | N42: 1514.2512 | O42: 1513.5159 | P42: 1542.4067 | Q42: 1571.2976 | R42: 1600.1884 | S42: 1599.4081 | T42: 1628.299 | U42: 1657.1898 | V42: 1686.0806 | W42: 1685.2547 | X42: 1714.1455 | Y42: 1743.0363 | Z42: 1771.9271 | AA42: 1771.0549 | AB42: 1799.9457 | AC42: 1828.8365 | AD42: 1857.7273 | AE42: 1856.808 | AF42: 1885.6988 | AG42: 1914.5896 | AH42: 1943.4804 | AI42: 1942.5134 | AJ42: 1971.4042 | AK42: 2000.295 | AL42: 2029.1858 | AM42: 2028.1702 | AN42: 2057.0611 | AO42: 2085.9519 | AP42: 2114.8427 | AQ42: 2113.7779 | AR42: 2142.6687 | AS42: 2171.5595 | AT42: 2200.4504 | AU42: 2199.3357 | AV42: 2228.2265 | AW42: 2257.1173 | AX42: 2286.0081 | AY42: 2284.8427 | AZ42: 2313.7335 | BA42: 2342.6243 | BB42: 2371.5151 | BC42: 2370.2983 | BD42: 2399.1891 | BE42: 2428.0799 | BF42: 2456.9707 | BG42: 2455.7017 | BH42: 2484.5925 | BI42: 2513.4833 | BJ42: 2542.3741 | BK42: 2541.052 | BL42: 2569.9428 | BM42: 2598.8336 | BN42: 2627.7245 | BO42: 2626.3486 | BP42: 2655.2394 | BQ42: 2684.1302 | BR42: 2713.021 | BS42: 2711.5905 | BT42: 2740.4813 | BU42: 2769.3722 | BV42: 2798.263 | BW42: 2767.8862 | BX42: 2767.8862 | BY42: 2767.8862 | BZ42: 2767.8862 | CA42: 2737.4532 | CB42: 2737.4532 | CC42: 2737.4532 | CD42: 2737.4532 | CE42: 2706.9631 | CF42: 2706.9631 | CG42: 2706.9631 | CH42: 2706.9631 | CI42: 2676.4151 | CJ42: 2676.4151 | CK42: 2676.4151 | CL42: 2676.4151
B43: 법인세비용 | C43: [KRWm] | D43: -36951.244 | E43: 0 | F43: 0 | G43: 0 | H43: 0 | I43: 0 | J43: 0 | K43: -299.70349 | L43: -316.20346 | M43: -316.20346 | N43: -316.20346 | O43: -316.04993 | P43: -322.09427 | Q43: -328.12741 | R43: -334.16056 | S43: -333.99763 | T43: -340.04542 | U43: -346.07882 | V43: -352.11223 | W43: -351.93975 | X43: -357.98705 | Y43: -364.02069 | Z43: -370.05433 | AA43: -369.87217 | AB43: -375.91902 | AC43: -381.95287 | AD43: -387.98673 | AE43: -387.79473 | AF43: -393.84118 | AG43: -399.87523 | AH43: -405.90927 | AI43: -405.70729 | AJ43: -411.75338 | AK43: -417.78761 | AL43: -423.82183 | AM43: -423.60972 | AN43: -429.65547 | AO43: -435.68985 | AP43: -441.72424 | AQ43: -441.50184 | AR43: -447.54729 | AS43: -453.58182 | AT43: -459.61635 | AU43: -459.38352 | AV43: -465.42868 | AW43: -471.46335 | AX43: -477.49802 | AY43: -477.2546 | AZ43: -483.2995 | BA43: -489.33429 | BB43: -495.36909 | BC43: -495.11491 | BD43: -501.15957 | BE43: -507.19448 | BF43: -513.2294 | BG43: -512.96431 | BH43: -519.00873 | BI43: -525.04376 | BJ43: -531.07879 | BK43: -530.80262 | BL43: -536.84683 | BM43: -542.88196 | BN43: -548.91709 | BO43: -548.62968 | BP43: -554.67369 | BQ43: -560.70891 | BR43: -566.74414 | BS43: -566.44532 | BT43: -572.48843 | BU43: -578.52374 | BV43: -584.55905 | BW43: -578.21333 | BX43: -578.21247 | BY43: -578.21247 | BZ43: -578.21247 | CA43: -571.855 | CB43: -571.85196 | CC43: -571.85196 | CD43: -571.85196 | CE43: -565.4826 | CF43: -565.47952 | CG43: -565.47952 | CH43: -565.47952 | CI43: -559.09809 | CJ43: -417.92909 | CK43: -417.92909 | CL43: -417.92909
B44: 당기순이익 | C44: [KRWm] | D44: 142059.49 | E44: 0 | F44: 0 | G44: 0 | H44: 0 | I44: 0 | J44: 0 | K44: 1214.5477 | L44: 1198.0477 | M44: 1198.0477 | N44: 1198.0477 | O44: 1197.466 | P44: 1220.3125 | Q44: 1243.1701 | R44: 1266.0278 | S44: 1265.4105 | T44: 1288.2535 | U44: 1311.111 | V44: 1333.9684 | W44: 1333.3149 | X44: 1356.1584 | Y44: 1379.0156 | Z44: 1401.8728 | AA44: 1401.1827 | AB44: 1424.0267 | AC44: 1446.8836 | AD44: 1469.7406 | AE44: 1469.0133 | AF44: 1491.8576 | AG44: 1514.7144 | AH44: 1537.5712 | AI44: 1536.8061 | AJ44: 1559.6508 | AK44: 1582.5074 | AL44: 1605.364 | AM44: 1604.5605 | AN44: 1627.4056 | AO44: 1650.262 | AP44: 1673.1184 | AQ44: 1672.2761 | AR44: 1695.1214 | AS44: 1717.9777 | AT44: 1740.834 | AU44: 1739.9521 | AV44: 1762.7978 | AW44: 1785.6539 | AX44: 1808.5101 | AY44: 1807.5881 | AZ44: 1830.434 | BA44: 1853.29 | BB44: 1876.146 | BC44: 1875.1834 | BD44: 1898.0295 | BE44: 1920.8854 | BF44: 1943.7413 | BG44: 1942.7374 | BH44: 1965.5837 | BI44: 1988.4395 | BJ44: 2011.2953 | BK44: 2010.2494 | BL44: 2033.096 | BM44: 2055.9517 | BN44: 2078.8074 | BO44: 2077.7189 | BP44: 2100.5657 | BQ44: 2123.4213 | BR44: 2146.2769 | BS44: 2145.1452 | BT44: 2167.9929 | BU44: 2190.8484 | BV44: 2213.7039 | BW44: 2189.6729 | BX44: 2189.6738 | BY44: 2189.6738 | BZ44: 2189.6738 | CA44: 2165.5982 | CB44: 2165.6013 | CC44: 2165.6013 | CD44: 2165.6013 | CE44: 2141.4805 | CF44: 2141.4836 | CG44: 2141.4836 | CH44: 2141.4836 | CI44: 2117.317 | CJ44: 2258.486 | CK44: 2258.486 | CL44: 2258.486
B46: ※ 영업비용 세부내역은 실측 오버라이드가 적용된 분기의 경우 항목별 실제값이 아니라, 공식(항목별 물가상승률) 기준 비중을 실제 합계에 비례 배분한 근사치입니다 — 합계 자체는 검증된 실제값과 정확히 일치합니다.

Sheet CF(Q)
A1: 태양광 발전사업
A2: 추정 현금흐름표 (분기) · DSCR · 배당
B4: 영업/재무 현금흐름
B6: 구 분 | C6: unit | D6: 합 계 | E6: 2024-06-30 | F6: 2024-09-30 | G6: 2024-12-31 | H6: 2025-03-31 | I6: 2025-06-30 | J6: 2025-09-30 | K6: 2025-12-31 | L6: 2026-03-31 | M6: 2026-06-30 | N6: 2026-09-30 | O6: 2026-12-31 | P6: 2027-03-31 | Q6: 2027-06-30 | R6: 2027-09-30 | S6: 2027-12-31 | T6: 2028-03-31 | U6: 2028-06-30 | V6: 2028-09-30 | W6: 2028-12-31 | X6: 2029-03-31 | Y6: 2029-06-30 | Z6: 2029-09-30 | AA6: 2029-12-31 | AB6: 2030-03-31 | AC6: 2030-06-30 | AD6: 2030-09-30 | AE6: 2030-12-31 | AF6: 2031-03-31 | AG6: 2031-06-30 | AH6: 2031-09-30 | AI6: 2031-12-31 | AJ6: 2032-03-31 | AK6: 2032-06-30 | AL6: 2032-09-30 | AM6: 2032-12-31 | AN6: 2033-03-31 | AO6: 2033-06-30 | AP6: 2033-09-30 | AQ6: 2033-12-31 | AR6: 2034-03-31 | AS6: 2034-06-30 | AT6: 2034-09-30 | AU6: 2034-12-31 | AV6: 2035-03-31 | AW6: 2035-06-30 | AX6: 2035-09-30 | AY6: 2035-12-31 | AZ6: 2036-03-31 | BA6: 2036-06-30 | BB6: 2036-09-30 | BC6: 2036-12-31 | BD6: 2037-03-31 | BE6: 2037-06-30 | BF6: 2037-09-30 | BG6: 2037-12-31 | BH6: 2038-03-31 | BI6: 2038-06-30 | BJ6: 2038-09-30 | BK6: 2038-12-31 | BL6: 2039-03-31 | BM6: 2039-06-30 | BN6: 2039-09-30 | BO6: 2039-12-31 | BP6: 2040-03-31 | BQ6: 2040-06-30 | BR6: 2040-09-30 | BS6: 2040-12-31 | BT6: 2041-03-31 | BU6: 2041-06-30 | BV6: 2041-09-30 | BW6: 2041-12-31 | BX6: 2042-03-31 | BY6: 2042-06-30 | BZ6: 2042-09-30 | CA6: 2042-12-31 | CB6: 2043-03-31 | CC6: 2043-06-30 | CD6: 2043-09-30 | CE6: 2043-12-31 | CF6: 2044-03-31 | CG6: 2044-06-30 | CH6: 2044-09-30 | CI6: 2044-12-31 | CJ6: 2045-03-31 | CK6: 2045-06-30 | CL6: 2045-09-30
B9: CFADS (원리금상환재원) | C9: [KRWm] | D9: 340330.59 | E9: 0 | F9: 0 | G9: 0 | H9: 0 | I9: 0 | J9: 0 | K9: 4700.5035 | L9: 4684.0035 | M9: 4684.0035 | N9: 4684.0035 | O9: 4654.531 | P9: 4648.4867 | Q9: 4642.4535 | R9: 4636.4204 | S9: 4606.9123 | T9: 4600.8645 | U9: 4594.8311 | V9: 4588.7977 | W9: 4559.2535 | X9: 4553.2062 | Y9: 4547.1725 | Z9: 4541.1389 | AA9: 4511.558 | AB9: 4505.5111 | AC9: 4499.4773 | AD9: 4493.4434 | AE9: 4463.8253 | AF9: 4457.7788 | AG9: 4451.7448 | AH9: 4445.7107 | AI9: 4416.0548 | AJ9: 4410.0087 | AK9: 4403.9745 | AL9: 4397.9403 | AM9: 4368.2461 | AN9: 4362.2003 | AO9: 4356.1659 | AP9: 4350.1315 | AQ9: 4320.3984 | AR9: 4314.3529 | AS9: 4308.3184 | AT9: 4302.2838 | AU9: 4272.5112 | AV9: 4266.466 | AW9: 4260.4313 | AX9: 4254.3967 | AY9: 4224.5839 | AZ9: 4218.539 | BA9: 4212.5042 | BB9: 4206.4694 | BC9: 4176.6159 | BD9: 4170.5713 | BE9: 4164.5363 | BF9: 4158.5014 | BG9: 4128.6066 | BH9: 4122.5622 | BI9: 4116.5272 | BJ9: 4110.4922 | BK9: 4080.5554 | BL9: 4074.5112 | BM9: 4068.4761 | BN9: 4062.441 | BO9: 4032.4617 | BP9: 4026.4177 | BQ9: 4020.3824 | BR9: 4014.3472 | BS9: 3984.3247 | BT9: 3978.2816 | BU9: 3972.2463 | BV9: 3966.211 | BW9: 3942.18 | BX9: 3942.1809 | BY9: 3942.1809 | BZ9: 3942.1809 | CA9: 3918.1053 | CB9: 3918.1084 | CC9: 3918.1084 | CD9: 3918.1084 | CE9: 3893.9876 | CF9: 3893.9907 | CG9: 3893.9907 | CH9: 3893.9907 | CI9: 3869.8241 | CJ9: 4010.9931 | CK9: 4010.9931 | CL9: 4010.9931
B10: 원리금(DS) | C10: [KRWm] | D10: 184139.53 | E10: 0 | F10: 0 | G10: 0 | H10: 0 | I10: 0 | J10: 0 | K10: 1733.4488 | L10: 1733.4488 | M10: 1733.4488 | N10: 3834.5988 | O10: 3805.7079 | P10: 3776.8171 | Q10: 3747.9263 | R10: 3719.0355 | S10: 3690.1447 | T10: 3661.2539 | U10: 3632.3631 | V10: 3603.4723 | W10: 3574.5814 | X10: 3545.6906 | Y10: 3516.7998 | Z10: 3487.909 | AA10: 3459.0182 | AB10: 3430.1274 | AC10: 3401.2366 | AD10: 3372.3458 | AE10: 3343.4549 | AF10: 3314.5641 | AG10: 3285.6733 | AH10: 3256.7825 | AI10: 3227.8917 | AJ10: 3199.0009 | AK10: 3170.1101 | AL10: 3141.2193 | AM10: 3112.3284 | AN10: 3083.4376 | AO10: 3054.5468 | AP10: 3025.656 | AQ10: 2996.7652 | AR10: 2967.8744 | AS10: 2938.9836 | AT10: 2910.0928 | AU10: 2881.2019 | AV10: 2852.3111 | AW10: 2823.4203 | AX10: 2794.5295 | AY10: 2765.6387 | AZ10: 2736.7479 | BA10: 2707.8571 | BB10: 2678.9663 | BC10: 2650.0754 | BD10: 2621.1846 | BE10: 2592.2938 | BF10: 2563.403 | BG10: 2534.5122 | BH10: 2505.6214 | BI10: 2476.7306 | BJ10: 2447.8398 | BK10: 2418.9489 | BL10: 2390.0581 | BM10: 2361.1673 | BN10: 2332.2765 | BO10: 2303.3857 | BP10: 2274.4949 | BQ10: 2245.6041 | BR10: 2216.7133 | BS10: 2187.8224 | BT10: 2158.9316 | BU10: 2130.0408 | BV10: 1.788294e-12 | BW10: 1.788294e-12 | BX10: 1.788294e-12 | BY10: 1.788294e-12 | BZ10: 1.788294e-12 | CA10: 1.788294e-12 | CB10: 1.788294e-12 | CC10: 1.788294e-12 | CD10: 1.788294e-12 | CE10: 1.788294e-12 | CF10: 1.788294e-12 | CG10: 1.788294e-12 | CH10: 1.788294e-12 | CI10: 1.788294e-12 | CJ10: 1.788294e-12 | CK10: 1.788294e-12 | CL10: 1.788294e-12
B11: 단순 DSCR | C11: [x] | K11: 2.7116484 | L11: 2.7021298 | M11: 2.7021298 | N11: 1.2215107 | O11: 1.2230395 | P11: 1.2307948 | Q11: 1.2386726 | R11: 1.2466728 | S11: 1.2484368 | T11: 1.2566363 | U11: 1.2649702 | V11: 1.2734378 | W11: 1.275465 | X11: 1.2841521 | Y11: 1.2929859 | Z11: 1.301966 | AA11: 1.3042886 | AB11: 1.3135113 | AC11: 1.3228945 | AD11: 1.3324385 | AE11: 1.3350936 | AF11: 1.3449065 | AG11: 1.3548957 | AH11: 1.3650622 | AI11: 1.3680926 | AJ11: 1.3785582 | AK11: 1.3892182 | AL11: 1.4000743 | AM11: 1.4035299 | AN11: 1.4147198 | AO11: 1.4261251 | AP11: 1.4377482 | AQ11: 1.4416873 | AR11: 1.4536845 | AS11: 1.4659212 | AT11: 1.4784009 | AU11: 1.482892 | AV11: 1.4957926 | AW11: 1.5089611 | AX11: 1.5224018 | AY11: 1.5275256 | AZ11: 1.5414423 | BA11: 1.5556597 | BB11: 1.5701838 | BC11: 1.5760366 | BD11: 1.5911017 | BE11: 1.6065063 | BF11: 1.6222582 | BG11: 1.6289551 | BH11: 1.6453253 | BI11: 1.6620811 | BJ11: 1.6792325 | BK11: 1.6869126 | BL11: 1.704775 | BM11: 1.7230783 | BN11: 1.7418351 | BO11: 1.7506672 | BP11: 1.770247 | BQ11: 1.7903345 | BR11: 1.8109456 | BS11: 1.8211372 | BT11: 1.8427085 | BU11: 1.8648686
B13: FCFE | C13: [KRWm] | D13: 159191.06 | E13: 0 | F13: 0 | G13: 0 | H13: 0 | I13: 0 | J13: 0 | K13: 4500.1573 | L13: 849.40479 | M13: 878.2956 | N13: 907.18641 | O13: 906.60472 | P13: 929.45119 | Q13: 952.30886 | R13: 975.16652 | S13: 974.54923 | T13: 997.39226 | U13: 1020.2497 | V13: 1043.1071 | W13: 1042.4536 | X13: 1065.2972 | Y13: 1088.1543 | Z13: 1111.0115 | AA13: 1110.3214 | AB13: 1133.1654 | AC13: 1156.0223 | AD13: 1178.8793 | AE13: 1178.152 | AF13: 1200.9963 | AG13: 1223.8531 | AH13: 1246.7099 | AI13: 1245.9448 | AJ13: 1268.7895 | AK13: 1291.6461 | AL13: 1314.5027 | AM13: 1313.6992 | AN13: 1336.5443 | AO13: 1359.4007 | AP13: 1382.2572 | AQ13: 1381.4148 | AR13: 1404.2602 | AS13: 1427.1164 | AT13: 1449.9727 | AU13: 1449.0908 | AV13: 1471.9365 | AW13: 1494.7926 | AX13: 1517.6488 | AY13: 1516.7268 | AZ13: 1539.5727 | BA13: 1562.4287 | BB13: 1585.2848 | BC13: 1584.3221 | BD13: 1607.1683 | BE13: 1630.0242 | BF13: 1652.88 | BG13: 1651.8761 | BH13: 1674.7225 | BI13: 1697.5782 | BJ13: 1720.434 | BK13: 1719.3881 | BL13: 1742.2347 | BM13: 1765.0904 | BN13: 1787.9461 | BO13: 1786.8576 | BP13: 1809.7044 | BQ13: 1832.56 | BR13: 1855.4156 | BS13: 1854.2839 | BT13: 3978.2816 | BU13: 3972.2463 | BV13: 3966.211 | BW13: 3942.18 | BX13: 3942.1809 | BY13: 3942.1809 | BZ13: 3942.1809 | CA13: 3918.1053 | CB13: 3918.1084 | CC13: 3918.1084 | CD13: 3918.1084 | CE13: 3893.9876 | CF13: 3893.9907 | CG13: 3893.9907 | CH13: 3893.9907 | CI13: 3869.8241 | CJ13: 4010.9931 | CK13: 4010.9931 | CL13: 2010.9931
B14: DSRA 증감 | C14: [KRWm] | D14: -5000 | E14: 0 | F14: 0 | G14: 0 | H14: 0 | I14: 0 | J14: 0 | K14: -1533.1025 | L14: 2101.15 | M14: 2072.2592 | N14: -57.781625 | O14: -57.781625 | P14: -57.781625 | Q14: -57.781625 | R14: -57.781625 | S14: -57.781625 | T14: -57.781625 | U14: -57.781625 | V14: -57.781625 | W14: -57.781625 | X14: -57.781625 | Y14: -57.781625 | Z14: -57.781625 | AA14: -57.781625 | AB14: -57.781625 | AC14: -57.781625 | AD14: -57.781625 | AE14: -57.781625 | AF14: -57.781625 | AG14: -57.781625 | AH14: -57.781625 | AI14: -57.781625 | AJ14: -57.781625 | AK14: -57.781625 | AL14: -57.781625 | AM14: -57.781625 | AN14: -57.781625 | AO14: -57.781625 | AP14: -57.781625 | AQ14: -57.781625 | AR14: -57.781625 | AS14: -57.781625 | AT14: -57.781625 | AU14: -57.781625 | AV14: -57.781625 | AW14: -57.781625 | AX14: -57.781625 | AY14: -57.781625 | AZ14: -57.781625 | BA14: -57.781625 | BB14: -57.781625 | BC14: -57.781625 | BD14: -57.781625 | BE14: -57.781625 | BF14: -57.781625 | BG14: -57.781625 | BH14: -57.781625 | BI14: -57.781625 | BJ14: -57.781625 | BK14: -57.781625 | BL14: -57.781625 | BM14: -57.781625 | BN14: -57.781625 | BO14: -57.781625 | BP14: -57.781625 | BQ14: -57.781625 | BR14: -57.781625 | BS14: -57.781625 | BT14: -2158.9316 | BU14: -2130.0408 | BV14: 0 | BW14: 0 | BX14: 0 | BY14: 0 | BZ14: 0 | CA14: 0 | CB14: 0 | CC14: 0 | CD14: 0 | CE14: 0 | CF14: 0 | CG14: 0 | CH14: 0 | CI14: 0 | CJ14: 0 | CK14: -1.788294e-12 | CL14: -1.788294e-12
B15: 기초현금 | C15: [KRWm] | E15: 0 | F15: 0 | G15: 0 | H15: 0 | I15: 0 | J15: 0 | K15: 0 | L15: 4500.1573 | M15: 5349.562 | N15: 6227.8576 | O15: 7135.044 | P15: 1000 | Q15: 1000 | R15: 1000 | S15: 1000 | T15: 1000 | U15: 1000 | V15: 1000 | W15: 1000 | X15: 1000 | Y15: 1000 | Z15: 1000 | AA15: 1000 | AB15: 1000 | AC15: 1000 | AD15: 1000 | AE15: 1000 | AF15: 1000 | AG15: 1000 | AH15: 1000 | AI15: 1000 | AJ15: 1000 | AK15: 1000 | AL15: 1000 | AM15: 1000 | AN15: 1000 | AO15: 1000 | AP15: 1000 | AQ15: 1000 | AR15: 1000 | AS15: 1000 | AT15: 1000 | AU15: 1000 | AV15: 1000 | AW15: 1000 | AX15: 1000 | AY15: 1000 | AZ15: 1000 | BA15: 1000 | BB15: 1000 | BC15: 1000 | BD15: 1000 | BE15: 1000 | BF15: 1000 | BG15: 1000 | BH15: 1000 | BI15: 1000 | BJ15: 1000 | BK15: 1000 | BL15: 1000 | BM15: 1000 | BN15: 1000 | BO15: 1000 | BP15: 1000 | BQ15: 1000 | BR15: 1000 | BS15: 1000 | BT15: 1000 | BU15: 1000 | BV15: 1000 | BW15: 1000 | BX15: 1000 | BY15: 1000 | BZ15: 1000 | CA15: 1000 | CB15: 1000 | CC15: 1000 | CD15: 1000 | CE15: 1000 | CF15: 1000 | CG15: 1000 | CH15: 1000 | CI15: 1000 | CJ15: 1000 | CK15: 1000 | CL15: 1000
B16: 배당(연차+청산) | C16: [KRWm] | D16: 159191.06 | E16: 0 | F16: 0 | G16: 0 | H16: 0 | I16: 0 | J16: 0 | K16: 0 | L16: 0 | M16: 0 | N16: 0 | O16: 7041.6488 | P16: 929.45119 | Q16: 952.30886 | R16: 975.16652 | S16: 974.54923 | T16: 997.39226 | U16: 1020.2497 | V16: 1043.1071 | W16: 1042.4536 | X16: 1065.2972 | Y16: 1088.1543 | Z16: 1111.0115 | AA16: 1110.3214 | AB16: 1133.1654 | AC16: 1156.0223 | AD16: 1178.8793 | AE16: 1178.152 | AF16: 1200.9963 | AG16: 1223.8531 | AH16: 1246.7099 | AI16: 1245.9448 | AJ16: 1268.7895 | AK16: 1291.6461 | AL16: 1314.5027 | AM16: 1313.6992 | AN16: 1336.5443 | AO16: 1359.4007 | AP16: 1382.2572 | AQ16: 1381.4148 | AR16: 1404.2602 | AS16: 1427.1164 | AT16: 1449.9727 | AU16: 1449.0908 | AV16: 1471.9365 | AW16: 1494.7926 | AX16: 1517.6488 | AY16: 1516.7268 | AZ16: 1539.5727 | BA16: 1562.4287 | BB16: 1585.2848 | BC16: 1584.3221 | BD16: 1607.1683 | BE16: 1630.0242 | BF16: 1652.88 | BG16: 1651.8761 | BH16: 1674.7225 | BI16: 1697.5782 | BJ16: 1720.434 | BK16: 1719.3881 | BL16: 1742.2347 | BM16: 1765.0904 | BN16: 1787.9461 | BO16: 1786.8576 | BP16: 1809.7044 | BQ16: 1832.56 | BR16: 1855.4156 | BS16: 1854.2839 | BT16: 3978.2816 | BU16: 3972.2463 | BV16: 3966.211 | BW16: 3942.18 | BX16: 3942.1809 | BY16: 3942.1809 | BZ16: 3942.1809 | CA16: 3918.1053 | CB16: 3918.1084 | CC16: 3918.1084 | CD16: 3918.1084 | CE16: 3893.9876 | CF16: 3893.9907 | CG16: 3893.9907 | CH16: 3893.9907 | CI16: 3869.8241 | CJ16: 4010.9931 | CK16: 4010.9931 | CL16: 3010.9931
B17: 기말현금 | C17: [KRWm] | E17: 0 | F17: 0 | G17: 0 | H17: 0 | I17: 0 | J17: 0 | K17: 4500.1573 | L17: 5349.562 | M17: 6227.8576 | N17: 7135.044 | O17: 1000 | P17: 1000 | Q17: 1000 | R17: 1000 | S17: 1000 | T17: 1000 | U17: 1000 | V17: 1000 | W17: 1000 | X17: 1000 | Y17: 1000 | Z17: 1000 | AA17: 1000 | AB17: 1000 | AC17: 1000 | AD17: 1000 | AE17: 1000 | AF17: 1000 | AG17: 1000 | AH17: 1000 | AI17: 1000 | AJ17: 1000 | AK17: 1000 | AL17: 1000 | AM17: 1000 | AN17: 1000 | AO17: 1000 | AP17: 1000 | AQ17: 1000 | AR17: 1000 | AS17: 1000 | AT17: 1000 | AU17: 1000 | AV17: 1000 | AW17: 1000 | AX17: 1000 | AY17: 1000 | AZ17: 1000 | BA17: 1000 | BB17: 1000 | BC17: 1000 | BD17: 1000 | BE17: 1000 | BF17: 1000 | BG17: 1000 | BH17: 1000 | BI17: 1000 | BJ17: 1000 | BK17: 1000 | BL17: 1000 | BM17: 1000 | BN17: 1000 | BO17: 1000 | BP17: 1000 | BQ17: 1000 | BR17: 1000 | BS17: 1000 | BT17: 1000 | BU17: 1000 | BV17: 1000 | BW17: 1000 | BX17: 1000 | BY17: 1000 | BZ17: 1000 | CA17: 1000 | CB17: 1000 | CC17: 1000 | CD17: 1000 | CE17: 1000 | CF17: 1000 | CG17: 1000 | CH17: 1000 | CI17: 1000 | CJ17: 1000 | CK17: 1000 | CL17: 0
B20: 검증
B22: 최소 단순DSCR(연 합산) | C22: [x] | D22: 1.2410853
B23: 최소 누적DSCR | C23: [x] | D23: 1.8119161
B24: 최종 기말현금(음수면 오류) | C24: [KRWm] | D24: 0
